Workbook

Sheet Read me
A1: STUDENT HOUSING INVESTMENT | Brussels | 20 years
A2: VUB master course: Decision Analytics
A3: Purpose | B3: Unlevered project cash flow, NPV, IRR and simple/discounted payback.
A4: Status | B4: Illustrative feasibility model; replace blue inputs with quotations and validated project data.
A5: Timing | B5: Acquisition and construction at year 0; full operation years 1–20; disposal at end of year 20.
A6: Scope | B6: All amounts EUR nominal; no debt. Tax rate is an editable simplified cash-tax assumption.
A7: Social rooms | B7: 20% chosen target. City of Brussels guidance specifies 20% for 30+ student units; other municipalities and site conditions must be confirmed.
A8: Partnership | B8: Assumes cooperation with VUB/ULB; no signed allocation or nomination agreement.
A9: Location | B9: Illustrative Etterbeek/Ixelles candidate near VUB/ULB; actual site and commute times require validation.
A10: Use | B10: Change blue cells in Inputs. Green cells/formulas are calculated. Results is the final tab.
A11: Payback | B11: Fractional year based on cumulative cash flow; sale proceeds can cause recovery only at year 20.
A12: Limitations | B12: No construction phasing, funding structure, VAT recovery or legal certification. Acquisition tax proxy must be checked.
A13: Version | B13: Enhanced version: official sources reviewed 14 October 2026; numeric results cached for immediate viewing.
A14: Social definition | B14: Reduced rent alone does not establish legal social status. Confirm eligibility, allocation, affordable rents, duration and university/AISE management.
... A16: Cost completeness | B16: Works and furniture inputs must include nonrecoverable VAT. Fire safety, accessibility, permits, EPB and communal facilities belong in works/fees; no grant assumed.

Sheet Cost summary
A1: COST TYPE | B1: YEAR 0 / YEAR 1 EUR | C1: TIMING | D1: BASIS
A2: Acquisition | B2: ='Inputs'!$B$12 -> 2400000 | C2: Year 0 | D2: Purchase of land / existing asset
A3: Acquisition tax | B3: ='Inputs'!$B$12*'Inputs'!$B$13 -> 300000 | C3: Year 0 | D3: Proxy; confirm transaction treatment
A4: Legal fees | B4: ='Inputs'!$B$14 -> 50000 | C4: Year 0 | D4: Fixed assumption
A5: Works | B5: ='Inputs'!$B$15 -> 3000000 | C5: Year 0 | D5: Development / refurbishment
A6: Professional fees | B6: ='Inputs'!$B$15*'Inputs'!$B$16 -> 300000 | C6: Year 0 | D6: Percentage of works
A7: Contingency | B7: ='Inputs'!$B$15*(1+'Inputs'!$B$16)*'Inputs'!$B$17 -> 330000 | C7: Year 0 | D7: Works plus fees
A8: Furniture | B8: ='Inputs'!$B$3*'Inputs'!$B$18 -> 250000 | C8: Year 0 | D8: Initial fitout
A9: Working capital | B9: ='Inputs'!$B$19 -> 25000 | C9: Year 0; released at exit | D9: Cash tied up
A10: TOTAL INITIAL INVESTMENT | B10: =SUM(B2:B9) -> 6655000 | C10: Year 0 | D10: All initial outlays
A11: Maintenance | B11: ='Inputs'!$B$3*'Inputs'!$B$20 -> 45000 | C11: Annual, inflated | D11: Routine repairs
A12: Utilities | B12: ='Inputs'!$B$3*'Inputs'!$B$21 -> 30000 | C12: Annual, inflated | D12: Landlord share
A13: Insurance | B13: ='Inputs'!$B$22 -> 15000 | C13: Annual, inflated | D13: Insurance
A14: Property tax | B14: ='Inputs'!$B$23 -> 20000 | C14: Annual, inflated | D14: Property charge
A15: Administration | B15: ='Inputs'!$B$24 -> 15000 | C15: Annual, inflated | D15: Management / partnership
A16: Management fee | B16: ='Model'!G3 -> 41724 | C16: Annual, % of rent | D16: Variable fee
A17: Replacement | B17: ='Inputs'!$B$26 -> 250000 | C17: Specified year, inflated | D17: Capital outlay; not maintenance
A18: Sale expenses | B18: ='Inputs'!$B$29 -> 0.02 | C18: End of year 20 | D18: Fraction of terminal sale value

Sheet Inputs
A1: INPUT | B1: VALUE | C1: UNIT | D1: ASSUMPTION / DEFINITION
A2: Horizon | B2: 20 | C2: years | D2: Fixed 20-year workbook horizon; do not change.
A3: Rooms | B3: 100 | C3: rooms | D3: Illustrative capacity
A4: Social share | B4: 0.2 | C4: % | D4: 20% affordable/social room target; eligible tenants and rent mechanism require agreement.
A5: Market room rent | B5: 650 | C5: EUR/month | D5: Illustrative; excluding tenant-paid utilities
A6: Social room rent | B6: 450 | C6: EUR/month | D6: Illustrative affordability assumption
A7: Billable months | B7: 12 | C7: months/year | D7: Annual student lease assumption
A8: Occupancy | B8: 0.95 | C8: % | D8: Same for both room types
A9: Rent growth | B9: 0.02 | C9: %/year | D9: Nominal annual escalation
A10: Operating cost growth | B10: 0.025 | C10: %/year | D10: Nominal annual escalation
A11: Discount rate | B11: 0.07 | C11: %/year | D11: Nominal unlevered required return
A12: Acquisition price | B12: 2400000 | C12: EUR | D12: Land/existing asset; excludes development works
A13: Acquisition tax proxy | B13: 0.125 | C13: % of acquisition | D13: Regional standard 12.5% registration duty; actual asset transfer may instead trigger VAT. No personal residence abatement assumed.
... A34: Maximum weighted commute | B34: 30 | C34: minutes | D34: Illustrative location constraint

Sheet Model
A1: Year | B1: Social rooms | C1: Market rooms | D1: Market revenue | E1: Social revenue | F1: Total revenue | G1: Management fee | H1: Fixed operating costs | I1: NOI | J1: Cash tax | K1: Initial investment | L1: Replacement capex | M1: Net sale proceeds | N1: Working capital released | O1: Net cash flow | P1: Cumulative cash flow | Q1: Discount factor | R1: Discounted cash flow | S1: Cumulative discounted CF | T1: Simple recovery year | U1: Discounted recovery year
A2: 0 | B2: =ROUNDUP('Inputs'!$B$3*'Inputs'!$B$4,0) -> 20 | C2: ='Inputs'!$B$3-B2 -> 80 | D2: =IF(A2=0,0,C2*'Inputs'!$B$5*'Inputs'!$B$7*'Inputs'!$B$8*(1+'Inputs'!$B$9)^(A2-1)) -> 0 | E2: =IF(A2=0,0,B2*'Inputs'!$B$6*'Inputs'!$B$7*'Inputs'!$B$8*(1+'Inputs'!$B$9)^(A2-1)) -> 0 | F2: =D2+E2 -> 0 | G2: =F2*'Inputs'!$B$25 -> 0 | H2: =IF(A2=0,0,('Inputs'!$B$3*('Inputs'!$B$20+'Inputs'!$B$21)+'Inputs'!$B$22+'Inputs'!$B$23+'Inputs'!$B$24)*(1+'Inputs'!$B$10)^(A2-1)) -> 0 | I2: =F2-G2-H2 -> 0 | J2: =MAX(0,I2)*'Inputs'!$B$30 -> 0 | K2: =IF(A2=0,'Cost summary'!B10,0) -> 6655000 | L2: =IF(A2='Inputs'!$B$27,'Inputs'!$B$26*(1+'Inputs'!$B$10)^(A2-1),0) -> 0 | M2: =IF(A2='Inputs'!$B$2,(F2*(1+'Inputs'!$B$9)*(1-'Inputs'!$B$25)-H2*(1+'Inputs'!$B$10))/'Inputs'!$B$28*(1-'Inputs'!$B$29),0) -> 0 | N2: =IF(A2='Inputs'!$B$2,'Inputs'!$B$19,0) -> 0 | O2: =I2-J2-K2-L2+M2+N2 -> -6655000 | P2: =O2 -> -6655000 | Q2: =1/(1+'Inputs'!$B$11)^A2 -> 1 | R2: =O2*Q2 -> -6655000 | S2: =R2 -> -6655000 | T2: =999 -> 999 | U2: =999 -> 999
A3: 1 | B3: =ROUNDUP('Inputs'!$B$3*'Inputs'!$B$4,0) -> 20 | C3: ='Inputs'!$B$3-B3 -> 80 | D3: =IF(A3=0,0,C3*'Inputs'!$B$5*'Inputs'!$B$7*'Inputs'!$B$8*(1+'Inputs'!$B$9)^(A3-1)) -> 592800 | E3: =IF(A3=0,0,B3*'Inputs'!$B$6*'Inputs'!$B$7*'Inputs'!$B$8*(1+'Inputs'!$B$9)^(A3-1)) -> 102600 | F3: =D3+E3 -> 695400 | G3: =F3*'Inputs'!$B$25 -> 41724 | H3: =IF(A3=0,0,('Inputs'!$B$3*('Inputs'!$B$20+'Inputs'!$B$21)+'Inputs'!$B$22+'Inputs'!$B$23+'Inputs'!$B$24)*(1+'Inputs'!$B$10)^(A3-1)) -> 125000 | I3: =F3-G3-H3 -> 528676 | J3: =MAX(0,I3)*'Inputs'!$B$30 -> 0 | K3: =IF(A3=0,'Cost summary'!B10,0) -> 0 | L3: =IF(A3='Inputs'!$B$27,'Inputs'!$B$26*(1+'Inputs'!$B$10)^(A3-1),0) -> 0 | M3: =IF(A3='Inputs'!$B$2,(F3*(1+'Inputs'!$B$9)*(1-'Inputs'!$B$25)-H3*(1+'Inputs'!$B$10))/'Inputs'!$B$28*(1-'Inputs'!$B$29),0) -> 0 | N3: =IF(A3='Inputs'!$B$2,'Inputs'!$B$19,0) -> 0 | O3: =I3-J3-K3-L3+M3+N3 -> 528676 | P3: =P2+O3 -> -6126324 | Q3: =1/(1+'Inputs'!$B$11)^A3 -> 0.93457944 | R3: =O3*Q3 -> 494089.72 | S3: =S2+R3 -> -6160910.3 | T3: =IF(AND(P3>=0,P2<0),A3-1-P2/O3,999) -> 999 | U3: =IF(AND(S3>=0,S2<0),A3-1-S2/R3,999) -> 999
A4: 2 | B4: =ROUNDUP('Inputs'!$B$3*'Inputs'!$B$4,0) -> 20 | C4: ='Inputs'!$B$3-B4 -> 80 | D4: =IF(A4=0,0,C4*'Inputs'!$B$5*'Inputs'!$B$7*'Inputs'!$B$8*(1+'Inputs'!$B$9)^(A4-1)) -> 604656 | E4: =IF(A4=0,0,B4*'Inputs'!$B$6*'Inputs'!$B$7*'Inputs'!$B$8*(1+'Inputs'!$B$9)^(A4-1)) -> 104652 | F4: =D4+E4 -> 709308 | G4: =F4*'Inputs'!$B$25 -> 42558.48 | H4: =IF(A4=0,0,('Inputs'!$B$3*('Inputs'!$B$20+'Inputs'!$B$21)+'Inputs'!$B$22+'Inputs'!$B$23+'Inputs'!$B$24)*(1+'Inputs'!$B$10)^(A4-1)) -> 128125 | I4: =F4-G4-H4 -> 538624.52 | J4: =MAX(0,I4)*'Inputs'!$B$30 -> 0 | K4: =IF(A4=0,'Cost summary'!B10,0) -> 0 | L4: =IF(A4='Inputs'!$B$27,'Inputs'!$B$26*(1+'Inputs'!$B$10)^(A4-1),0) -> 0 | M4: =IF(A4='Inputs'!$B$2,(F4*(1+'Inputs'!$B$9)*(1-'Inputs'!$B$25)-H4*(1+'Inputs'!$B$10))/'Inputs'!$B$28*(1-'Inputs'!$B$29),0) -> 0 | N4: =IF(A4='Inputs'!$B$2,'Inputs'!$B$19,0) -> 0 | O4: =I4-J4-K4-L4+M4+N4 -> 538624.52 | P4: =P3+O4 -> -5587699.5 | Q4: =1/(1+'Inputs'!$B$11)^A4 -> 0.87343873 | R4: =O4*Q4 -> 470455.52 | S4: =S3+R4 -> -5690454.8 | T4: =IF(AND(P4>=0,P3<0),A4-1-P3/O4,999) -> 999 | U4: =IF(AND(S4>=0,S3<0),A4-1-S3/R4,999) -> 999
A5: 3 | B5: =ROUNDUP('Inputs'!$B$3*'Inputs'!$B$4,0) -> 20 | C5: ='Inputs'!$B$3-B5 -> 80 | D5: =IF(A5=0,0,C5*'Inputs'!$B$5*'Inputs'!$B$7*'Inputs'!$B$8*(1+'Inputs'!$B$9)^(A5-1)) -> 616749.12 | E5: =IF(A5=0,0,B5*'Inputs'!$B$6*'Inputs'!$B$7*'Inputs'!$B$8*(1+'Inputs'!$B$9)^(A5-1)) -> 106745.04 | F5: =D5+E5 -> 723494.16 | G5: =F5*'Inputs'!$B$25 -> 43409.65 | H5: =IF(A5=0,0,('Inputs'!$B$3*('Inputs'!$B$20+'Inputs'!$B$21)+'Inputs'!$B$22+'Inputs'!$B$23+'Inputs'!$B$24)*(1+'Inputs'!$B$10)^(A5-1)) -> 131328.12 | I5: =F5-G5-H5 -> 548756.39 | J5: =MAX(0,I5)*'Inputs'!$B$30 -> 0 | K5: =IF(A5=0,'Cost summary'!B10,0) -> 0 | L5: =IF(A5='Inputs'!$B$27,'Inputs'!$B$26*(1+'Inputs'!$B$10)^(A5-1),0) -> 0 | M5: =IF(A5='Inputs'!$B$2,(F5*(1+'Inputs'!$B$9)*(1-'Inputs'!$B$25)-H5*(1+'Inputs'!$B$10))/'Inputs'!$B$28*(1-'Inputs'!$B$29),0) -> 0 | N5: =IF(A5='Inputs'!$B$2,'Inputs'!$B$19,0) -> 0 | O5: =I5-J5-K5-L5+M5+N5 -> 548756.39 | P5: =P4+O5 -> -5038943.1 | Q5: =1/(1+'Inputs'!$B$11)^A5 -> 0.81629788 | R5: =O5*Q5 -> 447948.67 | S5: =S4+R5 -> -5242506.1 | T5: =IF(AND(P5>=0,P4<0),A5-1-P4/O5,999) -> 999 | U5: =IF(AND(S5>=0,S4<0),A5-1-S4/R5,999) -> 999
A6: 4 | B6: =ROUNDUP('Inputs'!$B$3*'Inputs'!$B$4,0) -> 20 | C6: ='Inputs'!$B$3-B6 -> 80 | D6: =IF(A6=0,0,C6*'Inputs'!$B$5*'Inputs'!$B$7*'Inputs'!$B$8*(1+'Inputs'!$B$9)^(A6-1)) -> 629084.1 | E6: =IF(A6=0,0,B6*'Inputs'!$B$6*'Inputs'!$B$7*'Inputs'!$B$8*(1+'Inputs'!$B$9)^(A6-1)) -> 108879.94 | F6: =D6+E6 -> 737964.04 | G6: =F6*'Inputs'!$B$25 -> 44277.843 | H6: =IF(A6=0,0,('Inputs'!$B$3*('Inputs'!$B$20+'Inputs'!$B$21)+'Inputs'!$B$22+'Inputs'!$B$23+'Inputs'!$B$24)*(1+'Inputs'!$B$10)^(A6-1)) -> 134611.33 | I6: =F6-G6-H6 -> 559074.87 | J6: =MAX(0,I6)*'Inputs'!$B$30 -> 0 | K6: =IF(A6=0,'Cost summary'!B10,0) -> 0 | L6: =IF(A6='Inputs'!$B$27,'Inputs'!$B$26*(1+'Inputs'!$B$10)^(A6-1),0) -> 0 | M6: =IF(A6='Inputs'!$B$2,(F6*(1+'Inputs'!$B$9)*(1-'Inputs'!$B$25)-H6*(1+'Inputs'!$B$10))/'Inputs'!$B$28*(1-'Inputs'!$B$29),0) -> 0 | N6: =IF(A6='Inputs'!$B$2,'Inputs'!$B$19,0) -> 0 | O6: =I6-J6-K6-L6+M6+N6 -> 559074.87 | P6: =P5+O6 -> -4479868.2 | Q6: =1/(1+'Inputs'!$B$11)^A6 -> 0.76289521 | R6: =O6*Q6 -> 426515.54 | S6: =S5+R6 -> -4815990.5 | T6: =IF(AND(P6>=0,P5<0),A6-1-P5/O6,999) -> 999 | U6: =IF(AND(S6>=0,S5<0),A6-1-S5/R6,999) -> 999
A7: 5 | B7: =ROUNDUP('Inputs'!$B$3*'Inputs'!$B$4,0) -> 20 | C7: ='Inputs'!$B$3-B7 -> 80 | D7: =IF(A7=0,0,C7*'Inputs'!$B$5*'Inputs'!$B$7*'Inputs'!$B$8*(1+'Inputs'!$B$9)^(A7-1)) -> 641665.78 | E7: =IF(A7=0,0,B7*'Inputs'!$B$6*'Inputs'!$B$7*'Inputs'!$B$8*(1+'Inputs'!$B$9)^(A7-1)) -> 111057.54 | F7: =D7+E7 -> 752723.32 | G7: =F7*'Inputs'!$B$25 -> 45163.399 | H7: =IF(A7=0,0,('Inputs'!$B$3*('Inputs'!$B$20+'Inputs'!$B$21)+'Inputs'!$B$22+'Inputs'!$B$23+'Inputs'!$B$24)*(1+'Inputs'!$B$10)^(A7-1)) -> 137976.61 | I7: =F7-G7-H7 -> 569583.31 | J7: =MAX(0,I7)*'Inputs'!$B$30 -> 0 | K7: =IF(A7=0,'Cost summary'!B10,0) -> 0 | L7: =IF(A7='Inputs'!$B$27,'Inputs'!$B$26*(1+'Inputs'!$B$10)^(A7-1),0) -> 0 | M7: =IF(A7='Inputs'!$B$2,(F7*(1+'Inputs'!$B$9)*(1-'Inputs'!$B$25)-H7*(1+'Inputs'!$B$10))/'Inputs'!$B$28*(1-'Inputs'!$B$29),0) -> 0 | N7: =IF(A7='Inputs'!$B$2,'Inputs'!$B$19,0) -> 0 | O7: =I7-J7-K7-L7+M7+N7 -> 569583.31 | P7: =P6+O7 -> -3910284.9 | Q7: =1/(1+'Inputs'!$B$11)^A7 -> 0.71298618 | R7: =O7*Q7 -> 406105.03 | S7: =S6+R7 -> -4409885.5 | T7: =IF(AND(P7>=0,P6<0),A7-1-P6/O7,999) -> 999 | U7: =IF(AND(S7>=0,S6<0),A7-1-S6/R7,999) -> 999
A8: 6 | B8: =ROUNDUP('Inputs'!$B$3*'Inputs'!$B$4,0) -> 20 | C8: ='Inputs'!$B$3-B8 -> 80 | D8: =IF(A8=0,0,C8*'Inputs'!$B$5*'Inputs'!$B$7*'Inputs'!$B$8*(1+'Inputs'!$B$9)^(A8-1)) -> 654499.1 | E8: =IF(A8=0,0,B8*'Inputs'!$B$6*'Inputs'!$B$7*'Inputs'!$B$8*(1+'Inputs'!$B$9)^(A8-1)) -> 113278.69 | F8: =D8+E8 -> 767777.79 | G8: =F8*'Inputs'!$B$25 -> 46066.667 | H8: =IF(A8=0,0,('Inputs'!$B$3*('Inputs'!$B$20+'Inputs'!$B$21)+'Inputs'!$B$22+'Inputs'!$B$23+'Inputs'!$B$24)*(1+'Inputs'!$B$10)^(A8-1)) -> 141426.03 | I8: =F8-G8-H8 -> 580285.1 | J8: =MAX(0,I8)*'Inputs'!$B$30 -> 0 | K8: =IF(A8=0,'Cost summary'!B10,0) -> 0 | L8: =IF(A8='Inputs'!$B$27,'Inputs'!$B$26*(1+'Inputs'!$B$10)^(A8-1),0) -> 0 | M8: =IF(A8='Inputs'!$B$2,(F8*(1+'Inputs'!$B$9)*(1-'Inputs'!$B$25)-H8*(1+'Inputs'!$B$10))/'Inputs'!$B$28*(1-'Inputs'!$B$29),0) -> 0 | N8: =IF(A8='Inputs'!$B$2,'Inputs'!$B$19,0) -> 0 | O8: =I8-J8-K8-L8+M8+N8 -> 580285.1 | P8: =P7+O8 -> -3329999.8 | Q8: =1/(1+'Inputs'!$B$11)^A8 -> 0.66634222 | R8: =O8*Q8 -> 386668.46 | S8: =S7+R8 -> -4023217.1 | T8: =IF(AND(P8>=0,P7<0),A8-1-P7/O8,999) -> 999 | U8: =IF(AND(S8>=0,S7<0),A8-1-S7/R8,999) -> 999
A9: 7 | B9: =ROUNDUP('Inputs'!$B$3*'Inputs'!$B$4,0) -> 20 | C9: ='Inputs'!$B$3-B9 -> 80 | D9: =IF(A9=0,0,C9*'Inputs'!$B$5*'Inputs'!$B$7*'Inputs'!$B$8*(1+'Inputs'!$B$9)^(A9-1)) -> 667589.08 | E9: =IF(A9=0,0,B9*'Inputs'!$B$6*'Inputs'!$B$7*'Inputs'!$B$8*(1+'Inputs'!$B$9)^(A9-1)) -> 115544.26 | F9: =D9+E9 -> 783133.35 | G9: =F9*'Inputs'!$B$25 -> 46988.001 | H9: =IF(A9=0,0,('Inputs'!$B$3*('Inputs'!$B$20+'Inputs'!$B$21)+'Inputs'!$B$22+'Inputs'!$B$23+'Inputs'!$B$24)*(1+'Inputs'!$B$10)^(A9-1)) -> 144961.68 | I9: =F9-G9-H9 -> 591183.67 | J9: =MAX(0,I9)*'Inputs'!$B$30 -> 0 | K9: =IF(A9=0,'Cost summary'!B10,0) -> 0 | L9: =IF(A9='Inputs'!$B$27,'Inputs'!$B$26*(1+'Inputs'!$B$10)^(A9-1),0) -> 0 | M9: =IF(A9='Inputs'!$B$2,(F9*(1+'Inputs'!$B$9)*(1-'Inputs'!$B$25)-H9*(1+'Inputs'!$B$10))/'Inputs'!$B$28*(1-'Inputs'!$B$29),0) -> 0 | N9: =IF(A9='Inputs'!$B$2,'Inputs'!$B$19,0) -> 0 | O9: =I9-J9-K9-L9+M9+N9 -> 591183.67 | P9: =P8+O9 -> -2738816.1 | Q9: =1/(1+'Inputs'!$B$11)^A9 -> 0.62274974 | R9: =O9*Q9 -> 368159.48 | S9: =S8+R9 -> -3655057.6 | T9: =IF(AND(P9>=0,P8<0),A9-1-P8/O9,999) -> 999 | U9: =IF(AND(S9>=0,S8<0),A9-1-S8/R9,999) -> 999
A10: 8 | B10: =ROUNDUP('Inputs'!$B$3*'Inputs'!$B$4,0) -> 20 | C10: ='Inputs'!$B$3-B10 -> 80 | D10: =IF(A10=0,0,C10*'Inputs'!$B$5*'Inputs'!$B$7*'Inputs'!$B$8*(1+'Inputs'!$B$9)^(A10-1)) -> 680940.86 | E10: =IF(A10=0,0,B10*'Inputs'!$B$6*'Inputs'!$B$7*'Inputs'!$B$8*(1+'Inputs'!$B$9)^(A10-1)) -> 117855.15 | F10: =D10+E10 -> 798796.01 | G10: =F10*'Inputs'!$B$25 -> 47927.761 | H10: =IF(A10=0,0,('Inputs'!$B$3*('Inputs'!$B$20+'Inputs'!$B$21)+'Inputs'!$B$22+'Inputs'!$B$23+'Inputs'!$B$24)*(1+'Inputs'!$B$10)^(A10-1)) -> 148585.72 | I10: =F10-G10-H10 -> 602282.53 | J10: =MAX(0,I10)*'Inputs'!$B$30 -> 0 | K10: =IF(A10=0,'Cost summary'!B10,0) -> 0 | L10: =IF(A10='Inputs'!$B$27,'Inputs'!$B$26*(1+'Inputs'!$B$10)^(A10-1),0) -> 0 | M10: =IF(A10='Inputs'!$B$2,(F10*(1+'Inputs'!$B$9)*(1-'Inputs'!$B$25)-H10*(1+'Inputs'!$B$10))/'Inputs'!$B$28*(1-'Inputs'!$B$29),0) -> 0 | N10: =IF(A10='Inputs'!$B$2,'Inputs'!$B$19,0) -> 0 | O10: =I10-J10-K10-L10+M10+N10 -> 602282.53 | P10: =P9+O10 -> -2136533.6 | Q10: =1/(1+'Inputs'!$B$11)^A10 -> 0.5820091 | R10: =O10*Q10 -> 350533.92 | S10: =S9+R10 -> -3304523.7 | T10: =IF(AND(P10>=0,P9<0),A10-1-P9/O10,999) -> 999 | U10: =IF(AND(S10>=0,S9<0),A10-1-S9/R10,999) -> 999
A11: 9 | B11: =ROUNDUP('Inputs'!$B$3*'Inputs'!$B$4,0) -> 20 | C11: ='Inputs'!$B$3-B11 -> 80 | D11: =IF(A11=0,0,C11*'Inputs'!$B$5*'Inputs'!$B$7*'Inputs'!$B$8*(1+'Inputs'!$B$9)^(A11-1)) -> 694559.68 | E11: =IF(A11=0,0,B11*'Inputs'!$B$6*'Inputs'!$B$7*'Inputs'!$B$8*(1+'Inputs'!$B$9)^(A11-1)) -> 120212.25 | F11: =D11+E11 -> 814771.93 | G11: =F11*'Inputs'!$B$25 -> 48886.316 | H11: =IF(A11=0,0,('Inputs'!$B$3*('Inputs'!$B$20+'Inputs'!$B$21)+'Inputs'!$B$22+'Inputs'!$B$23+'Inputs'!$B$24)*(1+'Inputs'!$B$10)^(A11-1)) -> 152300.36 | I11: =F11-G11-H11 -> 613585.26 | J11: =MAX(0,I11)*'Inputs'!$B$30 -> 0 | K11: =IF(A11=0,'Cost summary'!B10,0) -> 0 | L11: =IF(A11='Inputs'!$B$27,'Inputs'!$B$26*(1+'Inputs'!$B$10)^(A11-1),0) -> 0 | M11: =IF(A11='Inputs'!$B$2,(F11*(1+'Inputs'!$B$9)*(1-'Inputs'!$B$25)-H11*(1+'Inputs'!$B$10))/'Inputs'!$B$28*(1-'Inputs'!$B$29),0) -> 0 | N11: =IF(A11='Inputs'!$B$2,'Inputs'!$B$19,0) -> 0 | O11: =I11-J11-K11-L11+M11+N11 -> 613585.26 | P11: =P10+O11 -> -1522948.4 | Q11: =1/(1+'Inputs'!$B$11)^A11 -> 0.54393374 | R11: =O11*Q11 -> 333749.72 | S11: =S10+R11 -> -2970773.9 | T11: =IF(AND(P11>=0,P10<0),A11-1-P10/O11,999) -> 999 | U11: =IF(AND(S11>=0,S10<0),A11-1-S10/R11,999) -> 999
A12: 10 | B12: =ROUNDUP('Inputs'!$B$3*'Inputs'!$B$4,0) -> 20 | C12: ='Inputs'!$B$3-B12 -> 80 | D12: =IF(A12=0,0,C12*'Inputs'!$B$5*'Inputs'!$B$7*'Inputs'!$B$8*(1+'Inputs'!$B$9)^(A12-1)) -> 708450.87 | E12: =IF(A12=0,0,B12*'Inputs'!$B$6*'Inputs'!$B$7*'Inputs'!$B$8*(1+'Inputs'!$B$9)^(A12-1)) -> 122616.5 | F12: =D12+E12 -> 831067.37 | G12: =F12*'Inputs'!$B$25 -> 49864.042 | H12: =IF(A12=0,0,('Inputs'!$B$3*('Inputs'!$B$20+'Inputs'!$B$21)+'Inputs'!$B$22+'Inputs'!$B$23+'Inputs'!$B$24)*(1+'Inputs'!$B$10)^(A12-1)) -> 156107.87 | I12: =F12-G12-H12 -> 625095.46 | J12: =MAX(0,I12)*'Inputs'!$B$30 -> 0 | K12: =IF(A12=0,'Cost summary'!B10,0) -> 0 | L12: =IF(A12='Inputs'!$B$27,'Inputs'!$B$26*(1+'Inputs'!$B$10)^(A12-1),0) -> 312215.74 | M12: =IF(A12='Inputs'!$B$2,(F12*(1+'Inputs'!$B$9)*(1-'Inputs'!$B$25)-H12*(1+'Inputs'!$B$10))/'Inputs'!$B$28*(1-'Inputs'!$B$29),0) -> 0 | N12: =IF(A12='Inputs'!$B$2,'Inputs'!$B$19,0) -> 0 | O12: =I12-J12-K12-L12+M12+N12 -> 312879.72 | P12: =P11+O12 -> -1210068.6 | Q12: =1/(1+'Inputs'!$B$11)^A12 -> 0.50834929 | R12: =O12*Q12 -> 159052.18 | S12: =S11+R12 -> -2811721.8 | T12: =IF(AND(P12>=0,P11<0),A12-1-P11/O12,999) -> 999 | U12: =IF(AND(S12>=0,S11<0),A12-1-S11/R12,999) -> 999
A13: 11 | B13: =ROUNDUP('Inputs'!$B$3*'Inputs'!$B$4,0) -> 20 | C13: ='Inputs'!$B$3-B13 -> 80 | D13: =IF(A13=0,0,C13*'Inputs'!$B$5*'Inputs'!$B$7*'Inputs'!$B$8*(1+'Inputs'!$B$9)^(A13-1)) -> 722619.89 | E13: =IF(A13=0,0,B13*'Inputs'!$B$6*'Inputs'!$B$7*'Inputs'!$B$8*(1+'Inputs'!$B$9)^(A13-1)) -> 125068.83 | F13: =D13+E13 -> 847688.72 | G13: =F13*'Inputs'!$B$25 -> 50861.323 | H13: =IF(A13=0,0,('Inputs'!$B$3*('Inputs'!$B$20+'Inputs'!$B$21)+'Inputs'!$B$22+'Inputs'!$B$23+'Inputs'!$B$24)*(1+'Inputs'!$B$10)^(A13-1)) -> 160010.57 | I13: =F13-G13-H13 -> 636816.83 | J13: =MAX(0,I13)*'Inputs'!$B$30 -> 0 | K13: =IF(A13=0,'Cost summary'!B10,0) -> 0 | L13: =IF(A13='Inputs'!$B$27,'Inputs'!$B$26*(1+'Inputs'!$B$10)^(A13-1),0) -> 0 | M13: =IF(A13='Inputs'!$B$2,(F13*(1+'Inputs'!$B$9)*(1-'Inputs'!$B$25)-H13*(1+'Inputs'!$B$10))/'Inputs'!$B$28*(1-'Inputs'!$B$29),0) -> 0 | N13: =IF(A13='Inputs'!$B$2,'Inputs'!$B$19,0) -> 0 | O13: =I13-J13-K13-L13+M13+N13 -> 636816.83 | P13: =P12+O13 -> -573251.81 | Q13: =1/(1+'Inputs'!$B$11)^A13 -> 0.4750928 | R13: =O13*Q13 -> 302547.09 | S13: =S12+R13 -> -2509174.7 | T13: =IF(AND(P13>=0,P12<0),A13-1-P12/O13,999) -> 999 | U13: =IF(AND(S13>=0,S12<0),A13-1-S12/R13,999) -> 999
A14: 12 | B14: =ROUNDUP('Inputs'!$B$3*'Inputs'!$B$4,0) -> 20 | C14: ='Inputs'!$B$3-B14 -> 80 | D14: =IF(A14=0,0,C14*'Inputs'!$B$5*'Inputs'!$B$7*'Inputs'!$B$8*(1+'Inputs'!$B$9)^(A14-1)) -> 737072.29 | E14: =IF(A14=0,0,B14*'Inputs'!$B$6*'Inputs'!$B$7*'Inputs'!$B$8*(1+'Inputs'!$B$9)^(A14-1)) -> 127570.2 | F14: =D14+E14 -> 864642.49 | G14: =F14*'Inputs'!$B$25 -> 51878.55 | H14: =IF(A14=0,0,('Inputs'!$B$3*('Inputs'!$B$20+'Inputs'!$B$21)+'Inputs'!$B$22+'Inputs'!$B$23+'Inputs'!$B$24)*(1+'Inputs'!$B$10)^(A14-1)) -> 164010.83 | I14: =F14-G14-H14 -> 648753.11 | J14: =MAX(0,I14)*'Inputs'!$B$30 -> 0 | K14: =IF(A14=0,'Cost summary'!B10,0) -> 0 | L14: =IF(A14='Inputs'!$B$27,'Inputs'!$B$26*(1+'Inputs'!$B$10)^(A14-1),0) -> 0 | M14: =IF(A14='Inputs'!$B$2,(F14*(1+'Inputs'!$B$9)*(1-'Inputs'!$B$25)-H14*(1+'Inputs'!$B$10))/'Inputs'!$B$28*(1-'Inputs'!$B$29),0) -> 0 | N14: =IF(A14='Inputs'!$B$2,'Inputs'!$B$19,0) -> 0 | O14: =I14-J14-K14-L14+M14+N14 -> 648753.11 | P14: =P13+O14 -> 75501.301 | Q14: =1/(1+'Inputs'!$B$11)^A14 -> 0.44401196 | R14: =O14*Q14 -> 288054.14 | S14: =S13+R14 -> -2221120.5 | T14: =IF(AND(P14>=0,P13<0),A14-1-P13/O14,999) -> 11.883621 | U14: =IF(AND(S14>=0,S13<0),A14-1-S13/R14,999) -> 999
A15: 13 | B15: =ROUNDUP('Inputs'!$B$3*'Inputs'!$B$4,0) -> 20 | C15: ='Inputs'!$B$3-B15 -> 80 | D15: =IF(A15=0,0,C15*'Inputs'!$B$5*'Inputs'!$B$7*'Inputs'!$B$8*(1+'Inputs'!$B$9)^(A15-1)) -> 751813.74 | E15: =IF(A15=0,0,B15*'Inputs'!$B$6*'Inputs'!$B$7*'Inputs'!$B$8*(1+'Inputs'!$B$9)^(A15-1)) -> 130121.61 | F15: =D15+E15 -> 881935.34 | G15: =F15*'Inputs'!$B$25 -> 52916.121 | H15: =IF(A15=0,0,('Inputs'!$B$3*('Inputs'!$B$20+'Inputs'!$B$21)+'Inputs'!$B$22+'Inputs'!$B$23+'Inputs'!$B$24)*(1+'Inputs'!$B$10)^(A15-1)) -> 168111.1 | I15: =F15-G15-H15 -> 660908.12 | J15: =MAX(0,I15)*'Inputs'!$B$30 -> 0 | K15: =IF(A15=0,'Cost summary'!B10,0) -> 0 | L15: =IF(A15='Inputs'!$B$27,'Inputs'!$B$26*(1+'Inputs'!$B$10)^(A15-1),0) -> 0 | M15: =IF(A15='Inputs'!$B$2,(F15*(1+'Inputs'!$B$9)*(1-'Inputs'!$B$25)-H15*(1+'Inputs'!$B$10))/'Inputs'!$B$28*(1-'Inputs'!$B$29),0) -> 0 | N15: =IF(A15='Inputs'!$B$2,'Inputs'!$B$19,0) -> 0 | O15: =I15-J15-K15-L15+M15+N15 -> 660908.12 | P15: =P14+O15 -> 736409.42 | Q15: =1/(1+'Inputs'!$B$11)^A15 -> 0.41496445 | R15: =O15*Q15 -> 274253.37 | S15: =S14+R15 -> -1946867.2 | T15: =IF(AND(P15>=0,P14<0),A15-1-P14/O15,999) -> 999 | U15: =IF(AND(S15>=0,S14<0),A15-1-S14/R15,999) -> 999
A16: 14 | B16: =ROUNDUP('Inputs'!$B$3*'Inputs'!$B$4,0) -> 20 | C16: ='Inputs'!$B$3-B16 -> 80 | D16: =IF(A16=0,0,C16*'Inputs'!$B$5*'Inputs'!$B$7*'Inputs'!$B$8*(1+'Inputs'!$B$9)^(A16-1)) -> 766850.01 | E16: =IF(A16=0,0,B16*'Inputs'!$B$6*'Inputs'!$B$7*'Inputs'!$B$8*(1+'Inputs'!$B$9)^(A16-1)) -> 132724.04 | F16: =D16+E16 -> 899574.05 | G16: =F16*'Inputs'!$B$25 -> 53974.443 | H16: =IF(A16=0,0,('Inputs'!$B$3*('Inputs'!$B$20+'Inputs'!$B$21)+'Inputs'!$B$22+'Inputs'!$B$23+'Inputs'!$B$24)*(1+'Inputs'!$B$10)^(A16-1)) -> 172313.88 | I16: =F16-G16-H16 -> 673285.73 | J16: =MAX(0,I16)*'Inputs'!$B$30 -> 0 | K16: =IF(A16=0,'Cost summary'!B10,0) -> 0 | L16: =IF(A16='Inputs'!$B$27,'Inputs'!$B$26*(1+'Inputs'!$B$10)^(A16-1),0) -> 0 | M16: =IF(A16='Inputs'!$B$2,(F16*(1+'Inputs'!$B$9)*(1-'Inputs'!$B$25)-H16*(1+'Inputs'!$B$10))/'Inputs'!$B$28*(1-'Inputs'!$B$29),0) -> 0 | N16: =IF(A16='Inputs'!$B$2,'Inputs'!$B$19,0) -> 0 | O16: =I16-J16-K16-L16+M16+N16 -> 673285.73 | P16: =P15+O16 -> 1409695.1 | Q16: =1/(1+'Inputs'!$B$11)^A16 -> 0.38781724 | R16: =O16*Q16 -> 261111.81 | S16: =S15+R16 -> -1685755.3 | T16: =IF(AND(P16>=0,P15<0),A16-1-P15/O16,999) -> 999 | U16: =IF(AND(S16>=0,S15<0),A16-1-S15/R16,999) -> 999
A17: 15 | B17: =ROUNDUP('Inputs'!$B$3*'Inputs'!$B$4,0) -> 20 | C17: ='Inputs'!$B$3-B17 -> 80 | D17: =IF(A17=0,0,C17*'Inputs'!$B$5*'Inputs'!$B$7*'Inputs'!$B$8*(1+'Inputs'!$B$9)^(A17-1)) -> 782187.01 | E17: =IF(A17=0,0,B17*'Inputs'!$B$6*'Inputs'!$B$7*'Inputs'!$B$8*(1+'Inputs'!$B$9)^(A17-1)) -> 135378.52 | F17: =D17+E17 -> 917565.53 | G17: =F17*'Inputs'!$B$25 -> 55053.932 | H17: =IF(A17=0,0,('Inputs'!$B$3*('Inputs'!$B$20+'Inputs'!$B$21)+'Inputs'!$B$22+'Inputs'!$B$23+'Inputs'!$B$24)*(1+'Inputs'!$B$10)^(A17-1)) -> 176621.73 | I17: =F17-G17-H17 -> 685889.87 | J17: =MAX(0,I17)*'Inputs'!$B$30 -> 0 | K17: =IF(A17=0,'Cost summary'!B10,0) -> 0 | L17: =IF(A17='Inputs'!$B$27,'Inputs'!$B$26*(1+'Inputs'!$B$10)^(A17-1),0) -> 0 | M17: =IF(A17='Inputs'!$B$2,(F17*(1+'Inputs'!$B$9)*(1-'Inputs'!$B$25)-H17*(1+'Inputs'!$B$10))/'Inputs'!$B$28*(1-'Inputs'!$B$29),0) -> 0 | N17: =IF(A17='Inputs'!$B$2,'Inputs'!$B$19,0) -> 0 | O17: =I17-J17-K17-L17+M17+N17 -> 685889.87 | P17: =P16+O17 -> 2095585 | Q17: =1/(1+'Inputs'!$B$11)^A17 -> 0.36244602 | R17: =O17*Q17 -> 248598.05 | S17: =S16+R17 -> -1437157.3 | T17: =IF(AND(P17>=0,P16<0),A17-1-P16/O17,999) -> 999 | U17: =IF(AND(S17>=0,S16<0),A17-1-S16/R17,999) -> 999
A18: 16 | B18: =ROUNDUP('Inputs'!$B$3*'Inputs'!$B$4,0) -> 20 | C18: ='Inputs'!$B$3-B18 -> 80 | D18: =IF(A18=0,0,C18*'Inputs'!$B$5*'Inputs'!$B$7*'Inputs'!$B$8*(1+'Inputs'!$B$9)^(A18-1)) -> 797830.75 | E18: =IF(A18=0,0,B18*'Inputs'!$B$6*'Inputs'!$B$7*'Inputs'!$B$8*(1+'Inputs'!$B$9)^(A18-1)) -> 138086.09 | F18: =D18+E18 -> 935916.84 | G18: =F18*'Inputs'!$B$25 -> 56155.011 | H18: =IF(A18=0,0,('Inputs'!$B$3*('Inputs'!$B$20+'Inputs'!$B$21)+'Inputs'!$B$22+'Inputs'!$B$23+'Inputs'!$B$24)*(1+'Inputs'!$B$10)^(A18-1)) -> 181037.27 | I18: =F18-G18-H18 -> 698724.56 | J18: =MAX(0,I18)*'Inputs'!$B$30 -> 0 | K18: =IF(A18=0,'Cost summary'!B10,0) -> 0 | L18: =IF(A18='Inputs'!$B$27,'Inputs'!$B$26*(1+'Inputs'!$B$10)^(A18-1),0) -> 0 | M18: =IF(A18='Inputs'!$B$2,(F18*(1+'Inputs'!$B$9)*(1-'Inputs'!$B$25)-H18*(1+'Inputs'!$B$10))/'Inputs'!$B$28*(1-'Inputs'!$B$29),0) -> 0 | N18: =IF(A18='Inputs'!$B$2,'Inputs'!$B$19,0) -> 0 | O18: =I18-J18-K18-L18+M18+N18 -> 698724.56 | P18: =P17+O18 -> 2794309.6 | Q18: =1/(1+'Inputs'!$B$11)^A18 -> 0.3387346 | R18: =O18*Q18 -> 236682.18 | S18: =S17+R18 -> -1200475.1 | T18: =IF(AND(P18>=0,P17<0),A18-1-P17/O18,999) -> 999 | U18: =IF(AND(S18>=0,S17<0),A18-1-S17/R18,999) -> 999
A19: 17 | B19: =ROUNDUP('Inputs'!$B$3*'Inputs'!$B$4,0) -> 20 | C19: ='Inputs'!$B$3-B19 -> 80 | D19: =IF(A19=0,0,C19*'Inputs'!$B$5*'Inputs'!$B$7*'Inputs'!$B$8*(1+'Inputs'!$B$9)^(A19-1)) -> 813787.37 | E19: =IF(A19=0,0,B19*'Inputs'!$B$6*'Inputs'!$B$7*'Inputs'!$B$8*(1+'Inputs'!$B$9)^(A19-1)) -> 140847.81 | F19: =D19+E19 -> 954635.18 | G19: =F19*'Inputs'!$B$25 -> 57278.111 | H19: =IF(A19=0,0,('Inputs'!$B$3*('Inputs'!$B$20+'Inputs'!$B$21)+'Inputs'!$B$22+'Inputs'!$B$23+'Inputs'!$B$24)*(1+'Inputs'!$B$10)^(A19-1)) -> 185563.2 | I19: =F19-G19-H19 -> 711793.87 | J19: =MAX(0,I19)*'Inputs'!$B$30 -> 0 | K19: =IF(A19=0,'Cost summary'!B10,0) -> 0 | L19: =IF(A19='Inputs'!$B$27,'Inputs'!$B$26*(1+'Inputs'!$B$10)^(A19-1),0) -> 0 | M19: =IF(A19='Inputs'!$B$2,(F19*(1+'Inputs'!$B$9)*(1-'Inputs'!$B$25)-H19*(1+'Inputs'!$B$10))/'Inputs'!$B$28*(1-'Inputs'!$B$29),0) -> 0 | N19: =IF(A19='Inputs'!$B$2,'Inputs'!$B$19,0) -> 0 | O19: =I19-J19-K19-L19+M19+N19 -> 711793.87 | P19: =P18+O19 -> 3506103.4 | Q19: =1/(1+'Inputs'!$B$11)^A19 -> 0.31657439 | R19: =O19*Q19 -> 225335.71 | S19: =S18+R19 -> -975139.39 | T19: =IF(AND(P19>=0,P18<0),A19-1-P18/O19,999) -> 999 | U19: =IF(AND(S19>=0,S18<0),A19-1-S18/R19,999) -> 999
A20: 18 | B20: =ROUNDUP('Inputs'!$B$3*'Inputs'!$B$4,0) -> 20 | C20: ='Inputs'!$B$3-B20 -> 80 | D20: =IF(A20=0,0,C20*'Inputs'!$B$5*'Inputs'!$B$7*'Inputs'!$B$8*(1+'Inputs'!$B$9)^(A20-1)) -> 830063.11 | E20: =IF(A20=0,0,B20*'Inputs'!$B$6*'Inputs'!$B$7*'Inputs'!$B$8*(1+'Inputs'!$B$9)^(A20-1)) -> 143664.77 | F20: =D20+E20 -> 973727.88 | G20: =F20*'Inputs'!$B$25 -> 58423.673 | H20: =IF(A20=0,0,('Inputs'!$B$3*('Inputs'!$B$20+'Inputs'!$B$21)+'Inputs'!$B$22+'Inputs'!$B$23+'Inputs'!$B$24)*(1+'Inputs'!$B$10)^(A20-1)) -> 190202.28 | I20: =F20-G20-H20 -> 725101.93 | J20: =MAX(0,I20)*'Inputs'!$B$30 -> 0 | K20: =IF(A20=0,'Cost summary'!B10,0) -> 0 | L20: =IF(A20='Inputs'!$B$27,'Inputs'!$B$26*(1+'Inputs'!$B$10)^(A20-1),0) -> 0 | M20: =IF(A20='Inputs'!$B$2,(F20*(1+'Inputs'!$B$9)*(1-'Inputs'!$B$25)-H20*(1+'Inputs'!$B$10))/'Inputs'!$B$28*(1-'Inputs'!$B$29),0) -> 0 | N20: =IF(A20='Inputs'!$B$2,'Inputs'!$B$19,0) -> 0 | O20: =I20-J20-K20-L20+M20+N20 -> 725101.93 | P20: =P19+O20 -> 4231205.4 | Q20: =1/(1+'Inputs'!$B$11)^A20 -> 0.29586392 | R20: =O20*Q20 -> 214531.5 | S20: =S19+R20 -> -760607.9 | T20: =IF(AND(P20>=0,P19<0),A20-1-P19/O20,999) -> 999 | U20: =IF(AND(S20>=0,S19<0),A20-1-S19/R20,999) -> 999
A21: 19 | B21: =ROUNDUP('Inputs'!$B$3*'Inputs'!$B$4,0) -> 20 | C21: ='Inputs'!$B$3-B21 -> 80 | D21: =IF(A21=0,0,C21*'Inputs'!$B$5*'Inputs'!$B$7*'Inputs'!$B$8*(1+'Inputs'!$B$9)^(A21-1)) -> 846664.38 | E21: =IF(A21=0,0,B21*'Inputs'!$B$6*'Inputs'!$B$7*'Inputs'!$B$8*(1+'Inputs'!$B$9)^(A21-1)) -> 146538.07 | F21: =D21+E21 -> 993202.44 | G21: =F21*'Inputs'!$B$25 -> 59592.146 | H21: =IF(A21=0,0,('Inputs'!$B$3*('Inputs'!$B$20+'Inputs'!$B$21)+'Inputs'!$B$22+'Inputs'!$B$23+'Inputs'!$B$24)*(1+'Inputs'!$B$10)^(A21-1)) -> 194957.34 | I21: =F21-G21-H21 -> 738652.95 | J21: =MAX(0,I21)*'Inputs'!$B$30 -> 0 | K21: =IF(A21=0,'Cost summary'!B10,0) -> 0 | L21: =IF(A21='Inputs'!$B$27,'Inputs'!$B$26*(1+'Inputs'!$B$10)^(A21-1),0) -> 0 | M21: =IF(A21='Inputs'!$B$2,(F21*(1+'Inputs'!$B$9)*(1-'Inputs'!$B$25)-H21*(1+'Inputs'!$B$10))/'Inputs'!$B$28*(1-'Inputs'!$B$29),0) -> 0 | N21: =IF(A21='Inputs'!$B$2,'Inputs'!$B$19,0) -> 0 | O21: =I21-J21-K21-L21+M21+N21 -> 738652.95 | P21: =P20+O21 -> 4969858.3 | Q21: =1/(1+'Inputs'!$B$11)^A21 -> 0.27650833 | R21: =O21*Q21 -> 204243.7 | S21: =S20+R21 -> -556364.2 | T21: =IF(AND(P21>=0,P20<0),A21-1-P20/O21,999) -> 999 | U21: =IF(AND(S21>=0,S20<0),A21-1-S20/R21,999) -> 999
A22: 20 | B22: =ROUNDUP('Inputs'!$B$3*'Inputs'!$B$4,0) -> 20 | C22: ='Inputs'!$B$3-B22 -> 80 | D22: =IF(A22=0,0,C22*'Inputs'!$B$5*'Inputs'!$B$7*'Inputs'!$B$8*(1+'Inputs'!$B$9)^(A22-1)) -> 863597.66 | E22: =IF(A22=0,0,B22*'Inputs'!$B$6*'Inputs'!$B$7*'Inputs'!$B$8*(1+'Inputs'!$B$9)^(A22-1)) -> 149468.83 | F22: =D22+E22 -> 1013066.5 | G22: =F22*'Inputs'!$B$25 -> 60783.989 | H22: =IF(A22=0,0,('Inputs'!$B$3*('Inputs'!$B$20+'Inputs'!$B$21)+'Inputs'!$B$22+'Inputs'!$B$23+'Inputs'!$B$24)*(1+'Inputs'!$B$10)^(A22-1)) -> 199831.27 | I22: =F22-G22-H22 -> 752451.23 | J22: =MAX(0,I22)*'Inputs'!$B$30 -> 0 | K22: =IF(A22=0,'Cost summary'!B10,0) -> 0 | L22: =IF(A22='Inputs'!$B$27,'Inputs'!$B$26*(1+'Inputs'!$B$10)^(A22-1),0) -> 0 | M22: =IF(A22='Inputs'!$B$2,(F22*(1+'Inputs'!$B$9)*(1-'Inputs'!$B$25)-H22*(1+'Inputs'!$B$10))/'Inputs'!$B$28*(1-'Inputs'!$B$29),0) -> 13657656 | N22: =IF(A22='Inputs'!$B$2,'Inputs'!$B$19,0) -> 25000 | O22: =I22-J22-K22-L22+M22+N22 -> 14435107 | P22: =P21+O22 -> 19404965 | Q22: =1/(1+'Inputs'!$B$11)^A22 -> 0.258419 | R22: =O22*Q22 -> 3730306 | S22: =S21+R22 -> 3173941.8 | T22: =IF(AND(P22>=0,P21<0),A22-1-P21/O22,999) -> 999 | U22: =IF(AND(S22>=0,S21<0),A22-1-S21/R22,999) -> 19.149147

Sheet Locations
A1: Candidate | B1: VUB Etterbeek min | C1: ULB Solbosch min | D1: VUB Jette min | E1: Weighted commute min | F1: Status
A2: Etterbeek / Ixelles | B2: 10 | C2: 15 | D2: 50 | E2: =SUMPRODUCT(B2:D2,$B$7:$D$7) -> 16.25 | F2: Illustrative times; provisional candidate
A3: Brussels centre | B3: 25 | C3: 30 | D3: 30 | E3: =SUMPRODUCT(B3:D3,$B$7:$D$7) -> 27.75 | F3: Illustrative times
A4: Jette | B4: 50 | C4: 55 | D4: 10 | E4: =SUMPRODUCT(B4:D4,$B$7:$D$7) -> 48.25 | F4: Illustrative times
A5: Travel times are assumptions, not verified transit measurements.
A6: Weights reflect target students; change to match institution agreements.
A7: Student weights | B7: 0.45 | C7: 0.45 | D7: 0.1 | E7: =SUM(B7:D7) -> 1 | F7: Weights must sum to 1
A8: Lowest weighted commute | B8: =MIN(E2:E4) -> 16.25
A9: Preferred candidate | B9: =INDEX(A2:A4,MATCH(B8,E2:E4,0)) -> Etterbeek / Ixelles

Sheet Sources
A1: TOPIC | B1: SOURCE / URL | C1: STATUS | D1: MODEL IMPLICATION
A2: All financial inputs | B2: Analyst assumptions | C2: Unverified | D2: Replace with actual quotations; no claim of market accuracy
A3: Social room quota | B3: https://www.bruxelles.be/sites/default/files/bxl/Recommandations_logements_etudiants_VBX_17juin2021.pdf | C3: City guidance, 17 June 2021; search-index excerpt; full PDF fetch blocked | D3: 20% social student units from 30 units; City of Brussels scope. Confirm current permit conditions locally.
A4: Registration duty | B4: https://be.brussels/fr/impots-financement/impots-et-taxes/fiscalite-immobiliere/droits-denregistrement | C4: Official Brussels Region; reviewed 2026-10-14 | D4: Standard rate 12.5%; applied to acquisition proxy; transaction basis needs notary confirmation.
A5: VAT alternative | B5: https://financien.belgium.be/fr/particuliers/habitation/acheter-vendre/droits-enregistrement/bruxelles | C5: Federal Finance; reviewed 2026-10-14 | D5: New property purchase may trigger VAT instead of registration duty. Avoid double counting.
A6: Student quality label | B6: https://be.brussels/en/housing/rental/conformity-for-rental-properties/ensuring-quality-student-housing | C6: Official Brussels Region; reviewed 2026-10-14 | D6: Housing Code conformity, compliant student lease and valid EPB required for label application; label lasts five years.
A7: Student social eligibility | B7: https://www.vub.be/sites/default/files/2026-04/2026_Huurinformatie_VUB_Koten_Handleiding_aanvraag_SVKS_ENG_0.pdf | C7: VUB 2026 SVKS guidance; reviewed search excerpt | D7: SVKS route requires student enrolment and social income eligibility; use VUB/AISE to validate allocation rules.
A8: Institution collaboration | B8: https://www.ulb.be/medias/fichier/20250725-ulb-environnement-et-mobilite-rapport-de-durabilite-en_1753692398626-pdf?ID_FICHE=1020633&INLINE=FALSE | C8: ULB sustainability report 2025; reviewed search excerpt | D8: ULB describes AISE partnership. Candidate counterpart, not a secured agreement for this project.
A9: AISE contact | B9: https://www.aise-svks.brussels/proprietaires/ | C9: Site under construction when checked 2026-10-14 | D9: Published contact info@aise-svks.brussels; negotiate landlord contract, allocation and rent terms.
A10: Municipal housing tax | B10: https://www.brussels.be/student-housing | C10: City of Brussels; reviewed 2026-10-14 | D10: City distinguishes student second-home exemption from furnished letting tax on landlord. Check municipality of actual site.
A11: Travel / financial market data | B11: Analyst scenario assumptions | C11: Not independently measured or quoted | D11: Rents, capital costs and travel times are illustrative; require property quotations and timetable measurements.

Sheet LLM prompt
A1: REUSABLE PROJECT PROMPT
A2: Build an auditable Excel workbook for the VUB master course Decision Analytics: a basic student housing investment in Brussels over 20 years. Include cost summary, editable inputs, annual mathematical cash flow model with cumulative and discounted cash flows, and a final results tab for NPV, IRR, simple and discounted payback. Separate market and social rooms, rents, occupancy, escalation, acquisition, works, transaction costs, management, maintenance, taxes, replacement capital expenditure, working capital and terminal sale. Use year 0 investment and years 1–20 operations. Document every assumption and cite official sources for any legal claims. Do not invent a minimum social housing percentage: provide a separate editable required quota and a verification flag, and identify project-specific planning and university agreement checks. Compare candidate locations using student-weighted commute times to VUB/ULB campuses, clearly marking unverified travel times. Distinguish unlevered project returns from financed equity returns. Include an investment recommendation conditional on financial and legal assumptions. Save as model.xlsx. Note the City of Brussels 2021 student housing recommendations specify a 20% social share from 30 units; verify current applicability to the selected municipality and permit. Supply a numeric baseline while keeping formulas editable, show the impact of excluding terminal sale, and provide a source and status for each legal assumption.

Sheet Results
A1: RESULT | B1: VALUE | C1: INTERPRETATION
A2: NPV | B2: =SUM(Model!R2:R22) -> 3173941.8 | C2: Nominal discount rate; includes exit
A3: IRR | B3: =IFERROR(IRR(Model!O2:O22),"No IRR") -> 0.10516992 | C3: Annual project return; includes exit
A4: Initial investment | B4: ='Cost summary'!B10 -> 6655000 | C4: Year 0 outflow
A5: Year 1 NOI | B5: =Model!I3 -> 528676 | C5: Revenue less operating costs
A6: Net exit proceeds | B6: =Model!M22 -> 13657656 | C6: Year 21 NOI / exit cap rate less sale costs
A7: NPV excluding exit | B7: =B2-Model!M22*Model!Q22 -> -355456.03 | C7: Shows dependence on disposal
A8: Simple payback years | B8: =IF(MIN(Model!T2:T22)=999,"Not reached in 20 years",MIN(Model!T2:T22)) -> 11.883621 | C8: Linear interpolation; includes sale
A9: Discounted payback years | B9: =IF(MIN(Model!U2:U22)=999,"Not reached in 20 years",MIN(Model!U2:U22)) -> 19.149147 | C9: Linear interpolation; includes sale
A10: Financial indication | B10: =IF(B2>0,"Positive NPV","Negative / zero NPV") -> Positive NPV | C10: At selected discount rate
A11: Social / partnership status | B11: =IF(AND('Inputs'!$B$32=1,'Inputs'!$B$33=1,'Inputs'!$B$4>='Inputs'!$B$31),"Checks recorded","Pending verification / agreement") -> Pending verification / agreement | C11: No automatic legal certification
A12: Provisional location | B12: =Locations!B9 -> Etterbeek / Ixelles | C12: Among illustrative candidates only
A13: Location constraint | B13: =IF(Locations!B8<='Inputs'!$B$34,"Meets assumed target","Above target") -> Meets assumed target | C13: Assumed student weights and times
A14: Decision | B14: =IF(AND(B2>0,'Inputs'!$B$32=1,'Inputs'!$B$33=1,'Inputs'!$B$4>='Inputs'!$B$31,Locations!B8<='Inputs'!$B$34),"Proceed to detailed due diligence","Revise / verify before committing") -> Revise / verify before committing | C14: Screening only
A16: Total undiscounted net cash | B16: =SUM(Model!O2:O22) -> 19404965 | C16: Includes initial investment and disposal
A17: Social rooms | B17: =Model!B3 -> 20 | C17: Rounded up to whole rooms
A18: Cumulative operations at year 20 | B18: =Model!P22-Model!M22-Model!N22 -> 5722309.6 | C18: Excludes sale proceeds and working capital release
A19: Model checks | B19: =IF(AND('Inputs'!$B$2=20,Locations!E7=1,Model!B3+Model!C3='Inputs'!$B$3),"OK","CHECK INPUTS") -> OK | C19: 20-year horizon, student weights sum to 1, room counts reconcile
