Workbook

Sheet Read Me
A1: BRUSSELS | STUDENT HOUSING | B1: How to use this investment screen
A2: Decision | B2: Illustrative 100-room sustainable development; 10% affordable allocation. Investment screening, not a site valuation or loan offer.
A3: Workflow | B3: Read Dashboard and Executive Report; edit blue Inputs; inspect Budget and annual Cash Flow; compare Scenarios, Sensitivity and Simulation.
A4: Student housing | B4: Furnished individual study/bedrooms, private bathrooms, shared kitchens per 8–10 rooms, quiet study rooms, social space, laundry, secure bikes, accessible rooms and resident support.
A5: Location hypothesis | B5: Walkable transit corridor near ULB/VUB or another Brussels campus; site is not selected. Validate planning use, transit and room-level competing rents.
A6: Timing | B6: Year 0 financial close and all development spend; Year 1 construction with no rent; Years 2–21 are 20 operating years; sale at end of Year 21.
A7: Cash-flow convention | B7: Nominal EUR, annual end-year cash flows; pre-corporate-tax; no income-tax shield. Property taxes and irrecoverable development VAT included.
A8: Financing simplification | B8: All debt drawn at Year 0, interest-only during construction, 25-year amortisation from Year 2. Upfront spend/draw is conservative vs staged drawdown.
A9: Affordability | B9: 10 rooms at EUR450/month including EUR95 services in first operating year. Income eligibility via university welfare partner; identical room quality. Model annual 2% growth; covenant should cap increases.
A10: Sustainability | B10: Heat pumps, insulation/ventilation, solar, water-saving fixtures, reusable furniture, low-carbon/reused materials and zero parking. Energy targets are design assumptions, not certification.
A11: Sources and confidence | B11: Sources tab records primary evidence and limitations. Blue inputs are planning assumptions unless marked sourced. Construction, financing, yields and occupancy need quotations.
A12: Simulations | B12: 2,000 fixed-seed joint draws + 7 deterministic cases + 81-point rent/cost grid. Draws are fixed for auditability; formula outcomes recalculate when Inputs change. Rerun script to regenerate.
... A14: Reproduction | B14: Code: enhanced_model.py (openpyxl). Formula results cached for preview; Excel/LibreOffice recalculates after edits. All saves use a temporary XLSX and atomic replacement.

Sheet Inputs
A1: Input | B1: Value | C1: Unit | D1: Basis / reader guidance
A2: Rooms | B2: 100 | C2: rooms | D2: Concept; 90 standard and 10 affordable rooms.
A3: Affordable share | B3: 0.1 | C3: % | D3: User requirement: at least 10%; maintain covenant through sale.
A4: Standard bare rent | B4: 575 | C4: EUR/month | D4: 2025–26 Brussels room with bathroom benchmark: Kotkompas p3; no forecast premium.
A5: Affordable bare rent | B5: 355 | C5: EUR/month | D5: Assumption; EUR450 including services, close to VUB EUR449.30 all-in 2026–27.
A6: Service charge / occupied room | B6: 95 | C6: EUR/month | D6: Assumption; below Brussels EUR125 average charges in Kotkompas. Covers utilities and communal services.
A7: Billable months | B7: 12 | C7: months | D7: Annual lease assumption; financial occupancy captures voids and non-payment.
A8: Stabilised paid occupancy | B8: 0.95 | C8: % | D8: Assumption; demand alone does not prove absorption.
A9: First operating year occupancy | B9: 0.85 | C9: % | D9: Lease-up assumption.
A10: Rent and service charge growth | B10: 0.02 | C10: % | D10: Nominal assumption; not a legal entitlement to indexation.
A11: Operating cost inflation | B11: 0.025 | C11: % | D11: Assumption.
A12: Project discount rate | B12: 0.07 | C12: % | D12: Unlevered nominal pre-tax hurdle assumption.
A13: Equity discount rate | B13: 0.09 | C13: % | D13: Levered nominal pre-tax hurdle assumption.
... A48: Affordable tenant monthly resources | B48: 1300 | C48: EUR/month | D48: Targeting example for affordability burden, not observed household income.

Sheet Budget
A1: Development cost item | B1: EUR | C1: Definition
A2: Site acquisition | B2: =Inputs!$B$16 -> 1500000
A3: Site registration duty | B3: =Inputs!$B$16*Inputs!$B$17 -> 187500
A4: Base construction | B4: =Inputs!$B$18*Inputs!$B$19 -> 5400000
A5: Sustainability package | B5: =Inputs!$B$20 -> 400000
A6: Furniture | B6: =Inputs!$B$21 -> 250000
A7: Professional fees | B7: =(B4+B5)*Inputs!$B$22 -> 580000
A8: Contingency | B8: =(B4+B5)*Inputs!$B$23 -> 580000
A9: Irrecoverable VAT | B9: =SUM(B4:B8)*Inputs!$B$24 -> 1514100
A10: Legal and due diligence | B10: =Inputs!$B$25 -> 50000
A11: Financing fees | B11: =Inputs!$B$26 -> 50000
A12: Working capital | B12: =Inputs!$B$27 -> 100000
A13: GROSS DEVELOPMENT COST | B13: =SUM(B2:B12) -> 10611600
A14: Confirmed grant | B14: =Inputs!$B$28 -> 0
A15: Net cost to capital providers | B15: =B13-B14 -> 10611600
A16: Initial debt | B16: =B13*Inputs!$B$29 -> 5305800
A17: Initial equity | B17: =B15-B16 -> 5305800
A18: Gross cost / room | B18: =B13/Inputs!$B$2 -> 106116

Sheet Cash Flow
A1: Year | B1: Operating year | C1: Total revenue | D1: Fixed operating costs | E1: Management fee | F1: NOI | G1: Replacement reserve | H1: Opening debt | I1: Interest | J1: Principal | K1: Debt service | L1: Closing debt | M1: Net sale proceeds | N1: Project CF | O1: Equity CF | P1: Cash DSCR | Q1: Cum project CF | R1: Discounted project CF | S1: Cum discounted CF | T1: Cumulative equity CF
A2: 0 | B2: 0 | C2: 0 | D2: 0 | E2: 0 | F2: 0 | G2: 0 | H2: 0 | I2: 0 | J2: 0 | K2: 0 | L2: =Budget!B16 -> 5305800 | M2: 0 | N2: =-Budget!B15 -> -10611600 | O2: =-Budget!B17 -> -5305800 | P2: 0 | Q2: =N2 -> -10611600 | R2: =N2 -> -10611600 | S2: =R2 -> -10611600 | T2: =SUM(O$2:O2) -> -5305800
A3: 1 | B3: =A3-1 -> 0 | C3: =IF(B3<1,0,Inputs!$B$2*((1-Inputs!$B$3)*Inputs!$B$4+Inputs!$B$3*Inputs!$B$5+Inputs!$B$6)*Inputs!$B$7*IF(B3=1,Inputs!$B$9,Inputs!$B$8)*(1+Inputs!$B$10)^(B3-1)) -> 0 | D3: =IF(B3<1,Inputs!$B$32,SUM(Inputs!$B$33,Inputs!$B$34,Inputs!$B$35,Inputs!$B$36,Inputs!$B$37,Inputs!$B$38,Inputs!$B$39)*(1+Inputs!$B$11)^(B3-1)) -> 25000 | E3: =C3*Inputs!$B$40 -> 0 | F3: =C3-D3-E3 -> -25000 | G3: =IF(B3<1,0,Inputs!$B$2*Inputs!$B$41*(1+Inputs!$B$11)^(B3-1)) -> 0 | H3: =L2 -> 5305800 | I3: =H3*Inputs!$B$30 -> 238761 | J3: =IF(B3<1,0,MIN(H3,MAX(0,-PMT(Inputs!$B$30,Inputs!$B$31,Budget!B16)-I3))) -> 0 | K3: =I3+J3 -> 238761 | L3: =H3-J3 -> 5305800 | M3: =IF(A3=21,((C3/IF(B3=1,Inputs!$B$9,Inputs!$B$8)*Inputs!$B$8*(1+Inputs!$B$10)*(1-Inputs!$B$40)-D3*(1+Inputs!$B$11))/Inputs!$B$14*(1-Inputs!$B$15),0) -> 0 | N3: =F3-G3+M3 -> -25000 | O3: =N3-K3-IF(A3=21,L3,0) -> -263761 | P3: =IF(B3<1,"Construction",(F3-G3)/K3) -> Construction | Q3: =Q2+N3 -> -10636600 | R3: =N3/(1+Inputs!$B$12)^A3 -> -23364.486 | S3: =S2+R3 -> -10634964 | T3: =SUM(O$2:O3) -> -5569561
A4: 2 | B4: =A4-1 -> 1 | C4: =IF(B4<1,0,Inputs!$B$2*((1-Inputs!$B$3)*Inputs!$B$4+Inputs!$B$3*Inputs!$B$5+Inputs!$B$6)*Inputs!$B$7*IF(B4=1,Inputs!$B$9,Inputs!$B$8)*(1+Inputs!$B$10)^(B4-1)) -> 660960 | D4: =IF(B4<1,Inputs!$B$32,SUM(Inputs!$B$33,Inputs!$B$34,Inputs!$B$35,Inputs!$B$36,Inputs!$B$37,Inputs!$B$38,Inputs!$B$39)*(1+Inputs!$B$11)^(B4-1)) -> 228000 | E4: =C4*Inputs!$B$40 -> 26438.4 | F4: =C4-D4-E4 -> 406521.6 | G4: =IF(B4<1,0,Inputs!$B$2*Inputs!$B$41*(1+Inputs!$B$11)^(B4-1)) -> 20000 | H4: =L3 -> 5305800 | I4: =H4*Inputs!$B$30 -> 238761 | J4: =IF(B4<1,0,MIN(H4,MAX(0,-PMT(Inputs!$B$30,Inputs!$B$31,Budget!B16)-I4))) -> 119056.99 | K4: =I4+J4 -> 357817.99 | L4: =H4-J4 -> 5186743 | M4: =IF(A4=21,((C4/IF(B4=1,Inputs!$B$9,Inputs!$B$8)*Inputs!$B$8*(1+Inputs!$B$10)*(1-Inputs!$B$40)-D4*(1+Inputs!$B$11))/Inputs!$B$14*(1-Inputs!$B$15),0) -> 0 | N4: =F4-G4+M4 -> 386521.6 | O4: =N4-K4-IF(A4=21,L4,0) -> 28703.605 | P4: =IF(B4<1,"Construction",(F4-G4)/K4) -> 1.0802185 | Q4: =Q3+N4 -> -10250078 | R4: =N4/(1+Inputs!$B$12)^A4 -> 337602.93 | S4: =S3+R4 -> -10297362 | T4: =SUM(O$2:O4) -> -5540857.4
A5: 3 | B5: =A5-1 -> 2 | C5: =IF(B5<1,0,Inputs!$B$2*((1-Inputs!$B$3)*Inputs!$B$4+Inputs!$B$3*Inputs!$B$5+Inputs!$B$6)*Inputs!$B$7*IF(B5=1,Inputs!$B$9,Inputs!$B$8)*(1+Inputs!$B$10)^(B5-1)) -> 753494.4 | D5: =IF(B5<1,Inputs!$B$32,SUM(Inputs!$B$33,Inputs!$B$34,Inputs!$B$35,Inputs!$B$36,Inputs!$B$37,Inputs!$B$38,Inputs!$B$39)*(1+Inputs!$B$11)^(B5-1)) -> 233700 | E5: =C5*Inputs!$B$40 -> 30139.776 | F5: =C5-D5-E5 -> 489654.62 | G5: =IF(B5<1,0,Inputs!$B$2*Inputs!$B$41*(1+Inputs!$B$11)^(B5-1)) -> 20500 | H5: =L4 -> 5186743 | I5: =H5*Inputs!$B$30 -> 233403.44 | J5: =IF(B5<1,0,MIN(H5,MAX(0,-PMT(Inputs!$B$30,Inputs!$B$31,Budget!B16)-I5))) -> 124414.56 | K5: =I5+J5 -> 357817.99 | L5: =H5-J5 -> 5062328.4 | M5: =IF(A5=21,((C5/IF(B5=1,Inputs!$B$9,Inputs!$B$8)*Inputs!$B$8*(1+Inputs!$B$10)*(1-Inputs!$B$40)-D5*(1+Inputs!$B$11))/Inputs!$B$14*(1-Inputs!$B$15),0) -> 0 | N5: =F5-G5+M5 -> 469154.62 | O5: =N5-K5-IF(A5=21,L5,0) -> 111336.63 | P5: =IF(B5<1,"Construction",(F5-G5)/K5) -> 1.3111544 | Q5: =Q4+N5 -> -9780923.8 | R5: =N5/(1+Inputs!$B$12)^A5 -> 382969.92 | S5: =S4+R5 -> -9914391.6 | T5: =SUM(O$2:O5) -> -5429520.8
A6: 4 | B6: =A6-1 -> 3 | C6: =IF(B6<1,0,Inputs!$B$2*((1-Inputs!$B$3)*Inputs!$B$4+Inputs!$B$3*Inputs!$B$5+Inputs!$B$6)*Inputs!$B$7*IF(B6=1,Inputs!$B$9,Inputs!$B$8)*(1+Inputs!$B$10)^(B6-1)) -> 768564.29 | D6: =IF(B6<1,Inputs!$B$32,SUM(Inputs!$B$33,Inputs!$B$34,Inputs!$B$35,Inputs!$B$36,Inputs!$B$37,Inputs!$B$38,Inputs!$B$39)*(1+Inputs!$B$11)^(B6-1)) -> 239542.5 | E6: =C6*Inputs!$B$40 -> 30742.572 | F6: =C6-D6-E6 -> 498279.22 | G6: =IF(B6<1,0,Inputs!$B$2*Inputs!$B$41*(1+Inputs!$B$11)^(B6-1)) -> 21012.5 | H6: =L5 -> 5062328.4 | I6: =H6*Inputs!$B$30 -> 227804.78 | J6: =IF(B6<1,0,MIN(H6,MAX(0,-PMT(Inputs!$B$30,Inputs!$B$31,Budget!B16)-I6))) -> 130013.21 | K6: =I6+J6 -> 357817.99 | L6: =H6-J6 -> 4932315.2 | M6: =IF(A6=21,((C6/IF(B6=1,Inputs!$B$9,Inputs!$B$8)*Inputs!$B$8*(1+Inputs!$B$10)*(1-Inputs!$B$40)-D6*(1+Inputs!$B$11))/Inputs!$B$14*(1-Inputs!$B$15),0) -> 0 | N6: =F6-G6+M6 -> 477266.72 | O6: =N6-K6-IF(A6=21,L6,0) -> 119448.72 | P6: =IF(B6<1,"Construction",(F6-G6)/K6) -> 1.3338254 | Q6: =Q5+N6 -> -9303657.1 | R6: =N6/(1+Inputs!$B$12)^A6 -> 364104.49 | S6: =S5+R6 -> -9550287.1 | T6: =SUM(O$2:O6) -> -5310072
A7: 5 | B7: =A7-1 -> 4 | C7: =IF(B7<1,0,Inputs!$B$2*((1-Inputs!$B$3)*Inputs!$B$4+Inputs!$B$3*Inputs!$B$5+Inputs!$B$6)*Inputs!$B$7*IF(B7=1,Inputs!$B$9,Inputs!$B$8)*(1+Inputs!$B$10)^(B7-1)) -> 783935.57 | D7: =IF(B7<1,Inputs!$B$32,SUM(Inputs!$B$33,Inputs!$B$34,Inputs!$B$35,Inputs!$B$36,Inputs!$B$37,Inputs!$B$38,Inputs!$B$39)*(1+Inputs!$B$11)^(B7-1)) -> 245531.06 | E7: =C7*Inputs!$B$40 -> 31357.423 | F7: =C7-D7-E7 -> 507047.09 | G7: =IF(B7<1,0,Inputs!$B$2*Inputs!$B$41*(1+Inputs!$B$11)^(B7-1)) -> 21537.812 | H7: =L6 -> 4932315.2 | I7: =H7*Inputs!$B$30 -> 221954.19 | J7: =IF(B7<1,0,MIN(H7,MAX(0,-PMT(Inputs!$B$30,Inputs!$B$31,Budget!B16)-I7))) -> 135863.81 | K7: =I7+J7 -> 357817.99 | L7: =H7-J7 -> 4796451.4 | M7: =IF(A7=21,((C7/IF(B7=1,Inputs!$B$9,Inputs!$B$8)*Inputs!$B$8*(1+Inputs!$B$10)*(1-Inputs!$B$40)-D7*(1+Inputs!$B$11))/Inputs!$B$14*(1-Inputs!$B$15),0) -> 0 | N7: =F7-G7+M7 -> 485509.28 | O7: =N7-K7-IF(A7=21,L7,0) -> 127691.28 | P7: =IF(B7<1,"Construction",(F7-G7)/K7) -> 1.356861 | Q7: =Q6+N7 -> -8818147.8 | R7: =N7/(1+Inputs!$B$12)^A7 -> 346161.4 | S7: =S6+R7 -> -9204125.7 | T7: =SUM(O$2:O7) -> -5182380.8
A8: 6 | B8: =A8-1 -> 5 | C8: =IF(B8<1,0,Inputs!$B$2*((1-Inputs!$B$3)*Inputs!$B$4+Inputs!$B$3*Inputs!$B$5+Inputs!$B$6)*Inputs!$B$7*IF(B8=1,Inputs!$B$9,Inputs!$B$8)*(1+Inputs!$B$10)^(B8-1)) -> 799614.29 | D8: =IF(B8<1,Inputs!$B$32,SUM(Inputs!$B$33,Inputs!$B$34,Inputs!$B$35,Inputs!$B$36,Inputs!$B$37,Inputs!$B$38,Inputs!$B$39)*(1+Inputs!$B$11)^(B8-1)) -> 251669.34 | E8: =C8*Inputs!$B$40 -> 31984.571 | F8: =C8-D8-E8 -> 515960.37 | G8: =IF(B8<1,0,Inputs!$B$2*Inputs!$B$41*(1+Inputs!$B$11)^(B8-1)) -> 22076.258 | H8: =L7 -> 4796451.4 | I8: =H8*Inputs!$B$30 -> 215840.31 | J8: =IF(B8<1,0,MIN(H8,MAX(0,-PMT(Inputs!$B$30,Inputs!$B$31,Budget!B16)-I8))) -> 141977.68 | K8: =I8+J8 -> 357817.99 | L8: =H8-J8 -> 4654473.7 | M8: =IF(A8=21,((C8/IF(B8=1,Inputs!$B$9,Inputs!$B$8)*Inputs!$B$8*(1+Inputs!$B$10)*(1-Inputs!$B$40)-D8*(1+Inputs!$B$11))/Inputs!$B$14*(1-Inputs!$B$15),0) -> 0 | N8: =F8-G8+M8 -> 493884.12 | O8: =N8-K8-IF(A8=21,L8,0) -> 136066.12 | P8: =IF(B8<1,"Construction",(F8-G8)/K8) -> 1.3802663 | Q8: =Q7+N8 -> -8324263.7 | R8: =N8/(1+Inputs!$B$12)^A8 -> 329095.84 | S8: =S7+R8 -> -8875029.9 | T8: =SUM(O$2:O8) -> -5046314.6
A9: 7 | B9: =A9-1 -> 6 | C9: =IF(B9<1,0,Inputs!$B$2*((1-Inputs!$B$3)*Inputs!$B$4+Inputs!$B$3*Inputs!$B$5+Inputs!$B$6)*Inputs!$B$7*IF(B9=1,Inputs!$B$9,Inputs!$B$8)*(1+Inputs!$B$10)^(B9-1)) -> 815606.57 | D9: =IF(B9<1,Inputs!$B$32,SUM(Inputs!$B$33,Inputs!$B$34,Inputs!$B$35,Inputs!$B$36,Inputs!$B$37,Inputs!$B$38,Inputs!$B$39)*(1+Inputs!$B$11)^(B9-1)) -> 257961.07 | E9: =C9*Inputs!$B$40 -> 32624.263 | F9: =C9-D9-E9 -> 525021.24 | G9: =IF(B9<1,0,Inputs!$B$2*Inputs!$B$41*(1+Inputs!$B$11)^(B9-1)) -> 22628.164 | H9: =L8 -> 4654473.7 | I9: =H9*Inputs!$B$30 -> 209451.32 | J9: =IF(B9<1,0,MIN(H9,MAX(0,-PMT(Inputs!$B$30,Inputs!$B$31,Budget!B16)-I9))) -> 148366.68 | K9: =I9+J9 -> 357817.99 | L9: =H9-J9 -> 4506107.1 | M9: =IF(A9=21,((C9/IF(B9=1,Inputs!$B$9,Inputs!$B$8)*Inputs!$B$8*(1+Inputs!$B$10)*(1-Inputs!$B$40)-D9*(1+Inputs!$B$11))/Inputs!$B$14*(1-Inputs!$B$15),0) -> 0 | N9: =F9-G9+M9 -> 502393.07 | O9: =N9-K9-IF(A9=21,L9,0) -> 144575.08 | P9: =IF(B9<1,"Construction",(F9-G9)/K9) -> 1.4040464 | Q9: =Q8+N9 -> -7821870.6 | R9: =N9/(1+Inputs!$B$12)^A9 -> 312865.16 | S9: =S8+R9 -> -8562164.7 | T9: =SUM(O$2:O9) -> -4901739.6
A10: 8 | B10: =A10-1 -> 7 | C10: =IF(B10<1,0,Inputs!$B$2*((1-Inputs!$B$3)*Inputs!$B$4+Inputs!$B$3*Inputs!$B$5+Inputs!$B$6)*Inputs!$B$7*IF(B10=1,Inputs!$B$9,Inputs!$B$8)*(1+Inputs!$B$10)^(B10-1)) -> 831918.7 | D10: =IF(B10<1,Inputs!$B$32,SUM(Inputs!$B$33,Inputs!$B$34,Inputs!$B$35,Inputs!$B$36,Inputs!$B$37,Inputs!$B$38,Inputs!$B$39)*(1+Inputs!$B$11)^(B10-1)) -> 264410.1 | E10: =C10*Inputs!$B$40 -> 33276.748 | F10: =C10-D10-E10 -> 534231.85 | G10: =IF(B10<1,0,Inputs!$B$2*Inputs!$B$41*(1+Inputs!$B$11)^(B10-1)) -> 23193.868 | H10: =L9 -> 4506107.1 | I10: =H10*Inputs!$B$30 -> 202774.82 | J10: =IF(B10<1,0,MIN(H10,MAX(0,-PMT(Inputs!$B$30,Inputs!$B$31,Budget!B16)-I10))) -> 155043.18 | K10: =I10+J10 -> 357817.99 | L10: =H10-J10 -> 4351063.9 | M10: =IF(A10=21,((C10/IF(B10=1,Inputs!$B$9,Inputs!$B$8)*Inputs!$B$8*(1+Inputs!$B$10)*(1-Inputs!$B$40)-D10*(1+Inputs!$B$11))/Inputs!$B$14*(1-Inputs!$B$15),0) -> 0 | N10: =F10-G10+M10 -> 511037.99 | O10: =N10-K10-IF(A10=21,L10,0) -> 153219.99 | P10: =IF(B10<1,"Construction",(F10-G10)/K10) -> 1.4282065 | Q10: =Q9+N10 -> -7310832.6 | R10: =N10/(1+Inputs!$B$12)^A10 -> 297428.76 | S10: =S9+R10 -> -8264736 | T10: =SUM(O$2:O10) -> -4748519.6
A11: 9 | B11: =A11-1 -> 8 | C11: =IF(B11<1,0,Inputs!$B$2*((1-Inputs!$B$3)*Inputs!$B$4+Inputs!$B$3*Inputs!$B$5+Inputs!$B$6)*Inputs!$B$7*IF(B11=1,Inputs!$B$9,Inputs!$B$8)*(1+Inputs!$B$10)^(B11-1)) -> 848557.08 | D11: =IF(B11<1,Inputs!$B$32,SUM(Inputs!$B$33,Inputs!$B$34,Inputs!$B$35,Inputs!$B$36,Inputs!$B$37,Inputs!$B$38,Inputs!$B$39)*(1+Inputs!$B$11)^(B11-1)) -> 271020.35 | E11: =C11*Inputs!$B$40 -> 33942.283 | F11: =C11-D11-E11 -> 543594.44 | G11: =IF(B11<1,0,Inputs!$B$2*Inputs!$B$41*(1+Inputs!$B$11)^(B11-1)) -> 23773.715 | H11: =L10 -> 4351063.9 | I11: =H11*Inputs!$B$30 -> 195797.87 | J11: =IF(B11<1,0,MIN(H11,MAX(0,-PMT(Inputs!$B$30,Inputs!$B$31,Budget!B16)-I11))) -> 162020.12 | K11: =I11+J11 -> 357817.99 | L11: =H11-J11 -> 4189043.8 | M11: =IF(A11=21,((C11/IF(B11=1,Inputs!$B$9,Inputs!$B$8)*Inputs!$B$8*(1+Inputs!$B$10)*(1-Inputs!$B$40)-D11*(1+Inputs!$B$11))/Inputs!$B$14*(1-Inputs!$B$15),0) -> 0 | N11: =F11-G11+M11 -> 519820.73 | O11: =N11-K11-IF(A11=21,L11,0) -> 162002.73 | P11: =IF(B11<1,"Construction",(F11-G11)/K11) -> 1.4527518 | Q11: =Q10+N11 -> -6791011.9 | R11: =N11/(1+Inputs!$B$12)^A11 -> 282748.03 | S11: =S10+R11 -> -7981987.9 | T11: =SUM(O$2:O11) -> -4586516.8
A12: 10 | B12: =A12-1 -> 9 | C12: =IF(B12<1,0,Inputs!$B$2*((1-Inputs!$B$3)*Inputs!$B$4+Inputs!$B$3*Inputs!$B$5+Inputs!$B$6)*Inputs!$B$7*IF(B12=1,Inputs!$B$9,Inputs!$B$8)*(1+Inputs!$B$10)^(B12-1)) -> 865528.22 | D12: =IF(B12<1,Inputs!$B$32,SUM(Inputs!$B$33,Inputs!$B$34,Inputs!$B$35,Inputs!$B$36,Inputs!$B$37,Inputs!$B$38,Inputs!$B$39)*(1+Inputs!$B$11)^(B12-1)) -> 277795.86 | E12: =C12*Inputs!$B$40 -> 34621.129 | F12: =C12-D12-E12 -> 553111.23 | G12: =IF(B12<1,0,Inputs!$B$2*Inputs!$B$41*(1+Inputs!$B$11)^(B12-1)) -> 24368.058 | H12: =L11 -> 4189043.8 | I12: =H12*Inputs!$B$30 -> 188506.97 | J12: =IF(B12<1,0,MIN(H12,MAX(0,-PMT(Inputs!$B$30,Inputs!$B$31,Budget!B16)-I12))) -> 169311.03 | K12: =I12+J12 -> 357817.99 | L12: =H12-J12 -> 4019732.7 | M12: =IF(A12=21,((C12/IF(B12=1,Inputs!$B$9,Inputs!$B$8)*Inputs!$B$8*(1+Inputs!$B$10)*(1-Inputs!$B$40)-D12*(1+Inputs!$B$11))/Inputs!$B$14*(1-Inputs!$B$15),0) -> 0 | N12: =F12-G12+M12 -> 528743.17 | O12: =N12-K12-IF(A12=21,L12,0) -> 170925.18 | P12: =IF(B12<1,"Construction",(F12-G12)/K12) -> 1.4776875 | Q12: =Q11+N12 -> -6262268.7 | R12: =N12/(1+Inputs!$B$12)^A12 -> 268786.22 | S12: =S11+R12 -> -7713201.7 | T12: =SUM(O$2:O12) -> -4415591.7
A13: 11 | B13: =A13-1 -> 10 | C13: =IF(B13<1,0,Inputs!$B$2*((1-Inputs!$B$3)*Inputs!$B$4+Inputs!$B$3*Inputs!$B$5+Inputs!$B$6)*Inputs!$B$7*IF(B13=1,Inputs!$B$9,Inputs!$B$8)*(1+Inputs!$B$10)^(B13-1)) -> 882838.78 | D13: =IF(B13<1,Inputs!$B$32,SUM(Inputs!$B$33,Inputs!$B$34,Inputs!$B$35,Inputs!$B$36,Inputs!$B$37,Inputs!$B$38,Inputs!$B$39)*(1+Inputs!$B$11)^(B13-1)) -> 284740.76 | E13: =C13*Inputs!$B$40 -> 35313.551 | F13: =C13-D13-E13 -> 562784.47 | G13: =IF(B13<1,0,Inputs!$B$2*Inputs!$B$41*(1+Inputs!$B$11)^(B13-1)) -> 24977.259 | H13: =L12 -> 4019732.7 | I13: =H13*Inputs!$B$30 -> 180887.97 | J13: =IF(B13<1,0,MIN(H13,MAX(0,-PMT(Inputs!$B$30,Inputs!$B$31,Budget!B16)-I13))) -> 176930.02 | K13: =I13+J13 -> 357817.99 | L13: =H13-J13 -> 3842802.7 | M13: =IF(A13=21,((C13/IF(B13=1,Inputs!$B$9,Inputs!$B$8)*Inputs!$B$8*(1+Inputs!$B$10)*(1-Inputs!$B$40)-D13*(1+Inputs!$B$11))/Inputs!$B$14*(1-Inputs!$B$15),0) -> 0 | N13: =F13-G13+M13 -> 537807.21 | O13: =N13-K13-IF(A13=21,L13,0) -> 179989.22 | P13: =IF(B13<1,"Construction",(F13-G13)/K13) -> 1.5030189 | Q13: =Q12+N13 -> -5724461.5 | R13: =N13/(1+Inputs!$B$12)^A13 -> 255508.33 | S13: =S12+R13 -> -7457693.4 | T13: =SUM(O$2:O13) -> -4235602.4
A14: 12 | B14: =A14-1 -> 11 | C14: =IF(B14<1,0,Inputs!$B$2*((1-Inputs!$B$3)*Inputs!$B$4+Inputs!$B$3*Inputs!$B$5+Inputs!$B$6)*Inputs!$B$7*IF(B14=1,Inputs!$B$9,Inputs!$B$8)*(1+Inputs!$B$10)^(B14-1)) -> 900495.56 | D14: =IF(B14<1,Inputs!$B$32,SUM(Inputs!$B$33,Inputs!$B$34,Inputs!$B$35,Inputs!$B$36,Inputs!$B$37,Inputs!$B$38,Inputs!$B$39)*(1+Inputs!$B$11)^(B14-1)) -> 291859.28 | E14: =C14*Inputs!$B$40 -> 36019.822 | F14: =C14-D14-E14 -> 572616.46 | G14: =IF(B14<1,0,Inputs!$B$2*Inputs!$B$41*(1+Inputs!$B$11)^(B14-1)) -> 25601.691 | H14: =L13 -> 3842802.7 | I14: =H14*Inputs!$B$30 -> 172926.12 | J14: =IF(B14<1,0,MIN(H14,MAX(0,-PMT(Inputs!$B$30,Inputs!$B$31,Budget!B16)-I14))) -> 184891.87 | K14: =I14+J14 -> 357817.99 | L14: =H14-J14 -> 3657910.8 | M14: =IF(A14=21,((C14/IF(B14=1,Inputs!$B$9,Inputs!$B$8)*Inputs!$B$8*(1+Inputs!$B$10)*(1-Inputs!$B$40)-D14*(1+Inputs!$B$11))/Inputs!$B$14*(1-Inputs!$B$15),0) -> 0 | N14: =F14-G14+M14 -> 547014.77 | O14: =N14-K14-IF(A14=21,L14,0) -> 189196.77 | P14: =IF(B14<1,"Construction",(F14-G14)/K14) -> 1.5287514 | Q14: =Q13+N14 -> -5177446.7 | R14: =N14/(1+Inputs!$B$12)^A14 -> 242881.1 | S14: =S13+R14 -> -7214812.3 | T14: =SUM(O$2:O14) -> -4046405.7
A15: 13 | B15: =A15-1 -> 12 | C15: =IF(B15<1,0,Inputs!$B$2*((1-Inputs!$B$3)*Inputs!$B$4+Inputs!$B$3*Inputs!$B$5+Inputs!$B$6)*Inputs!$B$7*IF(B15=1,Inputs!$B$9,Inputs!$B$8)*(1+Inputs!$B$10)^(B15-1)) -> 918505.47 | D15: =IF(B15<1,Inputs!$B$32,SUM(Inputs!$B$33,Inputs!$B$34,Inputs!$B$35,Inputs!$B$36,Inputs!$B$37,Inputs!$B$38,Inputs!$B$39)*(1+Inputs!$B$11)^(B15-1)) -> 299155.76 | E15: =C15*Inputs!$B$40 -> 36740.219 | F15: =C15-D15-E15 -> 582609.49 | G15: =IF(B15<1,0,Inputs!$B$2*Inputs!$B$41*(1+Inputs!$B$11)^(B15-1)) -> 26241.733 | H15: =L14 -> 3657910.8 | I15: =H15*Inputs!$B$30 -> 164605.99 | J15: =IF(B15<1,0,MIN(H15,MAX(0,-PMT(Inputs!$B$30,Inputs!$B$31,Budget!B16)-I15))) -> 193212.01 | K15: =I15+J15 -> 357817.99 | L15: =H15-J15 -> 3464698.8 | M15: =IF(A15=21,((C15/IF(B15=1,Inputs!$B$9,Inputs!$B$8)*Inputs!$B$8*(1+Inputs!$B$10)*(1-Inputs!$B$40)-D15*(1+Inputs!$B$11))/Inputs!$B$14*(1-Inputs!$B$15),0) -> 0 | N15: =F15-G15+M15 -> 556367.76 | O15: =N15-K15-IF(A15=21,L15,0) -> 198549.76 | P15: =IF(B15<1,"Construction",(F15-G15)/K15) -> 1.5548904 | Q15: =Q14+N15 -> -4621079 | R15: =N15/(1+Inputs!$B$12)^A15 -> 230872.84 | S15: =S14+R15 -> -6983939.5 | T15: =SUM(O$2:O15) -> -3847855.9
A16: 14 | B16: =A16-1 -> 13 | C16: =IF(B16<1,0,Inputs!$B$2*((1-Inputs!$B$3)*Inputs!$B$4+Inputs!$B$3*Inputs!$B$5+Inputs!$B$6)*Inputs!$B$7*IF(B16=1,Inputs!$B$9,Inputs!$B$8)*(1+Inputs!$B$10)^(B16-1)) -> 936875.58 | D16: =IF(B16<1,Inputs!$B$32,SUM(Inputs!$B$33,Inputs!$B$34,Inputs!$B$35,Inputs!$B$36,Inputs!$B$37,Inputs!$B$38,Inputs!$B$39)*(1+Inputs!$B$11)^(B16-1)) -> 306634.65 | E16: =C16*Inputs!$B$40 -> 37475.023 | F16: =C16-D16-E16 -> 592765.9 | G16: =IF(B16<1,0,Inputs!$B$2*Inputs!$B$41*(1+Inputs!$B$11)^(B16-1)) -> 26897.776 | H16: =L15 -> 3464698.8 | I16: =H16*Inputs!$B$30 -> 155911.45 | J16: =IF(B16<1,0,MIN(H16,MAX(0,-PMT(Inputs!$B$30,Inputs!$B$31,Budget!B16)-I16))) -> 201906.55 | K16: =I16+J16 -> 357817.99 | L16: =H16-J16 -> 3262792.3 | M16: =IF(A16=21,((C16/IF(B16=1,Inputs!$B$9,Inputs!$B$8)*Inputs!$B$8*(1+Inputs!$B$10)*(1-Inputs!$B$40)-D16*(1+Inputs!$B$11))/Inputs!$B$14*(1-Inputs!$B$15),0) -> 0 | N16: =F16-G16+M16 -> 565868.13 | O16: =N16-K16-IF(A16=21,L16,0) -> 208050.13 | P16: =IF(B16<1,"Construction",(F16-G16)/K16) -> 1.5814412 | Q16: =Q15+N16 -> -4055210.8 | R16: =N16/(1+Inputs!$B$12)^A16 -> 219453.42 | S16: =S15+R16 -> -6764486 | T16: =SUM(O$2:O16) -> -3639805.8
A17: 15 | B17: =A17-1 -> 14 | C17: =IF(B17<1,0,Inputs!$B$2*((1-Inputs!$B$3)*Inputs!$B$4+Inputs!$B$3*Inputs!$B$5+Inputs!$B$6)*Inputs!$B$7*IF(B17=1,Inputs!$B$9,Inputs!$B$8)*(1+Inputs!$B$10)^(B17-1)) -> 955613.09 | D17: =IF(B17<1,Inputs!$B$32,SUM(Inputs!$B$33,Inputs!$B$34,Inputs!$B$35,Inputs!$B$36,Inputs!$B$37,Inputs!$B$38,Inputs!$B$39)*(1+Inputs!$B$11)^(B17-1)) -> 314300.52 | E17: =C17*Inputs!$B$40 -> 38224.524 | F17: =C17-D17-E17 -> 603088.05 | G17: =IF(B17<1,0,Inputs!$B$2*Inputs!$B$41*(1+Inputs!$B$11)^(B17-1)) -> 27570.221 | H17: =L16 -> 3262792.3 | I17: =H17*Inputs!$B$30 -> 146825.65 | J17: =IF(B17<1,0,MIN(H17,MAX(0,-PMT(Inputs!$B$30,Inputs!$B$31,Budget!B16)-I17))) -> 210992.34 | K17: =I17+J17 -> 357817.99 | L17: =H17-J17 -> 3051800 | M17: =IF(A17=21,((C17/IF(B17=1,Inputs!$B$9,Inputs!$B$8)*Inputs!$B$8*(1+Inputs!$B$10)*(1-Inputs!$B$40)-D17*(1+Inputs!$B$11))/Inputs!$B$14*(1-Inputs!$B$15),0) -> 0 | N17: =F17-G17+M17 -> 575517.83 | O17: =N17-K17-IF(A17=21,L17,0) -> 217699.83 | P17: =IF(B17<1,"Construction",(F17-G17)/K17) -> 1.6084094 | Q17: =Q16+N17 -> -3479693 | R17: =N17/(1+Inputs!$B$12)^A17 -> 208594.15 | S17: =S16+R17 -> -6555891.9 | T17: =SUM(O$2:O17) -> -3422105.9
A18: 16 | B18: =A18-1 -> 15 | C18: =IF(B18<1,0,Inputs!$B$2*((1-Inputs!$B$3)*Inputs!$B$4+Inputs!$B$3*Inputs!$B$5+Inputs!$B$6)*Inputs!$B$7*IF(B18=1,Inputs!$B$9,Inputs!$B$8)*(1+Inputs!$B$10)^(B18-1)) -> 974725.35 | D18: =IF(B18<1,Inputs!$B$32,SUM(Inputs!$B$33,Inputs!$B$34,Inputs!$B$35,Inputs!$B$36,Inputs!$B$37,Inputs!$B$38,Inputs!$B$39)*(1+Inputs!$B$11)^(B18-1)) -> 322158.03 | E18: =C18*Inputs!$B$40 -> 38989.014 | F18: =C18-D18-E18 -> 613578.31 | G18: =IF(B18<1,0,Inputs!$B$2*Inputs!$B$41*(1+Inputs!$B$11)^(B18-1)) -> 28259.476 | H18: =L17 -> 3051800 | I18: =H18*Inputs!$B$30 -> 137331 | J18: =IF(B18<1,0,MIN(H18,MAX(0,-PMT(Inputs!$B$30,Inputs!$B$31,Budget!B16)-I18))) -> 220487 | K18: =I18+J18 -> 357817.99 | L18: =H18-J18 -> 2831313 | M18: =IF(A18=21,((C18/IF(B18=1,Inputs!$B$9,Inputs!$B$8)*Inputs!$B$8*(1+Inputs!$B$10)*(1-Inputs!$B$40)-D18*(1+Inputs!$B$11))/Inputs!$B$14*(1-Inputs!$B$15),0) -> 0 | N18: =F18-G18+M18 -> 585318.83 | O18: =N18-K18-IF(A18=21,L18,0) -> 227500.84 | P18: =IF(B18<1,"Construction",(F18-G18)/K18) -> 1.6358004 | Q18: =Q17+N18 -> -2894374.2 | R18: =N18/(1+Inputs!$B$12)^A18 -> 198267.74 | S18: =S17+R18 -> -6357624.2 | T18: =SUM(O$2:O18) -> -3194605.1
A19: 17 | B19: =A19-1 -> 16 | C19: =IF(B19<1,0,Inputs!$B$2*((1-Inputs!$B$3)*Inputs!$B$4+Inputs!$B$3*Inputs!$B$5+Inputs!$B$6)*Inputs!$B$7*IF(B19=1,Inputs!$B$9,Inputs!$B$8)*(1+Inputs!$B$10)^(B19-1)) -> 994219.86 | D19: =IF(B19<1,Inputs!$B$32,SUM(Inputs!$B$33,Inputs!$B$34,Inputs!$B$35,Inputs!$B$36,Inputs!$B$37,Inputs!$B$38,Inputs!$B$39)*(1+Inputs!$B$11)^(B19-1)) -> 330211.98 | E19: =C19*Inputs!$B$40 -> 39768.794 | F19: =C19-D19-E19 -> 624239.08 | G19: =IF(B19<1,0,Inputs!$B$2*Inputs!$B$41*(1+Inputs!$B$11)^(B19-1)) -> 28965.963 | H19: =L18 -> 2831313 | I19: =H19*Inputs!$B$30 -> 127409.08 | J19: =IF(B19<1,0,MIN(H19,MAX(0,-PMT(Inputs!$B$30,Inputs!$B$31,Budget!B16)-I19))) -> 230408.91 | K19: =I19+J19 -> 357817.99 | L19: =H19-J19 -> 2600904 | M19: =IF(A19=21,((C19/IF(B19=1,Inputs!$B$9,Inputs!$B$8)*Inputs!$B$8*(1+Inputs!$B$10)*(1-Inputs!$B$40)-D19*(1+Inputs!$B$11))/Inputs!$B$14*(1-Inputs!$B$15),0) -> 0 | N19: =F19-G19+M19 -> 595273.12 | O19: =N19-K19-IF(A19=21,L19,0) -> 237455.12 | P19: =IF(B19<1,"Construction",(F19-G19)/K19) -> 1.6636199 | Q19: =Q18+N19 -> -2299101.1 | R19: =N19/(1+Inputs!$B$12)^A19 -> 188448.22 | S19: =S18+R19 -> -6169175.9 | T19: =SUM(O$2:O19) -> -2957150
A20: 18 | B20: =A20-1 -> 17 | C20: =IF(B20<1,0,Inputs!$B$2*((1-Inputs!$B$3)*Inputs!$B$4+Inputs!$B$3*Inputs!$B$5+Inputs!$B$6)*Inputs!$B$7*IF(B20=1,Inputs!$B$9,Inputs!$B$8)*(1+Inputs!$B$10)^(B20-1)) -> 1014104.3 | D20: =IF(B20<1,Inputs!$B$32,SUM(Inputs!$B$33,Inputs!$B$34,Inputs!$B$35,Inputs!$B$36,Inputs!$B$37,Inputs!$B$38,Inputs!$B$39)*(1+Inputs!$B$11)^(B20-1)) -> 338467.28 | E20: =C20*Inputs!$B$40 -> 40564.17 | F20: =C20-D20-E20 -> 635072.8 | G20: =IF(B20<1,0,Inputs!$B$2*Inputs!$B$41*(1+Inputs!$B$11)^(B20-1)) -> 29690.112 | H20: =L19 -> 2600904 | I20: =H20*Inputs!$B$30 -> 117040.68 | J20: =IF(B20<1,0,MIN(H20,MAX(0,-PMT(Inputs!$B$30,Inputs!$B$31,Budget!B16)-I20))) -> 240777.31 | K20: =I20+J20 -> 357817.99 | L20: =H20-J20 -> 2360126.7 | M20: =IF(A20=21,((C20/IF(B20=1,Inputs!$B$9,Inputs!$B$8)*Inputs!$B$8*(1+Inputs!$B$10)*(1-Inputs!$B$40)-D20*(1+Inputs!$B$11))/Inputs!$B$14*(1-Inputs!$B$15),0) -> 0 | N20: =F20-G20+M20 -> 605382.69 | O20: =N20-K20-IF(A20=21,L20,0) -> 247564.7 | P20: =IF(B20<1,"Construction",(F20-G20)/K20) -> 1.6918732 | Q20: =Q19+N20 -> -1693718.4 | R20: =N20/(1+Inputs!$B$12)^A20 -> 179110.89 | S20: =S19+R20 -> -5990065 | T20: =SUM(O$2:O20) -> -2709585.3
A21: 19 | B21: =A21-1 -> 18 | C21: =IF(B21<1,0,Inputs!$B$2*((1-Inputs!$B$3)*Inputs!$B$4+Inputs!$B$3*Inputs!$B$5+Inputs!$B$6)*Inputs!$B$7*IF(B21=1,Inputs!$B$9,Inputs!$B$8)*(1+Inputs!$B$10)^(B21-1)) -> 1034386.3 | D21: =IF(B21<1,Inputs!$B$32,SUM(Inputs!$B$33,Inputs!$B$34,Inputs!$B$35,Inputs!$B$36,Inputs!$B$37,Inputs!$B$38,Inputs!$B$39)*(1+Inputs!$B$11)^(B21-1)) -> 346928.96 | E21: =C21*Inputs!$B$40 -> 41375.454 | F21: =C21-D21-E21 -> 646081.92 | G21: =IF(B21<1,0,Inputs!$B$2*Inputs!$B$41*(1+Inputs!$B$11)^(B21-1)) -> 30432.365 | H21: =L20 -> 2360126.7 | I21: =H21*Inputs!$B$30 -> 106205.7 | J21: =IF(B21<1,0,MIN(H21,MAX(0,-PMT(Inputs!$B$30,Inputs!$B$31,Budget!B16)-I21))) -> 251612.29 | K21: =I21+J21 -> 357817.99 | L21: =H21-J21 -> 2108514.4 | M21: =IF(A21=21,((C21/IF(B21=1,Inputs!$B$9,Inputs!$B$8)*Inputs!$B$8*(1+Inputs!$B$10)*(1-Inputs!$B$40)-D21*(1+Inputs!$B$11))/Inputs!$B$14*(1-Inputs!$B$15),0) -> 0 | N21: =F21-G21+M21 -> 615649.56 | O21: =N21-K21-IF(A21=21,L21,0) -> 257831.56 | P21: =IF(B21<1,"Construction",(F21-G21)/K21) -> 1.7205662 | Q21: =Q20+N21 -> -1078068.8 | R21: =N21/(1+Inputs!$B$12)^A21 -> 170232.23 | S21: =S20+R21 -> -5819832.8 | T21: =SUM(O$2:O21) -> -2451753.7
A22: 20 | B22: =A22-1 -> 19 | C22: =IF(B22<1,0,Inputs!$B$2*((1-Inputs!$B$3)*Inputs!$B$4+Inputs!$B$3*Inputs!$B$5+Inputs!$B$6)*Inputs!$B$7*IF(B22=1,Inputs!$B$9,Inputs!$B$8)*(1+Inputs!$B$10)^(B22-1)) -> 1055074.1 | D22: =IF(B22<1,Inputs!$B$32,SUM(Inputs!$B$33,Inputs!$B$34,Inputs!$B$35,Inputs!$B$36,Inputs!$B$37,Inputs!$B$38,Inputs!$B$39)*(1+Inputs!$B$11)^(B22-1)) -> 355602.19 | E22: =C22*Inputs!$B$40 -> 42202.963 | F22: =C22-D22-E22 -> 657268.92 | G22: =IF(B22<1,0,Inputs!$B$2*Inputs!$B$41*(1+Inputs!$B$11)^(B22-1)) -> 31193.174 | H22: =L21 -> 2108514.4 | I22: =H22*Inputs!$B$30 -> 94883.15 | J22: =IF(B22<1,0,MIN(H22,MAX(0,-PMT(Inputs!$B$30,Inputs!$B$31,Budget!B16)-I22))) -> 262934.85 | K22: =I22+J22 -> 357817.99 | L22: =H22-J22 -> 1845579.6 | M22: =IF(A22=21,((C22/IF(B22=1,Inputs!$B$9,Inputs!$B$8)*Inputs!$B$8*(1+Inputs!$B$10)*(1-Inputs!$B$40)-D22*(1+Inputs!$B$11))/Inputs!$B$14*(1-Inputs!$B$15),0) -> 0 | N22: =F22-G22+M22 -> 626075.74 | O22: =N22-K22-IF(A22=21,L22,0) -> 268257.75 | P22: =IF(B22<1,"Construction",(F22-G22)/K22) -> 1.7497045 | Q22: =Q21+N22 -> -451993.07 | R22: =N22/(1+Inputs!$B$12)^A22 -> 161789.87 | S22: =S21+R22 -> -5658042.9 | T22: =SUM(O$2:O22) -> -2183496
A23: 21 | B23: =A23-1 -> 20 | C23: =IF(B23<1,0,Inputs!$B$2*((1-Inputs!$B$3)*Inputs!$B$4+Inputs!$B$3*Inputs!$B$5+Inputs!$B$6)*Inputs!$B$7*IF(B23=1,Inputs!$B$9,Inputs!$B$8)*(1+Inputs!$B$10)^(B23-1)) -> 1076175.5 | D23: =IF(B23<1,Inputs!$B$32,SUM(Inputs!$B$33,Inputs!$B$34,Inputs!$B$35,Inputs!$B$36,Inputs!$B$37,Inputs!$B$38,Inputs!$B$39)*(1+Inputs!$B$11)^(B23-1)) -> 364492.24 | E23: =C23*Inputs!$B$40 -> 43047.022 | F23: =C23-D23-E23 -> 668636.29 | G23: =IF(B23<1,0,Inputs!$B$2*Inputs!$B$41*(1+Inputs!$B$11)^(B23-1)) -> 31973.004 | H23: =L22 -> 1845579.6 | I23: =H23*Inputs!$B$30 -> 83051.082 | J23: =IF(B23<1,0,MIN(H23,MAX(0,-PMT(Inputs!$B$30,Inputs!$B$31,Budget!B16)-I23))) -> 274766.91 | K23: =I23+J23 -> 357817.99 | L23: =H23-J23 -> 1570812.7 | M23: =IF(A23=21,((C23/IF(B23=1,Inputs!$B$9,Inputs!$B$8)*Inputs!$B$8*(1+Inputs!$B$10)*(1-Inputs!$B$40)-D23*(1+Inputs!$B$11))/Inputs!$B$14*(1-Inputs!$B$15),0) -> 12119688 | N23: =F23-G23+M23 -> 12756351 | O23: =N23-K23-IF(A23=21,L23,0) -> 10827720 | P23: =IF(B23<1,"Construction",(F23-G23)/K23) -> 1.7792936 | Q23: =Q22+N23 -> 12304358 | R23: =N23/(1+Inputs!$B$12)^A23 -> 3080825.7 | S23: =S22+R23 -> -2577217.3 | T23: =SUM(O$2:O23) -> 8644224.2

Sheet Dashboard
A1: Investment KPI | B1: Base case | C1: Interpretation
A2: Project NPV | B2: =NPV(Inputs!$B$12,'Cash Flow'!N3:N23)+'Cash Flow'!N2 -> -2577217.3 | C2: Net cost incl grant; pre-tax, nominal 7% hurdle.
A3: Project IRR | B3: =IRR('Cash Flow'!N2:N23) -> 0.049594687 | C3: Cash flows include Year 21 sale.
A4: Equity NPV | B4: =NPV(Inputs!$B$13,'Cash Flow'!O3:O23)+'Cash Flow'!O2 -> -2527187.8 | C4: 9% nominal equity hurdle; construction interest and debt payoff included.
A5: Equity IRR | B5: =IRR('Cash Flow'!O2:O23) -> 0.052157867 | C5: Leverage can lower return if debt cost exceeds property return.
A6: Gross development cost | B6: =Budget!B13 -> 10611600 | C6: Includes VAT and contingency; excludes construction-year holding/interest.
A7: Stabilised NOI | B7: ='Cash Flow'!F5 -> 489654.62 | C7: Second operating year; replacement reserve is below NOI.
A8: Stabilised yield on gross cost | B8: ='Cash Flow'!F5/Budget!B13 -> 0.046143336 | C8: Compare with cost of capital and exit yield.
A9: Minimum operating cash DSCR | B9: =MIN('Cash Flow'!P4:P23) -> 1.0802185 | C9: NOI less replacement reserve / debt service; excludes construction.
A10: Simple payback incl sale | B10: =IF(MAX('Cash Flow'!Q2:Q23)<0,"Not reached",MATCH(TRUE,INDEX('Cash Flow'!Q2:Q23>=0,0),0)-2-INDEX('Cash Flow'!Q2:Q23,MATCH(TRUE,INDEX('Cash Flow'!Q2:Q23>=0,0),0)-1)/INDEX('Cash Flow'!N2:N23,MATCH(TRUE,INDEX('Cash Flow'!Q2:Q23>=0,0),0))) -> 20.035433 | C10: Fractional annual cash-flow interpolation; exit-dependent.
A11: Discounted payback incl sale | B11: =IF(MAX('Cash Flow'!S2:S23)<0,"Not reached",MATCH(TRUE,INDEX('Cash Flow'!S2:S23>=0,0),0)-2-INDEX('Cash Flow'!S2:S23,MATCH(TRUE,INDEX('Cash Flow'!S2:S23>=0,0),0)-1)/INDEX('Cash Flow'!R2:R23,MATCH(TRUE,INDEX('Cash Flow'!S2:S23>=0,0),0))) -> Not reached | C11: Uses project discount rate.
A12: Additional upfront grant for NPV=0 | B12: =MAX(0,-B2) -> 2577217.3 | C12: Minimum support at unchanged operation and terminal value; not committed.
A13: Maximum gross cost at project hurdle | B13: =Budget!B13+B2 -> 8034382.7 | C13: Includes confirmed grants; assumes unchanged future cash flow.
A14: Affordable rooms | B14: =Inputs!$B$2*Inputs!$B$3 -> 10 | C14: Same quality, income-targeted allocation.
A15: Standard all-in monthly cost | B15: =Inputs!$B$4+Inputs!$B$6 -> 670 | C15: Bare rent plus services in first operating year.
A16: Affordable all-in monthly cost | B16: =Inputs!$B$5+Inputs!$B$6 -> 450 | C16: Affordability judged on full cost of tenancy.
A17: Annual affordable rent concession | B17: =Inputs!$B$2*Inputs!$B$3*(Inputs!$B$4-Inputs!$B$5)*Inputs!$B$7*Inputs!$B$8 -> 25080 | C17: Foregone gross rent vs all standard rooms at stabilised occupancy.
A18: Peak cumulative equity committed | B18: =MAX(0,-MIN('Cash Flow'!T2:T23)) -> 5569561 | C18: Includes any subsequent operating funding shortfalls.
A19: Operating-only payback | B19: =IF(SUM('Cash Flow'!N2:N23)-SUM('Cash Flow'!M2:M23)<0,"Not reached","See Cash Flow") -> 20.709941 | C19: Excludes sale; do not confuse with exit-inclusive payback.
