Workbook

Sheet Executive Summary
A1: Student housing: investment screening | B1: Illustrative case — 14 October 2026
A2: Metric | B2: Value
A3: Total project cost | B3: ='Sources & Uses'!B10 -> 4686320
A4: Initial equity | B4: ='Sources & Uses'!B13 -> 2766320
A5: Year 1 NOI | B5: ='Operations'!B13 -> 221616
A6: Year 1 cash flow after debt | B6: ='Returns'!C3 -> 80133.066
A7: Equity IRR | B7: ='Returns'!B9 -> 0.054435677
A8: NPV at 9% required return | B8: ='Returns'!B10 -> -692163.3
A9: Year 1 DSCR | B9: ='Returns'!B14 -> 1.711546
A10: Break-even economic occupancy | B10: ='Returns'!B15 -> 0.67676941
A11: Investment view | B11: Do not proceed at illustrative terms: return is below target. Confirm lawful capacity and rent before bidding.
A12: Required property data | B12: Address / commune; price; approved room count and plans; floor areas; EPC; surveys; renovation quotes; utility allocation; historic rents / occupancy; tax bill; lender terms; investor tax structure.
A13: Legal gate | B13: Open: property-specific permit, fire, quality, rent and tax verification. Regional rules checked; compliance not certified.

Sheet Read Me
A1: Student housing investment — VUB/ULB, Brussels
A2: Status | B2: Research-informed screening model; financial inputs remain illustrative.
A3: Instructions | B3: Edit blue cells in Assumptions; formulas recalculate in Excel. All currency EUR.
A4: Investment basis | B4: 40 rooms, 10-year hold; annual debt payments; sale valued on forward Year 11 NOI.
A5: Model scope | B5: Pre-income-tax equity returns; costs and capex gross of nonrecoverable VAT.
A6: Critical limitation | B6: Exact address, planning permission, fire/quality compliance and investment taxes require verification.
A7: Timing | B7: Construction delay reduces Year 1 rent; full debt service and fixed costs apply throughout.
A8: Reserve | B8: Initial funded reserve released on exit; annual replacement reserve treated as spent.
A9: Sensitivity | B9: Equity NPV sensitivity to base rent and exit cap; no price evidence implied.
A10: Decision | B10: Do not commit until property-specific legal, technical and lender diligence is complete.

Sheet Assumptions
A1: Assumption | B1: Value | C1: Unit | D1: Basis / action needed
A2: Rooms | B2: 40 | C2: rooms | D2: Illustrative; confirm lawful room capacity
A3: Purchase price | B3: 3200000 | C3: EUR | D3: Illustrative; obtain appraisal and vendor terms
A4: Registration duty | B4: 0.125 | C4: % | D4: Verified 12.5% ordinary existing-property acquisition duty; no abatement assumed
A5: Other acquisition costs | B5: 0.02 | C5: % of purchase | D5: Notary and acquisition diligence allowance; mortgage costs separately included
A6: Refurbishment per room | B6: 18000 | C6: EUR/room | D6: Illustrative contractor budget; gross including nonrecoverable VAT
A7: Capex contingency | B7: 0.1 | C7: % of refurbishment | D7: Illustrative
A8: Setup & professional costs | B8: 80000 | C8: EUR | D8: Architect, permit and setup allowance, gross
A9: Initial reserve | B9: 100000 | C9: EUR | D9: Funded at closing; released at sale
A10: Monthly rent per room | B10: 650 | C10: EUR | D10: Illustrative base rent; excludes tenant utility reimbursements
A11: Occupancy | B11: 0.95 | C11: % | D11: Economic occupancy; includes voids and rent losses
A12: Paid months per year | B12: 12 | C12: months | D12: Confirm lease terms; test 10 months
A13: Other annual income | B13: 0 | C13: EUR | D13: No assumed ancillary income
... A34: Other loan deed / security costs | B34: 10000 | C34: EUR | D34: Illustrative notary, inscription and security costs; obtain quote

Sheet Sources & Uses
A1: Sources / uses | B1: EUR
A2: Purchase | B2: ='Assumptions'!$B$3 -> 3200000
A3: Registration duty | B3: ='Assumptions'!$B$3*'Assumptions'!$B$4 -> 400000
A4: Other acquisition costs | B4: ='Assumptions'!$B$3*'Assumptions'!$B$5 -> 64000
A5: Refurbishment | B5: ='Assumptions'!$B$2*'Assumptions'!$B$6 -> 720000
A6: Contingency | B6: =B5*'Assumptions'!$B$7 -> 72000
A7: Setup costs | B7: ='Assumptions'!$B$8 -> 80000
A8: Initial reserve | B8: ='Assumptions'!$B$9 -> 100000
A9: Debt fee | B9: =B12*'Assumptions'!$B$26 -> 19200
A10: Total uses | B10: =SUM(B2:B9)+B16 -> 4686320
A12: Debt proceeds | B12: ='Assumptions'!$B$3*'Assumptions'!$B$23 -> 1920000
A13: Equity required | B13: =B10-B12 -> 2766320
A14: Total sources | B14: =SUM(B12:B13) -> 4686320
A15: Funding check | B15: =B14-B10 -> 0
A16: Mortgage taxes & other loan costs | B16: =B12*'Assumptions'!B32*'Assumptions'!B33+'Assumptions'!B34 -> 31120

Sheet Operations
A1: Year | B1: 1 | C1: 2 | D1: 3 | E1: 4 | F1: 5 | G1: 6 | H1: 7 | I1: 8 | J1: 9 | K1: 10 | L1: 11
A2: Potential room rent | B2: ='Assumptions'!$B$2*'Assumptions'!$B$10*'Assumptions'!$B$12*(1+'Assumptions'!$B$14)^(B$1-1) -> 312000 | C2: ='Assumptions'!$B$2*'Assumptions'!$B$10*'Assumptions'!$B$12*(1+'Assumptions'!$B$14)^(C$1-1) -> 318240 | D2: ='Assumptions'!$B$2*'Assumptions'!$B$10*'Assumptions'!$B$12*(1+'Assumptions'!$B$14)^(D$1-1) -> 324604.8 | E2: ='Assumptions'!$B$2*'Assumptions'!$B$10*'Assumptions'!$B$12*(1+'Assumptions'!$B$14)^(E$1-1) -> 331096.9 | F2: ='Assumptions'!$B$2*'Assumptions'!$B$10*'Assumptions'!$B$12*(1+'Assumptions'!$B$14)^(F$1-1) -> 337718.83 | G2: ='Assumptions'!$B$2*'Assumptions'!$B$10*'Assumptions'!$B$12*(1+'Assumptions'!$B$14)^(G$1-1) -> 344473.21 | H2: ='Assumptions'!$B$2*'Assumptions'!$B$10*'Assumptions'!$B$12*(1+'Assumptions'!$B$14)^(H$1-1) -> 351362.67 | I2: ='Assumptions'!$B$2*'Assumptions'!$B$10*'Assumptions'!$B$12*(1+'Assumptions'!$B$14)^(I$1-1) -> 358389.93 | ... L2: ='Assumptions'!$B$2*'Assumptions'!$B$10*'Assumptions'!$B$12*(1+'Assumptions'!$B$14)^(L$1-1) -> 380326.26
A3: Effective room rent | B3: =B2*'Assumptions'!$B$11*(1-'Assumptions'!$B$31/12) -> 296400 | C3: =C2*'Assumptions'!$B$11 -> 302328 | D3: =D2*'Assumptions'!$B$11 -> 308374.56 | E3: =E2*'Assumptions'!$B$11 -> 314542.05 | F3: =F2*'Assumptions'!$B$11 -> 320832.89 | G3: =G2*'Assumptions'!$B$11 -> 327249.55 | H3: =H2*'Assumptions'!$B$11 -> 333794.54 | I3: =I2*'Assumptions'!$B$11 -> 340470.43 | J3: =J2*'Assumptions'!$B$11 -> 347279.84 | ... L3: =L2*'Assumptions'!$B$11 -> 361309.95
A4: Other revenue | B4: ='Assumptions'!$B$13*(1+'Assumptions'!$B$14)^(B$1-1) -> 0 | C4: ='Assumptions'!$B$13*(1+'Assumptions'!$B$14)^(C$1-1) -> 0 | D4: ='Assumptions'!$B$13*(1+'Assumptions'!$B$14)^(D$1-1) -> 0 | E4: ='Assumptions'!$B$13*(1+'Assumptions'!$B$14)^(E$1-1) -> 0 | F4: ='Assumptions'!$B$13*(1+'Assumptions'!$B$14)^(F$1-1) -> 0 | G4: ='Assumptions'!$B$13*(1+'Assumptions'!$B$14)^(G$1-1) -> 0 | H4: ='Assumptions'!$B$13*(1+'Assumptions'!$B$14)^(H$1-1) -> 0 | I4: ='Assumptions'!$B$13*(1+'Assumptions'!$B$14)^(I$1-1) -> 0 | ... L4: ='Assumptions'!$B$13*(1+'Assumptions'!$B$14)^(L$1-1) -> 0
A5: Total revenue | B5: =SUM(B3:B4) -> 296400 | C5: =SUM(C3:C4) -> 302328 | D5: =SUM(D3:D4) -> 308374.56 | E5: =SUM(E3:E4) -> 314542.05 | F5: =SUM(F3:F4) -> 320832.89 | G5: =SUM(G3:G4) -> 327249.55 | H5: =SUM(H3:H4) -> 333794.54 | I5: =SUM(I3:I4) -> 340470.43 | ... L5: =SUM(L3:L4) -> 361309.95
A6: Management | B6: =B5*'Assumptions'!$B$15 -> 17784 | C6: =C5*'Assumptions'!$B$15 -> 18139.68 | D6: =D5*'Assumptions'!$B$15 -> 18502.474 | E6: =E5*'Assumptions'!$B$15 -> 18872.523 | F6: =F5*'Assumptions'!$B$15 -> 19249.974 | G6: =G5*'Assumptions'!$B$15 -> 19634.973 | H6: =H5*'Assumptions'!$B$15 -> 20027.672 | I6: =I5*'Assumptions'!$B$15 -> 20428.226 | ... L6: =L5*'Assumptions'!$B$15 -> 21678.597
A7: Utilities | B7: ='Assumptions'!$B$16*(1+'Assumptions'!$B$21)^(B$1-1) -> 18000 | C7: ='Assumptions'!$B$16*(1+'Assumptions'!$B$21)^(C$1-1) -> 18450 | D7: ='Assumptions'!$B$16*(1+'Assumptions'!$B$21)^(D$1-1) -> 18911.25 | E7: ='Assumptions'!$B$16*(1+'Assumptions'!$B$21)^(E$1-1) -> 19384.031 | F7: ='Assumptions'!$B$16*(1+'Assumptions'!$B$21)^(F$1-1) -> 19868.632 | G7: ='Assumptions'!$B$16*(1+'Assumptions'!$B$21)^(G$1-1) -> 20365.348 | H7: ='Assumptions'!$B$16*(1+'Assumptions'!$B$21)^(H$1-1) -> 20874.482 | I7: ='Assumptions'!$B$16*(1+'Assumptions'!$B$21)^(I$1-1) -> 21396.344 | ... L7: ='Assumptions'!$B$16*(1+'Assumptions'!$B$21)^(L$1-1) -> 23041.522
A8: Maintenance | B8: ='Assumptions'!$B$17*(1+'Assumptions'!$B$21)^(B$1-1) -> 14000 | C8: ='Assumptions'!$B$17*(1+'Assumptions'!$B$21)^(C$1-1) -> 14350 | D8: ='Assumptions'!$B$17*(1+'Assumptions'!$B$21)^(D$1-1) -> 14708.75 | E8: ='Assumptions'!$B$17*(1+'Assumptions'!$B$21)^(E$1-1) -> 15076.469 | F8: ='Assumptions'!$B$17*(1+'Assumptions'!$B$21)^(F$1-1) -> 15453.38 | G8: ='Assumptions'!$B$17*(1+'Assumptions'!$B$21)^(G$1-1) -> 15839.715 | H8: ='Assumptions'!$B$17*(1+'Assumptions'!$B$21)^(H$1-1) -> 16235.708 | I8: ='Assumptions'!$B$17*(1+'Assumptions'!$B$21)^(I$1-1) -> 16641.601 | ... L8: ='Assumptions'!$B$17*(1+'Assumptions'!$B$21)^(L$1-1) -> 17921.184
A9: Insurance | B9: ='Assumptions'!$B$18*(1+'Assumptions'!$B$21)^(B$1-1) -> 6000 | C9: ='Assumptions'!$B$18*(1+'Assumptions'!$B$21)^(C$1-1) -> 6150 | D9: ='Assumptions'!$B$18*(1+'Assumptions'!$B$21)^(D$1-1) -> 6303.75 | E9: ='Assumptions'!$B$18*(1+'Assumptions'!$B$21)^(E$1-1) -> 6461.3437 | F9: ='Assumptions'!$B$18*(1+'Assumptions'!$B$21)^(F$1-1) -> 6622.8773 | G9: ='Assumptions'!$B$18*(1+'Assumptions'!$B$21)^(G$1-1) -> 6788.4493 | H9: ='Assumptions'!$B$18*(1+'Assumptions'!$B$21)^(H$1-1) -> 6958.1605 | I9: ='Assumptions'!$B$18*(1+'Assumptions'!$B$21)^(I$1-1) -> 7132.1145 | ... L9: ='Assumptions'!$B$18*(1+'Assumptions'!$B$21)^(L$1-1) -> 7680.5073
A10: Property tax | B10: ='Assumptions'!$B$19*(1+'Assumptions'!$B$21)^(B$1-1) -> 14000 | C10: ='Assumptions'!$B$19*(1+'Assumptions'!$B$21)^(C$1-1) -> 14350 | D10: ='Assumptions'!$B$19*(1+'Assumptions'!$B$21)^(D$1-1) -> 14708.75 | E10: ='Assumptions'!$B$19*(1+'Assumptions'!$B$21)^(E$1-1) -> 15076.469 | F10: ='Assumptions'!$B$19*(1+'Assumptions'!$B$21)^(F$1-1) -> 15453.38 | G10: ='Assumptions'!$B$19*(1+'Assumptions'!$B$21)^(G$1-1) -> 15839.715 | H10: ='Assumptions'!$B$19*(1+'Assumptions'!$B$21)^(H$1-1) -> 16235.708 | I10: ='Assumptions'!$B$19*(1+'Assumptions'!$B$21)^(I$1-1) -> 16641.601 | ... L10: ='Assumptions'!$B$19*(1+'Assumptions'!$B$21)^(L$1-1) -> 17921.184
A11: Administration | B11: ='Assumptions'!$B$20*(1+'Assumptions'!$B$21)^(B$1-1) -> 5000 | C11: ='Assumptions'!$B$20*(1+'Assumptions'!$B$21)^(C$1-1) -> 5125 | D11: ='Assumptions'!$B$20*(1+'Assumptions'!$B$21)^(D$1-1) -> 5253.125 | E11: ='Assumptions'!$B$20*(1+'Assumptions'!$B$21)^(E$1-1) -> 5384.4531 | F11: ='Assumptions'!$B$20*(1+'Assumptions'!$B$21)^(F$1-1) -> 5519.0645 | G11: ='Assumptions'!$B$20*(1+'Assumptions'!$B$21)^(G$1-1) -> 5657.0411 | H11: ='Assumptions'!$B$20*(1+'Assumptions'!$B$21)^(H$1-1) -> 5798.4671 | I11: ='Assumptions'!$B$20*(1+'Assumptions'!$B$21)^(I$1-1) -> 5943.4288 | ... L11: ='Assumptions'!$B$20*(1+'Assumptions'!$B$21)^(L$1-1) -> 6400.4227
A12: Total operating costs | B12: =SUM(B6:B11) -> 74784 | C12: =SUM(C6:C11) -> 76564.68 | D12: =SUM(D6:D11) -> 78388.099 | E12: =SUM(E6:E11) -> 80255.289 | F12: =SUM(F6:F11) -> 82167.308 | G12: =SUM(G6:G11) -> 84125.241 | H12: =SUM(H6:H11) -> 86130.197 | I12: =SUM(I6:I11) -> 88183.314 | ... L12: =SUM(L6:L11) -> 94643.416
A13: Net operating income (NOI) | B13: =B5-B12 -> 221616 | C13: =C5-C12 -> 225763.32 | D13: =D5-D12 -> 229986.46 | E13: =E5-E12 -> 234286.76 | F13: =F5-F12 -> 238665.58 | G13: =G5-G12 -> 243124.31 | H13: =H5-H12 -> 247664.34 | I13: =I5-I12 -> 252287.12 | ... L13: =L5-L12 -> 266666.53
A14: Replacement reserve | B14: ='Assumptions'!$B$22*(1+'Assumptions'!$B$21)^(B$1-1) -> 12000 | C14: ='Assumptions'!$B$22*(1+'Assumptions'!$B$21)^(C$1-1) -> 12300 | D14: ='Assumptions'!$B$22*(1+'Assumptions'!$B$21)^(D$1-1) -> 12607.5 | E14: ='Assumptions'!$B$22*(1+'Assumptions'!$B$21)^(E$1-1) -> 12922.687 | F14: ='Assumptions'!$B$22*(1+'Assumptions'!$B$21)^(F$1-1) -> 13245.755 | G14: ='Assumptions'!$B$22*(1+'Assumptions'!$B$21)^(G$1-1) -> 13576.899 | H14: ='Assumptions'!$B$22*(1+'Assumptions'!$B$21)^(H$1-1) -> 13916.321 | I14: ='Assumptions'!$B$22*(1+'Assumptions'!$B$21)^(I$1-1) -> 14264.229 | ... L14: ='Assumptions'!$B$22*(1+'Assumptions'!$B$21)^(L$1-1) -> 15361.015
A15: Cash flow before debt | B15: =B13-B14 -> 209616 | C15: =C13-C14 -> 213463.32 | D15: =D13-D14 -> 217378.96 | E15: =E13-E14 -> 221364.08 | F15: =F13-F14 -> 225419.83 | G15: =G13-G14 -> 229547.41 | H15: =H13-H14 -> 233748.02 | I15: =I13-I14 -> 238022.89 | ... L15: =L13-L14 -> 251305.52

Sheet Debt
A1: Year | B1: 1 | C1: 2 | D1: 3 | E1: 4 | F1: 5 | G1: 6 | H1: 7 | I1: 8 | J1: 9 | K1: 10
A2: Opening balance | B2: ='Sources & Uses'!B12 -> 1920000 | C2: =B6 -> 1876917.1 | D2: =C6 -> 1831895.4 | E2: =D6 -> 1784847.8 | F2: =E6 -> 1735683 | G2: =F6 -> 1684305.8 | H2: =G6 -> 1630616.6 | I2: =H6 -> 1574511.4 | J2: =I6 -> 1515881.5 | K2: =J6 -> 1454613.2
A3: Debt service | B3: =MIN(B2*(1+'Assumptions'!$B$24),-PMT('Assumptions'!$B$24,'Assumptions'!$B$25,'Sources & Uses'!$B$12)) -> 129482.93 | C3: =MIN(C2*(1+'Assumptions'!$B$24),-PMT('Assumptions'!$B$24,'Assumptions'!$B$25,'Sources & Uses'!$B$12)) -> 129482.93 | D3: =MIN(D2*(1+'Assumptions'!$B$24),-PMT('Assumptions'!$B$24,'Assumptions'!$B$25,'Sources & Uses'!$B$12)) -> 129482.93 | E3: =MIN(E2*(1+'Assumptions'!$B$24),-PMT('Assumptions'!$B$24,'Assumptions'!$B$25,'Sources & Uses'!$B$12)) -> 129482.93 | F3: =MIN(F2*(1+'Assumptions'!$B$24),-PMT('Assumptions'!$B$24,'Assumptions'!$B$25,'Sources & Uses'!$B$12)) -> 129482.93 | G3: =MIN(G2*(1+'Assumptions'!$B$24),-PMT('Assumptions'!$B$24,'Assumptions'!$B$25,'Sources & Uses'!$B$12)) -> 129482.93 | H3: =MIN(H2*(1+'Assumptions'!$B$24),-PMT('Assumptions'!$B$24,'Assumptions'!$B$25,'Sources & Uses'!$B$12)) -> 129482.93 | I3: =MIN(I2*(1+'Assumptions'!$B$24),-PMT('Assumptions'!$B$24,'Assumptions'!$B$25,'Sources & Uses'!$B$12)) -> 129482.93 | ... K3: =MIN(K2*(1+'Assumptions'!$B$24),-PMT('Assumptions'!$B$24,'Assumptions'!$B$25,'Sources & Uses'!$B$12)) -> 129482.93
A4: Interest | B4: =B2*'Assumptions'!$B$24 -> 86400 | C4: =C2*'Assumptions'!$B$24 -> 84461.268 | D4: =D2*'Assumptions'!$B$24 -> 82435.293 | E4: =E2*'Assumptions'!$B$24 -> 80318.149 | F4: =F2*'Assumptions'!$B$24 -> 78105.734 | G4: =G2*'Assumptions'!$B$24 -> 75793.76 | H4: =H2*'Assumptions'!$B$24 -> 73377.747 | I4: =I2*'Assumptions'!$B$24 -> 70853.014 | ... K4: =K2*'Assumptions'!$B$24 -> 65457.595
A5: Principal | B5: =B3-B4 -> 43082.934 | C5: =C3-C4 -> 45021.666 | D5: =D3-D4 -> 47047.641 | E5: =E3-E4 -> 49164.785 | F5: =F3-F4 -> 51377.2 | G5: =G3-G4 -> 53689.174 | H5: =H3-H4 -> 56105.187 | I5: =I3-I4 -> 58629.92 | ... K5: =K3-K4 -> 64025.339
A6: Closing balance | B6: =MAX(0,B2-B5) -> 1876917.1 | C6: =MAX(0,C2-C5) -> 1831895.4 | D6: =MAX(0,D2-D5) -> 1784847.8 | E6: =MAX(0,E2-E5) -> 1735683 | F6: =MAX(0,F2-F5) -> 1684305.8 | G6: =MAX(0,G2-G5) -> 1630616.6 | H6: =MAX(0,H2-H5) -> 1574511.4 | I6: =MAX(0,I2-I5) -> 1515881.5 | ... K6: =MAX(0,K2-K5) -> 1390587.9
A7: DSCR | B7: ='Operations'!B13/B3 -> 1.711546 | C7: ='Operations'!C13/C3 -> 1.7435759 | D7: ='Operations'!D13/D3 -> 1.7761913 | E7: ='Operations'!E13/E3 -> 1.8094026 | F7: ='Operations'!F13/F3 -> 1.8432204 | G7: ='Operations'!G13/G3 -> 1.8776552 | H7: ='Operations'!H13/H3 -> 1.912718 | I7: ='Operations'!I13/I3 -> 1.9484198 | ... K7: ='Operations'!K13/K3 -> 2.0217855

Sheet Returns
A1: Year | B1: 0 | C1: 1 | D1: 2 | E1: 3 | F1: 4 | G1: 5 | H1: 6 | I1: 7 | J1: 8 | K1: 9 | L1: 10
A2: Initial equity | B2: =-'Sources & Uses'!B13 -> -2766320
A3: Cash after debt | C3: ='Operations'!B15-'Debt'!B3 -> 80133.066 | D3: ='Operations'!C15-'Debt'!C3 -> 83980.386 | E3: ='Operations'!D15-'Debt'!D3 -> 87896.028 | F3: ='Operations'!E15-'Debt'!E3 -> 91881.141 | G3: ='Operations'!F15-'Debt'!F3 -> 95936.895 | H3: ='Operations'!G15-'Debt'!G3 -> 100064.48 | I3: ='Operations'!H15-'Debt'!H3 -> 104265.09 | J3: ='Operations'!I15-'Debt'!I3 -> 108539.96 | ... L3: ='Operations'!K15-'Debt'!K3 -> 117317.43
A4: Gross sale value | L4: ='Operations'!L13/'Assumptions'!$B$28 -> 4848482.4
A5: Selling costs | L5: =L4*'Assumptions'!$B$29 -> 96969.647
A6: Debt repayment | L6: ='Debt'!K6 -> 1390587.9
A7: Reserve released | L7: ='Assumptions'!$B$9 -> 100000
A8: Total equity cash flow | B8: =B2 -> -2766320 | C8: =C3+C4-C5-C6+C7 -> 80133.066 | D8: =D3+D4-D5-D6+D7 -> 83980.386 | E8: =E3+E4-E5-E6+E7 -> 87896.028 | F8: =F3+F4-F5-F6+F7 -> 91881.141 | G8: =G3+G4-G5-G6+G7 -> 95936.895 | H8: =H3+H4-H5-H6+H7 -> 100064.48 | I8: =I3+I4-I5-I6+I7 -> 104265.09 | J8: =J3+J4-J5-J6+J7 -> 108539.96 | ... L8: =L3+L4-L5-L6+L7 -> 3578242.3
A9: Equity IRR | B9: =IRR(B8:L8) -> 0.054435677
A10: Equity NPV | B10: =NPV('Assumptions'!$B$30,C8:L8)+B8 -> -692163.3
A11: Equity multiple | B11: =SUM(C8:L8)/-B8 -> 1.6064048
A12: Year 1 cash yield | B12: =C3/-B8 -> 0.028967389
A13: Year 1 NOI yield on cost | B13: ='Operations'!B13/'Sources & Uses'!B10 -> 0.047289984
A14: Year 1 DSCR | B14: ='Debt'!B7 -> 1.711546
A15: Break-even occupancy (cash) | B15: =('Operations'!B12-'Operations'!B6+'Operations'!B14+'Debt'!B3)/('Operations'!B2*(1-'Assumptions'!$B$15)) -> 0.67676941

Sheet Sensitivity
A1: Exit cap rate / rent change | B1: -0.1 | C1: 0 | D1: 0.1
A2: 0.045 | B2: ='Returns'!B10+('Operations'!B3*B$1*(1-'Assumptions'!$B$15))/(1+'Assumptions'!$B$30)^1+('Operations'!C3*B$1*(1-'Assumptions'!$B$15))/(1+'Assumptions'!$B$30)^2+('Operations'!D3*B$1*(1-'Assumptions'!$B$15))/(1+'Assumptions'!$B$30)^3+('Operations'!E3*B$1*(1-'Assumptions'!$B$15))/(1+'Assumptions'!$B$30)^4+('Operations'!F3*B$1*(1-'Assumptions'!$B$15))/(1+'Assumptions'!$B$30)^5+('Operations'!G3*B$1*(1-'Assumptions'!$B$15))/(1+'Assumptions'!$B$30)^6+('Operations'!H3*B$1*(1-'Assumptions'!$B$15))/(1+'Assumptions'!$B$30)^7+('Operations'!I3*B$1*(1-'Assumptions'!$B$15))/(1+'Assumptions'!$B$30)^8+('Operations'!J3*B$1*(1-'Assumptions'!$B$15))/(1+'Assumptions'!$B$30)^9+('Operations'!K3*B$1*(1-'Assumptions'!$B$15))/(1+'Assumptions'!$B$30)^10+((('Operations'!L13+'Operations'!L3*B$1*(1-'Assumptions'!$B$15))/$A2)*(1-'Assumptions'!$B$29)-'Returns'!L4+'Returns'!L5)/(1+'Assumptions'!$B$30)^10 -> -751650.19 | C2: ='Returns'!B10+('Operations'!B3*C$1*(1-'Assumptions'!$B$15))/(1+'Assumptions'!$B$30)^1+('Operations'!C3*C$1*(1-'Assumptions'!$B$15))/(1+'Assumptions'!$B$30)^2+('Operations'!D3*C$1*(1-'Assumptions'!$B$15))/(1+'Assumptions'!$B$30)^3+('Operations'!E3*C$1*(1-'Assumptions'!$B$15))/(1+'Assumptions'!$B$30)^4+('Operations'!F3*C$1*(1-'Assumptions'!$B$15))/(1+'Assumptions'!$B$30)^5+('Operations'!G3*C$1*(1-'Assumptions'!$B$15))/(1+'Assumptions'!$B$30)^6+('Operations'!H3*C$1*(1-'Assumptions'!$B$15))/(1+'Assumptions'!$B$30)^7+('Operations'!I3*C$1*(1-'Assumptions'!$B$15))/(1+'Assumptions'!$B$30)^8+('Operations'!J3*C$1*(1-'Assumptions'!$B$15))/(1+'Assumptions'!$B$30)^9+('Operations'!K3*C$1*(1-'Assumptions'!$B$15))/(1+'Assumptions'!$B$30)^10+((('Operations'!L13+'Operations'!L3*C$1*(1-'Assumptions'!$B$15))/$A2)*(1-'Assumptions'!$B$29)-'Returns'!L4+'Returns'!L5)/(1+'Assumptions'!$B$30)^10 -> -246143.23 | D2: ='Returns'!B10+('Operations'!B3*D$1*(1-'Assumptions'!$B$15))/(1+'Assumptions'!$B$30)^1+('Operations'!C3*D$1*(1-'Assumptions'!$B$15))/(1+'Assumptions'!$B$30)^2+('Operations'!D3*D$1*(1-'Assumptions'!$B$15))/(1+'Assumptions'!$B$30)^3+('Operations'!E3*D$1*(1-'Assumptions'!$B$15))/(1+'Assumptions'!$B$30)^4+('Operations'!F3*D$1*(1-'Assumptions'!$B$15))/(1+'Assumptions'!$B$30)^5+('Operations'!G3*D$1*(1-'Assumptions'!$B$15))/(1+'Assumptions'!$B$30)^6+('Operations'!H3*D$1*(1-'Assumptions'!$B$15))/(1+'Assumptions'!$B$30)^7+('Operations'!I3*D$1*(1-'Assumptions'!$B$15))/(1+'Assumptions'!$B$30)^8+('Operations'!J3*D$1*(1-'Assumptions'!$B$15))/(1+'Assumptions'!$B$30)^9+('Operations'!K3*D$1*(1-'Assumptions'!$B$15))/(1+'Assumptions'!$B$30)^10+((('Operations'!L13+'Operations'!L3*D$1*(1-'Assumptions'!$B$15))/$A2)*(1-'Assumptions'!$B$29)-'Returns'!L4+'Returns'!L5)/(1+'Assumptions'!$B$30)^10 -> 259363.73
A3: 0.055 | B3: ='Returns'!B10+('Operations'!B3*B$1*(1-'Assumptions'!$B$15))/(1+'Assumptions'!$B$30)^1+('Operations'!C3*B$1*(1-'Assumptions'!$B$15))/(1+'Assumptions'!$B$30)^2+('Operations'!D3*B$1*(1-'Assumptions'!$B$15))/(1+'Assumptions'!$B$30)^3+('Operations'!E3*B$1*(1-'Assumptions'!$B$15))/(1+'Assumptions'!$B$30)^4+('Operations'!F3*B$1*(1-'Assumptions'!$B$15))/(1+'Assumptions'!$B$30)^5+('Operations'!G3*B$1*(1-'Assumptions'!$B$15))/(1+'Assumptions'!$B$30)^6+('Operations'!H3*B$1*(1-'Assumptions'!$B$15))/(1+'Assumptions'!$B$30)^7+('Operations'!I3*B$1*(1-'Assumptions'!$B$15))/(1+'Assumptions'!$B$30)^8+('Operations'!J3*B$1*(1-'Assumptions'!$B$15))/(1+'Assumptions'!$B$30)^9+('Operations'!K3*B$1*(1-'Assumptions'!$B$15))/(1+'Assumptions'!$B$30)^10+((('Operations'!L13+'Operations'!L3*B$1*(1-'Assumptions'!$B$15))/$A3)*(1-'Assumptions'!$B$29)-'Returns'!L4+'Returns'!L5)/(1+'Assumptions'!$B$30)^10 -> -1140864.3 | C3: ='Returns'!B10+('Operations'!B3*C$1*(1-'Assumptions'!$B$15))/(1+'Assumptions'!$B$30)^1+('Operations'!C3*C$1*(1-'Assumptions'!$B$15))/(1+'Assumptions'!$B$30)^2+('Operations'!D3*C$1*(1-'Assumptions'!$B$15))/(1+'Assumptions'!$B$30)^3+('Operations'!E3*C$1*(1-'Assumptions'!$B$15))/(1+'Assumptions'!$B$30)^4+('Operations'!F3*C$1*(1-'Assumptions'!$B$15))/(1+'Assumptions'!$B$30)^5+('Operations'!G3*C$1*(1-'Assumptions'!$B$15))/(1+'Assumptions'!$B$30)^6+('Operations'!H3*C$1*(1-'Assumptions'!$B$15))/(1+'Assumptions'!$B$30)^7+('Operations'!I3*C$1*(1-'Assumptions'!$B$15))/(1+'Assumptions'!$B$30)^8+('Operations'!J3*C$1*(1-'Assumptions'!$B$15))/(1+'Assumptions'!$B$30)^9+('Operations'!K3*C$1*(1-'Assumptions'!$B$15))/(1+'Assumptions'!$B$30)^10+((('Operations'!L13+'Operations'!L3*C$1*(1-'Assumptions'!$B$15))/$A3)*(1-'Assumptions'!$B$29)-'Returns'!L4+'Returns'!L5)/(1+'Assumptions'!$B$30)^10 -> -692163.3 | D3: ='Returns'!B10+('Operations'!B3*D$1*(1-'Assumptions'!$B$15))/(1+'Assumptions'!$B$30)^1+('Operations'!C3*D$1*(1-'Assumptions'!$B$15))/(1+'Assumptions'!$B$30)^2+('Operations'!D3*D$1*(1-'Assumptions'!$B$15))/(1+'Assumptions'!$B$30)^3+('Operations'!E3*D$1*(1-'Assumptions'!$B$15))/(1+'Assumptions'!$B$30)^4+('Operations'!F3*D$1*(1-'Assumptions'!$B$15))/(1+'Assumptions'!$B$30)^5+('Operations'!G3*D$1*(1-'Assumptions'!$B$15))/(1+'Assumptions'!$B$30)^6+('Operations'!H3*D$1*(1-'Assumptions'!$B$15))/(1+'Assumptions'!$B$30)^7+('Operations'!I3*D$1*(1-'Assumptions'!$B$15))/(1+'Assumptions'!$B$30)^8+('Operations'!J3*D$1*(1-'Assumptions'!$B$15))/(1+'Assumptions'!$B$30)^9+('Operations'!K3*D$1*(1-'Assumptions'!$B$15))/(1+'Assumptions'!$B$30)^10+((('Operations'!L13+'Operations'!L3*D$1*(1-'Assumptions'!$B$15))/$A3)*(1-'Assumptions'!$B$29)-'Returns'!L4+'Returns'!L5)/(1+'Assumptions'!$B$30)^10 -> -243462.27
A4: 0.065 | B4: ='Returns'!B10+('Operations'!B3*B$1*(1-'Assumptions'!$B$15))/(1+'Assumptions'!$B$30)^1+('Operations'!C3*B$1*(1-'Assumptions'!$B$15))/(1+'Assumptions'!$B$30)^2+('Operations'!D3*B$1*(1-'Assumptions'!$B$15))/(1+'Assumptions'!$B$30)^3+('Operations'!E3*B$1*(1-'Assumptions'!$B$15))/(1+'Assumptions'!$B$30)^4+('Operations'!F3*B$1*(1-'Assumptions'!$B$15))/(1+'Assumptions'!$B$30)^5+('Operations'!G3*B$1*(1-'Assumptions'!$B$15))/(1+'Assumptions'!$B$30)^6+('Operations'!H3*B$1*(1-'Assumptions'!$B$15))/(1+'Assumptions'!$B$30)^7+('Operations'!I3*B$1*(1-'Assumptions'!$B$15))/(1+'Assumptions'!$B$30)^8+('Operations'!J3*B$1*(1-'Assumptions'!$B$15))/(1+'Assumptions'!$B$30)^9+('Operations'!K3*B$1*(1-'Assumptions'!$B$15))/(1+'Assumptions'!$B$30)^10+((('Operations'!L13+'Operations'!L3*B$1*(1-'Assumptions'!$B$15))/$A4)*(1-'Assumptions'!$B$29)-'Returns'!L4+'Returns'!L5)/(1+'Assumptions'!$B$30)^10 -> -1410320.3 | C4: ='Returns'!B10+('Operations'!B3*C$1*(1-'Assumptions'!$B$15))/(1+'Assumptions'!$B$30)^1+('Operations'!C3*C$1*(1-'Assumptions'!$B$15))/(1+'Assumptions'!$B$30)^2+('Operations'!D3*C$1*(1-'Assumptions'!$B$15))/(1+'Assumptions'!$B$30)^3+('Operations'!E3*C$1*(1-'Assumptions'!$B$15))/(1+'Assumptions'!$B$30)^4+('Operations'!F3*C$1*(1-'Assumptions'!$B$15))/(1+'Assumptions'!$B$30)^5+('Operations'!G3*C$1*(1-'Assumptions'!$B$15))/(1+'Assumptions'!$B$30)^6+('Operations'!H3*C$1*(1-'Assumptions'!$B$15))/(1+'Assumptions'!$B$30)^7+('Operations'!I3*C$1*(1-'Assumptions'!$B$15))/(1+'Assumptions'!$B$30)^8+('Operations'!J3*C$1*(1-'Assumptions'!$B$15))/(1+'Assumptions'!$B$30)^9+('Operations'!K3*C$1*(1-'Assumptions'!$B$15))/(1+'Assumptions'!$B$30)^10+((('Operations'!L13+'Operations'!L3*C$1*(1-'Assumptions'!$B$15))/$A4)*(1-'Assumptions'!$B$29)-'Returns'!L4+'Returns'!L5)/(1+'Assumptions'!$B$30)^10 -> -1000946.4 | D4: ='Returns'!B10+('Operations'!B3*D$1*(1-'Assumptions'!$B$15))/(1+'Assumptions'!$B$30)^1+('Operations'!C3*D$1*(1-'Assumptions'!$B$15))/(1+'Assumptions'!$B$30)^2+('Operations'!D3*D$1*(1-'Assumptions'!$B$15))/(1+'Assumptions'!$B$30)^3+('Operations'!E3*D$1*(1-'Assumptions'!$B$15))/(1+'Assumptions'!$B$30)^4+('Operations'!F3*D$1*(1-'Assumptions'!$B$15))/(1+'Assumptions'!$B$30)^5+('Operations'!G3*D$1*(1-'Assumptions'!$B$15))/(1+'Assumptions'!$B$30)^6+('Operations'!H3*D$1*(1-'Assumptions'!$B$15))/(1+'Assumptions'!$B$30)^7+('Operations'!I3*D$1*(1-'Assumptions'!$B$15))/(1+'Assumptions'!$B$30)^8+('Operations'!J3*D$1*(1-'Assumptions'!$B$15))/(1+'Assumptions'!$B$30)^9+('Operations'!K3*D$1*(1-'Assumptions'!$B$15))/(1+'Assumptions'!$B$30)^10+((('Operations'!L13+'Operations'!L3*D$1*(1-'Assumptions'!$B$15))/$A4)*(1-'Assumptions'!$B$29)-'Returns'!L4+'Returns'!L5)/(1+'Assumptions'!$B$30)^10 -> -591572.58
A5: Values show equity NPV (EUR), with fixed costs and debt unchanged.

Sheet Legal Checklist
A1: Topic | B1: Required verification | C1: Status | D1: Source
A2: Municipality & zoning | B2: Identify exact address, commune, lawful use and permitted room count. VUB/ULB campus area may involve Ixelles or Etterbeek, not necessarily City of Brussels. | C2: OPEN
A3: Planning permission | B3: Check conversion/change of use, works, planning permit and local rules before purchase. | C3: OPEN
A4: Housing quality | B4: Confirm Brussels minimum safety, health and equipment standards; inspect every unit. | C4: OPEN
A5: Fire safety | B5: Obtain applicable fire service/municipal requirements, occupancy limit and certificates. | C5: OPEN
A6: Student tenancy | B6: Check student lease regime, student status, duration, termination, deposit and registration. | C6: OPEN
A7: Rent & indexation | B7: Check reference rent / excessive rent rules and EPC-related indexation conditions. Forecast growth is conditional. | C7: OPEN
A8: Energy | B8: Obtain valid PEB/EPC and price required renovation works; assess regional obligations. | C8: OPEN
A9: Taxes & VAT | B9: Confirm registration duty, property tax, ownership vehicle, VAT recoverability and income/capital gains taxes. Model is pre-income-tax. | C9: OPEN
A10: Planning rule verified | B10: Exclusive student housing conversion requires permit; ask commune for existing permits and applicable communal planning rules. | C10: RULE VERIFIED; PROPERTY OPEN | D10: Sources: Student housing planning guidance
A11: 2026 standards | B11: Apply current 2026 safety, health and equipment requirements; compliance budget remains unquoted. | C11: RULE VERIFIED; PROPERTY OPEN | D11: Sources: Housing standards
A12: Lease administration | B12: Use regional student lease template; verify student status, termination risk; register with Irisrent and MyRent within two months. | C12: RULE VERIFIED; EXECUTION OPEN | D12: Sources: Student lease model and Lease registration
A13: Acquisition tax | B13: 12.5% duty assumed for existing asset acquisition; new-build VAT, share purchase, exemptions and market-value tax base require transaction advice. | C13: RATE VERIFIED; STRUCTURE OPEN | D13: Sources: Brussels registration and mortgage duties
A14: Rent controls | B14: Excessive rent prohibition in force since May 2025. EUR650 is a scenario input, not a confirmed lawful or market rent. | C14: RULE VERIFIED; PROPERTY OPEN | D14: Sources: Excessive rents

Sheet Sources
A1: Source | B1: URL | C1: Access date | D1: Use / reliability
A2: Initial model | B2: User request | C2: 2026-10-14 | D2: All financial assumptions illustrative, pending research
A3: Brussels registration and mortgage duties | B3: https://be.brussels/fr/impots-financement/impots-et-taxes/fiscalite-immobiliere/droits-denregistrement | C3: 2026-10-14 | D3: 12.5% acquisition duty; 1% mortgage duty on secured amounts; no owner-occupier relief assumed
A4: Student lease model and rules | B4: https://be.brussels/fr/logement/location/bail-dhabitation/contrat-de-bail-modeles-et-annexe | C4: 2026-10-14 | D4: Maximum 12 months; student can terminate with two months notice without indemnity; mutual choice and proof of student status
A5: Housing standards | B5: https://be.brussels/fr/logement/location/conformite-logement/normes-et-securite | C5: 2026-10-14 | D5: Minimum safety, health and equipment rules; updated standards from 1 January 2026
A6: Lease registration | B6: https://be.brussels/nl/huisvesting/huren-en-verhuren/huurovereenkomst/registratie-woninghuurovereenkomst | C6: 2026-10-14 | D6: Landlord registers within two months; Irisrent and MyRent both required per regional guidance
A7: Student housing planning guidance | B7: https://urban.brussels/storage/uploads/7782bb55-caef-4a03-9780-aac7547d23f5/Vademecum---changements-utilisation-soumis-permis.pdf | C7: 2026-10-14 | D7: Conversion to exclusive student housing requires planning permission; student tenancy alone does not establish planning status
A8: Excessive rents: regional activity report | B8: https://be.brussels/fr/logement/bruxelles-logement-publie-son-rapport-dactivite-2025 | C8: 2026-10-14 | D8: Excessive rents prohibited since 1 May 2025; validate rent against applicable reference and condition rules
A9: Smoke detectors | B9: https://be.brussels/fr/logement/construction-et-renovation/securite-et-reglementation/detecteurs-de-fumee | C9: 2026-10-14 | D9: Mandatory in all housing from 2025; verify placement, interconnection and applicable transitions
A10: PEB certification scope | B10: https://environnement.brussels/pro/reglementation-et-inspection/obligations-et-autorisations/les-certificats-peb | C10: 2026-10-14 | D10: Verify certificate obligation and unit scope before letting
A11: Indexation and correction factors | B11: https://be.brussels/fr/logement/location/bail-dhabitation/indexation-des-loyers/indexation-des-loyers-avec-facteur-de-correction | C11: 2026-10-14 | D11: Certain pre-14 October 2022 E/F/G leases need correction; registration and certificate conditions apply
A12: Ixelles urban planning | B12: https://www.ixelles.be/site/124-Urbanisme | C12: 2026-10-14 | D12: Municipal planning contact if property is in Ixelles; exact address unknown
