Workbook

Sheet Overview
A1: VUB STUDENT HOUSING — investment screening
A2: RESEARCHED SCREENING MODEL — 14 October 2026; sourced context, explicit investment assumptions
A3: Metric | B3: Result | C3: Classification / interpretation
A4: Total investment | B4: =Inputs!B31 -> 11009200 | C4: Derived; continuous; ratio; nominal EUR
A5: NPV at required return | B5: =NPV(Inputs!B15,'Cash flow'!L4:L34)+'Cash flow'!L3 -> -803425.46 | C5: Output; continuous; interval; EUR; t=0
A6: Project IRR | B6: =IRR('Cash flow'!L3:L34) -> 0.06506627 | C6: Output; continuous; rate; unlevered
A7: Simple payback incl. exit | B7: =IF(COUNTIF('Cash flow'!R3:R34,">0")=0,"Not reached",SUM('Cash flow'!R3:R34)) -> 18.247857 | C7: Output; continuous; ratio; years from t=0; interpolation
A8: Time until operations | B8: =Inputs!B18 -> 2 | C8: Assumption; discrete; ratio; years incl. approvals
A9: Operating horizon | B9: =Inputs!B19 -> 30 | C9: Assumption; discrete; ratio; years
A10: International share | B10: =Inputs!B20 -> 0.2438 | C10: Context; continuous; ratio; see Inputs evidence
A11: Annual student resources | B11: =Inputs!B21 -> 14000 | C11: Scenario; continuous; ratio; EUR/year; no VUB average established
A12: Rent / month | B12: =Inputs!B10 -> 650 | C12: Decision; continuous; ratio; EUR excl. utilities
A13: Academic dropout proxy | B13: =Inputs!B22 -> 0.16 | C13: Context; continuous; ratio; Flemish proxy, not VUB rate; S9
A14: Annual rent / resources | B14: =Inputs!B10*12/Inputs!B21 -> 0.55714286 | C14: Derived; continuous; ratio; excludes utilities
A15: First operating year NOI | B15: ='Cash flow'!H5 -> 555750 | C15: Output; continuous; ratio; EUR/year
A18: Investment interpretation | B18: Negative NPV at 7% implies the assumed rent, costs and exit value do not meet the required return.
A20: Scope | B20: 100-room illustrative development. No secured land or construction quote. 30 operating years; terminal sale in year 31.
A21: Student income | B21: There is no universal minimum annual income for a student. Wages apply only to hours worked; family support, grants and earnings vary.
A22: Dropout versus departures | B22: 16% dropout is a Flemish first-year cohort proxy, not VUB-specific. Price-driven departures below are hypothetical, not measured VUB behaviour; baseline vacancy already includes turnover.
A23: Payback convention | B23: Simple PBP includes sale if needed; the base case pays back before sale. Fractional years assume uniform within-year operating cash flow. Discounted payback uses the 7% required return.
A25: Operating-only payback (years) | B25: =IF(COUNTIF('Cash flow'!S3:S34,">0")=0,"Not reached",SUM('Cash flow'!S3:S34)) -> 18.247857 | C25: Derived; continuous; ratio; excludes terminal sale
A26: Discounted payback (years) | B26: =IF(COUNTIF('Cash flow'!T3:T34,">0")=0,"Not reached",SUM('Cash flow'!T3:T34)) -> Not reached | C26: Derived; continuous; ratio; includes sale
A28: Minimum proof of means / year | B28: ='Student budget'!B5*12 -> 12744 | C28: Regulatory benchmark; continuous; ratio; EUR; certain non-EU students (S3)
A29: Minimum student wage, age 21 | B29: ='Student budget'!B12 -> 13.5644 | C29: Regulatory benchmark; continuous; ratio; EUR/hour; fallback absent sector CBA (S11)
A30: Illustrative 650h gross pay, age 21 | B30: ='Student budget'!C12 -> 8816.86 | C30: Derived scenario; continuous; ratio; EUR/year; not VUB average
A32: Model controls | B32: Blue cells are assumptions. Development duration and horizon are fixed to 2 and 30 years; rebuild the saved code for another schedule. No debt, grants, income tax or financing fees; costs gross of nonrecoverable tax.

Sheet Inputs
A1: PROJECT INPUTS — blue cells editable
A2: Nominal EUR; unlevered, before income tax. Costs assumed inclusive of nonrecoverable taxes.
A3: Variable | B3: Value | C3: Unit | D3: Variable classification | E3: Definition / evidence
A4: Rooms | B4: 100 | C4: rooms | D4: Decision; discrete; ratio | E4: Illustrative scale; no plot secured
A5: Gross floor area per room | B5: 28 | C5: m²/room | D5: Assumption; continuous; ratio | E5: Includes share of circulation and common areas
A6: Construction cost | B6: 2600 | C6: EUR/m² | D6: Assumption; continuous; ratio | E6: Concept estimate, gross of nonrecoverable VAT; obtain quotations
A7: Land / acquisition | B7: 1800000 | C7: EUR | D7: Assumption; continuous; ratio | E7: No parcel or offer secured
A8: Professional / permit fees | B8: 0.15 | C8: % of construction | D8: Assumption; continuous; ratio | E8: Architect, studies, permit; gross cost assumption
A9: Contingency | B9: 0.1 | C9: % of construction + fees | D9: Assumption; continuous; ratio | E9: No double counting with operating reserve
A10: Monthly room rent | B10: 650 | C10: EUR/room/month | D10: Decision; continuous; ratio | E10: EUR650 private new-build rent assumption, excluding utilities. S10: VUB standard room 2026–2027 EUR449.30 including listed costs; S2 historical private average EUR550. Premium and achievable rent require local comparables.
A11: Annual rent growth | B11: 0.02 | C11: %/year | D11: Assumption; continuous; ratio | E11: Subject to lawful indexation and lease provisions
A12: Stabilised occupancy | B12: 0.95 | C12: % of rooms | D12: Assumption; continuous; ratio | E12: Includes vacancy and replacement after departures
A13: Operating expense share | B13: 0.25 | C13: % of collected rent | D13: Assumption; continuous; ratio | E13: Management, repairs, insurance, property tax, owner utilities; excludes debt and income tax
A14: Annual capital reserve | B14: 150 | C14: EUR/room/year | D14: Assumption; continuous; ratio | E14: Inflates at annual rent growth
A15: Discount rate | B15: 0.07 | C15: %/year | D15: Assumption; continuous; ratio | E15: Nominal unlevered required return
... A24: Departure response to rent rise | B24: 0.15 | C24: fraction/fraction | D24: Assumption; continuous; ratio | E24: A 10% rent increase adds 1.5 percentage points of departures; unvalidated
A27: Gross area | B27: =B4*B5 -> 2800
A28: Construction subtotal | B28: =B27*B6 -> 7280000
A29: Fees | B29: =B28*B8 -> 1092000
A30: Contingency | B30: =(B28+B29)*B9 -> 837200
A31: Total investment | B31: =B7+SUM(B28:B30) -> 11009200
A33: Location | B33: Etterbeek / Ixelles, near VUB Main Campus, Pleinlaan / Boulevard de la Plaine
A34: Site status | B34: Search area only: no identified parcel, zoning clearance or buildability confirmation.

Sheet Cash flow
A1: UNLEVERED ANNUAL CASH FLOW — end-of-year convention
A2: Year | B2: Stage | C2: Capex | D2: Gross rent | E2: Occupancy | F2: Collected rent | G2: Operating costs | H2: NOI | I2: Capital reserve | J2: Net operating CF | K2: Net sale proceeds | L2: Total CF | M2: Discount factor | N2: PV | O2: Cumulative CF | P2: Cumulative CF excl. exit | Q2: Cumulative discounted CF | R2: PBP crossing | S2: Operating PBP crossing | T2: Discounted PBP crossing
A3: 0 | B3: Construction | C3: =-Inputs!B7-(Inputs!B31-Inputs!B7)/2 -> -6404600 | D3: =0 -> 0 | E3: =0 -> 0 | F3: =D3*E3 -> 0 | G3: =F3*Inputs!B13 -> 0 | H3: =F3-G3 -> 0 | I3: =0 -> 0 | J3: =H3-I3 -> 0 | K3: =0 -> 0 | L3: =C3+J3+K3 -> -6404600 | M3: =1/(1+Inputs!B15)^A3 -> 1 | N3: =L3*M3 -> -6404600 | O3: =SUM(L$3:L3) -> -6404600 | P3: =SUM(L$3:L3)-SUM(K$3:K3) -> -6404600 | Q3: =SUM(N$3:N3) -> -6404600 | R3: =0 -> 0 | S3: =0 -> 0 | T3: =0 -> 0
A4: 1 | B4: Construction | C4: =-(Inputs!B31-Inputs!B7)/2 -> -4604600 | D4: =0 -> 0 | E4: =0 -> 0 | F4: =D4*E4 -> 0 | G4: =F4*Inputs!B13 -> 0 | H4: =F4-G4 -> 0 | I4: =0 -> 0 | J4: =H4-I4 -> 0 | K4: =0 -> 0 | L4: =C4+J4+K4 -> -4604600 | M4: =1/(1+Inputs!B15)^A4 -> 0.93457944 | N4: =L4*M4 -> -4303364.5 | O4: =SUM(L$3:L4) -> -11009200 | P4: =SUM(L$3:L4)-SUM(K$3:K4) -> -11009200 | Q4: =SUM(N$3:N4) -> -10707964 | R4: =IF(AND(O4>=0,O3<0),A4-1-O3/L4,0) -> 0 | S4: =IF(AND(P4>=0,P3<0),A4-1-P3/J4,0) -> 0 | T4: =IF(AND(Q4>=0,Q3<0),A4-1-Q3/N4,0) -> 0
A5: 2 | B5: Operating | C5: =0 -> 0 | D5: =Inputs!B4*Inputs!B10*12*(1+Inputs!B11)^(A5-Inputs!B18) -> 780000 | E5: =Inputs!B12 -> 0.95 | F5: =D5*E5 -> 741000 | G5: =F5*Inputs!B13 -> 185250 | H5: =F5-G5 -> 555750 | I5: =Inputs!B4*Inputs!B14*(1+Inputs!B11)^(A5-Inputs!B18) -> 15000 | J5: =H5-I5 -> 540750 | K5: =0 -> 0 | L5: =C5+J5+K5 -> 540750 | M5: =1/(1+Inputs!B15)^A5 -> 0.87343873 | N5: =L5*M5 -> 472311.99 | O5: =SUM(L$3:L5) -> -10468450 | P5: =SUM(L$3:L5)-SUM(K$3:K5) -> -10468450 | Q5: =SUM(N$3:N5) -> -10235652 | R5: =IF(AND(O5>=0,O4<0),A5-1-O4/L5,0) -> 0 | S5: =IF(AND(P5>=0,P4<0),A5-1-P4/J5,0) -> 0 | T5: =IF(AND(Q5>=0,Q4<0),A5-1-Q4/N5,0) -> 0
A6: 3 | B6: Operating | C6: =0 -> 0 | D6: =Inputs!B4*Inputs!B10*12*(1+Inputs!B11)^(A6-Inputs!B18) -> 795600 | E6: =Inputs!B12 -> 0.95 | F6: =D6*E6 -> 755820 | G6: =F6*Inputs!B13 -> 188955 | H6: =F6-G6 -> 566865 | I6: =Inputs!B4*Inputs!B14*(1+Inputs!B11)^(A6-Inputs!B18) -> 15300 | J6: =H6-I6 -> 551565 | K6: =0 -> 0 | L6: =C6+J6+K6 -> 551565 | M6: =1/(1+Inputs!B15)^A6 -> 0.81629788 | N6: =L6*M6 -> 450241.34 | O6: =SUM(L$3:L6) -> -9916885 | P6: =SUM(L$3:L6)-SUM(K$3:K6) -> -9916885 | Q6: =SUM(N$3:N6) -> -9785411.2 | R6: =IF(AND(O6>=0,O5<0),A6-1-O5/L6,0) -> 0 | S6: =IF(AND(P6>=0,P5<0),A6-1-P5/J6,0) -> 0 | T6: =IF(AND(Q6>=0,Q5<0),A6-1-Q5/N6,0) -> 0
A7: 4 | B7: Operating | C7: =0 -> 0 | D7: =Inputs!B4*Inputs!B10*12*(1+Inputs!B11)^(A7-Inputs!B18) -> 811512 | E7: =Inputs!B12 -> 0.95 | F7: =D7*E7 -> 770936.4 | G7: =F7*Inputs!B13 -> 192734.1 | H7: =F7-G7 -> 578202.3 | I7: =Inputs!B4*Inputs!B14*(1+Inputs!B11)^(A7-Inputs!B18) -> 15606 | J7: =H7-I7 -> 562596.3 | K7: =0 -> 0 | L7: =C7+J7+K7 -> 562596.3 | M7: =1/(1+Inputs!B15)^A7 -> 0.76289521 | N7: =L7*M7 -> 429202.02 | O7: =SUM(L$3:L7) -> -9354288.7 | P7: =SUM(L$3:L7)-SUM(K$3:K7) -> -9354288.7 | Q7: =SUM(N$3:N7) -> -9356209.1 | R7: =IF(AND(O7>=0,O6<0),A7-1-O6/L7,0) -> 0 | S7: =IF(AND(P7>=0,P6<0),A7-1-P6/J7,0) -> 0 | T7: =IF(AND(Q7>=0,Q6<0),A7-1-Q6/N7,0) -> 0
A8: 5 | B8: Operating | C8: =0 -> 0 | D8: =Inputs!B4*Inputs!B10*12*(1+Inputs!B11)^(A8-Inputs!B18) -> 827742.24 | E8: =Inputs!B12 -> 0.95 | F8: =D8*E8 -> 786355.13 | G8: =F8*Inputs!B13 -> 196588.78 | H8: =F8-G8 -> 589766.35 | I8: =Inputs!B4*Inputs!B14*(1+Inputs!B11)^(A8-Inputs!B18) -> 15918.12 | J8: =H8-I8 -> 573848.23 | K8: =0 -> 0 | L8: =C8+J8+K8 -> 573848.23 | M8: =1/(1+Inputs!B15)^A8 -> 0.71298618 | N8: =L8*M8 -> 409145.85 | O8: =SUM(L$3:L8) -> -8780440.5 | P8: =SUM(L$3:L8)-SUM(K$3:K8) -> -8780440.5 | Q8: =SUM(N$3:N8) -> -8947063.3 | R8: =IF(AND(O8>=0,O7<0),A8-1-O7/L8,0) -> 0 | S8: =IF(AND(P8>=0,P7<0),A8-1-P7/J8,0) -> 0 | T8: =IF(AND(Q8>=0,Q7<0),A8-1-Q7/N8,0) -> 0
A9: 6 | B9: Operating | C9: =0 -> 0 | D9: =Inputs!B4*Inputs!B10*12*(1+Inputs!B11)^(A9-Inputs!B18) -> 844297.08 | E9: =Inputs!B12 -> 0.95 | F9: =D9*E9 -> 802082.23 | G9: =F9*Inputs!B13 -> 200520.56 | H9: =F9-G9 -> 601561.67 | I9: =Inputs!B4*Inputs!B14*(1+Inputs!B11)^(A9-Inputs!B18) -> 16236.482 | J9: =H9-I9 -> 585325.19 | K9: =0 -> 0 | L9: =C9+J9+K9 -> 585325.19 | M9: =1/(1+Inputs!B15)^A9 -> 0.66634222 | N9: =L9*M9 -> 390026.89 | O9: =SUM(L$3:L9) -> -8195115.3 | P9: =SUM(L$3:L9)-SUM(K$3:K9) -> -8195115.3 | Q9: =SUM(N$3:N9) -> -8557036.4 | R9: =IF(AND(O9>=0,O8<0),A9-1-O8/L9,0) -> 0 | S9: =IF(AND(P9>=0,P8<0),A9-1-P8/J9,0) -> 0 | T9: =IF(AND(Q9>=0,Q8<0),A9-1-Q8/N9,0) -> 0
A10: 7 | B10: Operating | C10: =0 -> 0 | D10: =Inputs!B4*Inputs!B10*12*(1+Inputs!B11)^(A10-Inputs!B18) -> 861183.03 | E10: =Inputs!B12 -> 0.95 | F10: =D10*E10 -> 818123.88 | G10: =F10*Inputs!B13 -> 204530.97 | H10: =F10-G10 -> 613592.91 | I10: =Inputs!B4*Inputs!B14*(1+Inputs!B11)^(A10-Inputs!B18) -> 16561.212 | J10: =H10-I10 -> 597031.69 | K10: =0 -> 0 | L10: =C10+J10+K10 -> 597031.69 | M10: =1/(1+Inputs!B15)^A10 -> 0.62274974 | N10: =L10*M10 -> 371801.33 | O10: =SUM(L$3:L10) -> -7598083.6 | P10: =SUM(L$3:L10)-SUM(K$3:K10) -> -7598083.6 | Q10: =SUM(N$3:N10) -> -8185235.1 | R10: =IF(AND(O10>=0,O9<0),A10-1-O9/L10,0) -> 0 | S10: =IF(AND(P10>=0,P9<0),A10-1-P9/J10,0) -> 0 | T10: =IF(AND(Q10>=0,Q9<0),A10-1-Q9/N10,0) -> 0
A11: 8 | B11: Operating | C11: =0 -> 0 | D11: =Inputs!B4*Inputs!B10*12*(1+Inputs!B11)^(A11-Inputs!B18) -> 878406.69 | E11: =Inputs!B12 -> 0.95 | F11: =D11*E11 -> 834486.35 | G11: =F11*Inputs!B13 -> 208621.59 | H11: =F11-G11 -> 625864.76 | I11: =Inputs!B4*Inputs!B14*(1+Inputs!B11)^(A11-Inputs!B18) -> 16892.436 | J11: =H11-I11 -> 608972.33 | K11: =0 -> 0 | L11: =C11+J11+K11 -> 608972.33 | M11: =1/(1+Inputs!B15)^A11 -> 0.5820091 | N11: =L11*M11 -> 354427.44 | O11: =SUM(L$3:L11) -> -6989111.3 | P11: =SUM(L$3:L11)-SUM(K$3:K11) -> -6989111.3 | Q11: =SUM(N$3:N11) -> -7830807.6 | R11: =IF(AND(O11>=0,O10<0),A11-1-O10/L11,0) -> 0 | S11: =IF(AND(P11>=0,P10<0),A11-1-P10/J11,0) -> 0 | T11: =IF(AND(Q11>=0,Q10<0),A11-1-Q10/N11,0) -> 0
A12: 9 | B12: Operating | C12: =0 -> 0 | D12: =Inputs!B4*Inputs!B10*12*(1+Inputs!B11)^(A12-Inputs!B18) -> 895974.82 | E12: =Inputs!B12 -> 0.95 | F12: =D12*E12 -> 851176.08 | G12: =F12*Inputs!B13 -> 212794.02 | H12: =F12-G12 -> 638382.06 | I12: =Inputs!B4*Inputs!B14*(1+Inputs!B11)^(A12-Inputs!B18) -> 17230.285 | J12: =H12-I12 -> 621151.77 | K12: =0 -> 0 | L12: =C12+J12+K12 -> 621151.77 | M12: =1/(1+Inputs!B15)^A12 -> 0.54393374 | N12: =L12*M12 -> 337865.41 | O12: =SUM(L$3:L12) -> -6367959.5 | P12: =SUM(L$3:L12)-SUM(K$3:K12) -> -6367959.5 | Q12: =SUM(N$3:N12) -> -7492942.2 | R12: =IF(AND(O12>=0,O11<0),A12-1-O11/L12,0) -> 0 | S12: =IF(AND(P12>=0,P11<0),A12-1-P11/J12,0) -> 0 | T12: =IF(AND(Q12>=0,Q11<0),A12-1-Q11/N12,0) -> 0
A13: 10 | B13: Operating | C13: =0 -> 0 | D13: =Inputs!B4*Inputs!B10*12*(1+Inputs!B11)^(A13-Inputs!B18) -> 913894.32 | E13: =Inputs!B12 -> 0.95 | F13: =D13*E13 -> 868199.6 | G13: =F13*Inputs!B13 -> 217049.9 | H13: =F13-G13 -> 651149.7 | I13: =Inputs!B4*Inputs!B14*(1+Inputs!B11)^(A13-Inputs!B18) -> 17574.891 | J13: =H13-I13 -> 633574.81 | K13: =0 -> 0 | L13: =C13+J13+K13 -> 633574.81 | M13: =1/(1+Inputs!B15)^A13 -> 0.50834929 | N13: =L13*M13 -> 322077.31 | O13: =SUM(L$3:L13) -> -5734384.7 | P13: =SUM(L$3:L13)-SUM(K$3:K13) -> -5734384.7 | Q13: =SUM(N$3:N13) -> -7170864.9 | R13: =IF(AND(O13>=0,O12<0),A13-1-O12/L13,0) -> 0 | S13: =IF(AND(P13>=0,P12<0),A13-1-P12/J13,0) -> 0 | T13: =IF(AND(Q13>=0,Q12<0),A13-1-Q12/N13,0) -> 0
A14: 11 | B14: Operating | C14: =0 -> 0 | D14: =Inputs!B4*Inputs!B10*12*(1+Inputs!B11)^(A14-Inputs!B18) -> 932172.2 | E14: =Inputs!B12 -> 0.95 | F14: =D14*E14 -> 885563.59 | G14: =F14*Inputs!B13 -> 221390.9 | H14: =F14-G14 -> 664172.7 | I14: =Inputs!B4*Inputs!B14*(1+Inputs!B11)^(A14-Inputs!B18) -> 17926.389 | J14: =H14-I14 -> 646246.31 | K14: =0 -> 0 | L14: =C14+J14+K14 -> 646246.31 | M14: =1/(1+Inputs!B15)^A14 -> 0.4750928 | N14: =L14*M14 -> 307026.96 | O14: =SUM(L$3:L14) -> -5088138.4 | P14: =SUM(L$3:L14)-SUM(K$3:K14) -> -5088138.4 | Q14: =SUM(N$3:N14) -> -6863837.9 | R14: =IF(AND(O14>=0,O13<0),A14-1-O13/L14,0) -> 0 | S14: =IF(AND(P14>=0,P13<0),A14-1-P13/J14,0) -> 0 | T14: =IF(AND(Q14>=0,Q13<0),A14-1-Q13/N14,0) -> 0
A15: 12 | B15: Operating | C15: =0 -> 0 | D15: =Inputs!B4*Inputs!B10*12*(1+Inputs!B11)^(A15-Inputs!B18) -> 950815.65 | E15: =Inputs!B12 -> 0.95 | F15: =D15*E15 -> 903274.87 | G15: =F15*Inputs!B13 -> 225818.72 | H15: =F15-G15 -> 677456.15 | I15: =Inputs!B4*Inputs!B14*(1+Inputs!B11)^(A15-Inputs!B18) -> 18284.916 | J15: =H15-I15 -> 659171.23 | K15: =0 -> 0 | L15: =C15+J15+K15 -> 659171.23 | M15: =1/(1+Inputs!B15)^A15 -> 0.44401196 | N15: =L15*M15 -> 292679.91 | O15: =SUM(L$3:L15) -> -4428967.1 | P15: =SUM(L$3:L15)-SUM(K$3:K15) -> -4428967.1 | Q15: =SUM(N$3:N15) -> -6571158 | R15: =IF(AND(O15>=0,O14<0),A15-1-O14/L15,0) -> 0 | S15: =IF(AND(P15>=0,P14<0),A15-1-P14/J15,0) -> 0 | T15: =IF(AND(Q15>=0,Q14<0),A15-1-Q14/N15,0) -> 0
A16: 13 | B16: Operating | C16: =0 -> 0 | D16: =Inputs!B4*Inputs!B10*12*(1+Inputs!B11)^(A16-Inputs!B18) -> 969831.96 | E16: =Inputs!B12 -> 0.95 | F16: =D16*E16 -> 921340.36 | G16: =F16*Inputs!B13 -> 230335.09 | H16: =F16-G16 -> 691005.27 | I16: =Inputs!B4*Inputs!B14*(1+Inputs!B11)^(A16-Inputs!B18) -> 18650.615 | J16: =H16-I16 -> 672354.66 | K16: =0 -> 0 | L16: =C16+J16+K16 -> 672354.66 | M16: =1/(1+Inputs!B15)^A16 -> 0.41496445 | N16: =L16*M16 -> 279003.28 | O16: =SUM(L$3:L16) -> -3756612.5 | P16: =SUM(L$3:L16)-SUM(K$3:K16) -> -3756612.5 | Q16: =SUM(N$3:N16) -> -6292154.7 | R16: =IF(AND(O16>=0,O15<0),A16-1-O15/L16,0) -> 0 | S16: =IF(AND(P16>=0,P15<0),A16-1-P15/J16,0) -> 0 | T16: =IF(AND(Q16>=0,Q15<0),A16-1-Q15/N16,0) -> 0
A17: 14 | B17: Operating | C17: =0 -> 0 | D17: =Inputs!B4*Inputs!B10*12*(1+Inputs!B11)^(A17-Inputs!B18) -> 989228.6 | E17: =Inputs!B12 -> 0.95 | F17: =D17*E17 -> 939767.17 | G17: =F17*Inputs!B13 -> 234941.79 | H17: =F17-G17 -> 704825.38 | I17: =Inputs!B4*Inputs!B14*(1+Inputs!B11)^(A17-Inputs!B18) -> 19023.627 | J17: =H17-I17 -> 685801.75 | K17: =0 -> 0 | L17: =C17+J17+K17 -> 685801.75 | M17: =1/(1+Inputs!B15)^A17 -> 0.38781724 | N17: =L17*M17 -> 265965.74 | O17: =SUM(L$3:L17) -> -3070810.7 | P17: =SUM(L$3:L17)-SUM(K$3:K17) -> -3070810.7 | Q17: =SUM(N$3:N17) -> -6026189 | R17: =IF(AND(O17>=0,O16<0),A17-1-O16/L17,0) -> 0 | S17: =IF(AND(P17>=0,P16<0),A17-1-P16/J17,0) -> 0 | T17: =IF(AND(Q17>=0,Q16<0),A17-1-Q16/N17,0) -> 0
A18: 15 | B18: Operating | C18: =0 -> 0 | D18: =Inputs!B4*Inputs!B10*12*(1+Inputs!B11)^(A18-Inputs!B18) -> 1009013.2 | E18: =Inputs!B12 -> 0.95 | F18: =D18*E18 -> 958562.51 | G18: =F18*Inputs!B13 -> 239640.63 | H18: =F18-G18 -> 718921.88 | I18: =Inputs!B4*Inputs!B14*(1+Inputs!B11)^(A18-Inputs!B18) -> 19404.099 | J18: =H18-I18 -> 699517.79 | K18: =0 -> 0 | L18: =C18+J18+K18 -> 699517.79 | M18: =1/(1+Inputs!B15)^A18 -> 0.36244602 | N18: =L18*M18 -> 253537.44 | O18: =SUM(L$3:L18) -> -2371292.9 | P18: =SUM(L$3:L18)-SUM(K$3:K18) -> -2371292.9 | Q18: =SUM(N$3:N18) -> -5772651.6 | R18: =IF(AND(O18>=0,O17<0),A18-1-O17/L18,0) -> 0 | S18: =IF(AND(P18>=0,P17<0),A18-1-P17/J18,0) -> 0 | T18: =IF(AND(Q18>=0,Q17<0),A18-1-Q17/N18,0) -> 0
A19: 16 | B19: Operating | C19: =0 -> 0 | D19: =Inputs!B4*Inputs!B10*12*(1+Inputs!B11)^(A19-Inputs!B18) -> 1029193.4 | E19: =Inputs!B12 -> 0.95 | F19: =D19*E19 -> 977733.76 | G19: =F19*Inputs!B13 -> 244433.44 | H19: =F19-G19 -> 733300.32 | I19: =Inputs!B4*Inputs!B14*(1+Inputs!B11)^(A19-Inputs!B18) -> 19792.181 | J19: =H19-I19 -> 713508.14 | K19: =0 -> 0 | L19: =C19+J19+K19 -> 713508.14 | M19: =1/(1+Inputs!B15)^A19 -> 0.3387346 | N19: =L19*M19 -> 241689.89 | O19: =SUM(L$3:L19) -> -1657784.8 | P19: =SUM(L$3:L19)-SUM(K$3:K19) -> -1657784.8 | Q19: =SUM(N$3:N19) -> -5530961.7 | R19: =IF(AND(O19>=0,O18<0),A19-1-O18/L19,0) -> 0 | S19: =IF(AND(P19>=0,P18<0),A19-1-P18/J19,0) -> 0 | T19: =IF(AND(Q19>=0,Q18<0),A19-1-Q18/N19,0) -> 0
A20: 17 | B20: Operating | C20: =0 -> 0 | D20: =Inputs!B4*Inputs!B10*12*(1+Inputs!B11)^(A20-Inputs!B18) -> 1049777.3 | E20: =Inputs!B12 -> 0.95 | F20: =D20*E20 -> 997288.44 | G20: =F20*Inputs!B13 -> 249322.11 | H20: =F20-G20 -> 747966.33 | I20: =Inputs!B4*Inputs!B14*(1+Inputs!B11)^(A20-Inputs!B18) -> 20188.025 | J20: =H20-I20 -> 727778.3 | K20: =0 -> 0 | L20: =C20+J20+K20 -> 727778.3 | M20: =1/(1+Inputs!B15)^A20 -> 0.31657439 | N20: =L20*M20 -> 230395.97 | O20: =SUM(L$3:L20) -> -930006.5 | P20: =SUM(L$3:L20)-SUM(K$3:K20) -> -930006.5 | Q20: =SUM(N$3:N20) -> -5300565.7 | R20: =IF(AND(O20>=0,O19<0),A20-1-O19/L20,0) -> 0 | S20: =IF(AND(P20>=0,P19<0),A20-1-P19/J20,0) -> 0 | T20: =IF(AND(Q20>=0,Q19<0),A20-1-Q19/N20,0) -> 0
A21: 18 | B21: Operating | C21: =0 -> 0 | D21: =Inputs!B4*Inputs!B10*12*(1+Inputs!B11)^(A21-Inputs!B18) -> 1070772.8 | E21: =Inputs!B12 -> 0.95 | F21: =D21*E21 -> 1017234.2 | G21: =F21*Inputs!B13 -> 254308.55 | H21: =F21-G21 -> 762925.66 | I21: =Inputs!B4*Inputs!B14*(1+Inputs!B11)^(A21-Inputs!B18) -> 20591.786 | J21: =H21-I21 -> 742333.87 | K21: =0 -> 0 | L21: =C21+J21+K21 -> 742333.87 | M21: =1/(1+Inputs!B15)^A21 -> 0.29586392 | N21: =L21*M21 -> 219629.81 | O21: =SUM(L$3:L21) -> -187672.63 | P21: =SUM(L$3:L21)-SUM(K$3:K21) -> -187672.63 | Q21: =SUM(N$3:N21) -> -5080935.9 | R21: =IF(AND(O21>=0,O20<0),A21-1-O20/L21,0) -> 0 | S21: =IF(AND(P21>=0,P20<0),A21-1-P20/J21,0) -> 0 | T21: =IF(AND(Q21>=0,Q20<0),A21-1-Q20/N21,0) -> 0
A22: 19 | B22: Operating | C22: =0 -> 0 | D22: =Inputs!B4*Inputs!B10*12*(1+Inputs!B11)^(A22-Inputs!B18) -> 1092188.3 | E22: =Inputs!B12 -> 0.95 | F22: =D22*E22 -> 1037578.9 | G22: =F22*Inputs!B13 -> 259394.72 | H22: =F22-G22 -> 778184.17 | I22: =Inputs!B4*Inputs!B14*(1+Inputs!B11)^(A22-Inputs!B18) -> 21003.621 | J22: =H22-I22 -> 757180.55 | K22: =0 -> 0 | L22: =C22+J22+K22 -> 757180.55 | M22: =1/(1+Inputs!B15)^A22 -> 0.27650833 | N22: =L22*M22 -> 209366.73 | O22: =SUM(L$3:L22) -> 569507.92 | P22: =SUM(L$3:L22)-SUM(K$3:K22) -> 569507.92 | Q22: =SUM(N$3:N22) -> -4871569.2 | R22: =IF(AND(O22>=0,O21<0),A22-1-O21/L22,0) -> 18.247857 | S22: =IF(AND(P22>=0,P21<0),A22-1-P21/J22,0) -> 18.247857 | T22: =IF(AND(Q22>=0,Q21<0),A22-1-Q21/N22,0) -> 0
A23: 20 | B23: Operating | C23: =0 -> 0 | D23: =Inputs!B4*Inputs!B10*12*(1+Inputs!B11)^(A23-Inputs!B18) -> 1114032.1 | E23: =Inputs!B12 -> 0.95 | F23: =D23*E23 -> 1058330.5 | G23: =F23*Inputs!B13 -> 264582.62 | H23: =F23-G23 -> 793747.85 | I23: =Inputs!B4*Inputs!B14*(1+Inputs!B11)^(A23-Inputs!B18) -> 21423.694 | J23: =H23-I23 -> 772324.16 | K23: =0 -> 0 | L23: =C23+J23+K23 -> 772324.16 | M23: =1/(1+Inputs!B15)^A23 -> 0.258419 | N23: =L23*M23 -> 199583.24 | O23: =SUM(L$3:L23) -> 1341832.1 | P23: =SUM(L$3:L23)-SUM(K$3:K23) -> 1341832.1 | Q23: =SUM(N$3:N23) -> -4671985.9 | R23: =IF(AND(O23>=0,O22<0),A23-1-O22/L23,0) -> 0 | S23: =IF(AND(P23>=0,P22<0),A23-1-P22/J23,0) -> 0 | T23: =IF(AND(Q23>=0,Q22<0),A23-1-Q22/N23,0) -> 0
A24: 21 | B24: Operating | C24: =0 -> 0 | D24: =Inputs!B4*Inputs!B10*12*(1+Inputs!B11)^(A24-Inputs!B18) -> 1136312.7 | E24: =Inputs!B12 -> 0.95 | F24: =D24*E24 -> 1079497.1 | G24: =F24*Inputs!B13 -> 269874.27 | H24: =F24-G24 -> 809622.81 | I24: =Inputs!B4*Inputs!B14*(1+Inputs!B11)^(A24-Inputs!B18) -> 21852.168 | J24: =H24-I24 -> 787770.64 | K24: =0 -> 0 | L24: =C24+J24+K24 -> 787770.64 | M24: =1/(1+Inputs!B15)^A24 -> 0.24151309 | N24: =L24*M24 -> 190256.92 | O24: =SUM(L$3:L24) -> 2129602.7 | P24: =SUM(L$3:L24)-SUM(K$3:K24) -> 2129602.7 | Q24: =SUM(N$3:N24) -> -4481729 | R24: =IF(AND(O24>=0,O23<0),A24-1-O23/L24,0) -> 0 | S24: =IF(AND(P24>=0,P23<0),A24-1-P23/J24,0) -> 0 | T24: =IF(AND(Q24>=0,Q23<0),A24-1-Q23/N24,0) -> 0
A25: 22 | B25: Operating | C25: =0 -> 0 | D25: =Inputs!B4*Inputs!B10*12*(1+Inputs!B11)^(A25-Inputs!B18) -> 1159039 | E25: =Inputs!B12 -> 0.95 | F25: =D25*E25 -> 1101087 | G25: =F25*Inputs!B13 -> 275271.76 | H25: =F25-G25 -> 825815.27 | I25: =Inputs!B4*Inputs!B14*(1+Inputs!B11)^(A25-Inputs!B18) -> 22289.211 | J25: =H25-I25 -> 803526.05 | K25: =0 -> 0 | L25: =C25+J25+K25 -> 803526.05 | M25: =1/(1+Inputs!B15)^A25 -> 0.22571317 | N25: =L25*M25 -> 181366.41 | O25: =SUM(L$3:L25) -> 2933128.8 | P25: =SUM(L$3:L25)-SUM(K$3:K25) -> 2933128.8 | Q25: =SUM(N$3:N25) -> -4300362.6 | R25: =IF(AND(O25>=0,O24<0),A25-1-O24/L25,0) -> 0 | S25: =IF(AND(P25>=0,P24<0),A25-1-P24/J25,0) -> 0 | T25: =IF(AND(Q25>=0,Q24<0),A25-1-Q24/N25,0) -> 0
A26: 23 | B26: Operating | C26: =0 -> 0 | D26: =Inputs!B4*Inputs!B10*12*(1+Inputs!B11)^(A26-Inputs!B18) -> 1182219.7 | E26: =Inputs!B12 -> 0.95 | F26: =D26*E26 -> 1123108.8 | G26: =F26*Inputs!B13 -> 280777.19 | H26: =F26-G26 -> 842331.57 | I26: =Inputs!B4*Inputs!B14*(1+Inputs!B11)^(A26-Inputs!B18) -> 22734.995 | J26: =H26-I26 -> 819596.58 | K26: =0 -> 0 | L26: =C26+J26+K26 -> 819596.58 | M26: =1/(1+Inputs!B15)^A26 -> 0.21094688 | N26: =L26*M26 -> 172891.34 | O26: =SUM(L$3:L26) -> 3752725.3 | P26: =SUM(L$3:L26)-SUM(K$3:K26) -> 3752725.3 | Q26: =SUM(N$3:N26) -> -4127471.3 | R26: =IF(AND(O26>=0,O25<0),A26-1-O25/L26,0) -> 0 | S26: =IF(AND(P26>=0,P25<0),A26-1-P25/J26,0) -> 0 | T26: =IF(AND(Q26>=0,Q25<0),A26-1-Q25/N26,0) -> 0
A27: 24 | B27: Operating | C27: =0 -> 0 | D27: =Inputs!B4*Inputs!B10*12*(1+Inputs!B11)^(A27-Inputs!B18) -> 1205864.1 | E27: =Inputs!B12 -> 0.95 | F27: =D27*E27 -> 1145570.9 | G27: =F27*Inputs!B13 -> 286392.73 | H27: =F27-G27 -> 859178.2 | I27: =Inputs!B4*Inputs!B14*(1+Inputs!B11)^(A27-Inputs!B18) -> 23189.695 | J27: =H27-I27 -> 835988.51 | K27: =0 -> 0 | L27: =C27+J27+K27 -> 835988.51 | M27: =1/(1+Inputs!B15)^A27 -> 0.19714662 | N27: =L27*M27 -> 164812.31 | O27: =SUM(L$3:L27) -> 4588713.9 | P27: =SUM(L$3:L27)-SUM(K$3:K27) -> 4588713.9 | Q27: =SUM(N$3:N27) -> -3962658.9 | R27: =IF(AND(O27>=0,O26<0),A27-1-O26/L27,0) -> 0 | S27: =IF(AND(P27>=0,P26<0),A27-1-P26/J27,0) -> 0 | T27: =IF(AND(Q27>=0,Q26<0),A27-1-Q26/N27,0) -> 0
A28: 25 | B28: Operating | C28: =0 -> 0 | D28: =Inputs!B4*Inputs!B10*12*(1+Inputs!B11)^(A28-Inputs!B18) -> 1229981.4 | E28: =Inputs!B12 -> 0.95 | F28: =D28*E28 -> 1168482.4 | G28: =F28*Inputs!B13 -> 292120.59 | H28: =F28-G28 -> 876361.77 | I28: =Inputs!B4*Inputs!B14*(1+Inputs!B11)^(A28-Inputs!B18) -> 23653.489 | J28: =H28-I28 -> 852708.28 | K28: =0 -> 0 | L28: =C28+J28+K28 -> 852708.28 | M28: =1/(1+Inputs!B15)^A28 -> 0.18424918 | N28: =L28*M28 -> 157110.8 | O28: =SUM(L$3:L28) -> 5441422.1 | P28: =SUM(L$3:L28)-SUM(K$3:K28) -> 5441422.1 | Q28: =SUM(N$3:N28) -> -3805548.1 | R28: =IF(AND(O28>=0,O27<0),A28-1-O27/L28,0) -> 0 | S28: =IF(AND(P28>=0,P27<0),A28-1-P27/J28,0) -> 0 | T28: =IF(AND(Q28>=0,Q27<0),A28-1-Q27/N28,0) -> 0
A29: 26 | B29: Operating | C29: =0 -> 0 | D29: =Inputs!B4*Inputs!B10*12*(1+Inputs!B11)^(A29-Inputs!B18) -> 1254581.1 | E29: =Inputs!B12 -> 0.95 | F29: =D29*E29 -> 1191852 | G29: =F29*Inputs!B13 -> 297963 | H29: =F29-G29 -> 893889 | I29: =Inputs!B4*Inputs!B14*(1+Inputs!B11)^(A29-Inputs!B18) -> 24126.559 | J29: =H29-I29 -> 869762.44 | K29: =0 -> 0 | L29: =C29+J29+K29 -> 869762.44 | M29: =1/(1+Inputs!B15)^A29 -> 0.17219549 | N29: =L29*M29 -> 149769.17 | O29: =SUM(L$3:L29) -> 6311184.6 | P29: =SUM(L$3:L29)-SUM(K$3:K29) -> 6311184.6 | Q29: =SUM(N$3:N29) -> -3655779 | R29: =IF(AND(O29>=0,O28<0),A29-1-O28/L29,0) -> 0 | S29: =IF(AND(P29>=0,P28<0),A29-1-P28/J29,0) -> 0 | T29: =IF(AND(Q29>=0,Q28<0),A29-1-Q28/N29,0) -> 0
A30: 27 | B30: Operating | C30: =0 -> 0 | D30: =Inputs!B4*Inputs!B10*12*(1+Inputs!B11)^(A30-Inputs!B18) -> 1279672.7 | E30: =Inputs!B12 -> 0.95 | F30: =D30*E30 -> 1215689 | G30: =F30*Inputs!B13 -> 303922.26 | H30: =F30-G30 -> 911766.78 | I30: =Inputs!B4*Inputs!B14*(1+Inputs!B11)^(A30-Inputs!B18) -> 24609.09 | J30: =H30-I30 -> 887157.69 | K30: =0 -> 0 | L30: =C30+J30+K30 -> 887157.69 | M30: =1/(1+Inputs!B15)^A30 -> 0.16093037 | N30: =L30*M30 -> 142770.61 | O30: =SUM(L$3:L30) -> 7198342.3 | P30: =SUM(L$3:L30)-SUM(K$3:K30) -> 7198342.3 | Q30: =SUM(N$3:N30) -> -3513008.4 | R30: =IF(AND(O30>=0,O29<0),A30-1-O29/L30,0) -> 0 | S30: =IF(AND(P30>=0,P29<0),A30-1-P29/J30,0) -> 0 | T30: =IF(AND(Q30>=0,Q29<0),A30-1-Q29/N30,0) -> 0
A31: 28 | B31: Operating | C31: =0 -> 0 | D31: =Inputs!B4*Inputs!B10*12*(1+Inputs!B11)^(A31-Inputs!B18) -> 1305266.1 | E31: =Inputs!B12 -> 0.95 | F31: =D31*E31 -> 1240002.8 | G31: =F31*Inputs!B13 -> 310000.71 | H31: =F31-G31 -> 930002.12 | I31: =Inputs!B4*Inputs!B14*(1+Inputs!B11)^(A31-Inputs!B18) -> 25101.272 | J31: =H31-I31 -> 904900.85 | K31: =0 -> 0 | L31: =C31+J31+K31 -> 904900.85 | M31: =1/(1+Inputs!B15)^A31 -> 0.15040221 | N31: =L31*M31 -> 136099.09 | O31: =SUM(L$3:L31) -> 8103243.1 | P31: =SUM(L$3:L31)-SUM(K$3:K31) -> 8103243.1 | Q31: =SUM(N$3:N31) -> -3376909.3 | R31: =IF(AND(O31>=0,O30<0),A31-1-O30/L31,0) -> 0 | S31: =IF(AND(P31>=0,P30<0),A31-1-P30/J31,0) -> 0 | T31: =IF(AND(Q31>=0,Q30<0),A31-1-Q30/N31,0) -> 0
A32: 29 | B32: Operating | C32: =0 -> 0 | D32: =Inputs!B4*Inputs!B10*12*(1+Inputs!B11)^(A32-Inputs!B18) -> 1331371.5 | E32: =Inputs!B12 -> 0.95 | F32: =D32*E32 -> 1264802.9 | G32: =F32*Inputs!B13 -> 316200.72 | H32: =F32-G32 -> 948602.16 | I32: =Inputs!B4*Inputs!B14*(1+Inputs!B11)^(A32-Inputs!B18) -> 25603.297 | J32: =H32-I32 -> 922998.86 | K32: =0 -> 0 | L32: =C32+J32+K32 -> 922998.86 | M32: =1/(1+Inputs!B15)^A32 -> 0.14056282 | N32: =L32*M32 -> 129739.32 | O32: =SUM(L$3:L32) -> 9026242 | P32: =SUM(L$3:L32)-SUM(K$3:K32) -> 9026242 | Q32: =SUM(N$3:N32) -> -3247170 | R32: =IF(AND(O32>=0,O31<0),A32-1-O31/L32,0) -> 0 | S32: =IF(AND(P32>=0,P31<0),A32-1-P31/J32,0) -> 0 | T32: =IF(AND(Q32>=0,Q31<0),A32-1-Q31/N32,0) -> 0
A33: 30 | B33: Operating | C33: =0 -> 0 | D33: =Inputs!B4*Inputs!B10*12*(1+Inputs!B11)^(A33-Inputs!B18) -> 1357998.9 | E33: =Inputs!B12 -> 0.95 | F33: =D33*E33 -> 1290098.9 | G33: =F33*Inputs!B13 -> 322524.73 | H33: =F33-G33 -> 967574.2 | I33: =Inputs!B4*Inputs!B14*(1+Inputs!B11)^(A33-Inputs!B18) -> 26115.363 | J33: =H33-I33 -> 941458.84 | K33: =0 -> 0 | L33: =C33+J33+K33 -> 941458.84 | M33: =1/(1+Inputs!B15)^A33 -> 0.13136712 | N33: =L33*M33 -> 123676.73 | O33: =SUM(L$3:L33) -> 9967700.8 | P33: =SUM(L$3:L33)-SUM(K$3:K33) -> 9967700.8 | Q33: =SUM(N$3:N33) -> -3123493.2 | R33: =IF(AND(O33>=0,O32<0),A33-1-O32/L33,0) -> 0 | S33: =IF(AND(P33>=0,P32<0),A33-1-P32/J33,0) -> 0 | T33: =IF(AND(Q33>=0,Q32<0),A33-1-Q32/N33,0) -> 0
A34: 31 | B34: Operating | C34: =0 -> 0 | D34: =Inputs!B4*Inputs!B10*12*(1+Inputs!B11)^(A34-Inputs!B18) -> 1385158.9 | E34: =Inputs!B12 -> 0.95 | F34: =D34*E34 -> 1315900.9 | G34: =F34*Inputs!B13 -> 328975.23 | H34: =F34-G34 -> 986925.69 | I34: =Inputs!B4*Inputs!B14*(1+Inputs!B11)^(A34-Inputs!B18) -> 26637.67 | J34: =H34-I34 -> 960288.02 | K34: =H34*(1+Inputs!B11)/Inputs!B16*(1-Inputs!B17) -> 17936926 | L34: =C34+J34+K34 -> 18897214 | M34: =1/(1+Inputs!B15)^A34 -> 0.12277301 | N34: =L34*M34 -> 2320067.8 | O34: =SUM(L$3:L34) -> 28864915 | P34: =SUM(L$3:L34)-SUM(K$3:K34) -> 10927989 | Q34: =SUM(N$3:N34) -> -803425.46 | R34: =IF(AND(O34>=0,O33<0),A34-1-O33/L34,0) -> 0 | S34: =IF(AND(P34>=0,P33<0),A34-1-P33/J34,0) -> 0 | T34: =IF(AND(Q34>=0,Q33<0),A34-1-Q33/N34,0) -> 0

Sheet Rent sensitivity
A1: ILLUSTRATIVE PRICE RESPONSE — NOT EMPIRICAL VUB DATA
A2: Rent increase | B2: Monthly rent EUR | C2: Annual departures | D2: Incremental departures | E2: Occupancy proxy | F2: NPV EUR
A3: 0 | B3: =Inputs!B10*(1+A3) -> 650 | C3: =MIN(1,MAX(0,Inputs!B23+A3*Inputs!B24)) -> 0.08 | D3: =C3-Inputs!B23 -> 0 | E3: =MAX(0,Inputs!B12-D3) -> 0.95 | F3: =Overview!B5+(B3*E3/(Inputs!B10*Inputs!B12)-1)*(SUM('Cash flow'!N5:N34)+SUMPRODUCT('Cash flow'!I5:I34,'Cash flow'!M5:M34)) -> -803425.46
A4: 0.025 | B4: =Inputs!B10*(1+A4) -> 666.25 | C4: =MIN(1,MAX(0,Inputs!B23+A4*Inputs!B24)) -> 0.08375 | D4: =C4-Inputs!B23 -> 0.00375 | E4: =MAX(0,Inputs!B12-D4) -> 0.94625 | F4: =Overview!B5+(B4*E4/(Inputs!B10*Inputs!B12)-1)*(SUM('Cash flow'!N5:N34)+SUMPRODUCT('Cash flow'!I5:I34,'Cash flow'!M5:M34)) -> -591409.3
A5: 0.05 | B5: =Inputs!B10*(1+A5) -> 682.5 | C5: =MIN(1,MAX(0,Inputs!B23+A5*Inputs!B24)) -> 0.0875 | D5: =C5-Inputs!B23 -> 0.0075 | E5: =MAX(0,Inputs!B12-D5) -> 0.9425 | F5: =Overview!B5+(B5*E5/(Inputs!B10*Inputs!B12)-1)*(SUM('Cash flow'!N5:N34)+SUMPRODUCT('Cash flow'!I5:I34,'Cash flow'!M5:M34)) -> -381390.14
A6: 0.075 | B6: =Inputs!B10*(1+A6) -> 698.75 | C6: =MIN(1,MAX(0,Inputs!B23+A6*Inputs!B24)) -> 0.09125 | D6: =C6-Inputs!B23 -> 0.01125 | E6: =MAX(0,Inputs!B12-D6) -> 0.93875 | F6: =Overview!B5+(B6*E6/(Inputs!B10*Inputs!B12)-1)*(SUM('Cash flow'!N5:N34)+SUMPRODUCT('Cash flow'!I5:I34,'Cash flow'!M5:M34)) -> -173368
A7: 0.1 | B7: =Inputs!B10*(1+A7) -> 715 | C7: =MIN(1,MAX(0,Inputs!B23+A7*Inputs!B24)) -> 0.095 | D7: =C7-Inputs!B23 -> 0.015 | E7: =MAX(0,Inputs!B12-D7) -> 0.935 | F7: =Overview!B5+(B7*E7/(Inputs!B10*Inputs!B12)-1)*(SUM('Cash flow'!N5:N34)+SUMPRODUCT('Cash flow'!I5:I34,'Cash flow'!M5:M34)) -> 32657.126
A8: 0.15 | B8: =Inputs!B10*(1+A8) -> 747.5 | C8: =MIN(1,MAX(0,Inputs!B23+A8*Inputs!B24)) -> 0.1025 | D8: =C8-Inputs!B23 -> 0.0225 | E8: =MAX(0,Inputs!B12-D8) -> 0.9275 | F8: =Overview!B5+(B8*E8/(Inputs!B10*Inputs!B12)-1)*(SUM('Cash flow'!N5:N34)+SUMPRODUCT('Cash flow'!I5:I34,'Cash flow'!M5:M34)) -> 438716.35
A9: 0.2 | B9: =Inputs!B10*(1+A9) -> 780 | C9: =MIN(1,MAX(0,Inputs!B23+A9*Inputs!B24)) -> 0.11 | D9: =C9-Inputs!B23 -> 0.03 | E9: =MAX(0,Inputs!B12-D9) -> 0.92 | F9: =Overview!B5+(B9*E9/(Inputs!B10*Inputs!B12)-1)*(SUM('Cash flow'!N5:N34)+SUMPRODUCT('Cash flow'!I5:I34,'Cash flow'!M5:M34)) -> 836787.52
A10: 0.25 | B10: =Inputs!B10*(1+A10) -> 812.5 | C10: =MIN(1,MAX(0,Inputs!B23+A10*Inputs!B24)) -> 0.1175 | D10: =C10-Inputs!B23 -> 0.0375 | E10: =MAX(0,Inputs!B12-D10) -> 0.9125 | F10: =Overview!B5+(B10*E10/(Inputs!B10*Inputs!B12)-1)*(SUM('Cash flow'!N5:N34)+SUMPRODUCT('Cash flow'!I5:I34,'Cash flow'!M5:M34)) -> 1226870.6
A11: 0.3 | B11: =Inputs!B10*(1+A11) -> 845 | C11: =MIN(1,MAX(0,Inputs!B23+A11*Inputs!B24)) -> 0.125 | D11: =C11-Inputs!B23 -> 0.045 | E11: =MAX(0,Inputs!B12-D11) -> 0.905 | F11: =Overview!B5+(B11*E11/(Inputs!B10*Inputs!B12)-1)*(SUM('Cash flow'!N5:N34)+SUMPRODUCT('Cash flow'!I5:I34,'Cash flow'!M5:M34)) -> 1608965.7
A14: Interpretation | B14: One-time rent uplift at opening; normal annual growth thereafter. Every incremental departure assumed to cause one full year of vacancy, without replacement: conservative scenario only.
A15: Academic dropout | B15: Not used as a housing-exit probability; cohorts and denominators differ.

Sheet Variables
A1: VARIABLE DICTIONARY
A2: Variable | B2: Role / scale | C2: Meaning
A3: Rooms | B3: Decision; discrete; ratio | C3: Illustrative scale; no plot secured
A4: Gross floor area per room | B4: Assumption; continuous; ratio | C4: Includes share of circulation and common areas
A5: Construction cost | B5: Assumption; continuous; ratio | C5: Concept estimate, gross of nonrecoverable VAT; obtain quotations
A6: Land / acquisition | B6: Assumption; continuous; ratio | C6: No parcel or offer secured
A7: Professional / permit fees | B7: Assumption; continuous; ratio | C7: Architect, studies, permit; gross cost assumption
A8: Contingency | B8: Assumption; continuous; ratio | C8: No double counting with operating reserve
A9: Monthly room rent | B9: Decision; continuous; ratio | C9: EUR650 private new-build rent assumption, excluding utilities. S10: VUB standard room 2026–2027 EUR449.30 including listed costs; S2 historical private average EUR550. Premium and achievable rent require local comparables.
A10: Annual rent growth | B10: Assumption; continuous; ratio | C10: Subject to lawful indexation and lease provisions
A11: Stabilised occupancy | B11: Assumption; continuous; ratio | C11: Includes vacancy and replacement after departures
A12: Operating expense share | B12: Assumption; continuous; ratio | C12: Management, repairs, insurance, property tax, owner utilities; excludes debt and income tax
A13: Annual capital reserve | B13: Assumption; continuous; ratio | C13: Inflates at annual rent growth
... A38: Year | B38: Index; discrete; interval | C38: Relative annual dates from investment start

Sheet Regulations
A1: BRUSSELS REGULATORY DUE DILIGENCE
A2: Topic | B2: Requirement / action | C2: Model implication | D2: Source
A3: Planning and location | B3: Search near VUB Main Campus, Pleinlaan 2, 1050 Brussels, in Ixelles / Etterbeek. No parcel secured. Verify ownership, land use, planning permit, municipal conditions and any campus agreement. | C3: 2-year development estimate includes approvals and construction; illustrative, not confirmed. No entitlement to build on VUB land. | D3: A1; municipality / urban.brussels review required
A4: Housing quality from 2026 | B4: Apply Brussels safety, sanitation and equipment standards effective 2026-01-01. Architect must validate private room area, daylight, ventilation, sanitary/kitchen capacity and common spaces against applicable rules. | C4: 28 m² gross per room includes circulation and shared spaces; it does not demonstrate minimum compliant net area. | D4: S6
A5: Rent and reference rent | B5: Include required reference rent. Since 2025-05-01 landlords must avoid excessive rents; >20% above reference is rebuttably presumed excessive, and quality defects can matter below this threshold. | C5: EUR650 is an assumption, not legal clearance. Establish the relevant room category and lawful rent before pricing; rent-reduction risk not quantified. | D5: S5
A6: Student tenancy | B6: Use a compliant Brussels student lease, verify student status, notices, deposit, disclosures and registration at letting. Obtain current specialist advice on the applicable regime. | C6: Model assumes 12 chargeable months and 95% occupancy; early termination / summer voids could reduce income. | D6: S8; contract review required
A7: Indexation / energy | B7: Check registration and EPB conditions and the current lawful indexation mechanism before each annual adjustment. | C7: 2% yearly growth is a forecast, not a guaranteed legal increase. Tax, EPB and retrofit impacts require site review. | D7: S5 / S8; detailed indexation check pending
A8: Fire and access | B8: Validate smoke detection, fire-service requirements, evacuation, accessibility and EPB with architect and competent authority. | C8: Fees and contingency are preliminary; final scope may increase cost and delay opening. | D8: S6; project-specific approval required
A9: Quality label | B9: Consider the Brussels student-housing quality label: 5-year renewable validity; compliance declaration, student lease/commitment and valid EPB among application documents. | C9: Label may help marketing; not a substitute for planning permission or compliant construction. | D9: S7
A10: Student housing minimum surface | B10: 2026 housing-code rules: student dwelling minimum 12 m² for one person, 18 m² for two. Habitable rooms must cover at least 70% of dwelling area. Collective common rooms counted pro rata by maximum residents using them. | C10: Do not equate 12 m² with a universal private-bedroom minimum. Architect must calculate qualifying area and apply stricter planning/fire rules; 28 m² gross allocation is not compliance proof. | D10: S12, pp.13–14, right-hand column

Sheet Sources
A1: SOURCES AND RESEARCH LOG
A2: ID | B2: Organisation / title | C2: URL | D2: Period / access | E2: Evidence and limits
A3: S1 | B3: VUB: Facts & Figures 2024–2025 | C3: https://www.vub.be/en/news/vub-launches-facts-figures-2024-2025 | D3: Published 2025-12-16; accessed 2026-10-14 | E3: 24,199 students; 24.38% from abroad; 151 nationalities. University-wide, not a local housing-demand count.
A4: S2 | B4: VUB: 2025 study cost sheet | C4: https://www.vub.be/sites/default/files/2025-03/2025_Hoeveel_kost_studeren_kostenplaatje_1BA_Business_economics_ENG_0.pdf | D4: 2025 sheet; housing benchmark Brik 2023; accessed 2026-10-14 | E4: Private room average EUR550/month excluding charges; VUB standard room EUR408.30 including costs. Historical benchmark, not 2026 market evidence.
A5: S3 | B5: Belgian FPS Foreign Affairs: student sponsorship | C5: https://verenigdkoninkrijk.diplomatie.belgium.be/en/travel-belgium/financial-guarantee-student-sponsorship | D5: Academic year 2026–2027; accessed 2026-10-14 | E5: Student means-of-subsistence requirement EUR1,062 net/month; EUR12,744 annual equivalent. Applies to relevant third-country students, not all VUB students or average wages.
A6: S4 | B6: Student At Work / Belgian social security: hours package | C6: https://www.studentatwork.be/en/hours-package-and-impact.html | D6: Since 2025-01-01; accessed 2026-10-14 | E6: 650 annual hours with reduced social contributions; student contribution 2.71%; may work beyond quota with ordinary contributions. Not guaranteed work or income.
A7: S5 | B7: Brussels Housing: reference rents | C7: https://be.brussels/fr/logement/location/bail-dhabitation/loyers-de-reference | D7: Rule effective 2025-05-01; accessed 2026-10-14 | E7: Reference rent must be in residential leases. Rent over reference by more than 20% presumed excessive, rebuttable by specific comforts; defects can also establish excessiveness. Verify room applicability.
A8: S6 | B8: Brussels Housing: quality and safety | C8: https://be.brussels/fr/logement/location/conformite-logement/normes-et-securite | D8: 2026 standards; accessed 2026-10-14 | E8: Official page links applicable standards and comparison before/after 2026-01-01; 2025 smoke detection rules. Design must be checked against actual legal text.
A9: S7 | B9: Brussels Housing: student housing quality label | C9: https://be.brussels/fr/logement/location/conformite-logement/label-logement-etudiant | D9: Accessed 2026-10-14 | E9: Quality label valid 5 years, renewable; application involves compliance declaration, student lease or commitment, and valid EPB certificate. Does not replace permits.
A10: S8 | B10: Brussels Housing: rental process | C10: https://be.brussels/nl/huisvesting/huren-en-verhuren/de-verschillende-stappen-van-het-huren-en-verhuren | D10: Accessed 2026-10-14 | E10: Housing quality, disclosures and registration obligations; check current process and documents before leasing.
A11: S9 | B11: Statistics Flanders: dropout in higher education | C11: https://www.vlaanderen.be/statistiek-vlaanderen/onderwijs-en-vorming/drop-out-in-het-hoger-onderwijs | D11: Published 2026-03-31; cohort 2023–2024; accessed 2026-10-14 | E11: 16% first-year bachelor dropout (8,881 entrants); figure provisional. Flemish academic and professional bachelors, not VUB-specific. Obtain VUB cohort data before treating as a VUB estimate.
A12: A1 | B12: Author scenario assumptions | D12: 2026-10-14 | E12: Construction costs, acquisition, expenses, timing, discount rate, exit cap rate, occupancy, student resources and price response are unsourced illustrative assumptions. Obtain parcel, cost, tax and letting evidence before investment.
A13: S10 | B13: VUB: current practical housing information | C13: https://www.vub.be/en/studying-vub/practical-info-for-students/student-housing/practical-housing-information | D13: 2026–2027; updated 2026-09-18; accessed 2026-10-14 | E13: Standard VUB room EUR449.30/month including energy, internet, fire insurance, repairs and communal cleaning. Demand exceeds availability; allocation conditions apply. Not a private new-build market comparable.
A14: S11 | B14: FPS Employment: student employment remuneration | C14: https://emploi.belgique.be/fr/themes/contrats-de-travail/contrats-de-travail-particuliers/contrat-doccupation-detudiants | D14: Rates effective 2026-07-01; accessed 2026-10-14 | E14: Sector collective agreement governs pay. Where not applicable, age-adjusted interprofessional minimum; indicative hourly rates at 38h/week: age18 EUR10.7158;19 EUR11.5297;20 EUR12.2079;21 EUR13.5644. Annual student income depends on actual hours.
A15: S12 | B15: Brussels Housing: comparison of minimum requirements | C15: https://admin.be.brussels/sites/default/files/2025-06/Tableau%20comparatif%20AGRBC%202003-2023%20FR.pdf | D15: 2026 rules, right-hand column; pp.13–14; accessed 2026-10-14 | E15: Student housing surface: 12 m² for one person, 18 m² for two. Habitable rooms at least 70% of dwelling area. Collective common rooms allocated by maximum residents using them. These are housing-code minima; planning/fire rules can be stricter.

Sheet Student budget
A1: STUDENT RESOURCES AND AFFORDABILITY
A2: Item / age | B2: Value / hourly pay EUR | C2: Annual gross EUR | D2: After solidarity contribution EUR | E2: Classification / evidence
A4: Illustrative annual total resources | B4: =Inputs!B21 -> 14000 | E4: Scenario; continuous; ratio. Family support + grants + work; no observed VUB average.
A5: Monthly proof of means | B5: 1062 | E5: S3: 2026–2027 benchmark for relevant non-EU student residence applicants; not wages.
A6: Reduced-contribution annual hours | B6: 650 | E6: S4: count, discrete, ratio; scenario assumes entire quota worked, not guaranteed employment.
A7: Student solidarity contribution | B7: 0.0271 | E7: S4: continuous ratio; 2.71%; tax treatment depends on personal circumstances.
A9: 18 | B9: 10.7158 | C9: =B9*$B$6 -> 6965.27 | D9: =C9*(1-$B$7) -> 6776.5112 | E9: S11: fallback hourly rate effective July 2026, indicative 38h-week basis; sector CBA may apply. Gross annual pay assumes rate unchanged for all 650h; D is before any income tax.
A10: 19 | B10: 11.5297 | C10: =B10*$B$6 -> 7494.305 | D10: =C10*(1-$B$7) -> 7291.2093 | E10: S11: fallback hourly rate effective July 2026, indicative 38h-week basis; sector CBA may apply. Gross annual pay assumes rate unchanged for all 650h; D is before any income tax.
A11: 20 | B11: 12.2079 | C11: =B11*$B$6 -> 7935.135 | D11: =C11*(1-$B$7) -> 7720.0928 | E11: S11: fallback hourly rate effective July 2026, indicative 38h-week basis; sector CBA may apply. Gross annual pay assumes rate unchanged for all 650h; D is before any income tax.
A12: 21 | B12: 13.5644 | C12: =B12*$B$6 -> 8816.86 | D12: =C12*(1-$B$7) -> 8577.9231 | E12: S11: fallback hourly rate effective July 2026, indicative 38h-week basis; sector CBA may apply. Gross annual pay assumes rate unchanged for all 650h; D is before any income tax.
A15: VUB standard rent incl. listed costs | B15: 449.3 | E15: S10: EUR/month; continuous ratio; 2026–2027; subsidised university offering with eligibility conditions.
A16: Project rent excl. utilities | B16: =Inputs!B10 -> 650 | E16: Decision; continuous ratio; EUR/month.
A17: Rent share of proof-of-means amount | B17: =B16/B5 -> 0.61205273 | E17: Derived; continuous ratio; excludes utilities, tuition and other living expenses.
A19: Minimum annual earnings | B19: No guaranteed amount: a student with no paid work may earn EUR0. Actual average VUB earnings were not established.

Sheet Risk sensitivity
A1: NPV SENSITIVITY — required return versus exit capitalisation
A2: Discount rate / exit cap | B2: 0.045 | C2: 0.055 | D2: 0.065
A3: 0.05 | B3: =NPV($A3,'Cash flow'!L4:L34)+'Cash flow'!L3+('Cash flow'!H34*(1+Inputs!B11)/B$2*(1-Inputs!B17)-'Cash flow'!K34)/(1+$A3)^31 -> 4012963 | C3: =NPV($A3,'Cash flow'!L4:L34)+'Cash flow'!L3+('Cash flow'!H34*(1+Inputs!B11)/C$2*(1-Inputs!B17)-'Cash flow'!K34)/(1+$A3)^31 -> 3134613.7 | D3: =NPV($A3,'Cash flow'!L4:L34)+'Cash flow'!L3+('Cash flow'!H34*(1+Inputs!B11)/D$2*(1-Inputs!B17)-'Cash flow'!K34)/(1+$A3)^31 -> 2526525.8
A4: 0.06 | B4: =NPV($A4,'Cash flow'!L4:L34)+'Cash flow'!L3+('Cash flow'!H34*(1+Inputs!B11)/B$2*(1-Inputs!B17)-'Cash flow'!K34)/(1+$A4)^31 -> 1583754.6 | C4: =NPV($A4,'Cash flow'!L4:L34)+'Cash flow'!L3+('Cash flow'!H34*(1+Inputs!B11)/C$2*(1-Inputs!B17)-'Cash flow'!K34)/(1+$A4)^31 -> 929037.5 | D4: =NPV($A4,'Cash flow'!L4:L34)+'Cash flow'!L3+('Cash flow'!H34*(1+Inputs!B11)/D$2*(1-Inputs!B17)-'Cash flow'!K34)/(1+$A4)^31 -> 475771.83
A5: 0.07 | B5: =NPV($A5,'Cash flow'!L4:L34)+'Cash flow'!L3+('Cash flow'!H34*(1+Inputs!B11)/B$2*(1-Inputs!B17)-'Cash flow'!K34)/(1+$A5)^31 -> -314054.29 | C5: =NPV($A5,'Cash flow'!L4:L34)+'Cash flow'!L3+('Cash flow'!H34*(1+Inputs!B11)/C$2*(1-Inputs!B17)-'Cash flow'!K34)/(1+$A5)^31 -> -803425.46 | D5: =NPV($A5,'Cash flow'!L4:L34)+'Cash flow'!L3+('Cash flow'!H34*(1+Inputs!B11)/D$2*(1-Inputs!B17)-'Cash flow'!K34)/(1+$A5)^31 -> -1142220.9
A6: 0.08 | B6: =NPV($A6,'Cash flow'!L4:L34)+'Cash flow'!L3+('Cash flow'!H34*(1+Inputs!B11)/B$2*(1-Inputs!B17)-'Cash flow'!K34)/(1+$A6)^31 -> -1808104.1 | C6: =NPV($A6,'Cash flow'!L4:L34)+'Cash flow'!L3+('Cash flow'!H34*(1+Inputs!B11)/C$2*(1-Inputs!B17)-'Cash flow'!K34)/(1+$A6)^31 -> -2174878.5 | D6: =NPV($A6,'Cash flow'!L4:L34)+'Cash flow'!L3+('Cash flow'!H34*(1+Inputs!B11)/D$2*(1-Inputs!B17)-'Cash flow'!K34)/(1+$A6)^31 -> -2428799.3
A7: 0.09 | B7: =NPV($A7,'Cash flow'!L4:L34)+'Cash flow'!L3+('Cash flow'!H34*(1+Inputs!B11)/B$2*(1-Inputs!B17)-'Cash flow'!K34)/(1+$A7)^31 -> -2993495.7 | C7: =NPV($A7,'Cash flow'!L4:L34)+'Cash flow'!L3+('Cash flow'!H34*(1+Inputs!B11)/C$2*(1-Inputs!B17)-'Cash flow'!K34)/(1+$A7)^31 -> -3269117.8 | D7: =NPV($A7,'Cash flow'!L4:L34)+'Cash flow'!L3+('Cash flow'!H34*(1+Inputs!B11)/D$2*(1-Inputs!B17)-'Cash flow'!K34)/(1+$A7)^31 -> -3459933.1
A10: Break-even opening rent, no extra departures | B10: =Inputs!B10*(1-Overview!B5/(SUM('Cash flow'!N5:N34)+SUMPRODUCT('Cash flow'!I5:I34,'Cash flow'!M5:M34))) -> 701.61261
A12: Interpretation | B12: Discount and exit cap are continuous ratio assumptions; NPV is a derived continuous EUR output. Break-even rent holds occupancy fixed; verify affordability, lawfulness and departures separately.
