Workbook

Sheet Read me
A1: PROJECT XL — student housing near VUB, Brussels
A2: Decision model • illustrative development, not a property valuation
A3: Status | B3: Researched rent guidance; investment costs, student budget and finance remain explicit assumptions. 14 October 2026.
A4: How to use | B4: Edit blue cells on Inputs; Excel recalculates all formulas on opening.
A5: Rent rule | B5: Affordable rent = minimum of student budget, market ceiling and applicable regulatory/comparator ceiling.
A6: Legal caveat | B6: A market average is not a legal rent cap. Reference rent must be obtained for the exact dwelling.
A7: Scenario | B7: Development/major conversion, with land acquisition entered separately.
A8: Model boundaries | B8: Unlevered annual cash flow; debt-service and equity cash flow shown separately; no sale proceeds in payback.
A9: Room choice | B9: Room sizing compares every integer from 12–96 rooms; selects highest recurring cash flow among feasible candidates.
A10: Feasible means | B10: Total cost within budget, positive equity cash flow, DSCR target and assumed site capacity; return target shown separately.
A11: Exclusions | B11: Personal/company income tax, capital gains tax and sale proceeds; acquisition costs and VAT must be validated.
A12: Sources | B12: Source links and dates in Sources; all cost and financing inputs are illustrative unless marked otherwise.

Sheet Inputs
A1: Input | B1: Value | C1: Units | D1: Basis / status
A2: Number of rooms | B2: 40 | C2: rooms | D2: Illustrative baseline
A3: Student monthly housing budget incl. charges | B3: 600 | C3: EUR/month | D3: User can replace with surveyed student budget
A4: Monthly charges paid by student | B4: 100 | C4: EUR/month | D4: Separate from rent; assumed to cover utilities only
A5: Local market rent comparator excl. charges | B5: 500 | C5: EUR/month | D5: Bru Kot room median EUR500 excl. charges; Brussels-wide listing data
A6: Conservative reference-rent planning ceiling | B6: 500 | C6: EUR/month | D6: UNVERIFIED placeholder, NOT a legal cap; replace with address-specific assessment
A7: Chosen base rent excl. charges | B7: 475 | C7: EUR/month | D7: Investor proposal
A8: Occupancy | B8: 0.95 | C8: % | D8: Assumption; all 12 months are billable
A9: Billable months | B9: 12 | C9: months/year | D9: Adjust for 10-month contracts
A10: Land / property acquisition | B10: 900000 | C10: EUR | D10: Land for new build; avoid double counting existing structure
A11: Gross floor area per room incl. common areas | B11: 34 | C11: m²/room | D11: Planning assumption, not minimum legal room area
A12: Build cost per gross m² | B12: 2400 | C12: EUR/m² | D12: Assumed VAT-inclusive; validate with contractor
A13: Furnishing per room | B13: 5000 | C13: EUR/room | D13: Assumption
... A30: Net private room area | B30: 18 | C30: m² | D30: Illustrative design; 12 m² student dwelling minimum is not full planning clearance

Sheet Investment
A1: Measure | B1: Value | C1: Meaning
A2: Affordable base rent | B2: =MAX(0,MIN(Inputs!B3-Inputs!B4,Inputs!B5,Inputs!B6,Inputs!B7)) -> 475 | C2: Student budget and comparator constrained
A3: All-in student monthly payment | B3: =B2+Inputs!B4 -> 575 | C3: Rent + utility charge
A4: Gross floor area | B4: =Inputs!B2*Inputs!B11 -> 1360 | C4: m²
A5: Build cost | B5: =B4*Inputs!B12 -> 3264000 | C5: EUR
A6: Furnishing | B6: =Inputs!B2*Inputs!B13 -> 200000 | C6: EUR
A7: Contingency | B7: =(B5+B6)*Inputs!B15 -> 346400 | C7: EUR
A8: Total project investment | B8: =Inputs!B10+B5+B6+B7+Inputs!B14 -> 4960400 | C8: All-in development capital
A9: Loan | B9: =B8*Inputs!B19 -> 1736140 | C9: EUR
A10: Required equity | B10: =B8-B9 -> 3224260 | C10: EUR
A11: Potential annual base rent | B11: =Inputs!B2*B2*Inputs!B9 -> 228000 | C11: Excludes charges
A12: Collected annual rent | B12: =B11*Inputs!B8 -> 216600 | C12: Vacancy adjusted
A13: Operating expenses | B13: =B12*Inputs!B16 -> 54150 | C13: Year one
A14: Net operating income (NOI) | B14: =B12-B13 -> 162450 | C14: Before debt and income tax
A15: Annual debt service | B15: =IF(B9=0,0,IF(Inputs!B20=0,B9/Inputs!B21,-PMT(Inputs!B20,Inputs!B21,B9))) -> 117083.59 | C15: Principal + interest
A16: Annual equity cash flow | B16: =B14-B15 -> 45366.406 | C16: Before investor income tax
A17: Unlevered net yield | B17: =B14/B8 -> 0.032749375 | C17: NOI / all-in investment
A18: Cash-on-cash equity return | B18: =B16/B10 -> 0.014070331 | C18: Annual equity cash flow / equity
A19: DSCR | B19: =IF(B15=0,999,B14/B15) -> 1.3874702 | C19: NOI / debt service
A20: Static project payback years | B20: =IF(B14>0,B8/B14,999)+Inputs!B28 -> 32.534934 | C20: Includes development delay; no escalation
A21: Static equity payback years | B21: =IF(B16>0,B10/B16,999)+Inputs!B28 -> 73.071533 | C21: Includes development delay; before income tax
A22: Rent needed for required net yield | B22: =B8*Inputs!B25/(Inputs!B2*Inputs!B9*Inputs!B8*(1-Inputs!B16)) -> 652.68421 | C22: Excl. charges; compare with affordable rent
A23: Budget and debt feasibility | B23: =IF(AND(B8<=Inputs!B22,B10<=Inputs!B23,B16>0,B19>=Inputs!B24,Inputs!B2<=Inputs!B29),"PASS","FAIL") -> PASS | C23: Yield target assessed separately
A24: Required net yield met | B24: =IF(B17>=Inputs!B25,"YES","NO") -> NO | C24: Target is not a forecast
A25: NPV excluding terminal value | B25: =NPV(Inputs!B26,'Annual cash flow'!F3:F42)+'Annual cash flow'!F2 -> -2535050.7 | C25: 40-year cash flow range; inactive years set to zero
A26: IRR excluding terminal value | B26: =IFERROR(IRR('Annual cash flow'!F2:F42),"No IRR") -> 0.014088073 | C26: Zero cash flow after horizon
A27: Dynamic project payback | B27: =IFERROR(MATCH(1,'Annual cash flow'!J2:J42,0)-1,"Beyond model horizon") -> 27 | C27: First end-year cumulative unlevered cash flow >= 0
A28: Maximum investment at target yield | B28: =B14/Inputs!B25 -> 3610000
A29: Cost reduction needed for target yield | B29: =MAX(0,B8-B28) -> 1350400
A30: Unlevered yield at ten collected months | B30: =B14*10/Inputs!B9/B8 -> 0.027291146
A31: Legal reference verified? | B31: NO — exact address and dwelling details missing
A32: Dynamic equity payback | B32: =IFERROR(MATCH(1,'Annual cash flow'!L2:L42,0)-1,"Beyond model horizon") -> 32

Sheet Annual cash flow
A1: Year | B1: Operating year | C1: Rent | D1: Operating costs | E1: NOI | F1: Project cash flow | G1: Debt service | H1: Equity cash flow | I1: Cumulative project CF | J1: Payback flag | K1: Cumulative equity CF | L1: Equity payback flag
A2: 0 | B2: =MAX(0,A2-Inputs!B28) -> 0 | C2: =IF(AND(B2>0,B2<=Inputs!B27),Investment!B12*(1+Inputs!B17)^(B2-1),0) -> 0 | D2: =IF(AND(B2>0,B2<=Inputs!B27),Investment!B13*(1+Inputs!B18)^(B2-1),0) -> 0 | E2: =C2-D2 -> 0 | F2: =-Investment!B8 -> -4960400 | G2: =IF(AND(B2>0,B2<=Inputs!B21),Investment!B15,0) -> 0 | H2: =-Investment!B10 -> -3224260 | I2: =F2 -> -4960400 | J2: =IF(I2>=0,1,0) -> 0 | K2: =H2 -> -3224260 | L2: =IF(K2>=0,1,0) -> 0
A3: 1 | B3: =MAX(0,A3-Inputs!B28) -> 0 | C3: =IF(AND(B3>0,B3<=Inputs!B27),Investment!B12*(1+Inputs!B17)^(B3-1),0) -> 0 | D3: =IF(AND(B3>0,B3<=Inputs!B27),Investment!B13*(1+Inputs!B18)^(B3-1),0) -> 0 | E3: =C3-D3 -> 0 | F3: =E3 -> 0 | G3: =IF(AND(B3>0,B3<=Inputs!B21),Investment!B15,0) -> 0 | H3: =E3-G3 -> 0 | I3: =I2+F3 -> -4960400 | J3: =IF(I3>=0,1,0) -> 0 | K3: =K2+H3 -> -3224260 | L3: =IF(K3>=0,1,0) -> 0
A4: 2 | B4: =MAX(0,A4-Inputs!B28) -> 0 | C4: =IF(AND(B4>0,B4<=Inputs!B27),Investment!B12*(1+Inputs!B17)^(B4-1),0) -> 0 | D4: =IF(AND(B4>0,B4<=Inputs!B27),Investment!B13*(1+Inputs!B18)^(B4-1),0) -> 0 | E4: =C4-D4 -> 0 | F4: =E4 -> 0 | G4: =IF(AND(B4>0,B4<=Inputs!B21),Investment!B15,0) -> 0 | H4: =E4-G4 -> 0 | I4: =I3+F4 -> -4960400 | J4: =IF(I4>=0,1,0) -> 0 | K4: =K3+H4 -> -3224260 | L4: =IF(K4>=0,1,0) -> 0
A5: 3 | B5: =MAX(0,A5-Inputs!B28) -> 1 | C5: =IF(AND(B5>0,B5<=Inputs!B27),Investment!B12*(1+Inputs!B17)^(B5-1),0) -> 216600 | D5: =IF(AND(B5>0,B5<=Inputs!B27),Investment!B13*(1+Inputs!B18)^(B5-1),0) -> 54150 | E5: =C5-D5 -> 162450 | F5: =E5 -> 162450 | G5: =IF(AND(B5>0,B5<=Inputs!B21),Investment!B15,0) -> 117083.59 | H5: =E5-G5 -> 45366.406 | I5: =I4+F5 -> -4797950 | J5: =IF(I5>=0,1,0) -> 0 | K5: =K4+H5 -> -3178893.6 | L5: =IF(K5>=0,1,0) -> 0
A6: 4 | B6: =MAX(0,A6-Inputs!B28) -> 2 | C6: =IF(AND(B6>0,B6<=Inputs!B27),Investment!B12*(1+Inputs!B17)^(B6-1),0) -> 220932 | D6: =IF(AND(B6>0,B6<=Inputs!B27),Investment!B13*(1+Inputs!B18)^(B6-1),0) -> 55503.75 | E6: =C6-D6 -> 165428.25 | F6: =E6 -> 165428.25 | G6: =IF(AND(B6>0,B6<=Inputs!B21),Investment!B15,0) -> 117083.59 | H6: =E6-G6 -> 48344.656 | I6: =I5+F6 -> -4632521.8 | J6: =IF(I6>=0,1,0) -> 0 | K6: =K5+H6 -> -3130548.9 | L6: =IF(K6>=0,1,0) -> 0
A7: 5 | B7: =MAX(0,A7-Inputs!B28) -> 3 | C7: =IF(AND(B7>0,B7<=Inputs!B27),Investment!B12*(1+Inputs!B17)^(B7-1),0) -> 225350.64 | D7: =IF(AND(B7>0,B7<=Inputs!B27),Investment!B13*(1+Inputs!B18)^(B7-1),0) -> 56891.344 | E7: =C7-D7 -> 168459.3 | F7: =E7 -> 168459.3 | G7: =IF(AND(B7>0,B7<=Inputs!B21),Investment!B15,0) -> 117083.59 | H7: =E7-G7 -> 51375.702 | I7: =I6+F7 -> -4464062.5 | J7: =IF(I7>=0,1,0) -> 0 | K7: =K6+H7 -> -3079173.2 | L7: =IF(K7>=0,1,0) -> 0
A8: 6 | B8: =MAX(0,A8-Inputs!B28) -> 4 | C8: =IF(AND(B8>0,B8<=Inputs!B27),Investment!B12*(1+Inputs!B17)^(B8-1),0) -> 229857.65 | D8: =IF(AND(B8>0,B8<=Inputs!B27),Investment!B13*(1+Inputs!B18)^(B8-1),0) -> 58313.627 | E8: =C8-D8 -> 171544.03 | F8: =E8 -> 171544.03 | G8: =IF(AND(B8>0,B8<=Inputs!B21),Investment!B15,0) -> 117083.59 | H8: =E8-G8 -> 54460.431 | I8: =I7+F8 -> -4292518.4 | J8: =IF(I8>=0,1,0) -> 0 | K8: =K7+H8 -> -3024712.8 | L8: =IF(K8>=0,1,0) -> 0
A9: 7 | B9: =MAX(0,A9-Inputs!B28) -> 5 | C9: =IF(AND(B9>0,B9<=Inputs!B27),Investment!B12*(1+Inputs!B17)^(B9-1),0) -> 234454.81 | D9: =IF(AND(B9>0,B9<=Inputs!B27),Investment!B13*(1+Inputs!B18)^(B9-1),0) -> 59771.468 | E9: =C9-D9 -> 174683.34 | F9: =E9 -> 174683.34 | G9: =IF(AND(B9>0,B9<=Inputs!B21),Investment!B15,0) -> 117083.59 | H9: =E9-G9 -> 57599.744 | I9: =I8+F9 -> -4117835.1 | J9: =IF(I9>=0,1,0) -> 0 | K9: =K8+H9 -> -2967113.1 | L9: =IF(K9>=0,1,0) -> 0
A10: 8 | B10: =MAX(0,A10-Inputs!B28) -> 6 | C10: =IF(AND(B10>0,B10<=Inputs!B27),Investment!B12*(1+Inputs!B17)^(B10-1),0) -> 239143.9 | D10: =IF(AND(B10>0,B10<=Inputs!B27),Investment!B13*(1+Inputs!B18)^(B10-1),0) -> 61265.755 | E10: =C10-D10 -> 177878.15 | F10: =E10 -> 177878.15 | G10: =IF(AND(B10>0,B10<=Inputs!B21),Investment!B15,0) -> 117083.59 | H10: =E10-G10 -> 60794.553 | I10: =I9+F10 -> -3939956.9 | J10: =IF(I10>=0,1,0) -> 0 | K10: =K9+H10 -> -2906318.5 | L10: =IF(K10>=0,1,0) -> 0
A11: 9 | B11: =MAX(0,A11-Inputs!B28) -> 7 | C11: =IF(AND(B11>0,B11<=Inputs!B27),Investment!B12*(1+Inputs!B17)^(B11-1),0) -> 243926.78 | D11: =IF(AND(B11>0,B11<=Inputs!B27),Investment!B13*(1+Inputs!B18)^(B11-1),0) -> 62797.399 | E11: =C11-D11 -> 181129.38 | F11: =E11 -> 181129.38 | G11: =IF(AND(B11>0,B11<=Inputs!B21),Investment!B15,0) -> 117083.59 | H11: =E11-G11 -> 64045.787 | I11: =I10+F11 -> -3758827.6 | J11: =IF(I11>=0,1,0) -> 0 | K11: =K10+H11 -> -2842272.7 | L11: =IF(K11>=0,1,0) -> 0
A12: 10 | B12: =MAX(0,A12-Inputs!B28) -> 8 | C12: =IF(AND(B12>0,B12<=Inputs!B27),Investment!B12*(1+Inputs!B17)^(B12-1),0) -> 248805.32 | D12: =IF(AND(B12>0,B12<=Inputs!B27),Investment!B13*(1+Inputs!B18)^(B12-1),0) -> 64367.334 | E12: =C12-D12 -> 184437.98 | F12: =E12 -> 184437.98 | G12: =IF(AND(B12>0,B12<=Inputs!B21),Investment!B15,0) -> 117083.59 | H12: =E12-G12 -> 67354.388 | I12: =I11+F12 -> -3574389.6 | J12: =IF(I12>=0,1,0) -> 0 | K12: =K11+H12 -> -2774918.3 | L12: =IF(K12>=0,1,0) -> 0
A13: 11 | B13: =MAX(0,A13-Inputs!B28) -> 9 | C13: =IF(AND(B13>0,B13<=Inputs!B27),Investment!B12*(1+Inputs!B17)^(B13-1),0) -> 253781.42 | D13: =IF(AND(B13>0,B13<=Inputs!B27),Investment!B13*(1+Inputs!B18)^(B13-1),0) -> 65976.517 | E13: =C13-D13 -> 187804.91 | F13: =E13 -> 187804.91 | G13: =IF(AND(B13>0,B13<=Inputs!B21),Investment!B15,0) -> 117083.59 | H13: =E13-G13 -> 70721.311 | I13: =I12+F13 -> -3386584.7 | J13: =IF(I13>=0,1,0) -> 0 | K13: =K12+H13 -> -2704197 | L13: =IF(K13>=0,1,0) -> 0
A14: 12 | B14: =MAX(0,A14-Inputs!B28) -> 10 | C14: =IF(AND(B14>0,B14<=Inputs!B27),Investment!B12*(1+Inputs!B17)^(B14-1),0) -> 258857.05 | D14: =IF(AND(B14>0,B14<=Inputs!B27),Investment!B13*(1+Inputs!B18)^(B14-1),0) -> 67625.93 | E14: =C14-D14 -> 191231.12 | F14: =E14 -> 191231.12 | G14: =IF(AND(B14>0,B14<=Inputs!B21),Investment!B15,0) -> 117083.59 | H14: =E14-G14 -> 74147.526 | I14: =I13+F14 -> -3195353.6 | J14: =IF(I14>=0,1,0) -> 0 | K14: =K13+H14 -> -2630049.5 | L14: =IF(K14>=0,1,0) -> 0
A15: 13 | B15: =MAX(0,A15-Inputs!B28) -> 11 | C15: =IF(AND(B15>0,B15<=Inputs!B27),Investment!B12*(1+Inputs!B17)^(B15-1),0) -> 264034.19 | D15: =IF(AND(B15>0,B15<=Inputs!B27),Investment!B13*(1+Inputs!B18)^(B15-1),0) -> 69316.578 | E15: =C15-D15 -> 194717.61 | F15: =E15 -> 194717.61 | G15: =IF(AND(B15>0,B15<=Inputs!B21),Investment!B15,0) -> 117083.59 | H15: =E15-G15 -> 77634.019 | I15: =I14+F15 -> -3000635.9 | J15: =IF(I15>=0,1,0) -> 0 | K15: =K14+H15 -> -2552415.5 | L15: =IF(K15>=0,1,0) -> 0
A16: 14 | B16: =MAX(0,A16-Inputs!B28) -> 12 | C16: =IF(AND(B16>0,B16<=Inputs!B27),Investment!B12*(1+Inputs!B17)^(B16-1),0) -> 269314.88 | D16: =IF(AND(B16>0,B16<=Inputs!B27),Investment!B13*(1+Inputs!B18)^(B16-1),0) -> 71049.493 | E16: =C16-D16 -> 198265.38 | F16: =E16 -> 198265.38 | G16: =IF(AND(B16>0,B16<=Inputs!B21),Investment!B15,0) -> 117083.59 | H16: =E16-G16 -> 81181.789 | I16: =I15+F16 -> -2802370.6 | J16: =IF(I16>=0,1,0) -> 0 | K16: =K15+H16 -> -2471233.7 | L16: =IF(K16>=0,1,0) -> 0
A17: 15 | B17: =MAX(0,A17-Inputs!B28) -> 13 | C17: =IF(AND(B17>0,B17<=Inputs!B27),Investment!B12*(1+Inputs!B17)^(B17-1),0) -> 274701.17 | D17: =IF(AND(B17>0,B17<=Inputs!B27),Investment!B13*(1+Inputs!B18)^(B17-1),0) -> 72825.73 | E17: =C17-D17 -> 201875.44 | F17: =E17 -> 201875.44 | G17: =IF(AND(B17>0,B17<=Inputs!B21),Investment!B15,0) -> 117083.59 | H17: =E17-G17 -> 84791.849 | I17: =I16+F17 -> -2600495.1 | J17: =IF(I17>=0,1,0) -> 0 | K17: =K16+H17 -> -2386441.8 | L17: =IF(K17>=0,1,0) -> 0
A18: 16 | B18: =MAX(0,A18-Inputs!B28) -> 14 | C18: =IF(AND(B18>0,B18<=Inputs!B27),Investment!B12*(1+Inputs!B17)^(B18-1),0) -> 280195.2 | D18: =IF(AND(B18>0,B18<=Inputs!B27),Investment!B13*(1+Inputs!B18)^(B18-1),0) -> 74646.373 | E18: =C18-D18 -> 205548.82 | F18: =E18 -> 205548.82 | G18: =IF(AND(B18>0,B18<=Inputs!B21),Investment!B15,0) -> 117083.59 | H18: =E18-G18 -> 88465.229 | I18: =I17+F18 -> -2394946.3 | J18: =IF(I18>=0,1,0) -> 0 | K18: =K17+H18 -> -2297976.6 | L18: =IF(K18>=0,1,0) -> 0
A19: 17 | B19: =MAX(0,A19-Inputs!B28) -> 15 | C19: =IF(AND(B19>0,B19<=Inputs!B27),Investment!B12*(1+Inputs!B17)^(B19-1),0) -> 285799.1 | D19: =IF(AND(B19>0,B19<=Inputs!B27),Investment!B13*(1+Inputs!B18)^(B19-1),0) -> 76512.532 | E19: =C19-D19 -> 209286.57 | F19: =E19 -> 209286.57 | G19: =IF(AND(B19>0,B19<=Inputs!B21),Investment!B15,0) -> 117083.59 | H19: =E19-G19 -> 92202.974 | I19: =I18+F19 -> -2185659.7 | J19: =IF(I19>=0,1,0) -> 0 | K19: =K18+H19 -> -2205773.6 | L19: =IF(K19>=0,1,0) -> 0
A20: 18 | B20: =MAX(0,A20-Inputs!B28) -> 16 | C20: =IF(AND(B20>0,B20<=Inputs!B27),Investment!B12*(1+Inputs!B17)^(B20-1),0) -> 291515.08 | D20: =IF(AND(B20>0,B20<=Inputs!B27),Investment!B13*(1+Inputs!B18)^(B20-1),0) -> 78425.346 | E20: =C20-D20 -> 213089.74 | F20: =E20 -> 213089.74 | G20: =IF(AND(B20>0,B20<=Inputs!B21),Investment!B15,0) -> 117083.59 | H20: =E20-G20 -> 96006.142 | I20: =I19+F20 -> -1972570 | J20: =IF(I20>=0,1,0) -> 0 | K20: =K19+H20 -> -2109767.5 | L20: =IF(K20>=0,1,0) -> 0
A21: 19 | B21: =MAX(0,A21-Inputs!B28) -> 17 | C21: =IF(AND(B21>0,B21<=Inputs!B27),Investment!B12*(1+Inputs!B17)^(B21-1),0) -> 297345.38 | D21: =IF(AND(B21>0,B21<=Inputs!B27),Investment!B13*(1+Inputs!B18)^(B21-1),0) -> 80385.979 | E21: =C21-D21 -> 216959.4 | F21: =E21 -> 216959.4 | G21: =IF(AND(B21>0,B21<=Inputs!B21),Investment!B15,0) -> 117083.59 | H21: =E21-G21 -> 99875.81 | I21: =I20+F21 -> -1755610.6 | J21: =IF(I21>=0,1,0) -> 0 | K21: =K20+H21 -> -2009891.7 | L21: =IF(K21>=0,1,0) -> 0
A22: 20 | B22: =MAX(0,A22-Inputs!B28) -> 18 | C22: =IF(AND(B22>0,B22<=Inputs!B27),Investment!B12*(1+Inputs!B17)^(B22-1),0) -> 303292.29 | D22: =IF(AND(B22>0,B22<=Inputs!B27),Investment!B13*(1+Inputs!B18)^(B22-1),0) -> 82395.629 | E22: =C22-D22 -> 220896.66 | F22: =E22 -> 220896.66 | G22: =IF(AND(B22>0,B22<=Inputs!B21),Investment!B15,0) -> 117083.59 | H22: =E22-G22 -> 103813.07 | I22: =I21+F22 -> -1534713.9 | J22: =IF(I22>=0,1,0) -> 0 | K22: =K21+H22 -> -1906078.6 | L22: =IF(K22>=0,1,0) -> 0
A23: 21 | B23: =MAX(0,A23-Inputs!B28) -> 19 | C23: =IF(AND(B23>0,B23<=Inputs!B27),Investment!B12*(1+Inputs!B17)^(B23-1),0) -> 309358.14 | D23: =IF(AND(B23>0,B23<=Inputs!B27),Investment!B13*(1+Inputs!B18)^(B23-1),0) -> 84455.52 | E23: =C23-D23 -> 224902.62 | F23: =E23 -> 224902.62 | G23: =IF(AND(B23>0,B23<=Inputs!B21),Investment!B15,0) -> 117083.59 | H23: =E23-G23 -> 107819.02 | I23: =I22+F23 -> -1309811.3 | J23: =IF(I23>=0,1,0) -> 0 | K23: =K22+H23 -> -1798259.6 | L23: =IF(K23>=0,1,0) -> 0
A24: 22 | B24: =MAX(0,A24-Inputs!B28) -> 20 | C24: =IF(AND(B24>0,B24<=Inputs!B27),Investment!B12*(1+Inputs!B17)^(B24-1),0) -> 315545.3 | D24: =IF(AND(B24>0,B24<=Inputs!B27),Investment!B13*(1+Inputs!B18)^(B24-1),0) -> 86566.908 | E24: =C24-D24 -> 228978.39 | F24: =E24 -> 228978.39 | G24: =IF(AND(B24>0,B24<=Inputs!B21),Investment!B15,0) -> 117083.59 | H24: =E24-G24 -> 111894.8 | I24: =I23+F24 -> -1080832.9 | J24: =IF(I24>=0,1,0) -> 0 | K24: =K23+H24 -> -1686364.8 | L24: =IF(K24>=0,1,0) -> 0
A25: 23 | B25: =MAX(0,A25-Inputs!B28) -> 21 | C25: =IF(AND(B25>0,B25<=Inputs!B27),Investment!B12*(1+Inputs!B17)^(B25-1),0) -> 321856.21 | D25: =IF(AND(B25>0,B25<=Inputs!B27),Investment!B13*(1+Inputs!B18)^(B25-1),0) -> 88731.08 | E25: =C25-D25 -> 233125.13 | F25: =E25 -> 233125.13 | G25: =IF(AND(B25>0,B25<=Inputs!B21),Investment!B15,0) -> 117083.59 | H25: =E25-G25 -> 116041.53 | I25: =I24+F25 -> -847707.79 | J25: =IF(I25>=0,1,0) -> 0 | K25: =K24+H25 -> -1570323.3 | L25: =IF(K25>=0,1,0) -> 0
A26: 24 | B26: =MAX(0,A26-Inputs!B28) -> 22 | C26: =IF(AND(B26>0,B26<=Inputs!B27),Investment!B12*(1+Inputs!B17)^(B26-1),0) -> 328293.33 | D26: =IF(AND(B26>0,B26<=Inputs!B27),Investment!B13*(1+Inputs!B18)^(B26-1),0) -> 90949.357 | E26: =C26-D26 -> 237343.97 | F26: =E26 -> 237343.97 | G26: =IF(AND(B26>0,B26<=Inputs!B21),Investment!B15,0) -> 117083.59 | H26: =E26-G26 -> 120260.38 | I26: =I25+F26 -> -610363.81 | J26: =IF(I26>=0,1,0) -> 0 | K26: =K25+H26 -> -1450062.9 | L26: =IF(K26>=0,1,0) -> 0
A27: 25 | B27: =MAX(0,A27-Inputs!B28) -> 23 | C27: =IF(AND(B27>0,B27<=Inputs!B27),Investment!B12*(1+Inputs!B17)^(B27-1),0) -> 334859.2 | D27: =IF(AND(B27>0,B27<=Inputs!B27),Investment!B13*(1+Inputs!B18)^(B27-1),0) -> 93223.091 | E27: =C27-D27 -> 241636.11 | F27: =E27 -> 241636.11 | G27: =IF(AND(B27>0,B27<=Inputs!B21),Investment!B15,0) -> 117083.59 | H27: =E27-G27 -> 124552.51 | I27: =I26+F27 -> -368727.71 | J27: =IF(I27>=0,1,0) -> 0 | K27: =K26+H27 -> -1325510.4 | L27: =IF(K27>=0,1,0) -> 0
A28: 26 | B28: =MAX(0,A28-Inputs!B28) -> 24 | C28: =IF(AND(B28>0,B28<=Inputs!B27),Investment!B12*(1+Inputs!B17)^(B28-1),0) -> 341556.38 | D28: =IF(AND(B28>0,B28<=Inputs!B27),Investment!B13*(1+Inputs!B18)^(B28-1),0) -> 95553.668 | E28: =C28-D28 -> 246002.71 | F28: =E28 -> 246002.71 | G28: =IF(AND(B28>0,B28<=Inputs!B21),Investment!B15,0) -> 117083.59 | H28: =E28-G28 -> 128919.12 | I28: =I27+F28 -> -122724.99 | J28: =IF(I28>=0,1,0) -> 0 | K28: =K27+H28 -> -1196591.3 | L28: =IF(K28>=0,1,0) -> 0
A29: 27 | B29: =MAX(0,A29-Inputs!B28) -> 25 | C29: =IF(AND(B29>0,B29<=Inputs!B27),Investment!B12*(1+Inputs!B17)^(B29-1),0) -> 348387.51 | D29: =IF(AND(B29>0,B29<=Inputs!B27),Investment!B13*(1+Inputs!B18)^(B29-1),0) -> 97942.51 | E29: =C29-D29 -> 250445 | F29: =E29 -> 250445 | G29: =IF(AND(B29>0,B29<=Inputs!B21),Investment!B15,0) -> 117083.59 | H29: =E29-G29 -> 133361.4 | I29: =I28+F29 -> 127720 | J29: =IF(I29>=0,1,0) -> 1 | K29: =K28+H29 -> -1063229.9 | L29: =IF(K29>=0,1,0) -> 0
A30: 28 | B30: =MAX(0,A30-Inputs!B28) -> 26 | C30: =IF(AND(B30>0,B30<=Inputs!B27),Investment!B12*(1+Inputs!B17)^(B30-1),0) -> 355355.26 | D30: =IF(AND(B30>0,B30<=Inputs!B27),Investment!B13*(1+Inputs!B18)^(B30-1),0) -> 100391.07 | E30: =C30-D30 -> 254964.19 | F30: =E30 -> 254964.19 | G30: =IF(AND(B30>0,B30<=Inputs!B21),Investment!B15,0) -> 0 | H30: =E30-G30 -> 254964.19 | I30: =I29+F30 -> 382684.19 | J30: =IF(I30>=0,1,0) -> 1 | K30: =K29+H30 -> -808265.66 | L30: =IF(K30>=0,1,0) -> 0
A31: 29 | B31: =MAX(0,A31-Inputs!B28) -> 27 | C31: =IF(AND(B31>0,B31<=Inputs!B27),Investment!B12*(1+Inputs!B17)^(B31-1),0) -> 362462.36 | D31: =IF(AND(B31>0,B31<=Inputs!B27),Investment!B13*(1+Inputs!B18)^(B31-1),0) -> 102900.85 | E31: =C31-D31 -> 259561.51 | F31: =E31 -> 259561.51 | G31: =IF(AND(B31>0,B31<=Inputs!B21),Investment!B15,0) -> 0 | H31: =E31-G31 -> 259561.51 | I31: =I30+F31 -> 642245.7 | J31: =IF(I31>=0,1,0) -> 1 | K31: =K30+H31 -> -548704.15 | L31: =IF(K31>=0,1,0) -> 0
A32: 30 | B32: =MAX(0,A32-Inputs!B28) -> 28 | C32: =IF(AND(B32>0,B32<=Inputs!B27),Investment!B12*(1+Inputs!B17)^(B32-1),0) -> 369711.61 | D32: =IF(AND(B32>0,B32<=Inputs!B27),Investment!B13*(1+Inputs!B18)^(B32-1),0) -> 105473.37 | E32: =C32-D32 -> 264238.24 | F32: =E32 -> 264238.24 | G32: =IF(AND(B32>0,B32<=Inputs!B21),Investment!B15,0) -> 0 | H32: =E32-G32 -> 264238.24 | I32: =I31+F32 -> 906483.94 | J32: =IF(I32>=0,1,0) -> 1 | K32: =K31+H32 -> -284465.91 | L32: =IF(K32>=0,1,0) -> 0
A33: 31 | B33: =MAX(0,A33-Inputs!B28) -> 29 | C33: =IF(AND(B33>0,B33<=Inputs!B27),Investment!B12*(1+Inputs!B17)^(B33-1),0) -> 377105.84 | D33: =IF(AND(B33>0,B33<=Inputs!B27),Investment!B13*(1+Inputs!B18)^(B33-1),0) -> 108110.21 | E33: =C33-D33 -> 268995.64 | F33: =E33 -> 268995.64 | G33: =IF(AND(B33>0,B33<=Inputs!B21),Investment!B15,0) -> 0 | H33: =E33-G33 -> 268995.64 | I33: =I32+F33 -> 1175479.6 | J33: =IF(I33>=0,1,0) -> 1 | K33: =K32+H33 -> -15470.273 | L33: =IF(K33>=0,1,0) -> 0
A34: 32 | B34: =MAX(0,A34-Inputs!B28) -> 30 | C34: =IF(AND(B34>0,B34<=Inputs!B27),Investment!B12*(1+Inputs!B17)^(B34-1),0) -> 384647.96 | D34: =IF(AND(B34>0,B34<=Inputs!B27),Investment!B13*(1+Inputs!B18)^(B34-1),0) -> 110812.96 | E34: =C34-D34 -> 273835 | F34: =E34 -> 273835 | G34: =IF(AND(B34>0,B34<=Inputs!B21),Investment!B15,0) -> 0 | H34: =E34-G34 -> 273835 | I34: =I33+F34 -> 1449314.6 | J34: =IF(I34>=0,1,0) -> 1 | K34: =K33+H34 -> 258364.73 | L34: =IF(K34>=0,1,0) -> 1
A35: 33 | B35: =MAX(0,A35-Inputs!B28) -> 31 | C35: =IF(AND(B35>0,B35<=Inputs!B27),Investment!B12*(1+Inputs!B17)^(B35-1),0) -> 0 | D35: =IF(AND(B35>0,B35<=Inputs!B27),Investment!B13*(1+Inputs!B18)^(B35-1),0) -> 0 | E35: =C35-D35 -> 0 | F35: =E35 -> 0 | G35: =IF(AND(B35>0,B35<=Inputs!B21),Investment!B15,0) -> 0 | H35: =E35-G35 -> 0 | I35: =I34+F35 -> 1449314.6 | J35: =IF(I35>=0,1,0) -> 1 | K35: =K34+H35 -> 258364.73 | L35: =IF(K35>=0,1,0) -> 1
A36: 34 | B36: =MAX(0,A36-Inputs!B28) -> 32 | C36: =IF(AND(B36>0,B36<=Inputs!B27),Investment!B12*(1+Inputs!B17)^(B36-1),0) -> 0 | D36: =IF(AND(B36>0,B36<=Inputs!B27),Investment!B13*(1+Inputs!B18)^(B36-1),0) -> 0 | E36: =C36-D36 -> 0 | F36: =E36 -> 0 | G36: =IF(AND(B36>0,B36<=Inputs!B21),Investment!B15,0) -> 0 | H36: =E36-G36 -> 0 | I36: =I35+F36 -> 1449314.6 | J36: =IF(I36>=0,1,0) -> 1 | K36: =K35+H36 -> 258364.73 | L36: =IF(K36>=0,1,0) -> 1
A37: 35 | B37: =MAX(0,A37-Inputs!B28) -> 33 | C37: =IF(AND(B37>0,B37<=Inputs!B27),Investment!B12*(1+Inputs!B17)^(B37-1),0) -> 0 | D37: =IF(AND(B37>0,B37<=Inputs!B27),Investment!B13*(1+Inputs!B18)^(B37-1),0) -> 0 | E37: =C37-D37 -> 0 | F37: =E37 -> 0 | G37: =IF(AND(B37>0,B37<=Inputs!B21),Investment!B15,0) -> 0 | H37: =E37-G37 -> 0 | I37: =I36+F37 -> 1449314.6 | J37: =IF(I37>=0,1,0) -> 1 | K37: =K36+H37 -> 258364.73 | L37: =IF(K37>=0,1,0) -> 1
A38: 36 | B38: =MAX(0,A38-Inputs!B28) -> 34 | C38: =IF(AND(B38>0,B38<=Inputs!B27),Investment!B12*(1+Inputs!B17)^(B38-1),0) -> 0 | D38: =IF(AND(B38>0,B38<=Inputs!B27),Investment!B13*(1+Inputs!B18)^(B38-1),0) -> 0 | E38: =C38-D38 -> 0 | F38: =E38 -> 0 | G38: =IF(AND(B38>0,B38<=Inputs!B21),Investment!B15,0) -> 0 | H38: =E38-G38 -> 0 | I38: =I37+F38 -> 1449314.6 | J38: =IF(I38>=0,1,0) -> 1 | K38: =K37+H38 -> 258364.73 | L38: =IF(K38>=0,1,0) -> 1
A39: 37 | B39: =MAX(0,A39-Inputs!B28) -> 35 | C39: =IF(AND(B39>0,B39<=Inputs!B27),Investment!B12*(1+Inputs!B17)^(B39-1),0) -> 0 | D39: =IF(AND(B39>0,B39<=Inputs!B27),Investment!B13*(1+Inputs!B18)^(B39-1),0) -> 0 | E39: =C39-D39 -> 0 | F39: =E39 -> 0 | G39: =IF(AND(B39>0,B39<=Inputs!B21),Investment!B15,0) -> 0 | H39: =E39-G39 -> 0 | I39: =I38+F39 -> 1449314.6 | J39: =IF(I39>=0,1,0) -> 1 | K39: =K38+H39 -> 258364.73 | L39: =IF(K39>=0,1,0) -> 1
A40: 38 | B40: =MAX(0,A40-Inputs!B28) -> 36 | C40: =IF(AND(B40>0,B40<=Inputs!B27),Investment!B12*(1+Inputs!B17)^(B40-1),0) -> 0 | D40: =IF(AND(B40>0,B40<=Inputs!B27),Investment!B13*(1+Inputs!B18)^(B40-1),0) -> 0 | E40: =C40-D40 -> 0 | F40: =E40 -> 0 | G40: =IF(AND(B40>0,B40<=Inputs!B21),Investment!B15,0) -> 0 | H40: =E40-G40 -> 0 | I40: =I39+F40 -> 1449314.6 | J40: =IF(I40>=0,1,0) -> 1 | K40: =K39+H40 -> 258364.73 | L40: =IF(K40>=0,1,0) -> 1
A41: 39 | B41: =MAX(0,A41-Inputs!B28) -> 37 | C41: =IF(AND(B41>0,B41<=Inputs!B27),Investment!B12*(1+Inputs!B17)^(B41-1),0) -> 0 | D41: =IF(AND(B41>0,B41<=Inputs!B27),Investment!B13*(1+Inputs!B18)^(B41-1),0) -> 0 | E41: =C41-D41 -> 0 | F41: =E41 -> 0 | G41: =IF(AND(B41>0,B41<=Inputs!B21),Investment!B15,0) -> 0 | H41: =E41-G41 -> 0 | I41: =I40+F41 -> 1449314.6 | J41: =IF(I41>=0,1,0) -> 1 | K41: =K40+H41 -> 258364.73 | L41: =IF(K41>=0,1,0) -> 1
A42: 40 | B42: =MAX(0,A42-Inputs!B28) -> 38 | C42: =IF(AND(B42>0,B42<=Inputs!B27),Investment!B12*(1+Inputs!B17)^(B42-1),0) -> 0 | D42: =IF(AND(B42>0,B42<=Inputs!B27),Investment!B13*(1+Inputs!B18)^(B42-1),0) -> 0 | E42: =C42-D42 -> 0 | F42: =E42 -> 0 | G42: =IF(AND(B42>0,B42<=Inputs!B21),Investment!B15,0) -> 0 | H42: =E42-G42 -> 0 | I42: =I41+F42 -> 1449314.6 | J42: =IF(I42>=0,1,0) -> 1 | K42: =K41+H42 -> 258364.73 | L42: =IF(K42>=0,1,0) -> 1

Sheet Room sizing
A1: Rooms | B1: Floor area m² | C1: Total cost | D1: Equity | E1: NOI | F1: Debt service | G1: Equity CF | H1: Net yield | I1: DSCR | J1: Feasible | K1: Rank value
A2: 12 | B2: =A2*Inputs!B11 -> 408 | C2: =Inputs!B10+Inputs!B14+(B2*Inputs!B12+A2*Inputs!B13)*(1+Inputs!B15) -> 2293120 | D2: =C2*(1-Inputs!B19) -> 1490528 | E2: =A2*Investment!B2*Inputs!B9*Inputs!B8*(1-Inputs!B16) -> 48735 | F2: =IF(Inputs!B19=0,0,IF(Inputs!B20=0,C2*Inputs!B19/Inputs!B21,-PMT(Inputs!B20,Inputs!B21,C2*Inputs!B19))) -> 54126.024 | G2: =E2-F2 -> -5391.0244 | H2: =E2/C2 -> 0.021252704 | I2: =IF(F2=0,999,E2/F2) -> 0.90039866 | J2: =IF(AND(C2<=Inputs!B22,D2<=Inputs!B23,G2>0,I2>=Inputs!B24,A2<=Inputs!B29),"YES","NO") -> NO | K2: =IF(J2="YES",G2,-1) -> -1
A3: 13 | B3: =A3*Inputs!B11 -> 442 | C3: =Inputs!B10+Inputs!B14+(B3*Inputs!B12+A3*Inputs!B13)*(1+Inputs!B15) -> 2388380 | D3: =C3*(1-Inputs!B19) -> 1552447 | E3: =A3*Investment!B2*Inputs!B9*Inputs!B8*(1-Inputs!B16) -> 52796.25 | F3: =IF(Inputs!B19=0,0,IF(Inputs!B20=0,C3*Inputs!B19/Inputs!B21,-PMT(Inputs!B20,Inputs!B21,C3*Inputs!B19))) -> 56374.509 | G3: =E3-F3 -> -3578.259 | H3: =E3/C3 -> 0.022105465 | I3: =IF(F3=0,999,E3/F3) -> 0.936527 | J3: =IF(AND(C3<=Inputs!B22,D3<=Inputs!B23,G3>0,I3>=Inputs!B24,A3<=Inputs!B29),"YES","NO") -> NO | K3: =IF(J3="YES",G3,-1) -> -1
A4: 14 | B4: =A4*Inputs!B11 -> 476 | C4: =Inputs!B10+Inputs!B14+(B4*Inputs!B12+A4*Inputs!B13)*(1+Inputs!B15) -> 2483640 | D4: =C4*(1-Inputs!B19) -> 1614366 | E4: =A4*Investment!B2*Inputs!B9*Inputs!B8*(1-Inputs!B16) -> 56857.5 | F4: =IF(Inputs!B19=0,0,IF(Inputs!B20=0,C4*Inputs!B19/Inputs!B21,-PMT(Inputs!B20,Inputs!B21,C4*Inputs!B19))) -> 58622.994 | G4: =E4-F4 -> -1765.4937 | H4: =E4/C4 -> 0.022892811 | I4: =IF(F4=0,999,E4/F4) -> 0.96988394 | J4: =IF(AND(C4<=Inputs!B22,D4<=Inputs!B23,G4>0,I4>=Inputs!B24,A4<=Inputs!B29),"YES","NO") -> NO | K4: =IF(J4="YES",G4,-1) -> -1
A5: 15 | B5: =A5*Inputs!B11 -> 510 | C5: =Inputs!B10+Inputs!B14+(B5*Inputs!B12+A5*Inputs!B13)*(1+Inputs!B15) -> 2578900 | D5: =C5*(1-Inputs!B19) -> 1676285 | E5: =A5*Investment!B2*Inputs!B9*Inputs!B8*(1-Inputs!B16) -> 60918.75 | F5: =IF(Inputs!B19=0,0,IF(Inputs!B20=0,C5*Inputs!B19/Inputs!B21,-PMT(Inputs!B20,Inputs!B21,C5*Inputs!B19))) -> 60871.478 | G5: =E5-F5 -> 47.271707 | H5: =E5/C5 -> 0.02362199 | I5: =IF(F5=0,999,E5/F5) -> 1.0007766 | J5: =IF(AND(C5<=Inputs!B22,D5<=Inputs!B23,G5>0,I5>=Inputs!B24,A5<=Inputs!B29),"YES","NO") -> NO | K5: =IF(J5="YES",G5,-1) -> -1
A6: 16 | B6: =A6*Inputs!B11 -> 544 | C6: =Inputs!B10+Inputs!B14+(B6*Inputs!B12+A6*Inputs!B13)*(1+Inputs!B15) -> 2674160 | D6: =C6*(1-Inputs!B19) -> 1738204 | E6: =A6*Investment!B2*Inputs!B9*Inputs!B8*(1-Inputs!B16) -> 64980 | F6: =IF(Inputs!B19=0,0,IF(Inputs!B20=0,C6*Inputs!B19/Inputs!B21,-PMT(Inputs!B20,Inputs!B21,C6*Inputs!B19))) -> 63119.963 | G6: =E6-F6 -> 1860.0371 | H6: =E6/C6 -> 0.024299219 | I6: =IF(F6=0,999,E6/F6) -> 1.0294683 | J6: =IF(AND(C6<=Inputs!B22,D6<=Inputs!B23,G6>0,I6>=Inputs!B24,A6<=Inputs!B29),"YES","NO") -> NO | K6: =IF(J6="YES",G6,-1) -> -1
A7: 17 | B7: =A7*Inputs!B11 -> 578 | C7: =Inputs!B10+Inputs!B14+(B7*Inputs!B12+A7*Inputs!B13)*(1+Inputs!B15) -> 2769420 | D7: =C7*(1-Inputs!B19) -> 1800123 | E7: =A7*Investment!B2*Inputs!B9*Inputs!B8*(1-Inputs!B16) -> 69041.25 | F7: =IF(Inputs!B19=0,0,IF(Inputs!B20=0,C7*Inputs!B19/Inputs!B21,-PMT(Inputs!B20,Inputs!B21,C7*Inputs!B19))) -> 65368.448 | G7: =E7-F7 -> 3672.8024 | H7: =E7/C7 -> 0.024929859 | I7: =IF(F7=0,999,E7/F7) -> 1.0561862 | J7: =IF(AND(C7<=Inputs!B22,D7<=Inputs!B23,G7>0,I7>=Inputs!B24,A7<=Inputs!B29),"YES","NO") -> NO | K7: =IF(J7="YES",G7,-1) -> -1
A8: 18 | B8: =A8*Inputs!B11 -> 612 | C8: =Inputs!B10+Inputs!B14+(B8*Inputs!B12+A8*Inputs!B13)*(1+Inputs!B15) -> 2864680 | D8: =C8*(1-Inputs!B19) -> 1862042 | E8: =A8*Investment!B2*Inputs!B9*Inputs!B8*(1-Inputs!B16) -> 73102.5 | F8: =IF(Inputs!B19=0,0,IF(Inputs!B20=0,C8*Inputs!B19/Inputs!B21,-PMT(Inputs!B20,Inputs!B21,C8*Inputs!B19))) -> 67616.932 | G8: =E8-F8 -> 5485.5678 | H8: =E8/C8 -> 0.025518557 | I8: =IF(F8=0,999,E8/F8) -> 1.0811271 | J8: =IF(AND(C8<=Inputs!B22,D8<=Inputs!B23,G8>0,I8>=Inputs!B24,A8<=Inputs!B29),"YES","NO") -> NO | K8: =IF(J8="YES",G8,-1) -> -1
A9: 19 | B9: =A9*Inputs!B11 -> 646 | C9: =Inputs!B10+Inputs!B14+(B9*Inputs!B12+A9*Inputs!B13)*(1+Inputs!B15) -> 2959940 | D9: =C9*(1-Inputs!B19) -> 1923961 | E9: =A9*Investment!B2*Inputs!B9*Inputs!B8*(1-Inputs!B16) -> 77163.75 | F9: =IF(Inputs!B19=0,0,IF(Inputs!B20=0,C9*Inputs!B19/Inputs!B21,-PMT(Inputs!B20,Inputs!B21,C9*Inputs!B19))) -> 69865.417 | G9: =E9-F9 -> 7298.3332 | H9: =E9/C9 -> 0.026069363 | I9: =IF(F9=0,999,E9/F9) -> 1.1044627 | J9: =IF(AND(C9<=Inputs!B22,D9<=Inputs!B23,G9>0,I9>=Inputs!B24,A9<=Inputs!B29),"YES","NO") -> NO | K9: =IF(J9="YES",G9,-1) -> -1
A10: 20 | B10: =A10*Inputs!B11 -> 680 | C10: =Inputs!B10+Inputs!B14+(B10*Inputs!B12+A10*Inputs!B13)*(1+Inputs!B15) -> 3055200 | D10: =C10*(1-Inputs!B19) -> 1985880 | E10: =A10*Investment!B2*Inputs!B9*Inputs!B8*(1-Inputs!B16) -> 81225 | F10: =IF(Inputs!B19=0,0,IF(Inputs!B20=0,C10*Inputs!B19/Inputs!B21,-PMT(Inputs!B20,Inputs!B21,C10*Inputs!B19))) -> 72113.901 | G10: =E10-F10 -> 9111.0985 | H10: =E10/C10 -> 0.026585821 | I10: =IF(F10=0,999,E10/F10) -> 1.1263432 | J10: =IF(AND(C10<=Inputs!B22,D10<=Inputs!B23,G10>0,I10>=Inputs!B24,A10<=Inputs!B29),"YES","NO") -> NO | K10: =IF(J10="YES",G10,-1) -> -1
A11: 21 | B11: =A11*Inputs!B11 -> 714 | C11: =Inputs!B10+Inputs!B14+(B11*Inputs!B12+A11*Inputs!B13)*(1+Inputs!B15) -> 3150460 | D11: =C11*(1-Inputs!B19) -> 2047799 | E11: =A11*Investment!B2*Inputs!B9*Inputs!B8*(1-Inputs!B16) -> 85286.25 | F11: =IF(Inputs!B19=0,0,IF(Inputs!B20=0,C11*Inputs!B19/Inputs!B21,-PMT(Inputs!B20,Inputs!B21,C11*Inputs!B19))) -> 74362.386 | G11: =E11-F11 -> 10923.864 | H11: =E11/C11 -> 0.027071047 | I11: =IF(F11=0,999,E11/F11) -> 1.1469004 | J11: =IF(AND(C11<=Inputs!B22,D11<=Inputs!B23,G11>0,I11>=Inputs!B24,A11<=Inputs!B29),"YES","NO") -> NO | K11: =IF(J11="YES",G11,-1) -> -1
A12: 22 | B12: =A12*Inputs!B11 -> 748 | C12: =Inputs!B10+Inputs!B14+(B12*Inputs!B12+A12*Inputs!B13)*(1+Inputs!B15) -> 3245720 | D12: =C12*(1-Inputs!B19) -> 2109718 | E12: =A12*Investment!B2*Inputs!B9*Inputs!B8*(1-Inputs!B16) -> 89347.5 | F12: =IF(Inputs!B19=0,0,IF(Inputs!B20=0,C12*Inputs!B19/Inputs!B21,-PMT(Inputs!B20,Inputs!B21,C12*Inputs!B19))) -> 76610.871 | G12: =E12-F12 -> 12736.629 | H12: =E12/C12 -> 0.02752779 | I12: =IF(F12=0,999,E12/F12) -> 1.1662509 | J12: =IF(AND(C12<=Inputs!B22,D12<=Inputs!B23,G12>0,I12>=Inputs!B24,A12<=Inputs!B29),"YES","NO") -> NO | K12: =IF(J12="YES",G12,-1) -> -1
A13: 23 | B13: =A13*Inputs!B11 -> 782 | C13: =Inputs!B10+Inputs!B14+(B13*Inputs!B12+A13*Inputs!B13)*(1+Inputs!B15) -> 3340980 | D13: =C13*(1-Inputs!B19) -> 2171637 | E13: =A13*Investment!B2*Inputs!B9*Inputs!B8*(1-Inputs!B16) -> 93408.75 | F13: =IF(Inputs!B19=0,0,IF(Inputs!B20=0,C13*Inputs!B19/Inputs!B21,-PMT(Inputs!B20,Inputs!B21,C13*Inputs!B19))) -> 78859.355 | G13: =E13-F13 -> 14549.395 | H13: =E13/C13 -> 0.027958488 | I13: =IF(F13=0,999,E13/F13) -> 1.184498 | J13: =IF(AND(C13<=Inputs!B22,D13<=Inputs!B23,G13>0,I13>=Inputs!B24,A13<=Inputs!B29),"YES","NO") -> NO | K13: =IF(J13="YES",G13,-1) -> -1
A14: 24 | B14: =A14*Inputs!B11 -> 816 | C14: =Inputs!B10+Inputs!B14+(B14*Inputs!B12+A14*Inputs!B13)*(1+Inputs!B15) -> 3436240 | D14: =C14*(1-Inputs!B19) -> 2233556 | E14: =A14*Investment!B2*Inputs!B9*Inputs!B8*(1-Inputs!B16) -> 97470 | F14: =IF(Inputs!B19=0,0,IF(Inputs!B20=0,C14*Inputs!B19/Inputs!B21,-PMT(Inputs!B20,Inputs!B21,C14*Inputs!B19))) -> 81107.84 | G14: =E14-F14 -> 16362.16 | H14: =E14/C14 -> 0.028365306 | I14: =IF(F14=0,999,E14/F14) -> 1.2017334 | J14: =IF(AND(C14<=Inputs!B22,D14<=Inputs!B23,G14>0,I14>=Inputs!B24,A14<=Inputs!B29),"YES","NO") -> YES | K14: =IF(J14="YES",G14,-1) -> 16362.16
A15: 25 | B15: =A15*Inputs!B11 -> 850 | C15: =Inputs!B10+Inputs!B14+(B15*Inputs!B12+A15*Inputs!B13)*(1+Inputs!B15) -> 3531500 | D15: =C15*(1-Inputs!B19) -> 2295475 | E15: =A15*Investment!B2*Inputs!B9*Inputs!B8*(1-Inputs!B16) -> 101531.25 | F15: =IF(Inputs!B19=0,0,IF(Inputs!B20=0,C15*Inputs!B19/Inputs!B21,-PMT(Inputs!B20,Inputs!B21,C15*Inputs!B19))) -> 83356.325 | G15: =E15-F15 -> 18174.925 | H15: =E15/C15 -> 0.028750177 | I15: =IF(F15=0,999,E15/F15) -> 1.2180389 | J15: =IF(AND(C15<=Inputs!B22,D15<=Inputs!B23,G15>0,I15>=Inputs!B24,A15<=Inputs!B29),"YES","NO") -> YES | K15: =IF(J15="YES",G15,-1) -> 18174.925
A16: 26 | B16: =A16*Inputs!B11 -> 884 | C16: =Inputs!B10+Inputs!B14+(B16*Inputs!B12+A16*Inputs!B13)*(1+Inputs!B15) -> 3626760 | D16: =C16*(1-Inputs!B19) -> 2357394 | E16: =A16*Investment!B2*Inputs!B9*Inputs!B8*(1-Inputs!B16) -> 105592.5 | F16: =IF(Inputs!B19=0,0,IF(Inputs!B20=0,C16*Inputs!B19/Inputs!B21,-PMT(Inputs!B20,Inputs!B21,C16*Inputs!B19))) -> 85604.809 | G16: =E16-F16 -> 19987.691 | H16: =E16/C16 -> 0.02911483 | I16: =IF(F16=0,999,E16/F16) -> 1.2334879 | J16: =IF(AND(C16<=Inputs!B22,D16<=Inputs!B23,G16>0,I16>=Inputs!B24,A16<=Inputs!B29),"YES","NO") -> YES | K16: =IF(J16="YES",G16,-1) -> 19987.691
A17: 27 | B17: =A17*Inputs!B11 -> 918 | C17: =Inputs!B10+Inputs!B14+(B17*Inputs!B12+A17*Inputs!B13)*(1+Inputs!B15) -> 3722020 | D17: =C17*(1-Inputs!B19) -> 2419313 | E17: =A17*Investment!B2*Inputs!B9*Inputs!B8*(1-Inputs!B16) -> 109653.75 | F17: =IF(Inputs!B19=0,0,IF(Inputs!B20=0,C17*Inputs!B19/Inputs!B21,-PMT(Inputs!B20,Inputs!B21,C17*Inputs!B19))) -> 87853.294 | G17: =E17-F17 -> 21800.456 | H17: =E17/C17 -> 0.029460817 | I17: =IF(F17=0,999,E17/F17) -> 1.2481461 | J17: =IF(AND(C17<=Inputs!B22,D17<=Inputs!B23,G17>0,I17>=Inputs!B24,A17<=Inputs!B29),"YES","NO") -> YES | K17: =IF(J17="YES",G17,-1) -> 21800.456
A18: 28 | B18: =A18*Inputs!B11 -> 952 | C18: =Inputs!B10+Inputs!B14+(B18*Inputs!B12+A18*Inputs!B13)*(1+Inputs!B15) -> 3817280 | D18: =C18*(1-Inputs!B19) -> 2481232 | E18: =A18*Investment!B2*Inputs!B9*Inputs!B8*(1-Inputs!B16) -> 113715 | F18: =IF(Inputs!B19=0,0,IF(Inputs!B20=0,C18*Inputs!B19/Inputs!B21,-PMT(Inputs!B20,Inputs!B21,C18*Inputs!B19))) -> 90101.779 | G18: =E18-F18 -> 23613.221 | H18: =E18/C18 -> 0.029789536 | I18: =IF(F18=0,999,E18/F18) -> 1.2620728 | J18: =IF(AND(C18<=Inputs!B22,D18<=Inputs!B23,G18>0,I18>=Inputs!B24,A18<=Inputs!B29),"YES","NO") -> YES | K18: =IF(J18="YES",G18,-1) -> 23613.221
A19: 29 | B19: =A19*Inputs!B11 -> 986 | C19: =Inputs!B10+Inputs!B14+(B19*Inputs!B12+A19*Inputs!B13)*(1+Inputs!B15) -> 3912540 | D19: =C19*(1-Inputs!B19) -> 2543151 | E19: =A19*Investment!B2*Inputs!B9*Inputs!B8*(1-Inputs!B16) -> 117776.25 | F19: =IF(Inputs!B19=0,0,IF(Inputs!B20=0,C19*Inputs!B19/Inputs!B21,-PMT(Inputs!B20,Inputs!B21,C19*Inputs!B19))) -> 92350.263 | G19: =E19-F19 -> 25425.987 | H19: =E19/C19 -> 0.030102248 | I19: =IF(F19=0,999,E19/F19) -> 1.2753212 | J19: =IF(AND(C19<=Inputs!B22,D19<=Inputs!B23,G19>0,I19>=Inputs!B24,A19<=Inputs!B29),"YES","NO") -> YES | K19: =IF(J19="YES",G19,-1) -> 25425.987
A20: 30 | B20: =A20*Inputs!B11 -> 1020 | C20: =Inputs!B10+Inputs!B14+(B20*Inputs!B12+A20*Inputs!B13)*(1+Inputs!B15) -> 4007800 | D20: =C20*(1-Inputs!B19) -> 2605070 | E20: =A20*Investment!B2*Inputs!B9*Inputs!B8*(1-Inputs!B16) -> 121837.5 | F20: =IF(Inputs!B19=0,0,IF(Inputs!B20=0,C20*Inputs!B19/Inputs!B21,-PMT(Inputs!B20,Inputs!B21,C20*Inputs!B19))) -> 94598.748 | G20: =E20-F20 -> 27238.752 | H20: =E20/C20 -> 0.030400095 | I20: =IF(F20=0,999,E20/F20) -> 1.2879399 | J20: =IF(AND(C20<=Inputs!B22,D20<=Inputs!B23,G20>0,I20>=Inputs!B24,A20<=Inputs!B29),"YES","NO") -> YES | K20: =IF(J20="YES",G20,-1) -> 27238.752
A21: 31 | B21: =A21*Inputs!B11 -> 1054 | C21: =Inputs!B10+Inputs!B14+(B21*Inputs!B12+A21*Inputs!B13)*(1+Inputs!B15) -> 4103060 | D21: =C21*(1-Inputs!B19) -> 2666989 | E21: =A21*Investment!B2*Inputs!B9*Inputs!B8*(1-Inputs!B16) -> 125898.75 | F21: =IF(Inputs!B19=0,0,IF(Inputs!B20=0,C21*Inputs!B19/Inputs!B21,-PMT(Inputs!B20,Inputs!B21,C21*Inputs!B19))) -> 96847.232 | G21: =E21-F21 -> 29051.518 | H21: =E21/C21 -> 0.030684111 | I21: =IF(F21=0,999,E21/F21) -> 1.2999726 | J21: =IF(AND(C21<=Inputs!B22,D21<=Inputs!B23,G21>0,I21>=Inputs!B24,A21<=Inputs!B29),"YES","NO") -> YES | K21: =IF(J21="YES",G21,-1) -> 29051.518
A22: 32 | B22: =A22*Inputs!B11 -> 1088 | C22: =Inputs!B10+Inputs!B14+(B22*Inputs!B12+A22*Inputs!B13)*(1+Inputs!B15) -> 4198320 | D22: =C22*(1-Inputs!B19) -> 2728908 | E22: =A22*Investment!B2*Inputs!B9*Inputs!B8*(1-Inputs!B16) -> 129960 | F22: =IF(Inputs!B19=0,0,IF(Inputs!B20=0,C22*Inputs!B19/Inputs!B21,-PMT(Inputs!B20,Inputs!B21,C22*Inputs!B19))) -> 99095.717 | G22: =E22-F22 -> 30864.283 | H22: =E22/C22 -> 0.030955239 | I22: =IF(F22=0,999,E22/F22) -> 1.3114593 | J22: =IF(AND(C22<=Inputs!B22,D22<=Inputs!B23,G22>0,I22>=Inputs!B24,A22<=Inputs!B29),"YES","NO") -> YES | K22: =IF(J22="YES",G22,-1) -> 30864.283
A23: 33 | B23: =A23*Inputs!B11 -> 1122 | C23: =Inputs!B10+Inputs!B14+(B23*Inputs!B12+A23*Inputs!B13)*(1+Inputs!B15) -> 4293580 | D23: =C23*(1-Inputs!B19) -> 2790827 | E23: =A23*Investment!B2*Inputs!B9*Inputs!B8*(1-Inputs!B16) -> 134021.25 | F23: =IF(Inputs!B19=0,0,IF(Inputs!B20=0,C23*Inputs!B19/Inputs!B21,-PMT(Inputs!B20,Inputs!B21,C23*Inputs!B19))) -> 101344.2 | G23: =E23-F23 -> 32677.048 | H23: =E23/C23 -> 0.031214336 | I23: =IF(F23=0,999,E23/F23) -> 1.3224363 | J23: =IF(AND(C23<=Inputs!B22,D23<=Inputs!B23,G23>0,I23>=Inputs!B24,A23<=Inputs!B29),"YES","NO") -> YES | K23: =IF(J23="YES",G23,-1) -> 32677.048
A24: 34 | B24: =A24*Inputs!B11 -> 1156 | C24: =Inputs!B10+Inputs!B14+(B24*Inputs!B12+A24*Inputs!B13)*(1+Inputs!B15) -> 4388840 | D24: =C24*(1-Inputs!B19) -> 2852746 | E24: =A24*Investment!B2*Inputs!B9*Inputs!B8*(1-Inputs!B16) -> 138082.5 | F24: =IF(Inputs!B19=0,0,IF(Inputs!B20=0,C24*Inputs!B19/Inputs!B21,-PMT(Inputs!B20,Inputs!B21,C24*Inputs!B19))) -> 103592.69 | G24: =E24-F24 -> 34489.814 | H24: =E24/C24 -> 0.031462186 | I24: =IF(F24=0,999,E24/F24) -> 1.3329368 | J24: =IF(AND(C24<=Inputs!B22,D24<=Inputs!B23,G24>0,I24>=Inputs!B24,A24<=Inputs!B29),"YES","NO") -> YES | K24: =IF(J24="YES",G24,-1) -> 34489.814
A25: 35 | B25: =A25*Inputs!B11 -> 1190 | C25: =Inputs!B10+Inputs!B14+(B25*Inputs!B12+A25*Inputs!B13)*(1+Inputs!B15) -> 4484100 | D25: =C25*(1-Inputs!B19) -> 2914665 | E25: =A25*Investment!B2*Inputs!B9*Inputs!B8*(1-Inputs!B16) -> 142143.75 | F25: =IF(Inputs!B19=0,0,IF(Inputs!B20=0,C25*Inputs!B19/Inputs!B21,-PMT(Inputs!B20,Inputs!B21,C25*Inputs!B19))) -> 105841.17 | G25: =E25-F25 -> 36302.579 | H25: =E25/C25 -> 0.031699505 | I25: =IF(F25=0,999,E25/F25) -> 1.3429911 | J25: =IF(AND(C25<=Inputs!B22,D25<=Inputs!B23,G25>0,I25>=Inputs!B24,A25<=Inputs!B29),"YES","NO") -> YES | K25: =IF(J25="YES",G25,-1) -> 36302.579
A26: 36 | B26: =A26*Inputs!B11 -> 1224 | C26: =Inputs!B10+Inputs!B14+(B26*Inputs!B12+A26*Inputs!B13)*(1+Inputs!B15) -> 4579360 | D26: =C26*(1-Inputs!B19) -> 2976584 | E26: =A26*Investment!B2*Inputs!B9*Inputs!B8*(1-Inputs!B16) -> 146205 | F26: =IF(Inputs!B19=0,0,IF(Inputs!B20=0,C26*Inputs!B19/Inputs!B21,-PMT(Inputs!B20,Inputs!B21,C26*Inputs!B19))) -> 108089.66 | G26: =E26-F26 -> 38115.344 | H26: =E26/C26 -> 0.03192695 | I26: =IF(F26=0,999,E26/F26) -> 1.3526271 | J26: =IF(AND(C26<=Inputs!B22,D26<=Inputs!B23,G26>0,I26>=Inputs!B24,A26<=Inputs!B29),"YES","NO") -> YES | K26: =IF(J26="YES",G26,-1) -> 38115.344
A27: 37 | B27: =A27*Inputs!B11 -> 1258 | C27: =Inputs!B10+Inputs!B14+(B27*Inputs!B12+A27*Inputs!B13)*(1+Inputs!B15) -> 4674620 | D27: =C27*(1-Inputs!B19) -> 3038503 | E27: =A27*Investment!B2*Inputs!B9*Inputs!B8*(1-Inputs!B16) -> 150266.25 | F27: =IF(Inputs!B19=0,0,IF(Inputs!B20=0,C27*Inputs!B19/Inputs!B21,-PMT(Inputs!B20,Inputs!B21,C27*Inputs!B19))) -> 110338.14 | G27: =E27-F27 -> 39928.11 | H27: =E27/C27 -> 0.032145126 | I27: =IF(F27=0,999,E27/F27) -> 1.3618704 | J27: =IF(AND(C27<=Inputs!B22,D27<=Inputs!B23,G27>0,I27>=Inputs!B24,A27<=Inputs!B29),"YES","NO") -> YES | K27: =IF(J27="YES",G27,-1) -> 39928.11
A28: 38 | B28: =A28*Inputs!B11 -> 1292 | C28: =Inputs!B10+Inputs!B14+(B28*Inputs!B12+A28*Inputs!B13)*(1+Inputs!B15) -> 4769880 | D28: =C28*(1-Inputs!B19) -> 3100422 | E28: =A28*Investment!B2*Inputs!B9*Inputs!B8*(1-Inputs!B16) -> 154327.5 | F28: =IF(Inputs!B19=0,0,IF(Inputs!B20=0,C28*Inputs!B19/Inputs!B21,-PMT(Inputs!B20,Inputs!B21,C28*Inputs!B19))) -> 112586.62 | G28: =E28-F28 -> 41740.875 | H28: =E28/C28 -> 0.032354588 | I28: =IF(F28=0,999,E28/F28) -> 1.3707445 | J28: =IF(AND(C28<=Inputs!B22,D28<=Inputs!B23,G28>0,I28>=Inputs!B24,A28<=Inputs!B29),"YES","NO") -> YES | K28: =IF(J28="YES",G28,-1) -> 41740.875
A29: 39 | B29: =A29*Inputs!B11 -> 1326 | C29: =Inputs!B10+Inputs!B14+(B29*Inputs!B12+A29*Inputs!B13)*(1+Inputs!B15) -> 4865140 | D29: =C29*(1-Inputs!B19) -> 3162341 | E29: =A29*Investment!B2*Inputs!B9*Inputs!B8*(1-Inputs!B16) -> 158388.75 | F29: =IF(Inputs!B19=0,0,IF(Inputs!B20=0,C29*Inputs!B19/Inputs!B21,-PMT(Inputs!B20,Inputs!B21,C29*Inputs!B19))) -> 114835.11 | G29: =E29-F29 -> 43553.64 | H29: =E29/C29 -> 0.032555846 | I29: =IF(F29=0,999,E29/F29) -> 1.3792711 | J29: =IF(AND(C29<=Inputs!B22,D29<=Inputs!B23,G29>0,I29>=Inputs!B24,A29<=Inputs!B29),"YES","NO") -> YES | K29: =IF(J29="YES",G29,-1) -> 43553.64
A30: 40 | B30: =A30*Inputs!B11 -> 1360 | C30: =Inputs!B10+Inputs!B14+(B30*Inputs!B12+A30*Inputs!B13)*(1+Inputs!B15) -> 4960400 | D30: =C30*(1-Inputs!B19) -> 3224260 | E30: =A30*Investment!B2*Inputs!B9*Inputs!B8*(1-Inputs!B16) -> 162450 | F30: =IF(Inputs!B19=0,0,IF(Inputs!B20=0,C30*Inputs!B19/Inputs!B21,-PMT(Inputs!B20,Inputs!B21,C30*Inputs!B19))) -> 117083.59 | G30: =E30-F30 -> 45366.406 | H30: =E30/C30 -> 0.032749375 | I30: =IF(F30=0,999,E30/F30) -> 1.3874702 | J30: =IF(AND(C30<=Inputs!B22,D30<=Inputs!B23,G30>0,I30>=Inputs!B24,A30<=Inputs!B29),"YES","NO") -> YES | K30: =IF(J30="YES",G30,-1) -> 45366.406
A31: 41 | B31: =A31*Inputs!B11 -> 1394 | C31: =Inputs!B10+Inputs!B14+(B31*Inputs!B12+A31*Inputs!B13)*(1+Inputs!B15) -> 5055660 | D31: =C31*(1-Inputs!B19) -> 3286179 | E31: =A31*Investment!B2*Inputs!B9*Inputs!B8*(1-Inputs!B16) -> 166511.25 | F31: =IF(Inputs!B19=0,0,IF(Inputs!B20=0,C31*Inputs!B19/Inputs!B21,-PMT(Inputs!B20,Inputs!B21,C31*Inputs!B19))) -> 119332.08 | G31: =E31-F31 -> 47179.171 | H31: =E31/C31 -> 0.032935611 | I31: =IF(F31=0,999,E31/F31) -> 1.3953603 | J31: =IF(AND(C31<=Inputs!B22,D31<=Inputs!B23,G31>0,I31>=Inputs!B24,A31<=Inputs!B29),"YES","NO") -> NO | K31: =IF(J31="YES",G31,-1) -> -1
A32: 42 | B32: =A32*Inputs!B11 -> 1428 | C32: =Inputs!B10+Inputs!B14+(B32*Inputs!B12+A32*Inputs!B13)*(1+Inputs!B15) -> 5150920 | D32: =C32*(1-Inputs!B19) -> 3348098 | E32: =A32*Investment!B2*Inputs!B9*Inputs!B8*(1-Inputs!B16) -> 170572.5 | F32: =IF(Inputs!B19=0,0,IF(Inputs!B20=0,C32*Inputs!B19/Inputs!B21,-PMT(Inputs!B20,Inputs!B21,C32*Inputs!B19))) -> 121580.56 | G32: =E32-F32 -> 48991.937 | H32: =E32/C32 -> 0.033114958 | I32: =IF(F32=0,999,E32/F32) -> 1.4029586 | J32: =IF(AND(C32<=Inputs!B22,D32<=Inputs!B23,G32>0,I32>=Inputs!B24,A32<=Inputs!B29),"YES","NO") -> NO | K32: =IF(J32="YES",G32,-1) -> -1
A33: 43 | B33: =A33*Inputs!B11 -> 1462 | C33: =Inputs!B10+Inputs!B14+(B33*Inputs!B12+A33*Inputs!B13)*(1+Inputs!B15) -> 5246180 | D33: =C33*(1-Inputs!B19) -> 3410017 | E33: =A33*Investment!B2*Inputs!B9*Inputs!B8*(1-Inputs!B16) -> 174633.75 | F33: =IF(Inputs!B19=0,0,IF(Inputs!B20=0,C33*Inputs!B19/Inputs!B21,-PMT(Inputs!B20,Inputs!B21,C33*Inputs!B19))) -> 123829.05 | G33: =E33-F33 -> 50804.702 | H33: =E33/C33 -> 0.033287792 | I33: =IF(F33=0,999,E33/F33) -> 1.410281 | J33: =IF(AND(C33<=Inputs!B22,D33<=Inputs!B23,G33>0,I33>=Inputs!B24,A33<=Inputs!B29),"YES","NO") -> NO | K33: =IF(J33="YES",G33,-1) -> -1
A34: 44 | B34: =A34*Inputs!B11 -> 1496 | C34: =Inputs!B10+Inputs!B14+(B34*Inputs!B12+A34*Inputs!B13)*(1+Inputs!B15) -> 5341440 | D34: =C34*(1-Inputs!B19) -> 3471936 | E34: =A34*Investment!B2*Inputs!B9*Inputs!B8*(1-Inputs!B16) -> 178695 | F34: =IF(Inputs!B19=0,0,IF(Inputs!B20=0,C34*Inputs!B19/Inputs!B21,-PMT(Inputs!B20,Inputs!B21,C34*Inputs!B19))) -> 126077.53 | G34: =E34-F34 -> 52617.467 | H34: =E34/C34 -> 0.033454462 | I34: =IF(F34=0,999,E34/F34) -> 1.4173421 | J34: =IF(AND(C34<=Inputs!B22,D34<=Inputs!B23,G34>0,I34>=Inputs!B24,A34<=Inputs!B29),"YES","NO") -> NO | K34: =IF(J34="YES",G34,-1) -> -1
A35: 45 | B35: =A35*Inputs!B11 -> 1530 | C35: =Inputs!B10+Inputs!B14+(B35*Inputs!B12+A35*Inputs!B13)*(1+Inputs!B15) -> 5436700 | D35: =C35*(1-Inputs!B19) -> 3533855 | E35: =A35*Investment!B2*Inputs!B9*Inputs!B8*(1-Inputs!B16) -> 182756.25 | F35: =IF(Inputs!B19=0,0,IF(Inputs!B20=0,C35*Inputs!B19/Inputs!B21,-PMT(Inputs!B20,Inputs!B21,C35*Inputs!B19))) -> 128326.02 | G35: =E35-F35 -> 54430.233 | H35: =E35/C35 -> 0.033615291 | I35: =IF(F35=0,999,E35/F35) -> 1.4241559 | J35: =IF(AND(C35<=Inputs!B22,D35<=Inputs!B23,G35>0,I35>=Inputs!B24,A35<=Inputs!B29),"YES","NO") -> NO | K35: =IF(J35="YES",G35,-1) -> -1
A36: 46 | B36: =A36*Inputs!B11 -> 1564 | C36: =Inputs!B10+Inputs!B14+(B36*Inputs!B12+A36*Inputs!B13)*(1+Inputs!B15) -> 5531960 | D36: =C36*(1-Inputs!B19) -> 3595774 | E36: =A36*Investment!B2*Inputs!B9*Inputs!B8*(1-Inputs!B16) -> 186817.5 | F36: =IF(Inputs!B19=0,0,IF(Inputs!B20=0,C36*Inputs!B19/Inputs!B21,-PMT(Inputs!B20,Inputs!B21,C36*Inputs!B19))) -> 130574.5 | G36: =E36-F36 -> 56242.998 | H36: =E36/C36 -> 0.03377058 | I36: =IF(F36=0,999,E36/F36) -> 1.4307349 | J36: =IF(AND(C36<=Inputs!B22,D36<=Inputs!B23,G36>0,I36>=Inputs!B24,A36<=Inputs!B29),"YES","NO") -> NO | K36: =IF(J36="YES",G36,-1) -> -1
A37: 47 | B37: =A37*Inputs!B11 -> 1598 | C37: =Inputs!B10+Inputs!B14+(B37*Inputs!B12+A37*Inputs!B13)*(1+Inputs!B15) -> 5627220 | D37: =C37*(1-Inputs!B19) -> 3657693 | E37: =A37*Investment!B2*Inputs!B9*Inputs!B8*(1-Inputs!B16) -> 190878.75 | F37: =IF(Inputs!B19=0,0,IF(Inputs!B20=0,C37*Inputs!B19/Inputs!B21,-PMT(Inputs!B20,Inputs!B21,C37*Inputs!B19))) -> 132822.99 | G37: =E37-F37 -> 58055.763 | H37: =E37/C37 -> 0.033920613 | I37: =IF(F37=0,999,E37/F37) -> 1.4370912 | J37: =IF(AND(C37<=Inputs!B22,D37<=Inputs!B23,G37>0,I37>=Inputs!B24,A37<=Inputs!B29),"YES","NO") -> NO | K37: =IF(J37="YES",G37,-1) -> -1
A38: 48 | B38: =A38*Inputs!B11 -> 1632 | C38: =Inputs!B10+Inputs!B14+(B38*Inputs!B12+A38*Inputs!B13)*(1+Inputs!B15) -> 5722480 | D38: =C38*(1-Inputs!B19) -> 3719612 | E38: =A38*Investment!B2*Inputs!B9*Inputs!B8*(1-Inputs!B16) -> 194940 | F38: =IF(Inputs!B19=0,0,IF(Inputs!B20=0,C38*Inputs!B19/Inputs!B21,-PMT(Inputs!B20,Inputs!B21,C38*Inputs!B19))) -> 135071.47 | G38: =E38-F38 -> 59868.529 | H38: =E38/C38 -> 0.03406565 | I38: =IF(F38=0,999,E38/F38) -> 1.4432359 | J38: =IF(AND(C38<=Inputs!B22,D38<=Inputs!B23,G38>0,I38>=Inputs!B24,A38<=Inputs!B29),"YES","NO") -> NO | K38: =IF(J38="YES",G38,-1) -> -1
A39: 49 | B39: =A39*Inputs!B11 -> 1666 | C39: =Inputs!B10+Inputs!B14+(B39*Inputs!B12+A39*Inputs!B13)*(1+Inputs!B15) -> 5817740 | D39: =C39*(1-Inputs!B19) -> 3781531 | E39: =A39*Investment!B2*Inputs!B9*Inputs!B8*(1-Inputs!B16) -> 199001.25 | F39: =IF(Inputs!B19=0,0,IF(Inputs!B20=0,C39*Inputs!B19/Inputs!B21,-PMT(Inputs!B20,Inputs!B21,C39*Inputs!B19))) -> 137319.96 | G39: =E39-F39 -> 61681.294 | H39: =E39/C39 -> 0.034205937 | I39: =IF(F39=0,999,E39/F39) -> 1.4491794 | J39: =IF(AND(C39<=Inputs!B22,D39<=Inputs!B23,G39>0,I39>=Inputs!B24,A39<=Inputs!B29),"YES","NO") -> NO | K39: =IF(J39="YES",G39,-1) -> -1
A40: 50 | B40: =A40*Inputs!B11 -> 1700 | C40: =Inputs!B10+Inputs!B14+(B40*Inputs!B12+A40*Inputs!B13)*(1+Inputs!B15) -> 5913000 | D40: =C40*(1-Inputs!B19) -> 3843450 | E40: =A40*Investment!B2*Inputs!B9*Inputs!B8*(1-Inputs!B16) -> 203062.5 | F40: =IF(Inputs!B19=0,0,IF(Inputs!B20=0,C40*Inputs!B19/Inputs!B21,-PMT(Inputs!B20,Inputs!B21,C40*Inputs!B19))) -> 139568.44 | G40: =E40-F40 -> 63494.06 | H40: =E40/C40 -> 0.034341705 | I40: =IF(F40=0,999,E40/F40) -> 1.4549314 | J40: =IF(AND(C40<=Inputs!B22,D40<=Inputs!B23,G40>0,I40>=Inputs!B24,A40<=Inputs!B29),"YES","NO") -> NO | K40: =IF(J40="YES",G40,-1) -> -1
A41: 51 | B41: =A41*Inputs!B11 -> 1734 | C41: =Inputs!B10+Inputs!B14+(B41*Inputs!B12+A41*Inputs!B13)*(1+Inputs!B15) -> 6008260 | D41: =C41*(1-Inputs!B19) -> 3905369 | E41: =A41*Investment!B2*Inputs!B9*Inputs!B8*(1-Inputs!B16) -> 207123.75 | F41: =IF(Inputs!B19=0,0,IF(Inputs!B20=0,C41*Inputs!B19/Inputs!B21,-PMT(Inputs!B20,Inputs!B21,C41*Inputs!B19))) -> 141816.93 | G41: =E41-F41 -> 65306.825 | H41: =E41/C41 -> 0.034473167 | I41: =IF(F41=0,999,E41/F41) -> 1.4605009 | J41: =IF(AND(C41<=Inputs!B22,D41<=Inputs!B23,G41>0,I41>=Inputs!B24,A41<=Inputs!B29),"YES","NO") -> NO | K41: =IF(J41="YES",G41,-1) -> -1
A42: 52 | B42: =A42*Inputs!B11 -> 1768 | C42: =Inputs!B10+Inputs!B14+(B42*Inputs!B12+A42*Inputs!B13)*(1+Inputs!B15) -> 6103520 | D42: =C42*(1-Inputs!B19) -> 3967288 | E42: =A42*Investment!B2*Inputs!B9*Inputs!B8*(1-Inputs!B16) -> 211185 | F42: =IF(Inputs!B19=0,0,IF(Inputs!B20=0,C42*Inputs!B19/Inputs!B21,-PMT(Inputs!B20,Inputs!B21,C42*Inputs!B19))) -> 144065.41 | G42: =E42-F42 -> 67119.59 | H42: =E42/C42 -> 0.034600526 | I42: =IF(F42=0,999,E42/F42) -> 1.4658966 | J42: =IF(AND(C42<=Inputs!B22,D42<=Inputs!B23,G42>0,I42>=Inputs!B24,A42<=Inputs!B29),"YES","NO") -> NO | K42: =IF(J42="YES",G42,-1) -> -1
A43: 53 | B43: =A43*Inputs!B11 -> 1802 | C43: =Inputs!B10+Inputs!B14+(B43*Inputs!B12+A43*Inputs!B13)*(1+Inputs!B15) -> 6198780 | D43: =C43*(1-Inputs!B19) -> 4029207 | E43: =A43*Investment!B2*Inputs!B9*Inputs!B8*(1-Inputs!B16) -> 215246.25 | F43: =IF(Inputs!B19=0,0,IF(Inputs!B20=0,C43*Inputs!B19/Inputs!B21,-PMT(Inputs!B20,Inputs!B21,C43*Inputs!B19))) -> 146313.89 | G43: =E43-F43 -> 68932.356 | H43: =E43/C43 -> 0.03472397 | I43: =IF(F43=0,999,E43/F43) -> 1.4711265 | J43: =IF(AND(C43<=Inputs!B22,D43<=Inputs!B23,G43>0,I43>=Inputs!B24,A43<=Inputs!B29),"YES","NO") -> NO | K43: =IF(J43="YES",G43,-1) -> -1
A44: 54 | B44: =A44*Inputs!B11 -> 1836 | C44: =Inputs!B10+Inputs!B14+(B44*Inputs!B12+A44*Inputs!B13)*(1+Inputs!B15) -> 6294040 | D44: =C44*(1-Inputs!B19) -> 4091126 | E44: =A44*Investment!B2*Inputs!B9*Inputs!B8*(1-Inputs!B16) -> 219307.5 | F44: =IF(Inputs!B19=0,0,IF(Inputs!B20=0,C44*Inputs!B19/Inputs!B21,-PMT(Inputs!B20,Inputs!B21,C44*Inputs!B19))) -> 148562.38 | G44: =E44-F44 -> 70745.121 | H44: =E44/C44 -> 0.034843678 | I44: =IF(F44=0,999,E44/F44) -> 1.4761981 | J44: =IF(AND(C44<=Inputs!B22,D44<=Inputs!B23,G44>0,I44>=Inputs!B24,A44<=Inputs!B29),"YES","NO") -> NO | K44: =IF(J44="YES",G44,-1) -> -1
A45: 55 | B45: =A45*Inputs!B11 -> 1870 | C45: =Inputs!B10+Inputs!B14+(B45*Inputs!B12+A45*Inputs!B13)*(1+Inputs!B15) -> 6389300 | D45: =C45*(1-Inputs!B19) -> 4153045 | E45: =A45*Investment!B2*Inputs!B9*Inputs!B8*(1-Inputs!B16) -> 223368.75 | F45: =IF(Inputs!B19=0,0,IF(Inputs!B20=0,C45*Inputs!B19/Inputs!B21,-PMT(Inputs!B20,Inputs!B21,C45*Inputs!B19))) -> 150810.86 | G45: =E45-F45 -> 72557.886 | H45: =E45/C45 -> 0.034959816 | I45: =IF(F45=0,999,E45/F45) -> 1.4811184 | J45: =IF(AND(C45<=Inputs!B22,D45<=Inputs!B23,G45>0,I45>=Inputs!B24,A45<=Inputs!B29),"YES","NO") -> NO | K45: =IF(J45="YES",G45,-1) -> -1
A46: 56 | B46: =A46*Inputs!B11 -> 1904 | C46: =Inputs!B10+Inputs!B14+(B46*Inputs!B12+A46*Inputs!B13)*(1+Inputs!B15) -> 6484560 | D46: =C46*(1-Inputs!B19) -> 4214964 | E46: =A46*Investment!B2*Inputs!B9*Inputs!B8*(1-Inputs!B16) -> 227430 | F46: =IF(Inputs!B19=0,0,IF(Inputs!B20=0,C46*Inputs!B19/Inputs!B21,-PMT(Inputs!B20,Inputs!B21,C46*Inputs!B19))) -> 153059.35 | G46: =E46-F46 -> 74370.652 | H46: =E46/C46 -> 0.035072542 | I46: =IF(F46=0,999,E46/F46) -> 1.4858942 | J46: =IF(AND(C46<=Inputs!B22,D46<=Inputs!B23,G46>0,I46>=Inputs!B24,A46<=Inputs!B29),"YES","NO") -> NO | K46: =IF(J46="YES",G46,-1) -> -1
A47: 57 | B47: =A47*Inputs!B11 -> 1938 | C47: =Inputs!B10+Inputs!B14+(B47*Inputs!B12+A47*Inputs!B13)*(1+Inputs!B15) -> 6579820 | D47: =C47*(1-Inputs!B19) -> 4276883 | E47: =A47*Investment!B2*Inputs!B9*Inputs!B8*(1-Inputs!B16) -> 231491.25 | F47: =IF(Inputs!B19=0,0,IF(Inputs!B20=0,C47*Inputs!B19/Inputs!B21,-PMT(Inputs!B20,Inputs!B21,C47*Inputs!B19))) -> 155307.83 | G47: =E47-F47 -> 76183.417 | H47: =E47/C47 -> 0.035182003 | I47: =IF(F47=0,999,E47/F47) -> 1.4905317 | J47: =IF(AND(C47<=Inputs!B22,D47<=Inputs!B23,G47>0,I47>=Inputs!B24,A47<=Inputs!B29),"YES","NO") -> NO | K47: =IF(J47="YES",G47,-1) -> -1
A48: 58 | B48: =A48*Inputs!B11 -> 1972 | C48: =Inputs!B10+Inputs!B14+(B48*Inputs!B12+A48*Inputs!B13)*(1+Inputs!B15) -> 6675080 | D48: =C48*(1-Inputs!B19) -> 4338802 | E48: =A48*Investment!B2*Inputs!B9*Inputs!B8*(1-Inputs!B16) -> 235552.5 | F48: =IF(Inputs!B19=0,0,IF(Inputs!B20=0,C48*Inputs!B19/Inputs!B21,-PMT(Inputs!B20,Inputs!B21,C48*Inputs!B19))) -> 157556.32 | G48: =E48-F48 -> 77996.182 | H48: =E48/C48 -> 0.035288341 | I48: =IF(F48=0,999,E48/F48) -> 1.4950368 | J48: =IF(AND(C48<=Inputs!B22,D48<=Inputs!B23,G48>0,I48>=Inputs!B24,A48<=Inputs!B29),"YES","NO") -> NO | K48: =IF(J48="YES",G48,-1) -> -1
A49: 59 | B49: =A49*Inputs!B11 -> 2006 | C49: =Inputs!B10+Inputs!B14+(B49*Inputs!B12+A49*Inputs!B13)*(1+Inputs!B15) -> 6770340 | D49: =C49*(1-Inputs!B19) -> 4400721 | E49: =A49*Investment!B2*Inputs!B9*Inputs!B8*(1-Inputs!B16) -> 239613.75 | F49: =IF(Inputs!B19=0,0,IF(Inputs!B20=0,C49*Inputs!B19/Inputs!B21,-PMT(Inputs!B20,Inputs!B21,C49*Inputs!B19))) -> 159804.8 | G49: =E49-F49 -> 79808.948 | H49: =E49/C49 -> 0.035391686 | I49: =IF(F49=0,999,E49/F49) -> 1.4994152 | J49: =IF(AND(C49<=Inputs!B22,D49<=Inputs!B23,G49>0,I49>=Inputs!B24,A49<=Inputs!B29),"YES","NO") -> NO | K49: =IF(J49="YES",G49,-1) -> -1
A50: 60 | B50: =A50*Inputs!B11 -> 2040 | C50: =Inputs!B10+Inputs!B14+(B50*Inputs!B12+A50*Inputs!B13)*(1+Inputs!B15) -> 6865600 | D50: =C50*(1-Inputs!B19) -> 4462640 | E50: =A50*Investment!B2*Inputs!B9*Inputs!B8*(1-Inputs!B16) -> 243675 | F50: =IF(Inputs!B19=0,0,IF(Inputs!B20=0,C50*Inputs!B19/Inputs!B21,-PMT(Inputs!B20,Inputs!B21,C50*Inputs!B19))) -> 162053.29 | G50: =E50-F50 -> 81621.713 | H50: =E50/C50 -> 0.035492164 | I50: =IF(F50=0,999,E50/F50) -> 1.5036721 | J50: =IF(AND(C50<=Inputs!B22,D50<=Inputs!B23,G50>0,I50>=Inputs!B24,A50<=Inputs!B29),"YES","NO") -> NO | K50: =IF(J50="YES",G50,-1) -> -1
A51: 61 | B51: =A51*Inputs!B11 -> 2074 | C51: =Inputs!B10+Inputs!B14+(B51*Inputs!B12+A51*Inputs!B13)*(1+Inputs!B15) -> 6960860 | D51: =C51*(1-Inputs!B19) -> 4524559 | E51: =A51*Investment!B2*Inputs!B9*Inputs!B8*(1-Inputs!B16) -> 247736.25 | F51: =IF(Inputs!B19=0,0,IF(Inputs!B20=0,C51*Inputs!B19/Inputs!B21,-PMT(Inputs!B20,Inputs!B21,C51*Inputs!B19))) -> 164301.77 | G51: =E51-F51 -> 83434.479 | H51: =E51/C51 -> 0.035589891 | I51: =IF(F51=0,999,E51/F51) -> 1.5078124 | J51: =IF(AND(C51<=Inputs!B22,D51<=Inputs!B23,G51>0,I51>=Inputs!B24,A51<=Inputs!B29),"YES","NO") -> NO | K51: =IF(J51="YES",G51,-1) -> -1
A52: 62 | B52: =A52*Inputs!B11 -> 2108 | C52: =Inputs!B10+Inputs!B14+(B52*Inputs!B12+A52*Inputs!B13)*(1+Inputs!B15) -> 7056120 | D52: =C52*(1-Inputs!B19) -> 4586478 | E52: =A52*Investment!B2*Inputs!B9*Inputs!B8*(1-Inputs!B16) -> 251797.5 | F52: =IF(Inputs!B19=0,0,IF(Inputs!B20=0,C52*Inputs!B19/Inputs!B21,-PMT(Inputs!B20,Inputs!B21,C52*Inputs!B19))) -> 166550.26 | G52: =E52-F52 -> 85247.244 | H52: =E52/C52 -> 0.03568498 | I52: =IF(F52=0,999,E52/F52) -> 1.511841 | J52: =IF(AND(C52<=Inputs!B22,D52<=Inputs!B23,G52>0,I52>=Inputs!B24,A52<=Inputs!B29),"YES","NO") -> NO | K52: =IF(J52="YES",G52,-1) -> -1
A53: 63 | B53: =A53*Inputs!B11 -> 2142 | C53: =Inputs!B10+Inputs!B14+(B53*Inputs!B12+A53*Inputs!B13)*(1+Inputs!B15) -> 7151380 | D53: =C53*(1-Inputs!B19) -> 4648397 | E53: =A53*Investment!B2*Inputs!B9*Inputs!B8*(1-Inputs!B16) -> 255858.75 | F53: =IF(Inputs!B19=0,0,IF(Inputs!B20=0,C53*Inputs!B19/Inputs!B21,-PMT(Inputs!B20,Inputs!B21,C53*Inputs!B19))) -> 168798.74 | G53: =E53-F53 -> 87060.009 | H53: =E53/C53 -> 0.035777535 | I53: =IF(F53=0,999,E53/F53) -> 1.5157622 | J53: =IF(AND(C53<=Inputs!B22,D53<=Inputs!B23,G53>0,I53>=Inputs!B24,A53<=Inputs!B29),"YES","NO") -> NO | K53: =IF(J53="YES",G53,-1) -> -1
A54: 64 | B54: =A54*Inputs!B11 -> 2176 | C54: =Inputs!B10+Inputs!B14+(B54*Inputs!B12+A54*Inputs!B13)*(1+Inputs!B15) -> 7246640 | D54: =C54*(1-Inputs!B19) -> 4710316 | E54: =A54*Investment!B2*Inputs!B9*Inputs!B8*(1-Inputs!B16) -> 259920 | F54: =IF(Inputs!B19=0,0,IF(Inputs!B20=0,C54*Inputs!B19/Inputs!B21,-PMT(Inputs!B20,Inputs!B21,C54*Inputs!B19))) -> 171047.23 | G54: =E54-F54 -> 88872.775 | H54: =E54/C54 -> 0.035867657 | I54: =IF(F54=0,999,E54/F54) -> 1.5195803 | J54: =IF(AND(C54<=Inputs!B22,D54<=Inputs!B23,G54>0,I54>=Inputs!B24,A54<=Inputs!B29),"YES","NO") -> NO | K54: =IF(J54="YES",G54,-1) -> -1
A55: 65 | B55: =A55*Inputs!B11 -> 2210 | C55: =Inputs!B10+Inputs!B14+(B55*Inputs!B12+A55*Inputs!B13)*(1+Inputs!B15) -> 7341900 | D55: =C55*(1-Inputs!B19) -> 4772235 | E55: =A55*Investment!B2*Inputs!B9*Inputs!B8*(1-Inputs!B16) -> 263981.25 | F55: =IF(Inputs!B19=0,0,IF(Inputs!B20=0,C55*Inputs!B19/Inputs!B21,-PMT(Inputs!B20,Inputs!B21,C55*Inputs!B19))) -> 173295.71 | G55: =E55-F55 -> 90685.54 | H55: =E55/C55 -> 0.035955441 | I55: =IF(F55=0,999,E55/F55) -> 1.5232994 | J55: =IF(AND(C55<=Inputs!B22,D55<=Inputs!B23,G55>0,I55>=Inputs!B24,A55<=Inputs!B29),"YES","NO") -> NO | K55: =IF(J55="YES",G55,-1) -> -1
A56: 66 | B56: =A56*Inputs!B11 -> 2244 | C56: =Inputs!B10+Inputs!B14+(B56*Inputs!B12+A56*Inputs!B13)*(1+Inputs!B15) -> 7437160 | D56: =C56*(1-Inputs!B19) -> 4834154 | E56: =A56*Investment!B2*Inputs!B9*Inputs!B8*(1-Inputs!B16) -> 268042.5 | F56: =IF(Inputs!B19=0,0,IF(Inputs!B20=0,C56*Inputs!B19/Inputs!B21,-PMT(Inputs!B20,Inputs!B21,C56*Inputs!B19))) -> 175544.19 | G56: =E56-F56 -> 92498.305 | H56: =E56/C56 -> 0.036040975 | I56: =IF(F56=0,999,E56/F56) -> 1.5269232 | J56: =IF(AND(C56<=Inputs!B22,D56<=Inputs!B23,G56>0,I56>=Inputs!B24,A56<=Inputs!B29),"YES","NO") -> NO | K56: =IF(J56="YES",G56,-1) -> -1
A57: 67 | B57: =A57*Inputs!B11 -> 2278 | C57: =Inputs!B10+Inputs!B14+(B57*Inputs!B12+A57*Inputs!B13)*(1+Inputs!B15) -> 7532420 | D57: =C57*(1-Inputs!B19) -> 4896073 | E57: =A57*Investment!B2*Inputs!B9*Inputs!B8*(1-Inputs!B16) -> 272103.75 | F57: =IF(Inputs!B19=0,0,IF(Inputs!B20=0,C57*Inputs!B19/Inputs!B21,-PMT(Inputs!B20,Inputs!B21,C57*Inputs!B19))) -> 177792.68 | G57: =E57-F57 -> 94311.071 | H57: =E57/C57 -> 0.036124346 | I57: =IF(F57=0,999,E57/F57) -> 1.5304553 | J57: =IF(AND(C57<=Inputs!B22,D57<=Inputs!B23,G57>0,I57>=Inputs!B24,A57<=Inputs!B29),"YES","NO") -> NO | K57: =IF(J57="YES",G57,-1) -> -1
A58: 68 | B58: =A58*Inputs!B11 -> 2312 | C58: =Inputs!B10+Inputs!B14+(B58*Inputs!B12+A58*Inputs!B13)*(1+Inputs!B15) -> 7627680 | D58: =C58*(1-Inputs!B19) -> 4957992 | E58: =A58*Investment!B2*Inputs!B9*Inputs!B8*(1-Inputs!B16) -> 276165 | F58: =IF(Inputs!B19=0,0,IF(Inputs!B20=0,C58*Inputs!B19/Inputs!B21,-PMT(Inputs!B20,Inputs!B21,C58*Inputs!B19))) -> 180041.16 | G58: =E58-F58 -> 96123.836 | H58: =E58/C58 -> 0.036205635 | I58: =IF(F58=0,999,E58/F58) -> 1.5338992 | J58: =IF(AND(C58<=Inputs!B22,D58<=Inputs!B23,G58>0,I58>=Inputs!B24,A58<=Inputs!B29),"YES","NO") -> NO | K58: =IF(J58="YES",G58,-1) -> -1
A59: 69 | B59: =A59*Inputs!B11 -> 2346 | C59: =Inputs!B10+Inputs!B14+(B59*Inputs!B12+A59*Inputs!B13)*(1+Inputs!B15) -> 7722940 | D59: =C59*(1-Inputs!B19) -> 5019911 | E59: =A59*Investment!B2*Inputs!B9*Inputs!B8*(1-Inputs!B16) -> 280226.25 | F59: =IF(Inputs!B19=0,0,IF(Inputs!B20=0,C59*Inputs!B19/Inputs!B21,-PMT(Inputs!B20,Inputs!B21,C59*Inputs!B19))) -> 182289.65 | G59: =E59-F59 -> 97936.601 | H59: =E59/C59 -> 0.036284919 | I59: =IF(F59=0,999,E59/F59) -> 1.5372582 | J59: =IF(AND(C59<=Inputs!B22,D59<=Inputs!B23,G59>0,I59>=Inputs!B24,A59<=Inputs!B29),"YES","NO") -> NO | K59: =IF(J59="YES",G59,-1) -> -1
A60: 70 | B60: =A60*Inputs!B11 -> 2380 | C60: =Inputs!B10+Inputs!B14+(B60*Inputs!B12+A60*Inputs!B13)*(1+Inputs!B15) -> 7818200 | D60: =C60*(1-Inputs!B19) -> 5081830 | E60: =A60*Investment!B2*Inputs!B9*Inputs!B8*(1-Inputs!B16) -> 284287.5 | F60: =IF(Inputs!B19=0,0,IF(Inputs!B20=0,C60*Inputs!B19/Inputs!B21,-PMT(Inputs!B20,Inputs!B21,C60*Inputs!B19))) -> 184538.13 | G60: =E60-F60 -> 99749.367 | H60: =E60/C60 -> 0.03636227 | I60: =IF(F60=0,999,E60/F60) -> 1.5405353 | J60: =IF(AND(C60<=Inputs!B22,D60<=Inputs!B23,G60>0,I60>=Inputs!B24,A60<=Inputs!B29),"YES","NO") -> NO | K60: =IF(J60="YES",G60,-1) -> -1
A61: 71 | B61: =A61*Inputs!B11 -> 2414 | C61: =Inputs!B10+Inputs!B14+(B61*Inputs!B12+A61*Inputs!B13)*(1+Inputs!B15) -> 7913460 | D61: =C61*(1-Inputs!B19) -> 5143749 | E61: =A61*Investment!B2*Inputs!B9*Inputs!B8*(1-Inputs!B16) -> 288348.75 | F61: =IF(Inputs!B19=0,0,IF(Inputs!B20=0,C61*Inputs!B19/Inputs!B21,-PMT(Inputs!B20,Inputs!B21,C61*Inputs!B19))) -> 186786.62 | G61: =E61-F61 -> 101562.13 | H61: =E61/C61 -> 0.036437759 | I61: =IF(F61=0,999,E61/F61) -> 1.5437335 | J61: =IF(AND(C61<=Inputs!B22,D61<=Inputs!B23,G61>0,I61>=Inputs!B24,A61<=Inputs!B29),"YES","NO") -> NO | K61: =IF(J61="YES",G61,-1) -> -1
A62: 72 | B62: =A62*Inputs!B11 -> 2448 | C62: =Inputs!B10+Inputs!B14+(B62*Inputs!B12+A62*Inputs!B13)*(1+Inputs!B15) -> 8008720 | D62: =C62*(1-Inputs!B19) -> 5205668 | E62: =A62*Investment!B2*Inputs!B9*Inputs!B8*(1-Inputs!B16) -> 292410 | F62: =IF(Inputs!B19=0,0,IF(Inputs!B20=0,C62*Inputs!B19/Inputs!B21,-PMT(Inputs!B20,Inputs!B21,C62*Inputs!B19))) -> 189035.1 | G62: =E62-F62 -> 103374.9 | H62: =E62/C62 -> 0.036511453 | I62: =IF(F62=0,999,E62/F62) -> 1.5468556 | J62: =IF(AND(C62<=Inputs!B22,D62<=Inputs!B23,G62>0,I62>=Inputs!B24,A62<=Inputs!B29),"YES","NO") -> NO | K62: =IF(J62="YES",G62,-1) -> -1
A63: 73 | B63: =A63*Inputs!B11 -> 2482 | C63: =Inputs!B10+Inputs!B14+(B63*Inputs!B12+A63*Inputs!B13)*(1+Inputs!B15) -> 8103980 | D63: =C63*(1-Inputs!B19) -> 5267587 | E63: =A63*Investment!B2*Inputs!B9*Inputs!B8*(1-Inputs!B16) -> 296471.25 | F63: =IF(Inputs!B19=0,0,IF(Inputs!B20=0,C63*Inputs!B19/Inputs!B21,-PMT(Inputs!B20,Inputs!B21,C63*Inputs!B19))) -> 191283.59 | G63: =E63-F63 -> 105187.66 | H63: =E63/C63 -> 0.036583413 | I63: =IF(F63=0,999,E63/F63) -> 1.5499043 | J63: =IF(AND(C63<=Inputs!B22,D63<=Inputs!B23,G63>0,I63>=Inputs!B24,A63<=Inputs!B29),"YES","NO") -> NO | K63: =IF(J63="YES",G63,-1) -> -1
A64: 74 | B64: =A64*Inputs!B11 -> 2516 | C64: =Inputs!B10+Inputs!B14+(B64*Inputs!B12+A64*Inputs!B13)*(1+Inputs!B15) -> 8199240 | D64: =C64*(1-Inputs!B19) -> 5329506 | E64: =A64*Investment!B2*Inputs!B9*Inputs!B8*(1-Inputs!B16) -> 300532.5 | F64: =IF(Inputs!B19=0,0,IF(Inputs!B20=0,C64*Inputs!B19/Inputs!B21,-PMT(Inputs!B20,Inputs!B21,C64*Inputs!B19))) -> 193532.07 | G64: =E64-F64 -> 107000.43 | H64: =E64/C64 -> 0.036653702 | I64: =IF(F64=0,999,E64/F64) -> 1.5528822 | J64: =IF(AND(C64<=Inputs!B22,D64<=Inputs!B23,G64>0,I64>=Inputs!B24,A64<=Inputs!B29),"YES","NO") -> NO | K64: =IF(J64="YES",G64,-1) -> -1
A65: 75 | B65: =A65*Inputs!B11 -> 2550 | C65: =Inputs!B10+Inputs!B14+(B65*Inputs!B12+A65*Inputs!B13)*(1+Inputs!B15) -> 8294500 | D65: =C65*(1-Inputs!B19) -> 5391425 | E65: =A65*Investment!B2*Inputs!B9*Inputs!B8*(1-Inputs!B16) -> 304593.75 | F65: =IF(Inputs!B19=0,0,IF(Inputs!B20=0,C65*Inputs!B19/Inputs!B21,-PMT(Inputs!B20,Inputs!B21,C65*Inputs!B19))) -> 195780.56 | G65: =E65-F65 -> 108813.19 | H65: =E65/C65 -> 0.036722376 | I65: =IF(F65=0,999,E65/F65) -> 1.5557916 | J65: =IF(AND(C65<=Inputs!B22,D65<=Inputs!B23,G65>0,I65>=Inputs!B24,A65<=Inputs!B29),"YES","NO") -> NO | K65: =IF(J65="YES",G65,-1) -> -1
A66: 76 | B66: =A66*Inputs!B11 -> 2584 | C66: =Inputs!B10+Inputs!B14+(B66*Inputs!B12+A66*Inputs!B13)*(1+Inputs!B15) -> 8389760 | D66: =C66*(1-Inputs!B19) -> 5453344 | E66: =A66*Investment!B2*Inputs!B9*Inputs!B8*(1-Inputs!B16) -> 308655 | F66: =IF(Inputs!B19=0,0,IF(Inputs!B20=0,C66*Inputs!B19/Inputs!B21,-PMT(Inputs!B20,Inputs!B21,C66*Inputs!B19))) -> 198029.04 | G66: =E66-F66 -> 110625.96 | H66: =E66/C66 -> 0.036789491 | I66: =IF(F66=0,999,E66/F66) -> 1.558635 | J66: =IF(AND(C66<=Inputs!B22,D66<=Inputs!B23,G66>0,I66>=Inputs!B24,A66<=Inputs!B29),"YES","NO") -> NO | K66: =IF(J66="YES",G66,-1) -> -1
A67: 77 | B67: =A67*Inputs!B11 -> 2618 | C67: =Inputs!B10+Inputs!B14+(B67*Inputs!B12+A67*Inputs!B13)*(1+Inputs!B15) -> 8485020 | D67: =C67*(1-Inputs!B19) -> 5515263 | E67: =A67*Investment!B2*Inputs!B9*Inputs!B8*(1-Inputs!B16) -> 312716.25 | F67: =IF(Inputs!B19=0,0,IF(Inputs!B20=0,C67*Inputs!B19/Inputs!B21,-PMT(Inputs!B20,Inputs!B21,C67*Inputs!B19))) -> 200277.53 | G67: =E67-F67 -> 112438.72 | H67: =E67/C67 -> 0.036855099 | I67: =IF(F67=0,999,E67/F67) -> 1.5614146 | J67: =IF(AND(C67<=Inputs!B22,D67<=Inputs!B23,G67>0,I67>=Inputs!B24,A67<=Inputs!B29),"YES","NO") -> NO | K67: =IF(J67="YES",G67,-1) -> -1
A68: 78 | B68: =A68*Inputs!B11 -> 2652 | C68: =Inputs!B10+Inputs!B14+(B68*Inputs!B12+A68*Inputs!B13)*(1+Inputs!B15) -> 8580280 | D68: =C68*(1-Inputs!B19) -> 5577182 | E68: =A68*Investment!B2*Inputs!B9*Inputs!B8*(1-Inputs!B16) -> 316777.5 | F68: =IF(Inputs!B19=0,0,IF(Inputs!B20=0,C68*Inputs!B19/Inputs!B21,-PMT(Inputs!B20,Inputs!B21,C68*Inputs!B19))) -> 202526.01 | G68: =E68-F68 -> 114251.49 | H68: =E68/C68 -> 0.03691925 | I68: =IF(F68=0,999,E68/F68) -> 1.5641324 | J68: =IF(AND(C68<=Inputs!B22,D68<=Inputs!B23,G68>0,I68>=Inputs!B24,A68<=Inputs!B29),"YES","NO") -> NO | K68: =IF(J68="YES",G68,-1) -> -1
A69: 79 | B69: =A69*Inputs!B11 -> 2686 | C69: =Inputs!B10+Inputs!B14+(B69*Inputs!B12+A69*Inputs!B13)*(1+Inputs!B15) -> 8675540 | D69: =C69*(1-Inputs!B19) -> 5639101 | E69: =A69*Investment!B2*Inputs!B9*Inputs!B8*(1-Inputs!B16) -> 320838.75 | F69: =IF(Inputs!B19=0,0,IF(Inputs!B20=0,C69*Inputs!B19/Inputs!B21,-PMT(Inputs!B20,Inputs!B21,C69*Inputs!B19))) -> 204774.49 | G69: =E69-F69 -> 116064.26 | H69: =E69/C69 -> 0.036981992 | I69: =IF(F69=0,999,E69/F69) -> 1.5667906 | J69: =IF(AND(C69<=Inputs!B22,D69<=Inputs!B23,G69>0,I69>=Inputs!B24,A69<=Inputs!B29),"YES","NO") -> NO | K69: =IF(J69="YES",G69,-1) -> -1
A70: 80 | B70: =A70*Inputs!B11 -> 2720 | C70: =Inputs!B10+Inputs!B14+(B70*Inputs!B12+A70*Inputs!B13)*(1+Inputs!B15) -> 8770800 | D70: =C70*(1-Inputs!B19) -> 5701020 | E70: =A70*Investment!B2*Inputs!B9*Inputs!B8*(1-Inputs!B16) -> 324900 | F70: =IF(Inputs!B19=0,0,IF(Inputs!B20=0,C70*Inputs!B19/Inputs!B21,-PMT(Inputs!B20,Inputs!B21,C70*Inputs!B19))) -> 207022.98 | G70: =E70-F70 -> 117877.02 | H70: =E70/C70 -> 0.037043371 | I70: =IF(F70=0,999,E70/F70) -> 1.569391 | J70: =IF(AND(C70<=Inputs!B22,D70<=Inputs!B23,G70>0,I70>=Inputs!B24,A70<=Inputs!B29),"YES","NO") -> NO | K70: =IF(J70="YES",G70,-1) -> -1
A71: 81 | B71: =A71*Inputs!B11 -> 2754 | C71: =Inputs!B10+Inputs!B14+(B71*Inputs!B12+A71*Inputs!B13)*(1+Inputs!B15) -> 8866060 | D71: =C71*(1-Inputs!B19) -> 5762939 | E71: =A71*Investment!B2*Inputs!B9*Inputs!B8*(1-Inputs!B16) -> 328961.25 | F71: =IF(Inputs!B19=0,0,IF(Inputs!B20=0,C71*Inputs!B19/Inputs!B21,-PMT(Inputs!B20,Inputs!B21,C71*Inputs!B19))) -> 209271.46 | G71: =E71-F71 -> 119689.79 | H71: =E71/C71 -> 0.037103432 | I71: =IF(F71=0,999,E71/F71) -> 1.5719355 | J71: =IF(AND(C71<=Inputs!B22,D71<=Inputs!B23,G71>0,I71>=Inputs!B24,A71<=Inputs!B29),"YES","NO") -> NO | K71: =IF(J71="YES",G71,-1) -> -1
A72: 82 | B72: =A72*Inputs!B11 -> 2788 | C72: =Inputs!B10+Inputs!B14+(B72*Inputs!B12+A72*Inputs!B13)*(1+Inputs!B15) -> 8961320 | D72: =C72*(1-Inputs!B19) -> 5824858 | E72: =A72*Investment!B2*Inputs!B9*Inputs!B8*(1-Inputs!B16) -> 333022.5 | F72: =IF(Inputs!B19=0,0,IF(Inputs!B20=0,C72*Inputs!B19/Inputs!B21,-PMT(Inputs!B20,Inputs!B21,C72*Inputs!B19))) -> 211519.95 | G72: =E72-F72 -> 121502.55 | H72: =E72/C72 -> 0.037162215 | I72: =IF(F72=0,999,E72/F72) -> 1.574426 | J72: =IF(AND(C72<=Inputs!B22,D72<=Inputs!B23,G72>0,I72>=Inputs!B24,A72<=Inputs!B29),"YES","NO") -> NO | K72: =IF(J72="YES",G72,-1) -> -1
A73: 83 | B73: =A73*Inputs!B11 -> 2822 | C73: =Inputs!B10+Inputs!B14+(B73*Inputs!B12+A73*Inputs!B13)*(1+Inputs!B15) -> 9056580 | D73: =C73*(1-Inputs!B19) -> 5886777 | E73: =A73*Investment!B2*Inputs!B9*Inputs!B8*(1-Inputs!B16) -> 337083.75 | F73: =IF(Inputs!B19=0,0,IF(Inputs!B20=0,C73*Inputs!B19/Inputs!B21,-PMT(Inputs!B20,Inputs!B21,C73*Inputs!B19))) -> 213768.43 | G73: =E73-F73 -> 123315.32 | H73: =E73/C73 -> 0.037219762 | I73: =IF(F73=0,999,E73/F73) -> 1.576864 | J73: =IF(AND(C73<=Inputs!B22,D73<=Inputs!B23,G73>0,I73>=Inputs!B24,A73<=Inputs!B29),"YES","NO") -> NO | K73: =IF(J73="YES",G73,-1) -> -1
A74: 84 | B74: =A74*Inputs!B11 -> 2856 | C74: =Inputs!B10+Inputs!B14+(B74*Inputs!B12+A74*Inputs!B13)*(1+Inputs!B15) -> 9151840 | D74: =C74*(1-Inputs!B19) -> 5948696 | E74: =A74*Investment!B2*Inputs!B9*Inputs!B8*(1-Inputs!B16) -> 341145 | F74: =IF(Inputs!B19=0,0,IF(Inputs!B20=0,C74*Inputs!B19/Inputs!B21,-PMT(Inputs!B20,Inputs!B21,C74*Inputs!B19))) -> 216016.92 | G74: =E74-F74 -> 125128.08 | H74: =E74/C74 -> 0.037276111 | I74: =IF(F74=0,999,E74/F74) -> 1.5792513 | J74: =IF(AND(C74<=Inputs!B22,D74<=Inputs!B23,G74>0,I74>=Inputs!B24,A74<=Inputs!B29),"YES","NO") -> NO | K74: =IF(J74="YES",G74,-1) -> -1
A75: 85 | B75: =A75*Inputs!B11 -> 2890 | C75: =Inputs!B10+Inputs!B14+(B75*Inputs!B12+A75*Inputs!B13)*(1+Inputs!B15) -> 9247100 | D75: =C75*(1-Inputs!B19) -> 6010615 | E75: =A75*Investment!B2*Inputs!B9*Inputs!B8*(1-Inputs!B16) -> 345206.25 | F75: =IF(Inputs!B19=0,0,IF(Inputs!B20=0,C75*Inputs!B19/Inputs!B21,-PMT(Inputs!B20,Inputs!B21,C75*Inputs!B19))) -> 218265.4 | G75: =E75-F75 -> 126940.85 | H75: =E75/C75 -> 0.037331298 | I75: =IF(F75=0,999,E75/F75) -> 1.5815894 | J75: =IF(AND(C75<=Inputs!B22,D75<=Inputs!B23,G75>0,I75>=Inputs!B24,A75<=Inputs!B29),"YES","NO") -> NO | K75: =IF(J75="YES",G75,-1) -> -1
A76: 86 | B76: =A76*Inputs!B11 -> 2924 | C76: =Inputs!B10+Inputs!B14+(B76*Inputs!B12+A76*Inputs!B13)*(1+Inputs!B15) -> 9342360 | D76: =C76*(1-Inputs!B19) -> 6072534 | E76: =A76*Investment!B2*Inputs!B9*Inputs!B8*(1-Inputs!B16) -> 349267.5 | F76: =IF(Inputs!B19=0,0,IF(Inputs!B20=0,C76*Inputs!B19/Inputs!B21,-PMT(Inputs!B20,Inputs!B21,C76*Inputs!B19))) -> 220513.89 | G76: =E76-F76 -> 128753.61 | H76: =E76/C76 -> 0.037385361 | I76: =IF(F76=0,999,E76/F76) -> 1.5838798 | J76: =IF(AND(C76<=Inputs!B22,D76<=Inputs!B23,G76>0,I76>=Inputs!B24,A76<=Inputs!B29),"YES","NO") -> NO | K76: =IF(J76="YES",G76,-1) -> -1
A77: 87 | B77: =A77*Inputs!B11 -> 2958 | C77: =Inputs!B10+Inputs!B14+(B77*Inputs!B12+A77*Inputs!B13)*(1+Inputs!B15) -> 9437620 | D77: =C77*(1-Inputs!B19) -> 6134453 | E77: =A77*Investment!B2*Inputs!B9*Inputs!B8*(1-Inputs!B16) -> 353328.75 | F77: =IF(Inputs!B19=0,0,IF(Inputs!B20=0,C77*Inputs!B19/Inputs!B21,-PMT(Inputs!B20,Inputs!B21,C77*Inputs!B19))) -> 222762.37 | G77: =E77-F77 -> 130566.38 | H77: =E77/C77 -> 0.037438332 | I77: =IF(F77=0,999,E77/F77) -> 1.586124 | J77: =IF(AND(C77<=Inputs!B22,D77<=Inputs!B23,G77>0,I77>=Inputs!B24,A77<=Inputs!B29),"YES","NO") -> NO | K77: =IF(J77="YES",G77,-1) -> -1
A78: 88 | B78: =A78*Inputs!B11 -> 2992 | C78: =Inputs!B10+Inputs!B14+(B78*Inputs!B12+A78*Inputs!B13)*(1+Inputs!B15) -> 9532880 | D78: =C78*(1-Inputs!B19) -> 6196372 | E78: =A78*Investment!B2*Inputs!B9*Inputs!B8*(1-Inputs!B16) -> 357390 | F78: =IF(Inputs!B19=0,0,IF(Inputs!B20=0,C78*Inputs!B19/Inputs!B21,-PMT(Inputs!B20,Inputs!B21,C78*Inputs!B19))) -> 225010.86 | G78: =E78-F78 -> 132379.14 | H78: =E78/C78 -> 0.037490244 | I78: =IF(F78=0,999,E78/F78) -> 1.5883234 | J78: =IF(AND(C78<=Inputs!B22,D78<=Inputs!B23,G78>0,I78>=Inputs!B24,A78<=Inputs!B29),"YES","NO") -> NO | K78: =IF(J78="YES",G78,-1) -> -1
A79: 89 | B79: =A79*Inputs!B11 -> 3026 | C79: =Inputs!B10+Inputs!B14+(B79*Inputs!B12+A79*Inputs!B13)*(1+Inputs!B15) -> 9628140 | D79: =C79*(1-Inputs!B19) -> 6258291 | E79: =A79*Investment!B2*Inputs!B9*Inputs!B8*(1-Inputs!B16) -> 361451.25 | F79: =IF(Inputs!B19=0,0,IF(Inputs!B20=0,C79*Inputs!B19/Inputs!B21,-PMT(Inputs!B20,Inputs!B21,C79*Inputs!B19))) -> 227259.34 | G79: =E79-F79 -> 134191.91 | H79: =E79/C79 -> 0.037541129 | I79: =IF(F79=0,999,E79/F79) -> 1.5904792 | J79: =IF(AND(C79<=Inputs!B22,D79<=Inputs!B23,G79>0,I79>=Inputs!B24,A79<=Inputs!B29),"YES","NO") -> NO | K79: =IF(J79="YES",G79,-1) -> -1
A80: 90 | B80: =A80*Inputs!B11 -> 3060 | C80: =Inputs!B10+Inputs!B14+(B80*Inputs!B12+A80*Inputs!B13)*(1+Inputs!B15) -> 9723400 | D80: =C80*(1-Inputs!B19) -> 6320210 | E80: =A80*Investment!B2*Inputs!B9*Inputs!B8*(1-Inputs!B16) -> 365512.5 | F80: =IF(Inputs!B19=0,0,IF(Inputs!B20=0,C80*Inputs!B19/Inputs!B21,-PMT(Inputs!B20,Inputs!B21,C80*Inputs!B19))) -> 229507.83 | G80: =E80-F80 -> 136004.67 | H80: =E80/C80 -> 0.037591018 | I80: =IF(F80=0,999,E80/F80) -> 1.5925928 | J80: =IF(AND(C80<=Inputs!B22,D80<=Inputs!B23,G80>0,I80>=Inputs!B24,A80<=Inputs!B29),"YES","NO") -> NO | K80: =IF(J80="YES",G80,-1) -> -1
A81: 91 | B81: =A81*Inputs!B11 -> 3094 | C81: =Inputs!B10+Inputs!B14+(B81*Inputs!B12+A81*Inputs!B13)*(1+Inputs!B15) -> 9818660 | D81: =C81*(1-Inputs!B19) -> 6382129 | E81: =A81*Investment!B2*Inputs!B9*Inputs!B8*(1-Inputs!B16) -> 369573.75 | F81: =IF(Inputs!B19=0,0,IF(Inputs!B20=0,C81*Inputs!B19/Inputs!B21,-PMT(Inputs!B20,Inputs!B21,C81*Inputs!B19))) -> 231756.31 | G81: =E81-F81 -> 137817.44 | H81: =E81/C81 -> 0.037639938 | I81: =IF(F81=0,999,E81/F81) -> 1.5946653 | J81: =IF(AND(C81<=Inputs!B22,D81<=Inputs!B23,G81>0,I81>=Inputs!B24,A81<=Inputs!B29),"YES","NO") -> NO | K81: =IF(J81="YES",G81,-1) -> -1
A82: 92 | B82: =A82*Inputs!B11 -> 3128 | C82: =Inputs!B10+Inputs!B14+(B82*Inputs!B12+A82*Inputs!B13)*(1+Inputs!B15) -> 9913920 | D82: =C82*(1-Inputs!B19) -> 6444048 | E82: =A82*Investment!B2*Inputs!B9*Inputs!B8*(1-Inputs!B16) -> 373635 | F82: =IF(Inputs!B19=0,0,IF(Inputs!B20=0,C82*Inputs!B19/Inputs!B21,-PMT(Inputs!B20,Inputs!B21,C82*Inputs!B19))) -> 234004.8 | G82: =E82-F82 -> 139630.2 | H82: =E82/C82 -> 0.037687918 | I82: =IF(F82=0,999,E82/F82) -> 1.596698 | J82: =IF(AND(C82<=Inputs!B22,D82<=Inputs!B23,G82>0,I82>=Inputs!B24,A82<=Inputs!B29),"YES","NO") -> NO | K82: =IF(J82="YES",G82,-1) -> -1
A83: 93 | B83: =A83*Inputs!B11 -> 3162 | C83: =Inputs!B10+Inputs!B14+(B83*Inputs!B12+A83*Inputs!B13)*(1+Inputs!B15) -> 10009180 | D83: =C83*(1-Inputs!B19) -> 6505967 | E83: =A83*Investment!B2*Inputs!B9*Inputs!B8*(1-Inputs!B16) -> 377696.25 | F83: =IF(Inputs!B19=0,0,IF(Inputs!B20=0,C83*Inputs!B19/Inputs!B21,-PMT(Inputs!B20,Inputs!B21,C83*Inputs!B19))) -> 236253.28 | G83: =E83-F83 -> 141442.97 | H83: =E83/C83 -> 0.037734984 | I83: =IF(F83=0,999,E83/F83) -> 1.5986921 | J83: =IF(AND(C83<=Inputs!B22,D83<=Inputs!B23,G83>0,I83>=Inputs!B24,A83<=Inputs!B29),"YES","NO") -> NO | K83: =IF(J83="YES",G83,-1) -> -1
A84: 94 | B84: =A84*Inputs!B11 -> 3196 | C84: =Inputs!B10+Inputs!B14+(B84*Inputs!B12+A84*Inputs!B13)*(1+Inputs!B15) -> 10104440 | D84: =C84*(1-Inputs!B19) -> 6567886 | E84: =A84*Investment!B2*Inputs!B9*Inputs!B8*(1-Inputs!B16) -> 381757.5 | F84: =IF(Inputs!B19=0,0,IF(Inputs!B20=0,C84*Inputs!B19/Inputs!B21,-PMT(Inputs!B20,Inputs!B21,C84*Inputs!B19))) -> 238501.76 | G84: =E84-F84 -> 143255.74 | H84: =E84/C84 -> 0.037781164 | I84: =IF(F84=0,999,E84/F84) -> 1.6006485 | J84: =IF(AND(C84<=Inputs!B22,D84<=Inputs!B23,G84>0,I84>=Inputs!B24,A84<=Inputs!B29),"YES","NO") -> NO | K84: =IF(J84="YES",G84,-1) -> -1
A85: 95 | B85: =A85*Inputs!B11 -> 3230 | C85: =Inputs!B10+Inputs!B14+(B85*Inputs!B12+A85*Inputs!B13)*(1+Inputs!B15) -> 10199700 | D85: =C85*(1-Inputs!B19) -> 6629805 | E85: =A85*Investment!B2*Inputs!B9*Inputs!B8*(1-Inputs!B16) -> 385818.75 | F85: =IF(Inputs!B19=0,0,IF(Inputs!B20=0,C85*Inputs!B19/Inputs!B21,-PMT(Inputs!B20,Inputs!B21,C85*Inputs!B19))) -> 240750.25 | G85: =E85-F85 -> 145068.5 | H85: =E85/C85 -> 0.03782648 | I85: =IF(F85=0,999,E85/F85) -> 1.6025684 | J85: =IF(AND(C85<=Inputs!B22,D85<=Inputs!B23,G85>0,I85>=Inputs!B24,A85<=Inputs!B29),"YES","NO") -> NO | K85: =IF(J85="YES",G85,-1) -> -1
A86: 96 | B86: =A86*Inputs!B11 -> 3264 | C86: =Inputs!B10+Inputs!B14+(B86*Inputs!B12+A86*Inputs!B13)*(1+Inputs!B15) -> 10294960 | D86: =C86*(1-Inputs!B19) -> 6691724 | E86: =A86*Investment!B2*Inputs!B9*Inputs!B8*(1-Inputs!B16) -> 389880 | F86: =IF(Inputs!B19=0,0,IF(Inputs!B20=0,C86*Inputs!B19/Inputs!B21,-PMT(Inputs!B20,Inputs!B21,C86*Inputs!B19))) -> 242998.73 | G86: =E86-F86 -> 146881.27 | H86: =E86/C86 -> 0.037870958 | I86: =IF(F86=0,999,E86/F86) -> 1.6044528 | J86: =IF(AND(C86<=Inputs!B22,D86<=Inputs!B23,G86>0,I86>=Inputs!B24,A86<=Inputs!B29),"YES","NO") -> NO | K86: =IF(J86="YES",G86,-1) -> -1
A89: Recommended rooms | B89: =IF(MAX(K2:K86)<0,"No feasible candidate",INDEX(A2:A86,MATCH(MAX(K2:K86),K2:K86,0))) -> 40
A90: Scope | B90: Best of tested sizes only; site capacity, planning consent and demand must be confirmed.
A91: Minimum feasible rooms | B91: =IF(COUNTIF(J2:J86,"YES")=0,"No feasible candidate",MATCH("YES",J2:J86,0)+11) -> 24
A92: Investment recommendation | B92: Conditional screening result only: target yield, address rent and planning require separate approval.

Sheet Scenarios
A1: Scenario | B1: Rent | C1: Occupancy | D1: Cost multiplier | E1: NOI | F1: Total investment | G1: Net yield | H1: Static project payback incl. delay
A2: Downside | B2: 400 | C2: 0.9 | D2: 1.15 | E2: =Inputs!B2*MIN(B2,Inputs!B3-Inputs!B4,Inputs!B5,Inputs!B6)*Inputs!B9*C2*(1-Inputs!B16) -> 129600 | F2: =Investment!B8*D2 -> 5704460 | G2: =E2/F2 -> 0.022719065 | H2: =F2/E2+Inputs!B28 -> 46.015895
A3: Base | B3: 475 | C3: 0.95 | D3: 1 | E3: =Inputs!B2*MIN(B3,Inputs!B3-Inputs!B4,Inputs!B5,Inputs!B6)*Inputs!B9*C3*(1-Inputs!B16) -> 162450 | F3: =Investment!B8*D3 -> 4960400 | G3: =E3/F3 -> 0.032749375 | H3: =F3/E3+Inputs!B28 -> 32.534934
A4: Upside | B4: 500 | C4: 0.98 | D4: 0.95 | E4: =Inputs!B2*MIN(B4,Inputs!B3-Inputs!B4,Inputs!B5,Inputs!B6)*Inputs!B9*C4*(1-Inputs!B16) -> 176400 | F4: =Investment!B8*D4 -> 4712380 | G4: =E4/F4 -> 0.037433314 | H4: =F4/E4+Inputs!B28 -> 28.714172
A5: VUB all-in match | B5: 349.3 | C5: 0.95 | D5: 1 | E5: =Inputs!B2*MIN(B5,Inputs!B3-Inputs!B4,Inputs!B5,Inputs!B6)*Inputs!B9*C5*(1-Inputs!B16) -> 119460.6 | F5: =Investment!B8*D5 -> 4960400 | G5: =E5/F5 -> 0.024082856 | H5: =F5/E5+Inputs!B28 -> 43.523314

Sheet Sources
A1: Item | B1: Source / URL | C1: Finding | D1: Accessed / status
A2: Private market room benchmark | B2: https://www.brukot.be/en/student-guide/rent-stats | C2: Own listing/residence statistics: student room median EUR500 excluding charges / EUR590 including charges; all housing median EUR550 / EUR650. Brussels-wide, not VUB-specific. | D2: 2026-10-14
A3: VUB standard student room | B3: https://www.vub.be/en/studying-vub/practical-info-for-students/student-housing/practical-housing-information | C3: 2026-27 standard room EUR449.30 all-in. Eligibility and limited availability; not a private investor rent cap. | D3: 2026-10-14
A4: Brussels reference rent rule | B4: https://be.brussels/nl/huisvesting/huren-en-verhuren/huurovereenkomst/referentiehuurprijs | C4: Reference must be disclosed. Above reference by more than 20% presumed excessive, rebuttable; defects can make lower rent excessive. No excessive rent since 1 May 2025. | D4: 2026-10-14
A5: Address-specific reference calculator | B5: https://loyers.brussels/ | C5: Enter actual address and dwelling characteristics; student/shared dwelling treatment needs confirmation. Placeholder in model is NOT verified legal clearance. | D5: 2026-10-14
A6: 2026 quality standards | B6: https://be.brussels/en/housing/new-minimum-quality-standards-2026 | C6: Student accommodation minimum net surface 12 m²; other safety, health, equipment and layout rules apply. Gross project area is a separate planning assumption. | D6: 2026-10-14
A7: Lease steps | B7: https://be.brussels/en/housing/rental/steps-renting-and-leasing | C7: Regional guidance: student lease 12 months; registration required. Cash flow stress tests cover fewer collected months. | D7: 2026-10-14
A8: Investment and financing assumptions | B8: No external quotation | C8: Land EUR900k; fixed costs EUR250k; construction EUR2400/gross m² VAT-inclusive assumption; furnishing EUR5k/room; 10% contingency; financing 4.5% over 25 years. Require quotes. | D8: ASSUMPTIONS
