Workbook

Sheet Executive Report
A1: BRUSSELS | EXECUTIVE INVESTMENT REPORT | B1: Result / decision | C1: Criterion / explanation
A2: Net present value EUR | B2: =SUM('Cash Flow'!L2:L62) -> 1.7992543e+08 | C2: Must be strictly positive
A3: Unlevered project IRR | B3: =IFERROR(IRR('Cash Flow'!J2:J62),"Not defined") -> 0.33503129 | C3: Must exceed effective nominal discount rate
A4: Simple payback years from t=0 | B4: =IF(MAX('Cash Flow'!O2:O62)>0,MAX('Cash Flow'!O2:O62),"Not reached") -> 4.1806919 | C4: Maximum 10 years; fractional year interpolation
A5: Discounted payback years from t=0 | B5: =IF(MAX('Cash Flow'!P2:P62)>0,MAX('Cash Flow'!P2:P62),"Not reached") -> 4.4861513 | C5: Supplementary conservative cash-recovery measure
A6: Effective discount rate | B6: =Inputs!B17 -> 0.043 | C6: Official Belgian reference + editable project risk premium
A7: Construction budget per room EUR | B7: =Inputs!B19 -> 7500 | C7: EUR 15 million / 2,000 rooms
A8: First operating year collected rent EUR | B8: =INDEX('Cash Flow'!E2:E62,Inputs!B6+2) -> 10260000 | C8: 95% occupancy assumption
A9: First operating year net cash flow EUR | B9: =INDEX('Cash Flow'!J2:J62,Inputs!B6+2) -> 6669000 | C9: After 30% operating costs and 5% maintenance reserve
A10: Financial tests | B10: =IF(AND(B2>0,ISNUMBER(B3),B3>B6,ISNUMBER(B4),B4<=Inputs!B12),"PASS","FAIL") -> PASS | C10: NPV, IRR and simple payback; excludes validation of physical feasibility
A11: Construction spending within budget | B11: =IF(SUM('Cash Flow'!H2:H62)-Inputs!B13<=Inputs!B5,"PASS","FAIL") -> PASS | C11: Cost is entered as budget, not independently estimated; this check is mechanical
A12: Input consistency | B12: =IF(AND(Inputs!B3<=450,Inputs!B3>0,Inputs!B9+Inputs!B10<1,Inputs!B6+Inputs!B7<=60,Inputs!B8>0),"PASS","REVIEW INPUTS") -> PASS | C12: Rent cap, positive occupancy, expense ratios, supported horizon
A13: Recommendation | B13: Proceed only to feasibility and cost validation. Financial screening passes, but do not approve construction on these assumptions.
A14: Budget feasibility | B14: EUR 7,500 per room is the stated budget implication, not a verified Brussels construction estimate. Confirm whether EUR 15m or 2,000 rooms needs revision.
A15: Construction and timing | B15: Build during t=0 to t=2; equal construction payments at t=0 and t=1. Opening at t=2; annual operating receipts at t=3 onward. No income during construction.
A16: Rent interpretation | B16: EUR 450 applies at opening; 5% growth begins in operating year 2. Year 30 rent is about EUR 1,852 per month; the affordability cap grows with the assumed inflation.
A17: Belgian rate | B17: 4.30% is the Belgian Federal Debt Agency 10-year sovereign yield dated 14 October 2026, used as an official benchmark. It is not an authority-prescribed property discount rate.
A18: Project risk | B18: A zero premium is used to match the requested official benchmark. Add a lender/investor-approved risk premium before investment approval; see stress scenarios.
A19: Indexation | B19: Brussels residential indexation follows the health index and applicable lease requirements. Fixed 5% annual growth is a financial scenario, not an automatic contractual entitlement.
A20: Operating assumptions | B20: 95% occupancy, 30% operating costs and 5% maintenance reserve are unverified assumptions. Occupancy is applied to all 12 months; no leasing ramp is assumed.
A21: Model scope | B21: Unlevered nominal pre-tax cash flows; no borrowing, income tax, or separately estimated land/VAT/professional costs. Enter omitted upfront costs in Inputs B13. Zero terminal value.
A22: Payback method | B22: Measured from t=0 including two construction years. Simple and discounted recovery use interpolation inside the crossing year; NPV uses end-of-year operating receipts.
A23: Action before commitment | B23: Validate land and planning capacity for 2,000 rooms, gross floor area, permits, procurement costs, VAT, financing, legal rent indexation and operating contracts.
A24: Use and reproduction | B24: Edit blue Inputs cells; Excel recalculates formulas. Supported range: up to 10 construction years and 50 operating years. Scenarios are explicit stresses, not forecasts. Code: build_model.py.

Sheet Inputs
A1: BRUSSELS INVESTMENT | editable blue cells | B1: Value | C1: Basis / interpretation
A2: Rooms | B2: 2000 | C2: User requirement
A3: Opening monthly rent EUR | B3: 450 | C3: Maximum rent at opening; assumed exclusive of charges
A4: Annual rent escalation | B4: 0.05 | C4: User scenario; not a guarantee of legally permitted indexation
A5: Construction budget EUR | B5: 15000000 | C5: User construction budget; excludes extra costs entered below
A6: Construction years | B6: 2 | C6: User requirement; opening at t=2, first annual receipt t=3
A7: Operating years | B7: 30 | C7: Assumption; no terminal resale value in base case
A8: Occupancy | B8: 0.95 | C8: Assumption; constant stabilized occupancy from opening
A9: Operating costs / collected rent | B9: 0.3 | C9: Assumption: management, utilities paid by owner, insurance, local property costs
A10: Maintenance reserve / collected rent | B10: 0.05 | C10: Assumption; additional reserve, treated as a cash outflow
A11: Belgian official reference yield | B11: 0.043 | C11: Belgian Federal Debt Agency: 10-year rate 4.30%, dated 14 October 2026
A12: Maximum payback years from investment | B12: 10 | C12: User limit; measured from t=0 commitment
A13: Extra upfront costs EUR | B13: 0 | C13: Enter land, acquisition, professional fees, VAT or other costs not in construction budget
... A15: Project risk premium | B15: 0 | C15: Assumption; 0% for requested official-rate test. Stress case adds 4 percentage points.
A16: Effective nominal discount rate | C16: Official reference yield + project risk premium; sovereign yield is not property WACC
A17: Total modeled funding EUR | B17: =B11+B16 -> 0.043 | C17: Construction + additional upfront costs
A18: Construction budget per room EUR | B18: =B5+B13 -> 15000000 | C18: Construction cost only; requires independent contractor validation
B19: =B5/B2 -> 7500

Sheet Cash Flow
A1: Year t | B1: Phase | C1: Operating year | D1: Monthly rent EUR | E1: Collected rent EUR | F1: Operating costs EUR | G1: Maintenance reserve EUR | H1: Construction + extras EUR | I1: Terminal value EUR | J1: Free cash flow EUR | K1: Discount factor | L1: Present value EUR | M1: Cumulative cash flow EUR | N1: Cumulative PV EUR | O1: Simple payback crossing | P1: Discounted payback crossing
A2: 0 | B2: =IF(A2<Inputs!$B$6,"Construction",IF(A2=Inputs!$B$6,"Opening",IF(A2<=Inputs!$B$6+Inputs!$B$7,"Operations","Outside horizon"))) -> Construction | C2: =IF(AND(A2>Inputs!$B$6,A2<=Inputs!$B$6+Inputs!$B$7),A2-Inputs!$B$6,0) -> 0 | D2: =IF(C2>0,Inputs!$B$3*(1+Inputs!$B$4)^(C2-1),0) -> 0 | E2: =Inputs!$B$2*D2*12*Inputs!$B$8 -> 0 | F2: =E2*Inputs!$B$9 -> 0 | G2: =E2*Inputs!$B$10 -> 0 | H2: =IF(A2<Inputs!$B$6,Inputs!$B$5/Inputs!$B$6,0)+IF(A2=0,Inputs!$B$13,0) -> 7500000 | I2: =IF(A2=Inputs!$B$6+Inputs!$B$7,Inputs!$B$14,0) -> 0 | J2: =E2-F2-G2-H2+I2 -> -7500000 | K2: =1/(1+Inputs!$B$17)^A2 -> 1 | L2: =J2*K2 -> -7500000 | M2: =SUM(J$2:J2) -> -7500000 | N2: =SUM(L$2:L2) -> -7500000 | O2: =0 -> 0 | P2: =0 -> 0
A3: 1 | B3: =IF(A3<Inputs!$B$6,"Construction",IF(A3=Inputs!$B$6,"Opening",IF(A3<=Inputs!$B$6+Inputs!$B$7,"Operations","Outside horizon"))) -> Construction | C3: =IF(AND(A3>Inputs!$B$6,A3<=Inputs!$B$6+Inputs!$B$7),A3-Inputs!$B$6,0) -> 0 | D3: =IF(C3>0,Inputs!$B$3*(1+Inputs!$B$4)^(C3-1),0) -> 0 | E3: =Inputs!$B$2*D3*12*Inputs!$B$8 -> 0 | F3: =E3*Inputs!$B$9 -> 0 | G3: =E3*Inputs!$B$10 -> 0 | H3: =IF(A3<Inputs!$B$6,Inputs!$B$5/Inputs!$B$6,0)+IF(A3=0,Inputs!$B$13,0) -> 7500000 | I3: =IF(A3=Inputs!$B$6+Inputs!$B$7,Inputs!$B$14,0) -> 0 | J3: =E3-F3-G3-H3+I3 -> -7500000 | K3: =1/(1+Inputs!$B$17)^A3 -> 0.95877277 | L3: =J3*K3 -> -7190795.8 | M3: =SUM(J$2:J3) -> -15000000 | N3: =SUM(L$2:L3) -> -14690796 | O3: =IF(AND(A3>Inputs!$B$6,M3>=0,M2<0),A3-1-M2/J3,0) -> 0 | P3: =IF(AND(A3>Inputs!$B$6,N3>=0,N2<0),A3-1-N2/L3,0) -> 0
A4: 2 | B4: =IF(A4<Inputs!$B$6,"Construction",IF(A4=Inputs!$B$6,"Opening",IF(A4<=Inputs!$B$6+Inputs!$B$7,"Operations","Outside horizon"))) -> Opening | C4: =IF(AND(A4>Inputs!$B$6,A4<=Inputs!$B$6+Inputs!$B$7),A4-Inputs!$B$6,0) -> 0 | D4: =IF(C4>0,Inputs!$B$3*(1+Inputs!$B$4)^(C4-1),0) -> 0 | E4: =Inputs!$B$2*D4*12*Inputs!$B$8 -> 0 | F4: =E4*Inputs!$B$9 -> 0 | G4: =E4*Inputs!$B$10 -> 0 | H4: =IF(A4<Inputs!$B$6,Inputs!$B$5/Inputs!$B$6,0)+IF(A4=0,Inputs!$B$13,0) -> 0 | I4: =IF(A4=Inputs!$B$6+Inputs!$B$7,Inputs!$B$14,0) -> 0 | J4: =E4-F4-G4-H4+I4 -> 0 | K4: =1/(1+Inputs!$B$17)^A4 -> 0.91924523 | L4: =J4*K4 -> 0 | M4: =SUM(J$2:J4) -> -15000000 | N4: =SUM(L$2:L4) -> -14690796 | O4: =IF(AND(A4>Inputs!$B$6,M4>=0,M3<0),A4-1-M3/J4,0) -> 0 | P4: =IF(AND(A4>Inputs!$B$6,N4>=0,N3<0),A4-1-N3/L4,0) -> 0
A5: 3 | B5: =IF(A5<Inputs!$B$6,"Construction",IF(A5=Inputs!$B$6,"Opening",IF(A5<=Inputs!$B$6+Inputs!$B$7,"Operations","Outside horizon"))) -> Operations | C5: =IF(AND(A5>Inputs!$B$6,A5<=Inputs!$B$6+Inputs!$B$7),A5-Inputs!$B$6,0) -> 1 | D5: =IF(C5>0,Inputs!$B$3*(1+Inputs!$B$4)^(C5-1),0) -> 450 | E5: =Inputs!$B$2*D5*12*Inputs!$B$8 -> 10260000 | F5: =E5*Inputs!$B$9 -> 3078000 | G5: =E5*Inputs!$B$10 -> 513000 | H5: =IF(A5<Inputs!$B$6,Inputs!$B$5/Inputs!$B$6,0)+IF(A5=0,Inputs!$B$13,0) -> 0 | I5: =IF(A5=Inputs!$B$6+Inputs!$B$7,Inputs!$B$14,0) -> 0 | J5: =E5-F5-G5-H5+I5 -> 6669000 | K5: =1/(1+Inputs!$B$17)^A5 -> 0.88134729 | L5: =J5*K5 -> 5877705.1 | M5: =SUM(J$2:J5) -> -8331000 | N5: =SUM(L$2:L5) -> -8813090.7 | O5: =IF(AND(A5>Inputs!$B$6,M5>=0,M4<0),A5-1-M4/J5,0) -> 0 | P5: =IF(AND(A5>Inputs!$B$6,N5>=0,N4<0),A5-1-N4/L5,0) -> 0
A6: 4 | B6: =IF(A6<Inputs!$B$6,"Construction",IF(A6=Inputs!$B$6,"Opening",IF(A6<=Inputs!$B$6+Inputs!$B$7,"Operations","Outside horizon"))) -> Operations | C6: =IF(AND(A6>Inputs!$B$6,A6<=Inputs!$B$6+Inputs!$B$7),A6-Inputs!$B$6,0) -> 2 | D6: =IF(C6>0,Inputs!$B$3*(1+Inputs!$B$4)^(C6-1),0) -> 472.5 | E6: =Inputs!$B$2*D6*12*Inputs!$B$8 -> 10773000 | F6: =E6*Inputs!$B$9 -> 3231900 | G6: =E6*Inputs!$B$10 -> 538650 | H6: =IF(A6<Inputs!$B$6,Inputs!$B$5/Inputs!$B$6,0)+IF(A6=0,Inputs!$B$13,0) -> 0 | I6: =IF(A6=Inputs!$B$6+Inputs!$B$7,Inputs!$B$14,0) -> 0 | J6: =E6-F6-G6-H6+I6 -> 7002450 | K6: =1/(1+Inputs!$B$17)^A6 -> 0.84501179 | L6: =J6*K6 -> 5917152.8 | M6: =SUM(J$2:J6) -> -1328550 | N6: =SUM(L$2:L6) -> -2895937.9 | O6: =IF(AND(A6>Inputs!$B$6,M6>=0,M5<0),A6-1-M5/J6,0) -> 0 | P6: =IF(AND(A6>Inputs!$B$6,N6>=0,N5<0),A6-1-N5/L6,0) -> 0
A7: 5 | B7: =IF(A7<Inputs!$B$6,"Construction",IF(A7=Inputs!$B$6,"Opening",IF(A7<=Inputs!$B$6+Inputs!$B$7,"Operations","Outside horizon"))) -> Operations | C7: =IF(AND(A7>Inputs!$B$6,A7<=Inputs!$B$6+Inputs!$B$7),A7-Inputs!$B$6,0) -> 3 | D7: =IF(C7>0,Inputs!$B$3*(1+Inputs!$B$4)^(C7-1),0) -> 496.125 | E7: =Inputs!$B$2*D7*12*Inputs!$B$8 -> 11311650 | F7: =E7*Inputs!$B$9 -> 3393495 | G7: =E7*Inputs!$B$10 -> 565582.5 | H7: =IF(A7<Inputs!$B$6,Inputs!$B$5/Inputs!$B$6,0)+IF(A7=0,Inputs!$B$13,0) -> 0 | I7: =IF(A7=Inputs!$B$6+Inputs!$B$7,Inputs!$B$14,0) -> 0 | J7: =E7-F7-G7-H7+I7 -> 7352572.5 | K7: =1/(1+Inputs!$B$17)^A7 -> 0.81017429 | L7: =J7*K7 -> 5956865.2 | M7: =SUM(J$2:J7) -> 6024022.5 | N7: =SUM(L$2:L7) -> 3060927.3 | O7: =IF(AND(A7>Inputs!$B$6,M7>=0,M6<0),A7-1-M6/J7,0) -> 4.1806919 | P7: =IF(AND(A7>Inputs!$B$6,N7>=0,N6<0),A7-1-N6/L7,0) -> 4.4861513
A8: 6 | B8: =IF(A8<Inputs!$B$6,"Construction",IF(A8=Inputs!$B$6,"Opening",IF(A8<=Inputs!$B$6+Inputs!$B$7,"Operations","Outside horizon"))) -> Operations | C8: =IF(AND(A8>Inputs!$B$6,A8<=Inputs!$B$6+Inputs!$B$7),A8-Inputs!$B$6,0) -> 4 | D8: =IF(C8>0,Inputs!$B$3*(1+Inputs!$B$4)^(C8-1),0) -> 520.93125 | E8: =Inputs!$B$2*D8*12*Inputs!$B$8 -> 11877233 | F8: =E8*Inputs!$B$9 -> 3563169.8 | G8: =E8*Inputs!$B$10 -> 593861.63 | H8: =IF(A8<Inputs!$B$6,Inputs!$B$5/Inputs!$B$6,0)+IF(A8=0,Inputs!$B$13,0) -> 0 | I8: =IF(A8=Inputs!$B$6+Inputs!$B$7,Inputs!$B$14,0) -> 0 | J8: =E8-F8-G8-H8+I8 -> 7720201.1 | K8: =1/(1+Inputs!$B$17)^A8 -> 0.77677305 | L8: =J8*K8 -> 5996844.2 | M8: =SUM(J$2:J8) -> 13744224 | N8: =SUM(L$2:L8) -> 9057771.5 | O8: =IF(AND(A8>Inputs!$B$6,M8>=0,M7<0),A8-1-M7/J8,0) -> 0 | P8: =IF(AND(A8>Inputs!$B$6,N8>=0,N7<0),A8-1-N7/L8,0) -> 0
A9: 7 | B9: =IF(A9<Inputs!$B$6,"Construction",IF(A9=Inputs!$B$6,"Opening",IF(A9<=Inputs!$B$6+Inputs!$B$7,"Operations","Outside horizon"))) -> Operations | C9: =IF(AND(A9>Inputs!$B$6,A9<=Inputs!$B$6+Inputs!$B$7),A9-Inputs!$B$6,0) -> 5 | D9: =IF(C9>0,Inputs!$B$3*(1+Inputs!$B$4)^(C9-1),0) -> 546.97781 | E9: =Inputs!$B$2*D9*12*Inputs!$B$8 -> 12471094 | F9: =E9*Inputs!$B$9 -> 3741328.2 | G9: =E9*Inputs!$B$10 -> 623554.71 | H9: =IF(A9<Inputs!$B$6,Inputs!$B$5/Inputs!$B$6,0)+IF(A9=0,Inputs!$B$13,0) -> 0 | I9: =IF(A9=Inputs!$B$6+Inputs!$B$7,Inputs!$B$14,0) -> 0 | J9: =E9-F9-G9-H9+I9 -> 8106211.2 | K9: =1/(1+Inputs!$B$17)^A9 -> 0.74474885 | L9: =J9*K9 -> 6037091.5 | M9: =SUM(J$2:J9) -> 21850435 | N9: =SUM(L$2:L9) -> 15094863 | O9: =IF(AND(A9>Inputs!$B$6,M9>=0,M8<0),A9-1-M8/J9,0) -> 0 | P9: =IF(AND(A9>Inputs!$B$6,N9>=0,N8<0),A9-1-N8/L9,0) -> 0
A10: 8 | B10: =IF(A10<Inputs!$B$6,"Construction",IF(A10=Inputs!$B$6,"Opening",IF(A10<=Inputs!$B$6+Inputs!$B$7,"Operations","Outside horizon"))) -> Operations | C10: =IF(AND(A10>Inputs!$B$6,A10<=Inputs!$B$6+Inputs!$B$7),A10-Inputs!$B$6,0) -> 6 | D10: =IF(C10>0,Inputs!$B$3*(1+Inputs!$B$4)^(C10-1),0) -> 574.3267 | E10: =Inputs!$B$2*D10*12*Inputs!$B$8 -> 13094649 | F10: =E10*Inputs!$B$9 -> 3928394.6 | G10: =E10*Inputs!$B$10 -> 654732.44 | H10: =IF(A10<Inputs!$B$6,Inputs!$B$5/Inputs!$B$6,0)+IF(A10=0,Inputs!$B$13,0) -> 0 | I10: =IF(A10=Inputs!$B$6+Inputs!$B$7,Inputs!$B$14,0) -> 0 | J10: =E10-F10-G10-H10+I10 -> 8511521.7 | K10: =1/(1+Inputs!$B$17)^A10 -> 0.71404492 | L10: =J10*K10 -> 6077608.8 | M10: =SUM(J$2:J10) -> 30361957 | N10: =SUM(L$2:L10) -> 21172472 | O10: =IF(AND(A10>Inputs!$B$6,M10>=0,M9<0),A10-1-M9/J10,0) -> 0 | P10: =IF(AND(A10>Inputs!$B$6,N10>=0,N9<0),A10-1-N9/L10,0) -> 0
A11: 9 | B11: =IF(A11<Inputs!$B$6,"Construction",IF(A11=Inputs!$B$6,"Opening",IF(A11<=Inputs!$B$6+Inputs!$B$7,"Operations","Outside horizon"))) -> Operations | C11: =IF(AND(A11>Inputs!$B$6,A11<=Inputs!$B$6+Inputs!$B$7),A11-Inputs!$B$6,0) -> 7 | D11: =IF(C11>0,Inputs!$B$3*(1+Inputs!$B$4)^(C11-1),0) -> 603.04304 | E11: =Inputs!$B$2*D11*12*Inputs!$B$8 -> 13749381 | F11: =E11*Inputs!$B$9 -> 4124814.4 | G11: =E11*Inputs!$B$10 -> 687469.06 | H11: =IF(A11<Inputs!$B$6,Inputs!$B$5/Inputs!$B$6,0)+IF(A11=0,Inputs!$B$13,0) -> 0 | I11: =IF(A11=Inputs!$B$6+Inputs!$B$7,Inputs!$B$14,0) -> 0 | J11: =E11-F11-G11-H11+I11 -> 8937097.8 | K11: =1/(1+Inputs!$B$17)^A11 -> 0.68460682 | L11: =J11*K11 -> 6118398.2 | M11: =SUM(J$2:J11) -> 39299054 | N11: =SUM(L$2:L11) -> 27290870 | O11: =IF(AND(A11>Inputs!$B$6,M11>=0,M10<0),A11-1-M10/J11,0) -> 0 | P11: =IF(AND(A11>Inputs!$B$6,N11>=0,N10<0),A11-1-N10/L11,0) -> 0
A12: 10 | B12: =IF(A12<Inputs!$B$6,"Construction",IF(A12=Inputs!$B$6,"Opening",IF(A12<=Inputs!$B$6+Inputs!$B$7,"Operations","Outside horizon"))) -> Operations | C12: =IF(AND(A12>Inputs!$B$6,A12<=Inputs!$B$6+Inputs!$B$7),A12-Inputs!$B$6,0) -> 8 | D12: =IF(C12>0,Inputs!$B$3*(1+Inputs!$B$4)^(C12-1),0) -> 633.19519 | E12: =Inputs!$B$2*D12*12*Inputs!$B$8 -> 14436850 | F12: =E12*Inputs!$B$9 -> 4331055.1 | G12: =E12*Inputs!$B$10 -> 721842.52 | H12: =IF(A12<Inputs!$B$6,Inputs!$B$5/Inputs!$B$6,0)+IF(A12=0,Inputs!$B$13,0) -> 0 | I12: =IF(A12=Inputs!$B$6+Inputs!$B$7,Inputs!$B$14,0) -> 0 | J12: =E12-F12-G12-H12+I12 -> 9383952.7 | K12: =1/(1+Inputs!$B$17)^A12 -> 0.65638238 | L12: =J12*K12 -> 6159461.2 | M12: =SUM(J$2:J12) -> 48683007 | N12: =SUM(L$2:L12) -> 33450331 | O12: =IF(AND(A12>Inputs!$B$6,M12>=0,M11<0),A12-1-M11/J12,0) -> 0 | P12: =IF(AND(A12>Inputs!$B$6,N12>=0,N11<0),A12-1-N11/L12,0) -> 0
A13: 11 | B13: =IF(A13<Inputs!$B$6,"Construction",IF(A13=Inputs!$B$6,"Opening",IF(A13<=Inputs!$B$6+Inputs!$B$7,"Operations","Outside horizon"))) -> Operations | C13: =IF(AND(A13>Inputs!$B$6,A13<=Inputs!$B$6+Inputs!$B$7),A13-Inputs!$B$6,0) -> 9 | D13: =IF(C13>0,Inputs!$B$3*(1+Inputs!$B$4)^(C13-1),0) -> 664.85495 | E13: =Inputs!$B$2*D13*12*Inputs!$B$8 -> 15158693 | F13: =E13*Inputs!$B$9 -> 4547607.9 | G13: =E13*Inputs!$B$10 -> 757934.64 | H13: =IF(A13<Inputs!$B$6,Inputs!$B$5/Inputs!$B$6,0)+IF(A13=0,Inputs!$B$13,0) -> 0 | I13: =IF(A13=Inputs!$B$6+Inputs!$B$7,Inputs!$B$14,0) -> 0 | J13: =E13-F13-G13-H13+I13 -> 9853150.4 | K13: =1/(1+Inputs!$B$17)^A13 -> 0.62932156 | L13: =J13*K13 -> 6200799.9 | M13: =SUM(J$2:J13) -> 58536157 | N13: =SUM(L$2:L13) -> 39651131 | O13: =IF(AND(A13>Inputs!$B$6,M13>=0,M12<0),A13-1-M12/J13,0) -> 0 | P13: =IF(AND(A13>Inputs!$B$6,N13>=0,N12<0),A13-1-N12/L13,0) -> 0
A14: 12 | B14: =IF(A14<Inputs!$B$6,"Construction",IF(A14=Inputs!$B$6,"Opening",IF(A14<=Inputs!$B$6+Inputs!$B$7,"Operations","Outside horizon"))) -> Operations | C14: =IF(AND(A14>Inputs!$B$6,A14<=Inputs!$B$6+Inputs!$B$7),A14-Inputs!$B$6,0) -> 10 | D14: =IF(C14>0,Inputs!$B$3*(1+Inputs!$B$4)^(C14-1),0) -> 698.0977 | E14: =Inputs!$B$2*D14*12*Inputs!$B$8 -> 15916627 | F14: =E14*Inputs!$B$9 -> 4774988.2 | G14: =E14*Inputs!$B$10 -> 795831.37 | H14: =IF(A14<Inputs!$B$6,Inputs!$B$5/Inputs!$B$6,0)+IF(A14=0,Inputs!$B$13,0) -> 0 | I14: =IF(A14=Inputs!$B$6+Inputs!$B$7,Inputs!$B$14,0) -> 0 | J14: =E14-F14-G14-H14+I14 -> 10345808 | K14: =1/(1+Inputs!$B$17)^A14 -> 0.60337637 | L14: =J14*K14 -> 6242416 | M14: =SUM(J$2:J14) -> 68881965 | N14: =SUM(L$2:L14) -> 45893547 | O14: =IF(AND(A14>Inputs!$B$6,M14>=0,M13<0),A14-1-M13/J14,0) -> 0 | P14: =IF(AND(A14>Inputs!$B$6,N14>=0,N13<0),A14-1-N13/L14,0) -> 0
... A62: 60 | B62: =IF(A62<Inputs!$B$6,"Construction",IF(A62=Inputs!$B$6,"Opening",IF(A62<=Inputs!$B$6+Inputs!$B$7,"Operations","Outside horizon"))) -> Outside horizon | C62: =IF(AND(A62>Inputs!$B$6,A62<=Inputs!$B$6+Inputs!$B$7),A62-Inputs!$B$6,0) -> 0 | D62: =IF(C62>0,Inputs!$B$3*(1+Inputs!$B$4)^(C62-1),0) -> 0 | E62: =Inputs!$B$2*D62*12*Inputs!$B$8 -> 0 | F62: =E62*Inputs!$B$9 -> 0 | G62: =E62*Inputs!$B$10 -> 0 | H62: =IF(A62<Inputs!$B$6,Inputs!$B$5/Inputs!$B$6,0)+IF(A62=0,Inputs!$B$13,0) -> 0 | I62: =IF(A62=Inputs!$B$6+Inputs!$B$7,Inputs!$B$14,0) -> 0 | J62: =E62-F62-G62-H62+I62 -> 0 | K62: =1/(1+Inputs!$B$17)^A62 -> 0.079972651 | L62: =J62*K62 -> 0 | M62: =SUM(J$2:J62) -> 4.2808067e+08 | N62: =SUM(L$2:L62) -> 1.7992543e+08 | O62: =IF(AND(A62>Inputs!$B$6,M62>=0,M61<0),A62-1-M61/J62,0) -> 0 | P62: =IF(AND(A62>Inputs!$B$6,N62>=0,N61<0),A62-1-N61/L62,0) -> 0

Sheet Scenarios
A1: Scenario | B1: Construction cost EUR | C1: Occupancy | D1: Rent growth | E1: Total expense share | F1: Discount rate | G1: NPV EUR | H1: IRR | I1: Simple payback yrs | J1: Discounted payback yrs | K1: Financial tests | L1: 0 | M1: 1 | N1: 2 | O1: 3 | P1: 4 | Q1: 5 | R1: 6 | S1: 7 | T1: 8 | U1: 9 | V1: 10 | W1: 11 | X1: 12 | Y1: 13 | Z1: 14 | AA1: 15 | AB1: 16 | AC1: 17 | AD1: 18 | AE1: 19 | AF1: 20 | AG1: 21 | AH1: 22 | AI1: 23 | AJ1: 24 | AK1: 25 | AL1: 26 | AM1: 27 | AN1: 28 | AO1: 29 | AP1: 30 | AQ1: 31 | AR1: 32 | AS1: 33 | AT1: 34 | AU1: 35 | AV1: 36 | AW1: 37 | AX1: 38 | AY1: 39 | AZ1: 40 | BA1: 41 | BB1: 42 | BC1: 43 | BD1: 44 | BE1: 45 | BF1: 46 | BG1: 47 | BH1: 48 | BI1: 49 | BJ1: 50 | BK1: 51 | BL1: 52 | BM1: 53 | BN1: 54 | BO1: 55 | BP1: 56 | BQ1: 57 | BR1: 58 | BS1: 59 | BT1: 60
A2: Requested assumptions | B2: =Inputs!$B$5*1 -> 15000000 | C2: =Inputs!$B$8 -> 0.95 | D2: =Inputs!$B$4 -> 0.05 | E2: =Inputs!$B$9+Inputs!$B$10 -> 0.35 | F2: =Inputs!$B$17+0 -> 0.043 | G2: =NPV(F2,M2:BT2)+L2 -> 1.7992543e+08 | H2: =IFERROR(IRR(L2:BT2),"Not defined") -> 0.33503129 | I2: =IF(MAX(L16:BT16)>0,MAX(L16:BT16),"Not reached") -> 4.1806919 | J2: =IF(MAX(L18:BT18)>0,MAX(L18:BT18),"Not reached") -> 4.4861513 | K2: =IF(AND(G2>0,ISNUMBER(H2),H2>F2,ISNUMBER(I2),I2<=Inputs!$B$12),"PASS","FAIL") -> PASS | L2: =IF(AND(L$1>Inputs!$B$6,L$1<=Inputs!$B$6+Inputs!$B$7),Inputs!$B$2*Inputs!$B$3*12*$C2*(1+$D2)^(L$1-Inputs!$B$6-1)*(1-$E2),0)-IF(L$1<Inputs!$B$6,$B2/Inputs!$B$6,0)-IF(L$1=0,Inputs!$B$13,0)+IF(L$1=Inputs!$B$6+Inputs!$B$7,Inputs!$B$14,0) -> -7500000 | M2: =IF(AND(M$1>Inputs!$B$6,M$1<=Inputs!$B$6+Inputs!$B$7),Inputs!$B$2*Inputs!$B$3*12*$C2*(1+$D2)^(M$1-Inputs!$B$6-1)*(1-$E2),0)-IF(M$1<Inputs!$B$6,$B2/Inputs!$B$6,0)-IF(M$1=0,Inputs!$B$13,0)+IF(M$1=Inputs!$B$6+Inputs!$B$7,Inputs!$B$14,0) -> -7500000 | N2: =IF(AND(N$1>Inputs!$B$6,N$1<=Inputs!$B$6+Inputs!$B$7),Inputs!$B$2*Inputs!$B$3*12*$C2*(1+$D2)^(N$1-Inputs!$B$6-1)*(1-$E2),0)-IF(N$1<Inputs!$B$6,$B2/Inputs!$B$6,0)-IF(N$1=0,Inputs!$B$13,0)+IF(N$1=Inputs!$B$6+Inputs!$B$7,Inputs!$B$14,0) -> 0 | O2: =IF(AND(O$1>Inputs!$B$6,O$1<=Inputs!$B$6+Inputs!$B$7),Inputs!$B$2*Inputs!$B$3*12*$C2*(1+$D2)^(O$1-Inputs!$B$6-1)*(1-$E2),0)-IF(O$1<Inputs!$B$6,$B2/Inputs!$B$6,0)-IF(O$1=0,Inputs!$B$13,0)+IF(O$1=Inputs!$B$6+Inputs!$B$7,Inputs!$B$14,0) -> 6669000 | P2: =IF(AND(P$1>Inputs!$B$6,P$1<=Inputs!$B$6+Inputs!$B$7),Inputs!$B$2*Inputs!$B$3*12*$C2*(1+$D2)^(P$1-Inputs!$B$6-1)*(1-$E2),0)-IF(P$1<Inputs!$B$6,$B2/Inputs!$B$6,0)-IF(P$1=0,Inputs!$B$13,0)+IF(P$1=Inputs!$B$6+Inputs!$B$7,Inputs!$B$14,0) -> 7002450 | Q2: =IF(AND(Q$1>Inputs!$B$6,Q$1<=Inputs!$B$6+Inputs!$B$7),Inputs!$B$2*Inputs!$B$3*12*$C2*(1+$D2)^(Q$1-Inputs!$B$6-1)*(1-$E2),0)-IF(Q$1<Inputs!$B$6,$B2/Inputs!$B$6,0)-IF(Q$1=0,Inputs!$B$13,0)+IF(Q$1=Inputs!$B$6+Inputs!$B$7,Inputs!$B$14,0) -> 7352572.5 | R2: =IF(AND(R$1>Inputs!$B$6,R$1<=Inputs!$B$6+Inputs!$B$7),Inputs!$B$2*Inputs!$B$3*12*$C2*(1+$D2)^(R$1-Inputs!$B$6-1)*(1-$E2),0)-IF(R$1<Inputs!$B$6,$B2/Inputs!$B$6,0)-IF(R$1=0,Inputs!$B$13,0)+IF(R$1=Inputs!$B$6+Inputs!$B$7,Inputs!$B$14,0) -> 7720201.1 | S2: =IF(AND(S$1>Inputs!$B$6,S$1<=Inputs!$B$6+Inputs!$B$7),Inputs!$B$2*Inputs!$B$3*12*$C2*(1+$D2)^(S$1-Inputs!$B$6-1)*(1-$E2),0)-IF(S$1<Inputs!$B$6,$B2/Inputs!$B$6,0)-IF(S$1=0,Inputs!$B$13,0)+IF(S$1=Inputs!$B$6+Inputs!$B$7,Inputs!$B$14,0) -> 8106211.2 | ... BT2: =IF(AND(BT$1>Inputs!$B$6,BT$1<=Inputs!$B$6+Inputs!$B$7),Inputs!$B$2*Inputs!$B$3*12*$C2*(1+$D2)^(BT$1-Inputs!$B$6-1)*(1-$E2),0)-IF(BT$1<Inputs!$B$6,$B2/Inputs!$B$6,0)-IF(BT$1=0,Inputs!$B$13,0)+IF(BT$1=Inputs!$B$6+Inputs!$B$7,Inputs!$B$14,0) -> 0
A3: Lower occupancy / no rent growth | B3: =Inputs!$B$5*1 -> 15000000 | C3: 0.8 | D3: 0 | E3: 0.45 | F3: =Inputs!$B$17+0 -> 0.043 | G3: =NPV(F3,M3:BT3)+L3 -> 58168179 | H3: =IFERROR(IRR(L3:BT3),"Not defined") -> 0.23041617 | I3: =IF(MAX(L21:BT21)>0,MAX(L21:BT21),"Not reached") -> 5.1565657 | J3: =IF(MAX(L23:BT23)>0,MAX(L23:BT23),"Not reached") -> 5.7144481 | K3: =IF(AND(G3>0,ISNUMBER(H3),H3>F3,ISNUMBER(I3),I3<=Inputs!$B$12),"PASS","FAIL") -> PASS | L3: =IF(AND(L$1>Inputs!$B$6,L$1<=Inputs!$B$6+Inputs!$B$7),Inputs!$B$2*Inputs!$B$3*12*$C3*(1+$D3)^(L$1-Inputs!$B$6-1)*(1-$E3),0)-IF(L$1<Inputs!$B$6,$B3/Inputs!$B$6,0)-IF(L$1=0,Inputs!$B$13,0)+IF(L$1=Inputs!$B$6+Inputs!$B$7,Inputs!$B$14,0) -> -7500000 | M3: =IF(AND(M$1>Inputs!$B$6,M$1<=Inputs!$B$6+Inputs!$B$7),Inputs!$B$2*Inputs!$B$3*12*$C3*(1+$D3)^(M$1-Inputs!$B$6-1)*(1-$E3),0)-IF(M$1<Inputs!$B$6,$B3/Inputs!$B$6,0)-IF(M$1=0,Inputs!$B$13,0)+IF(M$1=Inputs!$B$6+Inputs!$B$7,Inputs!$B$14,0) -> -7500000 | N3: =IF(AND(N$1>Inputs!$B$6,N$1<=Inputs!$B$6+Inputs!$B$7),Inputs!$B$2*Inputs!$B$3*12*$C3*(1+$D3)^(N$1-Inputs!$B$6-1)*(1-$E3),0)-IF(N$1<Inputs!$B$6,$B3/Inputs!$B$6,0)-IF(N$1=0,Inputs!$B$13,0)+IF(N$1=Inputs!$B$6+Inputs!$B$7,Inputs!$B$14,0) -> 0 | O3: =IF(AND(O$1>Inputs!$B$6,O$1<=Inputs!$B$6+Inputs!$B$7),Inputs!$B$2*Inputs!$B$3*12*$C3*(1+$D3)^(O$1-Inputs!$B$6-1)*(1-$E3),0)-IF(O$1<Inputs!$B$6,$B3/Inputs!$B$6,0)-IF(O$1=0,Inputs!$B$13,0)+IF(O$1=Inputs!$B$6+Inputs!$B$7,Inputs!$B$14,0) -> 4752000 | P3: =IF(AND(P$1>Inputs!$B$6,P$1<=Inputs!$B$6+Inputs!$B$7),Inputs!$B$2*Inputs!$B$3*12*$C3*(1+$D3)^(P$1-Inputs!$B$6-1)*(1-$E3),0)-IF(P$1<Inputs!$B$6,$B3/Inputs!$B$6,0)-IF(P$1=0,Inputs!$B$13,0)+IF(P$1=Inputs!$B$6+Inputs!$B$7,Inputs!$B$14,0) -> 4752000 | Q3: =IF(AND(Q$1>Inputs!$B$6,Q$1<=Inputs!$B$6+Inputs!$B$7),Inputs!$B$2*Inputs!$B$3*12*$C3*(1+$D3)^(Q$1-Inputs!$B$6-1)*(1-$E3),0)-IF(Q$1<Inputs!$B$6,$B3/Inputs!$B$6,0)-IF(Q$1=0,Inputs!$B$13,0)+IF(Q$1=Inputs!$B$6+Inputs!$B$7,Inputs!$B$14,0) -> 4752000 | R3: =IF(AND(R$1>Inputs!$B$6,R$1<=Inputs!$B$6+Inputs!$B$7),Inputs!$B$2*Inputs!$B$3*12*$C3*(1+$D3)^(R$1-Inputs!$B$6-1)*(1-$E3),0)-IF(R$1<Inputs!$B$6,$B3/Inputs!$B$6,0)-IF(R$1=0,Inputs!$B$13,0)+IF(R$1=Inputs!$B$6+Inputs!$B$7,Inputs!$B$14,0) -> 4752000 | S3: =IF(AND(S$1>Inputs!$B$6,S$1<=Inputs!$B$6+Inputs!$B$7),Inputs!$B$2*Inputs!$B$3*12*$C3*(1+$D3)^(S$1-Inputs!$B$6-1)*(1-$E3),0)-IF(S$1<Inputs!$B$6,$B3/Inputs!$B$6,0)-IF(S$1=0,Inputs!$B$13,0)+IF(S$1=Inputs!$B$6+Inputs!$B$7,Inputs!$B$14,0) -> 4752000 | ... BT3: =IF(AND(BT$1>Inputs!$B$6,BT$1<=Inputs!$B$6+Inputs!$B$7),Inputs!$B$2*Inputs!$B$3*12*$C3*(1+$D3)^(BT$1-Inputs!$B$6-1)*(1-$E3),0)-IF(BT$1<Inputs!$B$6,$B3/Inputs!$B$6,0)-IF(BT$1=0,Inputs!$B$13,0)+IF(BT$1=Inputs!$B$6+Inputs!$B$7,Inputs!$B$14,0) -> 0
A4: Cost doubles | B4: =Inputs!$B$5*2 -> 30000000 | C4: =Inputs!$B$8 -> 0.95 | D4: =Inputs!$B$4 -> 0.05 | E4: =Inputs!$B$9+Inputs!$B$10 -> 0.35 | F4: =Inputs!$B$17+0 -> 0.043 | G4: =NPV(F4,M4:BT4)+L4 -> 1.6523463e+08 | H4: =IFERROR(IRR(L4:BT4),"Not defined") -> 0.2133835 | I4: =IF(MAX(L26:BT26)>0,MAX(L26:BT26),"Not reached") -> 6.1549153 | J4: =IF(MAX(L28:BT28)>0,MAX(L28:BT28),"Not reached") -> 6.9330692 | K4: =IF(AND(G4>0,ISNUMBER(H4),H4>F4,ISNUMBER(I4),I4<=Inputs!$B$12),"PASS","FAIL") -> PASS | L4: =IF(AND(L$1>Inputs!$B$6,L$1<=Inputs!$B$6+Inputs!$B$7),Inputs!$B$2*Inputs!$B$3*12*$C4*(1+$D4)^(L$1-Inputs!$B$6-1)*(1-$E4),0)-IF(L$1<Inputs!$B$6,$B4/Inputs!$B$6,0)-IF(L$1=0,Inputs!$B$13,0)+IF(L$1=Inputs!$B$6+Inputs!$B$7,Inputs!$B$14,0) -> -15000000 | M4: =IF(AND(M$1>Inputs!$B$6,M$1<=Inputs!$B$6+Inputs!$B$7),Inputs!$B$2*Inputs!$B$3*12*$C4*(1+$D4)^(M$1-Inputs!$B$6-1)*(1-$E4),0)-IF(M$1<Inputs!$B$6,$B4/Inputs!$B$6,0)-IF(M$1=0,Inputs!$B$13,0)+IF(M$1=Inputs!$B$6+Inputs!$B$7,Inputs!$B$14,0) -> -15000000 | N4: =IF(AND(N$1>Inputs!$B$6,N$1<=Inputs!$B$6+Inputs!$B$7),Inputs!$B$2*Inputs!$B$3*12*$C4*(1+$D4)^(N$1-Inputs!$B$6-1)*(1-$E4),0)-IF(N$1<Inputs!$B$6,$B4/Inputs!$B$6,0)-IF(N$1=0,Inputs!$B$13,0)+IF(N$1=Inputs!$B$6+Inputs!$B$7,Inputs!$B$14,0) -> 0 | O4: =IF(AND(O$1>Inputs!$B$6,O$1<=Inputs!$B$6+Inputs!$B$7),Inputs!$B$2*Inputs!$B$3*12*$C4*(1+$D4)^(O$1-Inputs!$B$6-1)*(1-$E4),0)-IF(O$1<Inputs!$B$6,$B4/Inputs!$B$6,0)-IF(O$1=0,Inputs!$B$13,0)+IF(O$1=Inputs!$B$6+Inputs!$B$7,Inputs!$B$14,0) -> 6669000 | P4: =IF(AND(P$1>Inputs!$B$6,P$1<=Inputs!$B$6+Inputs!$B$7),Inputs!$B$2*Inputs!$B$3*12*$C4*(1+$D4)^(P$1-Inputs!$B$6-1)*(1-$E4),0)-IF(P$1<Inputs!$B$6,$B4/Inputs!$B$6,0)-IF(P$1=0,Inputs!$B$13,0)+IF(P$1=Inputs!$B$6+Inputs!$B$7,Inputs!$B$14,0) -> 7002450 | Q4: =IF(AND(Q$1>Inputs!$B$6,Q$1<=Inputs!$B$6+Inputs!$B$7),Inputs!$B$2*Inputs!$B$3*12*$C4*(1+$D4)^(Q$1-Inputs!$B$6-1)*(1-$E4),0)-IF(Q$1<Inputs!$B$6,$B4/Inputs!$B$6,0)-IF(Q$1=0,Inputs!$B$13,0)+IF(Q$1=Inputs!$B$6+Inputs!$B$7,Inputs!$B$14,0) -> 7352572.5 | R4: =IF(AND(R$1>Inputs!$B$6,R$1<=Inputs!$B$6+Inputs!$B$7),Inputs!$B$2*Inputs!$B$3*12*$C4*(1+$D4)^(R$1-Inputs!$B$6-1)*(1-$E4),0)-IF(R$1<Inputs!$B$6,$B4/Inputs!$B$6,0)-IF(R$1=0,Inputs!$B$13,0)+IF(R$1=Inputs!$B$6+Inputs!$B$7,Inputs!$B$14,0) -> 7720201.1 | S4: =IF(AND(S$1>Inputs!$B$6,S$1<=Inputs!$B$6+Inputs!$B$7),Inputs!$B$2*Inputs!$B$3*12*$C4*(1+$D4)^(S$1-Inputs!$B$6-1)*(1-$E4),0)-IF(S$1<Inputs!$B$6,$B4/Inputs!$B$6,0)-IF(S$1=0,Inputs!$B$13,0)+IF(S$1=Inputs!$B$6+Inputs!$B$7,Inputs!$B$14,0) -> 8106211.2 | ... BT4: =IF(AND(BT$1>Inputs!$B$6,BT$1<=Inputs!$B$6+Inputs!$B$7),Inputs!$B$2*Inputs!$B$3*12*$C4*(1+$D4)^(BT$1-Inputs!$B$6-1)*(1-$E4),0)-IF(BT$1<Inputs!$B$6,$B4/Inputs!$B$6,0)-IF(BT$1=0,Inputs!$B$13,0)+IF(BT$1=Inputs!$B$6+Inputs!$B$7,Inputs!$B$14,0) -> 0
A5: Project risk +4 percentage points | B5: =Inputs!$B$5*1 -> 15000000 | C5: =Inputs!$B$8 -> 0.95 | D5: =Inputs!$B$4 -> 0.05 | E5: =Inputs!$B$9+Inputs!$B$10 -> 0.35 | F5: =Inputs!$B$17+0.04 -> 0.083 | G5: =NPV(F5,M5:BT5)+L5 -> 89781626 | H5: =IFERROR(IRR(L5:BT5),"Not defined") -> 0.33503129 | I5: =IF(MAX(L31:BT31)>0,MAX(L31:BT31),"Not reached") -> 4.1806919 | J5: =IF(MAX(L33:BT33)>0,MAX(L33:BT33),"Not reached") -> 4.8277011 | K5: =IF(AND(G5>0,ISNUMBER(H5),H5>F5,ISNUMBER(I5),I5<=Inputs!$B$12),"PASS","FAIL") -> PASS | L5: =IF(AND(L$1>Inputs!$B$6,L$1<=Inputs!$B$6+Inputs!$B$7),Inputs!$B$2*Inputs!$B$3*12*$C5*(1+$D5)^(L$1-Inputs!$B$6-1)*(1-$E5),0)-IF(L$1<Inputs!$B$6,$B5/Inputs!$B$6,0)-IF(L$1=0,Inputs!$B$13,0)+IF(L$1=Inputs!$B$6+Inputs!$B$7,Inputs!$B$14,0) -> -7500000 | M5: =IF(AND(M$1>Inputs!$B$6,M$1<=Inputs!$B$6+Inputs!$B$7),Inputs!$B$2*Inputs!$B$3*12*$C5*(1+$D5)^(M$1-Inputs!$B$6-1)*(1-$E5),0)-IF(M$1<Inputs!$B$6,$B5/Inputs!$B$6,0)-IF(M$1=0,Inputs!$B$13,0)+IF(M$1=Inputs!$B$6+Inputs!$B$7,Inputs!$B$14,0) -> -7500000 | N5: =IF(AND(N$1>Inputs!$B$6,N$1<=Inputs!$B$6+Inputs!$B$7),Inputs!$B$2*Inputs!$B$3*12*$C5*(1+$D5)^(N$1-Inputs!$B$6-1)*(1-$E5),0)-IF(N$1<Inputs!$B$6,$B5/Inputs!$B$6,0)-IF(N$1=0,Inputs!$B$13,0)+IF(N$1=Inputs!$B$6+Inputs!$B$7,Inputs!$B$14,0) -> 0 | O5: =IF(AND(O$1>Inputs!$B$6,O$1<=Inputs!$B$6+Inputs!$B$7),Inputs!$B$2*Inputs!$B$3*12*$C5*(1+$D5)^(O$1-Inputs!$B$6-1)*(1-$E5),0)-IF(O$1<Inputs!$B$6,$B5/Inputs!$B$6,0)-IF(O$1=0,Inputs!$B$13,0)+IF(O$1=Inputs!$B$6+Inputs!$B$7,Inputs!$B$14,0) -> 6669000 | P5: =IF(AND(P$1>Inputs!$B$6,P$1<=Inputs!$B$6+Inputs!$B$7),Inputs!$B$2*Inputs!$B$3*12*$C5*(1+$D5)^(P$1-Inputs!$B$6-1)*(1-$E5),0)-IF(P$1<Inputs!$B$6,$B5/Inputs!$B$6,0)-IF(P$1=0,Inputs!$B$13,0)+IF(P$1=Inputs!$B$6+Inputs!$B$7,Inputs!$B$14,0) -> 7002450 | Q5: =IF(AND(Q$1>Inputs!$B$6,Q$1<=Inputs!$B$6+Inputs!$B$7),Inputs!$B$2*Inputs!$B$3*12*$C5*(1+$D5)^(Q$1-Inputs!$B$6-1)*(1-$E5),0)-IF(Q$1<Inputs!$B$6,$B5/Inputs!$B$6,0)-IF(Q$1=0,Inputs!$B$13,0)+IF(Q$1=Inputs!$B$6+Inputs!$B$7,Inputs!$B$14,0) -> 7352572.5 | R5: =IF(AND(R$1>Inputs!$B$6,R$1<=Inputs!$B$6+Inputs!$B$7),Inputs!$B$2*Inputs!$B$3*12*$C5*(1+$D5)^(R$1-Inputs!$B$6-1)*(1-$E5),0)-IF(R$1<Inputs!$B$6,$B5/Inputs!$B$6,0)-IF(R$1=0,Inputs!$B$13,0)+IF(R$1=Inputs!$B$6+Inputs!$B$7,Inputs!$B$14,0) -> 7720201.1 | S5: =IF(AND(S$1>Inputs!$B$6,S$1<=Inputs!$B$6+Inputs!$B$7),Inputs!$B$2*Inputs!$B$3*12*$C5*(1+$D5)^(S$1-Inputs!$B$6-1)*(1-$E5),0)-IF(S$1<Inputs!$B$6,$B5/Inputs!$B$6,0)-IF(S$1=0,Inputs!$B$13,0)+IF(S$1=Inputs!$B$6+Inputs!$B$7,Inputs!$B$14,0) -> 8106211.2 | ... BT5: =IF(AND(BT$1>Inputs!$B$6,BT$1<=Inputs!$B$6+Inputs!$B$7),Inputs!$B$2*Inputs!$B$3*12*$C5*(1+$D5)^(BT$1-Inputs!$B$6-1)*(1-$E5),0)-IF(BT$1<Inputs!$B$6,$B5/Inputs!$B$6,0)-IF(BT$1=0,Inputs!$B$13,0)+IF(BT$1=Inputs!$B$6+Inputs!$B$7,Inputs!$B$14,0) -> 0
A6: Combined stress | B6: =Inputs!$B$5*2 -> 30000000 | C6: 0.8 | D6: 0 | E6: 0.45 | F6: =Inputs!$B$17+0.04 -> 0.083 | G6: =NPV(F6,M6:BT6)+L6 -> 15499625 | H6: =IFERROR(IRR(L6:BT6),"Not defined") -> 0.1283895 | I6: =IF(MAX(L36:BT36)>0,MAX(L36:BT36),"Not reached") -> 8.3131313 | J6: =IF(MAX(L38:BT38)>0,MAX(L38:BT38),"Not reached") -> 13.220362 | K6: =IF(AND(G6>0,ISNUMBER(H6),H6>F6,ISNUMBER(I6),I6<=Inputs!$B$12),"PASS","FAIL") -> PASS | L6: =IF(AND(L$1>Inputs!$B$6,L$1<=Inputs!$B$6+Inputs!$B$7),Inputs!$B$2*Inputs!$B$3*12*$C6*(1+$D6)^(L$1-Inputs!$B$6-1)*(1-$E6),0)-IF(L$1<Inputs!$B$6,$B6/Inputs!$B$6,0)-IF(L$1=0,Inputs!$B$13,0)+IF(L$1=Inputs!$B$6+Inputs!$B$7,Inputs!$B$14,0) -> -15000000 | M6: =IF(AND(M$1>Inputs!$B$6,M$1<=Inputs!$B$6+Inputs!$B$7),Inputs!$B$2*Inputs!$B$3*12*$C6*(1+$D6)^(M$1-Inputs!$B$6-1)*(1-$E6),0)-IF(M$1<Inputs!$B$6,$B6/Inputs!$B$6,0)-IF(M$1=0,Inputs!$B$13,0)+IF(M$1=Inputs!$B$6+Inputs!$B$7,Inputs!$B$14,0) -> -15000000 | N6: =IF(AND(N$1>Inputs!$B$6,N$1<=Inputs!$B$6+Inputs!$B$7),Inputs!$B$2*Inputs!$B$3*12*$C6*(1+$D6)^(N$1-Inputs!$B$6-1)*(1-$E6),0)-IF(N$1<Inputs!$B$6,$B6/Inputs!$B$6,0)-IF(N$1=0,Inputs!$B$13,0)+IF(N$1=Inputs!$B$6+Inputs!$B$7,Inputs!$B$14,0) -> 0 | O6: =IF(AND(O$1>Inputs!$B$6,O$1<=Inputs!$B$6+Inputs!$B$7),Inputs!$B$2*Inputs!$B$3*12*$C6*(1+$D6)^(O$1-Inputs!$B$6-1)*(1-$E6),0)-IF(O$1<Inputs!$B$6,$B6/Inputs!$B$6,0)-IF(O$1=0,Inputs!$B$13,0)+IF(O$1=Inputs!$B$6+Inputs!$B$7,Inputs!$B$14,0) -> 4752000 | P6: =IF(AND(P$1>Inputs!$B$6,P$1<=Inputs!$B$6+Inputs!$B$7),Inputs!$B$2*Inputs!$B$3*12*$C6*(1+$D6)^(P$1-Inputs!$B$6-1)*(1-$E6),0)-IF(P$1<Inputs!$B$6,$B6/Inputs!$B$6,0)-IF(P$1=0,Inputs!$B$13,0)+IF(P$1=Inputs!$B$6+Inputs!$B$7,Inputs!$B$14,0) -> 4752000 | Q6: =IF(AND(Q$1>Inputs!$B$6,Q$1<=Inputs!$B$6+Inputs!$B$7),Inputs!$B$2*Inputs!$B$3*12*$C6*(1+$D6)^(Q$1-Inputs!$B$6-1)*(1-$E6),0)-IF(Q$1<Inputs!$B$6,$B6/Inputs!$B$6,0)-IF(Q$1=0,Inputs!$B$13,0)+IF(Q$1=Inputs!$B$6+Inputs!$B$7,Inputs!$B$14,0) -> 4752000 | R6: =IF(AND(R$1>Inputs!$B$6,R$1<=Inputs!$B$6+Inputs!$B$7),Inputs!$B$2*Inputs!$B$3*12*$C6*(1+$D6)^(R$1-Inputs!$B$6-1)*(1-$E6),0)-IF(R$1<Inputs!$B$6,$B6/Inputs!$B$6,0)-IF(R$1=0,Inputs!$B$13,0)+IF(R$1=Inputs!$B$6+Inputs!$B$7,Inputs!$B$14,0) -> 4752000 | S6: =IF(AND(S$1>Inputs!$B$6,S$1<=Inputs!$B$6+Inputs!$B$7),Inputs!$B$2*Inputs!$B$3*12*$C6*(1+$D6)^(S$1-Inputs!$B$6-1)*(1-$E6),0)-IF(S$1<Inputs!$B$6,$B6/Inputs!$B$6,0)-IF(S$1=0,Inputs!$B$13,0)+IF(S$1=Inputs!$B$6+Inputs!$B$7,Inputs!$B$14,0) -> 4752000 | ... BT6: =IF(AND(BT$1>Inputs!$B$6,BT$1<=Inputs!$B$6+Inputs!$B$7),Inputs!$B$2*Inputs!$B$3*12*$C6*(1+$D6)^(BT$1-Inputs!$B$6-1)*(1-$E6),0)-IF(BT$1<Inputs!$B$6,$B6/Inputs!$B$6,0)-IF(BT$1=0,Inputs!$B$13,0)+IF(BT$1=Inputs!$B$6+Inputs!$B$7,Inputs!$B$14,0) -> 0
A7: Cost feasibility stress: EUR 75k/room | B7: =Inputs!$B$5*10 -> 150000000 | C7: =Inputs!$B$8 -> 0.95 | D7: =Inputs!$B$4 -> 0.05 | E7: =Inputs!$B$9+Inputs!$B$10 -> 0.35 | F7: =Inputs!$B$17+0.04 -> 0.083 | G7: =NPV(F7,M7:BT7)+L7 -> -40045244 | H7: =IFERROR(IRR(L7:BT7),"Not defined") -> 0.060511452 | I7: =IF(MAX(L41:BT41)>0,MAX(L41:BT41),"Not reached") -> 17.43944 | J7: =IF(MAX(L43:BT43)>0,MAX(L43:BT43),"Not reached") -> Not reached | K7: =IF(AND(G7>0,ISNUMBER(H7),H7>F7,ISNUMBER(I7),I7<=Inputs!$B$12),"PASS","FAIL") -> FAIL | L7: =IF(AND(L$1>Inputs!$B$6,L$1<=Inputs!$B$6+Inputs!$B$7),Inputs!$B$2*Inputs!$B$3*12*$C7*(1+$D7)^(L$1-Inputs!$B$6-1)*(1-$E7),0)-IF(L$1<Inputs!$B$6,$B7/Inputs!$B$6,0)-IF(L$1=0,Inputs!$B$13,0)+IF(L$1=Inputs!$B$6+Inputs!$B$7,Inputs!$B$14,0) -> -75000000 | M7: =IF(AND(M$1>Inputs!$B$6,M$1<=Inputs!$B$6+Inputs!$B$7),Inputs!$B$2*Inputs!$B$3*12*$C7*(1+$D7)^(M$1-Inputs!$B$6-1)*(1-$E7),0)-IF(M$1<Inputs!$B$6,$B7/Inputs!$B$6,0)-IF(M$1=0,Inputs!$B$13,0)+IF(M$1=Inputs!$B$6+Inputs!$B$7,Inputs!$B$14,0) -> -75000000 | N7: =IF(AND(N$1>Inputs!$B$6,N$1<=Inputs!$B$6+Inputs!$B$7),Inputs!$B$2*Inputs!$B$3*12*$C7*(1+$D7)^(N$1-Inputs!$B$6-1)*(1-$E7),0)-IF(N$1<Inputs!$B$6,$B7/Inputs!$B$6,0)-IF(N$1=0,Inputs!$B$13,0)+IF(N$1=Inputs!$B$6+Inputs!$B$7,Inputs!$B$14,0) -> 0 | O7: =IF(AND(O$1>Inputs!$B$6,O$1<=Inputs!$B$6+Inputs!$B$7),Inputs!$B$2*Inputs!$B$3*12*$C7*(1+$D7)^(O$1-Inputs!$B$6-1)*(1-$E7),0)-IF(O$1<Inputs!$B$6,$B7/Inputs!$B$6,0)-IF(O$1=0,Inputs!$B$13,0)+IF(O$1=Inputs!$B$6+Inputs!$B$7,Inputs!$B$14,0) -> 6669000 | P7: =IF(AND(P$1>Inputs!$B$6,P$1<=Inputs!$B$6+Inputs!$B$7),Inputs!$B$2*Inputs!$B$3*12*$C7*(1+$D7)^(P$1-Inputs!$B$6-1)*(1-$E7),0)-IF(P$1<Inputs!$B$6,$B7/Inputs!$B$6,0)-IF(P$1=0,Inputs!$B$13,0)+IF(P$1=Inputs!$B$6+Inputs!$B$7,Inputs!$B$14,0) -> 7002450 | Q7: =IF(AND(Q$1>Inputs!$B$6,Q$1<=Inputs!$B$6+Inputs!$B$7),Inputs!$B$2*Inputs!$B$3*12*$C7*(1+$D7)^(Q$1-Inputs!$B$6-1)*(1-$E7),0)-IF(Q$1<Inputs!$B$6,$B7/Inputs!$B$6,0)-IF(Q$1=0,Inputs!$B$13,0)+IF(Q$1=Inputs!$B$6+Inputs!$B$7,Inputs!$B$14,0) -> 7352572.5 | R7: =IF(AND(R$1>Inputs!$B$6,R$1<=Inputs!$B$6+Inputs!$B$7),Inputs!$B$2*Inputs!$B$3*12*$C7*(1+$D7)^(R$1-Inputs!$B$6-1)*(1-$E7),0)-IF(R$1<Inputs!$B$6,$B7/Inputs!$B$6,0)-IF(R$1=0,Inputs!$B$13,0)+IF(R$1=Inputs!$B$6+Inputs!$B$7,Inputs!$B$14,0) -> 7720201.1 | S7: =IF(AND(S$1>Inputs!$B$6,S$1<=Inputs!$B$6+Inputs!$B$7),Inputs!$B$2*Inputs!$B$3*12*$C7*(1+$D7)^(S$1-Inputs!$B$6-1)*(1-$E7),0)-IF(S$1<Inputs!$B$6,$B7/Inputs!$B$6,0)-IF(S$1=0,Inputs!$B$13,0)+IF(S$1=Inputs!$B$6+Inputs!$B$7,Inputs!$B$14,0) -> 8106211.2 | ... BT7: =IF(AND(BT$1>Inputs!$B$6,BT$1<=Inputs!$B$6+Inputs!$B$7),Inputs!$B$2*Inputs!$B$3*12*$C7*(1+$D7)^(BT$1-Inputs!$B$6-1)*(1-$E7),0)-IF(BT$1<Inputs!$B$6,$B7/Inputs!$B$6,0)-IF(BT$1=0,Inputs!$B$13,0)+IF(BT$1=Inputs!$B$6+Inputs!$B$7,Inputs!$B$14,0) -> 0
A10: All cases keep 2,000 rooms and EUR 450 opening rent. Cost cases are illustrative stresses, not verified market quotes.
A15: Requested assumptions | cumulative CF | L15: =SUM($L2:L2) -> -7500000 | M15: =SUM($L2:M2) -> -15000000 | N15: =SUM($L2:N2) -> -15000000 | O15: =SUM($L2:O2) -> -8331000 | P15: =SUM($L2:P2) -> -1328550 | Q15: =SUM($L2:Q2) -> 6024022.5 | R15: =SUM($L2:R2) -> 13744224 | S15: =SUM($L2:S2) -> 21850435 | ... BT15: =SUM($L2:BT2) -> 4.2808067e+08
A16: Payback crossing | L16: =0 -> 0 | M16: =IF(AND(M$1>Inputs!$B$6,M15>=0,L15<0),M$1-1-L15/M2,0) -> 0 | N16: =IF(AND(N$1>Inputs!$B$6,N15>=0,M15<0),N$1-1-M15/N2,0) -> 0 | O16: =IF(AND(O$1>Inputs!$B$6,O15>=0,N15<0),O$1-1-N15/O2,0) -> 0 | P16: =IF(AND(P$1>Inputs!$B$6,P15>=0,O15<0),P$1-1-O15/P2,0) -> 0 | Q16: =IF(AND(Q$1>Inputs!$B$6,Q15>=0,P15<0),Q$1-1-P15/Q2,0) -> 4.1806919 | R16: =IF(AND(R$1>Inputs!$B$6,R15>=0,Q15<0),R$1-1-Q15/R2,0) -> 0 | S16: =IF(AND(S$1>Inputs!$B$6,S15>=0,R15<0),S$1-1-R15/S2,0) -> 0 | T16: =IF(AND(T$1>Inputs!$B$6,T15>=0,S15<0),T$1-1-S15/T2,0) -> 0 | ... BT16: =IF(AND(BT$1>Inputs!$B$6,BT15>=0,BS15<0),BT$1-1-BS15/BT2,0) -> 0
A17: Cumulative PV | L17: =L2/(1+$F$2)^L$1 -> -7500000 | M17: =M2/(1+$F$2)^M$1+L17 -> -14690796 | N17: =N2/(1+$F$2)^N$1+M17 -> -14690796 | O17: =O2/(1+$F$2)^O$1+N17 -> -8813090.7 | P17: =P2/(1+$F$2)^P$1+O17 -> -2895937.9 | Q17: =Q2/(1+$F$2)^Q$1+P17 -> 3060927.3 | R17: =R2/(1+$F$2)^R$1+Q17 -> 9057771.5 | S17: =S2/(1+$F$2)^S$1+R17 -> 15094863 | T17: =T2/(1+$F$2)^T$1+S17 -> 21172472 | ... BT17: =BT2/(1+$F$2)^BT$1+BS17 -> 1.7992543e+08
A18: Discounted crossing | L18: =0 -> 0 | M18: =IF(AND(M$1>Inputs!$B$6,M17>=0,L17<0),M$1-1-L17/(M2/(1+$F$2)^M$1),0) -> 0 | N18: =IF(AND(N$1>Inputs!$B$6,N17>=0,M17<0),N$1-1-M17/(N2/(1+$F$2)^N$1),0) -> 0 | O18: =IF(AND(O$1>Inputs!$B$6,O17>=0,N17<0),O$1-1-N17/(O2/(1+$F$2)^O$1),0) -> 0 | P18: =IF(AND(P$1>Inputs!$B$6,P17>=0,O17<0),P$1-1-O17/(P2/(1+$F$2)^P$1),0) -> 0 | Q18: =IF(AND(Q$1>Inputs!$B$6,Q17>=0,P17<0),Q$1-1-P17/(Q2/(1+$F$2)^Q$1),0) -> 4.4861513 | R18: =IF(AND(R$1>Inputs!$B$6,R17>=0,Q17<0),R$1-1-Q17/(R2/(1+$F$2)^R$1),0) -> 0 | S18: =IF(AND(S$1>Inputs!$B$6,S17>=0,R17<0),S$1-1-R17/(S2/(1+$F$2)^S$1),0) -> 0 | T18: =IF(AND(T$1>Inputs!$B$6,T17>=0,S17<0),T$1-1-S17/(T2/(1+$F$2)^T$1),0) -> 0 | ... BT18: =IF(AND(BT$1>Inputs!$B$6,BT17>=0,BS17<0),BT$1-1-BS17/(BT2/(1+$F$2)^BT$1),0) -> 0
A20: Lower occupancy / no rent growth | cumulative CF | L20: =SUM($L3:L3) -> -7500000 | M20: =SUM($L3:M3) -> -15000000 | N20: =SUM($L3:N3) -> -15000000 | O20: =SUM($L3:O3) -> -10248000 | P20: =SUM($L3:P3) -> -5496000 | Q20: =SUM($L3:Q3) -> -744000 | R20: =SUM($L3:R3) -> 4008000 | S20: =SUM($L3:S3) -> 8760000 | ... BT20: =SUM($L3:BT3) -> 127560000
A21: Payback crossing | L21: =0 -> 0 | M21: =IF(AND(M$1>Inputs!$B$6,M20>=0,L20<0),M$1-1-L20/M3,0) -> 0 | N21: =IF(AND(N$1>Inputs!$B$6,N20>=0,M20<0),N$1-1-M20/N3,0) -> 0 | O21: =IF(AND(O$1>Inputs!$B$6,O20>=0,N20<0),O$1-1-N20/O3,0) -> 0 | P21: =IF(AND(P$1>Inputs!$B$6,P20>=0,O20<0),P$1-1-O20/P3,0) -> 0 | Q21: =IF(AND(Q$1>Inputs!$B$6,Q20>=0,P20<0),Q$1-1-P20/Q3,0) -> 0 | R21: =IF(AND(R$1>Inputs!$B$6,R20>=0,Q20<0),R$1-1-Q20/R3,0) -> 5.1565657 | S21: =IF(AND(S$1>Inputs!$B$6,S20>=0,R20<0),S$1-1-R20/S3,0) -> 0 | T21: =IF(AND(T$1>Inputs!$B$6,T20>=0,S20<0),T$1-1-S20/T3,0) -> 0 | ... BT21: =IF(AND(BT$1>Inputs!$B$6,BT20>=0,BS20<0),BT$1-1-BS20/BT3,0) -> 0
A22: Cumulative PV | L22: =L3/(1+$F$3)^L$1 -> -7500000 | M22: =M3/(1+$F$3)^M$1+L22 -> -14690796 | N22: =N3/(1+$F$3)^N$1+M22 -> -14690796 | O22: =O3/(1+$F$3)^O$1+N22 -> -10502633 | P22: =P3/(1+$F$3)^P$1+O22 -> -6487137.4 | Q22: =Q3/(1+$F$3)^Q$1+P22 -> -2637189.2 | R22: =R3/(1+$F$3)^R$1+Q22 -> 1054036.3 | S22: =S3/(1+$F$3)^S$1+R22 -> 4593082.9 | T22: =T3/(1+$F$3)^T$1+S22 -> 7986224.3 | ... BT22: =BT3/(1+$F$3)^BT$1+BS22 -> 58168179
A23: Discounted crossing | L23: =0 -> 0 | M23: =IF(AND(M$1>Inputs!$B$6,M22>=0,L22<0),M$1-1-L22/(M3/(1+$F$3)^M$1),0) -> 0 | N23: =IF(AND(N$1>Inputs!$B$6,N22>=0,M22<0),N$1-1-M22/(N3/(1+$F$3)^N$1),0) -> 0 | O23: =IF(AND(O$1>Inputs!$B$6,O22>=0,N22<0),O$1-1-N22/(O3/(1+$F$3)^O$1),0) -> 0 | P23: =IF(AND(P$1>Inputs!$B$6,P22>=0,O22<0),P$1-1-O22/(P3/(1+$F$3)^P$1),0) -> 0 | Q23: =IF(AND(Q$1>Inputs!$B$6,Q22>=0,P22<0),Q$1-1-P22/(Q3/(1+$F$3)^Q$1),0) -> 0 | R23: =IF(AND(R$1>Inputs!$B$6,R22>=0,Q22<0),R$1-1-Q22/(R3/(1+$F$3)^R$1),0) -> 5.7144481 | S23: =IF(AND(S$1>Inputs!$B$6,S22>=0,R22<0),S$1-1-R22/(S3/(1+$F$3)^S$1),0) -> 0 | T23: =IF(AND(T$1>Inputs!$B$6,T22>=0,S22<0),T$1-1-S22/(T3/(1+$F$3)^T$1),0) -> 0 | ... BT23: =IF(AND(BT$1>Inputs!$B$6,BT22>=0,BS22<0),BT$1-1-BS22/(BT3/(1+$F$3)^BT$1),0) -> 0
A25: Cost doubles | cumulative CF | L25: =SUM($L4:L4) -> -15000000 | M25: =SUM($L4:M4) -> -30000000 | N25: =SUM($L4:N4) -> -30000000 | O25: =SUM($L4:O4) -> -23331000 | P25: =SUM($L4:P4) -> -16328550 | Q25: =SUM($L4:Q4) -> -8975977.5 | R25: =SUM($L4:R4) -> -1255776.4 | S25: =SUM($L4:S4) -> 6850434.8 | ... BT25: =SUM($L4:BT4) -> 4.1308067e+08
A26: Payback crossing | L26: =0 -> 0 | M26: =IF(AND(M$1>Inputs!$B$6,M25>=0,L25<0),M$1-1-L25/M4,0) -> 0 | N26: =IF(AND(N$1>Inputs!$B$6,N25>=0,M25<0),N$1-1-M25/N4,0) -> 0 | O26: =IF(AND(O$1>Inputs!$B$6,O25>=0,N25<0),O$1-1-N25/O4,0) -> 0 | P26: =IF(AND(P$1>Inputs!$B$6,P25>=0,O25<0),P$1-1-O25/P4,0) -> 0 | Q26: =IF(AND(Q$1>Inputs!$B$6,Q25>=0,P25<0),Q$1-1-P25/Q4,0) -> 0 | R26: =IF(AND(R$1>Inputs!$B$6,R25>=0,Q25<0),R$1-1-Q25/R4,0) -> 0 | S26: =IF(AND(S$1>Inputs!$B$6,S25>=0,R25<0),S$1-1-R25/S4,0) -> 6.1549153 | T26: =IF(AND(T$1>Inputs!$B$6,T25>=0,S25<0),T$1-1-S25/T4,0) -> 0 | ... BT26: =IF(AND(BT$1>Inputs!$B$6,BT25>=0,BS25<0),BT$1-1-BS25/BT4,0) -> 0
A27: Cumulative PV | L27: =L4/(1+$F$4)^L$1 -> -15000000 | M27: =M4/(1+$F$4)^M$1+L27 -> -29381592 | N27: =N4/(1+$F$4)^N$1+M27 -> -29381592 | O27: =O4/(1+$F$4)^O$1+N27 -> -23503886 | P27: =P4/(1+$F$4)^P$1+O27 -> -17586734 | Q27: =Q4/(1+$F$4)^Q$1+P27 -> -11629868 | R27: =R4/(1+$F$4)^R$1+Q27 -> -5633024.3 | S27: =S4/(1+$F$4)^S$1+R27 -> 404067.15 | T27: =T4/(1+$F$4)^T$1+S27 -> 6481676 | ... BT27: =BT4/(1+$F$4)^BT$1+BS27 -> 1.6523463e+08
A28: Discounted crossing | L28: =0 -> 0 | M28: =IF(AND(M$1>Inputs!$B$6,M27>=0,L27<0),M$1-1-L27/(M4/(1+$F$4)^M$1),0) -> 0 | N28: =IF(AND(N$1>Inputs!$B$6,N27>=0,M27<0),N$1-1-M27/(N4/(1+$F$4)^N$1),0) -> 0 | O28: =IF(AND(O$1>Inputs!$B$6,O27>=0,N27<0),O$1-1-N27/(O4/(1+$F$4)^O$1),0) -> 0 | P28: =IF(AND(P$1>Inputs!$B$6,P27>=0,O27<0),P$1-1-O27/(P4/(1+$F$4)^P$1),0) -> 0 | Q28: =IF(AND(Q$1>Inputs!$B$6,Q27>=0,P27<0),Q$1-1-P27/(Q4/(1+$F$4)^Q$1),0) -> 0 | R28: =IF(AND(R$1>Inputs!$B$6,R27>=0,Q27<0),R$1-1-Q27/(R4/(1+$F$4)^R$1),0) -> 0 | S28: =IF(AND(S$1>Inputs!$B$6,S27>=0,R27<0),S$1-1-R27/(S4/(1+$F$4)^S$1),0) -> 6.9330692 | T28: =IF(AND(T$1>Inputs!$B$6,T27>=0,S27<0),T$1-1-S27/(T4/(1+$F$4)^T$1),0) -> 0 | ... BT28: =IF(AND(BT$1>Inputs!$B$6,BT27>=0,BS27<0),BT$1-1-BS27/(BT4/(1+$F$4)^BT$1),0) -> 0
A30: Project risk +4 percentage points | cumulative CF | L30: =SUM($L5:L5) -> -7500000 | M30: =SUM($L5:M5) -> -15000000 | N30: =SUM($L5:N5) -> -15000000 | O30: =SUM($L5:O5) -> -8331000 | P30: =SUM($L5:P5) -> -1328550 | Q30: =SUM($L5:Q5) -> 6024022.5 | R30: =SUM($L5:R5) -> 13744224 | S30: =SUM($L5:S5) -> 21850435 | ... BT30: =SUM($L5:BT5) -> 4.2808067e+08
A31: Payback crossing | L31: =0 -> 0 | M31: =IF(AND(M$1>Inputs!$B$6,M30>=0,L30<0),M$1-1-L30/M5,0) -> 0 | N31: =IF(AND(N$1>Inputs!$B$6,N30>=0,M30<0),N$1-1-M30/N5,0) -> 0 | O31: =IF(AND(O$1>Inputs!$B$6,O30>=0,N30<0),O$1-1-N30/O5,0) -> 0 | P31: =IF(AND(P$1>Inputs!$B$6,P30>=0,O30<0),P$1-1-O30/P5,0) -> 0 | Q31: =IF(AND(Q$1>Inputs!$B$6,Q30>=0,P30<0),Q$1-1-P30/Q5,0) -> 4.1806919 | R31: =IF(AND(R$1>Inputs!$B$6,R30>=0,Q30<0),R$1-1-Q30/R5,0) -> 0 | S31: =IF(AND(S$1>Inputs!$B$6,S30>=0,R30<0),S$1-1-R30/S5,0) -> 0 | T31: =IF(AND(T$1>Inputs!$B$6,T30>=0,S30<0),T$1-1-S30/T5,0) -> 0 | ... BT31: =IF(AND(BT$1>Inputs!$B$6,BT30>=0,BS30<0),BT$1-1-BS30/BT5,0) -> 0
A32: Cumulative PV | L32: =L5/(1+$F$5)^L$1 -> -7500000 | M32: =M5/(1+$F$5)^M$1+L32 -> -14425208 | N32: =N5/(1+$F$5)^N$1+M32 -> -14425208 | O32: =O5/(1+$F$5)^O$1+N32 -> -9175013.8 | P32: =P5/(1+$F$5)^P$1+O32 -> -4084798.1 | Q32: =Q5/(1+$F$5)^Q$1+P32 -> 850314.16 | R32: =R5/(1+$F$5)^R$1+Q32 -> 5635049 | S32: =S5/(1+$F$5)^S$1+R32 -> 10273989 | T32: =T5/(1+$F$5)^T$1+S32 -> 14771575 | ... BT32: =BT5/(1+$F$5)^BT$1+BS32 -> 89781626
A33: Discounted crossing | L33: =0 -> 0 | M33: =IF(AND(M$1>Inputs!$B$6,M32>=0,L32<0),M$1-1-L32/(M5/(1+$F$5)^M$1),0) -> 0 | N33: =IF(AND(N$1>Inputs!$B$6,N32>=0,M32<0),N$1-1-M32/(N5/(1+$F$5)^N$1),0) -> 0 | O33: =IF(AND(O$1>Inputs!$B$6,O32>=0,N32<0),O$1-1-N32/(O5/(1+$F$5)^O$1),0) -> 0 | P33: =IF(AND(P$1>Inputs!$B$6,P32>=0,O32<0),P$1-1-O32/(P5/(1+$F$5)^P$1),0) -> 0 | Q33: =IF(AND(Q$1>Inputs!$B$6,Q32>=0,P32<0),Q$1-1-P32/(Q5/(1+$F$5)^Q$1),0) -> 4.8277011 | R33: =IF(AND(R$1>Inputs!$B$6,R32>=0,Q32<0),R$1-1-Q32/(R5/(1+$F$5)^R$1),0) -> 0 | S33: =IF(AND(S$1>Inputs!$B$6,S32>=0,R32<0),S$1-1-R32/(S5/(1+$F$5)^S$1),0) -> 0 | T33: =IF(AND(T$1>Inputs!$B$6,T32>=0,S32<0),T$1-1-S32/(T5/(1+$F$5)^T$1),0) -> 0 | ... BT33: =IF(AND(BT$1>Inputs!$B$6,BT32>=0,BS32<0),BT$1-1-BS32/(BT5/(1+$F$5)^BT$1),0) -> 0
A35: Combined stress | cumulative CF | L35: =SUM($L6:L6) -> -15000000 | M35: =SUM($L6:M6) -> -30000000 | N35: =SUM($L6:N6) -> -30000000 | O35: =SUM($L6:O6) -> -25248000 | P35: =SUM($L6:P6) -> -20496000 | Q35: =SUM($L6:Q6) -> -15744000 | R35: =SUM($L6:R6) -> -10992000 | S35: =SUM($L6:S6) -> -6240000 | ... BT35: =SUM($L6:BT6) -> 112560000
A36: Payback crossing | L36: =0 -> 0 | M36: =IF(AND(M$1>Inputs!$B$6,M35>=0,L35<0),M$1-1-L35/M6,0) -> 0 | N36: =IF(AND(N$1>Inputs!$B$6,N35>=0,M35<0),N$1-1-M35/N6,0) -> 0 | O36: =IF(AND(O$1>Inputs!$B$6,O35>=0,N35<0),O$1-1-N35/O6,0) -> 0 | P36: =IF(AND(P$1>Inputs!$B$6,P35>=0,O35<0),P$1-1-O35/P6,0) -> 0 | Q36: =IF(AND(Q$1>Inputs!$B$6,Q35>=0,P35<0),Q$1-1-P35/Q6,0) -> 0 | R36: =IF(AND(R$1>Inputs!$B$6,R35>=0,Q35<0),R$1-1-Q35/R6,0) -> 0 | S36: =IF(AND(S$1>Inputs!$B$6,S35>=0,R35<0),S$1-1-R35/S6,0) -> 0 | T36: =IF(AND(T$1>Inputs!$B$6,T35>=0,S35<0),T$1-1-S35/T6,0) -> 0 | ... BT36: =IF(AND(BT$1>Inputs!$B$6,BT35>=0,BS35<0),BT$1-1-BS35/BT6,0) -> 0
A37: Cumulative PV | L37: =L6/(1+$F$6)^L$1 -> -15000000 | M37: =M6/(1+$F$6)^M$1+L37 -> -28850416 | N37: =N6/(1+$F$6)^N$1+M37 -> -28850416 | O37: =O6/(1+$F$6)^O$1+N37 -> -25109387 | P37: =P6/(1+$F$6)^P$1+O37 -> -21655066 | Q37: =Q6/(1+$F$6)^Q$1+P37 -> -18465482 | R37: =R6/(1+$F$6)^R$1+Q37 -> -15520343 | S37: =S6/(1+$F$6)^S$1+R37 -> -12800917 | T37: =T6/(1+$F$6)^T$1+S37 -> -10289905 | ... BT37: =BT6/(1+$F$6)^BT$1+BS37 -> 15499625
A38: Discounted crossing | L38: =0 -> 0 | M38: =IF(AND(M$1>Inputs!$B$6,M37>=0,L37<0),M$1-1-L37/(M6/(1+$F$6)^M$1),0) -> 0 | N38: =IF(AND(N$1>Inputs!$B$6,N37>=0,M37<0),N$1-1-M37/(N6/(1+$F$6)^N$1),0) -> 0 | O38: =IF(AND(O$1>Inputs!$B$6,O37>=0,N37<0),O$1-1-N37/(O6/(1+$F$6)^O$1),0) -> 0 | P38: =IF(AND(P$1>Inputs!$B$6,P37>=0,O37<0),P$1-1-O37/(P6/(1+$F$6)^P$1),0) -> 0 | Q38: =IF(AND(Q$1>Inputs!$B$6,Q37>=0,P37<0),Q$1-1-P37/(Q6/(1+$F$6)^Q$1),0) -> 0 | R38: =IF(AND(R$1>Inputs!$B$6,R37>=0,Q37<0),R$1-1-Q37/(R6/(1+$F$6)^R$1),0) -> 0 | S38: =IF(AND(S$1>Inputs!$B$6,S37>=0,R37<0),S$1-1-R37/(S6/(1+$F$6)^S$1),0) -> 0 | T38: =IF(AND(T$1>Inputs!$B$6,T37>=0,S37<0),T$1-1-S37/(T6/(1+$F$6)^T$1),0) -> 0 | ... BT38: =IF(AND(BT$1>Inputs!$B$6,BT37>=0,BS37<0),BT$1-1-BS37/(BT6/(1+$F$6)^BT$1),0) -> 0
A40: Cost feasibility stress: EUR 75k/room | cumulative CF | L40: =SUM($L7:L7) -> -75000000 | M40: =SUM($L7:M7) -> -150000000 | N40: =SUM($L7:N7) -> -150000000 | O40: =SUM($L7:O7) -> -143331000 | P40: =SUM($L7:P7) -> -136328550 | Q40: =SUM($L7:Q7) -> -1.2897598e+08 | R40: =SUM($L7:R7) -> -1.2125578e+08 | S40: =SUM($L7:S7) -> -1.1314957e+08 | ... BT40: =SUM($L7:BT7) -> 2.9308067e+08
A41: Payback crossing | L41: =0 -> 0 | M41: =IF(AND(M$1>Inputs!$B$6,M40>=0,L40<0),M$1-1-L40/M7,0) -> 0 | N41: =IF(AND(N$1>Inputs!$B$6,N40>=0,M40<0),N$1-1-M40/N7,0) -> 0 | O41: =IF(AND(O$1>Inputs!$B$6,O40>=0,N40<0),O$1-1-N40/O7,0) -> 0 | P41: =IF(AND(P$1>Inputs!$B$6,P40>=0,O40<0),P$1-1-O40/P7,0) -> 0 | Q41: =IF(AND(Q$1>Inputs!$B$6,Q40>=0,P40<0),Q$1-1-P40/Q7,0) -> 0 | R41: =IF(AND(R$1>Inputs!$B$6,R40>=0,Q40<0),R$1-1-Q40/R7,0) -> 0 | S41: =IF(AND(S$1>Inputs!$B$6,S40>=0,R40<0),S$1-1-R40/S7,0) -> 0 | T41: =IF(AND(T$1>Inputs!$B$6,T40>=0,S40<0),T$1-1-S40/T7,0) -> 0 | ... BT41: =IF(AND(BT$1>Inputs!$B$6,BT40>=0,BS40<0),BT$1-1-BS40/BT7,0) -> 0
A42: Cumulative PV | L42: =L7/(1+$F$7)^L$1 -> -75000000 | M42: =M7/(1+$F$7)^M$1+L42 -> -1.4425208e+08 | N42: =N7/(1+$F$7)^N$1+M42 -> -1.4425208e+08 | O42: =O7/(1+$F$7)^O$1+N42 -> -1.3900188e+08 | P42: =P7/(1+$F$7)^P$1+O42 -> -1.3391167e+08 | Q42: =Q7/(1+$F$7)^Q$1+P42 -> -1.2897656e+08 | R42: =R7/(1+$F$7)^R$1+Q42 -> -1.2419182e+08 | S42: =S7/(1+$F$7)^S$1+R42 -> -1.1955288e+08 | T42: =T7/(1+$F$7)^T$1+S42 -> -1.1505529e+08 | ... BT42: =BT7/(1+$F$7)^BT$1+BS42 -> -40045244
A43: Discounted crossing | L43: =0 -> 0 | M43: =IF(AND(M$1>Inputs!$B$6,M42>=0,L42<0),M$1-1-L42/(M7/(1+$F$7)^M$1),0) -> 0 | N43: =IF(AND(N$1>Inputs!$B$6,N42>=0,M42<0),N$1-1-M42/(N7/(1+$F$7)^N$1),0) -> 0 | O43: =IF(AND(O$1>Inputs!$B$6,O42>=0,N42<0),O$1-1-N42/(O7/(1+$F$7)^O$1),0) -> 0 | P43: =IF(AND(P$1>Inputs!$B$6,P42>=0,O42<0),P$1-1-O42/(P7/(1+$F$7)^P$1),0) -> 0 | Q43: =IF(AND(Q$1>Inputs!$B$6,Q42>=0,P42<0),Q$1-1-P42/(Q7/(1+$F$7)^Q$1),0) -> 0 | R43: =IF(AND(R$1>Inputs!$B$6,R42>=0,Q42<0),R$1-1-Q42/(R7/(1+$F$7)^R$1),0) -> 0 | S43: =IF(AND(S$1>Inputs!$B$6,S42>=0,R42<0),S$1-1-R42/(S7/(1+$F$7)^S$1),0) -> 0 | T43: =IF(AND(T$1>Inputs!$B$6,T42>=0,S42<0),T$1-1-S42/(T7/(1+$F$7)^T$1),0) -> 0 | ... BT43: =IF(AND(BT$1>Inputs!$B$6,BT42>=0,BS42<0),BT$1-1-BS42/(BT7/(1+$F$7)^BT$1),0) -> 0

Sheet Sensitivity
A1: NPV EUR | occupancy vs discount rate | B1: 0.043 | C1: 0.063 | D1: 0.083 | E1: 0.103
A2: 0.6 | B2: =SUMPRODUCT(('Cash Flow'!D2:D62*Inputs!$B$2*12*$A2*(1-Inputs!$B$9-Inputs!$B$10)-'Cash Flow'!H2:H62+'Cash Flow'!I2:I62)/(1+B$1)^'Cash Flow'!A2:A62) -> 1.0822471e+08 | C2: =SUMPRODUCT(('Cash Flow'!D2:D62*Inputs!$B$2*12*$A2*(1-Inputs!$B$9-Inputs!$B$10)-'Cash Flow'!H2:H62+'Cash Flow'!I2:I62)/(1+C$1)^'Cash Flow'!A2:A62) -> 73952529 | D2: =SUMPRODUCT(('Cash Flow'!D2:D62*Inputs!$B$2*12*$A2*(1-Inputs!$B$9-Inputs!$B$10)-'Cash Flow'!H2:H62+'Cash Flow'!I2:I62)/(1+D$1)^'Cash Flow'!A2:A62) -> 51389634 | E2: =SUMPRODUCT(('Cash Flow'!D2:D62*Inputs!$B$2*12*$A2*(1-Inputs!$B$9-Inputs!$B$10)-'Cash Flow'!H2:H62+'Cash Flow'!I2:I62)/(1+E$1)^'Cash Flow'!A2:A62) -> 36112751
A3: 0.8 | B3: =SUMPRODUCT(('Cash Flow'!D2:D62*Inputs!$B$2*12*$A3*(1-Inputs!$B$9-Inputs!$B$10)-'Cash Flow'!H2:H62+'Cash Flow'!I2:I62)/(1+B$1)^'Cash Flow'!A2:A62) -> 1.4919655e+08 | C3: =SUMPRODUCT(('Cash Flow'!D2:D62*Inputs!$B$2*12*$A3*(1-Inputs!$B$9-Inputs!$B$10)-'Cash Flow'!H2:H62+'Cash Flow'!I2:I62)/(1+C$1)^'Cash Flow'!A2:A62) -> 1.0345521e+08 | D3: =SUMPRODUCT(('Cash Flow'!D2:D62*Inputs!$B$2*12*$A3*(1-Inputs!$B$9-Inputs!$B$10)-'Cash Flow'!H2:H62+'Cash Flow'!I2:I62)/(1+D$1)^'Cash Flow'!A2:A62) -> 73327915 | E3: =SUMPRODUCT(('Cash Flow'!D2:D62*Inputs!$B$2*12*$A3*(1-Inputs!$B$9-Inputs!$B$10)-'Cash Flow'!H2:H62+'Cash Flow'!I2:I62)/(1+E$1)^'Cash Flow'!A2:A62) -> 52916881
A4: 0.9 | B4: =SUMPRODUCT(('Cash Flow'!D2:D62*Inputs!$B$2*12*$A4*(1-Inputs!$B$9-Inputs!$B$10)-'Cash Flow'!H2:H62+'Cash Flow'!I2:I62)/(1+B$1)^'Cash Flow'!A2:A62) -> 1.6968247e+08 | C4: =SUMPRODUCT(('Cash Flow'!D2:D62*Inputs!$B$2*12*$A4*(1-Inputs!$B$9-Inputs!$B$10)-'Cash Flow'!H2:H62+'Cash Flow'!I2:I62)/(1+C$1)^'Cash Flow'!A2:A62) -> 1.1820654e+08 | D4: =SUMPRODUCT(('Cash Flow'!D2:D62*Inputs!$B$2*12*$A4*(1-Inputs!$B$9-Inputs!$B$10)-'Cash Flow'!H2:H62+'Cash Flow'!I2:I62)/(1+D$1)^'Cash Flow'!A2:A62) -> 84297055 | E4: =SUMPRODUCT(('Cash Flow'!D2:D62*Inputs!$B$2*12*$A4*(1-Inputs!$B$9-Inputs!$B$10)-'Cash Flow'!H2:H62+'Cash Flow'!I2:I62)/(1+E$1)^'Cash Flow'!A2:A62) -> 61318945
A5: 0.95 | B5: =SUMPRODUCT(('Cash Flow'!D2:D62*Inputs!$B$2*12*$A5*(1-Inputs!$B$9-Inputs!$B$10)-'Cash Flow'!H2:H62+'Cash Flow'!I2:I62)/(1+B$1)^'Cash Flow'!A2:A62) -> 1.7992543e+08 | C5: =SUMPRODUCT(('Cash Flow'!D2:D62*Inputs!$B$2*12*$A5*(1-Inputs!$B$9-Inputs!$B$10)-'Cash Flow'!H2:H62+'Cash Flow'!I2:I62)/(1+C$1)^'Cash Flow'!A2:A62) -> 1.2558221e+08 | D5: =SUMPRODUCT(('Cash Flow'!D2:D62*Inputs!$B$2*12*$A5*(1-Inputs!$B$9-Inputs!$B$10)-'Cash Flow'!H2:H62+'Cash Flow'!I2:I62)/(1+D$1)^'Cash Flow'!A2:A62) -> 89781626 | E5: =SUMPRODUCT(('Cash Flow'!D2:D62*Inputs!$B$2*12*$A5*(1-Inputs!$B$9-Inputs!$B$10)-'Cash Flow'!H2:H62+'Cash Flow'!I2:I62)/(1+E$1)^'Cash Flow'!A2:A62) -> 65519978
A6: 1 | B6: =SUMPRODUCT(('Cash Flow'!D2:D62*Inputs!$B$2*12*$A6*(1-Inputs!$B$9-Inputs!$B$10)-'Cash Flow'!H2:H62+'Cash Flow'!I2:I62)/(1+B$1)^'Cash Flow'!A2:A62) -> 1.9016838e+08 | C6: =SUMPRODUCT(('Cash Flow'!D2:D62*Inputs!$B$2*12*$A6*(1-Inputs!$B$9-Inputs!$B$10)-'Cash Flow'!H2:H62+'Cash Flow'!I2:I62)/(1+C$1)^'Cash Flow'!A2:A62) -> 1.3295788e+08 | D6: =SUMPRODUCT(('Cash Flow'!D2:D62*Inputs!$B$2*12*$A6*(1-Inputs!$B$9-Inputs!$B$10)-'Cash Flow'!H2:H62+'Cash Flow'!I2:I62)/(1+D$1)^'Cash Flow'!A2:A62) -> 95266196 | E6: =SUMPRODUCT(('Cash Flow'!D2:D62*Inputs!$B$2*12*$A6*(1-Inputs!$B$9-Inputs!$B$10)-'Cash Flow'!H2:H62+'Cash Flow'!I2:I62)/(1+E$1)^'Cash Flow'!A2:A62) -> 69721010
A9: Rates and occupancy are editable stress inputs; other assumptions follow Inputs. Positive NPV does not establish construction feasibility.

Sheet Sources & Method
A1: SOURCE / METHOD | B1: Evidence / model use | C1: URL / status
A2: Belgian Federal Debt Agency | B2: 10-year sovereign rate 4.30%; source observation dated 14 October 2026; accessed 14 October 2026. Used as nominal reference, not a mandated property hurdle rate. | C2: https://www.debtagency.be/nl
A3: Brussels-Capital Region | B3: Residential rent adjustment follows the health index, subject to lease registration, EPB and request requirements. Annual fixed 5% is modeled only as the user scenario. | C3: https://be.brussels/en/housing/rental/lease-contracts/rental-price-indexation
A4: User requirements | B4: 2,000 rooms; EUR 15m construction budget; EUR 450 opening rent; 5% annual growth; 2-year build; NPV > 0; IRR > discount rate; payback <= 10 years. | C4: Provided in task
A5: Analyst assumptions | B5: 30 operating years; 95% occupancy; costs 30% and reserve 5%; no terminal value; 0% project premium. All editable. | C5: Not independently sourced
A6: Construction schedule | B6: Equal payments at t=0 through t=construction years-1; opening at t=construction years; first annual rent receipt one year later. | C6: Cash flow timing convention
A7: NPV and IRR | B7: NPV = sum CF(t)/(1+r)^t, including t=0. IRR is the annual rate setting NPV to zero; nominal cash flows use a nominal rate. | C7: Excel formulas; initial cached values calculated independently in Python
A8: Payback | B8: Fractional crossing = preceding year + unrecovered balance / crossing-year cash flow. Discounted version uses PV cash flows. No recovery returns Not reached. | C8: From first commitment, not from opening
A9: Funding and tax | B9: Construction allocation sums to EUR 15m. Additional costs increase total funding and can exceed this amount. No financing, corporate tax or independently estimated VAT/land costs. | C9: Pre-tax, unlevered scope
A10: Recalculation | B10: Workbook stores numeric formula caches for immediate viewing; Excel recalculates after edits. Supported construction 1–10 years, operation 1–50 years. | C10: Rebuild with python3 build_model.py; needs openpyxl
