Workbook

Sheet Summary
A1: INVESTMENT DASHBOARD | B1: Base case | C1: Interpretation
A2: Status | B2: Illustrative feasibility model | C2: Replace all blue assumptions with quotes and site data.
A3: Horizon | B3: 31 years from land acquisition | C3: t0 land + construction deposit; t1 balance; t2–t31 operations; sale at t31.
A4: NPV | B4: =NPV(Inputs!$B$31,'Cash flows'!C24:AG24)+'Cash flows'!B24 -> 172795.37 | C4: EUR at selected nominal discount rate; includes terminal sale.
A5: Project IRR | B5: =IFERROR(IRR('Cash flows'!B24:AG24),"No IRR") -> 0.067279591 | C5: Unlevered, pre-income-tax; annual equally spaced periods; includes exit.
A6: Total development cost | B6: =Development!B20 -> 4688593.4 | C6: Includes assumed non-recoverable VAT, transfer duty and contingency.
A7: First operating year NOI | B7: ='Cash flows'!D15 -> 266380 | C7: Before recurring replacement reserve and furniture replacement.
A8: Initial NOI yield on development cost | B8: =B7/B6 -> 0.056814481 | C8: First operating-year NOI / total development cost.
A9: Simple PBP including sale | B9: =IF(MIN('Cash flows'!B33:AG33)=999,"Not reached",IF(MIN('Cash flows'!B33:AG33)>30,31,MIN('Cash flows'!B33:AG33))) -> 18.055498 | C9: Years from t0. Fractional year assumes cash arrives evenly; exit occurs at t31.
A10: Simple PBP from operations only | B10: =IF(MIN('Cash flows'!B34:AG34)=999,"Not reached",MIN('Cash flows'!B34:AG34)) -> 18.055498 | C10: Years from t0. Fractional year assumes cash arrives evenly; exit occurs at t31.
A11: Discounted PBP including sale | B11: =IF(MIN('Cash flows'!B35:AG35)=999,"Not reached",IF(MIN('Cash flows'!B35:AG35)>30,31,MIN('Cash flows'!B35:AG35))) -> 31 | C11: Years from t0. Fractional year assumes cash arrives evenly; exit occurs at t31.
A12: Discounted PBP from operations only | B12: =IF(MIN('Cash flows'!B36:AG36)=999,"Not reached",MIN('Cash flows'!B36:AG36)) -> Not reached | C12: Years from t0. Fractional year assumes cash arrives evenly; exit occurs at t31.
A14: Discount rate | B14: =Inputs!$B$31 -> 0.065
A15: Net sale proceeds at t31 | B15: ='Cash flows'!AG22 -> 8597459.8 | C15: Residual value has a material impact on IRR and NPV.
A17: Decision | B17: =IF(B4>=0,"Meets required return","Below required return") -> Meets required return | C17: NPV is the primary accept/reject criterion, subject to feasibility and risk.
A19: Affordable / planning rule | B19: Unresolved | C19: Confirm municipality, zoning and permit conditions. Inputs contain affordable share, rent discount and additional cost.
A20: Input validity | B20: =IF(AND(Inputs!$B$4>0,Inputs!$B$5>0,Inputs!$B$20>0,Inputs!$B$32>0,Inputs!$B$35>0),"OK","Correct positive inputs") -> OK

Sheet Inputs
A1: BRUSSELS STUDENT HOUSING | editable assumptions | B1: Value | C1: Unit | D1: Basis / caution
A2: Model basis | B2: Unlevered, nominal, pre-income-tax | D2: EUR. No financing or corporate income tax; not an equity IRR.
A3: Location | B3: Brussels-Capital Region; site TBD | D3: Empty site near university and public transport; exact municipality and plot not supplied.
A4: Rooms | B4: 40 | C4: rooms | D4: Illustrative; replace with architect feasibility study.
A5: Gross floor area | B5: 1200 | C5: m² | D5: Includes circulation and shared spaces; 30 m² gross per room.
A6: Land price | B6: 800000 | C6: EUR | D6: Illustrative empty plot; not a valuation or listing.
A7: Land transfer duty | B7: 0.125 | C7: % | D7: Ordinary Brussels rate verified in Legal & sources; confirm specific land transaction and market-value tax base.
A8: Land legal / acquisition fees | B8: 20000 | C8: EUR | D8: Allowance excluding transfer duty; obtain notarial quote.
A9: Structure / envelope / finishes | B9: 1450 | C9: EUR/m² net VAT | D9: Planning allowance, not a contractor quote.
A10: MEP / pipes / electrical / heating | B10: 350 | C10: EUR/m² net VAT | D10: Separate from structure; avoid double counting in quotations.
A11: Bathrooms / sanitary fixtures | B11: 4500 | C11: EUR/room net VAT | D11: Fixtures and fit-out; distribution pipes in MEP.
A12: Kitchens | B12: 60000 | C12: EUR net VAT | D12: Shared kitchen allowance; clarify room-by-room vs shared layout.
A13: Furniture | B13: 2500 | C13: EUR/room net VAT | D13: Bed, mattress, wardrobe, desk, chair; initial equipment.
A14: Site works / utility connections | B14: 80000 | C14: EUR net VAT | D14: External works and connections; soil issues excluded.
A15: Architect fee | B15: 0.08 | C15: % of hard works | D15: Illustrative planning allowance.
... A37: Construction share paid at time 0 | B37: 0.5 | C37: % | D37: Land at t0; construction balance at t1. First operations at t2.

Sheet Development
A1: DEVELOPMENT BUDGET | B1: EUR | C1: Treatment
A2: Land price | B2: =Inputs!$B$6 -> 800000
A3: Land transfer duty | B3: =Inputs!$B$6*Inputs!$B$7 -> 100000
A4: Other acquisition fees | B4: =Inputs!$B$8 -> 20000
A5: Structure / envelope / finishes | B5: =Inputs!$B$5*Inputs!$B$9 -> 1740000
A6: MEP / pipes / electrical / heating | B6: =Inputs!$B$5*Inputs!$B$10 -> 420000
A7: Bathrooms / sanitary fixtures | B7: =Inputs!$B$4*Inputs!$B$11 -> 180000
A8: Kitchens | B8: =Inputs!$B$12 -> 60000
A9: Furniture | B9: =Inputs!$B$13*Inputs!$B$4 -> 100000
A10: Site works / utility connections | B10: =Inputs!$B$14 -> 80000
A11: Hard works subtotal | B11: =SUM(B5:B10) -> 2580000
A12: Architect fee | B12: =B11*Inputs!$B$15 -> 206400
A13: Studies / permits / consultants | B13: =Inputs!$B$16 -> 45000
A14: Affordable / planning extra cost | B14: =Inputs!$B$36 -> 0
A15: Contingency | B15: =SUM(B11:B14)*Inputs!$B$17 -> 283140
A16: Construction budget net VAT | B16: =SUM(B11:B15) -> 3114540
A17: Non-recoverable construction VAT | B17: =B16*Inputs!$B$18 -> 654053.4
A18: Construction budget gross VAT | B18: =B16+B17 -> 3768593.4
A19: Land acquisition total | B19: =SUM(B2:B4) -> 920000
A20: TOTAL INITIAL DEVELOPMENT COST | B20: =B18+B19 -> 4688593.4
A21: Development cost per room | B21: =B20/Inputs!$B$4 -> 117214.84

Sheet Cash flows
A1: ANNUAL CASH FLOWS | EUR, nominal | B1: t=0 | C1: t=1 | D1: t=2 | E1: t=3 | F1: t=4 | G1: t=5 | H1: t=6 | I1: t=7 | J1: t=8 | K1: t=9 | L1: t=10 | M1: t=11 | N1: t=12 | O1: t=13 | P1: t=14 | Q1: t=15 | R1: t=16 | S1: t=17 | T1: t=18 | U1: t=19 | V1: t=20 | W1: t=21 | X1: t=22 | Y1: t=23 | Z1: t=24 | AA1: t=25 | AB1: t=26 | AC1: t=27 | AD1: t=28 | AE1: t=29 | AF1: t=30 | AG1: t=31
A2: Time from purchase (years) | B2: 0 | C2: 1 | D2: 2 | E2: 3 | F2: 4 | G2: 5 | H2: 6 | I2: 7 | J2: 8 | K2: 9 | L2: 10 | M2: 11 | N2: 12 | O2: 13 | P2: 14 | Q2: 15 | R2: 16 | S2: 17 | T2: 18 | U2: 19 | V2: 20 | W2: 21 | X2: 22 | Y2: 23 | Z2: 24 | AA2: 25 | AB2: 26 | AC2: 27 | AD2: 28 | AE2: 29 | AF2: 30 | AG2: 31
A3: Operating year (0 = construction) | B3: 0 | C3: 0 | D3: 1 | E3: 2 | F3: 3 | G3: 4 | H3: 5 | I3: 6 | J3: 7 | K3: 8 | L3: 9 | M3: 10 | N3: 11 | O3: 12 | P3: 13 | Q3: 14 | R3: 15 | S3: 16 | T3: 17 | U3: 18 | V3: 19 | W3: 20 | X3: 21 | Y3: 22 | Z3: 23 | AA3: 24 | AB3: 25 | AC3: 26 | AD3: 27 | AE3: 28 | AF3: 29 | AG3: 30
A5: Land acquisition | B5: =-Development!$B$19 -> -920000 | C5: =0 -> 0 | D5: =0 -> 0 | E5: =0 -> 0 | F5: =0 -> 0 | G5: =0 -> 0 | H5: =0 -> 0 | I5: =0 -> 0 | J5: =0 -> 0 | ... AG5: =0 -> 0
A6: Construction spending | B6: =-Development!$B$18*Inputs!$B$37 -> -1884296.7 | C6: =-Development!$B$18*(1-Inputs!$B$37) -> -1884296.7 | D6: =0 -> 0 | E6: =0 -> 0 | F6: =0 -> 0 | G6: =0 -> 0 | H6: =0 -> 0 | I6: =0 -> 0 | J6: =0 -> 0 | K6: =0 -> 0 | ... AG6: =0 -> 0
A8: Collected rental income | B8: =IF(B$3=0,0,Inputs!$B$4*12*Inputs!$B$20*(1-Inputs!$B$19*Inputs!$B$21 )*Inputs!$B$22*(1+Inputs!$B$23)^(B$3-1)) -> 0 | C8: =IF(C$3=0,0,Inputs!$B$4*12*Inputs!$B$20*(1-Inputs!$B$19*Inputs!$B$21 )*Inputs!$B$22*(1+Inputs!$B$23)^(C$3-1)) -> 0 | D8: =IF(D$3=0,0,Inputs!$B$4*12*Inputs!$B$20*(1-Inputs!$B$19*Inputs!$B$21 )*Inputs!$B$22*(1+Inputs!$B$23)^(D$3-1)) -> 342000 | E8: =IF(E$3=0,0,Inputs!$B$4*12*Inputs!$B$20*(1-Inputs!$B$19*Inputs!$B$21 )*Inputs!$B$22*(1+Inputs!$B$23)^(E$3-1)) -> 348840 | F8: =IF(F$3=0,0,Inputs!$B$4*12*Inputs!$B$20*(1-Inputs!$B$19*Inputs!$B$21 )*Inputs!$B$22*(1+Inputs!$B$23)^(F$3-1)) -> 355816.8 | G8: =IF(G$3=0,0,Inputs!$B$4*12*Inputs!$B$20*(1-Inputs!$B$19*Inputs!$B$21 )*Inputs!$B$22*(1+Inputs!$B$23)^(G$3-1)) -> 362933.14 | H8: =IF(H$3=0,0,Inputs!$B$4*12*Inputs!$B$20*(1-Inputs!$B$19*Inputs!$B$21 )*Inputs!$B$22*(1+Inputs!$B$23)^(H$3-1)) -> 370191.8 | I8: =IF(I$3=0,0,Inputs!$B$4*12*Inputs!$B$20*(1-Inputs!$B$19*Inputs!$B$21 )*Inputs!$B$22*(1+Inputs!$B$23)^(I$3-1)) -> 377595.63 | ... AG8: =IF(AG$3=0,0,Inputs!$B$4*12*Inputs!$B$20*(1-Inputs!$B$19*Inputs!$B$21 )*Inputs!$B$22*(1+Inputs!$B$23)^(AG$3-1)) -> 607338.88
A9: Maintenance / repairs | B9: =-B8*Inputs!$B$24 -> 0 | C9: =-C8*Inputs!$B$24 -> 0 | D9: =-D8*Inputs!$B$24 -> -20520 | E9: =-E8*Inputs!$B$24 -> -20930.4 | F9: =-F8*Inputs!$B$24 -> -21349.008 | G9: =-G8*Inputs!$B$24 -> -21775.988 | H9: =-H8*Inputs!$B$24 -> -22211.508 | I9: =-I8*Inputs!$B$24 -> -22655.738 | ... AG9: =-AG8*Inputs!$B$24 -> -36440.333
A10: Management | B10: =-B8*Inputs!$B$25 -> 0 | C10: =-C8*Inputs!$B$25 -> 0 | D10: =-D8*Inputs!$B$25 -> -17100 | E10: =-E8*Inputs!$B$25 -> -17442 | F10: =-F8*Inputs!$B$25 -> -17790.84 | G10: =-G8*Inputs!$B$25 -> -18146.657 | H10: =-H8*Inputs!$B$25 -> -18509.59 | I10: =-I8*Inputs!$B$25 -> -18879.782 | ... AG10: =-AG8*Inputs!$B$25 -> -30366.944
A11: Insurance | B11: =IF(B$3=0,0,-Inputs!$B$26*(1+Inputs!$B$30)^(B$3-1)) -> 0 | C11: =IF(C$3=0,0,-Inputs!$B$26*(1+Inputs!$B$30)^(C$3-1)) -> 0 | D11: =IF(D$3=0,0,-Inputs!$B$26*(1+Inputs!$B$30)^(D$3-1)) -> -6000 | E11: =IF(E$3=0,0,-Inputs!$B$26*(1+Inputs!$B$30)^(E$3-1)) -> -6120 | F11: =IF(F$3=0,0,-Inputs!$B$26*(1+Inputs!$B$30)^(F$3-1)) -> -6242.4 | G11: =IF(G$3=0,0,-Inputs!$B$26*(1+Inputs!$B$30)^(G$3-1)) -> -6367.248 | H11: =IF(H$3=0,0,-Inputs!$B$26*(1+Inputs!$B$30)^(H$3-1)) -> -6494.593 | I11: =IF(I$3=0,0,-Inputs!$B$26*(1+Inputs!$B$30)^(I$3-1)) -> -6624.4848 | ... AG11: =IF(AG$3=0,0,-Inputs!$B$26*(1+Inputs!$B$30)^(AG$3-1)) -> -10655.068
A12: Property tax | B12: =IF(B$3=0,0,-Inputs!$B$27*(1+Inputs!$B$30)^(B$3-1)) -> 0 | C12: =IF(C$3=0,0,-Inputs!$B$27*(1+Inputs!$B$30)^(C$3-1)) -> 0 | D12: =IF(D$3=0,0,-Inputs!$B$27*(1+Inputs!$B$30)^(D$3-1)) -> -10000 | E12: =IF(E$3=0,0,-Inputs!$B$27*(1+Inputs!$B$30)^(E$3-1)) -> -10200 | F12: =IF(F$3=0,0,-Inputs!$B$27*(1+Inputs!$B$30)^(F$3-1)) -> -10404 | G12: =IF(G$3=0,0,-Inputs!$B$27*(1+Inputs!$B$30)^(G$3-1)) -> -10612.08 | H12: =IF(H$3=0,0,-Inputs!$B$27*(1+Inputs!$B$30)^(H$3-1)) -> -10824.322 | I12: =IF(I$3=0,0,-Inputs!$B$27*(1+Inputs!$B$30)^(I$3-1)) -> -11040.808 | ... AG12: =IF(AG$3=0,0,-Inputs!$B$27*(1+Inputs!$B$30)^(AG$3-1)) -> -17758.447
A13: Common utilities / cleaning | B13: =IF(B$3=0,0,-Inputs!$B$28*(1+Inputs!$B$30)^(B$3-1)) -> 0 | C13: =IF(C$3=0,0,-Inputs!$B$28*(1+Inputs!$B$30)^(C$3-1)) -> 0 | D13: =IF(D$3=0,0,-Inputs!$B$28*(1+Inputs!$B$30)^(D$3-1)) -> -18000 | E13: =IF(E$3=0,0,-Inputs!$B$28*(1+Inputs!$B$30)^(E$3-1)) -> -18360 | F13: =IF(F$3=0,0,-Inputs!$B$28*(1+Inputs!$B$30)^(F$3-1)) -> -18727.2 | G13: =IF(G$3=0,0,-Inputs!$B$28*(1+Inputs!$B$30)^(G$3-1)) -> -19101.744 | H13: =IF(H$3=0,0,-Inputs!$B$28*(1+Inputs!$B$30)^(H$3-1)) -> -19483.779 | I13: =IF(I$3=0,0,-Inputs!$B$28*(1+Inputs!$B$30)^(I$3-1)) -> -19873.454 | ... AG13: =IF(AG$3=0,0,-Inputs!$B$28*(1+Inputs!$B$30)^(AG$3-1)) -> -31965.204
A14: Administration / compliance | B14: =IF(B$3=0,0,-Inputs!$B$29*(1+Inputs!$B$30)^(B$3-1)) -> 0 | C14: =IF(C$3=0,0,-Inputs!$B$29*(1+Inputs!$B$30)^(C$3-1)) -> 0 | D14: =IF(D$3=0,0,-Inputs!$B$29*(1+Inputs!$B$30)^(D$3-1)) -> -4000 | E14: =IF(E$3=0,0,-Inputs!$B$29*(1+Inputs!$B$30)^(E$3-1)) -> -4080 | F14: =IF(F$3=0,0,-Inputs!$B$29*(1+Inputs!$B$30)^(F$3-1)) -> -4161.6 | G14: =IF(G$3=0,0,-Inputs!$B$29*(1+Inputs!$B$30)^(G$3-1)) -> -4244.832 | H14: =IF(H$3=0,0,-Inputs!$B$29*(1+Inputs!$B$30)^(H$3-1)) -> -4329.7286 | I14: =IF(I$3=0,0,-Inputs!$B$29*(1+Inputs!$B$30)^(I$3-1)) -> -4416.3232 | ... AG14: =IF(AG$3=0,0,-Inputs!$B$29*(1+Inputs!$B$30)^(AG$3-1)) -> -7103.3788
A15: Net operating income (NOI) | B15: =SUM(B8:B14) -> 0 | C15: =SUM(C8:C14) -> 0 | D15: =SUM(D8:D14) -> 266380 | E15: =SUM(E8:E14) -> 271707.6 | F15: =SUM(F8:F14) -> 277141.75 | G15: =SUM(G8:G14) -> 282684.59 | H15: =SUM(H8:H14) -> 288338.28 | I15: =SUM(I8:I14) -> 294105.04 | ... AG15: =SUM(AG8:AG14) -> 473049.51
A16: Recurring replacement reserve / cash expense | B16: =IF(B$3=0,0,-Development!$B$11*Inputs!$B$34*(1+Inputs!$B$30)^(B$3-1)) -> 0 | C16: =IF(C$3=0,0,-Development!$B$11*Inputs!$B$34*(1+Inputs!$B$30)^(C$3-1)) -> 0 | D16: =IF(D$3=0,0,-Development!$B$11*Inputs!$B$34*(1+Inputs!$B$30)^(D$3-1)) -> -25800 | E16: =IF(E$3=0,0,-Development!$B$11*Inputs!$B$34*(1+Inputs!$B$30)^(E$3-1)) -> -26316 | F16: =IF(F$3=0,0,-Development!$B$11*Inputs!$B$34*(1+Inputs!$B$30)^(F$3-1)) -> -26842.32 | G16: =IF(G$3=0,0,-Development!$B$11*Inputs!$B$34*(1+Inputs!$B$30)^(G$3-1)) -> -27379.166 | H16: =IF(H$3=0,0,-Development!$B$11*Inputs!$B$34*(1+Inputs!$B$30)^(H$3-1)) -> -27926.75 | I16: =IF(I$3=0,0,-Development!$B$11*Inputs!$B$34*(1+Inputs!$B$30)^(I$3-1)) -> -28485.285 | ... AG16: =IF(AG$3=0,0,-Development!$B$11*Inputs!$B$34*(1+Inputs!$B$30)^(AG$3-1)) -> -45816.793
A17: Furniture replacement | B17: =IF(AND(B$3>0,MOD(B$3,Inputs!$B$35)=0,B$2<31),-Inputs!$B$13*Inputs!$B$4*(1+Inputs!$B$18)*(1+Inputs!$B$30)^(B$3-1),0) -> 0 | C17: =IF(AND(C$3>0,MOD(C$3,Inputs!$B$35)=0,C$2<31),-Inputs!$B$13*Inputs!$B$4*(1+Inputs!$B$18)*(1+Inputs!$B$30)^(C$3-1),0) -> 0 | D17: =IF(AND(D$3>0,MOD(D$3,Inputs!$B$35)=0,D$2<31),-Inputs!$B$13*Inputs!$B$4*(1+Inputs!$B$18)*(1+Inputs!$B$30)^(D$3-1),0) -> 0 | E17: =IF(AND(E$3>0,MOD(E$3,Inputs!$B$35)=0,E$2<31),-Inputs!$B$13*Inputs!$B$4*(1+Inputs!$B$18)*(1+Inputs!$B$30)^(E$3-1),0) -> 0 | F17: =IF(AND(F$3>0,MOD(F$3,Inputs!$B$35)=0,F$2<31),-Inputs!$B$13*Inputs!$B$4*(1+Inputs!$B$18)*(1+Inputs!$B$30)^(F$3-1),0) -> 0 | G17: =IF(AND(G$3>0,MOD(G$3,Inputs!$B$35)=0,G$2<31),-Inputs!$B$13*Inputs!$B$4*(1+Inputs!$B$18)*(1+Inputs!$B$30)^(G$3-1),0) -> 0 | H17: =IF(AND(H$3>0,MOD(H$3,Inputs!$B$35)=0,H$2<31),-Inputs!$B$13*Inputs!$B$4*(1+Inputs!$B$18)*(1+Inputs!$B$30)^(H$3-1),0) -> 0 | I17: =IF(AND(I$3>0,MOD(I$3,Inputs!$B$35)=0,I$2<31),-Inputs!$B$13*Inputs!$B$4*(1+Inputs!$B$18)*(1+Inputs!$B$30)^(I$3-1),0) -> 0 | ... AG17: =IF(AND(AG$3>0,MOD(AG$3,Inputs!$B$35)=0,AG$2<31),-Inputs!$B$13*Inputs!$B$4*(1+Inputs!$B$18)*(1+Inputs!$B$30)^(AG$3-1),0) -> 0
A18: Operating free cash flow | B18: =SUM(B15:B17) -> 0 | C18: =SUM(C15:C17) -> 0 | D18: =SUM(D15:D17) -> 240580 | E18: =SUM(E15:E17) -> 245391.6 | F18: =SUM(F15:F17) -> 250299.43 | G18: =SUM(G15:G17) -> 255305.42 | H18: =SUM(H15:H17) -> 260411.53 | I18: =SUM(I15:I17) -> 265619.76 | ... AG18: =SUM(AG15:AG17) -> 427232.72
A20: Gross terminal sale (next-year NOI / cap rate) | B20: =0 -> 0 | C20: =0 -> 0 | D20: =0 -> 0 | E20: =0 -> 0 | F20: =0 -> 0 | G20: =0 -> 0 | H20: =0 -> 0 | I20: =0 -> 0 | ... AF20: =0 -> 0 | AG20: =(AG8*(1+Inputs!$B$23)*(1-Inputs!$B$24-Inputs!$B$25)+SUM(AG11:AG14)*(1+Inputs!$B$30))/Inputs!$B$32 -> 8772918.2
A21: Selling costs | B21: =-B20*Inputs!$B$33 -> 0 | C21: =-C20*Inputs!$B$33 -> 0 | D21: =-D20*Inputs!$B$33 -> 0 | E21: =-E20*Inputs!$B$33 -> 0 | F21: =-F20*Inputs!$B$33 -> 0 | G21: =-G20*Inputs!$B$33 -> 0 | H21: =-H20*Inputs!$B$33 -> 0 | I21: =-I20*Inputs!$B$33 -> 0 | ... AG21: =-AG20*Inputs!$B$33 -> -175458.36
A22: Net terminal sale | B22: =SUM(B20:B21) -> 0 | C22: =SUM(C20:C21) -> 0 | D22: =SUM(D20:D21) -> 0 | E22: =SUM(E20:E21) -> 0 | F22: =SUM(F20:F21) -> 0 | G22: =SUM(G20:G21) -> 0 | H22: =SUM(H20:H21) -> 0 | I22: =SUM(I20:I21) -> 0 | ... AG22: =SUM(AG20:AG21) -> 8597459.8
A24: TOTAL PROJECT CASH FLOW | B24: =SUM(B5:B6)+B18+B22 -> -2804296.7 | C24: =SUM(C5:C6)+C18+C22 -> -1884296.7 | D24: =SUM(D5:D6)+D18+D22 -> 240580 | E24: =SUM(E5:E6)+E18+E22 -> 245391.6 | F24: =SUM(F5:F6)+F18+F22 -> 250299.43 | G24: =SUM(G5:G6)+G18+G22 -> 255305.42 | H24: =SUM(H5:H6)+H18+H22 -> 260411.53 | I24: =SUM(I5:I6)+I18+I22 -> 265619.76 | ... AG24: =SUM(AG5:AG6)+AG18+AG22 -> 9024692.5
A25: Discount factor | B25: =1/(1+Inputs!$B$31)^B$2 -> 1 | C25: =1/(1+Inputs!$B$31)^C$2 -> 0.93896714 | D25: =1/(1+Inputs!$B$31)^D$2 -> 0.88165928 | E25: =1/(1+Inputs!$B$31)^E$2 -> 0.82784909 | F25: =1/(1+Inputs!$B$31)^F$2 -> 0.77732309 | G25: =1/(1+Inputs!$B$31)^G$2 -> 0.72988084 | H25: =1/(1+Inputs!$B$31)^H$2 -> 0.68533412 | I25: =1/(1+Inputs!$B$31)^I$2 -> 0.64350621 | ... AG25: =1/(1+Inputs!$B$31)^AG$2 -> 0.14195875
A26: Discounted project cash flow | B26: =B24*B25 -> -2804296.7 | C26: =C24*C25 -> -1769292.7 | D26: =D24*D25 -> 212109.59 | E26: =E24*E25 -> 203147.21 | F26: =F24*F25 -> 194563.53 | G26: =G24*G25 -> 186342.53 | H26: =H24*H25 -> 178468.91 | I26: =I24*I25 -> 170927.97 | ... AG26: =AG24*AG25 -> 1281134
A28: Cumulative cash flow including exit | B28: =SUM($B24:B24) -> -2804296.7 | C28: =SUM($B24:C24) -> -4688593.4 | D28: =SUM($B24:D24) -> -4448013.4 | E28: =SUM($B24:E24) -> -4202621.8 | F28: =SUM($B24:F24) -> -3952322.4 | G28: =SUM($B24:G24) -> -3697016.9 | H28: =SUM($B24:H24) -> -3436605.4 | I28: =SUM($B24:I24) -> -3170985.7 | ... AG28: =SUM($B24:AG24) -> 13347855
A29: Cumulative operating cash flow excluding exit | B29: =B28-SUM($B22:B22) -> -2804296.7 | C29: =C28-SUM($B22:C22) -> -4688593.4 | D29: =D28-SUM($B22:D22) -> -4448013.4 | E29: =E28-SUM($B22:E22) -> -4202621.8 | F29: =F28-SUM($B22:F22) -> -3952322.4 | G29: =G28-SUM($B22:G22) -> -3697016.9 | H29: =H28-SUM($B22:H22) -> -3436605.4 | I29: =I28-SUM($B22:I22) -> -3170985.7 | ... AG29: =AG28-SUM($B22:AG22) -> 4750394.7
A30: Cumulative discounted cash flow including exit | B30: =SUM($B26:B26) -> -2804296.7 | C30: =SUM($B26:C26) -> -4573589.4 | D30: =SUM($B26:D26) -> -4361479.8 | E30: =SUM($B26:E26) -> -4158332.6 | F30: =SUM($B26:F26) -> -3963769 | G30: =SUM($B26:G26) -> -3777426.5 | H30: =SUM($B26:H26) -> -3598957.6 | I30: =SUM($B26:I26) -> -3428029.6 | ... AG30: =SUM($B26:AG26) -> 172795.37
A31: Cumulative discounted cash flow excluding exit | B31: =B30-SUMPRODUCT($B22:B22,$B25:B25) -> -2804296.7 | C31: =C30-SUMPRODUCT($B22:C22,$B25:C25) -> -4573589.4 | D31: =D30-SUMPRODUCT($B22:D22,$B25:D25) -> -4361479.8 | E31: =E30-SUMPRODUCT($B22:E22,$B25:E25) -> -4158332.6 | F31: =F30-SUMPRODUCT($B22:F22,$B25:F25) -> -3963769 | G31: =G30-SUMPRODUCT($B22:G22,$B25:G25) -> -3777426.5 | H31: =H30-SUMPRODUCT($B22:H22,$B25:H25) -> -3598957.6 | I31: =I30-SUMPRODUCT($B22:I22,$B25:I25) -> -3428029.6 | ... AG31: =AG30-SUMPRODUCT($B22:AG22,$B25:AG25) -> -1047689.3
A33: Payback helper incl. exit | B33: =999 -> 999 | C33: =IF(AND(B28<0,C28>=0),B$2+(-B28)/(C28-B28),999) -> 999 | D33: =IF(AND(C28<0,D28>=0),C$2+(-C28)/(D28-C28),999) -> 999 | E33: =IF(AND(D28<0,E28>=0),D$2+(-D28)/(E28-D28),999) -> 999 | F33: =IF(AND(E28<0,F28>=0),E$2+(-E28)/(F28-E28),999) -> 999 | G33: =IF(AND(F28<0,G28>=0),F$2+(-F28)/(G28-F28),999) -> 999 | H33: =IF(AND(G28<0,H28>=0),G$2+(-G28)/(H28-G28),999) -> 999 | I33: =IF(AND(H28<0,I28>=0),H$2+(-H28)/(I28-H28),999) -> 999 | J33: =IF(AND(I28<0,J28>=0),I$2+(-I28)/(J28-I28),999) -> 999 | ... AG33: =IF(AND(AF28<0,AG28>=0),AF$2+(-AF28)/(AG28-AF28),999) -> 999
A34: Payback helper excl. exit | B34: =999 -> 999 | C34: =IF(AND(B29<0,C29>=0),B$2+(-B29)/(C29-B29),999) -> 999 | D34: =IF(AND(C29<0,D29>=0),C$2+(-C29)/(D29-C29),999) -> 999 | E34: =IF(AND(D29<0,E29>=0),D$2+(-D29)/(E29-D29),999) -> 999 | F34: =IF(AND(E29<0,F29>=0),E$2+(-E29)/(F29-E29),999) -> 999 | G34: =IF(AND(F29<0,G29>=0),F$2+(-F29)/(G29-F29),999) -> 999 | H34: =IF(AND(G29<0,H29>=0),G$2+(-G29)/(H29-G29),999) -> 999 | I34: =IF(AND(H29<0,I29>=0),H$2+(-H29)/(I29-H29),999) -> 999 | J34: =IF(AND(I29<0,J29>=0),I$2+(-I29)/(J29-I29),999) -> 999 | ... AG34: =IF(AND(AF29<0,AG29>=0),AF$2+(-AF29)/(AG29-AF29),999) -> 999
A35: Discounted helper incl. exit | B35: =999 -> 999 | C35: =IF(AND(B30<0,C30>=0),B$2+(-B30)/(C30-B30),999) -> 999 | D35: =IF(AND(C30<0,D30>=0),C$2+(-C30)/(D30-C30),999) -> 999 | E35: =IF(AND(D30<0,E30>=0),D$2+(-D30)/(E30-D30),999) -> 999 | F35: =IF(AND(E30<0,F30>=0),E$2+(-E30)/(F30-E30),999) -> 999 | G35: =IF(AND(F30<0,G30>=0),F$2+(-F30)/(G30-F30),999) -> 999 | H35: =IF(AND(G30<0,H30>=0),G$2+(-G30)/(H30-G30),999) -> 999 | I35: =IF(AND(H30<0,I30>=0),H$2+(-H30)/(I30-H30),999) -> 999 | J35: =IF(AND(I30<0,J30>=0),I$2+(-I30)/(J30-I30),999) -> 999 | ... AG35: =IF(AND(AF30<0,AG30>=0),AF$2+(-AF30)/(AG30-AF30),999) -> 30.865123
A36: Discounted helper excl. exit | B36: =999 -> 999 | C36: =IF(AND(B31<0,C31>=0),B$2+(-B31)/(C31-B31),999) -> 999 | D36: =IF(AND(C31<0,D31>=0),C$2+(-C31)/(D31-C31),999) -> 999 | E36: =IF(AND(D31<0,E31>=0),D$2+(-D31)/(E31-D31),999) -> 999 | F36: =IF(AND(E31<0,F31>=0),E$2+(-E31)/(F31-E31),999) -> 999 | G36: =IF(AND(F31<0,G31>=0),F$2+(-F31)/(G31-F31),999) -> 999 | H36: =IF(AND(G31<0,H31>=0),G$2+(-G31)/(H31-G31),999) -> 999 | I36: =IF(AND(H31<0,I31>=0),H$2+(-H31)/(I31-H31),999) -> 999 | J36: =IF(AND(I31<0,J31>=0),I$2+(-I31)/(J31-I31),999) -> 999 | ... AG36: =IF(AND(AF31<0,AG31>=0),AF$2+(-AF31)/(AG31-AF31),999) -> 999

Sheet Read me
A1: HOW TO USE / LIMITATIONS | B1: Details
A2: Purpose | B2: Feasibility model for construction of student housing on an empty plot in Brussels. Prepared for Anne-Laure, Robbe d. and an unidentified team member.
A3: Edit | B3: Blue text on Inputs = editable. Black text = formulas. Currency EUR. Annual cash flows are year-end except t0. Excel recalculates on opening.
A4: Immediate base version | B4: Financial model saved before external research; official sources added afterwards. Costs/rent remain illustrative. Research date: 14 October 2026.
A5: Location | B5: University/transit proximity is a search criterion. No address, plot size, municipality, zoning or acquisition agreement supplied; no plot feasibility is established.
A6: Return definition | B6: Project IRR and NPV are unlevered and before income/capital gains tax. Debt, financing costs, grants and equity returns excluded.
A7: Timing | B7: One full construction year after t0, completion at t1, first operating-year cash received at t2. 30 operating years; fixed horizon.
A8: Cash costs | B8: Land duty assumed, construction VAT assumed non-recoverable; VAT on land sale is not modeled. Seller/site tax regime could materially alter cost.
A9: Rent | B9: 12 monthly rents at occupied fraction. Rent excludes tenant-paid private utilities; shared utility costs retained by owner. 10-month leases require annual rent adjustment.
A10: Reserves | B10: Maintenance margin plus recurring replacement cash expense. Furniture replacements separate every 10 operating years, excluding sale year. Avoid duplication when refining budgets.
A11: Terminal value | B11: Capitalized following-year NOI, before major replacement reserves, less sale costs. No appreciation assumption added separately.
A12: Payback | B12: Simple and discounted payback reported both with and without sale. Sale-dependent recovery shown at year 31. Not reached means not recovered within this horizon.
... A15: Sources | B15: Research notes will be added incrementally after the base workbook has been saved.

Sheet Legal & sources
A1: Topic | B1: Requirement / research note | C1: Official source / reference | D1: Status / date
A2: Land transfer duty | B2: Ordinary Brussels registration duty is 12.5%. Model applies it to assumed land price; ask notary to confirm market-value tax base and VAT interaction. No homebuyer abatement assumed. | C2: https://be.brussels/en/taxes-finances/taxes/property-related-taxes/registration-duties/abatement | D2: Verified ordinary rate; project treatment pending | checked 2026-10-14
A3: Construction VAT | B3: Federal guidance states 21% VAT for new construction. Model assumes all budgeted construction/professional VAT is non-recoverable; confirm project-specific exemptions or reduced rates. | C3: https://finances.belgium.be/fr/particuliers/habitation/construire-renover/renover/renover-taux-de-tva | D3: Verified standard rate; tax advice pending | checked 2026-10-14
A4: Planning / zoning | B4: Regional planning rules govern buildings and housing habitability; municipality and urban.brussels must confirm use, plot constraints, room layout, height and permit requirements. | C4: https://be.brussels/fr/developpement-urbain/urbanisme | D4: Site unknown; permit feasibility not assessed | checked 2026-10-14
A5: Permit application | B5: MyPermit is the official platform for regional and municipal planning applications. Obtain architect and authority advice before acquisition. | C5: https://mypermit.urban.brussels/ | D5: Official application route | checked 2026-10-14
A6: Housing quality / fire | B6: Official housing page references housing safety, health and equipment requirements applicable from 1 January 2026, and smoke-detection rules from 1 January 2025. Design compliance and SIAMU advice must be priced by architect. | C6: https://be.brussels/fr/logement/location/conformite-logement/normes-et-securite | D6: Current official standards page; design review pending | checked 2026-10-14
A7: Student lease term | B7: Regional rental guidance describes the student lease as 12 months. Model assumes a fully contracted year, adjusted for 95% collected occupancy. Account for termination and non-collection when refining occupancy. | C7: https://be.brussels/fr/logement/location/les-differentes-etapes-de-la-location | D7: Official rental guidance | checked 2026-10-14
A8: Lease / rent indexation | B8: Regional lease guidance covers rent, indexation and repair obligations. Fixed 2% rent growth is a financial assumption, not an automatic legal entitlement. | C8: https://be.brussels/fr/logement/location/bail-dhabitation | D8: Lease-specific applicability pending | checked 2026-10-14
A9: Student housing label | B9: Regional label requires housing-code compliance, an appropriate student lease and a valid energy certificate; label lasts five years and is renewable. The label does not establish a universal affordable-room quota. | C9: https://be.brussels/fr/logement/location/conformite-logement/label-logement-etudiant | D9: Optional label to assess | checked 2026-10-14
A10: Affordable threshold / planning charges | B10: User wording is unclear. No region-wide quota has been established by this research. Request the actual municipal policy, permit conditions and subsidy terms. Enter share, discount and additional capital cost on Inputs; zero is a modeling placeholder. | C10: https://be.brussels/fr/developpement-urbain/urbanisme | D10: UNRESOLVED — confirm exact plot and scheme | checked 2026-10-14
A11: Location / market evidence | B11: University and transit proximity remains a screening criterion. Brik provides student housing information; obtain comparable available-room rents for exact area and amenities before using EUR 750 as underwriting evidence. | C11: https://www.brik.be/en | D11: Rent, land and construction prices are illustrative | checked 2026-10-14
A12: Insurance | B12: EUR 6,000 annual owner building insurance is an allowance; request quotes covering fire, water damage, liability and loss of rent. Verify tenant insurance obligations separately. | D12: No insurer quote; allowance only | checked 2026-10-14
A13: Architect / construction / maintenance | B13: All cost rates and reserve margins are analyst planning assumptions, not official tariffs or quotations. Verify area take-off and bids; MEP, fixtures, kitchens and furniture are itemized separately. | D13: Quote required | checked 2026-10-14

Sheet Sensitivity
A1: NPV SENSITIVITY | EUR | B1: Exit cap rate →
A2: Monthly market rent ↓ | B2: =Inputs!$B$32*0.8 -> 0.044 | C2: =Inputs!$B$32*0.9 -> 0.0495 | D2: =Inputs!$B$32*1 -> 0.055 | E2: =Inputs!$B$32*1.1 -> 0.0605 | F2: =Inputs!$B$32*1.2 -> 0.066
A3: =Inputs!$B$20*0.8 -> 600 | B3: =Summary!$B$4+($A3/Inputs!$B$20-1)*(1-Inputs!$B$24-Inputs!$B$25)*SUMPRODUCT('Cash flows'!$D$8:$AG$8,'Cash flows'!$D$25:$AG$25)+(('Cash flows'!$AG$20*Inputs!$B$32/B$2+($A3/Inputs!$B$20-1)*'Cash flows'!$AG$8*(1+Inputs!$B$23)*(1-Inputs!$B$24-Inputs!$B$25)/B$2)*(1-Inputs!$B$33)-'Cash flows'!$AG$22)*'Cash flows'!$AG$25 -> -793108.8 | C3: =Summary!$B$4+($A3/Inputs!$B$20-1)*(1-Inputs!$B$24-Inputs!$B$25)*SUMPRODUCT('Cash flows'!$D$8:$AG$8,'Cash flows'!$D$25:$AG$25)+(('Cash flows'!$AG$20*Inputs!$B$32/C$2+($A3/Inputs!$B$20-1)*'Cash flows'!$AG$8*(1+Inputs!$B$23)*(1-Inputs!$B$24-Inputs!$B$25)/C$2)*(1-Inputs!$B$33)-'Cash flows'!$AG$22)*'Cash flows'!$AG$25 -> -923881.92 | D3: =Summary!$B$4+($A3/Inputs!$B$20-1)*(1-Inputs!$B$24-Inputs!$B$25)*SUMPRODUCT('Cash flows'!$D$8:$AG$8,'Cash flows'!$D$25:$AG$25)+(('Cash flows'!$AG$20*Inputs!$B$32/D$2+($A3/Inputs!$B$20-1)*'Cash flows'!$AG$8*(1+Inputs!$B$23)*(1-Inputs!$B$24-Inputs!$B$25)/D$2)*(1-Inputs!$B$33)-'Cash flows'!$AG$22)*'Cash flows'!$AG$25 -> -1028500.4 | E3: =Summary!$B$4+($A3/Inputs!$B$20-1)*(1-Inputs!$B$24-Inputs!$B$25)*SUMPRODUCT('Cash flows'!$D$8:$AG$8,'Cash flows'!$D$25:$AG$25)+(('Cash flows'!$AG$20*Inputs!$B$32/E$2+($A3/Inputs!$B$20-1)*'Cash flows'!$AG$8*(1+Inputs!$B$23)*(1-Inputs!$B$24-Inputs!$B$25)/E$2)*(1-Inputs!$B$33)-'Cash flows'!$AG$22)*'Cash flows'!$AG$25 -> -1114097.4 | F3: =Summary!$B$4+($A3/Inputs!$B$20-1)*(1-Inputs!$B$24-Inputs!$B$25)*SUMPRODUCT('Cash flows'!$D$8:$AG$8,'Cash flows'!$D$25:$AG$25)+(('Cash flows'!$AG$20*Inputs!$B$32/F$2+($A3/Inputs!$B$20-1)*'Cash flows'!$AG$8*(1+Inputs!$B$23)*(1-Inputs!$B$24-Inputs!$B$25)/F$2)*(1-Inputs!$B$33)-'Cash flows'!$AG$22)*'Cash flows'!$AG$25 -> -1185428.2
A4: =Inputs!$B$20*0.9 -> 675 | B4: =Summary!$B$4+($A4/Inputs!$B$20-1)*(1-Inputs!$B$24-Inputs!$B$25)*SUMPRODUCT('Cash flows'!$D$8:$AG$8,'Cash flows'!$D$25:$AG$25)+(('Cash flows'!$AG$20*Inputs!$B$32/B$2+($A4/Inputs!$B$20-1)*'Cash flows'!$AG$8*(1+Inputs!$B$23)*(1-Inputs!$B$24-Inputs!$B$25)/B$2)*(1-Inputs!$B$33)-'Cash flows'!$AG$22)*'Cash flows'!$AG$25 -> -157596.14 | C4: =Summary!$B$4+($A4/Inputs!$B$20-1)*(1-Inputs!$B$24-Inputs!$B$25)*SUMPRODUCT('Cash flows'!$D$8:$AG$8,'Cash flows'!$D$25:$AG$25)+(('Cash flows'!$AG$20*Inputs!$B$32/C$2+($A4/Inputs!$B$20-1)*'Cash flows'!$AG$8*(1+Inputs!$B$23)*(1-Inputs!$B$24-Inputs!$B$25)/C$2)*(1-Inputs!$B$33)-'Cash flows'!$AG$22)*'Cash flows'!$AG$25 -> -307738.58 | D4: =Summary!$B$4+($A4/Inputs!$B$20-1)*(1-Inputs!$B$24-Inputs!$B$25)*SUMPRODUCT('Cash flows'!$D$8:$AG$8,'Cash flows'!$D$25:$AG$25)+(('Cash flows'!$AG$20*Inputs!$B$32/D$2+($A4/Inputs!$B$20-1)*'Cash flows'!$AG$8*(1+Inputs!$B$23)*(1-Inputs!$B$24-Inputs!$B$25)/D$2)*(1-Inputs!$B$33)-'Cash flows'!$AG$22)*'Cash flows'!$AG$25 -> -427852.53 | E4: =Summary!$B$4+($A4/Inputs!$B$20-1)*(1-Inputs!$B$24-Inputs!$B$25)*SUMPRODUCT('Cash flows'!$D$8:$AG$8,'Cash flows'!$D$25:$AG$25)+(('Cash flows'!$AG$20*Inputs!$B$32/E$2+($A4/Inputs!$B$20-1)*'Cash flows'!$AG$8*(1+Inputs!$B$23)*(1-Inputs!$B$24-Inputs!$B$25)/E$2)*(1-Inputs!$B$33)-'Cash flows'!$AG$22)*'Cash flows'!$AG$25 -> -526127.57 | F4: =Summary!$B$4+($A4/Inputs!$B$20-1)*(1-Inputs!$B$24-Inputs!$B$25)*SUMPRODUCT('Cash flows'!$D$8:$AG$8,'Cash flows'!$D$25:$AG$25)+(('Cash flows'!$AG$20*Inputs!$B$32/F$2+($A4/Inputs!$B$20-1)*'Cash flows'!$AG$8*(1+Inputs!$B$23)*(1-Inputs!$B$24-Inputs!$B$25)/F$2)*(1-Inputs!$B$33)-'Cash flows'!$AG$22)*'Cash flows'!$AG$25 -> -608023.45
A5: =Inputs!$B$20*1 -> 750 | B5: =Summary!$B$4+($A5/Inputs!$B$20-1)*(1-Inputs!$B$24-Inputs!$B$25)*SUMPRODUCT('Cash flows'!$D$8:$AG$8,'Cash flows'!$D$25:$AG$25)+(('Cash flows'!$AG$20*Inputs!$B$32/B$2+($A5/Inputs!$B$20-1)*'Cash flows'!$AG$8*(1+Inputs!$B$23)*(1-Inputs!$B$24-Inputs!$B$25)/B$2)*(1-Inputs!$B$33)-'Cash flows'!$AG$22)*'Cash flows'!$AG$25 -> 477916.52 | C5: =Summary!$B$4+($A5/Inputs!$B$20-1)*(1-Inputs!$B$24-Inputs!$B$25)*SUMPRODUCT('Cash flows'!$D$8:$AG$8,'Cash flows'!$D$25:$AG$25)+(('Cash flows'!$AG$20*Inputs!$B$32/C$2+($A5/Inputs!$B$20-1)*'Cash flows'!$AG$8*(1+Inputs!$B$23)*(1-Inputs!$B$24-Inputs!$B$25)/C$2)*(1-Inputs!$B$33)-'Cash flows'!$AG$22)*'Cash flows'!$AG$25 -> 308404.77 | D5: =Summary!$B$4+($A5/Inputs!$B$20-1)*(1-Inputs!$B$24-Inputs!$B$25)*SUMPRODUCT('Cash flows'!$D$8:$AG$8,'Cash flows'!$D$25:$AG$25)+(('Cash flows'!$AG$20*Inputs!$B$32/D$2+($A5/Inputs!$B$20-1)*'Cash flows'!$AG$8*(1+Inputs!$B$23)*(1-Inputs!$B$24-Inputs!$B$25)/D$2)*(1-Inputs!$B$33)-'Cash flows'!$AG$22)*'Cash flows'!$AG$25 -> 172795.37 | E5: =Summary!$B$4+($A5/Inputs!$B$20-1)*(1-Inputs!$B$24-Inputs!$B$25)*SUMPRODUCT('Cash flows'!$D$8:$AG$8,'Cash flows'!$D$25:$AG$25)+(('Cash flows'!$AG$20*Inputs!$B$32/E$2+($A5/Inputs!$B$20-1)*'Cash flows'!$AG$8*(1+Inputs!$B$23)*(1-Inputs!$B$24-Inputs!$B$25)/E$2)*(1-Inputs!$B$33)-'Cash flows'!$AG$22)*'Cash flows'!$AG$25 -> 61842.219 | F5: =Summary!$B$4+($A5/Inputs!$B$20-1)*(1-Inputs!$B$24-Inputs!$B$25)*SUMPRODUCT('Cash flows'!$D$8:$AG$8,'Cash flows'!$D$25:$AG$25)+(('Cash flows'!$AG$20*Inputs!$B$32/F$2+($A5/Inputs!$B$20-1)*'Cash flows'!$AG$8*(1+Inputs!$B$23)*(1-Inputs!$B$24-Inputs!$B$25)/F$2)*(1-Inputs!$B$33)-'Cash flows'!$AG$22)*'Cash flows'!$AG$25 -> -30618.738
A6: =Inputs!$B$20*1.1 -> 825 | B6: =Summary!$B$4+($A6/Inputs!$B$20-1)*(1-Inputs!$B$24-Inputs!$B$25)*SUMPRODUCT('Cash flows'!$D$8:$AG$8,'Cash flows'!$D$25:$AG$25)+(('Cash flows'!$AG$20*Inputs!$B$32/B$2+($A6/Inputs!$B$20-1)*'Cash flows'!$AG$8*(1+Inputs!$B$23)*(1-Inputs!$B$24-Inputs!$B$25)/B$2)*(1-Inputs!$B$33)-'Cash flows'!$AG$22)*'Cash flows'!$AG$25 -> 1113429.2 | C6: =Summary!$B$4+($A6/Inputs!$B$20-1)*(1-Inputs!$B$24-Inputs!$B$25)*SUMPRODUCT('Cash flows'!$D$8:$AG$8,'Cash flows'!$D$25:$AG$25)+(('Cash flows'!$AG$20*Inputs!$B$32/C$2+($A6/Inputs!$B$20-1)*'Cash flows'!$AG$8*(1+Inputs!$B$23)*(1-Inputs!$B$24-Inputs!$B$25)/C$2)*(1-Inputs!$B$33)-'Cash flows'!$AG$22)*'Cash flows'!$AG$25 -> 924548.11 | D6: =Summary!$B$4+($A6/Inputs!$B$20-1)*(1-Inputs!$B$24-Inputs!$B$25)*SUMPRODUCT('Cash flows'!$D$8:$AG$8,'Cash flows'!$D$25:$AG$25)+(('Cash flows'!$AG$20*Inputs!$B$32/D$2+($A6/Inputs!$B$20-1)*'Cash flows'!$AG$8*(1+Inputs!$B$23)*(1-Inputs!$B$24-Inputs!$B$25)/D$2)*(1-Inputs!$B$33)-'Cash flows'!$AG$22)*'Cash flows'!$AG$25 -> 773443.26 | E6: =Summary!$B$4+($A6/Inputs!$B$20-1)*(1-Inputs!$B$24-Inputs!$B$25)*SUMPRODUCT('Cash flows'!$D$8:$AG$8,'Cash flows'!$D$25:$AG$25)+(('Cash flows'!$AG$20*Inputs!$B$32/E$2+($A6/Inputs!$B$20-1)*'Cash flows'!$AG$8*(1+Inputs!$B$23)*(1-Inputs!$B$24-Inputs!$B$25)/E$2)*(1-Inputs!$B$33)-'Cash flows'!$AG$22)*'Cash flows'!$AG$25 -> 649812.01 | F6: =Summary!$B$4+($A6/Inputs!$B$20-1)*(1-Inputs!$B$24-Inputs!$B$25)*SUMPRODUCT('Cash flows'!$D$8:$AG$8,'Cash flows'!$D$25:$AG$25)+(('Cash flows'!$AG$20*Inputs!$B$32/F$2+($A6/Inputs!$B$20-1)*'Cash flows'!$AG$8*(1+Inputs!$B$23)*(1-Inputs!$B$24-Inputs!$B$25)/F$2)*(1-Inputs!$B$33)-'Cash flows'!$AG$22)*'Cash flows'!$AG$25 -> 546785.97
A7: =Inputs!$B$20*1.2 -> 900 | B7: =Summary!$B$4+($A7/Inputs!$B$20-1)*(1-Inputs!$B$24-Inputs!$B$25)*SUMPRODUCT('Cash flows'!$D$8:$AG$8,'Cash flows'!$D$25:$AG$25)+(('Cash flows'!$AG$20*Inputs!$B$32/B$2+($A7/Inputs!$B$20-1)*'Cash flows'!$AG$8*(1+Inputs!$B$23)*(1-Inputs!$B$24-Inputs!$B$25)/B$2)*(1-Inputs!$B$33)-'Cash flows'!$AG$22)*'Cash flows'!$AG$25 -> 1748941.8 | C7: =Summary!$B$4+($A7/Inputs!$B$20-1)*(1-Inputs!$B$24-Inputs!$B$25)*SUMPRODUCT('Cash flows'!$D$8:$AG$8,'Cash flows'!$D$25:$AG$25)+(('Cash flows'!$AG$20*Inputs!$B$32/C$2+($A7/Inputs!$B$20-1)*'Cash flows'!$AG$8*(1+Inputs!$B$23)*(1-Inputs!$B$24-Inputs!$B$25)/C$2)*(1-Inputs!$B$33)-'Cash flows'!$AG$22)*'Cash flows'!$AG$25 -> 1540691.5 | D7: =Summary!$B$4+($A7/Inputs!$B$20-1)*(1-Inputs!$B$24-Inputs!$B$25)*SUMPRODUCT('Cash flows'!$D$8:$AG$8,'Cash flows'!$D$25:$AG$25)+(('Cash flows'!$AG$20*Inputs!$B$32/D$2+($A7/Inputs!$B$20-1)*'Cash flows'!$AG$8*(1+Inputs!$B$23)*(1-Inputs!$B$24-Inputs!$B$25)/D$2)*(1-Inputs!$B$33)-'Cash flows'!$AG$22)*'Cash flows'!$AG$25 -> 1374091.2 | E7: =Summary!$B$4+($A7/Inputs!$B$20-1)*(1-Inputs!$B$24-Inputs!$B$25)*SUMPRODUCT('Cash flows'!$D$8:$AG$8,'Cash flows'!$D$25:$AG$25)+(('Cash flows'!$AG$20*Inputs!$B$32/E$2+($A7/Inputs!$B$20-1)*'Cash flows'!$AG$8*(1+Inputs!$B$23)*(1-Inputs!$B$24-Inputs!$B$25)/E$2)*(1-Inputs!$B$33)-'Cash flows'!$AG$22)*'Cash flows'!$AG$25 -> 1237781.8 | F7: =Summary!$B$4+($A7/Inputs!$B$20-1)*(1-Inputs!$B$24-Inputs!$B$25)*SUMPRODUCT('Cash flows'!$D$8:$AG$8,'Cash flows'!$D$25:$AG$25)+(('Cash flows'!$AG$20*Inputs!$B$32/F$2+($A7/Inputs!$B$20-1)*'Cash flows'!$AG$8*(1+Inputs!$B$23)*(1-Inputs!$B$24-Inputs!$B$25)/F$2)*(1-Inputs!$B$33)-'Cash flows'!$AG$22)*'Cash flows'!$AG$25 -> 1124190.7
A9: Method | B9: Rent and exit cap vary; all other inputs fixed. Affordable discount and occupancy remain at Inputs values.
