Workbook

Sheet Report
A1: BRUSSELS | STUDENT HOUSING
A2: Investment committee report • capital allocation • model date 14 October 2026
A4: Use / evidence status | B4: =IF(Assumptions!B5="YES","DEMONSTRATION — hypothetical opportunities","LIVE INPUTS — evidence required") -> DEMONSTRATION — hypothetical opportunities
A5: Mandate | B5: Maximize 10-year discounted unlevered profit within budget; legal readiness is mandatory.
A6: Optimal portfolio NPV | B6: =MAX(Portfolio!N5:N260) -> 188913.04
A7: Winning subset position | B7: =MATCH(B6,Portfolio!N5:N260,0) -> 12
A8: Committed capital | B8: =INDEX(Portfolio!J5:J260,B7) -> 1786750
A9: Remaining capital | B9: =Assumptions!B6-B8 -> 213250
A10: Projects selected | B10: =INDEX(Portfolio!K5:K260,B7) -> 3
A11: Recommendation | B11: =IF(B10=0,"No eligible positive-NPV portfolio — retain capital",IF(Assumptions!B5="YES","Illustration only; obtain actual opportunities and evidence before investment","Selected projects require final due diligence and transaction approval")) -> Illustration only; obtain actual opportunities and evidence before investment
A14: Order | B14: Project | C14: NPV | D14: IRR | E14: All-in capital | F14: Ready (months) | G14: Downside NPV | H14: Compliance | I14: Selection
A15: =IF(1<=COUNTIF(Opportunities!$S$8:$S$15,"ELIGIBLE"),1,"") -> 1 | B15: =IF($A15="","",INDEX(Opportunities!$B$8:$B$15,MATCH($A15,Opportunities!$T$8:$T$15,0))) -> Illustrative conversion A | C15: =IF($A15="","",INDEX(Opportunities!$P$8:$P$15,MATCH($A15,Opportunities!$T$8:$T$15,0))) -> 90896.517 | D15: =IF($A15="","",INDEX(Opportunities!$Q$8:$Q$15,MATCH($A15,Opportunities!$T$8:$T$15,0))) -> 0.10331943 | E15: =IF($A15="","",INDEX(Opportunities!$L$8:$L$15,MATCH($A15,Opportunities!$T$8:$T$15,0))) -> 869500 | F15: =IF($A15="","",INDEX(Opportunities!$H$8:$H$15,MATCH($A15,Opportunities!$T$8:$T$15,0))) -> 12 | G15: =IF($A15="","",INDEX(Opportunities!$R$8:$R$15,MATCH($A15,Opportunities!$T$8:$T$15,0))) -> -103155.23 | H15: =IF($A15="","",INDEX(Opportunities!$M$8:$M$15,MATCH($A15,Opportunities!$T$8:$T$15,0))) -> DEMO PASS | I15: =IF($A15="","",IF(INDEX(Opportunities!$U$8:$U$15,MATCH($A15,Opportunities!$T$8:$T$15,0))=1,"SELECTED","WATCHLIST")) -> SELECTED
A16: =IF(2<=COUNTIF(Opportunities!$S$8:$S$15,"ELIGIBLE"),2,"") -> 2 | B16: =IF($A16="","",INDEX(Opportunities!$B$8:$B$15,MATCH($A16,Opportunities!$T$8:$T$15,0))) -> Illustrative renovation B | C16: =IF($A16="","",INDEX(Opportunities!$P$8:$P$15,MATCH($A16,Opportunities!$T$8:$T$15,0))) -> 76128.402 | D16: =IF($A16="","",INDEX(Opportunities!$Q$8:$Q$15,MATCH($A16,Opportunities!$T$8:$T$15,0))) -> 0.10690125 | E16: =IF($A16="","",INDEX(Opportunities!$L$8:$L$15,MATCH($A16,Opportunities!$T$8:$T$15,0))) -> 585000 | F16: =IF($A16="","",INDEX(Opportunities!$H$8:$H$15,MATCH($A16,Opportunities!$T$8:$T$15,0))) -> 6 | G16: =IF($A16="","",INDEX(Opportunities!$R$8:$R$15,MATCH($A16,Opportunities!$T$8:$T$15,0))) -> -55582.705 | H16: =IF($A16="","",INDEX(Opportunities!$M$8:$M$15,MATCH($A16,Opportunities!$T$8:$T$15,0))) -> DEMO PASS | I16: =IF($A16="","",IF(INDEX(Opportunities!$U$8:$U$15,MATCH($A16,Opportunities!$T$8:$T$15,0))=1,"SELECTED","WATCHLIST")) -> SELECTED
A17: =IF(3<=COUNTIF(Opportunities!$S$8:$S$15,"ELIGIBLE"),3,"") -> 3 | B17: =IF($A17="","",INDEX(Opportunities!$B$8:$B$15,MATCH($A17,Opportunities!$T$8:$T$15,0))) -> Illustrative new build C | C17: =IF($A17="","",INDEX(Opportunities!$P$8:$P$15,MATCH($A17,Opportunities!$T$8:$T$15,0))) -> 54783.715 | D17: =IF($A17="","",INDEX(Opportunities!$Q$8:$Q$15,MATCH($A17,Opportunities!$T$8:$T$15,0))) -> 0.094246244 | E17: =IF($A17="","",INDEX(Opportunities!$L$8:$L$15,MATCH($A17,Opportunities!$T$8:$T$15,0))) -> 1581000 | F17: =IF($A17="","",INDEX(Opportunities!$H$8:$H$15,MATCH($A17,Opportunities!$T$8:$T$15,0))) -> 30 | G17: =IF($A17="","",INDEX(Opportunities!$R$8:$R$15,MATCH($A17,Opportunities!$T$8:$T$15,0))) -> -325708.62 | H17: =IF($A17="","",INDEX(Opportunities!$M$8:$M$15,MATCH($A17,Opportunities!$T$8:$T$15,0))) -> DEMO PASS | I17: =IF($A17="","",IF(INDEX(Opportunities!$U$8:$U$15,MATCH($A17,Opportunities!$T$8:$T$15,0))=1,"SELECTED","WATCHLIST")) -> WATCHLIST
A18: =IF(4<=COUNTIF(Opportunities!$S$8:$S$15,"ELIGIBLE"),4,"") -> 4 | B18: =IF($A18="","",INDEX(Opportunities!$B$8:$B$15,MATCH($A18,Opportunities!$T$8:$T$15,0))) -> Illustrative small asset D | C18: =IF($A18="","",INDEX(Opportunities!$P$8:$P$15,MATCH($A18,Opportunities!$T$8:$T$15,0))) -> 21888.123 | D18: =IF($A18="","",INDEX(Opportunities!$Q$8:$Q$15,MATCH($A18,Opportunities!$T$8:$T$15,0))) -> 0.09882353 | E18: =IF($A18="","",INDEX(Opportunities!$L$8:$L$15,MATCH($A18,Opportunities!$T$8:$T$15,0))) -> 332250 | F18: =IF($A18="","",INDEX(Opportunities!$H$8:$H$15,MATCH($A18,Opportunities!$T$8:$T$15,0))) -> 4 | G18: =IF($A18="","",INDEX(Opportunities!$R$8:$R$15,MATCH($A18,Opportunities!$T$8:$T$15,0))) -> -50757.491 | H18: =IF($A18="","",INDEX(Opportunities!$M$8:$M$15,MATCH($A18,Opportunities!$T$8:$T$15,0))) -> DEMO PASS | I18: =IF($A18="","",IF(INDEX(Opportunities!$U$8:$U$15,MATCH($A18,Opportunities!$T$8:$T$15,0))=1,"SELECTED","WATCHLIST")) -> SELECTED
A19: =IF(5<=COUNTIF(Opportunities!$S$8:$S$15,"ELIGIBLE"),5,"") | B19: =IF($A19="","",INDEX(Opportunities!$B$8:$B$15,MATCH($A19,Opportunities!$T$8:$T$15,0))) | C19: =IF($A19="","",INDEX(Opportunities!$P$8:$P$15,MATCH($A19,Opportunities!$T$8:$T$15,0))) | D19: =IF($A19="","",INDEX(Opportunities!$Q$8:$Q$15,MATCH($A19,Opportunities!$T$8:$T$15,0))) | E19: =IF($A19="","",INDEX(Opportunities!$L$8:$L$15,MATCH($A19,Opportunities!$T$8:$T$15,0))) | F19: =IF($A19="","",INDEX(Opportunities!$H$8:$H$15,MATCH($A19,Opportunities!$T$8:$T$15,0))) | G19: =IF($A19="","",INDEX(Opportunities!$R$8:$R$15,MATCH($A19,Opportunities!$T$8:$T$15,0))) | H19: =IF($A19="","",INDEX(Opportunities!$M$8:$M$15,MATCH($A19,Opportunities!$T$8:$T$15,0))) | I19: =IF($A19="","",IF(INDEX(Opportunities!$U$8:$U$15,MATCH($A19,Opportunities!$T$8:$T$15,0))=1,"SELECTED","WATCHLIST"))
A20: =IF(6<=COUNTIF(Opportunities!$S$8:$S$15,"ELIGIBLE"),6,"") | B20: =IF($A20="","",INDEX(Opportunities!$B$8:$B$15,MATCH($A20,Opportunities!$T$8:$T$15,0))) | C20: =IF($A20="","",INDEX(Opportunities!$P$8:$P$15,MATCH($A20,Opportunities!$T$8:$T$15,0))) | D20: =IF($A20="","",INDEX(Opportunities!$Q$8:$Q$15,MATCH($A20,Opportunities!$T$8:$T$15,0))) | E20: =IF($A20="","",INDEX(Opportunities!$L$8:$L$15,MATCH($A20,Opportunities!$T$8:$T$15,0))) | F20: =IF($A20="","",INDEX(Opportunities!$H$8:$H$15,MATCH($A20,Opportunities!$T$8:$T$15,0))) | G20: =IF($A20="","",INDEX(Opportunities!$R$8:$R$15,MATCH($A20,Opportunities!$T$8:$T$15,0))) | H20: =IF($A20="","",INDEX(Opportunities!$M$8:$M$15,MATCH($A20,Opportunities!$T$8:$T$15,0))) | I20: =IF($A20="","",IF(INDEX(Opportunities!$U$8:$U$15,MATCH($A20,Opportunities!$T$8:$T$15,0))=1,"SELECTED","WATCHLIST"))
A21: =IF(7<=COUNTIF(Opportunities!$S$8:$S$15,"ELIGIBLE"),7,"") | B21: =IF($A21="","",INDEX(Opportunities!$B$8:$B$15,MATCH($A21,Opportunities!$T$8:$T$15,0))) | C21: =IF($A21="","",INDEX(Opportunities!$P$8:$P$15,MATCH($A21,Opportunities!$T$8:$T$15,0))) | D21: =IF($A21="","",INDEX(Opportunities!$Q$8:$Q$15,MATCH($A21,Opportunities!$T$8:$T$15,0))) | E21: =IF($A21="","",INDEX(Opportunities!$L$8:$L$15,MATCH($A21,Opportunities!$T$8:$T$15,0))) | F21: =IF($A21="","",INDEX(Opportunities!$H$8:$H$15,MATCH($A21,Opportunities!$T$8:$T$15,0))) | G21: =IF($A21="","",INDEX(Opportunities!$R$8:$R$15,MATCH($A21,Opportunities!$T$8:$T$15,0))) | H21: =IF($A21="","",INDEX(Opportunities!$M$8:$M$15,MATCH($A21,Opportunities!$T$8:$T$15,0))) | I21: =IF($A21="","",IF(INDEX(Opportunities!$U$8:$U$15,MATCH($A21,Opportunities!$T$8:$T$15,0))=1,"SELECTED","WATCHLIST"))
A22: =IF(8<=COUNTIF(Opportunities!$S$8:$S$15,"ELIGIBLE"),8,"") | B22: =IF($A22="","",INDEX(Opportunities!$B$8:$B$15,MATCH($A22,Opportunities!$T$8:$T$15,0))) | C22: =IF($A22="","",INDEX(Opportunities!$P$8:$P$15,MATCH($A22,Opportunities!$T$8:$T$15,0))) | D22: =IF($A22="","",INDEX(Opportunities!$Q$8:$Q$15,MATCH($A22,Opportunities!$T$8:$T$15,0))) | E22: =IF($A22="","",INDEX(Opportunities!$L$8:$L$15,MATCH($A22,Opportunities!$T$8:$T$15,0))) | F22: =IF($A22="","",INDEX(Opportunities!$H$8:$H$15,MATCH($A22,Opportunities!$T$8:$T$15,0))) | G22: =IF($A22="","",INDEX(Opportunities!$R$8:$R$15,MATCH($A22,Opportunities!$T$8:$T$15,0))) | H22: =IF($A22="","",INDEX(Opportunities!$M$8:$M$15,MATCH($A22,Opportunities!$T$8:$T$15,0))) | I22: =IF($A22="","",IF(INDEX(Opportunities!$U$8:$U$15,MATCH($A22,Opportunities!$T$8:$T$15,0))=1,"SELECTED","WATCHLIST"))
A25: Report inclusion policy
A26: Shortlist shows eligible positive-NPV investments in descending NPV order. Exclusions and raw inputs remain in Opportunities for audit. Portfolio selection respects budget and project count.
A28: Key risks
A29: Rent and occupancy, construction overrun, permit delay, terminal valuation and legal compliance. Downside is a sensitivity, not a probability forecast.
A31: Scope
A32: No source spreadsheet was supplied. Examples are fictional. NPV measures discounted profit; IRR is supplemental. Financing and investor-specific taxes are excluded.
A34: Excluded / incomplete opportunities | B34: =COUNTIF(Opportunities!S8:S15,"EXCLUDE") -> 2
A35: Portfolio downside NPV | B35: =Opportunities!U8*Opportunities!R8+Opportunities!U9*Opportunities!R9+Opportunities!U10*Opportunities!R10+Opportunities!U11*Opportunities!R11+Opportunities!U12*Opportunities!R12+Opportunities!U13*Opportunities!R13+Opportunities!U14*Opportunities!R14+Opportunities!U15*Opportunities!R15 -> -209495.43
A36: Undiscounted portfolio profit | B36: =Opportunities!U8*SUM('Cash flows'!B5:L5)+Opportunities!U9*SUM('Cash flows'!B6:L6)+Opportunities!U10*SUM('Cash flows'!B7:L7)+Opportunities!U11*SUM('Cash flows'!B8:L8)+Opportunities!U12*SUM('Cash flows'!B9:L9)+Opportunities!U13*SUM('Cash flows'!B10:L10)+Opportunities!U14*SUM('Cash flows'!B11:L11)+Opportunities!U15*SUM('Cash flows'!B12:L12) -> 2296579.6
A38: Independent analysis • Institutional report format • No affiliation with Vanguard.

Sheet Guide
A1: How to use this workbook
A2: Editable blue cells • formula-driven analysis • no macros or external links
A4: Step | B4: Instruction
A5: 1. Import | B5: Replace the eight input rows in Opportunities with the supplied spreadsheet. Preserve calculated columns L:U.
A6: 2. Set assumptions | B6: Change budget, required return, delay limit and scenario assumptions. The horizon is fixed at ten years.
A7: 3. Validate compliance | B7: Replace Demo pass by Verified / Unknown / Fail, and cite actual evidence in each evidence row. Switch Demo mode to NO for real evaluation.
A8: 4. Review | B8: Shortlist ranks eligible assets by NPV. Exact enumeration selects the best subset; excluded assets remain in Opportunities.
A9: 5. Rank | B9: Rank uses descending base NPV; ties are resolved by input row order. Portfolio selection maximizes aggregate NPV.
A10: Method | B10: Acquisition plus contingency capital is committed immediately. Rent and operating cost inflation use the same rate; operating costs begin at rental readiness.
A11: Limitations | B11: Annual timing is approximate. Add pre-opening carrying costs to Other capital costs. No leverage, tax, capex phasing or replacement capex is modeled.
A12: Capacity | B12: The model supports exactly eight projects; enumeration covers every subset, including retaining all capital.
A13: Saving | B13: Run python3 build_model.py to rebuild the template. This overwrites user edits; retain a copy before rerunning.
A14: Source status | B14: See Sources for 2026 official requirements. Verify every room and shared facility; project-wide Verified means all spaces passed, with linked evidence.

Sheet Assumptions
A1: Investment assumptions
A2: Blue cells are editable. Unlevered, pre-tax EUR model; all capital committed at time zero.
A4: Parameter | B4: Value | C4: Interpretation
A5: Demo mode (YES / NO) | B5: YES | C5: YES accepts hypothetical demonstration checks; NO requires Verified evidence.
A6: Available capital | B6: 2000000 | C6: EUR; includes all-in acquisition and construction costs
A7: Maximum projects | B7: 3 | C7: Portfolio cap; eight opportunity slots
A8: Discount rate | B8: 0.09 | C8: Required annual unlevered return
A9: Holding period (years) | B9: 10 | C9: Fixed 10 years; cash flow grid is ten years
A10: Annual rent growth | B10: 0.02 | C10: Applied to base rent from acquisition date
A11: Exit capitalization rate | B11: 0.055 | C11: Year 11 stabilized NOI / cap rate
A12: Exit selling costs | B12: 0.03 | C12: Fraction of exit value
A13: Acquisition costs | B13: 0.14 | C13: Planning estimate; replace with transaction-specific tax/legal fees
A14: Construction contingency | B14: 0.15 | C14: Fraction of base renovation budget
A15: Stress rent reduction | B15: 0.1 | C15: Rent haircut for downside case
A16: Stress delay (months) | B16: 6 | C16: Additional delay in downside case
A17: Stress construction uplift | B17: 0.2 | C17: Applied on top of contingency
A18: Maximum acceptable delay | B18: 36 | C18: Months from acquisition to legal rental readiness

Sheet Opportunities
A1: Opportunity universe | eight investment slots
A2: HYPOTHETICAL EXAMPLES ONLY. Replace with your spreadsheet data; no Brussels properties have been sourced.
A7: ID | B7: Project / location | C7: Rooms | D7: Monthly rent / room | E7: Purchase price | F7: Base construction cost | G7: Other capital costs | H7: Months to ready | I7: Occupancy | J7: Operating cost / revenue | K7: Annual fixed costs | L7: All-in capital | M7: Compliance gate | N7: Year 1 NOI | O7: Year 11 NOI | P7: Base NPV | Q7: Base IRR | R7: Downside NPV | S7: Decision | T7: Rank | U7: Portfolio selected
A8: DEMO01 | B8: Illustrative conversion A | C8: 14 | D8: 640 | E8: 500000 | F8: 230000 | G8: 35000 | H8: 12 | I8: 0.95 | J8: 0.24 | K8: 14000 | L8: =IF(B8="",0,E8*(1+Assumptions!$B$13)+F8*(1+Assumptions!$B$14)+G8) -> 869500 | M8: =IF(B8="","EMPTY",IF(COUNTIF(Compliance!D5:D16,"Fail")>0,"FAIL",IF(AND(COUNTIF(Compliance!D5:D16,"Verified")=12,COUNTBLANK(Compliance!E5:E16)=0),"PASS",IF(AND(Assumptions!$B$5="YES",COUNTIF(Compliance!D5:D16,"Demo pass")=12),"DEMO PASS","UNVERIFIED")))) -> DEMO PASS | N8: ='Cash flows'!C5 -> 0 | O8: =C8*D8*12*I8*(1-J8)*(1+Assumptions!$B$10)^10-K8*(1+Assumptions!$B$10)^10 -> 77563.932 | P8: =NPV(Assumptions!$B$8,'Cash flows'!C5:L5)+'Cash flows'!B5 -> 90896.517 | Q8: =IFERROR(IRR('Cash flows'!B5:L5),0) -> 0.10331943 | R8: =NPV(Assumptions!$B$8,'Cash flows'!C18:L18)+'Cash flows'!B18 -> -103155.23 | S8: =IF(B8="","EMPTY",IF(AND(OR(M8="PASS",M8="DEMO PASS"),H8<=Assumptions!$B$18,C8>0,D8>0,E8>0,H8>=0,I8>0,I8<=1,J8>=0,J8<1,F8>=0,G8>=0,K8>=0,P8>0),"ELIGIBLE","EXCLUDE")) -> ELIGIBLE | T8: =IF(S8="ELIGIBLE",1+COUNTIFS($S$8:$S$15,"ELIGIBLE",$P$8:$P$15,">"&P8)+COUNTIFS($S$8:S8,"ELIGIBLE",$P$8:P8,P8)-1,"") -> 1 | U8: =INDEX(Portfolio!B$5:B$260,Report!$B$7) -> 1
A9: DEMO02 | B9: Illustrative renovation B | C9: 10 | D9: 620 | E9: 350000 | F9: 140000 | G9: 25000 | H9: 6 | I9: 0.95 | J9: 0.25 | K9: 10500 | L9: =IF(B9="",0,E9*(1+Assumptions!$B$13)+F9*(1+Assumptions!$B$14)+G9) -> 585000 | M9: =IF(B9="","EMPTY",IF(COUNTIF(Compliance!D17:D28,"Fail")>0,"FAIL",IF(AND(COUNTIF(Compliance!D17:D28,"Verified")=12,COUNTBLANK(Compliance!E17:E28)=0),"PASS",IF(AND(Assumptions!$B$5="YES",COUNTIF(Compliance!D17:D28,"Demo pass")=12),"DEMO PASS","UNVERIFIED")))) -> DEMO PASS | N9: ='Cash flows'!C6 -> 21255 | O9: =C9*D9*12*I9*(1-J9)*(1+Assumptions!$B$10)^10-K9*(1+Assumptions!$B$10)^10 -> 51819.453 | P9: =NPV(Assumptions!$B$8,'Cash flows'!C6:L6)+'Cash flows'!B6 -> 76128.402 | Q9: =IFERROR(IRR('Cash flows'!B6:L6),0) -> 0.10690125 | R9: =NPV(Assumptions!$B$8,'Cash flows'!C19:L19)+'Cash flows'!B19 -> -55582.705 | S9: =IF(B9="","EMPTY",IF(AND(OR(M9="PASS",M9="DEMO PASS"),H9<=Assumptions!$B$18,C9>0,D9>0,E9>0,H9>=0,I9>0,I9<=1,J9>=0,J9<1,F9>=0,G9>=0,K9>=0,P9>0),"ELIGIBLE","EXCLUDE")) -> ELIGIBLE | T9: =IF(S9="ELIGIBLE",1+COUNTIFS($S$8:$S$15,"ELIGIBLE",$P$8:$P$15,">"&P9)+COUNTIFS($S$8:S9,"ELIGIBLE",$P$8:P9,P9)-1,"") -> 2 | U9: =INDEX(Portfolio!C$5:C$260,Report!$B$7) -> 1
A10: DEMO03 | B10: Illustrative new build C | C10: 24 | D10: 680 | E10: 700000 | F10: 620000 | G10: 70000 | H10: 30 | I10: 0.94 | J10: 0.23 | K10: 23500 | L10: =IF(B10="",0,E10*(1+Assumptions!$B$13)+F10*(1+Assumptions!$B$14)+G10) -> 1581000 | M10: =IF(B10="","EMPTY",IF(COUNTIF(Compliance!D29:D40,"Fail")>0,"FAIL",IF(AND(COUNTIF(Compliance!D29:D40,"Verified")=12,COUNTBLANK(Compliance!E29:E40)=0),"PASS",IF(AND(Assumptions!$B$5="YES",COUNTIF(Compliance!D29:D40,"Demo pass")=12),"DEMO PASS","UNVERIFIED")))) -> DEMO PASS | N10: ='Cash flows'!C7 -> 0 | O10: =C10*D10*12*I10*(1-J10)*(1+Assumptions!$B$10)^10-K10*(1+Assumptions!$B$10)^10 -> 144144.86 | P10: =NPV(Assumptions!$B$8,'Cash flows'!C7:L7)+'Cash flows'!B7 -> 54783.715 | Q10: =IFERROR(IRR('Cash flows'!B7:L7),0) -> 0.094246244 | R10: =NPV(Assumptions!$B$8,'Cash flows'!C20:L20)+'Cash flows'!B20 -> -325708.62 | S10: =IF(B10="","EMPTY",IF(AND(OR(M10="PASS",M10="DEMO PASS"),H10<=Assumptions!$B$18,C10>0,D10>0,E10>0,H10>=0,I10>0,I10<=1,J10>=0,J10<1,F10>=0,G10>=0,K10>=0,P10>0),"ELIGIBLE","EXCLUDE")) -> ELIGIBLE | T10: =IF(S10="ELIGIBLE",1+COUNTIFS($S$8:$S$15,"ELIGIBLE",$P$8:$P$15,">"&P10)+COUNTIFS($S$8:S10,"ELIGIBLE",$P$8:P10,P10)-1,"") -> 3 | U10: =INDEX(Portfolio!D$5:D$260,Report!$B$7) -> 0
A11: DEMO04 | B11: Illustrative small asset D | C11: 6 | D11: 590 | E11: 200000 | F11: 75000 | G11: 18000 | H11: 4 | I11: 0.94 | J11: 0.26 | K11: 7000 | L11: =IF(B11="",0,E11*(1+Assumptions!$B$13)+F11*(1+Assumptions!$B$14)+G11) -> 332250 | M11: =IF(B11="","EMPTY",IF(COUNTIF(Compliance!D41:D52,"Fail")>0,"FAIL",IF(AND(COUNTIF(Compliance!D41:D52,"Verified")=12,COUNTBLANK(Compliance!E41:E52)=0),"PASS",IF(AND(Assumptions!$B$5="YES",COUNTIF(Compliance!D41:D52,"Demo pass")=12),"DEMO PASS","UNVERIFIED")))) -> DEMO PASS | N11: ='Cash flows'!C8 -> 15032.725 | O11: =C11*D11*12*I11*(1-J11)*(1+Assumptions!$B$10)^10-K11*(1+Assumptions!$B$10)^10 -> 27487.212 | P11: =NPV(Assumptions!$B$8,'Cash flows'!C8:L8)+'Cash flows'!B8 -> 21888.123 | Q11: =IFERROR(IRR('Cash flows'!B8:L8),0) -> 0.09882353 | R11: =NPV(Assumptions!$B$8,'Cash flows'!C21:L21)+'Cash flows'!B21 -> -50757.491 | S11: =IF(B11="","EMPTY",IF(AND(OR(M11="PASS",M11="DEMO PASS"),H11<=Assumptions!$B$18,C11>0,D11>0,E11>0,H11>=0,I11>0,I11<=1,J11>=0,J11<1,F11>=0,G11>=0,K11>=0,P11>0),"ELIGIBLE","EXCLUDE")) -> ELIGIBLE | T11: =IF(S11="ELIGIBLE",1+COUNTIFS($S$8:$S$15,"ELIGIBLE",$P$8:$P$15,">"&P11)+COUNTIFS($S$8:S11,"ELIGIBLE",$P$8:P11,P11)-1,"") -> 4 | U11: =INDEX(Portfolio!E$5:E$260,Report!$B$7) -> 1
A12: DEMO05 | B12: Illustrative delayed asset E | C12: 16 | D12: 650 | E12: 600000 | F12: 360000 | G12: 45000 | H12: 42 | I12: 0.95 | J12: 0.24 | K12: 16000 | L12: =IF(B12="",0,E12*(1+Assumptions!$B$13)+F12*(1+Assumptions!$B$14)+G12) -> 1143000 | M12: =IF(B12="","EMPTY",IF(COUNTIF(Compliance!D53:D64,"Fail")>0,"FAIL",IF(AND(COUNTIF(Compliance!D53:D64,"Verified")=12,COUNTBLANK(Compliance!E53:E64)=0),"PASS",IF(AND(Assumptions!$B$5="YES",COUNTIF(Compliance!D53:D64,"Demo pass")=12),"DEMO PASS","UNVERIFIED")))) -> DEMO PASS | N12: ='Cash flows'!C9 -> 0 | O12: =C12*D12*12*I12*(1-J12)*(1+Assumptions!$B$10)^10-K12*(1+Assumptions!$B$10)^10 -> 90334.313 | P12: =NPV(Assumptions!$B$8,'Cash flows'!C9:L9)+'Cash flows'!B9 -> -175492.04 | Q12: =IFERROR(IRR('Cash flows'!B9:L9),0) -> 0.070241327 | R12: =NPV(Assumptions!$B$8,'Cash flows'!C22:L22)+'Cash flows'!B22 -> -400400.9 | S12: =IF(B12="","EMPTY",IF(AND(OR(M12="PASS",M12="DEMO PASS"),H12<=Assumptions!$B$18,C12>0,D12>0,E12>0,H12>=0,I12>0,I12<=1,J12>=0,J12<1,F12>=0,G12>=0,K12>=0,P12>0),"ELIGIBLE","EXCLUDE")) -> EXCLUDE | T12: =IF(S12="ELIGIBLE",1+COUNTIFS($S$8:$S$15,"ELIGIBLE",$P$8:$P$15,">"&P12)+COUNTIFS($S$8:S12,"ELIGIBLE",$P$8:P12,P12)-1,"") | U12: =INDEX(Portfolio!F$5:F$260,Report!$B$7) -> 0
A13: DEMO06 | B13: Illustrative compliance failure F | C13: 12 | D13: 660 | E13: 500000 | F13: 175000 | G13: 28000 | H13: 8 | I13: 0.95 | J13: 0.24 | K13: 12000 | L13: =IF(B13="",0,E13*(1+Assumptions!$B$13)+F13*(1+Assumptions!$B$14)+G13) -> 799250 | M13: =IF(B13="","EMPTY",IF(COUNTIF(Compliance!D65:D76,"Fail")>0,"FAIL",IF(AND(COUNTIF(Compliance!D65:D76,"Verified")=12,COUNTBLANK(Compliance!E65:E76)=0),"PASS",IF(AND(Assumptions!$B$5="YES",COUNTIF(Compliance!D65:D76,"Demo pass")=12),"DEMO PASS","UNVERIFIED")))) -> FAIL | N13: ='Cash flows'!C10 -> 18872.96 | O13: =C13*D13*12*I13*(1-J13)*(1+Assumptions!$B$10)^10-K13*(1+Assumptions!$B$10)^10 -> 69018.099 | P13: =NPV(Assumptions!$B$8,'Cash flows'!C10:L10)+'Cash flows'!B10 -> 72646.659 | Q13: =IFERROR(IRR('Cash flows'!B10:L10),0) -> 0.10185409 | R13: =NPV(Assumptions!$B$8,'Cash flows'!C23:L23)+'Cash flows'!B23 -> -95607.999 | S13: =IF(B13="","EMPTY",IF(AND(OR(M13="PASS",M13="DEMO PASS"),H13<=Assumptions!$B$18,C13>0,D13>0,E13>0,H13>=0,I13>0,I13<=1,J13>=0,J13<1,F13>=0,G13>=0,K13>=0,P13>0),"ELIGIBLE","EXCLUDE")) -> EXCLUDE | T13: =IF(S13="ELIGIBLE",1+COUNTIFS($S$8:$S$15,"ELIGIBLE",$P$8:$P$15,">"&P13)+COUNTIFS($S$8:S13,"ELIGIBLE",$P$8:P13,P13)-1,"") | U13: =INDEX(Portfolio!G$5:G$260,Report!$B$7) -> 0
A14: SLOT7 | C14: 0 | D14: 0 | E14: 0 | F14: 0 | G14: 0 | H14: 0 | I14: 0.95 | J14: 0.25 | K14: 0 | L14: =IF(B14="",0,E14*(1+Assumptions!$B$13)+F14*(1+Assumptions!$B$14)+G14) -> 0 | M14: =IF(B14="","EMPTY",IF(COUNTIF(Compliance!D77:D88,"Fail")>0,"FAIL",IF(AND(COUNTIF(Compliance!D77:D88,"Verified")=12,COUNTBLANK(Compliance!E77:E88)=0),"PASS",IF(AND(Assumptions!$B$5="YES",COUNTIF(Compliance!D77:D88,"Demo pass")=12),"DEMO PASS","UNVERIFIED")))) -> EMPTY | N14: ='Cash flows'!C11 -> 0 | O14: =C14*D14*12*I14*(1-J14)*(1+Assumptions!$B$10)^10-K14*(1+Assumptions!$B$10)^10 -> 0 | P14: =NPV(Assumptions!$B$8,'Cash flows'!C11:L11)+'Cash flows'!B11 -> 0 | Q14: =IFERROR(IRR('Cash flows'!B11:L11),0) -> 0 | R14: =NPV(Assumptions!$B$8,'Cash flows'!C24:L24)+'Cash flows'!B24 -> 0 | S14: =IF(B14="","EMPTY",IF(AND(OR(M14="PASS",M14="DEMO PASS"),H14<=Assumptions!$B$18,C14>0,D14>0,E14>0,H14>=0,I14>0,I14<=1,J14>=0,J14<1,F14>=0,G14>=0,K14>=0,P14>0),"ELIGIBLE","EXCLUDE")) -> EMPTY | T14: =IF(S14="ELIGIBLE",1+COUNTIFS($S$8:$S$15,"ELIGIBLE",$P$8:$P$15,">"&P14)+COUNTIFS($S$8:S14,"ELIGIBLE",$P$8:P14,P14)-1,"") | U14: =INDEX(Portfolio!H$5:H$260,Report!$B$7) -> 0
A15: SLOT8 | C15: 0 | D15: 0 | E15: 0 | F15: 0 | G15: 0 | H15: 0 | I15: 0.95 | J15: 0.25 | K15: 0 | L15: =IF(B15="",0,E15*(1+Assumptions!$B$13)+F15*(1+Assumptions!$B$14)+G15) -> 0 | M15: =IF(B15="","EMPTY",IF(COUNTIF(Compliance!D89:D100,"Fail")>0,"FAIL",IF(AND(COUNTIF(Compliance!D89:D100,"Verified")=12,COUNTBLANK(Compliance!E89:E100)=0),"PASS",IF(AND(Assumptions!$B$5="YES",COUNTIF(Compliance!D89:D100,"Demo pass")=12),"DEMO PASS","UNVERIFIED")))) -> EMPTY | N15: ='Cash flows'!C12 -> 0 | O15: =C15*D15*12*I15*(1-J15)*(1+Assumptions!$B$10)^10-K15*(1+Assumptions!$B$10)^10 -> 0 | P15: =NPV(Assumptions!$B$8,'Cash flows'!C12:L12)+'Cash flows'!B12 -> 0 | Q15: =IFERROR(IRR('Cash flows'!B12:L12),0) -> 0 | R15: =NPV(Assumptions!$B$8,'Cash flows'!C25:L25)+'Cash flows'!B25 -> 0 | S15: =IF(B15="","EMPTY",IF(AND(OR(M15="PASS",M15="DEMO PASS"),H15<=Assumptions!$B$18,C15>0,D15>0,E15>0,H15>=0,I15>0,I15<=1,J15>=0,J15<1,F15>=0,G15>=0,K15>=0,P15>0),"ELIGIBLE","EXCLUDE")) -> EMPTY | T15: =IF(S15="ELIGIBLE",1+COUNTIFS($S$8:$S$15,"ELIGIBLE",$P$8:$P$15,">"&P15)+COUNTIFS($S$8:S15,"ELIGIBLE",$P$8:P15,P15)-1,"") | U15: =INDEX(Portfolio!I$5:I$260,Report!$B$7) -> 0

Sheet Compliance
A1: Mandatory requirements | project evidence register
A2: Unknown evidence blocks eligibility. Demo pass is permitted only in explicit demonstration mode.
A4: ID | B4: Control | C4: Minimum / validation needed | D4: Status | E4: Evidence / authority / date
A5: DEMO01 | B5: Planning use | C5: Written confirmation that student housing use and works are lawful | D5: Demo pass | E5: Illustrative only — no evidence
A6: DEMO01 | B6: Rental authorization | C6: Check required planning/letting approvals; DIRL clearance required after a letting prohibition. Ordinary voluntary conformity certificate and quality label are not universal prerequisites. Source S3/S4. | D6: Demo pass | E6: Illustrative only — no evidence
A7: DEMO01 | B7: Minimum room area | C7: Student accommodation: 12 m² for one resident; 18 m² for two. Shared area counted pro rata. Validate legal classification, habitable share and height. Source S2, art. 4. | D7: Demo pass | E7: Illustrative only — no evidence
A8: DEMO01 | B8: Occupancy limits | C8: Shared WC and shower: maximum six users each; kitchen sink and four-ring hob: maximum eight users. Use contractual maximum occupancy. Source S2, art. 5. | D8: Demo pass | E8: Illustrative only — no evidence
A9: DEMO01 | B9: Sanitation | C9: Bath/shower with hot water and drainage; shared facilities accessible and lockable. Source S2, art. 5. | D9: Demo pass | E9: Illustrative only — no evidence
A10: DEMO01 | B10: Kitchen / cooking | C10: Operational cooking equipment in communal kitchen; suitable supply. Source S2, art. 5. | D10: Demo pass | E10: Illustrative only — no evidence
A11: DEMO01 | B11: Daylight / ventilation | C11: Daylight and permanent base ventilation; verify windows, airflow and configuration against S2, art. 3. | D11: Demo pass | E11: Illustrative only — no evidence
A12: DEMO01 | B12: Electrical / gas safety | C12: Safe electrical/gas installation; no type B gas heater in bedroom. Source S1/S2. | D12: Demo pass | E12: Illustrative only — no evidence
A13: DEMO01 | B13: Fire safety | C13: Fire authority requirements, escape routes and detection | D13: Demo pass | E13: Illustrative only — no evidence
A14: DEMO01 | B14: Water / heating / moisture | C14: Water, installed heating, dry structure, sound drainage and no harmful infestation; source S2, arts. 2–5. | D14: Demo pass | E14: Illustrative only — no evidence
A15: DEMO01 | B15: Energy certification | C15: Applicable PEB certificate and required disclosures | D15: Demo pass | E15: Illustrative only — no evidence
... A76: DEMO06 | B76: Accessibility / other rules | C76: Verify access, ceiling heights, structure, mailbox and doorbell, and all case-specific rules. Source S2; confirm municipal requirements. | D76: Unknown | E76: Illustrative only — no evidence
A77: SLOT7 | B77: Planning use | C77: Written confirmation that student housing use and works are lawful | D77: Unknown
A78: SLOT7 | B78: Rental authorization | C78: Check required planning/letting approvals; DIRL clearance required after a letting prohibition. Ordinary voluntary conformity certificate and quality label are not universal prerequisites. Source S3/S4. | D78: Unknown
A79: SLOT7 | B79: Minimum room area | C79: Student accommodation: 12 m² for one resident; 18 m² for two. Shared area counted pro rata. Validate legal classification, habitable share and height. Source S2, art. 4. | D79: Unknown
A80: SLOT7 | B80: Occupancy limits | C80: Shared WC and shower: maximum six users each; kitchen sink and four-ring hob: maximum eight users. Use contractual maximum occupancy. Source S2, art. 5. | D80: Unknown
A81: SLOT7 | B81: Sanitation | C81: Bath/shower with hot water and drainage; shared facilities accessible and lockable. Source S2, art. 5. | D81: Unknown
A82: SLOT7 | B82: Kitchen / cooking | C82: Operational cooking equipment in communal kitchen; suitable supply. Source S2, art. 5. | D82: Unknown
A83: SLOT7 | B83: Daylight / ventilation | C83: Daylight and permanent base ventilation; verify windows, airflow and configuration against S2, art. 3. | D83: Unknown
A84: SLOT7 | B84: Electrical / gas safety | C84: Safe electrical/gas installation; no type B gas heater in bedroom. Source S1/S2. | D84: Unknown
A85: SLOT7 | B85: Fire safety | C85: Fire authority requirements, escape routes and detection | D85: Unknown
A86: SLOT7 | B86: Water / heating / moisture | C86: Water, installed heating, dry structure, sound drainage and no harmful infestation; source S2, arts. 2–5. | D86: Unknown
A87: SLOT7 | B87: Energy certification | C87: Applicable PEB certificate and required disclosures | D87: Unknown
A88: SLOT7 | B88: Accessibility / other rules | C88: Verify access, ceiling heights, structure, mailbox and doorbell, and all case-specific rules. Source S2; confirm municipal requirements. | D88: Unknown
... A100: SLOT8 | B100: Accessibility / other rules | C100: Verify access, ceiling heights, structure, mailbox and doorbell, and all case-specific rules. Source S2; confirm municipal requirements. | D100: Unknown

Sheet Cash flows
A1: Ten-year cash flows | base and downside
A2: Annual approximation: delay reduces operating months. Capital paid at acquisition; terminal sale at year 10.
A4: Project | B4: Year 0 | C4: Year 1 | D4: Year 2 | E4: Year 3 | F4: Year 4 | G4: Year 5 | H4: Year 6 | I4: Year 7 | J4: Year 8 | K4: Year 9 | L4: Year 10
A5: =Opportunities!B8 -> Illustrative conversion A | B5: =-Opportunities!L8 -> -869500 | C5: =(Opportunities!C8*Opportunities!D8*12*Opportunities!I8*(1-Opportunities!J8)-Opportunities!K8)*(1+Assumptions!$B$10)^0*MAX(0,MIN(1,(1*12-(Opportunities!H8))/12)) -> 0 | D5: =(Opportunities!C8*Opportunities!D8*12*Opportunities!I8*(1-Opportunities!J8)-Opportunities!K8)*(1+Assumptions!$B$10)^1*MAX(0,MIN(1,(2*12-(Opportunities!H8))/12)) -> 64902.029 | E5: =(Opportunities!C8*Opportunities!D8*12*Opportunities!I8*(1-Opportunities!J8)-Opportunities!K8)*(1+Assumptions!$B$10)^2*MAX(0,MIN(1,(3*12-(Opportunities!H8))/12)) -> 66200.069 | F5: =(Opportunities!C8*Opportunities!D8*12*Opportunities!I8*(1-Opportunities!J8)-Opportunities!K8)*(1+Assumptions!$B$10)^3*MAX(0,MIN(1,(4*12-(Opportunities!H8))/12)) -> 67524.071 | G5: =(Opportunities!C8*Opportunities!D8*12*Opportunities!I8*(1-Opportunities!J8)-Opportunities!K8)*(1+Assumptions!$B$10)^4*MAX(0,MIN(1,(5*12-(Opportunities!H8))/12)) -> 68874.552 | H5: =(Opportunities!C8*Opportunities!D8*12*Opportunities!I8*(1-Opportunities!J8)-Opportunities!K8)*(1+Assumptions!$B$10)^5*MAX(0,MIN(1,(6*12-(Opportunities!H8))/12)) -> 70252.043 | I5: =(Opportunities!C8*Opportunities!D8*12*Opportunities!I8*(1-Opportunities!J8)-Opportunities!K8)*(1+Assumptions!$B$10)^6*MAX(0,MIN(1,(7*12-(Opportunities!H8))/12)) -> 71657.084 | J5: =(Opportunities!C8*Opportunities!D8*12*Opportunities!I8*(1-Opportunities!J8)-Opportunities!K8)*(1+Assumptions!$B$10)^7*MAX(0,MIN(1,(8*12-(Opportunities!H8))/12)) -> 73090.226 | K5: =(Opportunities!C8*Opportunities!D8*12*Opportunities!I8*(1-Opportunities!J8)-Opportunities!K8)*(1+Assumptions!$B$10)^8*MAX(0,MIN(1,(9*12-(Opportunities!H8))/12)) -> 74552.03 | L5: =(Opportunities!C8*Opportunities!D8*12*Opportunities!I8*(1-Opportunities!J8)-Opportunities!K8)*(1+Assumptions!$B$10)^9*MAX(0,MIN(1,(10*12-(Opportunities!H8))/12))+MAX(0,(Opportunities!O8)/Assumptions!$B$11)*(1-Assumptions!$B$12) -> 1443988.8
A6: =Opportunities!B9 -> Illustrative renovation B | B6: =-Opportunities!L9 -> -585000 | C6: =(Opportunities!C9*Opportunities!D9*12*Opportunities!I9*(1-Opportunities!J9)-Opportunities!K9)*(1+Assumptions!$B$10)^0*MAX(0,MIN(1,(1*12-(Opportunities!H9))/12)) -> 21255 | D6: =(Opportunities!C9*Opportunities!D9*12*Opportunities!I9*(1-Opportunities!J9)-Opportunities!K9)*(1+Assumptions!$B$10)^1*MAX(0,MIN(1,(2*12-(Opportunities!H9))/12)) -> 43360.2 | E6: =(Opportunities!C9*Opportunities!D9*12*Opportunities!I9*(1-Opportunities!J9)-Opportunities!K9)*(1+Assumptions!$B$10)^2*MAX(0,MIN(1,(3*12-(Opportunities!H9))/12)) -> 44227.404 | F6: =(Opportunities!C9*Opportunities!D9*12*Opportunities!I9*(1-Opportunities!J9)-Opportunities!K9)*(1+Assumptions!$B$10)^3*MAX(0,MIN(1,(4*12-(Opportunities!H9))/12)) -> 45111.952 | G6: =(Opportunities!C9*Opportunities!D9*12*Opportunities!I9*(1-Opportunities!J9)-Opportunities!K9)*(1+Assumptions!$B$10)^4*MAX(0,MIN(1,(5*12-(Opportunities!H9))/12)) -> 46014.191 | H6: =(Opportunities!C9*Opportunities!D9*12*Opportunities!I9*(1-Opportunities!J9)-Opportunities!K9)*(1+Assumptions!$B$10)^5*MAX(0,MIN(1,(6*12-(Opportunities!H9))/12)) -> 46934.475 | I6: =(Opportunities!C9*Opportunities!D9*12*Opportunities!I9*(1-Opportunities!J9)-Opportunities!K9)*(1+Assumptions!$B$10)^6*MAX(0,MIN(1,(7*12-(Opportunities!H9))/12)) -> 47873.164 | J6: =(Opportunities!C9*Opportunities!D9*12*Opportunities!I9*(1-Opportunities!J9)-Opportunities!K9)*(1+Assumptions!$B$10)^7*MAX(0,MIN(1,(8*12-(Opportunities!H9))/12)) -> 48830.628 | K6: =(Opportunities!C9*Opportunities!D9*12*Opportunities!I9*(1-Opportunities!J9)-Opportunities!K9)*(1+Assumptions!$B$10)^8*MAX(0,MIN(1,(9*12-(Opportunities!H9))/12)) -> 49807.24 | L6: =(Opportunities!C9*Opportunities!D9*12*Opportunities!I9*(1-Opportunities!J9)-Opportunities!K9)*(1+Assumptions!$B$10)^9*MAX(0,MIN(1,(10*12-(Opportunities!H9))/12))+MAX(0,(Opportunities!O9)/Assumptions!$B$11)*(1-Assumptions!$B$12) -> 964710.1
A7: =Opportunities!B10 -> Illustrative new build C | B7: =-Opportunities!L10 -> -1581000 | C7: =(Opportunities!C10*Opportunities!D10*12*Opportunities!I10*(1-Opportunities!J10)-Opportunities!K10)*(1+Assumptions!$B$10)^0*MAX(0,MIN(1,(1*12-(Opportunities!H10))/12)) -> 0 | D7: =(Opportunities!C10*Opportunities!D10*12*Opportunities!I10*(1-Opportunities!J10)-Opportunities!K10)*(1+Assumptions!$B$10)^1*MAX(0,MIN(1,(2*12-(Opportunities!H10))/12)) -> 0 | E7: =(Opportunities!C10*Opportunities!D10*12*Opportunities!I10*(1-Opportunities!J10)-Opportunities!K10)*(1+Assumptions!$B$10)^2*MAX(0,MIN(1,(3*12-(Opportunities!H10))/12)) -> 61513.126 | F7: =(Opportunities!C10*Opportunities!D10*12*Opportunities!I10*(1-Opportunities!J10)-Opportunities!K10)*(1+Assumptions!$B$10)^3*MAX(0,MIN(1,(4*12-(Opportunities!H10))/12)) -> 125486.78 | G7: =(Opportunities!C10*Opportunities!D10*12*Opportunities!I10*(1-Opportunities!J10)-Opportunities!K10)*(1+Assumptions!$B$10)^4*MAX(0,MIN(1,(5*12-(Opportunities!H10))/12)) -> 127996.51 | H7: =(Opportunities!C10*Opportunities!D10*12*Opportunities!I10*(1-Opportunities!J10)-Opportunities!K10)*(1+Assumptions!$B$10)^5*MAX(0,MIN(1,(6*12-(Opportunities!H10))/12)) -> 130556.44 | I7: =(Opportunities!C10*Opportunities!D10*12*Opportunities!I10*(1-Opportunities!J10)-Opportunities!K10)*(1+Assumptions!$B$10)^6*MAX(0,MIN(1,(7*12-(Opportunities!H10))/12)) -> 133167.57 | J7: =(Opportunities!C10*Opportunities!D10*12*Opportunities!I10*(1-Opportunities!J10)-Opportunities!K10)*(1+Assumptions!$B$10)^7*MAX(0,MIN(1,(8*12-(Opportunities!H10))/12)) -> 135830.92 | K7: =(Opportunities!C10*Opportunities!D10*12*Opportunities!I10*(1-Opportunities!J10)-Opportunities!K10)*(1+Assumptions!$B$10)^8*MAX(0,MIN(1,(9*12-(Opportunities!H10))/12)) -> 138547.54 | L7: =(Opportunities!C10*Opportunities!D10*12*Opportunities!I10*(1-Opportunities!J10)-Opportunities!K10)*(1+Assumptions!$B$10)^9*MAX(0,MIN(1,(10*12-(Opportunities!H10))/12))+MAX(0,(Opportunities!O10)/Assumptions!$B$11)*(1-Assumptions!$B$12) -> 2683509.7
A8: =Opportunities!B11 -> Illustrative small asset D | B8: =-Opportunities!L11 -> -332250 | C8: =(Opportunities!C11*Opportunities!D11*12*Opportunities!I11*(1-Opportunities!J11)-Opportunities!K11)*(1+Assumptions!$B$10)^0*MAX(0,MIN(1,(1*12-(Opportunities!H11))/12)) -> 15032.725 | D8: =(Opportunities!C11*Opportunities!D11*12*Opportunities!I11*(1-Opportunities!J11)-Opportunities!K11)*(1+Assumptions!$B$10)^1*MAX(0,MIN(1,(2*12-(Opportunities!H11))/12)) -> 23000.07 | E8: =(Opportunities!C11*Opportunities!D11*12*Opportunities!I11*(1-Opportunities!J11)-Opportunities!K11)*(1+Assumptions!$B$10)^2*MAX(0,MIN(1,(3*12-(Opportunities!H11))/12)) -> 23460.071 | F8: =(Opportunities!C11*Opportunities!D11*12*Opportunities!I11*(1-Opportunities!J11)-Opportunities!K11)*(1+Assumptions!$B$10)^3*MAX(0,MIN(1,(4*12-(Opportunities!H11))/12)) -> 23929.273 | G8: =(Opportunities!C11*Opportunities!D11*12*Opportunities!I11*(1-Opportunities!J11)-Opportunities!K11)*(1+Assumptions!$B$10)^4*MAX(0,MIN(1,(5*12-(Opportunities!H11))/12)) -> 24407.858 | H8: =(Opportunities!C11*Opportunities!D11*12*Opportunities!I11*(1-Opportunities!J11)-Opportunities!K11)*(1+Assumptions!$B$10)^5*MAX(0,MIN(1,(6*12-(Opportunities!H11))/12)) -> 24896.015 | I8: =(Opportunities!C11*Opportunities!D11*12*Opportunities!I11*(1-Opportunities!J11)-Opportunities!K11)*(1+Assumptions!$B$10)^6*MAX(0,MIN(1,(7*12-(Opportunities!H11))/12)) -> 25393.935 | J8: =(Opportunities!C11*Opportunities!D11*12*Opportunities!I11*(1-Opportunities!J11)-Opportunities!K11)*(1+Assumptions!$B$10)^7*MAX(0,MIN(1,(8*12-(Opportunities!H11))/12)) -> 25901.814 | K8: =(Opportunities!C11*Opportunities!D11*12*Opportunities!I11*(1-Opportunities!J11)-Opportunities!K11)*(1+Assumptions!$B$10)^8*MAX(0,MIN(1,(9*12-(Opportunities!H11))/12)) -> 26419.85 | L8: =(Opportunities!C11*Opportunities!D11*12*Opportunities!I11*(1-Opportunities!J11)-Opportunities!K11)*(1+Assumptions!$B$10)^9*MAX(0,MIN(1,(10*12-(Opportunities!H11))/12))+MAX(0,(Opportunities!O11)/Assumptions!$B$11)*(1-Assumptions!$B$12) -> 511722.72
A9: =Opportunities!B12 -> Illustrative delayed asset E | B9: =-Opportunities!L12 -> -1143000 | C9: =(Opportunities!C12*Opportunities!D12*12*Opportunities!I12*(1-Opportunities!J12)-Opportunities!K12)*(1+Assumptions!$B$10)^0*MAX(0,MIN(1,(1*12-(Opportunities!H12))/12)) -> 0 | D9: =(Opportunities!C12*Opportunities!D12*12*Opportunities!I12*(1-Opportunities!J12)-Opportunities!K12)*(1+Assumptions!$B$10)^1*MAX(0,MIN(1,(2*12-(Opportunities!H12))/12)) -> 0 | E9: =(Opportunities!C12*Opportunities!D12*12*Opportunities!I12*(1-Opportunities!J12)-Opportunities!K12)*(1+Assumptions!$B$10)^2*MAX(0,MIN(1,(3*12-(Opportunities!H12))/12)) -> 0 | F9: =(Opportunities!C12*Opportunities!D12*12*Opportunities!I12*(1-Opportunities!J12)-Opportunities!K12)*(1+Assumptions!$B$10)^3*MAX(0,MIN(1,(4*12-(Opportunities!H12))/12)) -> 39320.728 | G9: =(Opportunities!C12*Opportunities!D12*12*Opportunities!I12*(1-Opportunities!J12)-Opportunities!K12)*(1+Assumptions!$B$10)^4*MAX(0,MIN(1,(5*12-(Opportunities!H12))/12)) -> 80214.285 | H9: =(Opportunities!C12*Opportunities!D12*12*Opportunities!I12*(1-Opportunities!J12)-Opportunities!K12)*(1+Assumptions!$B$10)^5*MAX(0,MIN(1,(6*12-(Opportunities!H12))/12)) -> 81818.57 | I9: =(Opportunities!C12*Opportunities!D12*12*Opportunities!I12*(1-Opportunities!J12)-Opportunities!K12)*(1+Assumptions!$B$10)^6*MAX(0,MIN(1,(7*12-(Opportunities!H12))/12)) -> 83454.942 | J9: =(Opportunities!C12*Opportunities!D12*12*Opportunities!I12*(1-Opportunities!J12)-Opportunities!K12)*(1+Assumptions!$B$10)^7*MAX(0,MIN(1,(8*12-(Opportunities!H12))/12)) -> 85124.041 | K9: =(Opportunities!C12*Opportunities!D12*12*Opportunities!I12*(1-Opportunities!J12)-Opportunities!K12)*(1+Assumptions!$B$10)^8*MAX(0,MIN(1,(9*12-(Opportunities!H12))/12)) -> 86826.521 | L9: =(Opportunities!C12*Opportunities!D12*12*Opportunities!I12*(1-Opportunities!J12)-Opportunities!K12)*(1+Assumptions!$B$10)^9*MAX(0,MIN(1,(10*12-(Opportunities!H12))/12))+MAX(0,(Opportunities!O12)/Assumptions!$B$11)*(1-Assumptions!$B$12) -> 1681731.8
A10: =Opportunities!B13 -> Illustrative compliance failure F | B10: =-Opportunities!L13 -> -799250 | C10: =(Opportunities!C13*Opportunities!D13*12*Opportunities!I13*(1-Opportunities!J13)-Opportunities!K13)*(1+Assumptions!$B$10)^0*MAX(0,MIN(1,(1*12-(Opportunities!H13))/12)) -> 18872.96 | D10: =(Opportunities!C13*Opportunities!D13*12*Opportunities!I13*(1-Opportunities!J13)-Opportunities!K13)*(1+Assumptions!$B$10)^1*MAX(0,MIN(1,(2*12-(Opportunities!H13))/12)) -> 57751.258 | E10: =(Opportunities!C13*Opportunities!D13*12*Opportunities!I13*(1-Opportunities!J13)-Opportunities!K13)*(1+Assumptions!$B$10)^2*MAX(0,MIN(1,(3*12-(Opportunities!H13))/12)) -> 58906.283 | F10: =(Opportunities!C13*Opportunities!D13*12*Opportunities!I13*(1-Opportunities!J13)-Opportunities!K13)*(1+Assumptions!$B$10)^3*MAX(0,MIN(1,(4*12-(Opportunities!H13))/12)) -> 60084.408 | G10: =(Opportunities!C13*Opportunities!D13*12*Opportunities!I13*(1-Opportunities!J13)-Opportunities!K13)*(1+Assumptions!$B$10)^4*MAX(0,MIN(1,(5*12-(Opportunities!H13))/12)) -> 61286.097 | H10: =(Opportunities!C13*Opportunities!D13*12*Opportunities!I13*(1-Opportunities!J13)-Opportunities!K13)*(1+Assumptions!$B$10)^5*MAX(0,MIN(1,(6*12-(Opportunities!H13))/12)) -> 62511.819 | I10: =(Opportunities!C13*Opportunities!D13*12*Opportunities!I13*(1-Opportunities!J13)-Opportunities!K13)*(1+Assumptions!$B$10)^6*MAX(0,MIN(1,(7*12-(Opportunities!H13))/12)) -> 63762.055 | J10: =(Opportunities!C13*Opportunities!D13*12*Opportunities!I13*(1-Opportunities!J13)-Opportunities!K13)*(1+Assumptions!$B$10)^7*MAX(0,MIN(1,(8*12-(Opportunities!H13))/12)) -> 65037.296 | K10: =(Opportunities!C13*Opportunities!D13*12*Opportunities!I13*(1-Opportunities!J13)-Opportunities!K13)*(1+Assumptions!$B$10)^8*MAX(0,MIN(1,(9*12-(Opportunities!H13))/12)) -> 66338.042 | L10: =(Opportunities!C13*Opportunities!D13*12*Opportunities!I13*(1-Opportunities!J13)-Opportunities!K13)*(1+Assumptions!$B$10)^9*MAX(0,MIN(1,(10*12-(Opportunities!H13))/12))+MAX(0,(Opportunities!O13)/Assumptions!$B$11)*(1-Assumptions!$B$12) -> 1284893.1
A11: =Opportunities!B14 | B11: =-Opportunities!L14 -> 0 | C11: =(Opportunities!C14*Opportunities!D14*12*Opportunities!I14*(1-Opportunities!J14)-Opportunities!K14)*(1+Assumptions!$B$10)^0*MAX(0,MIN(1,(1*12-(Opportunities!H14))/12)) -> 0 | D11: =(Opportunities!C14*Opportunities!D14*12*Opportunities!I14*(1-Opportunities!J14)-Opportunities!K14)*(1+Assumptions!$B$10)^1*MAX(0,MIN(1,(2*12-(Opportunities!H14))/12)) -> 0 | E11: =(Opportunities!C14*Opportunities!D14*12*Opportunities!I14*(1-Opportunities!J14)-Opportunities!K14)*(1+Assumptions!$B$10)^2*MAX(0,MIN(1,(3*12-(Opportunities!H14))/12)) -> 0 | F11: =(Opportunities!C14*Opportunities!D14*12*Opportunities!I14*(1-Opportunities!J14)-Opportunities!K14)*(1+Assumptions!$B$10)^3*MAX(0,MIN(1,(4*12-(Opportunities!H14))/12)) -> 0 | G11: =(Opportunities!C14*Opportunities!D14*12*Opportunities!I14*(1-Opportunities!J14)-Opportunities!K14)*(1+Assumptions!$B$10)^4*MAX(0,MIN(1,(5*12-(Opportunities!H14))/12)) -> 0 | H11: =(Opportunities!C14*Opportunities!D14*12*Opportunities!I14*(1-Opportunities!J14)-Opportunities!K14)*(1+Assumptions!$B$10)^5*MAX(0,MIN(1,(6*12-(Opportunities!H14))/12)) -> 0 | I11: =(Opportunities!C14*Opportunities!D14*12*Opportunities!I14*(1-Opportunities!J14)-Opportunities!K14)*(1+Assumptions!$B$10)^6*MAX(0,MIN(1,(7*12-(Opportunities!H14))/12)) -> 0 | J11: =(Opportunities!C14*Opportunities!D14*12*Opportunities!I14*(1-Opportunities!J14)-Opportunities!K14)*(1+Assumptions!$B$10)^7*MAX(0,MIN(1,(8*12-(Opportunities!H14))/12)) -> 0 | K11: =(Opportunities!C14*Opportunities!D14*12*Opportunities!I14*(1-Opportunities!J14)-Opportunities!K14)*(1+Assumptions!$B$10)^8*MAX(0,MIN(1,(9*12-(Opportunities!H14))/12)) -> 0 | L11: =(Opportunities!C14*Opportunities!D14*12*Opportunities!I14*(1-Opportunities!J14)-Opportunities!K14)*(1+Assumptions!$B$10)^9*MAX(0,MIN(1,(10*12-(Opportunities!H14))/12))+MAX(0,(Opportunities!O14)/Assumptions!$B$11)*(1-Assumptions!$B$12) -> 0
A12: =Opportunities!B15 | B12: =-Opportunities!L15 -> 0 | C12: =(Opportunities!C15*Opportunities!D15*12*Opportunities!I15*(1-Opportunities!J15)-Opportunities!K15)*(1+Assumptions!$B$10)^0*MAX(0,MIN(1,(1*12-(Opportunities!H15))/12)) -> 0 | D12: =(Opportunities!C15*Opportunities!D15*12*Opportunities!I15*(1-Opportunities!J15)-Opportunities!K15)*(1+Assumptions!$B$10)^1*MAX(0,MIN(1,(2*12-(Opportunities!H15))/12)) -> 0 | E12: =(Opportunities!C15*Opportunities!D15*12*Opportunities!I15*(1-Opportunities!J15)-Opportunities!K15)*(1+Assumptions!$B$10)^2*MAX(0,MIN(1,(3*12-(Opportunities!H15))/12)) -> 0 | F12: =(Opportunities!C15*Opportunities!D15*12*Opportunities!I15*(1-Opportunities!J15)-Opportunities!K15)*(1+Assumptions!$B$10)^3*MAX(0,MIN(1,(4*12-(Opportunities!H15))/12)) -> 0 | G12: =(Opportunities!C15*Opportunities!D15*12*Opportunities!I15*(1-Opportunities!J15)-Opportunities!K15)*(1+Assumptions!$B$10)^4*MAX(0,MIN(1,(5*12-(Opportunities!H15))/12)) -> 0 | H12: =(Opportunities!C15*Opportunities!D15*12*Opportunities!I15*(1-Opportunities!J15)-Opportunities!K15)*(1+Assumptions!$B$10)^5*MAX(0,MIN(1,(6*12-(Opportunities!H15))/12)) -> 0 | I12: =(Opportunities!C15*Opportunities!D15*12*Opportunities!I15*(1-Opportunities!J15)-Opportunities!K15)*(1+Assumptions!$B$10)^6*MAX(0,MIN(1,(7*12-(Opportunities!H15))/12)) -> 0 | J12: =(Opportunities!C15*Opportunities!D15*12*Opportunities!I15*(1-Opportunities!J15)-Opportunities!K15)*(1+Assumptions!$B$10)^7*MAX(0,MIN(1,(8*12-(Opportunities!H15))/12)) -> 0 | K12: =(Opportunities!C15*Opportunities!D15*12*Opportunities!I15*(1-Opportunities!J15)-Opportunities!K15)*(1+Assumptions!$B$10)^8*MAX(0,MIN(1,(9*12-(Opportunities!H15))/12)) -> 0 | L12: =(Opportunities!C15*Opportunities!D15*12*Opportunities!I15*(1-Opportunities!J15)-Opportunities!K15)*(1+Assumptions!$B$10)^9*MAX(0,MIN(1,(10*12-(Opportunities!H15))/12))+MAX(0,(Opportunities!O15)/Assumptions!$B$11)*(1-Assumptions!$B$12) -> 0
A17: Downside | B17: Year 0 | C17: Year 1 | D17: Year 2 | E17: Year 3 | F17: Year 4 | G17: Year 5 | H17: Year 6 | I17: Year 7 | J17: Year 8 | K17: Year 9 | L17: Year 10
A18: =Opportunities!B8 -> Illustrative conversion A | B18: =-Opportunities!L8-Opportunities!F8*(1+Assumptions!$B$14)*Assumptions!$B$17 -> -922400 | C18: =(Opportunities!C8*Opportunities!D8*12*Opportunities!I8*(1-Opportunities!J8)*(1-Assumptions!$B$15)-Opportunities!K8)*(1+Assumptions!$B$10)^0*MAX(0,MIN(1,(1*12-(Opportunities!H8+Assumptions!$B$16))/12)) -> 0 | D18: =(Opportunities!C8*Opportunities!D8*12*Opportunities!I8*(1-Opportunities!J8)*(1-Assumptions!$B$15)-Opportunities!K8)*(1+Assumptions!$B$10)^1*MAX(0,MIN(1,(2*12-(Opportunities!H8+Assumptions!$B$16))/12)) -> 28491.913 | E18: =(Opportunities!C8*Opportunities!D8*12*Opportunities!I8*(1-Opportunities!J8)*(1-Assumptions!$B$15)-Opportunities!K8)*(1+Assumptions!$B$10)^2*MAX(0,MIN(1,(3*12-(Opportunities!H8+Assumptions!$B$16))/12)) -> 58123.502 | F18: =(Opportunities!C8*Opportunities!D8*12*Opportunities!I8*(1-Opportunities!J8)*(1-Assumptions!$B$15)-Opportunities!K8)*(1+Assumptions!$B$10)^3*MAX(0,MIN(1,(4*12-(Opportunities!H8+Assumptions!$B$16))/12)) -> 59285.972 | G18: =(Opportunities!C8*Opportunities!D8*12*Opportunities!I8*(1-Opportunities!J8)*(1-Assumptions!$B$15)-Opportunities!K8)*(1+Assumptions!$B$10)^4*MAX(0,MIN(1,(5*12-(Opportunities!H8+Assumptions!$B$16))/12)) -> 60471.692 | H18: =(Opportunities!C8*Opportunities!D8*12*Opportunities!I8*(1-Opportunities!J8)*(1-Assumptions!$B$15)-Opportunities!K8)*(1+Assumptions!$B$10)^5*MAX(0,MIN(1,(6*12-(Opportunities!H8+Assumptions!$B$16))/12)) -> 61681.126 | I18: =(Opportunities!C8*Opportunities!D8*12*Opportunities!I8*(1-Opportunities!J8)*(1-Assumptions!$B$15)-Opportunities!K8)*(1+Assumptions!$B$10)^6*MAX(0,MIN(1,(7*12-(Opportunities!H8+Assumptions!$B$16))/12)) -> 62914.748 | J18: =(Opportunities!C8*Opportunities!D8*12*Opportunities!I8*(1-Opportunities!J8)*(1-Assumptions!$B$15)-Opportunities!K8)*(1+Assumptions!$B$10)^7*MAX(0,MIN(1,(8*12-(Opportunities!H8+Assumptions!$B$16))/12)) -> 64173.043 | K18: =(Opportunities!C8*Opportunities!D8*12*Opportunities!I8*(1-Opportunities!J8)*(1-Assumptions!$B$15)-Opportunities!K8)*(1+Assumptions!$B$10)^8*MAX(0,MIN(1,(9*12-(Opportunities!H8+Assumptions!$B$16))/12)) -> 65456.504 | L18: =(Opportunities!C8*Opportunities!D8*12*Opportunities!I8*(1-Opportunities!J8)*(1-Assumptions!$B$15)-Opportunities!K8)*(1+Assumptions!$B$10)^9*MAX(0,MIN(1,(10*12-(Opportunities!H8+Assumptions!$B$16))/12))+MAX(0,((Opportunities!C8*Opportunities!D8*12*Opportunities!I8*(1-Opportunities!J8)*(1-Assumptions!$B$15)-Opportunities!K8)*(1+Assumptions!$B$10)^10)/Assumptions!$B$11)*(1-Assumptions!$B$12) -> 1267818.7
A19: =Opportunities!B9 -> Illustrative renovation B | B19: =-Opportunities!L9-Opportunities!F9*(1+Assumptions!$B$14)*Assumptions!$B$17 -> -617200 | C19: =(Opportunities!C9*Opportunities!D9*12*Opportunities!I9*(1-Opportunities!J9)*(1-Assumptions!$B$15)-Opportunities!K9)*(1+Assumptions!$B$10)^0*MAX(0,MIN(1,(1*12-(Opportunities!H9+Assumptions!$B$16))/12)) -> 0 | D19: =(Opportunities!C9*Opportunities!D9*12*Opportunities!I9*(1-Opportunities!J9)*(1-Assumptions!$B$15)-Opportunities!K9)*(1+Assumptions!$B$10)^1*MAX(0,MIN(1,(2*12-(Opportunities!H9+Assumptions!$B$16))/12)) -> 37953.18 | E19: =(Opportunities!C9*Opportunities!D9*12*Opportunities!I9*(1-Opportunities!J9)*(1-Assumptions!$B$15)-Opportunities!K9)*(1+Assumptions!$B$10)^2*MAX(0,MIN(1,(3*12-(Opportunities!H9+Assumptions!$B$16))/12)) -> 38712.244 | F19: =(Opportunities!C9*Opportunities!D9*12*Opportunities!I9*(1-Opportunities!J9)*(1-Assumptions!$B$15)-Opportunities!K9)*(1+Assumptions!$B$10)^3*MAX(0,MIN(1,(4*12-(Opportunities!H9+Assumptions!$B$16))/12)) -> 39486.488 | G19: =(Opportunities!C9*Opportunities!D9*12*Opportunities!I9*(1-Opportunities!J9)*(1-Assumptions!$B$15)-Opportunities!K9)*(1+Assumptions!$B$10)^4*MAX(0,MIN(1,(5*12-(Opportunities!H9+Assumptions!$B$16))/12)) -> 40276.218 | H19: =(Opportunities!C9*Opportunities!D9*12*Opportunities!I9*(1-Opportunities!J9)*(1-Assumptions!$B$15)-Opportunities!K9)*(1+Assumptions!$B$10)^5*MAX(0,MIN(1,(6*12-(Opportunities!H9+Assumptions!$B$16))/12)) -> 41081.743 | I19: =(Opportunities!C9*Opportunities!D9*12*Opportunities!I9*(1-Opportunities!J9)*(1-Assumptions!$B$15)-Opportunities!K9)*(1+Assumptions!$B$10)^6*MAX(0,MIN(1,(7*12-(Opportunities!H9+Assumptions!$B$16))/12)) -> 41903.377 | J19: =(Opportunities!C9*Opportunities!D9*12*Opportunities!I9*(1-Opportunities!J9)*(1-Assumptions!$B$15)-Opportunities!K9)*(1+Assumptions!$B$10)^7*MAX(0,MIN(1,(8*12-(Opportunities!H9+Assumptions!$B$16))/12)) -> 42741.445 | K19: =(Opportunities!C9*Opportunities!D9*12*Opportunities!I9*(1-Opportunities!J9)*(1-Assumptions!$B$15)-Opportunities!K9)*(1+Assumptions!$B$10)^8*MAX(0,MIN(1,(9*12-(Opportunities!H9+Assumptions!$B$16))/12)) -> 43596.274 | L19: =(Opportunities!C9*Opportunities!D9*12*Opportunities!I9*(1-Opportunities!J9)*(1-Assumptions!$B$15)-Opportunities!K9)*(1+Assumptions!$B$10)^9*MAX(0,MIN(1,(10*12-(Opportunities!H9+Assumptions!$B$16))/12))+MAX(0,((Opportunities!C9*Opportunities!D9*12*Opportunities!I9*(1-Opportunities!J9)*(1-Assumptions!$B$15)-Opportunities!K9)*(1+Assumptions!$B$10)^10)/Assumptions!$B$11)*(1-Assumptions!$B$12) -> 844410.68
A20: =Opportunities!B10 -> Illustrative new build C | B20: =-Opportunities!L10-Opportunities!F10*(1+Assumptions!$B$14)*Assumptions!$B$17 -> -1723600 | C20: =(Opportunities!C10*Opportunities!D10*12*Opportunities!I10*(1-Opportunities!J10)*(1-Assumptions!$B$15)-Opportunities!K10)*(1+Assumptions!$B$10)^0*MAX(0,MIN(1,(1*12-(Opportunities!H10+Assumptions!$B$16))/12)) -> 0 | D20: =(Opportunities!C10*Opportunities!D10*12*Opportunities!I10*(1-Opportunities!J10)*(1-Assumptions!$B$15)-Opportunities!K10)*(1+Assumptions!$B$10)^1*MAX(0,MIN(1,(2*12-(Opportunities!H10+Assumptions!$B$16))/12)) -> 0 | E20: =(Opportunities!C10*Opportunities!D10*12*Opportunities!I10*(1-Opportunities!J10)*(1-Assumptions!$B$15)-Opportunities!K10)*(1+Assumptions!$B$10)^2*MAX(0,MIN(1,(3*12-(Opportunities!H10+Assumptions!$B$16))/12)) -> 0 | F20: =(Opportunities!C10*Opportunities!D10*12*Opportunities!I10*(1-Opportunities!J10)*(1-Assumptions!$B$15)-Opportunities!K10)*(1+Assumptions!$B$10)^3*MAX(0,MIN(1,(4*12-(Opportunities!H10+Assumptions!$B$16))/12)) -> 110444.26 | G20: =(Opportunities!C10*Opportunities!D10*12*Opportunities!I10*(1-Opportunities!J10)*(1-Assumptions!$B$15)-Opportunities!K10)*(1+Assumptions!$B$10)^4*MAX(0,MIN(1,(5*12-(Opportunities!H10+Assumptions!$B$16))/12)) -> 112653.15 | H20: =(Opportunities!C10*Opportunities!D10*12*Opportunities!I10*(1-Opportunities!J10)*(1-Assumptions!$B$15)-Opportunities!K10)*(1+Assumptions!$B$10)^5*MAX(0,MIN(1,(6*12-(Opportunities!H10+Assumptions!$B$16))/12)) -> 114906.21 | I20: =(Opportunities!C10*Opportunities!D10*12*Opportunities!I10*(1-Opportunities!J10)*(1-Assumptions!$B$15)-Opportunities!K10)*(1+Assumptions!$B$10)^6*MAX(0,MIN(1,(7*12-(Opportunities!H10+Assumptions!$B$16))/12)) -> 117204.33 | J20: =(Opportunities!C10*Opportunities!D10*12*Opportunities!I10*(1-Opportunities!J10)*(1-Assumptions!$B$15)-Opportunities!K10)*(1+Assumptions!$B$10)^7*MAX(0,MIN(1,(8*12-(Opportunities!H10+Assumptions!$B$16))/12)) -> 119548.42 | K20: =(Opportunities!C10*Opportunities!D10*12*Opportunities!I10*(1-Opportunities!J10)*(1-Assumptions!$B$15)-Opportunities!K10)*(1+Assumptions!$B$10)^8*MAX(0,MIN(1,(9*12-(Opportunities!H10+Assumptions!$B$16))/12)) -> 121939.39 | L20: =(Opportunities!C10*Opportunities!D10*12*Opportunities!I10*(1-Opportunities!J10)*(1-Assumptions!$B$15)-Opportunities!K10)*(1+Assumptions!$B$10)^9*MAX(0,MIN(1,(10*12-(Opportunities!H10+Assumptions!$B$16))/12))+MAX(0,((Opportunities!C10*Opportunities!D10*12*Opportunities!I10*(1-Opportunities!J10)*(1-Assumptions!$B$15)-Opportunities!K10)*(1+Assumptions!$B$10)^10)/Assumptions!$B$11)*(1-Assumptions!$B$12) -> 2361828.5
A21: =Opportunities!B11 -> Illustrative small asset D | B21: =-Opportunities!L11-Opportunities!F11*(1+Assumptions!$B$14)*Assumptions!$B$17 -> -349500 | C21: =(Opportunities!C11*Opportunities!D11*12*Opportunities!I11*(1-Opportunities!J11)*(1-Assumptions!$B$15)-Opportunities!K11)*(1+Assumptions!$B$10)^0*MAX(0,MIN(1,(1*12-(Opportunities!H11+Assumptions!$B$16))/12)) -> 3265.6965 | D21: =(Opportunities!C11*Opportunities!D11*12*Opportunities!I11*(1-Opportunities!J11)*(1-Assumptions!$B$15)-Opportunities!K11)*(1+Assumptions!$B$10)^1*MAX(0,MIN(1,(2*12-(Opportunities!H11+Assumptions!$B$16))/12)) -> 19986.063 | E21: =(Opportunities!C11*Opportunities!D11*12*Opportunities!I11*(1-Opportunities!J11)*(1-Assumptions!$B$15)-Opportunities!K11)*(1+Assumptions!$B$10)^2*MAX(0,MIN(1,(3*12-(Opportunities!H11+Assumptions!$B$16))/12)) -> 20385.784 | F21: =(Opportunities!C11*Opportunities!D11*12*Opportunities!I11*(1-Opportunities!J11)*(1-Assumptions!$B$15)-Opportunities!K11)*(1+Assumptions!$B$10)^3*MAX(0,MIN(1,(4*12-(Opportunities!H11+Assumptions!$B$16))/12)) -> 20793.5 | G21: =(Opportunities!C11*Opportunities!D11*12*Opportunities!I11*(1-Opportunities!J11)*(1-Assumptions!$B$15)-Opportunities!K11)*(1+Assumptions!$B$10)^4*MAX(0,MIN(1,(5*12-(Opportunities!H11+Assumptions!$B$16))/12)) -> 21209.37 | H21: =(Opportunities!C11*Opportunities!D11*12*Opportunities!I11*(1-Opportunities!J11)*(1-Assumptions!$B$15)-Opportunities!K11)*(1+Assumptions!$B$10)^5*MAX(0,MIN(1,(6*12-(Opportunities!H11+Assumptions!$B$16))/12)) -> 21633.557 | I21: =(Opportunities!C11*Opportunities!D11*12*Opportunities!I11*(1-Opportunities!J11)*(1-Assumptions!$B$15)-Opportunities!K11)*(1+Assumptions!$B$10)^6*MAX(0,MIN(1,(7*12-(Opportunities!H11+Assumptions!$B$16))/12)) -> 22066.228 | J21: =(Opportunities!C11*Opportunities!D11*12*Opportunities!I11*(1-Opportunities!J11)*(1-Assumptions!$B$15)-Opportunities!K11)*(1+Assumptions!$B$10)^7*MAX(0,MIN(1,(8*12-(Opportunities!H11+Assumptions!$B$16))/12)) -> 22507.553 | K21: =(Opportunities!C11*Opportunities!D11*12*Opportunities!I11*(1-Opportunities!J11)*(1-Assumptions!$B$15)-Opportunities!K11)*(1+Assumptions!$B$10)^8*MAX(0,MIN(1,(9*12-(Opportunities!H11+Assumptions!$B$16))/12)) -> 22957.704 | L21: =(Opportunities!C11*Opportunities!D11*12*Opportunities!I11*(1-Opportunities!J11)*(1-Assumptions!$B$15)-Opportunities!K11)*(1+Assumptions!$B$10)^9*MAX(0,MIN(1,(10*12-(Opportunities!H11+Assumptions!$B$16))/12))+MAX(0,((Opportunities!C11*Opportunities!D11*12*Opportunities!I11*(1-Opportunities!J11)*(1-Assumptions!$B$15)-Opportunities!K11)*(1+Assumptions!$B$10)^10)/Assumptions!$B$11)*(1-Assumptions!$B$12) -> 444664.84
A22: =Opportunities!B12 -> Illustrative delayed asset E | B22: =-Opportunities!L12-Opportunities!F12*(1+Assumptions!$B$14)*Assumptions!$B$17 -> -1225800 | C22: =(Opportunities!C12*Opportunities!D12*12*Opportunities!I12*(1-Opportunities!J12)*(1-Assumptions!$B$15)-Opportunities!K12)*(1+Assumptions!$B$10)^0*MAX(0,MIN(1,(1*12-(Opportunities!H12+Assumptions!$B$16))/12)) -> 0 | D22: =(Opportunities!C12*Opportunities!D12*12*Opportunities!I12*(1-Opportunities!J12)*(1-Assumptions!$B$15)-Opportunities!K12)*(1+Assumptions!$B$10)^1*MAX(0,MIN(1,(2*12-(Opportunities!H12+Assumptions!$B$16))/12)) -> 0 | E22: =(Opportunities!C12*Opportunities!D12*12*Opportunities!I12*(1-Opportunities!J12)*(1-Assumptions!$B$15)-Opportunities!K12)*(1+Assumptions!$B$10)^2*MAX(0,MIN(1,(3*12-(Opportunities!H12+Assumptions!$B$16))/12)) -> 0 | F22: =(Opportunities!C12*Opportunities!D12*12*Opportunities!I12*(1-Opportunities!J12)*(1-Assumptions!$B$15)-Opportunities!K12)*(1+Assumptions!$B$10)^3*MAX(0,MIN(1,(4*12-(Opportunities!H12+Assumptions!$B$16))/12)) -> 0 | G22: =(Opportunities!C12*Opportunities!D12*12*Opportunities!I12*(1-Opportunities!J12)*(1-Assumptions!$B$15)-Opportunities!K12)*(1+Assumptions!$B$10)^4*MAX(0,MIN(1,(5*12-(Opportunities!H12+Assumptions!$B$16))/12)) -> 70460.965 | H22: =(Opportunities!C12*Opportunities!D12*12*Opportunities!I12*(1-Opportunities!J12)*(1-Assumptions!$B$15)-Opportunities!K12)*(1+Assumptions!$B$10)^5*MAX(0,MIN(1,(6*12-(Opportunities!H12+Assumptions!$B$16))/12)) -> 71870.184 | I22: =(Opportunities!C12*Opportunities!D12*12*Opportunities!I12*(1-Opportunities!J12)*(1-Assumptions!$B$15)-Opportunities!K12)*(1+Assumptions!$B$10)^6*MAX(0,MIN(1,(7*12-(Opportunities!H12+Assumptions!$B$16))/12)) -> 73307.588 | J22: =(Opportunities!C12*Opportunities!D12*12*Opportunities!I12*(1-Opportunities!J12)*(1-Assumptions!$B$15)-Opportunities!K12)*(1+Assumptions!$B$10)^7*MAX(0,MIN(1,(8*12-(Opportunities!H12+Assumptions!$B$16))/12)) -> 74773.739 | K22: =(Opportunities!C12*Opportunities!D12*12*Opportunities!I12*(1-Opportunities!J12)*(1-Assumptions!$B$15)-Opportunities!K12)*(1+Assumptions!$B$10)^8*MAX(0,MIN(1,(9*12-(Opportunities!H12+Assumptions!$B$16))/12)) -> 76269.214 | L22: =(Opportunities!C12*Opportunities!D12*12*Opportunities!I12*(1-Opportunities!J12)*(1-Assumptions!$B$15)-Opportunities!K12)*(1+Assumptions!$B$10)^9*MAX(0,MIN(1,(10*12-(Opportunities!H12+Assumptions!$B$16))/12))+MAX(0,((Opportunities!C12*Opportunities!D12*12*Opportunities!I12*(1-Opportunities!J12)*(1-Assumptions!$B$15)-Opportunities!K12)*(1+Assumptions!$B$10)^10)/Assumptions!$B$11)*(1-Assumptions!$B$12) -> 1477248.7
A23: =Opportunities!B13 -> Illustrative compliance failure F | B23: =-Opportunities!L13-Opportunities!F13*(1+Assumptions!$B$14)*Assumptions!$B$17 -> -839500 | C23: =(Opportunities!C13*Opportunities!D13*12*Opportunities!I13*(1-Opportunities!J13)*(1-Assumptions!$B$15)-Opportunities!K13)*(1+Assumptions!$B$10)^0*MAX(0,MIN(1,(1*12-(Opportunities!H13+Assumptions!$B$16))/12)) -> 0 | D23: =(Opportunities!C13*Opportunities!D13*12*Opportunities!I13*(1-Opportunities!J13)*(1-Assumptions!$B$15)-Opportunities!K13)*(1+Assumptions!$B$10)^1*MAX(0,MIN(1,(2*12-(Opportunities!H13+Assumptions!$B$16))/12)) -> 42293.443 | E23: =(Opportunities!C13*Opportunities!D13*12*Opportunities!I13*(1-Opportunities!J13)*(1-Assumptions!$B$15)-Opportunities!K13)*(1+Assumptions!$B$10)^2*MAX(0,MIN(1,(3*12-(Opportunities!H13+Assumptions!$B$16))/12)) -> 51767.174 | F23: =(Opportunities!C13*Opportunities!D13*12*Opportunities!I13*(1-Opportunities!J13)*(1-Assumptions!$B$15)-Opportunities!K13)*(1+Assumptions!$B$10)^3*MAX(0,MIN(1,(4*12-(Opportunities!H13+Assumptions!$B$16))/12)) -> 52802.518 | G23: =(Opportunities!C13*Opportunities!D13*12*Opportunities!I13*(1-Opportunities!J13)*(1-Assumptions!$B$15)-Opportunities!K13)*(1+Assumptions!$B$10)^4*MAX(0,MIN(1,(5*12-(Opportunities!H13+Assumptions!$B$16))/12)) -> 53858.568 | H23: =(Opportunities!C13*Opportunities!D13*12*Opportunities!I13*(1-Opportunities!J13)*(1-Assumptions!$B$15)-Opportunities!K13)*(1+Assumptions!$B$10)^5*MAX(0,MIN(1,(6*12-(Opportunities!H13+Assumptions!$B$16))/12)) -> 54935.74 | I23: =(Opportunities!C13*Opportunities!D13*12*Opportunities!I13*(1-Opportunities!J13)*(1-Assumptions!$B$15)-Opportunities!K13)*(1+Assumptions!$B$10)^6*MAX(0,MIN(1,(7*12-(Opportunities!H13+Assumptions!$B$16))/12)) -> 56034.454 | J23: =(Opportunities!C13*Opportunities!D13*12*Opportunities!I13*(1-Opportunities!J13)*(1-Assumptions!$B$15)-Opportunities!K13)*(1+Assumptions!$B$10)^7*MAX(0,MIN(1,(8*12-(Opportunities!H13+Assumptions!$B$16))/12)) -> 57155.144 | K23: =(Opportunities!C13*Opportunities!D13*12*Opportunities!I13*(1-Opportunities!J13)*(1-Assumptions!$B$15)-Opportunities!K13)*(1+Assumptions!$B$10)^8*MAX(0,MIN(1,(9*12-(Opportunities!H13+Assumptions!$B$16))/12)) -> 58298.246 | L23: =(Opportunities!C13*Opportunities!D13*12*Opportunities!I13*(1-Opportunities!J13)*(1-Assumptions!$B$15)-Opportunities!K13)*(1+Assumptions!$B$10)^9*MAX(0,MIN(1,(10*12-(Opportunities!H13+Assumptions!$B$16))/12))+MAX(0,((Opportunities!C13*Opportunities!D13*12*Opportunities!I13*(1-Opportunities!J13)*(1-Assumptions!$B$15)-Opportunities!K13)*(1+Assumptions!$B$10)^10)/Assumptions!$B$11)*(1-Assumptions!$B$12) -> 1129171.3
A24: =Opportunities!B14 | B24: =-Opportunities!L14-Opportunities!F14*(1+Assumptions!$B$14)*Assumptions!$B$17 -> 0 | C24: =(Opportunities!C14*Opportunities!D14*12*Opportunities!I14*(1-Opportunities!J14)*(1-Assumptions!$B$15)-Opportunities!K14)*(1+Assumptions!$B$10)^0*MAX(0,MIN(1,(1*12-(Opportunities!H14+Assumptions!$B$16))/12)) -> 0 | D24: =(Opportunities!C14*Opportunities!D14*12*Opportunities!I14*(1-Opportunities!J14)*(1-Assumptions!$B$15)-Opportunities!K14)*(1+Assumptions!$B$10)^1*MAX(0,MIN(1,(2*12-(Opportunities!H14+Assumptions!$B$16))/12)) -> 0 | E24: =(Opportunities!C14*Opportunities!D14*12*Opportunities!I14*(1-Opportunities!J14)*(1-Assumptions!$B$15)-Opportunities!K14)*(1+Assumptions!$B$10)^2*MAX(0,MIN(1,(3*12-(Opportunities!H14+Assumptions!$B$16))/12)) -> 0 | F24: =(Opportunities!C14*Opportunities!D14*12*Opportunities!I14*(1-Opportunities!J14)*(1-Assumptions!$B$15)-Opportunities!K14)*(1+Assumptions!$B$10)^3*MAX(0,MIN(1,(4*12-(Opportunities!H14+Assumptions!$B$16))/12)) -> 0 | G24: =(Opportunities!C14*Opportunities!D14*12*Opportunities!I14*(1-Opportunities!J14)*(1-Assumptions!$B$15)-Opportunities!K14)*(1+Assumptions!$B$10)^4*MAX(0,MIN(1,(5*12-(Opportunities!H14+Assumptions!$B$16))/12)) -> 0 | H24: =(Opportunities!C14*Opportunities!D14*12*Opportunities!I14*(1-Opportunities!J14)*(1-Assumptions!$B$15)-Opportunities!K14)*(1+Assumptions!$B$10)^5*MAX(0,MIN(1,(6*12-(Opportunities!H14+Assumptions!$B$16))/12)) -> 0 | I24: =(Opportunities!C14*Opportunities!D14*12*Opportunities!I14*(1-Opportunities!J14)*(1-Assumptions!$B$15)-Opportunities!K14)*(1+Assumptions!$B$10)^6*MAX(0,MIN(1,(7*12-(Opportunities!H14+Assumptions!$B$16))/12)) -> 0 | J24: =(Opportunities!C14*Opportunities!D14*12*Opportunities!I14*(1-Opportunities!J14)*(1-Assumptions!$B$15)-Opportunities!K14)*(1+Assumptions!$B$10)^7*MAX(0,MIN(1,(8*12-(Opportunities!H14+Assumptions!$B$16))/12)) -> 0 | K24: =(Opportunities!C14*Opportunities!D14*12*Opportunities!I14*(1-Opportunities!J14)*(1-Assumptions!$B$15)-Opportunities!K14)*(1+Assumptions!$B$10)^8*MAX(0,MIN(1,(9*12-(Opportunities!H14+Assumptions!$B$16))/12)) -> 0 | L24: =(Opportunities!C14*Opportunities!D14*12*Opportunities!I14*(1-Opportunities!J14)*(1-Assumptions!$B$15)-Opportunities!K14)*(1+Assumptions!$B$10)^9*MAX(0,MIN(1,(10*12-(Opportunities!H14+Assumptions!$B$16))/12))+MAX(0,((Opportunities!C14*Opportunities!D14*12*Opportunities!I14*(1-Opportunities!J14)*(1-Assumptions!$B$15)-Opportunities!K14)*(1+Assumptions!$B$10)^10)/Assumptions!$B$11)*(1-Assumptions!$B$12) -> 0
A25: =Opportunities!B15 | B25: =-Opportunities!L15-Opportunities!F15*(1+Assumptions!$B$14)*Assumptions!$B$17 -> 0 | C25: =(Opportunities!C15*Opportunities!D15*12*Opportunities!I15*(1-Opportunities!J15)*(1-Assumptions!$B$15)-Opportunities!K15)*(1+Assumptions!$B$10)^0*MAX(0,MIN(1,(1*12-(Opportunities!H15+Assumptions!$B$16))/12)) -> 0 | D25: =(Opportunities!C15*Opportunities!D15*12*Opportunities!I15*(1-Opportunities!J15)*(1-Assumptions!$B$15)-Opportunities!K15)*(1+Assumptions!$B$10)^1*MAX(0,MIN(1,(2*12-(Opportunities!H15+Assumptions!$B$16))/12)) -> 0 | E25: =(Opportunities!C15*Opportunities!D15*12*Opportunities!I15*(1-Opportunities!J15)*(1-Assumptions!$B$15)-Opportunities!K15)*(1+Assumptions!$B$10)^2*MAX(0,MIN(1,(3*12-(Opportunities!H15+Assumptions!$B$16))/12)) -> 0 | F25: =(Opportunities!C15*Opportunities!D15*12*Opportunities!I15*(1-Opportunities!J15)*(1-Assumptions!$B$15)-Opportunities!K15)*(1+Assumptions!$B$10)^3*MAX(0,MIN(1,(4*12-(Opportunities!H15+Assumptions!$B$16))/12)) -> 0 | G25: =(Opportunities!C15*Opportunities!D15*12*Opportunities!I15*(1-Opportunities!J15)*(1-Assumptions!$B$15)-Opportunities!K15)*(1+Assumptions!$B$10)^4*MAX(0,MIN(1,(5*12-(Opportunities!H15+Assumptions!$B$16))/12)) -> 0 | H25: =(Opportunities!C15*Opportunities!D15*12*Opportunities!I15*(1-Opportunities!J15)*(1-Assumptions!$B$15)-Opportunities!K15)*(1+Assumptions!$B$10)^5*MAX(0,MIN(1,(6*12-(Opportunities!H15+Assumptions!$B$16))/12)) -> 0 | I25: =(Opportunities!C15*Opportunities!D15*12*Opportunities!I15*(1-Opportunities!J15)*(1-Assumptions!$B$15)-Opportunities!K15)*(1+Assumptions!$B$10)^6*MAX(0,MIN(1,(7*12-(Opportunities!H15+Assumptions!$B$16))/12)) -> 0 | J25: =(Opportunities!C15*Opportunities!D15*12*Opportunities!I15*(1-Opportunities!J15)*(1-Assumptions!$B$15)-Opportunities!K15)*(1+Assumptions!$B$10)^7*MAX(0,MIN(1,(8*12-(Opportunities!H15+Assumptions!$B$16))/12)) -> 0 | K25: =(Opportunities!C15*Opportunities!D15*12*Opportunities!I15*(1-Opportunities!J15)*(1-Assumptions!$B$15)-Opportunities!K15)*(1+Assumptions!$B$10)^8*MAX(0,MIN(1,(9*12-(Opportunities!H15+Assumptions!$B$16))/12)) -> 0 | L25: =(Opportunities!C15*Opportunities!D15*12*Opportunities!I15*(1-Opportunities!J15)*(1-Assumptions!$B$15)-Opportunities!K15)*(1+Assumptions!$B$10)^9*MAX(0,MIN(1,(10*12-(Opportunities!H15+Assumptions!$B$16))/12))+MAX(0,((Opportunities!C15*Opportunities!D15*12*Opportunities!I15*(1-Opportunities!J15)*(1-Assumptions!$B$15)-Opportunities!K15)*(1+Assumptions!$B$10)^10)/Assumptions!$B$11)*(1-Assumptions!$B$12) -> 0

Sheet Portfolio
A1: Portfolio optimization | exact enumeration
A2: 256 subsets of eight projects. Maximize aggregate NPV subject to capital, project count and compliance.
A4: Subset | B4: Select 1 | C4: Select 2 | D4: Select 3 | E4: Select 4 | F4: Select 5 | G4: Select 6 | H4: Select 7 | I4: Select 8 | J4: Capital | K4: Projects | L4: NPV | M4: Feasible | N4: Objective
A5: 0 | B5: 0 | C5: 0 | D5: 0 | E5: 0 | F5: 0 | G5: 0 | H5: 0 | I5: 0 | J5: =B5*Opportunities!L8+C5*Opportunities!L9+D5*Opportunities!L10+E5*Opportunities!L11+F5*Opportunities!L12+G5*Opportunities!L13+H5*Opportunities!L14+I5*Opportunities!L15 -> 0 | K5: =SUM(B5:I5) -> 0 | L5: =B5*Opportunities!P8+C5*Opportunities!P9+D5*Opportunities!P10+E5*Opportunities!P11+F5*Opportunities!P12+G5*Opportunities!P13+H5*Opportunities!P14+I5*Opportunities!P15 -> 0 | M5: =IF(AND(J5<=Assumptions!$B$6,K5<=Assumptions!$B$7,B5*IF(Opportunities!S8="ELIGIBLE",0,1)+C5*IF(Opportunities!S9="ELIGIBLE",0,1)+D5*IF(Opportunities!S10="ELIGIBLE",0,1)+E5*IF(Opportunities!S11="ELIGIBLE",0,1)+F5*IF(Opportunities!S12="ELIGIBLE",0,1)+G5*IF(Opportunities!S13="ELIGIBLE",0,1)+H5*IF(Opportunities!S14="ELIGIBLE",0,1)+I5*IF(Opportunities!S15="ELIGIBLE",0,1)=0),1,0) -> 1 | N5: =IF(M5=1,L5,-1E99) -> 0
A6: 1 | B6: 1 | C6: 0 | D6: 0 | E6: 0 | F6: 0 | G6: 0 | H6: 0 | I6: 0 | J6: =B6*Opportunities!L8+C6*Opportunities!L9+D6*Opportunities!L10+E6*Opportunities!L11+F6*Opportunities!L12+G6*Opportunities!L13+H6*Opportunities!L14+I6*Opportunities!L15 -> 869500 | K6: =SUM(B6:I6) -> 1 | L6: =B6*Opportunities!P8+C6*Opportunities!P9+D6*Opportunities!P10+E6*Opportunities!P11+F6*Opportunities!P12+G6*Opportunities!P13+H6*Opportunities!P14+I6*Opportunities!P15 -> 90896.517 | M6: =IF(AND(J6<=Assumptions!$B$6,K6<=Assumptions!$B$7,B6*IF(Opportunities!S8="ELIGIBLE",0,1)+C6*IF(Opportunities!S9="ELIGIBLE",0,1)+D6*IF(Opportunities!S10="ELIGIBLE",0,1)+E6*IF(Opportunities!S11="ELIGIBLE",0,1)+F6*IF(Opportunities!S12="ELIGIBLE",0,1)+G6*IF(Opportunities!S13="ELIGIBLE",0,1)+H6*IF(Opportunities!S14="ELIGIBLE",0,1)+I6*IF(Opportunities!S15="ELIGIBLE",0,1)=0),1,0) -> 1 | N6: =IF(M6=1,L6,-1E99) -> 90896.517
A7: 2 | B7: 0 | C7: 1 | D7: 0 | E7: 0 | F7: 0 | G7: 0 | H7: 0 | I7: 0 | J7: =B7*Opportunities!L8+C7*Opportunities!L9+D7*Opportunities!L10+E7*Opportunities!L11+F7*Opportunities!L12+G7*Opportunities!L13+H7*Opportunities!L14+I7*Opportunities!L15 -> 585000 | K7: =SUM(B7:I7) -> 1 | L7: =B7*Opportunities!P8+C7*Opportunities!P9+D7*Opportunities!P10+E7*Opportunities!P11+F7*Opportunities!P12+G7*Opportunities!P13+H7*Opportunities!P14+I7*Opportunities!P15 -> 76128.402 | M7: =IF(AND(J7<=Assumptions!$B$6,K7<=Assumptions!$B$7,B7*IF(Opportunities!S8="ELIGIBLE",0,1)+C7*IF(Opportunities!S9="ELIGIBLE",0,1)+D7*IF(Opportunities!S10="ELIGIBLE",0,1)+E7*IF(Opportunities!S11="ELIGIBLE",0,1)+F7*IF(Opportunities!S12="ELIGIBLE",0,1)+G7*IF(Opportunities!S13="ELIGIBLE",0,1)+H7*IF(Opportunities!S14="ELIGIBLE",0,1)+I7*IF(Opportunities!S15="ELIGIBLE",0,1)=0),1,0) -> 1 | N7: =IF(M7=1,L7,-1E99) -> 76128.402
A8: 3 | B8: 1 | C8: 1 | D8: 0 | E8: 0 | F8: 0 | G8: 0 | H8: 0 | I8: 0 | J8: =B8*Opportunities!L8+C8*Opportunities!L9+D8*Opportunities!L10+E8*Opportunities!L11+F8*Opportunities!L12+G8*Opportunities!L13+H8*Opportunities!L14+I8*Opportunities!L15 -> 1454500 | K8: =SUM(B8:I8) -> 2 | L8: =B8*Opportunities!P8+C8*Opportunities!P9+D8*Opportunities!P10+E8*Opportunities!P11+F8*Opportunities!P12+G8*Opportunities!P13+H8*Opportunities!P14+I8*Opportunities!P15 -> 167024.92 | M8: =IF(AND(J8<=Assumptions!$B$6,K8<=Assumptions!$B$7,B8*IF(Opportunities!S8="ELIGIBLE",0,1)+C8*IF(Opportunities!S9="ELIGIBLE",0,1)+D8*IF(Opportunities!S10="ELIGIBLE",0,1)+E8*IF(Opportunities!S11="ELIGIBLE",0,1)+F8*IF(Opportunities!S12="ELIGIBLE",0,1)+G8*IF(Opportunities!S13="ELIGIBLE",0,1)+H8*IF(Opportunities!S14="ELIGIBLE",0,1)+I8*IF(Opportunities!S15="ELIGIBLE",0,1)=0),1,0) -> 1 | N8: =IF(M8=1,L8,-1E99) -> 167024.92
A9: 4 | B9: 0 | C9: 0 | D9: 1 | E9: 0 | F9: 0 | G9: 0 | H9: 0 | I9: 0 | J9: =B9*Opportunities!L8+C9*Opportunities!L9+D9*Opportunities!L10+E9*Opportunities!L11+F9*Opportunities!L12+G9*Opportunities!L13+H9*Opportunities!L14+I9*Opportunities!L15 -> 1581000 | K9: =SUM(B9:I9) -> 1 | L9: =B9*Opportunities!P8+C9*Opportunities!P9+D9*Opportunities!P10+E9*Opportunities!P11+F9*Opportunities!P12+G9*Opportunities!P13+H9*Opportunities!P14+I9*Opportunities!P15 -> 54783.715 | M9: =IF(AND(J9<=Assumptions!$B$6,K9<=Assumptions!$B$7,B9*IF(Opportunities!S8="ELIGIBLE",0,1)+C9*IF(Opportunities!S9="ELIGIBLE",0,1)+D9*IF(Opportunities!S10="ELIGIBLE",0,1)+E9*IF(Opportunities!S11="ELIGIBLE",0,1)+F9*IF(Opportunities!S12="ELIGIBLE",0,1)+G9*IF(Opportunities!S13="ELIGIBLE",0,1)+H9*IF(Opportunities!S14="ELIGIBLE",0,1)+I9*IF(Opportunities!S15="ELIGIBLE",0,1)=0),1,0) -> 1 | N9: =IF(M9=1,L9,-1E99) -> 54783.715
A10: 5 | B10: 1 | C10: 0 | D10: 1 | E10: 0 | F10: 0 | G10: 0 | H10: 0 | I10: 0 | J10: =B10*Opportunities!L8+C10*Opportunities!L9+D10*Opportunities!L10+E10*Opportunities!L11+F10*Opportunities!L12+G10*Opportunities!L13+H10*Opportunities!L14+I10*Opportunities!L15 -> 2450500 | K10: =SUM(B10:I10) -> 2 | L10: =B10*Opportunities!P8+C10*Opportunities!P9+D10*Opportunities!P10+E10*Opportunities!P11+F10*Opportunities!P12+G10*Opportunities!P13+H10*Opportunities!P14+I10*Opportunities!P15 -> 145680.23 | M10: =IF(AND(J10<=Assumptions!$B$6,K10<=Assumptions!$B$7,B10*IF(Opportunities!S8="ELIGIBLE",0,1)+C10*IF(Opportunities!S9="ELIGIBLE",0,1)+D10*IF(Opportunities!S10="ELIGIBLE",0,1)+E10*IF(Opportunities!S11="ELIGIBLE",0,1)+F10*IF(Opportunities!S12="ELIGIBLE",0,1)+G10*IF(Opportunities!S13="ELIGIBLE",0,1)+H10*IF(Opportunities!S14="ELIGIBLE",0,1)+I10*IF(Opportunities!S15="ELIGIBLE",0,1)=0),1,0) -> 0 | N10: =IF(M10=1,L10,-1E99) -> -1e+99
A11: 6 | B11: 0 | C11: 1 | D11: 1 | E11: 0 | F11: 0 | G11: 0 | H11: 0 | I11: 0 | J11: =B11*Opportunities!L8+C11*Opportunities!L9+D11*Opportunities!L10+E11*Opportunities!L11+F11*Opportunities!L12+G11*Opportunities!L13+H11*Opportunities!L14+I11*Opportunities!L15 -> 2166000 | K11: =SUM(B11:I11) -> 2 | L11: =B11*Opportunities!P8+C11*Opportunities!P9+D11*Opportunities!P10+E11*Opportunities!P11+F11*Opportunities!P12+G11*Opportunities!P13+H11*Opportunities!P14+I11*Opportunities!P15 -> 130912.12 | M11: =IF(AND(J11<=Assumptions!$B$6,K11<=Assumptions!$B$7,B11*IF(Opportunities!S8="ELIGIBLE",0,1)+C11*IF(Opportunities!S9="ELIGIBLE",0,1)+D11*IF(Opportunities!S10="ELIGIBLE",0,1)+E11*IF(Opportunities!S11="ELIGIBLE",0,1)+F11*IF(Opportunities!S12="ELIGIBLE",0,1)+G11*IF(Opportunities!S13="ELIGIBLE",0,1)+H11*IF(Opportunities!S14="ELIGIBLE",0,1)+I11*IF(Opportunities!S15="ELIGIBLE",0,1)=0),1,0) -> 0 | N11: =IF(M11=1,L11,-1E99) -> -1e+99
A12: 7 | B12: 1 | C12: 1 | D12: 1 | E12: 0 | F12: 0 | G12: 0 | H12: 0 | I12: 0 | J12: =B12*Opportunities!L8+C12*Opportunities!L9+D12*Opportunities!L10+E12*Opportunities!L11+F12*Opportunities!L12+G12*Opportunities!L13+H12*Opportunities!L14+I12*Opportunities!L15 -> 3035500 | K12: =SUM(B12:I12) -> 3 | L12: =B12*Opportunities!P8+C12*Opportunities!P9+D12*Opportunities!P10+E12*Opportunities!P11+F12*Opportunities!P12+G12*Opportunities!P13+H12*Opportunities!P14+I12*Opportunities!P15 -> 221808.63 | M12: =IF(AND(J12<=Assumptions!$B$6,K12<=Assumptions!$B$7,B12*IF(Opportunities!S8="ELIGIBLE",0,1)+C12*IF(Opportunities!S9="ELIGIBLE",0,1)+D12*IF(Opportunities!S10="ELIGIBLE",0,1)+E12*IF(Opportunities!S11="ELIGIBLE",0,1)+F12*IF(Opportunities!S12="ELIGIBLE",0,1)+G12*IF(Opportunities!S13="ELIGIBLE",0,1)+H12*IF(Opportunities!S14="ELIGIBLE",0,1)+I12*IF(Opportunities!S15="ELIGIBLE",0,1)=0),1,0) -> 0 | N12: =IF(M12=1,L12,-1E99) -> -1e+99
A13: 8 | B13: 0 | C13: 0 | D13: 0 | E13: 1 | F13: 0 | G13: 0 | H13: 0 | I13: 0 | J13: =B13*Opportunities!L8+C13*Opportunities!L9+D13*Opportunities!L10+E13*Opportunities!L11+F13*Opportunities!L12+G13*Opportunities!L13+H13*Opportunities!L14+I13*Opportunities!L15 -> 332250 | K13: =SUM(B13:I13) -> 1 | L13: =B13*Opportunities!P8+C13*Opportunities!P9+D13*Opportunities!P10+E13*Opportunities!P11+F13*Opportunities!P12+G13*Opportunities!P13+H13*Opportunities!P14+I13*Opportunities!P15 -> 21888.123 | M13: =IF(AND(J13<=Assumptions!$B$6,K13<=Assumptions!$B$7,B13*IF(Opportunities!S8="ELIGIBLE",0,1)+C13*IF(Opportunities!S9="ELIGIBLE",0,1)+D13*IF(Opportunities!S10="ELIGIBLE",0,1)+E13*IF(Opportunities!S11="ELIGIBLE",0,1)+F13*IF(Opportunities!S12="ELIGIBLE",0,1)+G13*IF(Opportunities!S13="ELIGIBLE",0,1)+H13*IF(Opportunities!S14="ELIGIBLE",0,1)+I13*IF(Opportunities!S15="ELIGIBLE",0,1)=0),1,0) -> 1 | N13: =IF(M13=1,L13,-1E99) -> 21888.123
A14: 9 | B14: 1 | C14: 0 | D14: 0 | E14: 1 | F14: 0 | G14: 0 | H14: 0 | I14: 0 | J14: =B14*Opportunities!L8+C14*Opportunities!L9+D14*Opportunities!L10+E14*Opportunities!L11+F14*Opportunities!L12+G14*Opportunities!L13+H14*Opportunities!L14+I14*Opportunities!L15 -> 1201750 | K14: =SUM(B14:I14) -> 2 | L14: =B14*Opportunities!P8+C14*Opportunities!P9+D14*Opportunities!P10+E14*Opportunities!P11+F14*Opportunities!P12+G14*Opportunities!P13+H14*Opportunities!P14+I14*Opportunities!P15 -> 112784.64 | M14: =IF(AND(J14<=Assumptions!$B$6,K14<=Assumptions!$B$7,B14*IF(Opportunities!S8="ELIGIBLE",0,1)+C14*IF(Opportunities!S9="ELIGIBLE",0,1)+D14*IF(Opportunities!S10="ELIGIBLE",0,1)+E14*IF(Opportunities!S11="ELIGIBLE",0,1)+F14*IF(Opportunities!S12="ELIGIBLE",0,1)+G14*IF(Opportunities!S13="ELIGIBLE",0,1)+H14*IF(Opportunities!S14="ELIGIBLE",0,1)+I14*IF(Opportunities!S15="ELIGIBLE",0,1)=0),1,0) -> 1 | N14: =IF(M14=1,L14,-1E99) -> 112784.64
A15: 10 | B15: 0 | C15: 1 | D15: 0 | E15: 1 | F15: 0 | G15: 0 | H15: 0 | I15: 0 | J15: =B15*Opportunities!L8+C15*Opportunities!L9+D15*Opportunities!L10+E15*Opportunities!L11+F15*Opportunities!L12+G15*Opportunities!L13+H15*Opportunities!L14+I15*Opportunities!L15 -> 917250 | K15: =SUM(B15:I15) -> 2 | L15: =B15*Opportunities!P8+C15*Opportunities!P9+D15*Opportunities!P10+E15*Opportunities!P11+F15*Opportunities!P12+G15*Opportunities!P13+H15*Opportunities!P14+I15*Opportunities!P15 -> 98016.525 | M15: =IF(AND(J15<=Assumptions!$B$6,K15<=Assumptions!$B$7,B15*IF(Opportunities!S8="ELIGIBLE",0,1)+C15*IF(Opportunities!S9="ELIGIBLE",0,1)+D15*IF(Opportunities!S10="ELIGIBLE",0,1)+E15*IF(Opportunities!S11="ELIGIBLE",0,1)+F15*IF(Opportunities!S12="ELIGIBLE",0,1)+G15*IF(Opportunities!S13="ELIGIBLE",0,1)+H15*IF(Opportunities!S14="ELIGIBLE",0,1)+I15*IF(Opportunities!S15="ELIGIBLE",0,1)=0),1,0) -> 1 | N15: =IF(M15=1,L15,-1E99) -> 98016.525
A16: 11 | B16: 1 | C16: 1 | D16: 0 | E16: 1 | F16: 0 | G16: 0 | H16: 0 | I16: 0 | J16: =B16*Opportunities!L8+C16*Opportunities!L9+D16*Opportunities!L10+E16*Opportunities!L11+F16*Opportunities!L12+G16*Opportunities!L13+H16*Opportunities!L14+I16*Opportunities!L15 -> 1786750 | K16: =SUM(B16:I16) -> 3 | L16: =B16*Opportunities!P8+C16*Opportunities!P9+D16*Opportunities!P10+E16*Opportunities!P11+F16*Opportunities!P12+G16*Opportunities!P13+H16*Opportunities!P14+I16*Opportunities!P15 -> 188913.04 | M16: =IF(AND(J16<=Assumptions!$B$6,K16<=Assumptions!$B$7,B16*IF(Opportunities!S8="ELIGIBLE",0,1)+C16*IF(Opportunities!S9="ELIGIBLE",0,1)+D16*IF(Opportunities!S10="ELIGIBLE",0,1)+E16*IF(Opportunities!S11="ELIGIBLE",0,1)+F16*IF(Opportunities!S12="ELIGIBLE",0,1)+G16*IF(Opportunities!S13="ELIGIBLE",0,1)+H16*IF(Opportunities!S14="ELIGIBLE",0,1)+I16*IF(Opportunities!S15="ELIGIBLE",0,1)=0),1,0) -> 1 | N16: =IF(M16=1,L16,-1E99) -> 188913.04
A17: 12 | B17: 0 | C17: 0 | D17: 1 | E17: 1 | F17: 0 | G17: 0 | H17: 0 | I17: 0 | J17: =B17*Opportunities!L8+C17*Opportunities!L9+D17*Opportunities!L10+E17*Opportunities!L11+F17*Opportunities!L12+G17*Opportunities!L13+H17*Opportunities!L14+I17*Opportunities!L15 -> 1913250 | K17: =SUM(B17:I17) -> 2 | L17: =B17*Opportunities!P8+C17*Opportunities!P9+D17*Opportunities!P10+E17*Opportunities!P11+F17*Opportunities!P12+G17*Opportunities!P13+H17*Opportunities!P14+I17*Opportunities!P15 -> 76671.838 | M17: =IF(AND(J17<=Assumptions!$B$6,K17<=Assumptions!$B$7,B17*IF(Opportunities!S8="ELIGIBLE",0,1)+C17*IF(Opportunities!S9="ELIGIBLE",0,1)+D17*IF(Opportunities!S10="ELIGIBLE",0,1)+E17*IF(Opportunities!S11="ELIGIBLE",0,1)+F17*IF(Opportunities!S12="ELIGIBLE",0,1)+G17*IF(Opportunities!S13="ELIGIBLE",0,1)+H17*IF(Opportunities!S14="ELIGIBLE",0,1)+I17*IF(Opportunities!S15="ELIGIBLE",0,1)=0),1,0) -> 1 | N17: =IF(M17=1,L17,-1E99) -> 76671.838
A18: 13 | B18: 1 | C18: 0 | D18: 1 | E18: 1 | F18: 0 | G18: 0 | H18: 0 | I18: 0 | J18: =B18*Opportunities!L8+C18*Opportunities!L9+D18*Opportunities!L10+E18*Opportunities!L11+F18*Opportunities!L12+G18*Opportunities!L13+H18*Opportunities!L14+I18*Opportunities!L15 -> 2782750 | K18: =SUM(B18:I18) -> 3 | L18: =B18*Opportunities!P8+C18*Opportunities!P9+D18*Opportunities!P10+E18*Opportunities!P11+F18*Opportunities!P12+G18*Opportunities!P13+H18*Opportunities!P14+I18*Opportunities!P15 -> 167568.35 | M18: =IF(AND(J18<=Assumptions!$B$6,K18<=Assumptions!$B$7,B18*IF(Opportunities!S8="ELIGIBLE",0,1)+C18*IF(Opportunities!S9="ELIGIBLE",0,1)+D18*IF(Opportunities!S10="ELIGIBLE",0,1)+E18*IF(Opportunities!S11="ELIGIBLE",0,1)+F18*IF(Opportunities!S12="ELIGIBLE",0,1)+G18*IF(Opportunities!S13="ELIGIBLE",0,1)+H18*IF(Opportunities!S14="ELIGIBLE",0,1)+I18*IF(Opportunities!S15="ELIGIBLE",0,1)=0),1,0) -> 0 | N18: =IF(M18=1,L18,-1E99) -> -1e+99
A19: 14 | B19: 0 | C19: 1 | D19: 1 | E19: 1 | F19: 0 | G19: 0 | H19: 0 | I19: 0 | J19: =B19*Opportunities!L8+C19*Opportunities!L9+D19*Opportunities!L10+E19*Opportunities!L11+F19*Opportunities!L12+G19*Opportunities!L13+H19*Opportunities!L14+I19*Opportunities!L15 -> 2498250 | K19: =SUM(B19:I19) -> 3 | L19: =B19*Opportunities!P8+C19*Opportunities!P9+D19*Opportunities!P10+E19*Opportunities!P11+F19*Opportunities!P12+G19*Opportunities!P13+H19*Opportunities!P14+I19*Opportunities!P15 -> 152800.24 | M19: =IF(AND(J19<=Assumptions!$B$6,K19<=Assumptions!$B$7,B19*IF(Opportunities!S8="ELIGIBLE",0,1)+C19*IF(Opportunities!S9="ELIGIBLE",0,1)+D19*IF(Opportunities!S10="ELIGIBLE",0,1)+E19*IF(Opportunities!S11="ELIGIBLE",0,1)+F19*IF(Opportunities!S12="ELIGIBLE",0,1)+G19*IF(Opportunities!S13="ELIGIBLE",0,1)+H19*IF(Opportunities!S14="ELIGIBLE",0,1)+I19*IF(Opportunities!S15="ELIGIBLE",0,1)=0),1,0) -> 0 | N19: =IF(M19=1,L19,-1E99) -> -1e+99
A20: 15 | B20: 1 | C20: 1 | D20: 1 | E20: 1 | F20: 0 | G20: 0 | H20: 0 | I20: 0 | J20: =B20*Opportunities!L8+C20*Opportunities!L9+D20*Opportunities!L10+E20*Opportunities!L11+F20*Opportunities!L12+G20*Opportunities!L13+H20*Opportunities!L14+I20*Opportunities!L15 -> 3367750 | K20: =SUM(B20:I20) -> 4 | L20: =B20*Opportunities!P8+C20*Opportunities!P9+D20*Opportunities!P10+E20*Opportunities!P11+F20*Opportunities!P12+G20*Opportunities!P13+H20*Opportunities!P14+I20*Opportunities!P15 -> 243696.76 | M20: =IF(AND(J20<=Assumptions!$B$6,K20<=Assumptions!$B$7,B20*IF(Opportunities!S8="ELIGIBLE",0,1)+C20*IF(Opportunities!S9="ELIGIBLE",0,1)+D20*IF(Opportunities!S10="ELIGIBLE",0,1)+E20*IF(Opportunities!S11="ELIGIBLE",0,1)+F20*IF(Opportunities!S12="ELIGIBLE",0,1)+G20*IF(Opportunities!S13="ELIGIBLE",0,1)+H20*IF(Opportunities!S14="ELIGIBLE",0,1)+I20*IF(Opportunities!S15="ELIGIBLE",0,1)=0),1,0) -> 0 | N20: =IF(M20=1,L20,-1E99) -> -1e+99
A21: 16 | B21: 0 | C21: 0 | D21: 0 | E21: 0 | F21: 1 | G21: 0 | H21: 0 | I21: 0 | J21: =B21*Opportunities!L8+C21*Opportunities!L9+D21*Opportunities!L10+E21*Opportunities!L11+F21*Opportunities!L12+G21*Opportunities!L13+H21*Opportunities!L14+I21*Opportunities!L15 -> 1143000 | K21: =SUM(B21:I21) -> 1 | L21: =B21*Opportunities!P8+C21*Opportunities!P9+D21*Opportunities!P10+E21*Opportunities!P11+F21*Opportunities!P12+G21*Opportunities!P13+H21*Opportunities!P14+I21*Opportunities!P15 -> -175492.04 | M21: =IF(AND(J21<=Assumptions!$B$6,K21<=Assumptions!$B$7,B21*IF(Opportunities!S8="ELIGIBLE",0,1)+C21*IF(Opportunities!S9="ELIGIBLE",0,1)+D21*IF(Opportunities!S10="ELIGIBLE",0,1)+E21*IF(Opportunities!S11="ELIGIBLE",0,1)+F21*IF(Opportunities!S12="ELIGIBLE",0,1)+G21*IF(Opportunities!S13="ELIGIBLE",0,1)+H21*IF(Opportunities!S14="ELIGIBLE",0,1)+I21*IF(Opportunities!S15="ELIGIBLE",0,1)=0),1,0) -> 0 | N21: =IF(M21=1,L21,-1E99) -> -1e+99
A22: 17 | B22: 1 | C22: 0 | D22: 0 | E22: 0 | F22: 1 | G22: 0 | H22: 0 | I22: 0 | J22: =B22*Opportunities!L8+C22*Opportunities!L9+D22*Opportunities!L10+E22*Opportunities!L11+F22*Opportunities!L12+G22*Opportunities!L13+H22*Opportunities!L14+I22*Opportunities!L15 -> 2012500 | K22: =SUM(B22:I22) -> 2 | L22: =B22*Opportunities!P8+C22*Opportunities!P9+D22*Opportunities!P10+E22*Opportunities!P11+F22*Opportunities!P12+G22*Opportunities!P13+H22*Opportunities!P14+I22*Opportunities!P15 -> -84595.523 | M22: =IF(AND(J22<=Assumptions!$B$6,K22<=Assumptions!$B$7,B22*IF(Opportunities!S8="ELIGIBLE",0,1)+C22*IF(Opportunities!S9="ELIGIBLE",0,1)+D22*IF(Opportunities!S10="ELIGIBLE",0,1)+E22*IF(Opportunities!S11="ELIGIBLE",0,1)+F22*IF(Opportunities!S12="ELIGIBLE",0,1)+G22*IF(Opportunities!S13="ELIGIBLE",0,1)+H22*IF(Opportunities!S14="ELIGIBLE",0,1)+I22*IF(Opportunities!S15="ELIGIBLE",0,1)=0),1,0) -> 0 | N22: =IF(M22=1,L22,-1E99) -> -1e+99
A23: 18 | B23: 0 | C23: 1 | D23: 0 | E23: 0 | F23: 1 | G23: 0 | H23: 0 | I23: 0 | J23: =B23*Opportunities!L8+C23*Opportunities!L9+D23*Opportunities!L10+E23*Opportunities!L11+F23*Opportunities!L12+G23*Opportunities!L13+H23*Opportunities!L14+I23*Opportunities!L15 -> 1728000 | K23: =SUM(B23:I23) -> 2 | L23: =B23*Opportunities!P8+C23*Opportunities!P9+D23*Opportunities!P10+E23*Opportunities!P11+F23*Opportunities!P12+G23*Opportunities!P13+H23*Opportunities!P14+I23*Opportunities!P15 -> -99363.637 | M23: =IF(AND(J23<=Assumptions!$B$6,K23<=Assumptions!$B$7,B23*IF(Opportunities!S8="ELIGIBLE",0,1)+C23*IF(Opportunities!S9="ELIGIBLE",0,1)+D23*IF(Opportunities!S10="ELIGIBLE",0,1)+E23*IF(Opportunities!S11="ELIGIBLE",0,1)+F23*IF(Opportunities!S12="ELIGIBLE",0,1)+G23*IF(Opportunities!S13="ELIGIBLE",0,1)+H23*IF(Opportunities!S14="ELIGIBLE",0,1)+I23*IF(Opportunities!S15="ELIGIBLE",0,1)=0),1,0) -> 0 | N23: =IF(M23=1,L23,-1E99) -> -1e+99
A24: 19 | B24: 1 | C24: 1 | D24: 0 | E24: 0 | F24: 1 | G24: 0 | H24: 0 | I24: 0 | J24: =B24*Opportunities!L8+C24*Opportunities!L9+D24*Opportunities!L10+E24*Opportunities!L11+F24*Opportunities!L12+G24*Opportunities!L13+H24*Opportunities!L14+I24*Opportunities!L15 -> 2597500 | K24: =SUM(B24:I24) -> 3 | L24: =B24*Opportunities!P8+C24*Opportunities!P9+D24*Opportunities!P10+E24*Opportunities!P11+F24*Opportunities!P12+G24*Opportunities!P13+H24*Opportunities!P14+I24*Opportunities!P15 -> -8467.1203 | M24: =IF(AND(J24<=Assumptions!$B$6,K24<=Assumptions!$B$7,B24*IF(Opportunities!S8="ELIGIBLE",0,1)+C24*IF(Opportunities!S9="ELIGIBLE",0,1)+D24*IF(Opportunities!S10="ELIGIBLE",0,1)+E24*IF(Opportunities!S11="ELIGIBLE",0,1)+F24*IF(Opportunities!S12="ELIGIBLE",0,1)+G24*IF(Opportunities!S13="ELIGIBLE",0,1)+H24*IF(Opportunities!S14="ELIGIBLE",0,1)+I24*IF(Opportunities!S15="ELIGIBLE",0,1)=0),1,0) -> 0 | N24: =IF(M24=1,L24,-1E99) -> -1e+99
A25: 20 | B25: 0 | C25: 0 | D25: 1 | E25: 0 | F25: 1 | G25: 0 | H25: 0 | I25: 0 | J25: =B25*Opportunities!L8+C25*Opportunities!L9+D25*Opportunities!L10+E25*Opportunities!L11+F25*Opportunities!L12+G25*Opportunities!L13+H25*Opportunities!L14+I25*Opportunities!L15 -> 2724000 | K25: =SUM(B25:I25) -> 2 | L25: =B25*Opportunities!P8+C25*Opportunities!P9+D25*Opportunities!P10+E25*Opportunities!P11+F25*Opportunities!P12+G25*Opportunities!P13+H25*Opportunities!P14+I25*Opportunities!P15 -> -120708.32 | M25: =IF(AND(J25<=Assumptions!$B$6,K25<=Assumptions!$B$7,B25*IF(Opportunities!S8="ELIGIBLE",0,1)+C25*IF(Opportunities!S9="ELIGIBLE",0,1)+D25*IF(Opportunities!S10="ELIGIBLE",0,1)+E25*IF(Opportunities!S11="ELIGIBLE",0,1)+F25*IF(Opportunities!S12="ELIGIBLE",0,1)+G25*IF(Opportunities!S13="ELIGIBLE",0,1)+H25*IF(Opportunities!S14="ELIGIBLE",0,1)+I25*IF(Opportunities!S15="ELIGIBLE",0,1)=0),1,0) -> 0 | N25: =IF(M25=1,L25,-1E99) -> -1e+99
A26: 21 | B26: 1 | C26: 0 | D26: 1 | E26: 0 | F26: 1 | G26: 0 | H26: 0 | I26: 0 | J26: =B26*Opportunities!L8+C26*Opportunities!L9+D26*Opportunities!L10+E26*Opportunities!L11+F26*Opportunities!L12+G26*Opportunities!L13+H26*Opportunities!L14+I26*Opportunities!L15 -> 3593500 | K26: =SUM(B26:I26) -> 3 | L26: =B26*Opportunities!P8+C26*Opportunities!P9+D26*Opportunities!P10+E26*Opportunities!P11+F26*Opportunities!P12+G26*Opportunities!P13+H26*Opportunities!P14+I26*Opportunities!P15 -> -29811.808 | M26: =IF(AND(J26<=Assumptions!$B$6,K26<=Assumptions!$B$7,B26*IF(Opportunities!S8="ELIGIBLE",0,1)+C26*IF(Opportunities!S9="ELIGIBLE",0,1)+D26*IF(Opportunities!S10="ELIGIBLE",0,1)+E26*IF(Opportunities!S11="ELIGIBLE",0,1)+F26*IF(Opportunities!S12="ELIGIBLE",0,1)+G26*IF(Opportunities!S13="ELIGIBLE",0,1)+H26*IF(Opportunities!S14="ELIGIBLE",0,1)+I26*IF(Opportunities!S15="ELIGIBLE",0,1)=0),1,0) -> 0 | N26: =IF(M26=1,L26,-1E99) -> -1e+99
A27: 22 | B27: 0 | C27: 1 | D27: 1 | E27: 0 | F27: 1 | G27: 0 | H27: 0 | I27: 0 | J27: =B27*Opportunities!L8+C27*Opportunities!L9+D27*Opportunities!L10+E27*Opportunities!L11+F27*Opportunities!L12+G27*Opportunities!L13+H27*Opportunities!L14+I27*Opportunities!L15 -> 3309000 | K27: =SUM(B27:I27) -> 3 | L27: =B27*Opportunities!P8+C27*Opportunities!P9+D27*Opportunities!P10+E27*Opportunities!P11+F27*Opportunities!P12+G27*Opportunities!P13+H27*Opportunities!P14+I27*Opportunities!P15 -> -44579.922 | M27: =IF(AND(J27<=Assumptions!$B$6,K27<=Assumptions!$B$7,B27*IF(Opportunities!S8="ELIGIBLE",0,1)+C27*IF(Opportunities!S9="ELIGIBLE",0,1)+D27*IF(Opportunities!S10="ELIGIBLE",0,1)+E27*IF(Opportunities!S11="ELIGIBLE",0,1)+F27*IF(Opportunities!S12="ELIGIBLE",0,1)+G27*IF(Opportunities!S13="ELIGIBLE",0,1)+H27*IF(Opportunities!S14="ELIGIBLE",0,1)+I27*IF(Opportunities!S15="ELIGIBLE",0,1)=0),1,0) -> 0 | N27: =IF(M27=1,L27,-1E99) -> -1e+99
A28: 23 | B28: 1 | C28: 1 | D28: 1 | E28: 0 | F28: 1 | G28: 0 | H28: 0 | I28: 0 | J28: =B28*Opportunities!L8+C28*Opportunities!L9+D28*Opportunities!L10+E28*Opportunities!L11+F28*Opportunities!L12+G28*Opportunities!L13+H28*Opportunities!L14+I28*Opportunities!L15 -> 4178500 | K28: =SUM(B28:I28) -> 4 | L28: =B28*Opportunities!P8+C28*Opportunities!P9+D28*Opportunities!P10+E28*Opportunities!P11+F28*Opportunities!P12+G28*Opportunities!P13+H28*Opportunities!P14+I28*Opportunities!P15 -> 46316.595 | M28: =IF(AND(J28<=Assumptions!$B$6,K28<=Assumptions!$B$7,B28*IF(Opportunities!S8="ELIGIBLE",0,1)+C28*IF(Opportunities!S9="ELIGIBLE",0,1)+D28*IF(Opportunities!S10="ELIGIBLE",0,1)+E28*IF(Opportunities!S11="ELIGIBLE",0,1)+F28*IF(Opportunities!S12="ELIGIBLE",0,1)+G28*IF(Opportunities!S13="ELIGIBLE",0,1)+H28*IF(Opportunities!S14="ELIGIBLE",0,1)+I28*IF(Opportunities!S15="ELIGIBLE",0,1)=0),1,0) -> 0 | N28: =IF(M28=1,L28,-1E99) -> -1e+99
A29: 24 | B29: 0 | C29: 0 | D29: 0 | E29: 1 | F29: 1 | G29: 0 | H29: 0 | I29: 0 | J29: =B29*Opportunities!L8+C29*Opportunities!L9+D29*Opportunities!L10+E29*Opportunities!L11+F29*Opportunities!L12+G29*Opportunities!L13+H29*Opportunities!L14+I29*Opportunities!L15 -> 1475250 | K29: =SUM(B29:I29) -> 2 | L29: =B29*Opportunities!P8+C29*Opportunities!P9+D29*Opportunities!P10+E29*Opportunities!P11+F29*Opportunities!P12+G29*Opportunities!P13+H29*Opportunities!P14+I29*Opportunities!P15 -> -153603.92 | M29: =IF(AND(J29<=Assumptions!$B$6,K29<=Assumptions!$B$7,B29*IF(Opportunities!S8="ELIGIBLE",0,1)+C29*IF(Opportunities!S9="ELIGIBLE",0,1)+D29*IF(Opportunities!S10="ELIGIBLE",0,1)+E29*IF(Opportunities!S11="ELIGIBLE",0,1)+F29*IF(Opportunities!S12="ELIGIBLE",0,1)+G29*IF(Opportunities!S13="ELIGIBLE",0,1)+H29*IF(Opportunities!S14="ELIGIBLE",0,1)+I29*IF(Opportunities!S15="ELIGIBLE",0,1)=0),1,0) -> 0 | N29: =IF(M29=1,L29,-1E99) -> -1e+99
A30: 25 | B30: 1 | C30: 0 | D30: 0 | E30: 1 | F30: 1 | G30: 0 | H30: 0 | I30: 0 | J30: =B30*Opportunities!L8+C30*Opportunities!L9+D30*Opportunities!L10+E30*Opportunities!L11+F30*Opportunities!L12+G30*Opportunities!L13+H30*Opportunities!L14+I30*Opportunities!L15 -> 2344750 | K30: =SUM(B30:I30) -> 3 | L30: =B30*Opportunities!P8+C30*Opportunities!P9+D30*Opportunities!P10+E30*Opportunities!P11+F30*Opportunities!P12+G30*Opportunities!P13+H30*Opportunities!P14+I30*Opportunities!P15 -> -62707.4 | M30: =IF(AND(J30<=Assumptions!$B$6,K30<=Assumptions!$B$7,B30*IF(Opportunities!S8="ELIGIBLE",0,1)+C30*IF(Opportunities!S9="ELIGIBLE",0,1)+D30*IF(Opportunities!S10="ELIGIBLE",0,1)+E30*IF(Opportunities!S11="ELIGIBLE",0,1)+F30*IF(Opportunities!S12="ELIGIBLE",0,1)+G30*IF(Opportunities!S13="ELIGIBLE",0,1)+H30*IF(Opportunities!S14="ELIGIBLE",0,1)+I30*IF(Opportunities!S15="ELIGIBLE",0,1)=0),1,0) -> 0 | N30: =IF(M30=1,L30,-1E99) -> -1e+99
A31: 26 | B31: 0 | C31: 1 | D31: 0 | E31: 1 | F31: 1 | G31: 0 | H31: 0 | I31: 0 | J31: =B31*Opportunities!L8+C31*Opportunities!L9+D31*Opportunities!L10+E31*Opportunities!L11+F31*Opportunities!L12+G31*Opportunities!L13+H31*Opportunities!L14+I31*Opportunities!L15 -> 2060250 | K31: =SUM(B31:I31) -> 3 | L31: =B31*Opportunities!P8+C31*Opportunities!P9+D31*Opportunities!P10+E31*Opportunities!P11+F31*Opportunities!P12+G31*Opportunities!P13+H31*Opportunities!P14+I31*Opportunities!P15 -> -77475.515 | M31: =IF(AND(J31<=Assumptions!$B$6,K31<=Assumptions!$B$7,B31*IF(Opportunities!S8="ELIGIBLE",0,1)+C31*IF(Opportunities!S9="ELIGIBLE",0,1)+D31*IF(Opportunities!S10="ELIGIBLE",0,1)+E31*IF(Opportunities!S11="ELIGIBLE",0,1)+F31*IF(Opportunities!S12="ELIGIBLE",0,1)+G31*IF(Opportunities!S13="ELIGIBLE",0,1)+H31*IF(Opportunities!S14="ELIGIBLE",0,1)+I31*IF(Opportunities!S15="ELIGIBLE",0,1)=0),1,0) -> 0 | N31: =IF(M31=1,L31,-1E99) -> -1e+99
A32: 27 | B32: 1 | C32: 1 | D32: 0 | E32: 1 | F32: 1 | G32: 0 | H32: 0 | I32: 0 | J32: =B32*Opportunities!L8+C32*Opportunities!L9+D32*Opportunities!L10+E32*Opportunities!L11+F32*Opportunities!L12+G32*Opportunities!L13+H32*Opportunities!L14+I32*Opportunities!L15 -> 2929750 | K32: =SUM(B32:I32) -> 4 | L32: =B32*Opportunities!P8+C32*Opportunities!P9+D32*Opportunities!P10+E32*Opportunities!P11+F32*Opportunities!P12+G32*Opportunities!P13+H32*Opportunities!P14+I32*Opportunities!P15 -> 13421.002 | M32: =IF(AND(J32<=Assumptions!$B$6,K32<=Assumptions!$B$7,B32*IF(Opportunities!S8="ELIGIBLE",0,1)+C32*IF(Opportunities!S9="ELIGIBLE",0,1)+D32*IF(Opportunities!S10="ELIGIBLE",0,1)+E32*IF(Opportunities!S11="ELIGIBLE",0,1)+F32*IF(Opportunities!S12="ELIGIBLE",0,1)+G32*IF(Opportunities!S13="ELIGIBLE",0,1)+H32*IF(Opportunities!S14="ELIGIBLE",0,1)+I32*IF(Opportunities!S15="ELIGIBLE",0,1)=0),1,0) -> 0 | N32: =IF(M32=1,L32,-1E99) -> -1e+99
A33: 28 | B33: 0 | C33: 0 | D33: 1 | E33: 1 | F33: 1 | G33: 0 | H33: 0 | I33: 0 | J33: =B33*Opportunities!L8+C33*Opportunities!L9+D33*Opportunities!L10+E33*Opportunities!L11+F33*Opportunities!L12+G33*Opportunities!L13+H33*Opportunities!L14+I33*Opportunities!L15 -> 3056250 | K33: =SUM(B33:I33) -> 3 | L33: =B33*Opportunities!P8+C33*Opportunities!P9+D33*Opportunities!P10+E33*Opportunities!P11+F33*Opportunities!P12+G33*Opportunities!P13+H33*Opportunities!P14+I33*Opportunities!P15 -> -98820.202 | M33: =IF(AND(J33<=Assumptions!$B$6,K33<=Assumptions!$B$7,B33*IF(Opportunities!S8="ELIGIBLE",0,1)+C33*IF(Opportunities!S9="ELIGIBLE",0,1)+D33*IF(Opportunities!S10="ELIGIBLE",0,1)+E33*IF(Opportunities!S11="ELIGIBLE",0,1)+F33*IF(Opportunities!S12="ELIGIBLE",0,1)+G33*IF(Opportunities!S13="ELIGIBLE",0,1)+H33*IF(Opportunities!S14="ELIGIBLE",0,1)+I33*IF(Opportunities!S15="ELIGIBLE",0,1)=0),1,0) -> 0 | N33: =IF(M33=1,L33,-1E99) -> -1e+99
A34: 29 | B34: 1 | C34: 0 | D34: 1 | E34: 1 | F34: 1 | G34: 0 | H34: 0 | I34: 0 | J34: =B34*Opportunities!L8+C34*Opportunities!L9+D34*Opportunities!L10+E34*Opportunities!L11+F34*Opportunities!L12+G34*Opportunities!L13+H34*Opportunities!L14+I34*Opportunities!L15 -> 3925750 | K34: =SUM(B34:I34) -> 4 | L34: =B34*Opportunities!P8+C34*Opportunities!P9+D34*Opportunities!P10+E34*Opportunities!P11+F34*Opportunities!P12+G34*Opportunities!P13+H34*Opportunities!P14+I34*Opportunities!P15 -> -7923.6849 | M34: =IF(AND(J34<=Assumptions!$B$6,K34<=Assumptions!$B$7,B34*IF(Opportunities!S8="ELIGIBLE",0,1)+C34*IF(Opportunities!S9="ELIGIBLE",0,1)+D34*IF(Opportunities!S10="ELIGIBLE",0,1)+E34*IF(Opportunities!S11="ELIGIBLE",0,1)+F34*IF(Opportunities!S12="ELIGIBLE",0,1)+G34*IF(Opportunities!S13="ELIGIBLE",0,1)+H34*IF(Opportunities!S14="ELIGIBLE",0,1)+I34*IF(Opportunities!S15="ELIGIBLE",0,1)=0),1,0) -> 0 | N34: =IF(M34=1,L34,-1E99) -> -1e+99
A35: 30 | B35: 0 | C35: 1 | D35: 1 | E35: 1 | F35: 1 | G35: 0 | H35: 0 | I35: 0 | J35: =B35*Opportunities!L8+C35*Opportunities!L9+D35*Opportunities!L10+E35*Opportunities!L11+F35*Opportunities!L12+G35*Opportunities!L13+H35*Opportunities!L14+I35*Opportunities!L15 -> 3641250 | K35: =SUM(B35:I35) -> 4 | L35: =B35*Opportunities!P8+C35*Opportunities!P9+D35*Opportunities!P10+E35*Opportunities!P11+F35*Opportunities!P12+G35*Opportunities!P13+H35*Opportunities!P14+I35*Opportunities!P15 -> -22691.799 | M35: =IF(AND(J35<=Assumptions!$B$6,K35<=Assumptions!$B$7,B35*IF(Opportunities!S8="ELIGIBLE",0,1)+C35*IF(Opportunities!S9="ELIGIBLE",0,1)+D35*IF(Opportunities!S10="ELIGIBLE",0,1)+E35*IF(Opportunities!S11="ELIGIBLE",0,1)+F35*IF(Opportunities!S12="ELIGIBLE",0,1)+G35*IF(Opportunities!S13="ELIGIBLE",0,1)+H35*IF(Opportunities!S14="ELIGIBLE",0,1)+I35*IF(Opportunities!S15="ELIGIBLE",0,1)=0),1,0) -> 0 | N35: =IF(M35=1,L35,-1E99) -> -1e+99
A36: 31 | B36: 1 | C36: 1 | D36: 1 | E36: 1 | F36: 1 | G36: 0 | H36: 0 | I36: 0 | J36: =B36*Opportunities!L8+C36*Opportunities!L9+D36*Opportunities!L10+E36*Opportunities!L11+F36*Opportunities!L12+G36*Opportunities!L13+H36*Opportunities!L14+I36*Opportunities!L15 -> 4510750 | K36: =SUM(B36:I36) -> 5 | L36: =B36*Opportunities!P8+C36*Opportunities!P9+D36*Opportunities!P10+E36*Opportunities!P11+F36*Opportunities!P12+G36*Opportunities!P13+H36*Opportunities!P14+I36*Opportunities!P15 -> 68204.718 | M36: =IF(AND(J36<=Assumptions!$B$6,K36<=Assumptions!$B$7,B36*IF(Opportunities!S8="ELIGIBLE",0,1)+C36*IF(Opportunities!S9="ELIGIBLE",0,1)+D36*IF(Opportunities!S10="ELIGIBLE",0,1)+E36*IF(Opportunities!S11="ELIGIBLE",0,1)+F36*IF(Opportunities!S12="ELIGIBLE",0,1)+G36*IF(Opportunities!S13="ELIGIBLE",0,1)+H36*IF(Opportunities!S14="ELIGIBLE",0,1)+I36*IF(Opportunities!S15="ELIGIBLE",0,1)=0),1,0) -> 0 | N36: =IF(M36=1,L36,-1E99) -> -1e+99
A37: 32 | B37: 0 | C37: 0 | D37: 0 | E37: 0 | F37: 0 | G37: 1 | H37: 0 | I37: 0 | J37: =B37*Opportunities!L8+C37*Opportunities!L9+D37*Opportunities!L10+E37*Opportunities!L11+F37*Opportunities!L12+G37*Opportunities!L13+H37*Opportunities!L14+I37*Opportunities!L15 -> 799250 | K37: =SUM(B37:I37) -> 1 | L37: =B37*Opportunities!P8+C37*Opportunities!P9+D37*Opportunities!P10+E37*Opportunities!P11+F37*Opportunities!P12+G37*Opportunities!P13+H37*Opportunities!P14+I37*Opportunities!P15 -> 72646.659 | M37: =IF(AND(J37<=Assumptions!$B$6,K37<=Assumptions!$B$7,B37*IF(Opportunities!S8="ELIGIBLE",0,1)+C37*IF(Opportunities!S9="ELIGIBLE",0,1)+D37*IF(Opportunities!S10="ELIGIBLE",0,1)+E37*IF(Opportunities!S11="ELIGIBLE",0,1)+F37*IF(Opportunities!S12="ELIGIBLE",0,1)+G37*IF(Opportunities!S13="ELIGIBLE",0,1)+H37*IF(Opportunities!S14="ELIGIBLE",0,1)+I37*IF(Opportunities!S15="ELIGIBLE",0,1)=0),1,0) -> 0 | N37: =IF(M37=1,L37,-1E99) -> -1e+99
A38: 33 | B38: 1 | C38: 0 | D38: 0 | E38: 0 | F38: 0 | G38: 1 | H38: 0 | I38: 0 | J38: =B38*Opportunities!L8+C38*Opportunities!L9+D38*Opportunities!L10+E38*Opportunities!L11+F38*Opportunities!L12+G38*Opportunities!L13+H38*Opportunities!L14+I38*Opportunities!L15 -> 1668750 | K38: =SUM(B38:I38) -> 2 | L38: =B38*Opportunities!P8+C38*Opportunities!P9+D38*Opportunities!P10+E38*Opportunities!P11+F38*Opportunities!P12+G38*Opportunities!P13+H38*Opportunities!P14+I38*Opportunities!P15 -> 163543.18 | M38: =IF(AND(J38<=Assumptions!$B$6,K38<=Assumptions!$B$7,B38*IF(Opportunities!S8="ELIGIBLE",0,1)+C38*IF(Opportunities!S9="ELIGIBLE",0,1)+D38*IF(Opportunities!S10="ELIGIBLE",0,1)+E38*IF(Opportunities!S11="ELIGIBLE",0,1)+F38*IF(Opportunities!S12="ELIGIBLE",0,1)+G38*IF(Opportunities!S13="ELIGIBLE",0,1)+H38*IF(Opportunities!S14="ELIGIBLE",0,1)+I38*IF(Opportunities!S15="ELIGIBLE",0,1)=0),1,0) -> 0 | N38: =IF(M38=1,L38,-1E99) -> -1e+99
A39: 34 | B39: 0 | C39: 1 | D39: 0 | E39: 0 | F39: 0 | G39: 1 | H39: 0 | I39: 0 | J39: =B39*Opportunities!L8+C39*Opportunities!L9+D39*Opportunities!L10+E39*Opportunities!L11+F39*Opportunities!L12+G39*Opportunities!L13+H39*Opportunities!L14+I39*Opportunities!L15 -> 1384250 | K39: =SUM(B39:I39) -> 2 | L39: =B39*Opportunities!P8+C39*Opportunities!P9+D39*Opportunities!P10+E39*Opportunities!P11+F39*Opportunities!P12+G39*Opportunities!P13+H39*Opportunities!P14+I39*Opportunities!P15 -> 148775.06 | M39: =IF(AND(J39<=Assumptions!$B$6,K39<=Assumptions!$B$7,B39*IF(Opportunities!S8="ELIGIBLE",0,1)+C39*IF(Opportunities!S9="ELIGIBLE",0,1)+D39*IF(Opportunities!S10="ELIGIBLE",0,1)+E39*IF(Opportunities!S11="ELIGIBLE",0,1)+F39*IF(Opportunities!S12="ELIGIBLE",0,1)+G39*IF(Opportunities!S13="ELIGIBLE",0,1)+H39*IF(Opportunities!S14="ELIGIBLE",0,1)+I39*IF(Opportunities!S15="ELIGIBLE",0,1)=0),1,0) -> 0 | N39: =IF(M39=1,L39,-1E99) -> -1e+99
A40: 35 | B40: 1 | C40: 1 | D40: 0 | E40: 0 | F40: 0 | G40: 1 | H40: 0 | I40: 0 | J40: =B40*Opportunities!L8+C40*Opportunities!L9+D40*Opportunities!L10+E40*Opportunities!L11+F40*Opportunities!L12+G40*Opportunities!L13+H40*Opportunities!L14+I40*Opportunities!L15 -> 2253750 | K40: =SUM(B40:I40) -> 3 | L40: =B40*Opportunities!P8+C40*Opportunities!P9+D40*Opportunities!P10+E40*Opportunities!P11+F40*Opportunities!P12+G40*Opportunities!P13+H40*Opportunities!P14+I40*Opportunities!P15 -> 239671.58 | M40: =IF(AND(J40<=Assumptions!$B$6,K40<=Assumptions!$B$7,B40*IF(Opportunities!S8="ELIGIBLE",0,1)+C40*IF(Opportunities!S9="ELIGIBLE",0,1)+D40*IF(Opportunities!S10="ELIGIBLE",0,1)+E40*IF(Opportunities!S11="ELIGIBLE",0,1)+F40*IF(Opportunities!S12="ELIGIBLE",0,1)+G40*IF(Opportunities!S13="ELIGIBLE",0,1)+H40*IF(Opportunities!S14="ELIGIBLE",0,1)+I40*IF(Opportunities!S15="ELIGIBLE",0,1)=0),1,0) -> 0 | N40: =IF(M40=1,L40,-1E99) -> -1e+99
A41: 36 | B41: 0 | C41: 0 | D41: 1 | E41: 0 | F41: 0 | G41: 1 | H41: 0 | I41: 0 | J41: =B41*Opportunities!L8+C41*Opportunities!L9+D41*Opportunities!L10+E41*Opportunities!L11+F41*Opportunities!L12+G41*Opportunities!L13+H41*Opportunities!L14+I41*Opportunities!L15 -> 2380250 | K41: =SUM(B41:I41) -> 2 | L41: =B41*Opportunities!P8+C41*Opportunities!P9+D41*Opportunities!P10+E41*Opportunities!P11+F41*Opportunities!P12+G41*Opportunities!P13+H41*Opportunities!P14+I41*Opportunities!P15 -> 127430.37 | M41: =IF(AND(J41<=Assumptions!$B$6,K41<=Assumptions!$B$7,B41*IF(Opportunities!S8="ELIGIBLE",0,1)+C41*IF(Opportunities!S9="ELIGIBLE",0,1)+D41*IF(Opportunities!S10="ELIGIBLE",0,1)+E41*IF(Opportunities!S11="ELIGIBLE",0,1)+F41*IF(Opportunities!S12="ELIGIBLE",0,1)+G41*IF(Opportunities!S13="ELIGIBLE",0,1)+H41*IF(Opportunities!S14="ELIGIBLE",0,1)+I41*IF(Opportunities!S15="ELIGIBLE",0,1)=0),1,0) -> 0 | N41: =IF(M41=1,L41,-1E99) -> -1e+99
A42: 37 | B42: 1 | C42: 0 | D42: 1 | E42: 0 | F42: 0 | G42: 1 | H42: 0 | I42: 0 | J42: =B42*Opportunities!L8+C42*Opportunities!L9+D42*Opportunities!L10+E42*Opportunities!L11+F42*Opportunities!L12+G42*Opportunities!L13+H42*Opportunities!L14+I42*Opportunities!L15 -> 3249750 | K42: =SUM(B42:I42) -> 3 | L42: =B42*Opportunities!P8+C42*Opportunities!P9+D42*Opportunities!P10+E42*Opportunities!P11+F42*Opportunities!P12+G42*Opportunities!P13+H42*Opportunities!P14+I42*Opportunities!P15 -> 218326.89 | M42: =IF(AND(J42<=Assumptions!$B$6,K42<=Assumptions!$B$7,B42*IF(Opportunities!S8="ELIGIBLE",0,1)+C42*IF(Opportunities!S9="ELIGIBLE",0,1)+D42*IF(Opportunities!S10="ELIGIBLE",0,1)+E42*IF(Opportunities!S11="ELIGIBLE",0,1)+F42*IF(Opportunities!S12="ELIGIBLE",0,1)+G42*IF(Opportunities!S13="ELIGIBLE",0,1)+H42*IF(Opportunities!S14="ELIGIBLE",0,1)+I42*IF(Opportunities!S15="ELIGIBLE",0,1)=0),1,0) -> 0 | N42: =IF(M42=1,L42,-1E99) -> -1e+99
A43: 38 | B43: 0 | C43: 1 | D43: 1 | E43: 0 | F43: 0 | G43: 1 | H43: 0 | I43: 0 | J43: =B43*Opportunities!L8+C43*Opportunities!L9+D43*Opportunities!L10+E43*Opportunities!L11+F43*Opportunities!L12+G43*Opportunities!L13+H43*Opportunities!L14+I43*Opportunities!L15 -> 2965250 | K43: =SUM(B43:I43) -> 3 | L43: =B43*Opportunities!P8+C43*Opportunities!P9+D43*Opportunities!P10+E43*Opportunities!P11+F43*Opportunities!P12+G43*Opportunities!P13+H43*Opportunities!P14+I43*Opportunities!P15 -> 203558.78 | M43: =IF(AND(J43<=Assumptions!$B$6,K43<=Assumptions!$B$7,B43*IF(Opportunities!S8="ELIGIBLE",0,1)+C43*IF(Opportunities!S9="ELIGIBLE",0,1)+D43*IF(Opportunities!S10="ELIGIBLE",0,1)+E43*IF(Opportunities!S11="ELIGIBLE",0,1)+F43*IF(Opportunities!S12="ELIGIBLE",0,1)+G43*IF(Opportunities!S13="ELIGIBLE",0,1)+H43*IF(Opportunities!S14="ELIGIBLE",0,1)+I43*IF(Opportunities!S15="ELIGIBLE",0,1)=0),1,0) -> 0 | N43: =IF(M43=1,L43,-1E99) -> -1e+99
A44: 39 | B44: 1 | C44: 1 | D44: 1 | E44: 0 | F44: 0 | G44: 1 | H44: 0 | I44: 0 | J44: =B44*Opportunities!L8+C44*Opportunities!L9+D44*Opportunities!L10+E44*Opportunities!L11+F44*Opportunities!L12+G44*Opportunities!L13+H44*Opportunities!L14+I44*Opportunities!L15 -> 3834750 | K44: =SUM(B44:I44) -> 4 | L44: =B44*Opportunities!P8+C44*Opportunities!P9+D44*Opportunities!P10+E44*Opportunities!P11+F44*Opportunities!P12+G44*Opportunities!P13+H44*Opportunities!P14+I44*Opportunities!P15 -> 294455.29 | M44: =IF(AND(J44<=Assumptions!$B$6,K44<=Assumptions!$B$7,B44*IF(Opportunities!S8="ELIGIBLE",0,1)+C44*IF(Opportunities!S9="ELIGIBLE",0,1)+D44*IF(Opportunities!S10="ELIGIBLE",0,1)+E44*IF(Opportunities!S11="ELIGIBLE",0,1)+F44*IF(Opportunities!S12="ELIGIBLE",0,1)+G44*IF(Opportunities!S13="ELIGIBLE",0,1)+H44*IF(Opportunities!S14="ELIGIBLE",0,1)+I44*IF(Opportunities!S15="ELIGIBLE",0,1)=0),1,0) -> 0 | N44: =IF(M44=1,L44,-1E99) -> -1e+99
A45: 40 | B45: 0 | C45: 0 | D45: 0 | E45: 1 | F45: 0 | G45: 1 | H45: 0 | I45: 0 | J45: =B45*Opportunities!L8+C45*Opportunities!L9+D45*Opportunities!L10+E45*Opportunities!L11+F45*Opportunities!L12+G45*Opportunities!L13+H45*Opportunities!L14+I45*Opportunities!L15 -> 1131500 | K45: =SUM(B45:I45) -> 2 | L45: =B45*Opportunities!P8+C45*Opportunities!P9+D45*Opportunities!P10+E45*Opportunities!P11+F45*Opportunities!P12+G45*Opportunities!P13+H45*Opportunities!P14+I45*Opportunities!P15 -> 94534.782 | M45: =IF(AND(J45<=Assumptions!$B$6,K45<=Assumptions!$B$7,B45*IF(Opportunities!S8="ELIGIBLE",0,1)+C45*IF(Opportunities!S9="ELIGIBLE",0,1)+D45*IF(Opportunities!S10="ELIGIBLE",0,1)+E45*IF(Opportunities!S11="ELIGIBLE",0,1)+F45*IF(Opportunities!S12="ELIGIBLE",0,1)+G45*IF(Opportunities!S13="ELIGIBLE",0,1)+H45*IF(Opportunities!S14="ELIGIBLE",0,1)+I45*IF(Opportunities!S15="ELIGIBLE",0,1)=0),1,0) -> 0 | N45: =IF(M45=1,L45,-1E99) -> -1e+99
A46: 41 | B46: 1 | C46: 0 | D46: 0 | E46: 1 | F46: 0 | G46: 1 | H46: 0 | I46: 0 | J46: =B46*Opportunities!L8+C46*Opportunities!L9+D46*Opportunities!L10+E46*Opportunities!L11+F46*Opportunities!L12+G46*Opportunities!L13+H46*Opportunities!L14+I46*Opportunities!L15 -> 2001000 | K46: =SUM(B46:I46) -> 3 | L46: =B46*Opportunities!P8+C46*Opportunities!P9+D46*Opportunities!P10+E46*Opportunities!P11+F46*Opportunities!P12+G46*Opportunities!P13+H46*Opportunities!P14+I46*Opportunities!P15 -> 185431.3 | M46: =IF(AND(J46<=Assumptions!$B$6,K46<=Assumptions!$B$7,B46*IF(Opportunities!S8="ELIGIBLE",0,1)+C46*IF(Opportunities!S9="ELIGIBLE",0,1)+D46*IF(Opportunities!S10="ELIGIBLE",0,1)+E46*IF(Opportunities!S11="ELIGIBLE",0,1)+F46*IF(Opportunities!S12="ELIGIBLE",0,1)+G46*IF(Opportunities!S13="ELIGIBLE",0,1)+H46*IF(Opportunities!S14="ELIGIBLE",0,1)+I46*IF(Opportunities!S15="ELIGIBLE",0,1)=0),1,0) -> 0 | N46: =IF(M46=1,L46,-1E99) -> -1e+99
A47: 42 | B47: 0 | C47: 1 | D47: 0 | E47: 1 | F47: 0 | G47: 1 | H47: 0 | I47: 0 | J47: =B47*Opportunities!L8+C47*Opportunities!L9+D47*Opportunities!L10+E47*Opportunities!L11+F47*Opportunities!L12+G47*Opportunities!L13+H47*Opportunities!L14+I47*Opportunities!L15 -> 1716500 | K47: =SUM(B47:I47) -> 3 | L47: =B47*Opportunities!P8+C47*Opportunities!P9+D47*Opportunities!P10+E47*Opportunities!P11+F47*Opportunities!P12+G47*Opportunities!P13+H47*Opportunities!P14+I47*Opportunities!P15 -> 170663.18 | M47: =IF(AND(J47<=Assumptions!$B$6,K47<=Assumptions!$B$7,B47*IF(Opportunities!S8="ELIGIBLE",0,1)+C47*IF(Opportunities!S9="ELIGIBLE",0,1)+D47*IF(Opportunities!S10="ELIGIBLE",0,1)+E47*IF(Opportunities!S11="ELIGIBLE",0,1)+F47*IF(Opportunities!S12="ELIGIBLE",0,1)+G47*IF(Opportunities!S13="ELIGIBLE",0,1)+H47*IF(Opportunities!S14="ELIGIBLE",0,1)+I47*IF(Opportunities!S15="ELIGIBLE",0,1)=0),1,0) -> 0 | N47: =IF(M47=1,L47,-1E99) -> -1e+99
A48: 43 | B48: 1 | C48: 1 | D48: 0 | E48: 1 | F48: 0 | G48: 1 | H48: 0 | I48: 0 | J48: =B48*Opportunities!L8+C48*Opportunities!L9+D48*Opportunities!L10+E48*Opportunities!L11+F48*Opportunities!L12+G48*Opportunities!L13+H48*Opportunities!L14+I48*Opportunities!L15 -> 2586000 | K48: =SUM(B48:I48) -> 4 | L48: =B48*Opportunities!P8+C48*Opportunities!P9+D48*Opportunities!P10+E48*Opportunities!P11+F48*Opportunities!P12+G48*Opportunities!P13+H48*Opportunities!P14+I48*Opportunities!P15 -> 261559.7 | M48: =IF(AND(J48<=Assumptions!$B$6,K48<=Assumptions!$B$7,B48*IF(Opportunities!S8="ELIGIBLE",0,1)+C48*IF(Opportunities!S9="ELIGIBLE",0,1)+D48*IF(Opportunities!S10="ELIGIBLE",0,1)+E48*IF(Opportunities!S11="ELIGIBLE",0,1)+F48*IF(Opportunities!S12="ELIGIBLE",0,1)+G48*IF(Opportunities!S13="ELIGIBLE",0,1)+H48*IF(Opportunities!S14="ELIGIBLE",0,1)+I48*IF(Opportunities!S15="ELIGIBLE",0,1)=0),1,0) -> 0 | N48: =IF(M48=1,L48,-1E99) -> -1e+99
A49: 44 | B49: 0 | C49: 0 | D49: 1 | E49: 1 | F49: 0 | G49: 1 | H49: 0 | I49: 0 | J49: =B49*Opportunities!L8+C49*Opportunities!L9+D49*Opportunities!L10+E49*Opportunities!L11+F49*Opportunities!L12+G49*Opportunities!L13+H49*Opportunities!L14+I49*Opportunities!L15 -> 2712500 | K49: =SUM(B49:I49) -> 3 | L49: =B49*Opportunities!P8+C49*Opportunities!P9+D49*Opportunities!P10+E49*Opportunities!P11+F49*Opportunities!P12+G49*Opportunities!P13+H49*Opportunities!P14+I49*Opportunities!P15 -> 149318.5 | M49: =IF(AND(J49<=Assumptions!$B$6,K49<=Assumptions!$B$7,B49*IF(Opportunities!S8="ELIGIBLE",0,1)+C49*IF(Opportunities!S9="ELIGIBLE",0,1)+D49*IF(Opportunities!S10="ELIGIBLE",0,1)+E49*IF(Opportunities!S11="ELIGIBLE",0,1)+F49*IF(Opportunities!S12="ELIGIBLE",0,1)+G49*IF(Opportunities!S13="ELIGIBLE",0,1)+H49*IF(Opportunities!S14="ELIGIBLE",0,1)+I49*IF(Opportunities!S15="ELIGIBLE",0,1)=0),1,0) -> 0 | N49: =IF(M49=1,L49,-1E99) -> -1e+99
A50: 45 | B50: 1 | C50: 0 | D50: 1 | E50: 1 | F50: 0 | G50: 1 | H50: 0 | I50: 0 | J50: =B50*Opportunities!L8+C50*Opportunities!L9+D50*Opportunities!L10+E50*Opportunities!L11+F50*Opportunities!L12+G50*Opportunities!L13+H50*Opportunities!L14+I50*Opportunities!L15 -> 3582000 | K50: =SUM(B50:I50) -> 4 | L50: =B50*Opportunities!P8+C50*Opportunities!P9+D50*Opportunities!P10+E50*Opportunities!P11+F50*Opportunities!P12+G50*Opportunities!P13+H50*Opportunities!P14+I50*Opportunities!P15 -> 240215.01 | M50: =IF(AND(J50<=Assumptions!$B$6,K50<=Assumptions!$B$7,B50*IF(Opportunities!S8="ELIGIBLE",0,1)+C50*IF(Opportunities!S9="ELIGIBLE",0,1)+D50*IF(Opportunities!S10="ELIGIBLE",0,1)+E50*IF(Opportunities!S11="ELIGIBLE",0,1)+F50*IF(Opportunities!S12="ELIGIBLE",0,1)+G50*IF(Opportunities!S13="ELIGIBLE",0,1)+H50*IF(Opportunities!S14="ELIGIBLE",0,1)+I50*IF(Opportunities!S15="ELIGIBLE",0,1)=0),1,0) -> 0 | N50: =IF(M50=1,L50,-1E99) -> -1e+99
A51: 46 | B51: 0 | C51: 1 | D51: 1 | E51: 1 | F51: 0 | G51: 1 | H51: 0 | I51: 0 | J51: =B51*Opportunities!L8+C51*Opportunities!L9+D51*Opportunities!L10+E51*Opportunities!L11+F51*Opportunities!L12+G51*Opportunities!L13+H51*Opportunities!L14+I51*Opportunities!L15 -> 3297500 | K51: =SUM(B51:I51) -> 4 | L51: =B51*Opportunities!P8+C51*Opportunities!P9+D51*Opportunities!P10+E51*Opportunities!P11+F51*Opportunities!P12+G51*Opportunities!P13+H51*Opportunities!P14+I51*Opportunities!P15 -> 225446.9 | M51: =IF(AND(J51<=Assumptions!$B$6,K51<=Assumptions!$B$7,B51*IF(Opportunities!S8="ELIGIBLE",0,1)+C51*IF(Opportunities!S9="ELIGIBLE",0,1)+D51*IF(Opportunities!S10="ELIGIBLE",0,1)+E51*IF(Opportunities!S11="ELIGIBLE",0,1)+F51*IF(Opportunities!S12="ELIGIBLE",0,1)+G51*IF(Opportunities!S13="ELIGIBLE",0,1)+H51*IF(Opportunities!S14="ELIGIBLE",0,1)+I51*IF(Opportunities!S15="ELIGIBLE",0,1)=0),1,0) -> 0 | N51: =IF(M51=1,L51,-1E99) -> -1e+99
A52: 47 | B52: 1 | C52: 1 | D52: 1 | E52: 1 | F52: 0 | G52: 1 | H52: 0 | I52: 0 | J52: =B52*Opportunities!L8+C52*Opportunities!L9+D52*Opportunities!L10+E52*Opportunities!L11+F52*Opportunities!L12+G52*Opportunities!L13+H52*Opportunities!L14+I52*Opportunities!L15 -> 4167000 | K52: =SUM(B52:I52) -> 5 | L52: =B52*Opportunities!P8+C52*Opportunities!P9+D52*Opportunities!P10+E52*Opportunities!P11+F52*Opportunities!P12+G52*Opportunities!P13+H52*Opportunities!P14+I52*Opportunities!P15 -> 316343.42 | M52: =IF(AND(J52<=Assumptions!$B$6,K52<=Assumptions!$B$7,B52*IF(Opportunities!S8="ELIGIBLE",0,1)+C52*IF(Opportunities!S9="ELIGIBLE",0,1)+D52*IF(Opportunities!S10="ELIGIBLE",0,1)+E52*IF(Opportunities!S11="ELIGIBLE",0,1)+F52*IF(Opportunities!S12="ELIGIBLE",0,1)+G52*IF(Opportunities!S13="ELIGIBLE",0,1)+H52*IF(Opportunities!S14="ELIGIBLE",0,1)+I52*IF(Opportunities!S15="ELIGIBLE",0,1)=0),1,0) -> 0 | N52: =IF(M52=1,L52,-1E99) -> -1e+99
A53: 48 | B53: 0 | C53: 0 | D53: 0 | E53: 0 | F53: 1 | G53: 1 | H53: 0 | I53: 0 | J53: =B53*Opportunities!L8+C53*Opportunities!L9+D53*Opportunities!L10+E53*Opportunities!L11+F53*Opportunities!L12+G53*Opportunities!L13+H53*Opportunities!L14+I53*Opportunities!L15 -> 1942250 | K53: =SUM(B53:I53) -> 2 | L53: =B53*Opportunities!P8+C53*Opportunities!P9+D53*Opportunities!P10+E53*Opportunities!P11+F53*Opportunities!P12+G53*Opportunities!P13+H53*Opportunities!P14+I53*Opportunities!P15 -> -102845.38 | M53: =IF(AND(J53<=Assumptions!$B$6,K53<=Assumptions!$B$7,B53*IF(Opportunities!S8="ELIGIBLE",0,1)+C53*IF(Opportunities!S9="ELIGIBLE",0,1)+D53*IF(Opportunities!S10="ELIGIBLE",0,1)+E53*IF(Opportunities!S11="ELIGIBLE",0,1)+F53*IF(Opportunities!S12="ELIGIBLE",0,1)+G53*IF(Opportunities!S13="ELIGIBLE",0,1)+H53*IF(Opportunities!S14="ELIGIBLE",0,1)+I53*IF(Opportunities!S15="ELIGIBLE",0,1)=0),1,0) -> 0 | N53: =IF(M53=1,L53,-1E99) -> -1e+99
A54: 49 | B54: 1 | C54: 0 | D54: 0 | E54: 0 | F54: 1 | G54: 1 | H54: 0 | I54: 0 | J54: =B54*Opportunities!L8+C54*Opportunities!L9+D54*Opportunities!L10+E54*Opportunities!L11+F54*Opportunities!L12+G54*Opportunities!L13+H54*Opportunities!L14+I54*Opportunities!L15 -> 2811750 | K54: =SUM(B54:I54) -> 3 | L54: =B54*Opportunities!P8+C54*Opportunities!P9+D54*Opportunities!P10+E54*Opportunities!P11+F54*Opportunities!P12+G54*Opportunities!P13+H54*Opportunities!P14+I54*Opportunities!P15 -> -11948.864 | M54: =IF(AND(J54<=Assumptions!$B$6,K54<=Assumptions!$B$7,B54*IF(Opportunities!S8="ELIGIBLE",0,1)+C54*IF(Opportunities!S9="ELIGIBLE",0,1)+D54*IF(Opportunities!S10="ELIGIBLE",0,1)+E54*IF(Opportunities!S11="ELIGIBLE",0,1)+F54*IF(Opportunities!S12="ELIGIBLE",0,1)+G54*IF(Opportunities!S13="ELIGIBLE",0,1)+H54*IF(Opportunities!S14="ELIGIBLE",0,1)+I54*IF(Opportunities!S15="ELIGIBLE",0,1)=0),1,0) -> 0 | N54: =IF(M54=1,L54,-1E99) -> -1e+99
A55: 50 | B55: 0 | C55: 1 | D55: 0 | E55: 0 | F55: 1 | G55: 1 | H55: 0 | I55: 0 | J55: =B55*Opportunities!L8+C55*Opportunities!L9+D55*Opportunities!L10+E55*Opportunities!L11+F55*Opportunities!L12+G55*Opportunities!L13+H55*Opportunities!L14+I55*Opportunities!L15 -> 2527250 | K55: =SUM(B55:I55) -> 3 | L55: =B55*Opportunities!P8+C55*Opportunities!P9+D55*Opportunities!P10+E55*Opportunities!P11+F55*Opportunities!P12+G55*Opportunities!P13+H55*Opportunities!P14+I55*Opportunities!P15 -> -26716.979 | M55: =IF(AND(J55<=Assumptions!$B$6,K55<=Assumptions!$B$7,B55*IF(Opportunities!S8="ELIGIBLE",0,1)+C55*IF(Opportunities!S9="ELIGIBLE",0,1)+D55*IF(Opportunities!S10="ELIGIBLE",0,1)+E55*IF(Opportunities!S11="ELIGIBLE",0,1)+F55*IF(Opportunities!S12="ELIGIBLE",0,1)+G55*IF(Opportunities!S13="ELIGIBLE",0,1)+H55*IF(Opportunities!S14="ELIGIBLE",0,1)+I55*IF(Opportunities!S15="ELIGIBLE",0,1)=0),1,0) -> 0 | N55: =IF(M55=1,L55,-1E99) -> -1e+99
A56: 51 | B56: 1 | C56: 1 | D56: 0 | E56: 0 | F56: 1 | G56: 1 | H56: 0 | I56: 0 | J56: =B56*Opportunities!L8+C56*Opportunities!L9+D56*Opportunities!L10+E56*Opportunities!L11+F56*Opportunities!L12+G56*Opportunities!L13+H56*Opportunities!L14+I56*Opportunities!L15 -> 3396750 | K56: =SUM(B56:I56) -> 4 | L56: =B56*Opportunities!P8+C56*Opportunities!P9+D56*Opportunities!P10+E56*Opportunities!P11+F56*Opportunities!P12+G56*Opportunities!P13+H56*Opportunities!P14+I56*Opportunities!P15 -> 64179.538 | M56: =IF(AND(J56<=Assumptions!$B$6,K56<=Assumptions!$B$7,B56*IF(Opportunities!S8="ELIGIBLE",0,1)+C56*IF(Opportunities!S9="ELIGIBLE",0,1)+D56*IF(Opportunities!S10="ELIGIBLE",0,1)+E56*IF(Opportunities!S11="ELIGIBLE",0,1)+F56*IF(Opportunities!S12="ELIGIBLE",0,1)+G56*IF(Opportunities!S13="ELIGIBLE",0,1)+H56*IF(Opportunities!S14="ELIGIBLE",0,1)+I56*IF(Opportunities!S15="ELIGIBLE",0,1)=0),1,0) -> 0 | N56: =IF(M56=1,L56,-1E99) -> -1e+99
A57: 52 | B57: 0 | C57: 0 | D57: 1 | E57: 0 | F57: 1 | G57: 1 | H57: 0 | I57: 0 | J57: =B57*Opportunities!L8+C57*Opportunities!L9+D57*Opportunities!L10+E57*Opportunities!L11+F57*Opportunities!L12+G57*Opportunities!L13+H57*Opportunities!L14+I57*Opportunities!L15 -> 3523250 | K57: =SUM(B57:I57) -> 3 | L57: =B57*Opportunities!P8+C57*Opportunities!P9+D57*Opportunities!P10+E57*Opportunities!P11+F57*Opportunities!P12+G57*Opportunities!P13+H57*Opportunities!P14+I57*Opportunities!P15 -> -48061.666 | M57: =IF(AND(J57<=Assumptions!$B$6,K57<=Assumptions!$B$7,B57*IF(Opportunities!S8="ELIGIBLE",0,1)+C57*IF(Opportunities!S9="ELIGIBLE",0,1)+D57*IF(Opportunities!S10="ELIGIBLE",0,1)+E57*IF(Opportunities!S11="ELIGIBLE",0,1)+F57*IF(Opportunities!S12="ELIGIBLE",0,1)+G57*IF(Opportunities!S13="ELIGIBLE",0,1)+H57*IF(Opportunities!S14="ELIGIBLE",0,1)+I57*IF(Opportunities!S15="ELIGIBLE",0,1)=0),1,0) -> 0 | N57: =IF(M57=1,L57,-1E99) -> -1e+99
A58: 53 | B58: 1 | C58: 0 | D58: 1 | E58: 0 | F58: 1 | G58: 1 | H58: 0 | I58: 0 | J58: =B58*Opportunities!L8+C58*Opportunities!L9+D58*Opportunities!L10+E58*Opportunities!L11+F58*Opportunities!L12+G58*Opportunities!L13+H58*Opportunities!L14+I58*Opportunities!L15 -> 4392750 | K58: =SUM(B58:I58) -> 4 | L58: =B58*Opportunities!P8+C58*Opportunities!P9+D58*Opportunities!P10+E58*Opportunities!P11+F58*Opportunities!P12+G58*Opportunities!P13+H58*Opportunities!P14+I58*Opportunities!P15 -> 42834.851 | M58: =IF(AND(J58<=Assumptions!$B$6,K58<=Assumptions!$B$7,B58*IF(Opportunities!S8="ELIGIBLE",0,1)+C58*IF(Opportunities!S9="ELIGIBLE",0,1)+D58*IF(Opportunities!S10="ELIGIBLE",0,1)+E58*IF(Opportunities!S11="ELIGIBLE",0,1)+F58*IF(Opportunities!S12="ELIGIBLE",0,1)+G58*IF(Opportunities!S13="ELIGIBLE",0,1)+H58*IF(Opportunities!S14="ELIGIBLE",0,1)+I58*IF(Opportunities!S15="ELIGIBLE",0,1)=0),1,0) -> 0 | N58: =IF(M58=1,L58,-1E99) -> -1e+99
A59: 54 | B59: 0 | C59: 1 | D59: 1 | E59: 0 | F59: 1 | G59: 1 | H59: 0 | I59: 0 | J59: =B59*Opportunities!L8+C59*Opportunities!L9+D59*Opportunities!L10+E59*Opportunities!L11+F59*Opportunities!L12+G59*Opportunities!L13+H59*Opportunities!L14+I59*Opportunities!L15 -> 4108250 | K59: =SUM(B59:I59) -> 4 | L59: =B59*Opportunities!P8+C59*Opportunities!P9+D59*Opportunities!P10+E59*Opportunities!P11+F59*Opportunities!P12+G59*Opportunities!P13+H59*Opportunities!P14+I59*Opportunities!P15 -> 28066.737 | M59: =IF(AND(J59<=Assumptions!$B$6,K59<=Assumptions!$B$7,B59*IF(Opportunities!S8="ELIGIBLE",0,1)+C59*IF(Opportunities!S9="ELIGIBLE",0,1)+D59*IF(Opportunities!S10="ELIGIBLE",0,1)+E59*IF(Opportunities!S11="ELIGIBLE",0,1)+F59*IF(Opportunities!S12="ELIGIBLE",0,1)+G59*IF(Opportunities!S13="ELIGIBLE",0,1)+H59*IF(Opportunities!S14="ELIGIBLE",0,1)+I59*IF(Opportunities!S15="ELIGIBLE",0,1)=0),1,0) -> 0 | N59: =IF(M59=1,L59,-1E99) -> -1e+99
A60: 55 | B60: 1 | C60: 1 | D60: 1 | E60: 0 | F60: 1 | G60: 1 | H60: 0 | I60: 0 | J60: =B60*Opportunities!L8+C60*Opportunities!L9+D60*Opportunities!L10+E60*Opportunities!L11+F60*Opportunities!L12+G60*Opportunities!L13+H60*Opportunities!L14+I60*Opportunities!L15 -> 4977750 | K60: =SUM(B60:I60) -> 5 | L60: =B60*Opportunities!P8+C60*Opportunities!P9+D60*Opportunities!P10+E60*Opportunities!P11+F60*Opportunities!P12+G60*Opportunities!P13+H60*Opportunities!P14+I60*Opportunities!P15 -> 118963.25 | M60: =IF(AND(J60<=Assumptions!$B$6,K60<=Assumptions!$B$7,B60*IF(Opportunities!S8="ELIGIBLE",0,1)+C60*IF(Opportunities!S9="ELIGIBLE",0,1)+D60*IF(Opportunities!S10="ELIGIBLE",0,1)+E60*IF(Opportunities!S11="ELIGIBLE",0,1)+F60*IF(Opportunities!S12="ELIGIBLE",0,1)+G60*IF(Opportunities!S13="ELIGIBLE",0,1)+H60*IF(Opportunities!S14="ELIGIBLE",0,1)+I60*IF(Opportunities!S15="ELIGIBLE",0,1)=0),1,0) -> 0 | N60: =IF(M60=1,L60,-1E99) -> -1e+99
A61: 56 | B61: 0 | C61: 0 | D61: 0 | E61: 1 | F61: 1 | G61: 1 | H61: 0 | I61: 0 | J61: =B61*Opportunities!L8+C61*Opportunities!L9+D61*Opportunities!L10+E61*Opportunities!L11+F61*Opportunities!L12+G61*Opportunities!L13+H61*Opportunities!L14+I61*Opportunities!L15 -> 2274500 | K61: =SUM(B61:I61) -> 3 | L61: =B61*Opportunities!P8+C61*Opportunities!P9+D61*Opportunities!P10+E61*Opportunities!P11+F61*Opportunities!P12+G61*Opportunities!P13+H61*Opportunities!P14+I61*Opportunities!P15 -> -80957.258 | M61: =IF(AND(J61<=Assumptions!$B$6,K61<=Assumptions!$B$7,B61*IF(Opportunities!S8="ELIGIBLE",0,1)+C61*IF(Opportunities!S9="ELIGIBLE",0,1)+D61*IF(Opportunities!S10="ELIGIBLE",0,1)+E61*IF(Opportunities!S11="ELIGIBLE",0,1)+F61*IF(Opportunities!S12="ELIGIBLE",0,1)+G61*IF(Opportunities!S13="ELIGIBLE",0,1)+H61*IF(Opportunities!S14="ELIGIBLE",0,1)+I61*IF(Opportunities!S15="ELIGIBLE",0,1)=0),1,0) -> 0 | N61: =IF(M61=1,L61,-1E99) -> -1e+99
A62: 57 | B62: 1 | C62: 0 | D62: 0 | E62: 1 | F62: 1 | G62: 1 | H62: 0 | I62: 0 | J62: =B62*Opportunities!L8+C62*Opportunities!L9+D62*Opportunities!L10+E62*Opportunities!L11+F62*Opportunities!L12+G62*Opportunities!L13+H62*Opportunities!L14+I62*Opportunities!L15 -> 3144000 | K62: =SUM(B62:I62) -> 4 | L62: =B62*Opportunities!P8+C62*Opportunities!P9+D62*Opportunities!P10+E62*Opportunities!P11+F62*Opportunities!P12+G62*Opportunities!P13+H62*Opportunities!P14+I62*Opportunities!P15 -> 9939.2588 | M62: =IF(AND(J62<=Assumptions!$B$6,K62<=Assumptions!$B$7,B62*IF(Opportunities!S8="ELIGIBLE",0,1)+C62*IF(Opportunities!S9="ELIGIBLE",0,1)+D62*IF(Opportunities!S10="ELIGIBLE",0,1)+E62*IF(Opportunities!S11="ELIGIBLE",0,1)+F62*IF(Opportunities!S12="ELIGIBLE",0,1)+G62*IF(Opportunities!S13="ELIGIBLE",0,1)+H62*IF(Opportunities!S14="ELIGIBLE",0,1)+I62*IF(Opportunities!S15="ELIGIBLE",0,1)=0),1,0) -> 0 | N62: =IF(M62=1,L62,-1E99) -> -1e+99
A63: 58 | B63: 0 | C63: 1 | D63: 0 | E63: 1 | F63: 1 | G63: 1 | H63: 0 | I63: 0 | J63: =B63*Opportunities!L8+C63*Opportunities!L9+D63*Opportunities!L10+E63*Opportunities!L11+F63*Opportunities!L12+G63*Opportunities!L13+H63*Opportunities!L14+I63*Opportunities!L15 -> 2859500 | K63: =SUM(B63:I63) -> 4 | L63: =B63*Opportunities!P8+C63*Opportunities!P9+D63*Opportunities!P10+E63*Opportunities!P11+F63*Opportunities!P12+G63*Opportunities!P13+H63*Opportunities!P14+I63*Opportunities!P15 -> -4828.8558 | M63: =IF(AND(J63<=Assumptions!$B$6,K63<=Assumptions!$B$7,B63*IF(Opportunities!S8="ELIGIBLE",0,1)+C63*IF(Opportunities!S9="ELIGIBLE",0,1)+D63*IF(Opportunities!S10="ELIGIBLE",0,1)+E63*IF(Opportunities!S11="ELIGIBLE",0,1)+F63*IF(Opportunities!S12="ELIGIBLE",0,1)+G63*IF(Opportunities!S13="ELIGIBLE",0,1)+H63*IF(Opportunities!S14="ELIGIBLE",0,1)+I63*IF(Opportunities!S15="ELIGIBLE",0,1)=0),1,0) -> 0 | N63: =IF(M63=1,L63,-1E99) -> -1e+99
A64: 59 | B64: 1 | C64: 1 | D64: 0 | E64: 1 | F64: 1 | G64: 1 | H64: 0 | I64: 0 | J64: =B64*Opportunities!L8+C64*Opportunities!L9+D64*Opportunities!L10+E64*Opportunities!L11+F64*Opportunities!L12+G64*Opportunities!L13+H64*Opportunities!L14+I64*Opportunities!L15 -> 3729000 | K64: =SUM(B64:I64) -> 5 | L64: =B64*Opportunities!P8+C64*Opportunities!P9+D64*Opportunities!P10+E64*Opportunities!P11+F64*Opportunities!P12+G64*Opportunities!P13+H64*Opportunities!P14+I64*Opportunities!P15 -> 86067.661 | M64: =IF(AND(J64<=Assumptions!$B$6,K64<=Assumptions!$B$7,B64*IF(Opportunities!S8="ELIGIBLE",0,1)+C64*IF(Opportunities!S9="ELIGIBLE",0,1)+D64*IF(Opportunities!S10="ELIGIBLE",0,1)+E64*IF(Opportunities!S11="ELIGIBLE",0,1)+F64*IF(Opportunities!S12="ELIGIBLE",0,1)+G64*IF(Opportunities!S13="ELIGIBLE",0,1)+H64*IF(Opportunities!S14="ELIGIBLE",0,1)+I64*IF(Opportunities!S15="ELIGIBLE",0,1)=0),1,0) -> 0 | N64: =IF(M64=1,L64,-1E99) -> -1e+99
A65: 60 | B65: 0 | C65: 0 | D65: 1 | E65: 1 | F65: 1 | G65: 1 | H65: 0 | I65: 0 | J65: =B65*Opportunities!L8+C65*Opportunities!L9+D65*Opportunities!L10+E65*Opportunities!L11+F65*Opportunities!L12+G65*Opportunities!L13+H65*Opportunities!L14+I65*Opportunities!L15 -> 3855500 | K65: =SUM(B65:I65) -> 4 | L65: =B65*Opportunities!P8+C65*Opportunities!P9+D65*Opportunities!P10+E65*Opportunities!P11+F65*Opportunities!P12+G65*Opportunities!P13+H65*Opportunities!P14+I65*Opportunities!P15 -> -26173.543 | M65: =IF(AND(J65<=Assumptions!$B$6,K65<=Assumptions!$B$7,B65*IF(Opportunities!S8="ELIGIBLE",0,1)+C65*IF(Opportunities!S9="ELIGIBLE",0,1)+D65*IF(Opportunities!S10="ELIGIBLE",0,1)+E65*IF(Opportunities!S11="ELIGIBLE",0,1)+F65*IF(Opportunities!S12="ELIGIBLE",0,1)+G65*IF(Opportunities!S13="ELIGIBLE",0,1)+H65*IF(Opportunities!S14="ELIGIBLE",0,1)+I65*IF(Opportunities!S15="ELIGIBLE",0,1)=0),1,0) -> 0 | N65: =IF(M65=1,L65,-1E99) -> -1e+99
A66: 61 | B66: 1 | C66: 0 | D66: 1 | E66: 1 | F66: 1 | G66: 1 | H66: 0 | I66: 0 | J66: =B66*Opportunities!L8+C66*Opportunities!L9+D66*Opportunities!L10+E66*Opportunities!L11+F66*Opportunities!L12+G66*Opportunities!L13+H66*Opportunities!L14+I66*Opportunities!L15 -> 4725000 | K66: =SUM(B66:I66) -> 5 | L66: =B66*Opportunities!P8+C66*Opportunities!P9+D66*Opportunities!P10+E66*Opportunities!P11+F66*Opportunities!P12+G66*Opportunities!P13+H66*Opportunities!P14+I66*Opportunities!P15 -> 64722.974 | M66: =IF(AND(J66<=Assumptions!$B$6,K66<=Assumptions!$B$7,B66*IF(Opportunities!S8="ELIGIBLE",0,1)+C66*IF(Opportunities!S9="ELIGIBLE",0,1)+D66*IF(Opportunities!S10="ELIGIBLE",0,1)+E66*IF(Opportunities!S11="ELIGIBLE",0,1)+F66*IF(Opportunities!S12="ELIGIBLE",0,1)+G66*IF(Opportunities!S13="ELIGIBLE",0,1)+H66*IF(Opportunities!S14="ELIGIBLE",0,1)+I66*IF(Opportunities!S15="ELIGIBLE",0,1)=0),1,0) -> 0 | N66: =IF(M66=1,L66,-1E99) -> -1e+99
A67: 62 | B67: 0 | C67: 1 | D67: 1 | E67: 1 | F67: 1 | G67: 1 | H67: 0 | I67: 0 | J67: =B67*Opportunities!L8+C67*Opportunities!L9+D67*Opportunities!L10+E67*Opportunities!L11+F67*Opportunities!L12+G67*Opportunities!L13+H67*Opportunities!L14+I67*Opportunities!L15 -> 4440500 | K67: =SUM(B67:I67) -> 5 | L67: =B67*Opportunities!P8+C67*Opportunities!P9+D67*Opportunities!P10+E67*Opportunities!P11+F67*Opportunities!P12+G67*Opportunities!P13+H67*Opportunities!P14+I67*Opportunities!P15 -> 49954.859 | M67: =IF(AND(J67<=Assumptions!$B$6,K67<=Assumptions!$B$7,B67*IF(Opportunities!S8="ELIGIBLE",0,1)+C67*IF(Opportunities!S9="ELIGIBLE",0,1)+D67*IF(Opportunities!S10="ELIGIBLE",0,1)+E67*IF(Opportunities!S11="ELIGIBLE",0,1)+F67*IF(Opportunities!S12="ELIGIBLE",0,1)+G67*IF(Opportunities!S13="ELIGIBLE",0,1)+H67*IF(Opportunities!S14="ELIGIBLE",0,1)+I67*IF(Opportunities!S15="ELIGIBLE",0,1)=0),1,0) -> 0 | N67: =IF(M67=1,L67,-1E99) -> -1e+99
A68: 63 | B68: 1 | C68: 1 | D68: 1 | E68: 1 | F68: 1 | G68: 1 | H68: 0 | I68: 0 | J68: =B68*Opportunities!L8+C68*Opportunities!L9+D68*Opportunities!L10+E68*Opportunities!L11+F68*Opportunities!L12+G68*Opportunities!L13+H68*Opportunities!L14+I68*Opportunities!L15 -> 5310000 | K68: =SUM(B68:I68) -> 6 | L68: =B68*Opportunities!P8+C68*Opportunities!P9+D68*Opportunities!P10+E68*Opportunities!P11+F68*Opportunities!P12+G68*Opportunities!P13+H68*Opportunities!P14+I68*Opportunities!P15 -> 140851.38 | M68: =IF(AND(J68<=Assumptions!$B$6,K68<=Assumptions!$B$7,B68*IF(Opportunities!S8="ELIGIBLE",0,1)+C68*IF(Opportunities!S9="ELIGIBLE",0,1)+D68*IF(Opportunities!S10="ELIGIBLE",0,1)+E68*IF(Opportunities!S11="ELIGIBLE",0,1)+F68*IF(Opportunities!S12="ELIGIBLE",0,1)+G68*IF(Opportunities!S13="ELIGIBLE",0,1)+H68*IF(Opportunities!S14="ELIGIBLE",0,1)+I68*IF(Opportunities!S15="ELIGIBLE",0,1)=0),1,0) -> 0 | N68: =IF(M68=1,L68,-1E99) -> -1e+99
A69: 64 | B69: 0 | C69: 0 | D69: 0 | E69: 0 | F69: 0 | G69: 0 | H69: 1 | I69: 0 | J69: =B69*Opportunities!L8+C69*Opportunities!L9+D69*Opportunities!L10+E69*Opportunities!L11+F69*Opportunities!L12+G69*Opportunities!L13+H69*Opportunities!L14+I69*Opportunities!L15 -> 0 | K69: =SUM(B69:I69) -> 1 | L69: =B69*Opportunities!P8+C69*Opportunities!P9+D69*Opportunities!P10+E69*Opportunities!P11+F69*Opportunities!P12+G69*Opportunities!P13+H69*Opportunities!P14+I69*Opportunities!P15 -> 0 | M69: =IF(AND(J69<=Assumptions!$B$6,K69<=Assumptions!$B$7,B69*IF(Opportunities!S8="ELIGIBLE",0,1)+C69*IF(Opportunities!S9="ELIGIBLE",0,1)+D69*IF(Opportunities!S10="ELIGIBLE",0,1)+E69*IF(Opportunities!S11="ELIGIBLE",0,1)+F69*IF(Opportunities!S12="ELIGIBLE",0,1)+G69*IF(Opportunities!S13="ELIGIBLE",0,1)+H69*IF(Opportunities!S14="ELIGIBLE",0,1)+I69*IF(Opportunities!S15="ELIGIBLE",0,1)=0),1,0) -> 0 | N69: =IF(M69=1,L69,-1E99) -> -1e+99
A70: 65 | B70: 1 | C70: 0 | D70: 0 | E70: 0 | F70: 0 | G70: 0 | H70: 1 | I70: 0 | J70: =B70*Opportunities!L8+C70*Opportunities!L9+D70*Opportunities!L10+E70*Opportunities!L11+F70*Opportunities!L12+G70*Opportunities!L13+H70*Opportunities!L14+I70*Opportunities!L15 -> 869500 | K70: =SUM(B70:I70) -> 2 | L70: =B70*Opportunities!P8+C70*Opportunities!P9+D70*Opportunities!P10+E70*Opportunities!P11+F70*Opportunities!P12+G70*Opportunities!P13+H70*Opportunities!P14+I70*Opportunities!P15 -> 90896.517 | M70: =IF(AND(J70<=Assumptions!$B$6,K70<=Assumptions!$B$7,B70*IF(Opportunities!S8="ELIGIBLE",0,1)+C70*IF(Opportunities!S9="ELIGIBLE",0,1)+D70*IF(Opportunities!S10="ELIGIBLE",0,1)+E70*IF(Opportunities!S11="ELIGIBLE",0,1)+F70*IF(Opportunities!S12="ELIGIBLE",0,1)+G70*IF(Opportunities!S13="ELIGIBLE",0,1)+H70*IF(Opportunities!S14="ELIGIBLE",0,1)+I70*IF(Opportunities!S15="ELIGIBLE",0,1)=0),1,0) -> 0 | N70: =IF(M70=1,L70,-1E99) -> -1e+99
A71: 66 | B71: 0 | C71: 1 | D71: 0 | E71: 0 | F71: 0 | G71: 0 | H71: 1 | I71: 0 | J71: =B71*Opportunities!L8+C71*Opportunities!L9+D71*Opportunities!L10+E71*Opportunities!L11+F71*Opportunities!L12+G71*Opportunities!L13+H71*Opportunities!L14+I71*Opportunities!L15 -> 585000 | K71: =SUM(B71:I71) -> 2 | L71: =B71*Opportunities!P8+C71*Opportunities!P9+D71*Opportunities!P10+E71*Opportunities!P11+F71*Opportunities!P12+G71*Opportunities!P13+H71*Opportunities!P14+I71*Opportunities!P15 -> 76128.402 | M71: =IF(AND(J71<=Assumptions!$B$6,K71<=Assumptions!$B$7,B71*IF(Opportunities!S8="ELIGIBLE",0,1)+C71*IF(Opportunities!S9="ELIGIBLE",0,1)+D71*IF(Opportunities!S10="ELIGIBLE",0,1)+E71*IF(Opportunities!S11="ELIGIBLE",0,1)+F71*IF(Opportunities!S12="ELIGIBLE",0,1)+G71*IF(Opportunities!S13="ELIGIBLE",0,1)+H71*IF(Opportunities!S14="ELIGIBLE",0,1)+I71*IF(Opportunities!S15="ELIGIBLE",0,1)=0),1,0) -> 0 | N71: =IF(M71=1,L71,-1E99) -> -1e+99
A72: 67 | B72: 1 | C72: 1 | D72: 0 | E72: 0 | F72: 0 | G72: 0 | H72: 1 | I72: 0 | J72: =B72*Opportunities!L8+C72*Opportunities!L9+D72*Opportunities!L10+E72*Opportunities!L11+F72*Opportunities!L12+G72*Opportunities!L13+H72*Opportunities!L14+I72*Opportunities!L15 -> 1454500 | K72: =SUM(B72:I72) -> 3 | L72: =B72*Opportunities!P8+C72*Opportunities!P9+D72*Opportunities!P10+E72*Opportunities!P11+F72*Opportunities!P12+G72*Opportunities!P13+H72*Opportunities!P14+I72*Opportunities!P15 -> 167024.92 | M72: =IF(AND(J72<=Assumptions!$B$6,K72<=Assumptions!$B$7,B72*IF(Opportunities!S8="ELIGIBLE",0,1)+C72*IF(Opportunities!S9="ELIGIBLE",0,1)+D72*IF(Opportunities!S10="ELIGIBLE",0,1)+E72*IF(Opportunities!S11="ELIGIBLE",0,1)+F72*IF(Opportunities!S12="ELIGIBLE",0,1)+G72*IF(Opportunities!S13="ELIGIBLE",0,1)+H72*IF(Opportunities!S14="ELIGIBLE",0,1)+I72*IF(Opportunities!S15="ELIGIBLE",0,1)=0),1,0) -> 0 | N72: =IF(M72=1,L72,-1E99) -> -1e+99
A73: 68 | B73: 0 | C73: 0 | D73: 1 | E73: 0 | F73: 0 | G73: 0 | H73: 1 | I73: 0 | J73: =B73*Opportunities!L8+C73*Opportunities!L9+D73*Opportunities!L10+E73*Opportunities!L11+F73*Opportunities!L12+G73*Opportunities!L13+H73*Opportunities!L14+I73*Opportunities!L15 -> 1581000 | K73: =SUM(B73:I73) -> 2 | L73: =B73*Opportunities!P8+C73*Opportunities!P9+D73*Opportunities!P10+E73*Opportunities!P11+F73*Opportunities!P12+G73*Opportunities!P13+H73*Opportunities!P14+I73*Opportunities!P15 -> 54783.715 | M73: =IF(AND(J73<=Assumptions!$B$6,K73<=Assumptions!$B$7,B73*IF(Opportunities!S8="ELIGIBLE",0,1)+C73*IF(Opportunities!S9="ELIGIBLE",0,1)+D73*IF(Opportunities!S10="ELIGIBLE",0,1)+E73*IF(Opportunities!S11="ELIGIBLE",0,1)+F73*IF(Opportunities!S12="ELIGIBLE",0,1)+G73*IF(Opportunities!S13="ELIGIBLE",0,1)+H73*IF(Opportunities!S14="ELIGIBLE",0,1)+I73*IF(Opportunities!S15="ELIGIBLE",0,1)=0),1,0) -> 0 | N73: =IF(M73=1,L73,-1E99) -> -1e+99
A74: 69 | B74: 1 | C74: 0 | D74: 1 | E74: 0 | F74: 0 | G74: 0 | H74: 1 | I74: 0 | J74: =B74*Opportunities!L8+C74*Opportunities!L9+D74*Opportunities!L10+E74*Opportunities!L11+F74*Opportunities!L12+G74*Opportunities!L13+H74*Opportunities!L14+I74*Opportunities!L15 -> 2450500 | K74: =SUM(B74:I74) -> 3 | L74: =B74*Opportunities!P8+C74*Opportunities!P9+D74*Opportunities!P10+E74*Opportunities!P11+F74*Opportunities!P12+G74*Opportunities!P13+H74*Opportunities!P14+I74*Opportunities!P15 -> 145680.23 | M74: =IF(AND(J74<=Assumptions!$B$6,K74<=Assumptions!$B$7,B74*IF(Opportunities!S8="ELIGIBLE",0,1)+C74*IF(Opportunities!S9="ELIGIBLE",0,1)+D74*IF(Opportunities!S10="ELIGIBLE",0,1)+E74*IF(Opportunities!S11="ELIGIBLE",0,1)+F74*IF(Opportunities!S12="ELIGIBLE",0,1)+G74*IF(Opportunities!S13="ELIGIBLE",0,1)+H74*IF(Opportunities!S14="ELIGIBLE",0,1)+I74*IF(Opportunities!S15="ELIGIBLE",0,1)=0),1,0) -> 0 | N74: =IF(M74=1,L74,-1E99) -> -1e+99
A75: 70 | B75: 0 | C75: 1 | D75: 1 | E75: 0 | F75: 0 | G75: 0 | H75: 1 | I75: 0 | J75: =B75*Opportunities!L8+C75*Opportunities!L9+D75*Opportunities!L10+E75*Opportunities!L11+F75*Opportunities!L12+G75*Opportunities!L13+H75*Opportunities!L14+I75*Opportunities!L15 -> 2166000 | K75: =SUM(B75:I75) -> 3 | L75: =B75*Opportunities!P8+C75*Opportunities!P9+D75*Opportunities!P10+E75*Opportunities!P11+F75*Opportunities!P12+G75*Opportunities!P13+H75*Opportunities!P14+I75*Opportunities!P15 -> 130912.12 | M75: =IF(AND(J75<=Assumptions!$B$6,K75<=Assumptions!$B$7,B75*IF(Opportunities!S8="ELIGIBLE",0,1)+C75*IF(Opportunities!S9="ELIGIBLE",0,1)+D75*IF(Opportunities!S10="ELIGIBLE",0,1)+E75*IF(Opportunities!S11="ELIGIBLE",0,1)+F75*IF(Opportunities!S12="ELIGIBLE",0,1)+G75*IF(Opportunities!S13="ELIGIBLE",0,1)+H75*IF(Opportunities!S14="ELIGIBLE",0,1)+I75*IF(Opportunities!S15="ELIGIBLE",0,1)=0),1,0) -> 0 | N75: =IF(M75=1,L75,-1E99) -> -1e+99
A76: 71 | B76: 1 | C76: 1 | D76: 1 | E76: 0 | F76: 0 | G76: 0 | H76: 1 | I76: 0 | J76: =B76*Opportunities!L8+C76*Opportunities!L9+D76*Opportunities!L10+E76*Opportunities!L11+F76*Opportunities!L12+G76*Opportunities!L13+H76*Opportunities!L14+I76*Opportunities!L15 -> 3035500 | K76: =SUM(B76:I76) -> 4 | L76: =B76*Opportunities!P8+C76*Opportunities!P9+D76*Opportunities!P10+E76*Opportunities!P11+F76*Opportunities!P12+G76*Opportunities!P13+H76*Opportunities!P14+I76*Opportunities!P15 -> 221808.63 | M76: =IF(AND(J76<=Assumptions!$B$6,K76<=Assumptions!$B$7,B76*IF(Opportunities!S8="ELIGIBLE",0,1)+C76*IF(Opportunities!S9="ELIGIBLE",0,1)+D76*IF(Opportunities!S10="ELIGIBLE",0,1)+E76*IF(Opportunities!S11="ELIGIBLE",0,1)+F76*IF(Opportunities!S12="ELIGIBLE",0,1)+G76*IF(Opportunities!S13="ELIGIBLE",0,1)+H76*IF(Opportunities!S14="ELIGIBLE",0,1)+I76*IF(Opportunities!S15="ELIGIBLE",0,1)=0),1,0) -> 0 | N76: =IF(M76=1,L76,-1E99) -> -1e+99
A77: 72 | B77: 0 | C77: 0 | D77: 0 | E77: 1 | F77: 0 | G77: 0 | H77: 1 | I77: 0 | J77: =B77*Opportunities!L8+C77*Opportunities!L9+D77*Opportunities!L10+E77*Opportunities!L11+F77*Opportunities!L12+G77*Opportunities!L13+H77*Opportunities!L14+I77*Opportunities!L15 -> 332250 | K77: =SUM(B77:I77) -> 2 | L77: =B77*Opportunities!P8+C77*Opportunities!P9+D77*Opportunities!P10+E77*Opportunities!P11+F77*Opportunities!P12+G77*Opportunities!P13+H77*Opportunities!P14+I77*Opportunities!P15 -> 21888.123 | M77: =IF(AND(J77<=Assumptions!$B$6,K77<=Assumptions!$B$7,B77*IF(Opportunities!S8="ELIGIBLE",0,1)+C77*IF(Opportunities!S9="ELIGIBLE",0,1)+D77*IF(Opportunities!S10="ELIGIBLE",0,1)+E77*IF(Opportunities!S11="ELIGIBLE",0,1)+F77*IF(Opportunities!S12="ELIGIBLE",0,1)+G77*IF(Opportunities!S13="ELIGIBLE",0,1)+H77*IF(Opportunities!S14="ELIGIBLE",0,1)+I77*IF(Opportunities!S15="ELIGIBLE",0,1)=0),1,0) -> 0 | N77: =IF(M77=1,L77,-1E99) -> -1e+99
A78: 73 | B78: 1 | C78: 0 | D78: 0 | E78: 1 | F78: 0 | G78: 0 | H78: 1 | I78: 0 | J78: =B78*Opportunities!L8+C78*Opportunities!L9+D78*Opportunities!L10+E78*Opportunities!L11+F78*Opportunities!L12+G78*Opportunities!L13+H78*Opportunities!L14+I78*Opportunities!L15 -> 1201750 | K78: =SUM(B78:I78) -> 3 | L78: =B78*Opportunities!P8+C78*Opportunities!P9+D78*Opportunities!P10+E78*Opportunities!P11+F78*Opportunities!P12+G78*Opportunities!P13+H78*Opportunities!P14+I78*Opportunities!P15 -> 112784.64 | M78: =IF(AND(J78<=Assumptions!$B$6,K78<=Assumptions!$B$7,B78*IF(Opportunities!S8="ELIGIBLE",0,1)+C78*IF(Opportunities!S9="ELIGIBLE",0,1)+D78*IF(Opportunities!S10="ELIGIBLE",0,1)+E78*IF(Opportunities!S11="ELIGIBLE",0,1)+F78*IF(Opportunities!S12="ELIGIBLE",0,1)+G78*IF(Opportunities!S13="ELIGIBLE",0,1)+H78*IF(Opportunities!S14="ELIGIBLE",0,1)+I78*IF(Opportunities!S15="ELIGIBLE",0,1)=0),1,0) -> 0 | N78: =IF(M78=1,L78,-1E99) -> -1e+99
A79: 74 | B79: 0 | C79: 1 | D79: 0 | E79: 1 | F79: 0 | G79: 0 | H79: 1 | I79: 0 | J79: =B79*Opportunities!L8+C79*Opportunities!L9+D79*Opportunities!L10+E79*Opportunities!L11+F79*Opportunities!L12+G79*Opportunities!L13+H79*Opportunities!L14+I79*Opportunities!L15 -> 917250 | K79: =SUM(B79:I79) -> 3 | L79: =B79*Opportunities!P8+C79*Opportunities!P9+D79*Opportunities!P10+E79*Opportunities!P11+F79*Opportunities!P12+G79*Opportunities!P13+H79*Opportunities!P14+I79*Opportunities!P15 -> 98016.525 | M79: =IF(AND(J79<=Assumptions!$B$6,K79<=Assumptions!$B$7,B79*IF(Opportunities!S8="ELIGIBLE",0,1)+C79*IF(Opportunities!S9="ELIGIBLE",0,1)+D79*IF(Opportunities!S10="ELIGIBLE",0,1)+E79*IF(Opportunities!S11="ELIGIBLE",0,1)+F79*IF(Opportunities!S12="ELIGIBLE",0,1)+G79*IF(Opportunities!S13="ELIGIBLE",0,1)+H79*IF(Opportunities!S14="ELIGIBLE",0,1)+I79*IF(Opportunities!S15="ELIGIBLE",0,1)=0),1,0) -> 0 | N79: =IF(M79=1,L79,-1E99) -> -1e+99
A80: 75 | B80: 1 | C80: 1 | D80: 0 | E80: 1 | F80: 0 | G80: 0 | H80: 1 | I80: 0 | J80: =B80*Opportunities!L8+C80*Opportunities!L9+D80*Opportunities!L10+E80*Opportunities!L11+F80*Opportunities!L12+G80*Opportunities!L13+H80*Opportunities!L14+I80*Opportunities!L15 -> 1786750 | K80: =SUM(B80:I80) -> 4 | L80: =B80*Opportunities!P8+C80*Opportunities!P9+D80*Opportunities!P10+E80*Opportunities!P11+F80*Opportunities!P12+G80*Opportunities!P13+H80*Opportunities!P14+I80*Opportunities!P15 -> 188913.04 | M80: =IF(AND(J80<=Assumptions!$B$6,K80<=Assumptions!$B$7,B80*IF(Opportunities!S8="ELIGIBLE",0,1)+C80*IF(Opportunities!S9="ELIGIBLE",0,1)+D80*IF(Opportunities!S10="ELIGIBLE",0,1)+E80*IF(Opportunities!S11="ELIGIBLE",0,1)+F80*IF(Opportunities!S12="ELIGIBLE",0,1)+G80*IF(Opportunities!S13="ELIGIBLE",0,1)+H80*IF(Opportunities!S14="ELIGIBLE",0,1)+I80*IF(Opportunities!S15="ELIGIBLE",0,1)=0),1,0) -> 0 | N80: =IF(M80=1,L80,-1E99) -> -1e+99
A81: 76 | B81: 0 | C81: 0 | D81: 1 | E81: 1 | F81: 0 | G81: 0 | H81: 1 | I81: 0 | J81: =B81*Opportunities!L8+C81*Opportunities!L9+D81*Opportunities!L10+E81*Opportunities!L11+F81*Opportunities!L12+G81*Opportunities!L13+H81*Opportunities!L14+I81*Opportunities!L15 -> 1913250 | K81: =SUM(B81:I81) -> 3 | L81: =B81*Opportunities!P8+C81*Opportunities!P9+D81*Opportunities!P10+E81*Opportunities!P11+F81*Opportunities!P12+G81*Opportunities!P13+H81*Opportunities!P14+I81*Opportunities!P15 -> 76671.838 | M81: =IF(AND(J81<=Assumptions!$B$6,K81<=Assumptions!$B$7,B81*IF(Opportunities!S8="ELIGIBLE",0,1)+C81*IF(Opportunities!S9="ELIGIBLE",0,1)+D81*IF(Opportunities!S10="ELIGIBLE",0,1)+E81*IF(Opportunities!S11="ELIGIBLE",0,1)+F81*IF(Opportunities!S12="ELIGIBLE",0,1)+G81*IF(Opportunities!S13="ELIGIBLE",0,1)+H81*IF(Opportunities!S14="ELIGIBLE",0,1)+I81*IF(Opportunities!S15="ELIGIBLE",0,1)=0),1,0) -> 0 | N81: =IF(M81=1,L81,-1E99) -> -1e+99
A82: 77 | B82: 1 | C82: 0 | D82: 1 | E82: 1 | F82: 0 | G82: 0 | H82: 1 | I82: 0 | J82: =B82*Opportunities!L8+C82*Opportunities!L9+D82*Opportunities!L10+E82*Opportunities!L11+F82*Opportunities!L12+G82*Opportunities!L13+H82*Opportunities!L14+I82*Opportunities!L15 -> 2782750 | K82: =SUM(B82:I82) -> 4 | L82: =B82*Opportunities!P8+C82*Opportunities!P9+D82*Opportunities!P10+E82*Opportunities!P11+F82*Opportunities!P12+G82*Opportunities!P13+H82*Opportunities!P14+I82*Opportunities!P15 -> 167568.35 | M82: =IF(AND(J82<=Assumptions!$B$6,K82<=Assumptions!$B$7,B82*IF(Opportunities!S8="ELIGIBLE",0,1)+C82*IF(Opportunities!S9="ELIGIBLE",0,1)+D82*IF(Opportunities!S10="ELIGIBLE",0,1)+E82*IF(Opportunities!S11="ELIGIBLE",0,1)+F82*IF(Opportunities!S12="ELIGIBLE",0,1)+G82*IF(Opportunities!S13="ELIGIBLE",0,1)+H82*IF(Opportunities!S14="ELIGIBLE",0,1)+I82*IF(Opportunities!S15="ELIGIBLE",0,1)=0),1,0) -> 0 | N82: =IF(M82=1,L82,-1E99) -> -1e+99
A83: 78 | B83: 0 | C83: 1 | D83: 1 | E83: 1 | F83: 0 | G83: 0 | H83: 1 | I83: 0 | J83: =B83*Opportunities!L8+C83*Opportunities!L9+D83*Opportunities!L10+E83*Opportunities!L11+F83*Opportunities!L12+G83*Opportunities!L13+H83*Opportunities!L14+I83*Opportunities!L15 -> 2498250 | K83: =SUM(B83:I83) -> 4 | L83: =B83*Opportunities!P8+C83*Opportunities!P9+D83*Opportunities!P10+E83*Opportunities!P11+F83*Opportunities!P12+G83*Opportunities!P13+H83*Opportunities!P14+I83*Opportunities!P15 -> 152800.24 | M83: =IF(AND(J83<=Assumptions!$B$6,K83<=Assumptions!$B$7,B83*IF(Opportunities!S8="ELIGIBLE",0,1)+C83*IF(Opportunities!S9="ELIGIBLE",0,1)+D83*IF(Opportunities!S10="ELIGIBLE",0,1)+E83*IF(Opportunities!S11="ELIGIBLE",0,1)+F83*IF(Opportunities!S12="ELIGIBLE",0,1)+G83*IF(Opportunities!S13="ELIGIBLE",0,1)+H83*IF(Opportunities!S14="ELIGIBLE",0,1)+I83*IF(Opportunities!S15="ELIGIBLE",0,1)=0),1,0) -> 0 | N83: =IF(M83=1,L83,-1E99) -> -1e+99
A84: 79 | B84: 1 | C84: 1 | D84: 1 | E84: 1 | F84: 0 | G84: 0 | H84: 1 | I84: 0 | J84: =B84*Opportunities!L8+C84*Opportunities!L9+D84*Opportunities!L10+E84*Opportunities!L11+F84*Opportunities!L12+G84*Opportunities!L13+H84*Opportunities!L14+I84*Opportunities!L15 -> 3367750 | K84: =SUM(B84:I84) -> 5 | L84: =B84*Opportunities!P8+C84*Opportunities!P9+D84*Opportunities!P10+E84*Opportunities!P11+F84*Opportunities!P12+G84*Opportunities!P13+H84*Opportunities!P14+I84*Opportunities!P15 -> 243696.76 | M84: =IF(AND(J84<=Assumptions!$B$6,K84<=Assumptions!$B$7,B84*IF(Opportunities!S8="ELIGIBLE",0,1)+C84*IF(Opportunities!S9="ELIGIBLE",0,1)+D84*IF(Opportunities!S10="ELIGIBLE",0,1)+E84*IF(Opportunities!S11="ELIGIBLE",0,1)+F84*IF(Opportunities!S12="ELIGIBLE",0,1)+G84*IF(Opportunities!S13="ELIGIBLE",0,1)+H84*IF(Opportunities!S14="ELIGIBLE",0,1)+I84*IF(Opportunities!S15="ELIGIBLE",0,1)=0),1,0) -> 0 | N84: =IF(M84=1,L84,-1E99) -> -1e+99
A85: 80 | B85: 0 | C85: 0 | D85: 0 | E85: 0 | F85: 1 | G85: 0 | H85: 1 | I85: 0 | J85: =B85*Opportunities!L8+C85*Opportunities!L9+D85*Opportunities!L10+E85*Opportunities!L11+F85*Opportunities!L12+G85*Opportunities!L13+H85*Opportunities!L14+I85*Opportunities!L15 -> 1143000 | K85: =SUM(B85:I85) -> 2 | L85: =B85*Opportunities!P8+C85*Opportunities!P9+D85*Opportunities!P10+E85*Opportunities!P11+F85*Opportunities!P12+G85*Opportunities!P13+H85*Opportunities!P14+I85*Opportunities!P15 -> -175492.04 | M85: =IF(AND(J85<=Assumptions!$B$6,K85<=Assumptions!$B$7,B85*IF(Opportunities!S8="ELIGIBLE",0,1)+C85*IF(Opportunities!S9="ELIGIBLE",0,1)+D85*IF(Opportunities!S10="ELIGIBLE",0,1)+E85*IF(Opportunities!S11="ELIGIBLE",0,1)+F85*IF(Opportunities!S12="ELIGIBLE",0,1)+G85*IF(Opportunities!S13="ELIGIBLE",0,1)+H85*IF(Opportunities!S14="ELIGIBLE",0,1)+I85*IF(Opportunities!S15="ELIGIBLE",0,1)=0),1,0) -> 0 | N85: =IF(M85=1,L85,-1E99) -> -1e+99
A86: 81 | B86: 1 | C86: 0 | D86: 0 | E86: 0 | F86: 1 | G86: 0 | H86: 1 | I86: 0 | J86: =B86*Opportunities!L8+C86*Opportunities!L9+D86*Opportunities!L10+E86*Opportunities!L11+F86*Opportunities!L12+G86*Opportunities!L13+H86*Opportunities!L14+I86*Opportunities!L15 -> 2012500 | K86: =SUM(B86:I86) -> 3 | L86: =B86*Opportunities!P8+C86*Opportunities!P9+D86*Opportunities!P10+E86*Opportunities!P11+F86*Opportunities!P12+G86*Opportunities!P13+H86*Opportunities!P14+I86*Opportunities!P15 -> -84595.523 | M86: =IF(AND(J86<=Assumptions!$B$6,K86<=Assumptions!$B$7,B86*IF(Opportunities!S8="ELIGIBLE",0,1)+C86*IF(Opportunities!S9="ELIGIBLE",0,1)+D86*IF(Opportunities!S10="ELIGIBLE",0,1)+E86*IF(Opportunities!S11="ELIGIBLE",0,1)+F86*IF(Opportunities!S12="ELIGIBLE",0,1)+G86*IF(Opportunities!S13="ELIGIBLE",0,1)+H86*IF(Opportunities!S14="ELIGIBLE",0,1)+I86*IF(Opportunities!S15="ELIGIBLE",0,1)=0),1,0) -> 0 | N86: =IF(M86=1,L86,-1E99) -> -1e+99
A87: 82 | B87: 0 | C87: 1 | D87: 0 | E87: 0 | F87: 1 | G87: 0 | H87: 1 | I87: 0 | J87: =B87*Opportunities!L8+C87*Opportunities!L9+D87*Opportunities!L10+E87*Opportunities!L11+F87*Opportunities!L12+G87*Opportunities!L13+H87*Opportunities!L14+I87*Opportunities!L15 -> 1728000 | K87: =SUM(B87:I87) -> 3 | L87: =B87*Opportunities!P8+C87*Opportunities!P9+D87*Opportunities!P10+E87*Opportunities!P11+F87*Opportunities!P12+G87*Opportunities!P13+H87*Opportunities!P14+I87*Opportunities!P15 -> -99363.637 | M87: =IF(AND(J87<=Assumptions!$B$6,K87<=Assumptions!$B$7,B87*IF(Opportunities!S8="ELIGIBLE",0,1)+C87*IF(Opportunities!S9="ELIGIBLE",0,1)+D87*IF(Opportunities!S10="ELIGIBLE",0,1)+E87*IF(Opportunities!S11="ELIGIBLE",0,1)+F87*IF(Opportunities!S12="ELIGIBLE",0,1)+G87*IF(Opportunities!S13="ELIGIBLE",0,1)+H87*IF(Opportunities!S14="ELIGIBLE",0,1)+I87*IF(Opportunities!S15="ELIGIBLE",0,1)=0),1,0) -> 0 | N87: =IF(M87=1,L87,-1E99) -> -1e+99
A88: 83 | B88: 1 | C88: 1 | D88: 0 | E88: 0 | F88: 1 | G88: 0 | H88: 1 | I88: 0 | J88: =B88*Opportunities!L8+C88*Opportunities!L9+D88*Opportunities!L10+E88*Opportunities!L11+F88*Opportunities!L12+G88*Opportunities!L13+H88*Opportunities!L14+I88*Opportunities!L15 -> 2597500 | K88: =SUM(B88:I88) -> 4 | L88: =B88*Opportunities!P8+C88*Opportunities!P9+D88*Opportunities!P10+E88*Opportunities!P11+F88*Opportunities!P12+G88*Opportunities!P13+H88*Opportunities!P14+I88*Opportunities!P15 -> -8467.1203 | M88: =IF(AND(J88<=Assumptions!$B$6,K88<=Assumptions!$B$7,B88*IF(Opportunities!S8="ELIGIBLE",0,1)+C88*IF(Opportunities!S9="ELIGIBLE",0,1)+D88*IF(Opportunities!S10="ELIGIBLE",0,1)+E88*IF(Opportunities!S11="ELIGIBLE",0,1)+F88*IF(Opportunities!S12="ELIGIBLE",0,1)+G88*IF(Opportunities!S13="ELIGIBLE",0,1)+H88*IF(Opportunities!S14="ELIGIBLE",0,1)+I88*IF(Opportunities!S15="ELIGIBLE",0,1)=0),1,0) -> 0 | N88: =IF(M88=1,L88,-1E99) -> -1e+99
A89: 84 | B89: 0 | C89: 0 | D89: 1 | E89: 0 | F89: 1 | G89: 0 | H89: 1 | I89: 0 | J89: =B89*Opportunities!L8+C89*Opportunities!L9+D89*Opportunities!L10+E89*Opportunities!L11+F89*Opportunities!L12+G89*Opportunities!L13+H89*Opportunities!L14+I89*Opportunities!L15 -> 2724000 | K89: =SUM(B89:I89) -> 3 | L89: =B89*Opportunities!P8+C89*Opportunities!P9+D89*Opportunities!P10+E89*Opportunities!P11+F89*Opportunities!P12+G89*Opportunities!P13+H89*Opportunities!P14+I89*Opportunities!P15 -> -120708.32 | M89: =IF(AND(J89<=Assumptions!$B$6,K89<=Assumptions!$B$7,B89*IF(Opportunities!S8="ELIGIBLE",0,1)+C89*IF(Opportunities!S9="ELIGIBLE",0,1)+D89*IF(Opportunities!S10="ELIGIBLE",0,1)+E89*IF(Opportunities!S11="ELIGIBLE",0,1)+F89*IF(Opportunities!S12="ELIGIBLE",0,1)+G89*IF(Opportunities!S13="ELIGIBLE",0,1)+H89*IF(Opportunities!S14="ELIGIBLE",0,1)+I89*IF(Opportunities!S15="ELIGIBLE",0,1)=0),1,0) -> 0 | N89: =IF(M89=1,L89,-1E99) -> -1e+99
A90: 85 | B90: 1 | C90: 0 | D90: 1 | E90: 0 | F90: 1 | G90: 0 | H90: 1 | I90: 0 | J90: =B90*Opportunities!L8+C90*Opportunities!L9+D90*Opportunities!L10+E90*Opportunities!L11+F90*Opportunities!L12+G90*Opportunities!L13+H90*Opportunities!L14+I90*Opportunities!L15 -> 3593500 | K90: =SUM(B90:I90) -> 4 | L90: =B90*Opportunities!P8+C90*Opportunities!P9+D90*Opportunities!P10+E90*Opportunities!P11+F90*Opportunities!P12+G90*Opportunities!P13+H90*Opportunities!P14+I90*Opportunities!P15 -> -29811.808 | M90: =IF(AND(J90<=Assumptions!$B$6,K90<=Assumptions!$B$7,B90*IF(Opportunities!S8="ELIGIBLE",0,1)+C90*IF(Opportunities!S9="ELIGIBLE",0,1)+D90*IF(Opportunities!S10="ELIGIBLE",0,1)+E90*IF(Opportunities!S11="ELIGIBLE",0,1)+F90*IF(Opportunities!S12="ELIGIBLE",0,1)+G90*IF(Opportunities!S13="ELIGIBLE",0,1)+H90*IF(Opportunities!S14="ELIGIBLE",0,1)+I90*IF(Opportunities!S15="ELIGIBLE",0,1)=0),1,0) -> 0 | N90: =IF(M90=1,L90,-1E99) -> -1e+99
A91: 86 | B91: 0 | C91: 1 | D91: 1 | E91: 0 | F91: 1 | G91: 0 | H91: 1 | I91: 0 | J91: =B91*Opportunities!L8+C91*Opportunities!L9+D91*Opportunities!L10+E91*Opportunities!L11+F91*Opportunities!L12+G91*Opportunities!L13+H91*Opportunities!L14+I91*Opportunities!L15 -> 3309000 | K91: =SUM(B91:I91) -> 4 | L91: =B91*Opportunities!P8+C91*Opportunities!P9+D91*Opportunities!P10+E91*Opportunities!P11+F91*Opportunities!P12+G91*Opportunities!P13+H91*Opportunities!P14+I91*Opportunities!P15 -> -44579.922 | M91: =IF(AND(J91<=Assumptions!$B$6,K91<=Assumptions!$B$7,B91*IF(Opportunities!S8="ELIGIBLE",0,1)+C91*IF(Opportunities!S9="ELIGIBLE",0,1)+D91*IF(Opportunities!S10="ELIGIBLE",0,1)+E91*IF(Opportunities!S11="ELIGIBLE",0,1)+F91*IF(Opportunities!S12="ELIGIBLE",0,1)+G91*IF(Opportunities!S13="ELIGIBLE",0,1)+H91*IF(Opportunities!S14="ELIGIBLE",0,1)+I91*IF(Opportunities!S15="ELIGIBLE",0,1)=0),1,0) -> 0 | N91: =IF(M91=1,L91,-1E99) -> -1e+99
A92: 87 | B92: 1 | C92: 1 | D92: 1 | E92: 0 | F92: 1 | G92: 0 | H92: 1 | I92: 0 | J92: =B92*Opportunities!L8+C92*Opportunities!L9+D92*Opportunities!L10+E92*Opportunities!L11+F92*Opportunities!L12+G92*Opportunities!L13+H92*Opportunities!L14+I92*Opportunities!L15 -> 4178500 | K92: =SUM(B92:I92) -> 5 | L92: =B92*Opportunities!P8+C92*Opportunities!P9+D92*Opportunities!P10+E92*Opportunities!P11+F92*Opportunities!P12+G92*Opportunities!P13+H92*Opportunities!P14+I92*Opportunities!P15 -> 46316.595 | M92: =IF(AND(J92<=Assumptions!$B$6,K92<=Assumptions!$B$7,B92*IF(Opportunities!S8="ELIGIBLE",0,1)+C92*IF(Opportunities!S9="ELIGIBLE",0,1)+D92*IF(Opportunities!S10="ELIGIBLE",0,1)+E92*IF(Opportunities!S11="ELIGIBLE",0,1)+F92*IF(Opportunities!S12="ELIGIBLE",0,1)+G92*IF(Opportunities!S13="ELIGIBLE",0,1)+H92*IF(Opportunities!S14="ELIGIBLE",0,1)+I92*IF(Opportunities!S15="ELIGIBLE",0,1)=0),1,0) -> 0 | N92: =IF(M92=1,L92,-1E99) -> -1e+99
A93: 88 | B93: 0 | C93: 0 | D93: 0 | E93: 1 | F93: 1 | G93: 0 | H93: 1 | I93: 0 | J93: =B93*Opportunities!L8+C93*Opportunities!L9+D93*Opportunities!L10+E93*Opportunities!L11+F93*Opportunities!L12+G93*Opportunities!L13+H93*Opportunities!L14+I93*Opportunities!L15 -> 1475250 | K93: =SUM(B93:I93) -> 3 | L93: =B93*Opportunities!P8+C93*Opportunities!P9+D93*Opportunities!P10+E93*Opportunities!P11+F93*Opportunities!P12+G93*Opportunities!P13+H93*Opportunities!P14+I93*Opportunities!P15 -> -153603.92 | M93: =IF(AND(J93<=Assumptions!$B$6,K93<=Assumptions!$B$7,B93*IF(Opportunities!S8="ELIGIBLE",0,1)+C93*IF(Opportunities!S9="ELIGIBLE",0,1)+D93*IF(Opportunities!S10="ELIGIBLE",0,1)+E93*IF(Opportunities!S11="ELIGIBLE",0,1)+F93*IF(Opportunities!S12="ELIGIBLE",0,1)+G93*IF(Opportunities!S13="ELIGIBLE",0,1)+H93*IF(Opportunities!S14="ELIGIBLE",0,1)+I93*IF(Opportunities!S15="ELIGIBLE",0,1)=0),1,0) -> 0 | N93: =IF(M93=1,L93,-1E99) -> -1e+99
A94: 89 | B94: 1 | C94: 0 | D94: 0 | E94: 1 | F94: 1 | G94: 0 | H94: 1 | I94: 0 | J94: =B94*Opportunities!L8+C94*Opportunities!L9+D94*Opportunities!L10+E94*Opportunities!L11+F94*Opportunities!L12+G94*Opportunities!L13+H94*Opportunities!L14+I94*Opportunities!L15 -> 2344750 | K94: =SUM(B94:I94) -> 4 | L94: =B94*Opportunities!P8+C94*Opportunities!P9+D94*Opportunities!P10+E94*Opportunities!P11+F94*Opportunities!P12+G94*Opportunities!P13+H94*Opportunities!P14+I94*Opportunities!P15 -> -62707.4 | M94: =IF(AND(J94<=Assumptions!$B$6,K94<=Assumptions!$B$7,B94*IF(Opportunities!S8="ELIGIBLE",0,1)+C94*IF(Opportunities!S9="ELIGIBLE",0,1)+D94*IF(Opportunities!S10="ELIGIBLE",0,1)+E94*IF(Opportunities!S11="ELIGIBLE",0,1)+F94*IF(Opportunities!S12="ELIGIBLE",0,1)+G94*IF(Opportunities!S13="ELIGIBLE",0,1)+H94*IF(Opportunities!S14="ELIGIBLE",0,1)+I94*IF(Opportunities!S15="ELIGIBLE",0,1)=0),1,0) -> 0 | N94: =IF(M94=1,L94,-1E99) -> -1e+99
A95: 90 | B95: 0 | C95: 1 | D95: 0 | E95: 1 | F95: 1 | G95: 0 | H95: 1 | I95: 0 | J95: =B95*Opportunities!L8+C95*Opportunities!L9+D95*Opportunities!L10+E95*Opportunities!L11+F95*Opportunities!L12+G95*Opportunities!L13+H95*Opportunities!L14+I95*Opportunities!L15 -> 2060250 | K95: =SUM(B95:I95) -> 4 | L95: =B95*Opportunities!P8+C95*Opportunities!P9+D95*Opportunities!P10+E95*Opportunities!P11+F95*Opportunities!P12+G95*Opportunities!P13+H95*Opportunities!P14+I95*Opportunities!P15 -> -77475.515 | M95: =IF(AND(J95<=Assumptions!$B$6,K95<=Assumptions!$B$7,B95*IF(Opportunities!S8="ELIGIBLE",0,1)+C95*IF(Opportunities!S9="ELIGIBLE",0,1)+D95*IF(Opportunities!S10="ELIGIBLE",0,1)+E95*IF(Opportunities!S11="ELIGIBLE",0,1)+F95*IF(Opportunities!S12="ELIGIBLE",0,1)+G95*IF(Opportunities!S13="ELIGIBLE",0,1)+H95*IF(Opportunities!S14="ELIGIBLE",0,1)+I95*IF(Opportunities!S15="ELIGIBLE",0,1)=0),1,0) -> 0 | N95: =IF(M95=1,L95,-1E99) -> -1e+99
A96: 91 | B96: 1 | C96: 1 | D96: 0 | E96: 1 | F96: 1 | G96: 0 | H96: 1 | I96: 0 | J96: =B96*Opportunities!L8+C96*Opportunities!L9+D96*Opportunities!L10+E96*Opportunities!L11+F96*Opportunities!L12+G96*Opportunities!L13+H96*Opportunities!L14+I96*Opportunities!L15 -> 2929750 | K96: =SUM(B96:I96) -> 5 | L96: =B96*Opportunities!P8+C96*Opportunities!P9+D96*Opportunities!P10+E96*Opportunities!P11+F96*Opportunities!P12+G96*Opportunities!P13+H96*Opportunities!P14+I96*Opportunities!P15 -> 13421.002 | M96: =IF(AND(J96<=Assumptions!$B$6,K96<=Assumptions!$B$7,B96*IF(Opportunities!S8="ELIGIBLE",0,1)+C96*IF(Opportunities!S9="ELIGIBLE",0,1)+D96*IF(Opportunities!S10="ELIGIBLE",0,1)+E96*IF(Opportunities!S11="ELIGIBLE",0,1)+F96*IF(Opportunities!S12="ELIGIBLE",0,1)+G96*IF(Opportunities!S13="ELIGIBLE",0,1)+H96*IF(Opportunities!S14="ELIGIBLE",0,1)+I96*IF(Opportunities!S15="ELIGIBLE",0,1)=0),1,0) -> 0 | N96: =IF(M96=1,L96,-1E99) -> -1e+99
A97: 92 | B97: 0 | C97: 0 | D97: 1 | E97: 1 | F97: 1 | G97: 0 | H97: 1 | I97: 0 | J97: =B97*Opportunities!L8+C97*Opportunities!L9+D97*Opportunities!L10+E97*Opportunities!L11+F97*Opportunities!L12+G97*Opportunities!L13+H97*Opportunities!L14+I97*Opportunities!L15 -> 3056250 | K97: =SUM(B97:I97) -> 4 | L97: =B97*Opportunities!P8+C97*Opportunities!P9+D97*Opportunities!P10+E97*Opportunities!P11+F97*Opportunities!P12+G97*Opportunities!P13+H97*Opportunities!P14+I97*Opportunities!P15 -> -98820.202 | M97: =IF(AND(J97<=Assumptions!$B$6,K97<=Assumptions!$B$7,B97*IF(Opportunities!S8="ELIGIBLE",0,1)+C97*IF(Opportunities!S9="ELIGIBLE",0,1)+D97*IF(Opportunities!S10="ELIGIBLE",0,1)+E97*IF(Opportunities!S11="ELIGIBLE",0,1)+F97*IF(Opportunities!S12="ELIGIBLE",0,1)+G97*IF(Opportunities!S13="ELIGIBLE",0,1)+H97*IF(Opportunities!S14="ELIGIBLE",0,1)+I97*IF(Opportunities!S15="ELIGIBLE",0,1)=0),1,0) -> 0 | N97: =IF(M97=1,L97,-1E99) -> -1e+99
A98: 93 | B98: 1 | C98: 0 | D98: 1 | E98: 1 | F98: 1 | G98: 0 | H98: 1 | I98: 0 | J98: =B98*Opportunities!L8+C98*Opportunities!L9+D98*Opportunities!L10+E98*Opportunities!L11+F98*Opportunities!L12+G98*Opportunities!L13+H98*Opportunities!L14+I98*Opportunities!L15 -> 3925750 | K98: =SUM(B98:I98) -> 5 | L98: =B98*Opportunities!P8+C98*Opportunities!P9+D98*Opportunities!P10+E98*Opportunities!P11+F98*Opportunities!P12+G98*Opportunities!P13+H98*Opportunities!P14+I98*Opportunities!P15 -> -7923.6849 | M98: =IF(AND(J98<=Assumptions!$B$6,K98<=Assumptions!$B$7,B98*IF(Opportunities!S8="ELIGIBLE",0,1)+C98*IF(Opportunities!S9="ELIGIBLE",0,1)+D98*IF(Opportunities!S10="ELIGIBLE",0,1)+E98*IF(Opportunities!S11="ELIGIBLE",0,1)+F98*IF(Opportunities!S12="ELIGIBLE",0,1)+G98*IF(Opportunities!S13="ELIGIBLE",0,1)+H98*IF(Opportunities!S14="ELIGIBLE",0,1)+I98*IF(Opportunities!S15="ELIGIBLE",0,1)=0),1,0) -> 0 | N98: =IF(M98=1,L98,-1E99) -> -1e+99
A99: 94 | B99: 0 | C99: 1 | D99: 1 | E99: 1 | F99: 1 | G99: 0 | H99: 1 | I99: 0 | J99: =B99*Opportunities!L8+C99*Opportunities!L9+D99*Opportunities!L10+E99*Opportunities!L11+F99*Opportunities!L12+G99*Opportunities!L13+H99*Opportunities!L14+I99*Opportunities!L15 -> 3641250 | K99: =SUM(B99:I99) -> 5 | L99: =B99*Opportunities!P8+C99*Opportunities!P9+D99*Opportunities!P10+E99*Opportunities!P11+F99*Opportunities!P12+G99*Opportunities!P13+H99*Opportunities!P14+I99*Opportunities!P15 -> -22691.799 | M99: =IF(AND(J99<=Assumptions!$B$6,K99<=Assumptions!$B$7,B99*IF(Opportunities!S8="ELIGIBLE",0,1)+C99*IF(Opportunities!S9="ELIGIBLE",0,1)+D99*IF(Opportunities!S10="ELIGIBLE",0,1)+E99*IF(Opportunities!S11="ELIGIBLE",0,1)+F99*IF(Opportunities!S12="ELIGIBLE",0,1)+G99*IF(Opportunities!S13="ELIGIBLE",0,1)+H99*IF(Opportunities!S14="ELIGIBLE",0,1)+I99*IF(Opportunities!S15="ELIGIBLE",0,1)=0),1,0) -> 0 | N99: =IF(M99=1,L99,-1E99) -> -1e+99
A100: 95 | B100: 1 | C100: 1 | D100: 1 | E100: 1 | F100: 1 | G100: 0 | H100: 1 | I100: 0 | J100: =B100*Opportunities!L8+C100*Opportunities!L9+D100*Opportunities!L10+E100*Opportunities!L11+F100*Opportunities!L12+G100*Opportunities!L13+H100*Opportunities!L14+I100*Opportunities!L15 -> 4510750 | K100: =SUM(B100:I100) -> 6 | L100: =B100*Opportunities!P8+C100*Opportunities!P9+D100*Opportunities!P10+E100*Opportunities!P11+F100*Opportunities!P12+G100*Opportunities!P13+H100*Opportunities!P14+I100*Opportunities!P15 -> 68204.718 | M100: =IF(AND(J100<=Assumptions!$B$6,K100<=Assumptions!$B$7,B100*IF(Opportunities!S8="ELIGIBLE",0,1)+C100*IF(Opportunities!S9="ELIGIBLE",0,1)+D100*IF(Opportunities!S10="ELIGIBLE",0,1)+E100*IF(Opportunities!S11="ELIGIBLE",0,1)+F100*IF(Opportunities!S12="ELIGIBLE",0,1)+G100*IF(Opportunities!S13="ELIGIBLE",0,1)+H100*IF(Opportunities!S14="ELIGIBLE",0,1)+I100*IF(Opportunities!S15="ELIGIBLE",0,1)=0),1,0) -> 0 | N100: =IF(M100=1,L100,-1E99) -> -1e+99
A101: 96 | B101: 0 | C101: 0 | D101: 0 | E101: 0 | F101: 0 | G101: 1 | H101: 1 | I101: 0 | J101: =B101*Opportunities!L8+C101*Opportunities!L9+D101*Opportunities!L10+E101*Opportunities!L11+F101*Opportunities!L12+G101*Opportunities!L13+H101*Opportunities!L14+I101*Opportunities!L15 -> 799250 | K101: =SUM(B101:I101) -> 2 | L101: =B101*Opportunities!P8+C101*Opportunities!P9+D101*Opportunities!P10+E101*Opportunities!P11+F101*Opportunities!P12+G101*Opportunities!P13+H101*Opportunities!P14+I101*Opportunities!P15 -> 72646.659 | M101: =IF(AND(J101<=Assumptions!$B$6,K101<=Assumptions!$B$7,B101*IF(Opportunities!S8="ELIGIBLE",0,1)+C101*IF(Opportunities!S9="ELIGIBLE",0,1)+D101*IF(Opportunities!S10="ELIGIBLE",0,1)+E101*IF(Opportunities!S11="ELIGIBLE",0,1)+F101*IF(Opportunities!S12="ELIGIBLE",0,1)+G101*IF(Opportunities!S13="ELIGIBLE",0,1)+H101*IF(Opportunities!S14="ELIGIBLE",0,1)+I101*IF(Opportunities!S15="ELIGIBLE",0,1)=0),1,0) -> 0 | N101: =IF(M101=1,L101,-1E99) -> -1e+99
...

Sheet Sources
A1: Sources and verification
A2: Official Brussels references checked 14 October 2026. Financial inputs remain illustrative assumptions.
A4: Topic | B4: Source / URL | C4: Use / caveat | D4: Checked
A5: S1 • 2026 changes | B5: https://be.brussels/en/housing/new-minimum-quality-standards-2026 | C5: Effective 1 January 2026; minimum area, heating and bathing requirements. | D5: 2026-10-14
A6: S2 • Consolidated decree | B6: https://www.slrb-bghm.brussels/sites/default/files/2026-02/arr%C3%AAt%C3%A9%20exigences%20%C3%A9l%C3%A9mentaires%20s%C3%A9curit%C3%A9%20%20texte%20coordonn%C3%A9%20fr%2001012026.pdf | C6: 30 November 2023 decree, coordinated at 1 January 2026. Articles 2–5: safety, sanitation, area, facilities. | D6: 2026-10-14
A7: S3 • DIRL | B7: https://be.brussels/en/about-region/structure-and-organisations/overview-administrations-and-institutions-region/brussels-housing/structure-brussels-housing/regional-housing-inspectorate-dirl | C7: Inspection framework; voluntary conformity certificate and clearance after a letting ban. | D7: 2026-10-14
A8: S4 • Student quality label | B8: https://be.brussels/en/housing/rental/conformity-for-rental-properties/ensuring-quality-student-housing | C8: Label application, student lease and valid PEB. Label is separate from mandatory dwelling standards. | D8: 2026-10-14
A9: S5 • Official comparison | B9: https://admin.be.brussels/en/bhg/document/download/4537 | C9: Official comparison of pre-2026 and 2026 minimum requirements. | D9: 2026-10-14
A10: Financial assumptions | B10: Assumptions / Opportunities | C10: No listings or market rents supplied. Prices, rent, tax/cost proxies and cap rate are fictional planning inputs. | D10: 2026-10-14
