Workbook

Sheet Read me
A1: VUB / ULB student housing — decision model
A2: Reference date | B2: 1 October 2026 (year assumed from assignment context)
A3: Status | B3: Screening model; hypothetical acquisition, no selected property
A4: Instructions | B4: Edit blue cells on Inputs. All amounts EUR nominal; unlevered project cash flows.
A5: Decision | B5: Proceed to due diligence only; do not commit to acquisition until permits, costs and rental demand are verified.
A6: Scope | B6: 24 rooms in an existing building near VUB/ULB; acquisition and renovation.
A7: Boundary | B7: Rent excludes recoverable utilities; tenant charges are pass-through and excluded from owner revenue.
A8: Important | B8: Formulas recalculate in Excel/LibreOffice. No property valuation or investment guarantee.
A9: Outputs | B9: Annual cash flow, NPV, IRR, simple payback, affordability and scenario comparison.
A10: Research date | B10: 14 October 2026. Live pages are current evidence, not archived proof of their content on 1 October. Dated 2026–27 and effective-date documents prioritised.
A11: Reproduce | B11: Run python3 enhance_model.py (requires openpyxl). build_model.py saves the basic version first.
A12: Contract duration | B12: Annual occupancy is paid room-months / 12. A 10-month lease without summer letting implies 83.3%, not 95%. See downside.

Sheet Inputs
A1: Input | B1: Value | C1: Unit / interpretation | D1: Evidence status
A2: Rooms | B2: 24 | C2: rooms | D2: Design assumption
A3: Purchase price | B3: 1800000 | C3: EUR | D3: Placeholder; obtain comparable transactions
A4: Acquisition tax | B4: 0.125 | C4: share of purchase price | D4: A1: standard 12.5% Brussels registration duty; no owner-occupier relief assumed
A5: Other acquisition costs | B5: 35000 | C5: EUR excluding acquisition tax | D5: Assumption; notary quote needed
A6: Renovation per room | B6: 30000 | C6: EUR/room incl. nonrecoverable VAT | D6: Assumption; contractor quote needed
A7: Furniture per room | B7: 3500 | C7: EUR/room incl. VAT | D7: Assumption
A8: Contingency | B8: 0.15 | C8: share of renovation + furniture | D8: Assumption
A9: Initial rent | B9: 550 | C9: EUR/room/month excluding utilities | D9: A2: EUR650 total incl. EUR100 utilities; screening assumption within published ULB EUR500–680 range
A10: Stabilised occupancy | B10: 0.95 | C10: share of available room months | D10: Assumption
A11: Annual rent growth | B11: 0.02 | C11: annual nominal escalation | D11: Scenario assumption; indexation legally conditional
A12: Fixed operating cost | B12: 25000 | C12: EUR/year | D12: Insurance, maintenance, admin, property tax allowance
A13: Variable operating cost | B13: 0.2 | C13: EUR/year: insurance 3000, maintenance 8000, admin 4000, property tax 10000 (all assumptions) | D13: Management, routine repairs, reserve
... A22: Replacement capex growth | B22: 0.025 | C22: annual escalation | D22: Assumption

Sheet Investment
A1: Item | B1: EUR
A2: Purchase | B2: ='Inputs'!$B$3 -> 1800000
A3: Acquisition tax | B3: =B2*'Inputs'!$B$4 -> 225000
A4: Other acquisition costs | B4: ='Inputs'!$B$5 -> 35000
A5: Renovation | B5: ='Inputs'!$B$2*'Inputs'!$B$6 -> 720000
A6: Furniture | B6: ='Inputs'!$B$2*'Inputs'!$B$7 -> 84000
A7: Contingency | B7: =(B5+B6)*'Inputs'!$B$8 -> 120600
A8: Total initial investment | B8: =SUM(B2:B7) -> 2984600

Sheet Cash flow
A1: Year | B1: Rent / room / month | C1: Occupancy | D1: Rent revenue | E1: Fixed costs | F1: Variable costs | G1: NOI | H1: Replacement capex | I1: Terminal proceeds | J1: Project cash flow | K1: Discounted cash flow | L1: Cumulative operating cash flow
A2: 0 | B2: 0 | C2: 0 | D2: 0 | E2: 0 | F2: 0 | G2: 0 | H2: 0 | I2: 0 | J2: =-'Investment'!B8 -> -2984600 | K2: =J2 -> -2984600 | L2: =J2 -> -2984600
A3: 1 | B3: ='Inputs'!$B$9*(1+'Inputs'!$B$11)^(A3-1) -> 550 | C3: ='Inputs'!$B$18 -> 0.75 | D3: ='Inputs'!$B$2*12*B3*C3 -> 118800 | E3: ='Inputs'!$B$12*(1+'Inputs'!$B$14)^(A3-1) -> 25000 | F3: =D3*'Inputs'!$B$13 -> 23760 | G3: =D3-E3-F3 -> 70040 | H3: ='Inputs'!$B$21*(1+'Inputs'!$B$22)^(A3-1) -> 10000 | I3: 0 | J3: =G3-H3+I3 -> 60040 | K3: =J3/(1+'Inputs'!$B$15)^A3 -> 56375.587 | L3: =L2+G3-H3 -> -2924560
A4: 2 | B4: ='Inputs'!$B$9*(1+'Inputs'!$B$11)^(A4-1) -> 561 | C4: ='Inputs'!$B$10 -> 0.95 | D4: ='Inputs'!$B$2*12*B4*C4 -> 153489.6 | E4: ='Inputs'!$B$12*(1+'Inputs'!$B$14)^(A4-1) -> 25625 | F4: =D4*'Inputs'!$B$13 -> 30697.92 | G4: =D4-E4-F4 -> 97166.68 | H4: ='Inputs'!$B$21*(1+'Inputs'!$B$22)^(A4-1) -> 10250 | I4: 0 | J4: =G4-H4+I4 -> 86916.68 | K4: =J4/(1+'Inputs'!$B$15)^A4 -> 76630.898 | L4: =L3+G4-H4 -> -2837643.3
A5: 3 | B5: ='Inputs'!$B$9*(1+'Inputs'!$B$11)^(A5-1) -> 572.22 | C5: ='Inputs'!$B$10 -> 0.95 | D5: ='Inputs'!$B$2*12*B5*C5 -> 156559.39 | E5: ='Inputs'!$B$12*(1+'Inputs'!$B$14)^(A5-1) -> 26265.625 | F5: =D5*'Inputs'!$B$13 -> 31311.878 | G5: =D5-E5-F5 -> 98981.889 | H5: ='Inputs'!$B$21*(1+'Inputs'!$B$22)^(A5-1) -> 10506.25 | I5: 0 | J5: =G5-H5+I5 -> 88475.639 | K5: =J5/(1+'Inputs'!$B$15)^A5 -> 73244.477 | L5: =L4+G5-H5 -> -2749167.7
A6: 4 | B6: ='Inputs'!$B$9*(1+'Inputs'!$B$11)^(A6-1) -> 583.6644 | C6: ='Inputs'!$B$10 -> 0.95 | D6: ='Inputs'!$B$2*12*B6*C6 -> 159690.58 | E6: ='Inputs'!$B$12*(1+'Inputs'!$B$14)^(A6-1) -> 26922.266 | F6: =D6*'Inputs'!$B$13 -> 31938.116 | G6: =D6-E6-F6 -> 100830.2 | H6: ='Inputs'!$B$21*(1+'Inputs'!$B$22)^(A6-1) -> 10768.906 | I6: 0 | J6: =G6-H6+I6 -> 90061.292 | K6: =J6/(1+'Inputs'!$B$15)^A6 -> 70006.722 | L6: =L5+G6-H6 -> -2659106.4
A7: 5 | B7: ='Inputs'!$B$9*(1+'Inputs'!$B$11)^(A7-1) -> 595.33769 | C7: ='Inputs'!$B$10 -> 0.95 | D7: ='Inputs'!$B$2*12*B7*C7 -> 162884.39 | E7: ='Inputs'!$B$12*(1+'Inputs'!$B$14)^(A7-1) -> 27595.322 | F7: =D7*'Inputs'!$B$13 -> 32576.878 | G7: =D7-E7-F7 -> 102712.19 | H7: ='Inputs'!$B$21*(1+'Inputs'!$B$22)^(A7-1) -> 11038.129 | I7: 0 | J7: =G7-H7+I7 -> 91674.062 | K7: =J7/(1+'Inputs'!$B$15)^A7 -> 66911.141 | L7: =L6+G7-H7 -> -2567432.3
A8: 6 | B8: ='Inputs'!$B$9*(1+'Inputs'!$B$11)^(A8-1) -> 607.24444 | C8: ='Inputs'!$B$10 -> 0.95 | D8: ='Inputs'!$B$2*12*B8*C8 -> 166142.08 | E8: ='Inputs'!$B$12*(1+'Inputs'!$B$14)^(A8-1) -> 28285.205 | F8: =D8*'Inputs'!$B$13 -> 33228.416 | G8: =D8-E8-F8 -> 104628.46 | H8: ='Inputs'!$B$21*(1+'Inputs'!$B$22)^(A8-1) -> 11314.082 | I8: 0 | J8: =G8-H8+I8 -> 93314.376 | K8: =J8/(1+'Inputs'!$B$15)^A8 -> 63951.526 | L8: =L7+G8-H8 -> -2474118
A9: 7 | B9: ='Inputs'!$B$9*(1+'Inputs'!$B$11)^(A9-1) -> 619.38933 | C9: ='Inputs'!$B$10 -> 0.95 | D9: ='Inputs'!$B$2*12*B9*C9 -> 169464.92 | E9: ='Inputs'!$B$12*(1+'Inputs'!$B$14)^(A9-1) -> 28992.335 | F9: =D9*'Inputs'!$B$13 -> 33892.984 | G9: =D9-E9-F9 -> 106579.6 | H9: ='Inputs'!$B$21*(1+'Inputs'!$B$22)^(A9-1) -> 11596.934 | I9: 0 | J9: =G9-H9+I9 -> 94982.667 | K9: =J9/(1+'Inputs'!$B$15)^A9 -> 61121.937 | L9: =L8+G9-H9 -> -2379135.3
A10: 8 | B10: ='Inputs'!$B$9*(1+'Inputs'!$B$11)^(A10-1) -> 631.77712 | C10: ='Inputs'!$B$10 -> 0.95 | D10: ='Inputs'!$B$2*12*B10*C10 -> 172854.22 | E10: ='Inputs'!$B$12*(1+'Inputs'!$B$14)^(A10-1) -> 29717.144 | F10: =D10*'Inputs'!$B$13 -> 34570.844 | G10: =D10-E10-F10 -> 108566.23 | H10: ='Inputs'!$B$21*(1+'Inputs'!$B$22)^(A10-1) -> 11886.858 | I10: 0 | J10: =G10-H10+I10 -> 96679.374 | K10: =J10/(1+'Inputs'!$B$15)^A10 -> 58416.693 | L10: =L9+G10-H10 -> -2282455.9
A11: 9 | B11: ='Inputs'!$B$9*(1+'Inputs'!$B$11)^(A11-1) -> 644.41266 | C11: ='Inputs'!$B$10 -> 0.95 | D11: ='Inputs'!$B$2*12*B11*C11 -> 176311.3 | E11: ='Inputs'!$B$12*(1+'Inputs'!$B$14)^(A11-1) -> 30460.072 | F11: =D11*'Inputs'!$B$13 -> 35262.261 | G11: =D11-E11-F11 -> 110588.97 | H11: ='Inputs'!$B$21*(1+'Inputs'!$B$22)^(A11-1) -> 12184.029 | I11: 0 | J11: =G11-H11+I11 -> 98404.942 | K11: =J11/(1+'Inputs'!$B$15)^A11 -> 55830.361 | L11: =L10+G11-H11 -> -2184051
A12: 10 | B12: ='Inputs'!$B$9*(1+'Inputs'!$B$11)^(A12-1) -> 657.30091 | C12: ='Inputs'!$B$10 -> 0.95 | D12: ='Inputs'!$B$2*12*B12*C12 -> 179837.53 | E12: ='Inputs'!$B$12*(1+'Inputs'!$B$14)^(A12-1) -> 31221.574 | F12: =D12*'Inputs'!$B$13 -> 35967.506 | G12: =D12-E12-F12 -> 112648.45 | H12: ='Inputs'!$B$21*(1+'Inputs'!$B$22)^(A12-1) -> 12488.63 | I12: 0 | J12: =G12-H12+I12 -> 100159.82 | K12: =J12/(1+'Inputs'!$B$15)^A12 -> 53357.744 | L12: =L11+G12-H12 -> -2083891.1
A13: 11 | B13: ='Inputs'!$B$9*(1+'Inputs'!$B$11)^(A13-1) -> 670.44693 | C13: ='Inputs'!$B$10 -> 0.95 | D13: ='Inputs'!$B$2*12*B13*C13 -> 183434.28 | E13: ='Inputs'!$B$12*(1+'Inputs'!$B$14)^(A13-1) -> 32002.114 | F13: =D13*'Inputs'!$B$13 -> 36686.856 | G13: =D13-E13-F13 -> 114745.31 | H13: ='Inputs'!$B$21*(1+'Inputs'!$B$22)^(A13-1) -> 12800.845 | I13: 0 | J13: =G13-H13+I13 -> 101944.47 | K13: =J13/(1+'Inputs'!$B$15)^A13 -> 50993.869 | L13: =L12+G13-H13 -> -1981946.7
A14: 12 | B14: ='Inputs'!$B$9*(1+'Inputs'!$B$11)^(A14-1) -> 683.85587 | C14: ='Inputs'!$B$10 -> 0.95 | D14: ='Inputs'!$B$2*12*B14*C14 -> 187102.97 | E14: ='Inputs'!$B$12*(1+'Inputs'!$B$14)^(A14-1) -> 32802.166 | F14: =D14*'Inputs'!$B$13 -> 37420.593 | G14: =D14-E14-F14 -> 116880.21 | H14: ='Inputs'!$B$21*(1+'Inputs'!$B$22)^(A14-1) -> 13120.867 | I14: 0 | J14: =G14-H14+I14 -> 103759.34 | K14: =J14/(1+'Inputs'!$B$15)^A14 -> 48733.983 | L14: =L13+G14-H14 -> -1878187.3
A15: 13 | B15: ='Inputs'!$B$9*(1+'Inputs'!$B$11)^(A15-1) -> 697.53299 | C15: ='Inputs'!$B$10 -> 0.95 | D15: ='Inputs'!$B$2*12*B15*C15 -> 190845.03 | E15: ='Inputs'!$B$12*(1+'Inputs'!$B$14)^(A15-1) -> 33622.221 | F15: =D15*'Inputs'!$B$13 -> 38169.005 | G15: =D15-E15-F15 -> 119053.8 | H15: ='Inputs'!$B$21*(1+'Inputs'!$B$22)^(A15-1) -> 13448.888 | I15: 0 | J15: =G15-H15+I15 -> 105604.91 | K15: =J15/(1+'Inputs'!$B$15)^A15 -> 46573.536 | L15: =L14+G15-H15 -> -1772582.4
... A21: 19 | B21: ='Inputs'!$B$9*(1+'Inputs'!$B$11)^(A21-1) -> 785.53544 | C21: ='Inputs'!$B$10 -> 0.95 | D21: ='Inputs'!$B$2*12*B21*C21 -> 214922.5 | E21: ='Inputs'!$B$12*(1+'Inputs'!$B$14)^(A21-1) -> 38991.468 | F21: =D21*'Inputs'!$B$13 -> 42984.499 | G21: =D21-E21-F21 -> 132946.53 | H21: ='Inputs'!$B$21*(1+'Inputs'!$B$22)^(A21-1) -> 15596.587 | I21: 0 | J21: =G21-H21+I21 -> 117349.94 | K21: =J21/(1+'Inputs'!$B$15)^A21 -> 35468.296 | L21: =L20+G21-H21 -> -1098416.5
A22: 20 | B22: ='Inputs'!$B$9*(1+'Inputs'!$B$11)^(A22-1) -> 801.24614 | C22: ='Inputs'!$B$10 -> 0.95 | D22: ='Inputs'!$B$2*12*B22*C22 -> 219220.95 | E22: ='Inputs'!$B$12*(1+'Inputs'!$B$14)^(A22-1) -> 39966.255 | F22: =D22*'Inputs'!$B$13 -> 43844.189 | G22: =D22-E22-F22 -> 135410.5 | H22: ='Inputs'!$B$21*(1+'Inputs'!$B$22)^(A22-1) -> 15986.502 | I22: =((D22*(1+'Inputs'!$B$11))-(E22*(1+'Inputs'!$B$14))-(F22*(1+'Inputs'!$B$11)))/'Inputs'!$B$16*(1-'Inputs'!$B$17) -> 2432387.5 | J22: =G22-H22+I22 -> 2551811.5 | K22: =J22/(1+'Inputs'!$B$15)^A22 -> 724196.53 | L22: =L21+G22-H22 -> -978992.45

Sheet Dashboard
A1: Metric | B1: Value | C1: Interpretation
A2: Initial investment | B2: ='Investment'!B8 -> 2984600 | C2: All-in cash outlay at year 0
A3: 20-year NPV | B3: =SUM('Cash flow'!K2:K22) -> -1239139.4 | C3: Includes resale; positive required for financial acceptance
A4: Project IRR | B4: =IRR('Cash flow'!J2:J22) -> 0.025799788 | C4: Unlevered, before income/corporate tax
A5: Year 2 net operating income | B5: ='Cash flow'!G4 -> 97166.68 | C5: Before replacement capex and financing
A6: Year 2 net cash yield | B6: =('Cash flow'!G4-'Cash flow'!H4)/B2 -> 0.029121718 | C6: Annual operating cash / initial investment
A7: Simple operating payback | B7: =IF('Cash flow'!L22<0,"Not reached in 20 years",COUNTIF('Cash flow'!L3:L22,"<0")+1) -> Not reached in 20 years | C7: Whole-year approximation; excludes resale
A8: Monthly tenant housing cost | B8: ='Inputs'!$B$9+'Inputs'!$B$19/12 -> 650 | C8: Rent plus utilities
A9: Housing share of student budget | B9: =B8/'Inputs'!$B$20 -> 0.5 | C9: Illustrative budget; compare affordability
A10: Terminal PV share of benefits | B10: ='Cash flow'!I22/(1+'Inputs'!B15)^20/(SUM('Cash flow'!K3:K22)) -> 0.39548551 | C10: Sensitivity to resale assumptions
A11: Break-even purchase price | B11: =MAX(0,('Inputs'!B3*(1+'Inputs'!B4)+B3)/(1+'Inputs'!B4)) -> 698542.71 | C11: NPV=0 holding rent, costs and exit yield fixed; negotiation screen
A12: Break-even purchase price | B12: =MAX(0,('Inputs'!B3*(1+'Inputs'!B4)+B3)/(1+'Inputs'!B4)) -> 698542.71 | C12: NPV=0 holding rent, costs and exit yield fixed; negotiation screen

Sheet Executive report
A1: Executive report — screening recommendation
A2: Proposal | B2: Acquire and renovate an existing 24-room building within walking/cycling distance of VUB/ULB and a frequent tram, metro or rail connection.
A3: Recommendation | B3: Conditional due diligence only. Financial feasibility must be demonstrated after quotes and site checks.
A4: Financial approach | B4: 20-year nominal unlevered DCF with full acquisition costs, renovation, contingency, annual replacement capex and terminal sale.
A5: Environmental | B5: Reuse the existing structure; verify PEB, insulation, heat pumps, ventilation, flood risk, bicycle provision and metered utilities.
A6: Economic | B6: Test rent against furnished student room comparables; tenant utilities shown separately. Contractor and furnishing costs are placeholders.
A7: Social | B7: Balance student affordability, accessible rooms, quiet hours, neighbour engagement and safe routes to campus.
A8: Legal | B8: Confirm planning use, number of units, fire approval, room habitability, lease conditions and municipal requirements before purchase.
A9: Limitations | B9: No identified property; no debt or investor income tax. Cost and rent assumptions require verification.
A10: Base-case results | B10: Investment EUR2,984,600; NPV EUR-1,239,139; IRR 2.58%; operating payback Not reached in 20 years; housing EUR650/month.
A11: Financial decision | B11: Reject acquisition at the assumed price: negative NPV. Renegotiate price, reduce construction costs or seek a transparent subsidy; do not rely on raising rent above affordability limits.
A12: Scenario outcomes | B12: Downside: NPV EUR-2,113,270, IRR -0.52%; Base: NPV EUR-1,239,139, IRR 2.58%; Upside: NPV EUR-608,250, IRR 4.27%
A13: Affordability | B13: EUR650 total is 50% of the illustrative EUR1300 budget. This is a concern despite being within the broad ULB room-cost range. Subsidised university rooms are cheaper.
... A27: Negotiation screen | B27: Break-even purchase price approximately EUR698,543, holding all other base assumptions fixed.

Sheet Sources
A1: ID | B1: Topic | C1: URL / source | D1: As-of / status | E1: Use in model
A2: A1 | B2: Acquisition duty | C2: https://be.brussels/fr/impots-financement/impots-et-taxes/fiscalite-immobiliere/droits-denregistrement/abattement-sur-les-droits-de-vente | D2: Live official page checked 2026-10-14 | E2: 12.5%; relief conditional, price ceiling EUR600000; no relief modelled
A3: A2 | B3: Market room cost | C3: https://www.ulb.be/fr/partir-ou-venir-en-echange/informations-pour-les-universites-partenaires | D3: Live university guidance checked 2026-10-14 | E3: EUR500–680/month including charges; indicative, not property comparables
A4: A3 | B4: University residence comparator | C4: https://www.ulb.be/medias/fichier/de-brouckere-2026-2027_1772020187753-pdf | D4: Academic year 2026–27 | E4: EUR491 including EUR61 charges; 10-month lease; subsidised university comparator
A5: A4 | B5: Campus transport | C5: https://www.vub.be/nl/over-de-vub/faculteiten-instituten-en-campussen/onze-campussen/vub-main-campus-brussel/bereikbaarheid | D5: Live university page checked 2026-10-14 | E5: Trams 7/25, metro 5 at Petillon, rail at Etterbeek; property walking times unverified
A6: A5 | B6: Housing standards | C6: https://be.brussels/fr/logement/location/conformite-logement/normes-et-securite | D6: Official page; new requirements from 2026-01-01 | E6: Safety, sanitation, equipment; updated standards must be checked room by room
A7: A6 | B7: Student lease | C7: https://be.brussels/nl/huisvesting/huren-en-verhuren/huurovereenkomst/huurcontracten-voor-woningen-modellen-en-bijlage | D7: Live official page checked 2026-10-14 | E7: Student status evidence; maximum 12-month student agreement
A8: A7 | B8: Etterbeek planning | C8: https://etterbeek.brussels/fr/demarches/espace-public-urbanisme/permis-durbanisme-demande | D8: Live municipal page checked 2026-10-14 | E8: Municipal permission and use/unit changes; ask planning department about exact address
A9: A8 | B9: Ixelles planning | C9: https://www.ixelles.be/site/124-Urbanisme | D9: Live municipal page checked 2026-10-14 | E9: PPAS and local planning procedure; check lawful existing use
A10: A9 | B10: Energy requirements | C10: https://environnement.brussels/pro/reglementation-et-inspection/obligations-et-autorisations/objectifs-peb-pour-chaque-bien-et-exigences-peb-en-cas-de-travaux | D10: Live regional environmental authority checked 2026-10-14 | E10: PEB275 by 2033; PEB150 no earlier than 2045; verify unit scope and implementation
A11: A10 | B11: Social integration income | C11: https://primabook.mi-is.be/fr/droit-lintegration-sociale/montants-ris | D11: Effective 2026-09-01 | E11: Monthly cohabitant EUR911.56; single EUR1367.34. Eligibility assessed by CPAS; not automatic student income
A12: A11 | B12: Student quality label | C12: https://be.brussels/fr/logement/location/conformite-logement/label-logement-etudiant | D12: Live regional page checked 2026-10-14 | E12: Quality label supporting housing conformity, student lease and valid PEB
A13: A12 | B13: Lease registration | C13: https://be.brussels/fr/logement/location/bail-dhabitation | D13: Live official page checked 2026-10-14 | E13: Register housing lease within two months; confirm applicable procedure

Sheet Due diligence
A1: Area | B1: Required evidence | C1: Gate / action
A2: Site | B2: Address, floor plans, cadastral records, transit walking time | C2: Select property and verify route on operator timetable
A3: Planning | B3: Authorised use and subdivision; municipal planning advice | C3: Written confirmation before binding purchase
A4: Fire | B4: SIAMU advice, evacuation routes, alarms and compartmentation | C4: Approval and contractor design
A5: Habitation | B5: Surface, daylight, ventilation, sanitation and safety | C5: Assess each room against Brussels Housing Code
A6: Energy | B6: PEB certificate, audit, bills, renovation estimates | C6: Costed retrofit and energy savings
A7: Financial | B7: Three contractor quotes, notary estimate, market comparables | C7: Replace placeholders and rerun scenarios
A8: Social | B8: Student budgets and disability access review | C8: Set affordable room mix and support procedures

Sheet Scenarios
A1: Scenario | B1: Rent multiplier | C1: Occupancy | D1: Renovation multiplier | E1: Exit cap rate | F1: Discount rate | G1: Initial investment | H1: NPV | I1: IRR | J1: Year 2 cash | K1: Interpretation
A2: Downside | B2: 0.9 | C2: 0.83333333 | D2: 1.2 | E2: 0.065 | F2: 0.075 | G2: ='Inputs'!B3*(1+'Inputs'!B4)+'Inputs'!B5+('Inputs'!B2*'Inputs'!B6*D2+'Inputs'!B2*'Inputs'!B7)*(1+'Inputs'!B8) -> 3150200 | H2: =SUM('Scenario cash'!B2:B22) -> -2113270.2 | I2: =IRR('Scenario cash'!A2:A22) -> -0.0051872042 | J2: ='Inputs'!B2*12*'Inputs'!B9*B2*(1+'Inputs'!B11)*C2*(1-'Inputs'!B13)-'Inputs'!B12*(1+'Inputs'!B14)-'Inputs'!B21*(1+'Inputs'!B22) -> 61065.8 | K2: 10 paid months, rent -10%, renovation +20%, higher yields
A3: Base | B3: 1 | C3: 0.95 | D3: 1 | E3: 0.055 | F3: 0.065 | G3: ='Inputs'!B3*(1+'Inputs'!B4)+'Inputs'!B5+('Inputs'!B2*'Inputs'!B6*D3+'Inputs'!B2*'Inputs'!B7)*(1+'Inputs'!B8) -> 2984600 | H3: =SUM('Scenario cash'!E2:E22) -> -1239139.4 | I3: =IRR('Scenario cash'!D2:D22) -> 0.025799788 | J3: ='Inputs'!B2*12*'Inputs'!B9*B3*(1+'Inputs'!B11)*C3*(1-'Inputs'!B13)-'Inputs'!B12*(1+'Inputs'!B14)-'Inputs'!B21*(1+'Inputs'!B22) -> 86916.68 | K3: All base assumptions
A4: Upside | B4: 1.1 | C4: 0.98 | D4: 0.9 | E4: 0.05 | F4: 0.06 | G4: ='Inputs'!B3*(1+'Inputs'!B4)+'Inputs'!B5+('Inputs'!B2*'Inputs'!B6*D4+'Inputs'!B2*'Inputs'!B7)*(1+'Inputs'!B8) -> 2901800 | H4: =SUM('Scenario cash'!H2:H22) -> -608249.54 | I4: =IRR('Scenario cash'!G2:G22) -> 0.04267786 | J4: ='Inputs'!B2*12*'Inputs'!B9*B4*(1+'Inputs'!B11)*C4*(1-'Inputs'!B13)-'Inputs'!B12*(1+'Inputs'!B14)-'Inputs'!B21*(1+'Inputs'!B22) -> 103461.24 | K4: Higher achieved rent and lower renovation cost; unverified

Sheet Scenario cash
A1: Downside cash | B1: Downside PV | C1: Year | D1: Base cash | E1: Base PV | F1: Year | G1: Upside cash | H1: Upside PV | I1: Year
A2: =-'Scenarios'!G2 -> -3150200 | B2: =A2/(1+'Scenarios'!F2)^0 -> -3150200 | C2: 0 | D2: =-'Scenarios'!G3 -> -2984600 | E2: =D2/(1+'Scenarios'!F3)^0 -> -2984600 | F2: 0 | G2: =-'Scenarios'!G4 -> -2901800 | H2: =G2/(1+'Scenarios'!F4)^0 -> -2901800 | I2: 0
A3: =('Inputs'!B2*12*'Inputs'!B9*'Scenarios'!B2*(1+'Inputs'!B11)^0*'Inputs'!B18*(1-'Inputs'!B13)-'Inputs'!B12*(1+'Inputs'!B14)^0-'Inputs'!B21*(1+'Inputs'!B22)^0) -> 50536 | B3: =A3/(1+'Scenarios'!F2)^1 -> 47010.233 | C3: 1 | D3: =('Inputs'!B2*12*'Inputs'!B9*'Scenarios'!B3*(1+'Inputs'!B11)^0*'Inputs'!B18*(1-'Inputs'!B13)-'Inputs'!B12*(1+'Inputs'!B14)^0-'Inputs'!B21*(1+'Inputs'!B22)^0) -> 60040 | E3: =D3/(1+'Scenarios'!F3)^1 -> 56375.587 | F3: 1 | G3: =('Inputs'!B2*12*'Inputs'!B9*'Scenarios'!B4*(1+'Inputs'!B11)^0*'Inputs'!B18*(1-'Inputs'!B13)-'Inputs'!B12*(1+'Inputs'!B14)^0-'Inputs'!B21*(1+'Inputs'!B22)^0) -> 69544 | H3: =G3/(1+'Scenarios'!F4)^1 -> 65607.547 | I3: 1
A4: =('Inputs'!B2*12*'Inputs'!B9*'Scenarios'!B2*(1+'Inputs'!B11)^1*'Scenarios'!C2*(1-'Inputs'!B13)-'Inputs'!B12*(1+'Inputs'!B14)^1-'Inputs'!B21*(1+'Inputs'!B22)^1) -> 61065.8 | B4: =A4/(1+'Scenarios'!F2)^2 -> 52842.228 | C4: 2 | D4: =('Inputs'!B2*12*'Inputs'!B9*'Scenarios'!B3*(1+'Inputs'!B11)^1*'Scenarios'!C3*(1-'Inputs'!B13)-'Inputs'!B12*(1+'Inputs'!B14)^1-'Inputs'!B21*(1+'Inputs'!B22)^1) -> 86916.68 | E4: =D4/(1+'Scenarios'!F3)^2 -> 76630.898 | F4: 2 | G4: =('Inputs'!B2*12*'Inputs'!B9*'Scenarios'!B4*(1+'Inputs'!B11)^1*'Scenarios'!C4*(1-'Inputs'!B13)-'Inputs'!B12*(1+'Inputs'!B14)^1-'Inputs'!B21*(1+'Inputs'!B22)^1) -> 103461.24 | H4: =G4/(1+'Scenarios'!F4)^2 -> 92080.138 | I4: 2
A5: =('Inputs'!B2*12*'Inputs'!B9*'Scenarios'!B2*(1+'Inputs'!B11)^2*'Scenarios'!C2*(1-'Inputs'!B13)-'Inputs'!B12*(1+'Inputs'!B14)^2-'Inputs'!B21*(1+'Inputs'!B22)^2) -> 62107.741 | B5: =A5/(1+'Scenarios'!F2)^3 -> 49994.283 | C5: 3 | D5: =('Inputs'!B2*12*'Inputs'!B9*'Scenarios'!B3*(1+'Inputs'!B11)^2*'Scenarios'!C3*(1-'Inputs'!B13)-'Inputs'!B12*(1+'Inputs'!B14)^2-'Inputs'!B21*(1+'Inputs'!B22)^2) -> 88475.639 | E5: =D5/(1+'Scenarios'!F3)^3 -> 73244.477 | F5: 3 | G5: =('Inputs'!B2*12*'Inputs'!B9*'Scenarios'!B4*(1+'Inputs'!B11)^2*'Scenarios'!C4*(1-'Inputs'!B13)-'Inputs'!B12*(1+'Inputs'!B14)^2-'Inputs'!B21*(1+'Inputs'!B22)^2) -> 105351.09 | H5: =G5/(1+'Scenarios'!F4)^3 -> 88454.809 | I5: 3
A6: =('Inputs'!B2*12*'Inputs'!B9*'Scenarios'!B2*(1+'Inputs'!B11)^3*'Scenarios'!C2*(1-'Inputs'!B13)-'Inputs'!B12*(1+'Inputs'!B14)^3-'Inputs'!B21*(1+'Inputs'!B22)^3) -> 63166.036 | B6: =A6/(1+'Scenarios'!F2)^4 -> 47298.762 | C6: 4 | D6: =('Inputs'!B2*12*'Inputs'!B9*'Scenarios'!B3*(1+'Inputs'!B11)^3*'Scenarios'!C3*(1-'Inputs'!B13)-'Inputs'!B12*(1+'Inputs'!B14)^3-'Inputs'!B21*(1+'Inputs'!B22)^3) -> 90061.292 | E6: =D6/(1+'Scenarios'!F3)^4 -> 70006.722 | F6: 4 | G6: =('Inputs'!B2*12*'Inputs'!B9*'Scenarios'!B4*(1+'Inputs'!B11)^3*'Scenarios'!C4*(1-'Inputs'!B13)-'Inputs'!B12*(1+'Inputs'!B14)^3-'Inputs'!B21*(1+'Inputs'!B22)^3) -> 107274.26 | H6: =G6/(1+'Scenarios'!F4)^4 -> 84971.258 | I6: 4
A7: =('Inputs'!B2*12*'Inputs'!B9*'Scenarios'!B2*(1+'Inputs'!B11)^4*'Scenarios'!C2*(1-'Inputs'!B13)-'Inputs'!B12*(1+'Inputs'!B14)^4-'Inputs'!B21*(1+'Inputs'!B22)^4) -> 64240.901 | B7: =A7/(1+'Scenarios'!F2)^5 -> 44747.554 | C7: 5 | D7: =('Inputs'!B2*12*'Inputs'!B9*'Scenarios'!B3*(1+'Inputs'!B11)^4*'Scenarios'!C3*(1-'Inputs'!B13)-'Inputs'!B12*(1+'Inputs'!B14)^4-'Inputs'!B21*(1+'Inputs'!B22)^4) -> 91674.062 | E7: =D7/(1+'Scenarios'!F3)^5 -> 66911.141 | F7: 5 | G7: =('Inputs'!B2*12*'Inputs'!B9*'Scenarios'!B4*(1+'Inputs'!B11)^4*'Scenarios'!C4*(1-'Inputs'!B13)-'Inputs'!B12*(1+'Inputs'!B14)^4-'Inputs'!B21*(1+'Inputs'!B22)^4) -> 109231.28 | H7: =G7/(1+'Scenarios'!F4)^5 -> 81623.97 | I7: 5
A8: =('Inputs'!B2*12*'Inputs'!B9*'Scenarios'!B2*(1+'Inputs'!B11)^5*'Scenarios'!C2*(1-'Inputs'!B13)-'Inputs'!B12*(1+'Inputs'!B14)^5-'Inputs'!B21*(1+'Inputs'!B22)^5) -> 65332.552 | B8: =A8/(1+'Scenarios'!F2)^6 -> 42332.98 | C8: 6 | D8: =('Inputs'!B2*12*'Inputs'!B9*'Scenarios'!B3*(1+'Inputs'!B11)^5*'Scenarios'!C3*(1-'Inputs'!B13)-'Inputs'!B12*(1+'Inputs'!B14)^5-'Inputs'!B21*(1+'Inputs'!B22)^5) -> 93314.376 | E8: =D8/(1+'Scenarios'!F3)^6 -> 63951.526 | F8: 6 | G8: =('Inputs'!B2*12*'Inputs'!B9*'Scenarios'!B4*(1+'Inputs'!B11)^5*'Scenarios'!C4*(1-'Inputs'!B13)-'Inputs'!B12*(1+'Inputs'!B14)^5-'Inputs'!B21*(1+'Inputs'!B22)^5) -> 111222.74 | H8: =G8/(1+'Scenarios'!F4)^6 -> 78407.645 | I8: 6
A9: =('Inputs'!B2*12*'Inputs'!B9*'Scenarios'!B2*(1+'Inputs'!B11)^6*'Scenarios'!C2*(1-'Inputs'!B13)-'Inputs'!B12*(1+'Inputs'!B14)^6-'Inputs'!B21*(1+'Inputs'!B22)^6) -> 66441.207 | B9: =A9/(1+'Scenarios'!F2)^7 -> 40047.763 | C9: 7 | D9: =('Inputs'!B2*12*'Inputs'!B9*'Scenarios'!B3*(1+'Inputs'!B11)^6*'Scenarios'!C3*(1-'Inputs'!B13)-'Inputs'!B12*(1+'Inputs'!B14)^6-'Inputs'!B21*(1+'Inputs'!B22)^6) -> 94982.667 | E9: =D9/(1+'Scenarios'!F3)^7 -> 61121.937 | F9: 7 | G9: =('Inputs'!B2*12*'Inputs'!B9*'Scenarios'!B4*(1+'Inputs'!B11)^6*'Scenarios'!C4*(1-'Inputs'!B13)-'Inputs'!B12*(1+'Inputs'!B14)^6-'Inputs'!B21*(1+'Inputs'!B22)^6) -> 113249.2 | H9: =G9/(1+'Scenarios'!F4)^7 -> 75317.187 | I9: 7
A10: =('Inputs'!B2*12*'Inputs'!B9*'Scenarios'!B2*(1+'Inputs'!B11)^7*'Scenarios'!C2*(1-'Inputs'!B13)-'Inputs'!B12*(1+'Inputs'!B14)^7-'Inputs'!B21*(1+'Inputs'!B22)^7) -> 67567.084 | B10: =A10/(1+'Scenarios'!F2)^8 -> 37885.015 | C10: 8 | D10: =('Inputs'!B2*12*'Inputs'!B9*'Scenarios'!B3*(1+'Inputs'!B11)^7*'Scenarios'!C3*(1-'Inputs'!B13)-'Inputs'!B12*(1+'Inputs'!B14)^7-'Inputs'!B21*(1+'Inputs'!B22)^7) -> 96679.374 | E10: =D10/(1+'Scenarios'!F3)^8 -> 58416.693 | F10: 8 | G10: =('Inputs'!B2*12*'Inputs'!B9*'Scenarios'!B4*(1+'Inputs'!B11)^7*'Scenarios'!C4*(1-'Inputs'!B13)-'Inputs'!B12*(1+'Inputs'!B14)^7-'Inputs'!B21*(1+'Inputs'!B22)^7) -> 115311.24 | H10: =G10/(1+'Scenarios'!F4)^8 -> 72347.698 | I10: 8
A11: =('Inputs'!B2*12*'Inputs'!B9*'Scenarios'!B2*(1+'Inputs'!B11)^8*'Scenarios'!C2*(1-'Inputs'!B13)-'Inputs'!B12*(1+'Inputs'!B14)^8-'Inputs'!B21*(1+'Inputs'!B22)^8) -> 68710.406 | B11: =A11/(1+'Scenarios'!F2)^9 -> 35838.212 | C11: 9 | D11: =('Inputs'!B2*12*'Inputs'!B9*'Scenarios'!B3*(1+'Inputs'!B11)^8*'Scenarios'!C3*(1-'Inputs'!B13)-'Inputs'!B12*(1+'Inputs'!B14)^8-'Inputs'!B21*(1+'Inputs'!B22)^8) -> 98404.942 | E11: =D11/(1+'Scenarios'!F3)^9 -> 55830.361 | F11: 9 | G11: =('Inputs'!B2*12*'Inputs'!B9*'Scenarios'!B4*(1+'Inputs'!B11)^8*'Scenarios'!C4*(1-'Inputs'!B13)-'Inputs'!B12*(1+'Inputs'!B14)^8-'Inputs'!B21*(1+'Inputs'!B22)^8) -> 117409.44 | H11: =G11/(1+'Scenarios'!F4)^9 -> 69494.47 | I11: 9
A12: =('Inputs'!B2*12*'Inputs'!B9*'Scenarios'!B2*(1+'Inputs'!B11)^9*'Scenarios'!C2*(1-'Inputs'!B13)-'Inputs'!B12*(1+'Inputs'!B14)^9-'Inputs'!B21*(1+'Inputs'!B22)^9) -> 69871.394 | B12: =A12/(1+'Scenarios'!F2)^10 -> 33901.176 | C12: 10 | D12: =('Inputs'!B2*12*'Inputs'!B9*'Scenarios'!B3*(1+'Inputs'!B11)^9*'Scenarios'!C3*(1-'Inputs'!B13)-'Inputs'!B12*(1+'Inputs'!B14)^9-'Inputs'!B21*(1+'Inputs'!B22)^9) -> 100159.82 | E12: =D12/(1+'Scenarios'!F3)^10 -> 53357.744 | F12: 10 | G12: =('Inputs'!B2*12*'Inputs'!B9*'Scenarios'!B4*(1+'Inputs'!B11)^9*'Scenarios'!C4*(1-'Inputs'!B13)-'Inputs'!B12*(1+'Inputs'!B14)^9-'Inputs'!B21*(1+'Inputs'!B22)^9) -> 119544.41 | H12: =G12/(1+'Scenarios'!F4)^10 -> 66752.976 | I12: 10
A13: =('Inputs'!B2*12*'Inputs'!B9*'Scenarios'!B2*(1+'Inputs'!B11)^10*'Scenarios'!C2*(1-'Inputs'!B13)-'Inputs'!B12*(1+'Inputs'!B14)^10-'Inputs'!B21*(1+'Inputs'!B22)^10) -> 71050.271 | B13: =A13/(1+'Scenarios'!F2)^11 -> 32068.056 | C13: 11 | D13: =('Inputs'!B2*12*'Inputs'!B9*'Scenarios'!B3*(1+'Inputs'!B11)^10*'Scenarios'!C3*(1-'Inputs'!B13)-'Inputs'!B12*(1+'Inputs'!B14)^10-'Inputs'!B21*(1+'Inputs'!B22)^10) -> 101944.47 | E13: =D13/(1+'Scenarios'!F3)^11 -> 50993.869 | F13: 11 | G13: =('Inputs'!B2*12*'Inputs'!B9*'Scenarios'!B4*(1+'Inputs'!B11)^10*'Scenarios'!C4*(1-'Inputs'!B13)-'Inputs'!B12*(1+'Inputs'!B14)^10-'Inputs'!B21*(1+'Inputs'!B22)^10) -> 121716.75 | H13: =G13/(1+'Scenarios'!F4)^11 -> 64118.865 | I13: 11
A14: =('Inputs'!B2*12*'Inputs'!B9*'Scenarios'!B2*(1+'Inputs'!B11)^11*'Scenarios'!C2*(1-'Inputs'!B13)-'Inputs'!B12*(1+'Inputs'!B14)^11-'Inputs'!B21*(1+'Inputs'!B22)^11) -> 72247.261 | B14: =A14/(1+'Scenarios'!F2)^12 -> 30333.311 | C14: 12 | D14: =('Inputs'!B2*12*'Inputs'!B9*'Scenarios'!B3*(1+'Inputs'!B11)^11*'Scenarios'!C3*(1-'Inputs'!B13)-'Inputs'!B12*(1+'Inputs'!B14)^11-'Inputs'!B21*(1+'Inputs'!B22)^11) -> 103759.34 | E14: =D14/(1+'Scenarios'!F3)^12 -> 48733.983 | F14: 12 | G14: =('Inputs'!B2*12*'Inputs'!B9*'Scenarios'!B4*(1+'Inputs'!B11)^11*'Scenarios'!C4*(1-'Inputs'!B13)-'Inputs'!B12*(1+'Inputs'!B14)^11-'Inputs'!B21*(1+'Inputs'!B22)^11) -> 123927.07 | H14: =G14/(1+'Scenarios'!F4)^12 -> 61587.957 | I14: 12
A15: =('Inputs'!B2*12*'Inputs'!B9*'Scenarios'!B2*(1+'Inputs'!B11)^12*'Scenarios'!C2*(1-'Inputs'!B13)-'Inputs'!B12*(1+'Inputs'!B14)^12-'Inputs'!B21*(1+'Inputs'!B22)^12) -> 73462.591 | B15: =A15/(1+'Scenarios'!F2)^13 -> 28691.695 | C15: 13 | D15: =('Inputs'!B2*12*'Inputs'!B9*'Scenarios'!B3*(1+'Inputs'!B11)^12*'Scenarios'!C3*(1-'Inputs'!B13)-'Inputs'!B12*(1+'Inputs'!B14)^12-'Inputs'!B21*(1+'Inputs'!B22)^12) -> 105604.91 | E15: =D15/(1+'Scenarios'!F3)^13 -> 46573.536 | F15: 13 | G15: =('Inputs'!B2*12*'Inputs'!B9*'Scenarios'!B4*(1+'Inputs'!B11)^12*'Scenarios'!C4*(1-'Inputs'!B13)-'Inputs'!B12*(1+'Inputs'!B14)^12-'Inputs'!B21*(1+'Inputs'!B22)^12) -> 126176 | H15: =G15/(1+'Scenarios'!F4)^13 -> 59156.231 | I15: 13
A16: =('Inputs'!B2*12*'Inputs'!B9*'Scenarios'!B2*(1+'Inputs'!B11)^13*'Scenarios'!C2*(1-'Inputs'!B13)-'Inputs'!B12*(1+'Inputs'!B14)^13-'Inputs'!B21*(1+'Inputs'!B22)^13) -> 74696.488 | B16: =A16/(1+'Scenarios'!F2)^14 -> 27138.24 | C16: 14 | D16: =('Inputs'!B2*12*'Inputs'!B9*'Scenarios'!B3*(1+'Inputs'!B11)^13*'Scenarios'!C3*(1-'Inputs'!B13)-'Inputs'!B12*(1+'Inputs'!B14)^13-'Inputs'!B21*(1+'Inputs'!B22)^13) -> 107481.65 | E16: =D16/(1+'Scenarios'!F3)^14 -> 44508.18 | F16: 14 | G16: =('Inputs'!B2*12*'Inputs'!B9*'Scenarios'!B4*(1+'Inputs'!B11)^13*'Scenarios'!C4*(1-'Inputs'!B13)-'Inputs'!B12*(1+'Inputs'!B14)^13-'Inputs'!B21*(1+'Inputs'!B22)^13) -> 128464.16 | H16: =G16/(1+'Scenarios'!F4)^14 -> 56819.822 | I16: 14
A17: =('Inputs'!B2*12*'Inputs'!B9*'Scenarios'!B2*(1+'Inputs'!B11)^14*'Scenarios'!C2*(1-'Inputs'!B13)-'Inputs'!B12*(1+'Inputs'!B14)^14-'Inputs'!B21*(1+'Inputs'!B22)^14) -> 75949.178 | B17: =A17/(1+'Scenarios'!F2)^15 -> 25668.241 | C17: 15 | D17: =('Inputs'!B2*12*'Inputs'!B9*'Scenarios'!B3*(1+'Inputs'!B11)^14*'Scenarios'!C3*(1-'Inputs'!B13)-'Inputs'!B12*(1+'Inputs'!B14)^14-'Inputs'!B21*(1+'Inputs'!B22)^14) -> 109390.05 | E17: =D17/(1+'Scenarios'!F3)^15 -> 42533.752 | F17: 15 | G17: =('Inputs'!B2*12*'Inputs'!B9*'Scenarios'!B4*(1+'Inputs'!B11)^14*'Scenarios'!C4*(1-'Inputs'!B13)-'Inputs'!B12*(1+'Inputs'!B14)^14-'Inputs'!B21*(1+'Inputs'!B22)^14) -> 130792.2 | H17: =G17/(1+'Scenarios'!F4)^15 -> 54575.017 | I17: 15
A18: =('Inputs'!B2*12*'Inputs'!B9*'Scenarios'!B2*(1+'Inputs'!B11)^15*'Scenarios'!C2*(1-'Inputs'!B13)-'Inputs'!B12*(1+'Inputs'!B14)^15-'Inputs'!B21*(1+'Inputs'!B22)^15) -> 77220.891 | B18: =A18/(1+'Scenarios'!F2)^16 -> 24277.244 | C18: 16 | D18: =('Inputs'!B2*12*'Inputs'!B9*'Scenarios'!B3*(1+'Inputs'!B11)^15*'Scenarios'!C3*(1-'Inputs'!B13)-'Inputs'!B12*(1+'Inputs'!B14)^15-'Inputs'!B21*(1+'Inputs'!B22)^15) -> 111330.58 | E18: =D18/(1+'Scenarios'!F3)^16 -> 40646.274 | F18: 16 | G18: =('Inputs'!B2*12*'Inputs'!B9*'Scenarios'!B4*(1+'Inputs'!B11)^15*'Scenarios'!C4*(1-'Inputs'!B13)-'Inputs'!B12*(1+'Inputs'!B14)^15-'Inputs'!B21*(1+'Inputs'!B22)^15) -> 133160.78 | H18: =G18/(1+'Scenarios'!F4)^16 -> 52418.245 | I18: 16
A19: =('Inputs'!B2*12*'Inputs'!B9*'Scenarios'!B2*(1+'Inputs'!B11)^16*'Scenarios'!C2*(1-'Inputs'!B13)-'Inputs'!B12*(1+'Inputs'!B14)^16-'Inputs'!B21*(1+'Inputs'!B22)^16) -> 78511.857 | B19: =A19/(1+'Scenarios'!F2)^17 -> 22961.029 | C19: 17 | D19: =('Inputs'!B2*12*'Inputs'!B9*'Scenarios'!B3*(1+'Inputs'!B11)^16*'Scenarios'!C3*(1-'Inputs'!B13)-'Inputs'!B12*(1+'Inputs'!B14)^16-'Inputs'!B21*(1+'Inputs'!B22)^16) -> 113303.74 | E19: =D19/(1+'Scenarios'!F3)^17 -> 38841.939 | F19: 17 | G19: =('Inputs'!B2*12*'Inputs'!B9*'Scenarios'!B4*(1+'Inputs'!B11)^16*'Scenarios'!C4*(1-'Inputs'!B13)-'Inputs'!B12*(1+'Inputs'!B14)^16-'Inputs'!B21*(1+'Inputs'!B22)^16) -> 135570.54 | H19: =G19/(1+'Scenarios'!F4)^17 -> 50346.075 | I19: 17
A20: =('Inputs'!B2*12*'Inputs'!B9*'Scenarios'!B2*(1+'Inputs'!B11)^17*'Scenarios'!C2*(1-'Inputs'!B13)-'Inputs'!B12*(1+'Inputs'!B14)^17-'Inputs'!B21*(1+'Inputs'!B22)^17) -> 79822.305 | B20: =A20/(1+'Scenarios'!F2)^18 -> 21715.604 | C20: 18 | D20: =('Inputs'!B2*12*'Inputs'!B9*'Scenarios'!B3*(1+'Inputs'!B11)^17*'Scenarios'!C3*(1-'Inputs'!B13)-'Inputs'!B12*(1+'Inputs'!B14)^17-'Inputs'!B21*(1+'Inputs'!B22)^17) -> 115310.02 | E20: =D20/(1+'Scenarios'!F3)^18 -> 37117.107 | F20: 18 | G20: =('Inputs'!B2*12*'Inputs'!B9*'Scenarios'!B4*(1+'Inputs'!B11)^17*'Scenarios'!C4*(1-'Inputs'!B13)-'Inputs'!B12*(1+'Inputs'!B14)^17-'Inputs'!B21*(1+'Inputs'!B22)^17) -> 138022.16 | H20: =G20/(1+'Scenarios'!F4)^18 -> 48355.208 | I20: 18
A21: =('Inputs'!B2*12*'Inputs'!B9*'Scenarios'!B2*(1+'Inputs'!B11)^18*'Scenarios'!C2*(1-'Inputs'!B13)-'Inputs'!B12*(1+'Inputs'!B14)^18-'Inputs'!B21*(1+'Inputs'!B22)^18) -> 81152.468 | B21: =A21/(1+'Scenarios'!F2)^19 -> 20537.185 | C21: 19 | D21: =('Inputs'!B2*12*'Inputs'!B9*'Scenarios'!B3*(1+'Inputs'!B11)^18*'Scenarios'!C3*(1-'Inputs'!B13)-'Inputs'!B12*(1+'Inputs'!B14)^18-'Inputs'!B21*(1+'Inputs'!B22)^18) -> 117349.94 | E21: =D21/(1+'Scenarios'!F3)^19 -> 35468.296 | F21: 19 | G21: =('Inputs'!B2*12*'Inputs'!B9*'Scenarios'!B4*(1+'Inputs'!B11)^18*'Scenarios'!C4*(1-'Inputs'!B13)-'Inputs'!B12*(1+'Inputs'!B14)^18-'Inputs'!B21*(1+'Inputs'!B22)^18) -> 140516.32 | H21: =G21/(1+'Scenarios'!F4)^19 -> 46442.473 | I21: 19
A22: =('Inputs'!B2*12*'Inputs'!B9*'Scenarios'!B2*(1+'Inputs'!B11)^19*'Scenarios'!C2*(1-'Inputs'!B13)-'Inputs'!B12*(1+'Inputs'!B14)^19-'Inputs'!B21*(1+'Inputs'!B22)^19)+('Inputs'!B2*12*'Inputs'!B9*'Scenarios'!B2*(1+'Inputs'!B11)^20*'Scenarios'!C2*(1-'Inputs'!B13)-'Inputs'!B12*(1+'Inputs'!B14)^20)/'Scenarios'!E2*(1-'Inputs'!B17) -> 1578675.8 | B22: =A22/(1+'Scenarios'!F2)^20 -> 371641.04 | C22: 20 | D22: =('Inputs'!B2*12*'Inputs'!B9*'Scenarios'!B3*(1+'Inputs'!B11)^19*'Scenarios'!C3*(1-'Inputs'!B13)-'Inputs'!B12*(1+'Inputs'!B14)^19-'Inputs'!B21*(1+'Inputs'!B22)^19)+('Inputs'!B2*12*'Inputs'!B9*'Scenarios'!B3*(1+'Inputs'!B11)^20*'Scenarios'!C3*(1-'Inputs'!B13)-'Inputs'!B12*(1+'Inputs'!B14)^20)/'Scenarios'!E3*(1-'Inputs'!B17) -> 2551811.5 | E22: =D22/(1+'Scenarios'!F3)^20 -> 724196.53 | F22: 20 | G22: =('Inputs'!B2*12*'Inputs'!B9*'Scenarios'!B4*(1+'Inputs'!B11)^19*'Scenarios'!C4*(1-'Inputs'!B13)-'Inputs'!B12*(1+'Inputs'!B14)^19-'Inputs'!B21*(1+'Inputs'!B22)^19)+('Inputs'!B2*12*'Inputs'!B9*'Scenarios'!B4*(1+'Inputs'!B11)^20*'Scenarios'!C4*(1-'Inputs'!B13)-'Inputs'!B12*(1+'Inputs'!B14)^20)/'Scenarios'!E4*(1-'Inputs'!B17) -> 3286264.7 | H22: =G22/(1+'Scenarios'!F4)^20 -> 1024672.9 | I22: 20

Sheet Environment
A1: Metric | B1: Before | C1: After | D1: Unit / evidence
A2: Floor area | B2: 600 | C2: 600 | D2: m2; design assumption
A3: Delivered energy intensity | B3: 250 | C3: 120 | D3: kWh/m2/year; assumptions, distinct from regulatory PEB primary-energy rating
A4: Energy price | B4: 0.15 | C4: 0.15 | D4: EUR/kWh; assumption not a supplier quote
A5: Operational emissions factor | B5: 0.2 | C5: 0.2 | D5: kgCO2e/kWh; illustrative, replace with heating-system factors
A6: Annual energy use | B6: =B2*B3 -> 150000 | C6: =C2*C3 -> 72000 | D6: kWh/year
A7: Annual utility expense | B7: =B6*B4 -> 22500 | C7: =C6*C4 -> 10800 | D7: EUR/year; tenant benefit, excluded from owner DCF
A8: Annual operational emissions | B8: =B6*B5/1000 -> 30 | C8: =C6*C5/1000 -> 14.4 | D8: tonnesCO2e/year; embodied carbon excluded
A9: Annual energy saved | C9: =B6-C6 -> 78000 | D9: kWh/year
A10: Annual emissions avoided | C10: =B8-C8 -> 15.6 | D10: tonnesCO2e/year
A11: Retrofit measures | B11: Insulation, airtightness, shading, ventilation | C11: Metering, efficient heating, water saving | D11: Cost included in renovation budget; audit needed
A12: Regulatory target A9 | B12: PEB275 by 2033 | C12: PEB150 no earlier than 2045 | D12: Check current implementing rules; aim for C where technically feasible

Sheet Social and services
A1: Measure | B1: Value | C1: Meaning / action
A2: Total monthly housing | B2: ='Dashboard'!B8 -> 650 | C2: Rent plus utilities
A3: Illustrative student budget | B3: ='Inputs'!B20 -> 1300 | C3: Assumption; survey target students
A4: Housing budget share | B4: =B2/B3 -> 0.5 | C4: Above 40% is a project screening concern, not a legal threshold
A5: Single-person RIS | B5: 1367.34 | C5: A10 effective September 2026; eligibility is individual CPAS decision
A6: Cohabitant RIS | B6: 911.56 | C6: A10 effective September 2026; shared housing status needs CPAS assessment
A7: Share of single RIS | B7: =B2/B5 -> 0.47537555 | C7: Affordability stress indicator
A8: Share of cohabitant RIS | B8: =B2/B6 -> 0.71306332 | C8: Affordability stress indicator
A9: Included in rent | B9: Furniture, Wi-Fi, communal cleaning | C9: Supplier quotes; operator costs in owner budget
A10: Utilities | B10: EUR100/month provisional | C10: Annual reconciliation, clear allocation and separate bills
A11: Optional services | B11: Laundry paid at cost; no meal plan | C11: No additional profit assumed
A12: Neighbourhood | B12: Quiet hours, complaint contact, waste separation | C12: Pre-opening neighbour meeting; monitor complaints
A13: Inclusion | B13: Accessible ground-floor room and step-free route | C13: Architect to verify feasibility and cost
A14: Support | B14: University social services / CPAS referral | C14: Do not assume grants as recurring owner income

Sheet Decision matrix
A1: Criterion | B1: Weight | C1: Etterbeek-Petillon | D1: Ixelles cemetery | E1: Solbosch edge | F1: Basis / illustrative scores 1–5
A2: Transport | B2: 0.25 | C2: 5 | D2: 4 | E2: 4 | F2: A4; test actual walking route and service frequency
A3: Campus access | B3: 0.2 | C3: 5 | D3: 5 | E3: 5 | F3: VUB/ULB proximity; exact address needed
A4: Affordability | B4: 0.2 | C4: 3 | D4: 3 | E4: 3 | F4: Same base budget; acquisition prices unverified
A5: Environmental potential | B5: 0.15 | C5: 3 | D5: 3 | E5: 3 | F5: No audited building; neutral scores
A6: Social fit | B6: 0.1 | C6: 3 | D6: 3 | E6: 4 | F6: Judgement only; survey neighbours
A7: Execution risk | B7: 0.1 | C7: 3 | D7: 3 | E7: 3 | F7: No site-specific permission assessed
A8: Weight total | B8: =SUM(B2:B7) -> 1
A9: Weighted score | C9: =SUMPRODUCT($B$2:$B$7,C2:C7) -> 3.9 | D9: =SUMPRODUCT($B$2:$B$7,D2:D7) -> 3.65 | E9: =SUMPRODUCT($B$2:$B$7,E2:E7) -> 3.75 | F9: Scores are provisional; no property ranking established
A10: Legal gate | B10: UNKNOWN | C10: UNKNOWN | D10: UNKNOWN | E10: UNKNOWN | F10: Any failure overrides score and NPV; no acquisition authorised

Sheet Legal and risks
A1: Issue | B1: Rule / evidence | C1: Status | D1: Next action | E1: Owner
A2: Registration duty | B2: 12.5% on existing-building purchase A1 | C2: Modelled | D2: Notary confirms tax base and VAT status | E2: Notary
A3: Planning | B3: Municipal permits; lawful use and unit count A7/A8 | C3: UNVERIFIED | D3: Obtain planning records; sale condition precedent | E3: Architect
A4: Habitability | B4: Brussels minimum standards changed January 2026 A5 | C4: UNVERIFIED | D4: Room-by-room compliance survey | E4: Architect
A5: Fire | B5: Smoke detection and fire safety A5 | C5: UNVERIFIED | D5: Consult SIAMU; cost evacuation and compartmentation | E5: Fire engineer
A6: Lease | B6: Student evidence and max 12 months A6; register within two months A12 | C6: UNVERIFIED | D6: Use current regional template; review deposit and termination | E6: Legal adviser
A7: Rent | B7: Indexation and rent fairness subject to regional rules | C7: UNVERIFIED | D7: Check reference rent and current indexation restrictions | E7: Legal adviser
A8: Energy | B8: Regional PEB targets A9; certificate A11 | C8: UNVERIFIED | D8: Obtain certificate, audit and staged retrofit plan | E8: Energy auditor
A9: Tax | B9: Investor income tax and VAT depend on entity and services | C9: EXCLUDED | D9: Add entity-specific taxation before investment decision | E9: Accountant
A10: Overruns | B10: 15% contingency, downside +20% renovation | C10: Scenario | D10: Fixed scope and quotes; inspect structural condition | E10: Project manager
A11: Letting | B11: 95% paid occupancy assumes summer demand | C11: Scenario | D11: Validate academic vs full-year lease mix | E11: Operator
A12: Municipal charges | B12: Property tax, local taxes and permit fees vary by address | C12: ALLOWANCE | D12: Replace EUR10000 tax allowance with actual assessment | E12: Accountant
