Workbook

Sheet Executive Report
A1: BRUSSELS STUDENT HOUSING | B1: EXECUTIVE DECISION REPORT | v2.0
A2: Recommendation | B2: Conditional shortlist: maximize affordable beds under the EUR15m planning budget.
A3: Evidence | B3: Brussels average total rent EUR695 in Kotkompas 2025–2026; designated supply is constrained (Sources).
A4: Approval gate | B4: Municipal and project policy applicability, social eligibility and quotes must be confirmed before commitment.
A5: Decision metric | B5: Affordable beds first, NPV second; no probability weighting; projects are illustrative.
A6: Feasible combinations | B6: =SUM(Portfolios!O2:O257) -> 75
A7: Recommended combination index | B7: =MATCH(MAX(Portfolios!Q2:Q257),Portfolios!Q2:Q257,0) -> 31
A8: KPI | B8: Recommended | C8: Manual selection
A9: Total investment | B9: =SUMPRODUCT(Projects!N2:N9,Projects!R2:R9) -> 14500000 | C9: =SUMPRODUCT(Projects!N2:N9,Projects!H2:H9) -> 14500000
A10: Total beds | B10: =SUMPRODUCT(Projects!C2:C9,Projects!R2:R9) -> 350 | C10: =SUMPRODUCT(Projects!C2:C9,Projects!H2:H9) -> 350
A11: Affordable beds | B11: =SUMPRODUCT(Projects!D2:D9,Projects!R2:R9) -> 172 | C11: =SUMPRODUCT(Projects!D2:D9,Projects!H2:H9) -> 172
A12: NPV incl terminal value | B12: =SUMPRODUCT(Projects!O2:O9,Projects!R2:R9) -> 11863873 | C12: =SUMPRODUCT(Projects!O2:O9,Projects!H2:H9) -> 11863873
A13: Year 1 NOI | B13: =SUMPRODUCT(Projects!M2:M9,Projects!R2:R9) -> 1216467.7 | C13: =SUMPRODUCT(Projects!M2:M9,Projects!H2:H9) -> 1216467.7
A14: Year 1 NOI yield | B14: =IFERROR(B13/B9,0) -> 0.083894324
A15: Budget headroom | B15: =Inputs!B2-B9 -> 500000
A16: Manual planning status | C16: =IF(AND(C9<=Inputs!B2,C11>=Inputs!B3,C12>=Inputs!B18,SUMPRODUCT(Projects!H2:H9,Projects!Q2:Q9)=SUM(Projects!H2:H9)),"PLANNING FEASIBLE","FAIL") -> PLANNING FEASIBLE
A18: Shortlist at saved inputs | B18: D / Etterbeek, E / Schaerbeek, F / Jette, G / Molenbeek-Saint-Jean
A19: Interpretation | B19: Recommendation updates via Projects R when inputs change; this text records the saved-input shortlist.
A20: Affordability | B20: EUR550 all-in ceiling is a course planning definition. It does not establish social-housing legal compliance.
A21: Municipal differences | B21: City Brussels policy: 20% from 30 student units. Ixelles: 15% for large projects. Other 17 minima unverified.
A22: Risk | B22: Downside: NPV about -EUR0.43m and cost EUR16.675m, exceeding the EUR15m budget. Secure contingency or reduce scope before commitment.
A23: Next agile sprint | B23: Validate thresholds and allocation with municipalities/AISE; replace costs with quotes; add delivery schedule and debt only after evidence.
A24: Decision requested | B24: Approve further feasibility work on the shortlist; capital commitment remains conditional on due diligence.

Sheet Guide
A1: HOW TO USE | B1: Decision model v2.0 | 14 October 2026
A2: 1 | B2: Read Executive Report. All eight developments are hypothetical investment opportunities.
A3: 2 | B3: Blue cells are editable assumptions; green cells hold external evidence; black cells are formulas.
A4: 3 | B4: Edit Inputs, project costs/rents/beds, municipal planning percentages and policy applicability.
A5: 4 | B5: Projects H is manual selection 0/1. Dashboard compares manual selection with the live optimal recommendation.
A6: 5 | B6: Portfolios enumerates all 256 binary combinations: maximize affordable beds, then NPV at equal beds.
A7: 6 | B7: Feasible requires budget, at least target affordable beds, nonnegative portfolio NPV and all selected projects passing planning/rent checks.
A8: 7 | B8: Municipal source evidence is distinct from verified legal approval. Unknown requirements do not mean zero requirements.
A9: 8 | B9: Change project policy applicability to 1 only when a cited policy applies; social allocation and rent must be validated separately.
A10: 9 | B10: Recommendation is conditional feasibility analysis. Obtain municipal confirmation, quotes, demand studies and due diligence before investment.
A11: 10 | B11: Reopen in Excel to recalculate edits. Run python3 build_model.py to regenerate defaults; it overwrites manual edits.
A12: Scope | B12: Unlevered pre-tax cash flow; no borrowing, grants, corporate tax, construction delays or VAT separately. Total cost inputs must include acquisition, fees, taxes and contingency.
... A15: Authors | B15: Nisa, Maite, Ilias — names supplied with uncertainty; confirm before course submission.

Sheet Inputs
A1: Parameter | B1: Value | C1: Definition / evidence
A2: Capital budget | B2: 15000000 | C2: EUR; total development outlay; illustrative
A3: Minimum affordable beds | B3: 80 | C3: Portfolio target; illustrative
A4: Base occupancy | B4: 0.95 | C4: Same for both rent classes; illustrative
A5: Months billed | B5: 12 | C5: Annual contracts; illustrative
A6: Variable operating share | B6: 0.15 | C6: Share of collected base rents; illustrative
A7: Fixed annual operating cost / bed | B7: 1600 | C7: EUR; includes reserve, insurance, maintenance; illustrative
A8: Rent and operating growth | B8: 0.02 | C8: Annual; both rent and costs grow at same rate
A9: Discount rate | B9: 0.06 | C9: Unlevered nominal annual hurdle; illustrative
A10: Exit capitalization rate | B10: 0.055 | C10: Terminal value on year 21 NOI; illustrative
A11: Sale cost share | B11: 0.02 | C11: Terminal sale proceeds haircut
A12: Hold years | B12: 20 | C12: Fixed 20-year DCF; change code to alter horizon
A13: Affordable all-in rent ceiling | B13: 550 | C13: EUR/month; course definition, not legal social-rent definition
... A18: Portfolio minimum NPV | B18: 0 | C18: Unlevered; positive-NPV requirement

Sheet Municipalities
A1: Municipality | B1: Sourced policy share | C1: Planning share (editable) | D1: Activation / scope | E1: Evidence status | F1: Source
A2: Anderlecht | C2: 0.25 | D2: Unknown; request project-specific minimum | E2: UNVERIFIED | F2: Not yet located
A3: Auderghem | C3: 0.25 | D3: Unknown; request project-specific minimum | E3: UNVERIFIED | F3: Not yet located
A4: Berchem-Sainte-Agathe | C4: 0.25 | D4: Unknown; request project-specific minimum | E4: UNVERIFIED | F4: Not yet located
A5: Bruxelles-Ville | B5: 0.2 | C5: 0.25 | D5: >=30 student units; social allocation | E5: POLICY FOUND; application not verified | F5: https://www.bruxelles.be/sites/default/files/bxl/Recommandations_logements_etudiants_VBX_17juin2021.pdf
A6: Etterbeek | C6: 0.25 | D6: Unknown; request project-specific minimum | E6: UNVERIFIED | F6: Not yet located
A7: Evere | C7: 0.25 | D7: Unknown; request project-specific minimum | E7: UNVERIFIED | F7: Not yet located
A8: Forest | C8: 0.25 | D8: Unknown; request project-specific minimum | E8: UNVERIFIED | F8: Not yet located
A9: Ganshoren | C9: 0.25 | D9: Unknown; request project-specific minimum | E9: UNVERIFIED | F9: Not yet located
A10: Ixelles | B10: 0.15 | C10: 0.25 | D10: Large kot projects; trigger needs confirmation | E10: POLICY FOUND; application not verified | F10: https://www.ixelles.be/site/downloads/publications/infoxl-2014-/infoxl20250304.pdf
A11: Jette | C11: 0.25 | D11: Unknown; request project-specific minimum | E11: UNVERIFIED | F11: Not yet located
A12: Koekelberg | C12: 0.25 | D12: Unknown; request project-specific minimum | E12: UNVERIFIED | F12: Not yet located
A13: Molenbeek-Saint-Jean | C13: 0.25 | D13: Unknown; request project-specific minimum | E13: UNVERIFIED | F13: Not yet located
A14: Saint-Gilles | C14: 0.25 | D14: Unknown; request project-specific minimum | E14: UNVERIFIED | F14: Not yet located
A15: Saint-Josse-ten-Noode | C15: 0.25 | D15: Unknown; request project-specific minimum | E15: UNVERIFIED | F15: Not yet located
A16: Schaerbeek | C16: 0.25 | D16: Unknown; request project-specific minimum | E16: UNVERIFIED | F16: Not yet located
A17: Uccle | C17: 0.25 | D17: Unknown; request project-specific minimum | E17: UNVERIFIED | F17: Not yet located
A18: Watermael-Boitsfort | C18: 0.25 | D18: Unknown; request project-specific minimum | E18: UNVERIFIED | F18: Not yet located
A19: Woluwe-Saint-Lambert | C19: 0.25 | D19: Unknown; request project-specific minimum | E19: UNVERIFIED | F19: Not yet located
A20: Woluwe-Saint-Pierre | C20: 0.25 | D20: Unknown; request project-specific minimum | E20: UNVERIFIED | F20: Not yet located

Sheet Projects
A1: ID | B1: Municipality | C1: Beds | D1: Affordable beds | E1: Affordable base rent/mo | F1: Market base rent/mo | G1: Total development cost | H1: Manual select 0/1 | I1: Policy applies 0/1 | J1: Effective planning minimum | K1: Required affordable beds | L1: Year 1 collected rent | M1: Year 1 NOI | N1: Cost with overrun | O1: NPV incl exit | P1: NOI yield | Q1: Planning & rent pass | R1: Recommended select | S1: Affordable all-in rent
A2: A | B2: Bruxelles-Ville | C2: 100 | D2: 40 | E2: 440 | F2: 680 | G2: 4800000 | H2: 0 | I2: 1 | J2: =MAX(Municipalities!C5,IF(I2=1,Municipalities!B5,0)) -> 0.25 | K2: =ROUNDUP(C2*J2,0) -> 25 | L2: =(D2*E2+(C2-D2)*F2)*Inputs!B5*Inputs!B4 -> 665760 | M2: =L2*(1-Inputs!B6)-C2*Inputs!B7 -> 405896 | N2: =G2*(1+Inputs!B17) -> 4800000 | O2: =SUM('Cash Flows'!D2:D22) -> 3996773.4 | P2: =IFERROR(M2/N2,0) -> 0.084561667 | Q2: =IF(AND(D2>=K2,D2<=C2,E2+Inputs!B14<=Inputs!B13,C2>0,D2>=0,E2>0,F2>0,G2>0),1,0) -> 1 | R2: =IF('Executive Report'!B6=0,0,INDEX(Portfolios!B$2:B$257,'Executive Report'!B7)) -> 0 | S2: =E2+Inputs!B14 -> 540
A3: B | B3: Ixelles | C3: 80 | D3: 24 | E3: 450 | F3: 730 | G3: 4300000 | H3: 0 | I3: 1 | J3: =MAX(Municipalities!C10,IF(I3=1,Municipalities!B10,0)) -> 0.25 | K3: =ROUNDUP(C3*J3,0) -> 20 | L3: =(D3*E3+(C3-D3)*F3)*Inputs!B5*Inputs!B4 -> 589152 | M3: =L3*(1-Inputs!B6)-C3*Inputs!B7 -> 372779.2 | N3: =G3*(1+Inputs!B17) -> 4300000 | O3: =SUM('Cash Flows'!D23:D43) -> 3779050.2 | P3: =IFERROR(M3/N3,0) -> 0.086692837 | Q3: =IF(AND(D3>=K3,D3<=C3,E3+Inputs!B14<=Inputs!B13,C3>0,D3>=0,E3>0,F3>0,G3>0),1,0) -> 1 | R3: =IF('Executive Report'!B6=0,0,INDEX(Portfolios!C$2:C$257,'Executive Report'!B7)) -> 0 | S3: =E3+Inputs!B14 -> 550
A4: C | B4: Anderlecht | C4: 120 | D4: 60 | E4: 400 | F4: 620 | G4: 4900000 | H4: 0 | I4: 0 | J4: =MAX(Municipalities!C2,IF(I4=1,Municipalities!B2,0)) -> 0.25 | K4: =ROUNDUP(C4*J4,0) -> 30 | L4: =(D4*E4+(C4-D4)*F4)*Inputs!B5*Inputs!B4 -> 697680 | M4: =L4*(1-Inputs!B6)-C4*Inputs!B7 -> 401028 | N4: =G4*(1+Inputs!B17) -> 4900000 | O4: =SUM('Cash Flows'!D44:D64) -> 3791271.7 | P4: =IFERROR(M4/N4,0) -> 0.081842449 | Q4: =IF(AND(D4>=K4,D4<=C4,E4+Inputs!B14<=Inputs!B13,C4>0,D4>=0,E4>0,F4>0,G4>0),1,0) -> 1 | R4: =IF('Executive Report'!B6=0,0,INDEX(Portfolios!D$2:D$257,'Executive Report'!B7)) -> 0 | S4: =E4+Inputs!B14 -> 500
A5: D | B5: Etterbeek | C5: 70 | D5: 21 | E5: 440 | F5: 700 | G5: 3400000 | H5: 1 | I5: 0 | J5: =MAX(Municipalities!C6,IF(I5=1,Municipalities!B6,0)) -> 0.25 | K5: =ROUNDUP(C5*J5,0) -> 18 | L5: =(D5*E5+(C5-D5)*F5)*Inputs!B5*Inputs!B4 -> 496356 | M5: =L5*(1-Inputs!B6)-C5*Inputs!B7 -> 309902.6 | N5: =G5*(1+Inputs!B17) -> 3400000 | O5: =SUM('Cash Flows'!D65:D85) -> 3316358.2 | P5: =IFERROR(M5/N5,0) -> 0.091147824 | Q5: =IF(AND(D5>=K5,D5<=C5,E5+Inputs!B14<=Inputs!B13,C5>0,D5>=0,E5>0,F5>0,G5>0),1,0) -> 1 | R5: =IF('Executive Report'!B6=0,0,INDEX(Portfolios!E$2:E$257,'Executive Report'!B7)) -> 1 | S5: =E5+Inputs!B14 -> 540
A6: E | B6: Schaerbeek | C6: 90 | D6: 45 | E6: 410 | F6: 640 | G6: 3800000 | H6: 1 | I6: 0 | J6: =MAX(Municipalities!C16,IF(I6=1,Municipalities!B16,0)) -> 0.25 | K6: =ROUNDUP(C6*J6,0) -> 23 | L6: =(D6*E6+(C6-D6)*F6)*Inputs!B5*Inputs!B4 -> 538650 | M6: =L6*(1-Inputs!B6)-C6*Inputs!B7 -> 313852.5 | N6: =G6*(1+Inputs!B17) -> 3800000 | O6: =SUM('Cash Flows'!D86:D106) -> 3001962.4 | P6: =IFERROR(M6/N6,0) -> 0.082592763 | Q6: =IF(AND(D6>=K6,D6<=C6,E6+Inputs!B14<=Inputs!B13,C6>0,D6>=0,E6>0,F6>0,G6>0),1,0) -> 1 | R6: =IF('Executive Report'!B6=0,0,INDEX(Portfolios!F$2:F$257,'Executive Report'!B7)) -> 1 | S6: =E6+Inputs!B14 -> 510
A7: F | B7: Jette | C7: 80 | D7: 40 | E7: 400 | F7: 610 | G7: 3200000 | H7: 1 | I7: 0 | J7: =MAX(Municipalities!C11,IF(I7=1,Municipalities!B11,0)) -> 0.25 | K7: =ROUNDUP(C7*J7,0) -> 20 | L7: =(D7*E7+(C7-D7)*F7)*Inputs!B5*Inputs!B4 -> 460560 | M7: =L7*(1-Inputs!B6)-C7*Inputs!B7 -> 263476 | N7: =G7*(1+Inputs!B17) -> 3200000 | O7: =SUM('Cash Flows'!D107:D127) -> 2510178.6 | P7: =IFERROR(M7/N7,0) -> 0.08233625 | Q7: =IF(AND(D7>=K7,D7<=C7,E7+Inputs!B14<=Inputs!B13,C7>0,D7>=0,E7>0,F7>0,G7>0),1,0) -> 1 | R7: =IF('Executive Report'!B6=0,0,INDEX(Portfolios!G$2:G$257,'Executive Report'!B7)) -> 1 | S7: =E7+Inputs!B14 -> 500
A8: G | B8: Molenbeek-Saint-Jean | C8: 110 | D8: 66 | E8: 390 | F8: 600 | G8: 4100000 | H8: 1 | I8: 0 | J8: =MAX(Municipalities!C13,IF(I8=1,Municipalities!B13,0)) -> 0.25 | K8: =ROUNDUP(C8*J8,0) -> 28 | L8: =(D8*E8+(C8-D8)*F8)*Inputs!B5*Inputs!B4 -> 594396 | M8: =L8*(1-Inputs!B6)-C8*Inputs!B7 -> 329236.6 | N8: =G8*(1+Inputs!B17) -> 4100000 | O8: =SUM('Cash Flows'!D128:D148) -> 3035374 | P8: =IFERROR(M8/N8,0) -> 0.08030161 | Q8: =IF(AND(D8>=K8,D8<=C8,E8+Inputs!B14<=Inputs!B13,C8>0,D8>=0,E8>0,F8>0,G8>0),1,0) -> 1 | R8: =IF('Executive Report'!B6=0,0,INDEX(Portfolios!H$2:H$257,'Executive Report'!B7)) -> 1 | S8: =E8+Inputs!B14 -> 490
A9: H | B9: Woluwe-Saint-Lambert | C9: 90 | D9: 27 | E9: 450 | F9: 720 | G9: 4500000 | H9: 0 | I9: 0 | J9: =MAX(Municipalities!C19,IF(I9=1,Municipalities!B19,0)) -> 0.25 | K9: =ROUNDUP(C9*J9,0) -> 23 | L9: =(D9*E9+(C9-D9)*F9)*Inputs!B5*Inputs!B4 -> 655614 | M9: =L9*(1-Inputs!B6)-C9*Inputs!B7 -> 413271.9 | N9: =G9*(1+Inputs!B17) -> 4500000 | O9: =SUM('Cash Flows'!D149:D169) -> 4456627.4 | P9: =IFERROR(M9/N9,0) -> 0.0918382 | Q9: =IF(AND(D9>=K9,D9<=C9,E9+Inputs!B14<=Inputs!B13,C9>0,D9>=0,E9>0,F9>0,G9>0),1,0) -> 1 | R9: =IF('Executive Report'!B6=0,0,INDEX(Portfolios!I$2:I$257,'Executive Report'!B7)) -> 0 | S9: =E9+Inputs!B14 -> 550

Sheet Cash Flows
A1: Project | B1: Year | C1: Unlevered cash flow | D1: Discounted cash flow
A2: A | B2: 0 | C2: =-Projects!N2 -> -4800000 | D2: =C2/(1+Inputs!B9)^B2 -> -4800000
A3: A | B3: 1 | C3: =Projects!M2*(1+Inputs!B8)^(B3-1) -> 405896 | D3: =C3/(1+Inputs!B9)^B3 -> 382920.75
A4: A | B4: 2 | C4: =Projects!M2*(1+Inputs!B8)^(B4-1) -> 414013.92 | D4: =C4/(1+Inputs!B9)^B4 -> 368470.91
A5: A | B5: 3 | C5: =Projects!M2*(1+Inputs!B8)^(B5-1) -> 422294.2 | D5: =C5/(1+Inputs!B9)^B5 -> 354566.35
A6: A | B6: 4 | C6: =Projects!M2*(1+Inputs!B8)^(B6-1) -> 430740.08 | D6: =C6/(1+Inputs!B9)^B6 -> 341186.49
A7: A | B7: 5 | C7: =Projects!M2*(1+Inputs!B8)^(B7-1) -> 439354.88 | D7: =C7/(1+Inputs!B9)^B7 -> 328311.53
A8: A | B8: 6 | C8: =Projects!M2*(1+Inputs!B8)^(B8-1) -> 448141.98 | D8: =C8/(1+Inputs!B9)^B8 -> 315922.41
A9: A | B9: 7 | C9: =Projects!M2*(1+Inputs!B8)^(B9-1) -> 457104.82 | D9: =C9/(1+Inputs!B9)^B9 -> 304000.81
A10: A | B10: 8 | C10: =Projects!M2*(1+Inputs!B8)^(B10-1) -> 466246.92 | D10: =C10/(1+Inputs!B9)^B10 -> 292529.08
A11: A | B11: 9 | C11: =Projects!M2*(1+Inputs!B8)^(B11-1) -> 475571.86 | D11: =C11/(1+Inputs!B9)^B11 -> 281490.25
A12: A | B12: 10 | C12: =Projects!M2*(1+Inputs!B8)^(B12-1) -> 485083.29 | D12: =C12/(1+Inputs!B9)^B12 -> 270867.98
A13: A | B13: 11 | C13: =Projects!M2*(1+Inputs!B8)^(B13-1) -> 494784.96 | D13: =C13/(1+Inputs!B9)^B13 -> 260646.54
A14: A | B14: 12 | C14: =Projects!M2*(1+Inputs!B8)^(B14-1) -> 504680.66 | D14: =C14/(1+Inputs!B9)^B14 -> 250810.83
A15: A | B15: 13 | C15: =Projects!M2*(1+Inputs!B8)^(B15-1) -> 514774.27 | D15: =C15/(1+Inputs!B9)^B15 -> 241346.27
A16: A | B16: 14 | C16: =Projects!M2*(1+Inputs!B8)^(B16-1) -> 525069.76 | D16: =C16/(1+Inputs!B9)^B16 -> 232238.86
A17: A | B17: 15 | C17: =Projects!M2*(1+Inputs!B8)^(B17-1) -> 535571.15 | D17: =C17/(1+Inputs!B9)^B17 -> 223475.13
A18: A | B18: 16 | C18: =Projects!M2*(1+Inputs!B8)^(B18-1) -> 546282.58 | D18: =C18/(1+Inputs!B9)^B18 -> 215042.11
A19: A | B19: 17 | C19: =Projects!M2*(1+Inputs!B8)^(B19-1) -> 557208.23 | D19: =C19/(1+Inputs!B9)^B19 -> 206927.31
A20: A | B20: 18 | C20: =Projects!M2*(1+Inputs!B8)^(B20-1) -> 568352.39 | D20: =C20/(1+Inputs!B9)^B20 -> 199118.73
A21: A | B21: 19 | C21: =Projects!M2*(1+Inputs!B8)^(B21-1) -> 579719.44 | D21: =C21/(1+Inputs!B9)^B21 -> 191604.82
A22: A | B22: 20 | C22: =Projects!M2*(1+Inputs!B8)^(B22-1)+Projects!M2*(1+Inputs!B8)^20/Inputs!B10*(1-Inputs!B11) -> 11338174 | D22: =C22/(1+Inputs!B9)^B22 -> 3535296.2
A23: B | B23: 0 | C23: =-Projects!N3 -> -4300000 | D23: =C23/(1+Inputs!B9)^B23 -> -4300000
A24: B | B24: 1 | C24: =Projects!M3*(1+Inputs!B8)^(B24-1) -> 372779.2 | D24: =C24/(1+Inputs!B9)^B24 -> 351678.49
A25: B | B25: 2 | C25: =Projects!M3*(1+Inputs!B8)^(B25-1) -> 380234.78 | D25: =C25/(1+Inputs!B9)^B25 -> 338407.6
A26: B | B26: 3 | C26: =Projects!M3*(1+Inputs!B8)^(B26-1) -> 387839.48 | D26: =C26/(1+Inputs!B9)^B26 -> 325637.51
A27: B | B27: 4 | C27: =Projects!M3*(1+Inputs!B8)^(B27-1) -> 395596.27 | D27: =C27/(1+Inputs!B9)^B27 -> 313349.3
A28: B | B28: 5 | C28: =Projects!M3*(1+Inputs!B8)^(B28-1) -> 403508.19 | D28: =C28/(1+Inputs!B9)^B28 -> 301524.8
A29: B | B29: 6 | C29: =Projects!M3*(1+Inputs!B8)^(B29-1) -> 411578.36 | D29: =C29/(1+Inputs!B9)^B29 -> 290146.5
A30: B | B30: 7 | C30: =Projects!M3*(1+Inputs!B8)^(B30-1) -> 419809.93 | D30: =C30/(1+Inputs!B9)^B30 -> 279197.58
A31: B | B31: 8 | C31: =Projects!M3*(1+Inputs!B8)^(B31-1) -> 428206.12 | D31: =C31/(1+Inputs!B9)^B31 -> 268661.82
A32: B | B32: 9 | C32: =Projects!M3*(1+Inputs!B8)^(B32-1) -> 436770.25 | D32: =C32/(1+Inputs!B9)^B32 -> 258523.64
A33: B | B33: 10 | C33: =Projects!M3*(1+Inputs!B8)^(B33-1) -> 445505.65 | D33: =C33/(1+Inputs!B9)^B33 -> 248768.03
A34: B | B34: 11 | C34: =Projects!M3*(1+Inputs!B8)^(B34-1) -> 454415.76 | D34: =C34/(1+Inputs!B9)^B34 -> 239380.56
A35: B | B35: 12 | C35: =Projects!M3*(1+Inputs!B8)^(B35-1) -> 463504.08 | D35: =C35/(1+Inputs!B9)^B35 -> 230347.33
A36: B | B36: 13 | C36: =Projects!M3*(1+Inputs!B8)^(B36-1) -> 472774.16 | D36: =C36/(1+Inputs!B9)^B36 -> 221654.98
A37: B | B37: 14 | C37: =Projects!M3*(1+Inputs!B8)^(B37-1) -> 482229.64 | D37: =C37/(1+Inputs!B9)^B37 -> 213290.64
A38: B | B38: 15 | C38: =Projects!M3*(1+Inputs!B8)^(B38-1) -> 491874.24 | D38: =C38/(1+Inputs!B9)^B38 -> 205241.93
A39: B | B39: 16 | C39: =Projects!M3*(1+Inputs!B8)^(B39-1) -> 501711.72 | D39: =C39/(1+Inputs!B9)^B39 -> 197496.96
A40: B | B40: 17 | C40: =Projects!M3*(1+Inputs!B8)^(B40-1) -> 511745.96 | D40: =C40/(1+Inputs!B9)^B40 -> 190044.24
A41: B | B41: 18 | C41: =Projects!M3*(1+Inputs!B8)^(B41-1) -> 521980.88 | D41: =C41/(1+Inputs!B9)^B41 -> 182872.76
A42: B | B42: 19 | C42: =Projects!M3*(1+Inputs!B8)^(B42-1) -> 532420.49 | D42: =C42/(1+Inputs!B9)^B42 -> 175971.9
A43: B | B43: 20 | C43: =Projects!M3*(1+Inputs!B8)^(B43-1)+Projects!M3*(1+Inputs!B8)^20/Inputs!B10*(1-Inputs!B11) -> 10413099 | D43: =C43/(1+Inputs!B9)^B43 -> 3246853.6
A44: C | B44: 0 | C44: =-Projects!N4 -> -4900000 | D44: =C44/(1+Inputs!B9)^B44 -> -4900000
A45: C | B45: 1 | C45: =Projects!M4*(1+Inputs!B8)^(B45-1) -> 401028 | D45: =C45/(1+Inputs!B9)^B45 -> 378328.3
A46: C | B46: 2 | C46: =Projects!M4*(1+Inputs!B8)^(B46-1) -> 409048.56 | D46: =C46/(1+Inputs!B9)^B46 -> 364051.76
A47: C | B47: 3 | C47: =Projects!M4*(1+Inputs!B8)^(B47-1) -> 417229.53 | D47: =C47/(1+Inputs!B9)^B47 -> 350313.96
A48: C | B48: 4 | C48: =Projects!M4*(1+Inputs!B8)^(B48-1) -> 425574.12 | D48: =C48/(1+Inputs!B9)^B48 -> 337094.57
A49: C | B49: 5 | C49: =Projects!M4*(1+Inputs!B8)^(B49-1) -> 434085.6 | D49: =C49/(1+Inputs!B9)^B49 -> 324374.02
A50: C | B50: 6 | C50: =Projects!M4*(1+Inputs!B8)^(B50-1) -> 442767.32 | D50: =C50/(1+Inputs!B9)^B50 -> 312133.49
A51: C | B51: 7 | C51: =Projects!M4*(1+Inputs!B8)^(B51-1) -> 451622.66 | D51: =C51/(1+Inputs!B9)^B51 -> 300354.86
A52: C | B52: 8 | C52: =Projects!M4*(1+Inputs!B8)^(B52-1) -> 460655.12 | D52: =C52/(1+Inputs!B9)^B52 -> 289020.72
A53: C | B53: 9 | C53: =Projects!M4*(1+Inputs!B8)^(B53-1) -> 469868.22 | D53: =C53/(1+Inputs!B9)^B53 -> 278114.28
A54: C | B54: 10 | C54: =Projects!M4*(1+Inputs!B8)^(B54-1) -> 479265.58 | D54: =C54/(1+Inputs!B9)^B54 -> 267619.4
A55: C | B55: 11 | C55: =Projects!M4*(1+Inputs!B8)^(B55-1) -> 488850.89 | D55: =C55/(1+Inputs!B9)^B55 -> 257520.55
A56: C | B56: 12 | C56: =Projects!M4*(1+Inputs!B8)^(B56-1) -> 498627.91 | D56: =C56/(1+Inputs!B9)^B56 -> 247802.8
A57: C | B57: 13 | C57: =Projects!M4*(1+Inputs!B8)^(B57-1) -> 508600.47 | D57: =C57/(1+Inputs!B9)^B57 -> 238451.75
A58: C | B58: 14 | C58: =Projects!M4*(1+Inputs!B8)^(B58-1) -> 518772.48 | D58: =C58/(1+Inputs!B9)^B58 -> 229453.57
A59: C | B59: 15 | C59: =Projects!M4*(1+Inputs!B8)^(B59-1) -> 529147.93 | D59: =C59/(1+Inputs!B9)^B59 -> 220794.94
A60: C | B60: 16 | C60: =Projects!M4*(1+Inputs!B8)^(B60-1) -> 539730.89 | D60: =C60/(1+Inputs!B9)^B60 -> 212463.06
A61: C | B61: 17 | C61: =Projects!M4*(1+Inputs!B8)^(B61-1) -> 550525.51 | D61: =C61/(1+Inputs!B9)^B61 -> 204445.58
A62: C | B62: 18 | C62: =Projects!M4*(1+Inputs!B8)^(B62-1) -> 561536.02 | D62: =C62/(1+Inputs!B9)^B62 -> 196730.66
A63: C | B63: 19 | C63: =Projects!M4*(1+Inputs!B8)^(B63-1) -> 572766.74 | D63: =C63/(1+Inputs!B9)^B63 -> 189306.86
A64: C | B64: 20 | C64: =Projects!M4*(1+Inputs!B8)^(B64-1)+Projects!M4*(1+Inputs!B8)^20/Inputs!B10*(1-Inputs!B11) -> 11202193 | D64: =C64/(1+Inputs!B9)^B64 -> 3492896.6
A65: D | B65: 0 | C65: =-Projects!N5 -> -3400000 | D65: =C65/(1+Inputs!B9)^B65 -> -3400000
A66: D | B66: 1 | C66: =Projects!M5*(1+Inputs!B8)^(B66-1) -> 309902.6 | D66: =C66/(1+Inputs!B9)^B66 -> 292360.94
A67: D | B67: 2 | C67: =Projects!M5*(1+Inputs!B8)^(B67-1) -> 316100.65 | D67: =C67/(1+Inputs!B9)^B67 -> 281328.45
A68: D | B68: 3 | C68: =Projects!M5*(1+Inputs!B8)^(B68-1) -> 322422.67 | D68: =C68/(1+Inputs!B9)^B68 -> 270712.29
A69: D | B69: 4 | C69: =Projects!M5*(1+Inputs!B8)^(B69-1) -> 328871.12 | D69: =C69/(1+Inputs!B9)^B69 -> 260496.73
A70: D | B70: 5 | C70: =Projects!M5*(1+Inputs!B8)^(B70-1) -> 335448.54 | D70: =C70/(1+Inputs!B9)^B70 -> 250666.66
A71: D | B71: 6 | C71: =Projects!M5*(1+Inputs!B8)^(B71-1) -> 342157.51 | D71: =C71/(1+Inputs!B9)^B71 -> 241207.54
A72: D | B72: 7 | C72: =Projects!M5*(1+Inputs!B8)^(B72-1) -> 349000.66 | D72: =C72/(1+Inputs!B9)^B72 -> 232105.37
A73: D | B73: 8 | C73: =Projects!M5*(1+Inputs!B8)^(B73-1) -> 355980.67 | D73: =C73/(1+Inputs!B9)^B73 -> 223346.68
A74: D | B74: 9 | C74: =Projects!M5*(1+Inputs!B8)^(B74-1) -> 363100.29 | D74: =C74/(1+Inputs!B9)^B74 -> 214918.5
A75: D | B75: 10 | C75: =Projects!M5*(1+Inputs!B8)^(B75-1) -> 370362.29 | D75: =C75/(1+Inputs!B9)^B75 -> 206808.37
A76: D | B76: 11 | C76: =Projects!M5*(1+Inputs!B8)^(B76-1) -> 377769.54 | D76: =C76/(1+Inputs!B9)^B76 -> 199004.28
A77: D | B77: 12 | C77: =Projects!M5*(1+Inputs!B8)^(B77-1) -> 385324.93 | D77: =C77/(1+Inputs!B9)^B77 -> 191494.69
A78: D | B78: 13 | C78: =Projects!M5*(1+Inputs!B8)^(B78-1) -> 393031.43 | D78: =C78/(1+Inputs!B9)^B78 -> 184268.47
A79: D | B79: 14 | C79: =Projects!M5*(1+Inputs!B8)^(B79-1) -> 400892.06 | D79: =C79/(1+Inputs!B9)^B79 -> 177314.94
A80: D | B80: 15 | C80: =Projects!M5*(1+Inputs!B8)^(B80-1) -> 408909.9 | D80: =C80/(1+Inputs!B9)^B80 -> 170623.81
A81: D | B81: 16 | C81: =Projects!M5*(1+Inputs!B8)^(B81-1) -> 417088.1 | D81: =C81/(1+Inputs!B9)^B81 -> 164185.18
A82: D | B82: 17 | C82: =Projects!M5*(1+Inputs!B8)^(B82-1) -> 425429.86 | D82: =C82/(1+Inputs!B9)^B82 -> 157989.51
A83: D | B83: 18 | C83: =Projects!M5*(1+Inputs!B8)^(B83-1) -> 433938.46 | D83: =C83/(1+Inputs!B9)^B83 -> 152027.64
A84: D | B84: 19 | C84: =Projects!M5*(1+Inputs!B8)^(B84-1) -> 442617.23 | D84: =C84/(1+Inputs!B9)^B84 -> 146290.75
A85: D | B85: 20 | C85: =Projects!M5*(1+Inputs!B8)^(B85-1)+Projects!M5*(1+Inputs!B8)^20/Inputs!B10*(1-Inputs!B11) -> 8656723.8 | D85: =C85/(1+Inputs!B9)^B85 -> 2699207.4
A86: E | B86: 0 | C86: =-Projects!N6 -> -3800000 | D86: =C86/(1+Inputs!B9)^B86 -> -3800000
A87: E | B87: 1 | C87: =Projects!M6*(1+Inputs!B8)^(B87-1) -> 313852.5 | D87: =C87/(1+Inputs!B9)^B87 -> 296087.26
A88: E | B88: 2 | C88: =Projects!M6*(1+Inputs!B8)^(B88-1) -> 320129.55 | D88: =C88/(1+Inputs!B9)^B88 -> 284914.16
A89: E | B89: 3 | C89: =Projects!M6*(1+Inputs!B8)^(B89-1) -> 326532.14 | D89: =C89/(1+Inputs!B9)^B89 -> 274162.68
A90: E | B90: 4 | C90: =Projects!M6*(1+Inputs!B8)^(B90-1) -> 333062.78 | D90: =C90/(1+Inputs!B9)^B90 -> 263816.92
A91: E | B91: 5 | C91: =Projects!M6*(1+Inputs!B8)^(B91-1) -> 339724.04 | D91: =C91/(1+Inputs!B9)^B91 -> 253861.57
A92: E | B92: 6 | C92: =Projects!M6*(1+Inputs!B8)^(B92-1) -> 346518.52 | D92: =C92/(1+Inputs!B9)^B92 -> 244281.88
A93: E | B93: 7 | C93: =Projects!M6*(1+Inputs!B8)^(B93-1) -> 353448.89 | D93: =C93/(1+Inputs!B9)^B93 -> 235063.7
A94: E | B94: 8 | C94: =Projects!M6*(1+Inputs!B8)^(B94-1) -> 360517.87 | D94: =C94/(1+Inputs!B9)^B94 -> 226193.37
A95: E | B95: 9 | C95: =Projects!M6*(1+Inputs!B8)^(B95-1) -> 367728.23 | D95: =C95/(1+Inputs!B9)^B95 -> 217657.77
A96: E | B96: 10 | C96: =Projects!M6*(1+Inputs!B8)^(B96-1) -> 375082.79 | D96: =C96/(1+Inputs!B9)^B96 -> 209444.27
A97: E | B97: 11 | C97: =Projects!M6*(1+Inputs!B8)^(B97-1) -> 382584.45 | D97: =C97/(1+Inputs!B9)^B97 -> 201540.71
A98: E | B98: 12 | C98: =Projects!M6*(1+Inputs!B8)^(B98-1) -> 390236.14 | D98: =C98/(1+Inputs!B9)^B98 -> 193935.4
A99: E | B99: 13 | C99: =Projects!M6*(1+Inputs!B8)^(B99-1) -> 398040.86 | D99: =C99/(1+Inputs!B9)^B99 -> 186617.09
A100: E | B100: 14 | C100: =Projects!M6*(1+Inputs!B8)^(B100-1) -> 406001.67 | D100: =C100/(1+Inputs!B9)^B100 -> 179574.93
...

Sheet Portfolios
A1: Combination | B1: A | C1: B | D1: C | E1: D | F1: E | G1: F | H1: G | I1: H | J1: Cost | K1: Beds | L1: Affordable beds | M1: NPV | N1: Selected planning failures | O1: Feasible | P1: Affordable objective | Q1: NPV tie break
A2: 0 | B2: 0 | C2: 0 | D2: 0 | E2: 0 | F2: 0 | G2: 0 | H2: 0 | I2: 0 | J2: =B2*Projects!N2+C2*Projects!N3+D2*Projects!N4+E2*Projects!N5+F2*Projects!N6+G2*Projects!N7+H2*Projects!N8+I2*Projects!N9 -> 0 | K2: =B2*Projects!C2+C2*Projects!C3+D2*Projects!C4+E2*Projects!C5+F2*Projects!C6+G2*Projects!C7+H2*Projects!C8+I2*Projects!C9 -> 0 | L2: =B2*Projects!D2+C2*Projects!D3+D2*Projects!D4+E2*Projects!D5+F2*Projects!D6+G2*Projects!D7+H2*Projects!D8+I2*Projects!D9 -> 0 | M2: =B2*Projects!O2+C2*Projects!O3+D2*Projects!O4+E2*Projects!O5+F2*Projects!O6+G2*Projects!O7+H2*Projects!O8+I2*Projects!O9 -> 0 | N2: =B2*(1-Projects!Q2)+C2*(1-Projects!Q3)+D2*(1-Projects!Q4)+E2*(1-Projects!Q5)+F2*(1-Projects!Q6)+G2*(1-Projects!Q7)+H2*(1-Projects!Q8)+I2*(1-Projects!Q9) -> 0 | O2: =IF(AND(J2<=Inputs!B2,L2>=Inputs!B3,M2>=Inputs!B18,N2=0),1,0) -> 0 | P2: =IF(O2=1,L2,-1) -> -1 | Q2: =IF(AND(O2=1,L2=MAX(P$2:P$257)),M2,-1E+99) -> -1e+99
A3: 1 | B3: 0 | C3: 0 | D3: 0 | E3: 0 | F3: 0 | G3: 0 | H3: 0 | I3: 1 | J3: =B3*Projects!N2+C3*Projects!N3+D3*Projects!N4+E3*Projects!N5+F3*Projects!N6+G3*Projects!N7+H3*Projects!N8+I3*Projects!N9 -> 4500000 | K3: =B3*Projects!C2+C3*Projects!C3+D3*Projects!C4+E3*Projects!C5+F3*Projects!C6+G3*Projects!C7+H3*Projects!C8+I3*Projects!C9 -> 90 | L3: =B3*Projects!D2+C3*Projects!D3+D3*Projects!D4+E3*Projects!D5+F3*Projects!D6+G3*Projects!D7+H3*Projects!D8+I3*Projects!D9 -> 27 | M3: =B3*Projects!O2+C3*Projects!O3+D3*Projects!O4+E3*Projects!O5+F3*Projects!O6+G3*Projects!O7+H3*Projects!O8+I3*Projects!O9 -> 4456627.4 | N3: =B3*(1-Projects!Q2)+C3*(1-Projects!Q3)+D3*(1-Projects!Q4)+E3*(1-Projects!Q5)+F3*(1-Projects!Q6)+G3*(1-Projects!Q7)+H3*(1-Projects!Q8)+I3*(1-Projects!Q9) -> 0 | O3: =IF(AND(J3<=Inputs!B2,L3>=Inputs!B3,M3>=Inputs!B18,N3=0),1,0) -> 0 | P3: =IF(O3=1,L3,-1) -> -1 | Q3: =IF(AND(O3=1,L3=MAX(P$2:P$257)),M3,-1E+99) -> -1e+99
A4: 2 | B4: 0 | C4: 0 | D4: 0 | E4: 0 | F4: 0 | G4: 0 | H4: 1 | I4: 0 | J4: =B4*Projects!N2+C4*Projects!N3+D4*Projects!N4+E4*Projects!N5+F4*Projects!N6+G4*Projects!N7+H4*Projects!N8+I4*Projects!N9 -> 4100000 | K4: =B4*Projects!C2+C4*Projects!C3+D4*Projects!C4+E4*Projects!C5+F4*Projects!C6+G4*Projects!C7+H4*Projects!C8+I4*Projects!C9 -> 110 | L4: =B4*Projects!D2+C4*Projects!D3+D4*Projects!D4+E4*Projects!D5+F4*Projects!D6+G4*Projects!D7+H4*Projects!D8+I4*Projects!D9 -> 66 | M4: =B4*Projects!O2+C4*Projects!O3+D4*Projects!O4+E4*Projects!O5+F4*Projects!O6+G4*Projects!O7+H4*Projects!O8+I4*Projects!O9 -> 3035374 | N4: =B4*(1-Projects!Q2)+C4*(1-Projects!Q3)+D4*(1-Projects!Q4)+E4*(1-Projects!Q5)+F4*(1-Projects!Q6)+G4*(1-Projects!Q7)+H4*(1-Projects!Q8)+I4*(1-Projects!Q9) -> 0 | O4: =IF(AND(J4<=Inputs!B2,L4>=Inputs!B3,M4>=Inputs!B18,N4=0),1,0) -> 0 | P4: =IF(O4=1,L4,-1) -> -1 | Q4: =IF(AND(O4=1,L4=MAX(P$2:P$257)),M4,-1E+99) -> -1e+99
A5: 3 | B5: 0 | C5: 0 | D5: 0 | E5: 0 | F5: 0 | G5: 0 | H5: 1 | I5: 1 | J5: =B5*Projects!N2+C5*Projects!N3+D5*Projects!N4+E5*Projects!N5+F5*Projects!N6+G5*Projects!N7+H5*Projects!N8+I5*Projects!N9 -> 8600000 | K5: =B5*Projects!C2+C5*Projects!C3+D5*Projects!C4+E5*Projects!C5+F5*Projects!C6+G5*Projects!C7+H5*Projects!C8+I5*Projects!C9 -> 200 | L5: =B5*Projects!D2+C5*Projects!D3+D5*Projects!D4+E5*Projects!D5+F5*Projects!D6+G5*Projects!D7+H5*Projects!D8+I5*Projects!D9 -> 93 | M5: =B5*Projects!O2+C5*Projects!O3+D5*Projects!O4+E5*Projects!O5+F5*Projects!O6+G5*Projects!O7+H5*Projects!O8+I5*Projects!O9 -> 7492001.4 | N5: =B5*(1-Projects!Q2)+C5*(1-Projects!Q3)+D5*(1-Projects!Q4)+E5*(1-Projects!Q5)+F5*(1-Projects!Q6)+G5*(1-Projects!Q7)+H5*(1-Projects!Q8)+I5*(1-Projects!Q9) -> 0 | O5: =IF(AND(J5<=Inputs!B2,L5>=Inputs!B3,M5>=Inputs!B18,N5=0),1,0) -> 1 | P5: =IF(O5=1,L5,-1) -> 93 | Q5: =IF(AND(O5=1,L5=MAX(P$2:P$257)),M5,-1E+99) -> -1e+99
A6: 4 | B6: 0 | C6: 0 | D6: 0 | E6: 0 | F6: 0 | G6: 1 | H6: 0 | I6: 0 | J6: =B6*Projects!N2+C6*Projects!N3+D6*Projects!N4+E6*Projects!N5+F6*Projects!N6+G6*Projects!N7+H6*Projects!N8+I6*Projects!N9 -> 3200000 | K6: =B6*Projects!C2+C6*Projects!C3+D6*Projects!C4+E6*Projects!C5+F6*Projects!C6+G6*Projects!C7+H6*Projects!C8+I6*Projects!C9 -> 80 | L6: =B6*Projects!D2+C6*Projects!D3+D6*Projects!D4+E6*Projects!D5+F6*Projects!D6+G6*Projects!D7+H6*Projects!D8+I6*Projects!D9 -> 40 | M6: =B6*Projects!O2+C6*Projects!O3+D6*Projects!O4+E6*Projects!O5+F6*Projects!O6+G6*Projects!O7+H6*Projects!O8+I6*Projects!O9 -> 2510178.6 | N6: =B6*(1-Projects!Q2)+C6*(1-Projects!Q3)+D6*(1-Projects!Q4)+E6*(1-Projects!Q5)+F6*(1-Projects!Q6)+G6*(1-Projects!Q7)+H6*(1-Projects!Q8)+I6*(1-Projects!Q9) -> 0 | O6: =IF(AND(J6<=Inputs!B2,L6>=Inputs!B3,M6>=Inputs!B18,N6=0),1,0) -> 0 | P6: =IF(O6=1,L6,-1) -> -1 | Q6: =IF(AND(O6=1,L6=MAX(P$2:P$257)),M6,-1E+99) -> -1e+99
A7: 5 | B7: 0 | C7: 0 | D7: 0 | E7: 0 | F7: 0 | G7: 1 | H7: 0 | I7: 1 | J7: =B7*Projects!N2+C7*Projects!N3+D7*Projects!N4+E7*Projects!N5+F7*Projects!N6+G7*Projects!N7+H7*Projects!N8+I7*Projects!N9 -> 7700000 | K7: =B7*Projects!C2+C7*Projects!C3+D7*Projects!C4+E7*Projects!C5+F7*Projects!C6+G7*Projects!C7+H7*Projects!C8+I7*Projects!C9 -> 170 | L7: =B7*Projects!D2+C7*Projects!D3+D7*Projects!D4+E7*Projects!D5+F7*Projects!D6+G7*Projects!D7+H7*Projects!D8+I7*Projects!D9 -> 67 | M7: =B7*Projects!O2+C7*Projects!O3+D7*Projects!O4+E7*Projects!O5+F7*Projects!O6+G7*Projects!O7+H7*Projects!O8+I7*Projects!O9 -> 6966806 | N7: =B7*(1-Projects!Q2)+C7*(1-Projects!Q3)+D7*(1-Projects!Q4)+E7*(1-Projects!Q5)+F7*(1-Projects!Q6)+G7*(1-Projects!Q7)+H7*(1-Projects!Q8)+I7*(1-Projects!Q9) -> 0 | O7: =IF(AND(J7<=Inputs!B2,L7>=Inputs!B3,M7>=Inputs!B18,N7=0),1,0) -> 0 | P7: =IF(O7=1,L7,-1) -> -1 | Q7: =IF(AND(O7=1,L7=MAX(P$2:P$257)),M7,-1E+99) -> -1e+99
A8: 6 | B8: 0 | C8: 0 | D8: 0 | E8: 0 | F8: 0 | G8: 1 | H8: 1 | I8: 0 | J8: =B8*Projects!N2+C8*Projects!N3+D8*Projects!N4+E8*Projects!N5+F8*Projects!N6+G8*Projects!N7+H8*Projects!N8+I8*Projects!N9 -> 7300000 | K8: =B8*Projects!C2+C8*Projects!C3+D8*Projects!C4+E8*Projects!C5+F8*Projects!C6+G8*Projects!C7+H8*Projects!C8+I8*Projects!C9 -> 190 | L8: =B8*Projects!D2+C8*Projects!D3+D8*Projects!D4+E8*Projects!D5+F8*Projects!D6+G8*Projects!D7+H8*Projects!D8+I8*Projects!D9 -> 106 | M8: =B8*Projects!O2+C8*Projects!O3+D8*Projects!O4+E8*Projects!O5+F8*Projects!O6+G8*Projects!O7+H8*Projects!O8+I8*Projects!O9 -> 5545552.6 | N8: =B8*(1-Projects!Q2)+C8*(1-Projects!Q3)+D8*(1-Projects!Q4)+E8*(1-Projects!Q5)+F8*(1-Projects!Q6)+G8*(1-Projects!Q7)+H8*(1-Projects!Q8)+I8*(1-Projects!Q9) -> 0 | O8: =IF(AND(J8<=Inputs!B2,L8>=Inputs!B3,M8>=Inputs!B18,N8=0),1,0) -> 1 | P8: =IF(O8=1,L8,-1) -> 106 | Q8: =IF(AND(O8=1,L8=MAX(P$2:P$257)),M8,-1E+99) -> -1e+99
A9: 7 | B9: 0 | C9: 0 | D9: 0 | E9: 0 | F9: 0 | G9: 1 | H9: 1 | I9: 1 | J9: =B9*Projects!N2+C9*Projects!N3+D9*Projects!N4+E9*Projects!N5+F9*Projects!N6+G9*Projects!N7+H9*Projects!N8+I9*Projects!N9 -> 11800000 | K9: =B9*Projects!C2+C9*Projects!C3+D9*Projects!C4+E9*Projects!C5+F9*Projects!C6+G9*Projects!C7+H9*Projects!C8+I9*Projects!C9 -> 280 | L9: =B9*Projects!D2+C9*Projects!D3+D9*Projects!D4+E9*Projects!D5+F9*Projects!D6+G9*Projects!D7+H9*Projects!D8+I9*Projects!D9 -> 133 | M9: =B9*Projects!O2+C9*Projects!O3+D9*Projects!O4+E9*Projects!O5+F9*Projects!O6+G9*Projects!O7+H9*Projects!O8+I9*Projects!O9 -> 10002180 | N9: =B9*(1-Projects!Q2)+C9*(1-Projects!Q3)+D9*(1-Projects!Q4)+E9*(1-Projects!Q5)+F9*(1-Projects!Q6)+G9*(1-Projects!Q7)+H9*(1-Projects!Q8)+I9*(1-Projects!Q9) -> 0 | O9: =IF(AND(J9<=Inputs!B2,L9>=Inputs!B3,M9>=Inputs!B18,N9=0),1,0) -> 1 | P9: =IF(O9=1,L9,-1) -> 133 | Q9: =IF(AND(O9=1,L9=MAX(P$2:P$257)),M9,-1E+99) -> -1e+99
A10: 8 | B10: 0 | C10: 0 | D10: 0 | E10: 0 | F10: 1 | G10: 0 | H10: 0 | I10: 0 | J10: =B10*Projects!N2+C10*Projects!N3+D10*Projects!N4+E10*Projects!N5+F10*Projects!N6+G10*Projects!N7+H10*Projects!N8+I10*Projects!N9 -> 3800000 | K10: =B10*Projects!C2+C10*Projects!C3+D10*Projects!C4+E10*Projects!C5+F10*Projects!C6+G10*Projects!C7+H10*Projects!C8+I10*Projects!C9 -> 90 | L10: =B10*Projects!D2+C10*Projects!D3+D10*Projects!D4+E10*Projects!D5+F10*Projects!D6+G10*Projects!D7+H10*Projects!D8+I10*Projects!D9 -> 45 | M10: =B10*Projects!O2+C10*Projects!O3+D10*Projects!O4+E10*Projects!O5+F10*Projects!O6+G10*Projects!O7+H10*Projects!O8+I10*Projects!O9 -> 3001962.4 | N10: =B10*(1-Projects!Q2)+C10*(1-Projects!Q3)+D10*(1-Projects!Q4)+E10*(1-Projects!Q5)+F10*(1-Projects!Q6)+G10*(1-Projects!Q7)+H10*(1-Projects!Q8)+I10*(1-Projects!Q9) -> 0 | O10: =IF(AND(J10<=Inputs!B2,L10>=Inputs!B3,M10>=Inputs!B18,N10=0),1,0) -> 0 | P10: =IF(O10=1,L10,-1) -> -1 | Q10: =IF(AND(O10=1,L10=MAX(P$2:P$257)),M10,-1E+99) -> -1e+99
A11: 9 | B11: 0 | C11: 0 | D11: 0 | E11: 0 | F11: 1 | G11: 0 | H11: 0 | I11: 1 | J11: =B11*Projects!N2+C11*Projects!N3+D11*Projects!N4+E11*Projects!N5+F11*Projects!N6+G11*Projects!N7+H11*Projects!N8+I11*Projects!N9 -> 8300000 | K11: =B11*Projects!C2+C11*Projects!C3+D11*Projects!C4+E11*Projects!C5+F11*Projects!C6+G11*Projects!C7+H11*Projects!C8+I11*Projects!C9 -> 180 | L11: =B11*Projects!D2+C11*Projects!D3+D11*Projects!D4+E11*Projects!D5+F11*Projects!D6+G11*Projects!D7+H11*Projects!D8+I11*Projects!D9 -> 72 | M11: =B11*Projects!O2+C11*Projects!O3+D11*Projects!O4+E11*Projects!O5+F11*Projects!O6+G11*Projects!O7+H11*Projects!O8+I11*Projects!O9 -> 7458589.8 | N11: =B11*(1-Projects!Q2)+C11*(1-Projects!Q3)+D11*(1-Projects!Q4)+E11*(1-Projects!Q5)+F11*(1-Projects!Q6)+G11*(1-Projects!Q7)+H11*(1-Projects!Q8)+I11*(1-Projects!Q9) -> 0 | O11: =IF(AND(J11<=Inputs!B2,L11>=Inputs!B3,M11>=Inputs!B18,N11=0),1,0) -> 0 | P11: =IF(O11=1,L11,-1) -> -1 | Q11: =IF(AND(O11=1,L11=MAX(P$2:P$257)),M11,-1E+99) -> -1e+99
A12: 10 | B12: 0 | C12: 0 | D12: 0 | E12: 0 | F12: 1 | G12: 0 | H12: 1 | I12: 0 | J12: =B12*Projects!N2+C12*Projects!N3+D12*Projects!N4+E12*Projects!N5+F12*Projects!N6+G12*Projects!N7+H12*Projects!N8+I12*Projects!N9 -> 7900000 | K12: =B12*Projects!C2+C12*Projects!C3+D12*Projects!C4+E12*Projects!C5+F12*Projects!C6+G12*Projects!C7+H12*Projects!C8+I12*Projects!C9 -> 200 | L12: =B12*Projects!D2+C12*Projects!D3+D12*Projects!D4+E12*Projects!D5+F12*Projects!D6+G12*Projects!D7+H12*Projects!D8+I12*Projects!D9 -> 111 | M12: =B12*Projects!O2+C12*Projects!O3+D12*Projects!O4+E12*Projects!O5+F12*Projects!O6+G12*Projects!O7+H12*Projects!O8+I12*Projects!O9 -> 6037336.3 | N12: =B12*(1-Projects!Q2)+C12*(1-Projects!Q3)+D12*(1-Projects!Q4)+E12*(1-Projects!Q5)+F12*(1-Projects!Q6)+G12*(1-Projects!Q7)+H12*(1-Projects!Q8)+I12*(1-Projects!Q9) -> 0 | O12: =IF(AND(J12<=Inputs!B2,L12>=Inputs!B3,M12>=Inputs!B18,N12=0),1,0) -> 1 | P12: =IF(O12=1,L12,-1) -> 111 | Q12: =IF(AND(O12=1,L12=MAX(P$2:P$257)),M12,-1E+99) -> -1e+99
A13: 11 | B13: 0 | C13: 0 | D13: 0 | E13: 0 | F13: 1 | G13: 0 | H13: 1 | I13: 1 | J13: =B13*Projects!N2+C13*Projects!N3+D13*Projects!N4+E13*Projects!N5+F13*Projects!N6+G13*Projects!N7+H13*Projects!N8+I13*Projects!N9 -> 12400000 | K13: =B13*Projects!C2+C13*Projects!C3+D13*Projects!C4+E13*Projects!C5+F13*Projects!C6+G13*Projects!C7+H13*Projects!C8+I13*Projects!C9 -> 290 | L13: =B13*Projects!D2+C13*Projects!D3+D13*Projects!D4+E13*Projects!D5+F13*Projects!D6+G13*Projects!D7+H13*Projects!D8+I13*Projects!D9 -> 138 | M13: =B13*Projects!O2+C13*Projects!O3+D13*Projects!O4+E13*Projects!O5+F13*Projects!O6+G13*Projects!O7+H13*Projects!O8+I13*Projects!O9 -> 10493964 | N13: =B13*(1-Projects!Q2)+C13*(1-Projects!Q3)+D13*(1-Projects!Q4)+E13*(1-Projects!Q5)+F13*(1-Projects!Q6)+G13*(1-Projects!Q7)+H13*(1-Projects!Q8)+I13*(1-Projects!Q9) -> 0 | O13: =IF(AND(J13<=Inputs!B2,L13>=Inputs!B3,M13>=Inputs!B18,N13=0),1,0) -> 1 | P13: =IF(O13=1,L13,-1) -> 138 | Q13: =IF(AND(O13=1,L13=MAX(P$2:P$257)),M13,-1E+99) -> -1e+99
A14: 12 | B14: 0 | C14: 0 | D14: 0 | E14: 0 | F14: 1 | G14: 1 | H14: 0 | I14: 0 | J14: =B14*Projects!N2+C14*Projects!N3+D14*Projects!N4+E14*Projects!N5+F14*Projects!N6+G14*Projects!N7+H14*Projects!N8+I14*Projects!N9 -> 7000000 | K14: =B14*Projects!C2+C14*Projects!C3+D14*Projects!C4+E14*Projects!C5+F14*Projects!C6+G14*Projects!C7+H14*Projects!C8+I14*Projects!C9 -> 170 | L14: =B14*Projects!D2+C14*Projects!D3+D14*Projects!D4+E14*Projects!D5+F14*Projects!D6+G14*Projects!D7+H14*Projects!D8+I14*Projects!D9 -> 85 | M14: =B14*Projects!O2+C14*Projects!O3+D14*Projects!O4+E14*Projects!O5+F14*Projects!O6+G14*Projects!O7+H14*Projects!O8+I14*Projects!O9 -> 5512141 | N14: =B14*(1-Projects!Q2)+C14*(1-Projects!Q3)+D14*(1-Projects!Q4)+E14*(1-Projects!Q5)+F14*(1-Projects!Q6)+G14*(1-Projects!Q7)+H14*(1-Projects!Q8)+I14*(1-Projects!Q9) -> 0 | O14: =IF(AND(J14<=Inputs!B2,L14>=Inputs!B3,M14>=Inputs!B18,N14=0),1,0) -> 1 | P14: =IF(O14=1,L14,-1) -> 85 | Q14: =IF(AND(O14=1,L14=MAX(P$2:P$257)),M14,-1E+99) -> -1e+99
A15: 13 | B15: 0 | C15: 0 | D15: 0 | E15: 0 | F15: 1 | G15: 1 | H15: 0 | I15: 1 | J15: =B15*Projects!N2+C15*Projects!N3+D15*Projects!N4+E15*Projects!N5+F15*Projects!N6+G15*Projects!N7+H15*Projects!N8+I15*Projects!N9 -> 11500000 | K15: =B15*Projects!C2+C15*Projects!C3+D15*Projects!C4+E15*Projects!C5+F15*Projects!C6+G15*Projects!C7+H15*Projects!C8+I15*Projects!C9 -> 260 | L15: =B15*Projects!D2+C15*Projects!D3+D15*Projects!D4+E15*Projects!D5+F15*Projects!D6+G15*Projects!D7+H15*Projects!D8+I15*Projects!D9 -> 112 | M15: =B15*Projects!O2+C15*Projects!O3+D15*Projects!O4+E15*Projects!O5+F15*Projects!O6+G15*Projects!O7+H15*Projects!O8+I15*Projects!O9 -> 9968768.4 | N15: =B15*(1-Projects!Q2)+C15*(1-Projects!Q3)+D15*(1-Projects!Q4)+E15*(1-Projects!Q5)+F15*(1-Projects!Q6)+G15*(1-Projects!Q7)+H15*(1-Projects!Q8)+I15*(1-Projects!Q9) -> 0 | O15: =IF(AND(J15<=Inputs!B2,L15>=Inputs!B3,M15>=Inputs!B18,N15=0),1,0) -> 1 | P15: =IF(O15=1,L15,-1) -> 112 | Q15: =IF(AND(O15=1,L15=MAX(P$2:P$257)),M15,-1E+99) -> -1e+99
A16: 14 | B16: 0 | C16: 0 | D16: 0 | E16: 0 | F16: 1 | G16: 1 | H16: 1 | I16: 0 | J16: =B16*Projects!N2+C16*Projects!N3+D16*Projects!N4+E16*Projects!N5+F16*Projects!N6+G16*Projects!N7+H16*Projects!N8+I16*Projects!N9 -> 11100000 | K16: =B16*Projects!C2+C16*Projects!C3+D16*Projects!C4+E16*Projects!C5+F16*Projects!C6+G16*Projects!C7+H16*Projects!C8+I16*Projects!C9 -> 280 | L16: =B16*Projects!D2+C16*Projects!D3+D16*Projects!D4+E16*Projects!D5+F16*Projects!D6+G16*Projects!D7+H16*Projects!D8+I16*Projects!D9 -> 151 | M16: =B16*Projects!O2+C16*Projects!O3+D16*Projects!O4+E16*Projects!O5+F16*Projects!O6+G16*Projects!O7+H16*Projects!O8+I16*Projects!O9 -> 8547515 | N16: =B16*(1-Projects!Q2)+C16*(1-Projects!Q3)+D16*(1-Projects!Q4)+E16*(1-Projects!Q5)+F16*(1-Projects!Q6)+G16*(1-Projects!Q7)+H16*(1-Projects!Q8)+I16*(1-Projects!Q9) -> 0 | O16: =IF(AND(J16<=Inputs!B2,L16>=Inputs!B3,M16>=Inputs!B18,N16=0),1,0) -> 1 | P16: =IF(O16=1,L16,-1) -> 151 | Q16: =IF(AND(O16=1,L16=MAX(P$2:P$257)),M16,-1E+99) -> -1e+99
A17: 15 | B17: 0 | C17: 0 | D17: 0 | E17: 0 | F17: 1 | G17: 1 | H17: 1 | I17: 1 | J17: =B17*Projects!N2+C17*Projects!N3+D17*Projects!N4+E17*Projects!N5+F17*Projects!N6+G17*Projects!N7+H17*Projects!N8+I17*Projects!N9 -> 15600000 | K17: =B17*Projects!C2+C17*Projects!C3+D17*Projects!C4+E17*Projects!C5+F17*Projects!C6+G17*Projects!C7+H17*Projects!C8+I17*Projects!C9 -> 370 | L17: =B17*Projects!D2+C17*Projects!D3+D17*Projects!D4+E17*Projects!D5+F17*Projects!D6+G17*Projects!D7+H17*Projects!D8+I17*Projects!D9 -> 178 | M17: =B17*Projects!O2+C17*Projects!O3+D17*Projects!O4+E17*Projects!O5+F17*Projects!O6+G17*Projects!O7+H17*Projects!O8+I17*Projects!O9 -> 13004142 | N17: =B17*(1-Projects!Q2)+C17*(1-Projects!Q3)+D17*(1-Projects!Q4)+E17*(1-Projects!Q5)+F17*(1-Projects!Q6)+G17*(1-Projects!Q7)+H17*(1-Projects!Q8)+I17*(1-Projects!Q9) -> 0 | O17: =IF(AND(J17<=Inputs!B2,L17>=Inputs!B3,M17>=Inputs!B18,N17=0),1,0) -> 0 | P17: =IF(O17=1,L17,-1) -> -1 | Q17: =IF(AND(O17=1,L17=MAX(P$2:P$257)),M17,-1E+99) -> -1e+99
A18: 16 | B18: 0 | C18: 0 | D18: 0 | E18: 1 | F18: 0 | G18: 0 | H18: 0 | I18: 0 | J18: =B18*Projects!N2+C18*Projects!N3+D18*Projects!N4+E18*Projects!N5+F18*Projects!N6+G18*Projects!N7+H18*Projects!N8+I18*Projects!N9 -> 3400000 | K18: =B18*Projects!C2+C18*Projects!C3+D18*Projects!C4+E18*Projects!C5+F18*Projects!C6+G18*Projects!C7+H18*Projects!C8+I18*Projects!C9 -> 70 | L18: =B18*Projects!D2+C18*Projects!D3+D18*Projects!D4+E18*Projects!D5+F18*Projects!D6+G18*Projects!D7+H18*Projects!D8+I18*Projects!D9 -> 21 | M18: =B18*Projects!O2+C18*Projects!O3+D18*Projects!O4+E18*Projects!O5+F18*Projects!O6+G18*Projects!O7+H18*Projects!O8+I18*Projects!O9 -> 3316358.2 | N18: =B18*(1-Projects!Q2)+C18*(1-Projects!Q3)+D18*(1-Projects!Q4)+E18*(1-Projects!Q5)+F18*(1-Projects!Q6)+G18*(1-Projects!Q7)+H18*(1-Projects!Q8)+I18*(1-Projects!Q9) -> 0 | O18: =IF(AND(J18<=Inputs!B2,L18>=Inputs!B3,M18>=Inputs!B18,N18=0),1,0) -> 0 | P18: =IF(O18=1,L18,-1) -> -1 | Q18: =IF(AND(O18=1,L18=MAX(P$2:P$257)),M18,-1E+99) -> -1e+99
A19: 17 | B19: 0 | C19: 0 | D19: 0 | E19: 1 | F19: 0 | G19: 0 | H19: 0 | I19: 1 | J19: =B19*Projects!N2+C19*Projects!N3+D19*Projects!N4+E19*Projects!N5+F19*Projects!N6+G19*Projects!N7+H19*Projects!N8+I19*Projects!N9 -> 7900000 | K19: =B19*Projects!C2+C19*Projects!C3+D19*Projects!C4+E19*Projects!C5+F19*Projects!C6+G19*Projects!C7+H19*Projects!C8+I19*Projects!C9 -> 160 | L19: =B19*Projects!D2+C19*Projects!D3+D19*Projects!D4+E19*Projects!D5+F19*Projects!D6+G19*Projects!D7+H19*Projects!D8+I19*Projects!D9 -> 48 | M19: =B19*Projects!O2+C19*Projects!O3+D19*Projects!O4+E19*Projects!O5+F19*Projects!O6+G19*Projects!O7+H19*Projects!O8+I19*Projects!O9 -> 7772985.7 | N19: =B19*(1-Projects!Q2)+C19*(1-Projects!Q3)+D19*(1-Projects!Q4)+E19*(1-Projects!Q5)+F19*(1-Projects!Q6)+G19*(1-Projects!Q7)+H19*(1-Projects!Q8)+I19*(1-Projects!Q9) -> 0 | O19: =IF(AND(J19<=Inputs!B2,L19>=Inputs!B3,M19>=Inputs!B18,N19=0),1,0) -> 0 | P19: =IF(O19=1,L19,-1) -> -1 | Q19: =IF(AND(O19=1,L19=MAX(P$2:P$257)),M19,-1E+99) -> -1e+99
A20: 18 | B20: 0 | C20: 0 | D20: 0 | E20: 1 | F20: 0 | G20: 0 | H20: 1 | I20: 0 | J20: =B20*Projects!N2+C20*Projects!N3+D20*Projects!N4+E20*Projects!N5+F20*Projects!N6+G20*Projects!N7+H20*Projects!N8+I20*Projects!N9 -> 7500000 | K20: =B20*Projects!C2+C20*Projects!C3+D20*Projects!C4+E20*Projects!C5+F20*Projects!C6+G20*Projects!C7+H20*Projects!C8+I20*Projects!C9 -> 180 | L20: =B20*Projects!D2+C20*Projects!D3+D20*Projects!D4+E20*Projects!D5+F20*Projects!D6+G20*Projects!D7+H20*Projects!D8+I20*Projects!D9 -> 87 | M20: =B20*Projects!O2+C20*Projects!O3+D20*Projects!O4+E20*Projects!O5+F20*Projects!O6+G20*Projects!O7+H20*Projects!O8+I20*Projects!O9 -> 6351732.2 | N20: =B20*(1-Projects!Q2)+C20*(1-Projects!Q3)+D20*(1-Projects!Q4)+E20*(1-Projects!Q5)+F20*(1-Projects!Q6)+G20*(1-Projects!Q7)+H20*(1-Projects!Q8)+I20*(1-Projects!Q9) -> 0 | O20: =IF(AND(J20<=Inputs!B2,L20>=Inputs!B3,M20>=Inputs!B18,N20=0),1,0) -> 1 | P20: =IF(O20=1,L20,-1) -> 87 | Q20: =IF(AND(O20=1,L20=MAX(P$2:P$257)),M20,-1E+99) -> -1e+99
A21: 19 | B21: 0 | C21: 0 | D21: 0 | E21: 1 | F21: 0 | G21: 0 | H21: 1 | I21: 1 | J21: =B21*Projects!N2+C21*Projects!N3+D21*Projects!N4+E21*Projects!N5+F21*Projects!N6+G21*Projects!N7+H21*Projects!N8+I21*Projects!N9 -> 12000000 | K21: =B21*Projects!C2+C21*Projects!C3+D21*Projects!C4+E21*Projects!C5+F21*Projects!C6+G21*Projects!C7+H21*Projects!C8+I21*Projects!C9 -> 270 | L21: =B21*Projects!D2+C21*Projects!D3+D21*Projects!D4+E21*Projects!D5+F21*Projects!D6+G21*Projects!D7+H21*Projects!D8+I21*Projects!D9 -> 114 | M21: =B21*Projects!O2+C21*Projects!O3+D21*Projects!O4+E21*Projects!O5+F21*Projects!O6+G21*Projects!O7+H21*Projects!O8+I21*Projects!O9 -> 10808360 | N21: =B21*(1-Projects!Q2)+C21*(1-Projects!Q3)+D21*(1-Projects!Q4)+E21*(1-Projects!Q5)+F21*(1-Projects!Q6)+G21*(1-Projects!Q7)+H21*(1-Projects!Q8)+I21*(1-Projects!Q9) -> 0 | O21: =IF(AND(J21<=Inputs!B2,L21>=Inputs!B3,M21>=Inputs!B18,N21=0),1,0) -> 1 | P21: =IF(O21=1,L21,-1) -> 114 | Q21: =IF(AND(O21=1,L21=MAX(P$2:P$257)),M21,-1E+99) -> -1e+99
A22: 20 | B22: 0 | C22: 0 | D22: 0 | E22: 1 | F22: 0 | G22: 1 | H22: 0 | I22: 0 | J22: =B22*Projects!N2+C22*Projects!N3+D22*Projects!N4+E22*Projects!N5+F22*Projects!N6+G22*Projects!N7+H22*Projects!N8+I22*Projects!N9 -> 6600000 | K22: =B22*Projects!C2+C22*Projects!C3+D22*Projects!C4+E22*Projects!C5+F22*Projects!C6+G22*Projects!C7+H22*Projects!C8+I22*Projects!C9 -> 150 | L22: =B22*Projects!D2+C22*Projects!D3+D22*Projects!D4+E22*Projects!D5+F22*Projects!D6+G22*Projects!D7+H22*Projects!D8+I22*Projects!D9 -> 61 | M22: =B22*Projects!O2+C22*Projects!O3+D22*Projects!O4+E22*Projects!O5+F22*Projects!O6+G22*Projects!O7+H22*Projects!O8+I22*Projects!O9 -> 5826536.8 | N22: =B22*(1-Projects!Q2)+C22*(1-Projects!Q3)+D22*(1-Projects!Q4)+E22*(1-Projects!Q5)+F22*(1-Projects!Q6)+G22*(1-Projects!Q7)+H22*(1-Projects!Q8)+I22*(1-Projects!Q9) -> 0 | O22: =IF(AND(J22<=Inputs!B2,L22>=Inputs!B3,M22>=Inputs!B18,N22=0),1,0) -> 0 | P22: =IF(O22=1,L22,-1) -> -1 | Q22: =IF(AND(O22=1,L22=MAX(P$2:P$257)),M22,-1E+99) -> -1e+99
A23: 21 | B23: 0 | C23: 0 | D23: 0 | E23: 1 | F23: 0 | G23: 1 | H23: 0 | I23: 1 | J23: =B23*Projects!N2+C23*Projects!N3+D23*Projects!N4+E23*Projects!N5+F23*Projects!N6+G23*Projects!N7+H23*Projects!N8+I23*Projects!N9 -> 11100000 | K23: =B23*Projects!C2+C23*Projects!C3+D23*Projects!C4+E23*Projects!C5+F23*Projects!C6+G23*Projects!C7+H23*Projects!C8+I23*Projects!C9 -> 240 | L23: =B23*Projects!D2+C23*Projects!D3+D23*Projects!D4+E23*Projects!D5+F23*Projects!D6+G23*Projects!D7+H23*Projects!D8+I23*Projects!D9 -> 88 | M23: =B23*Projects!O2+C23*Projects!O3+D23*Projects!O4+E23*Projects!O5+F23*Projects!O6+G23*Projects!O7+H23*Projects!O8+I23*Projects!O9 -> 10283164 | N23: =B23*(1-Projects!Q2)+C23*(1-Projects!Q3)+D23*(1-Projects!Q4)+E23*(1-Projects!Q5)+F23*(1-Projects!Q6)+G23*(1-Projects!Q7)+H23*(1-Projects!Q8)+I23*(1-Projects!Q9) -> 0 | O23: =IF(AND(J23<=Inputs!B2,L23>=Inputs!B3,M23>=Inputs!B18,N23=0),1,0) -> 1 | P23: =IF(O23=1,L23,-1) -> 88 | Q23: =IF(AND(O23=1,L23=MAX(P$2:P$257)),M23,-1E+99) -> -1e+99
A24: 22 | B24: 0 | C24: 0 | D24: 0 | E24: 1 | F24: 0 | G24: 1 | H24: 1 | I24: 0 | J24: =B24*Projects!N2+C24*Projects!N3+D24*Projects!N4+E24*Projects!N5+F24*Projects!N6+G24*Projects!N7+H24*Projects!N8+I24*Projects!N9 -> 10700000 | K24: =B24*Projects!C2+C24*Projects!C3+D24*Projects!C4+E24*Projects!C5+F24*Projects!C6+G24*Projects!C7+H24*Projects!C8+I24*Projects!C9 -> 260 | L24: =B24*Projects!D2+C24*Projects!D3+D24*Projects!D4+E24*Projects!D5+F24*Projects!D6+G24*Projects!D7+H24*Projects!D8+I24*Projects!D9 -> 127 | M24: =B24*Projects!O2+C24*Projects!O3+D24*Projects!O4+E24*Projects!O5+F24*Projects!O6+G24*Projects!O7+H24*Projects!O8+I24*Projects!O9 -> 8861910.8 | N24: =B24*(1-Projects!Q2)+C24*(1-Projects!Q3)+D24*(1-Projects!Q4)+E24*(1-Projects!Q5)+F24*(1-Projects!Q6)+G24*(1-Projects!Q7)+H24*(1-Projects!Q8)+I24*(1-Projects!Q9) -> 0 | O24: =IF(AND(J24<=Inputs!B2,L24>=Inputs!B3,M24>=Inputs!B18,N24=0),1,0) -> 1 | P24: =IF(O24=1,L24,-1) -> 127 | Q24: =IF(AND(O24=1,L24=MAX(P$2:P$257)),M24,-1E+99) -> -1e+99
A25: 23 | B25: 0 | C25: 0 | D25: 0 | E25: 1 | F25: 0 | G25: 1 | H25: 1 | I25: 1 | J25: =B25*Projects!N2+C25*Projects!N3+D25*Projects!N4+E25*Projects!N5+F25*Projects!N6+G25*Projects!N7+H25*Projects!N8+I25*Projects!N9 -> 15200000 | K25: =B25*Projects!C2+C25*Projects!C3+D25*Projects!C4+E25*Projects!C5+F25*Projects!C6+G25*Projects!C7+H25*Projects!C8+I25*Projects!C9 -> 350 | L25: =B25*Projects!D2+C25*Projects!D3+D25*Projects!D4+E25*Projects!D5+F25*Projects!D6+G25*Projects!D7+H25*Projects!D8+I25*Projects!D9 -> 154 | M25: =B25*Projects!O2+C25*Projects!O3+D25*Projects!O4+E25*Projects!O5+F25*Projects!O6+G25*Projects!O7+H25*Projects!O8+I25*Projects!O9 -> 13318538 | N25: =B25*(1-Projects!Q2)+C25*(1-Projects!Q3)+D25*(1-Projects!Q4)+E25*(1-Projects!Q5)+F25*(1-Projects!Q6)+G25*(1-Projects!Q7)+H25*(1-Projects!Q8)+I25*(1-Projects!Q9) -> 0 | O25: =IF(AND(J25<=Inputs!B2,L25>=Inputs!B3,M25>=Inputs!B18,N25=0),1,0) -> 0 | P25: =IF(O25=1,L25,-1) -> -1 | Q25: =IF(AND(O25=1,L25=MAX(P$2:P$257)),M25,-1E+99) -> -1e+99
A26: 24 | B26: 0 | C26: 0 | D26: 0 | E26: 1 | F26: 1 | G26: 0 | H26: 0 | I26: 0 | J26: =B26*Projects!N2+C26*Projects!N3+D26*Projects!N4+E26*Projects!N5+F26*Projects!N6+G26*Projects!N7+H26*Projects!N8+I26*Projects!N9 -> 7200000 | K26: =B26*Projects!C2+C26*Projects!C3+D26*Projects!C4+E26*Projects!C5+F26*Projects!C6+G26*Projects!C7+H26*Projects!C8+I26*Projects!C9 -> 160 | L26: =B26*Projects!D2+C26*Projects!D3+D26*Projects!D4+E26*Projects!D5+F26*Projects!D6+G26*Projects!D7+H26*Projects!D8+I26*Projects!D9 -> 66 | M26: =B26*Projects!O2+C26*Projects!O3+D26*Projects!O4+E26*Projects!O5+F26*Projects!O6+G26*Projects!O7+H26*Projects!O8+I26*Projects!O9 -> 6318320.6 | N26: =B26*(1-Projects!Q2)+C26*(1-Projects!Q3)+D26*(1-Projects!Q4)+E26*(1-Projects!Q5)+F26*(1-Projects!Q6)+G26*(1-Projects!Q7)+H26*(1-Projects!Q8)+I26*(1-Projects!Q9) -> 0 | O26: =IF(AND(J26<=Inputs!B2,L26>=Inputs!B3,M26>=Inputs!B18,N26=0),1,0) -> 0 | P26: =IF(O26=1,L26,-1) -> -1 | Q26: =IF(AND(O26=1,L26=MAX(P$2:P$257)),M26,-1E+99) -> -1e+99
A27: 25 | B27: 0 | C27: 0 | D27: 0 | E27: 1 | F27: 1 | G27: 0 | H27: 0 | I27: 1 | J27: =B27*Projects!N2+C27*Projects!N3+D27*Projects!N4+E27*Projects!N5+F27*Projects!N6+G27*Projects!N7+H27*Projects!N8+I27*Projects!N9 -> 11700000 | K27: =B27*Projects!C2+C27*Projects!C3+D27*Projects!C4+E27*Projects!C5+F27*Projects!C6+G27*Projects!C7+H27*Projects!C8+I27*Projects!C9 -> 250 | L27: =B27*Projects!D2+C27*Projects!D3+D27*Projects!D4+E27*Projects!D5+F27*Projects!D6+G27*Projects!D7+H27*Projects!D8+I27*Projects!D9 -> 93 | M27: =B27*Projects!O2+C27*Projects!O3+D27*Projects!O4+E27*Projects!O5+F27*Projects!O6+G27*Projects!O7+H27*Projects!O8+I27*Projects!O9 -> 10774948 | N27: =B27*(1-Projects!Q2)+C27*(1-Projects!Q3)+D27*(1-Projects!Q4)+E27*(1-Projects!Q5)+F27*(1-Projects!Q6)+G27*(1-Projects!Q7)+H27*(1-Projects!Q8)+I27*(1-Projects!Q9) -> 0 | O27: =IF(AND(J27<=Inputs!B2,L27>=Inputs!B3,M27>=Inputs!B18,N27=0),1,0) -> 1 | P27: =IF(O27=1,L27,-1) -> 93 | Q27: =IF(AND(O27=1,L27=MAX(P$2:P$257)),M27,-1E+99) -> -1e+99
A28: 26 | B28: 0 | C28: 0 | D28: 0 | E28: 1 | F28: 1 | G28: 0 | H28: 1 | I28: 0 | J28: =B28*Projects!N2+C28*Projects!N3+D28*Projects!N4+E28*Projects!N5+F28*Projects!N6+G28*Projects!N7+H28*Projects!N8+I28*Projects!N9 -> 11300000 | K28: =B28*Projects!C2+C28*Projects!C3+D28*Projects!C4+E28*Projects!C5+F28*Projects!C6+G28*Projects!C7+H28*Projects!C8+I28*Projects!C9 -> 270 | L28: =B28*Projects!D2+C28*Projects!D3+D28*Projects!D4+E28*Projects!D5+F28*Projects!D6+G28*Projects!D7+H28*Projects!D8+I28*Projects!D9 -> 132 | M28: =B28*Projects!O2+C28*Projects!O3+D28*Projects!O4+E28*Projects!O5+F28*Projects!O6+G28*Projects!O7+H28*Projects!O8+I28*Projects!O9 -> 9353694.6 | N28: =B28*(1-Projects!Q2)+C28*(1-Projects!Q3)+D28*(1-Projects!Q4)+E28*(1-Projects!Q5)+F28*(1-Projects!Q6)+G28*(1-Projects!Q7)+H28*(1-Projects!Q8)+I28*(1-Projects!Q9) -> 0 | O28: =IF(AND(J28<=Inputs!B2,L28>=Inputs!B3,M28>=Inputs!B18,N28=0),1,0) -> 1 | P28: =IF(O28=1,L28,-1) -> 132 | Q28: =IF(AND(O28=1,L28=MAX(P$2:P$257)),M28,-1E+99) -> -1e+99
A29: 27 | B29: 0 | C29: 0 | D29: 0 | E29: 1 | F29: 1 | G29: 0 | H29: 1 | I29: 1 | J29: =B29*Projects!N2+C29*Projects!N3+D29*Projects!N4+E29*Projects!N5+F29*Projects!N6+G29*Projects!N7+H29*Projects!N8+I29*Projects!N9 -> 15800000 | K29: =B29*Projects!C2+C29*Projects!C3+D29*Projects!C4+E29*Projects!C5+F29*Projects!C6+G29*Projects!C7+H29*Projects!C8+I29*Projects!C9 -> 360 | L29: =B29*Projects!D2+C29*Projects!D3+D29*Projects!D4+E29*Projects!D5+F29*Projects!D6+G29*Projects!D7+H29*Projects!D8+I29*Projects!D9 -> 159 | M29: =B29*Projects!O2+C29*Projects!O3+D29*Projects!O4+E29*Projects!O5+F29*Projects!O6+G29*Projects!O7+H29*Projects!O8+I29*Projects!O9 -> 13810322 | N29: =B29*(1-Projects!Q2)+C29*(1-Projects!Q3)+D29*(1-Projects!Q4)+E29*(1-Projects!Q5)+F29*(1-Projects!Q6)+G29*(1-Projects!Q7)+H29*(1-Projects!Q8)+I29*(1-Projects!Q9) -> 0 | O29: =IF(AND(J29<=Inputs!B2,L29>=Inputs!B3,M29>=Inputs!B18,N29=0),1,0) -> 0 | P29: =IF(O29=1,L29,-1) -> -1 | Q29: =IF(AND(O29=1,L29=MAX(P$2:P$257)),M29,-1E+99) -> -1e+99
A30: 28 | B30: 0 | C30: 0 | D30: 0 | E30: 1 | F30: 1 | G30: 1 | H30: 0 | I30: 0 | J30: =B30*Projects!N2+C30*Projects!N3+D30*Projects!N4+E30*Projects!N5+F30*Projects!N6+G30*Projects!N7+H30*Projects!N8+I30*Projects!N9 -> 10400000 | K30: =B30*Projects!C2+C30*Projects!C3+D30*Projects!C4+E30*Projects!C5+F30*Projects!C6+G30*Projects!C7+H30*Projects!C8+I30*Projects!C9 -> 240 | L30: =B30*Projects!D2+C30*Projects!D3+D30*Projects!D4+E30*Projects!D5+F30*Projects!D6+G30*Projects!D7+H30*Projects!D8+I30*Projects!D9 -> 106 | M30: =B30*Projects!O2+C30*Projects!O3+D30*Projects!O4+E30*Projects!O5+F30*Projects!O6+G30*Projects!O7+H30*Projects!O8+I30*Projects!O9 -> 8828499.2 | N30: =B30*(1-Projects!Q2)+C30*(1-Projects!Q3)+D30*(1-Projects!Q4)+E30*(1-Projects!Q5)+F30*(1-Projects!Q6)+G30*(1-Projects!Q7)+H30*(1-Projects!Q8)+I30*(1-Projects!Q9) -> 0 | O30: =IF(AND(J30<=Inputs!B2,L30>=Inputs!B3,M30>=Inputs!B18,N30=0),1,0) -> 1 | P30: =IF(O30=1,L30,-1) -> 106 | Q30: =IF(AND(O30=1,L30=MAX(P$2:P$257)),M30,-1E+99) -> -1e+99
A31: 29 | B31: 0 | C31: 0 | D31: 0 | E31: 1 | F31: 1 | G31: 1 | H31: 0 | I31: 1 | J31: =B31*Projects!N2+C31*Projects!N3+D31*Projects!N4+E31*Projects!N5+F31*Projects!N6+G31*Projects!N7+H31*Projects!N8+I31*Projects!N9 -> 14900000 | K31: =B31*Projects!C2+C31*Projects!C3+D31*Projects!C4+E31*Projects!C5+F31*Projects!C6+G31*Projects!C7+H31*Projects!C8+I31*Projects!C9 -> 330 | L31: =B31*Projects!D2+C31*Projects!D3+D31*Projects!D4+E31*Projects!D5+F31*Projects!D6+G31*Projects!D7+H31*Projects!D8+I31*Projects!D9 -> 133 | M31: =B31*Projects!O2+C31*Projects!O3+D31*Projects!O4+E31*Projects!O5+F31*Projects!O6+G31*Projects!O7+H31*Projects!O8+I31*Projects!O9 -> 13285127 | N31: =B31*(1-Projects!Q2)+C31*(1-Projects!Q3)+D31*(1-Projects!Q4)+E31*(1-Projects!Q5)+F31*(1-Projects!Q6)+G31*(1-Projects!Q7)+H31*(1-Projects!Q8)+I31*(1-Projects!Q9) -> 0 | O31: =IF(AND(J31<=Inputs!B2,L31>=Inputs!B3,M31>=Inputs!B18,N31=0),1,0) -> 1 | P31: =IF(O31=1,L31,-1) -> 133 | Q31: =IF(AND(O31=1,L31=MAX(P$2:P$257)),M31,-1E+99) -> -1e+99
A32: 30 | B32: 0 | C32: 0 | D32: 0 | E32: 1 | F32: 1 | G32: 1 | H32: 1 | I32: 0 | J32: =B32*Projects!N2+C32*Projects!N3+D32*Projects!N4+E32*Projects!N5+F32*Projects!N6+G32*Projects!N7+H32*Projects!N8+I32*Projects!N9 -> 14500000 | K32: =B32*Projects!C2+C32*Projects!C3+D32*Projects!C4+E32*Projects!C5+F32*Projects!C6+G32*Projects!C7+H32*Projects!C8+I32*Projects!C9 -> 350 | L32: =B32*Projects!D2+C32*Projects!D3+D32*Projects!D4+E32*Projects!D5+F32*Projects!D6+G32*Projects!D7+H32*Projects!D8+I32*Projects!D9 -> 172 | M32: =B32*Projects!O2+C32*Projects!O3+D32*Projects!O4+E32*Projects!O5+F32*Projects!O6+G32*Projects!O7+H32*Projects!O8+I32*Projects!O9 -> 11863873 | N32: =B32*(1-Projects!Q2)+C32*(1-Projects!Q3)+D32*(1-Projects!Q4)+E32*(1-Projects!Q5)+F32*(1-Projects!Q6)+G32*(1-Projects!Q7)+H32*(1-Projects!Q8)+I32*(1-Projects!Q9) -> 0 | O32: =IF(AND(J32<=Inputs!B2,L32>=Inputs!B3,M32>=Inputs!B18,N32=0),1,0) -> 1 | P32: =IF(O32=1,L32,-1) -> 172 | Q32: =IF(AND(O32=1,L32=MAX(P$2:P$257)),M32,-1E+99) -> 11863873
A33: 31 | B33: 0 | C33: 0 | D33: 0 | E33: 1 | F33: 1 | G33: 1 | H33: 1 | I33: 1 | J33: =B33*Projects!N2+C33*Projects!N3+D33*Projects!N4+E33*Projects!N5+F33*Projects!N6+G33*Projects!N7+H33*Projects!N8+I33*Projects!N9 -> 19000000 | K33: =B33*Projects!C2+C33*Projects!C3+D33*Projects!C4+E33*Projects!C5+F33*Projects!C6+G33*Projects!C7+H33*Projects!C8+I33*Projects!C9 -> 440 | L33: =B33*Projects!D2+C33*Projects!D3+D33*Projects!D4+E33*Projects!D5+F33*Projects!D6+G33*Projects!D7+H33*Projects!D8+I33*Projects!D9 -> 199 | M33: =B33*Projects!O2+C33*Projects!O3+D33*Projects!O4+E33*Projects!O5+F33*Projects!O6+G33*Projects!O7+H33*Projects!O8+I33*Projects!O9 -> 16320501 | N33: =B33*(1-Projects!Q2)+C33*(1-Projects!Q3)+D33*(1-Projects!Q4)+E33*(1-Projects!Q5)+F33*(1-Projects!Q6)+G33*(1-Projects!Q7)+H33*(1-Projects!Q8)+I33*(1-Projects!Q9) -> 0 | O33: =IF(AND(J33<=Inputs!B2,L33>=Inputs!B3,M33>=Inputs!B18,N33=0),1,0) -> 0 | P33: =IF(O33=1,L33,-1) -> -1 | Q33: =IF(AND(O33=1,L33=MAX(P$2:P$257)),M33,-1E+99) -> -1e+99
A34: 32 | B34: 0 | C34: 0 | D34: 1 | E34: 0 | F34: 0 | G34: 0 | H34: 0 | I34: 0 | J34: =B34*Projects!N2+C34*Projects!N3+D34*Projects!N4+E34*Projects!N5+F34*Projects!N6+G34*Projects!N7+H34*Projects!N8+I34*Projects!N9 -> 4900000 | K34: =B34*Projects!C2+C34*Projects!C3+D34*Projects!C4+E34*Projects!C5+F34*Projects!C6+G34*Projects!C7+H34*Projects!C8+I34*Projects!C9 -> 120 | L34: =B34*Projects!D2+C34*Projects!D3+D34*Projects!D4+E34*Projects!D5+F34*Projects!D6+G34*Projects!D7+H34*Projects!D8+I34*Projects!D9 -> 60 | M34: =B34*Projects!O2+C34*Projects!O3+D34*Projects!O4+E34*Projects!O5+F34*Projects!O6+G34*Projects!O7+H34*Projects!O8+I34*Projects!O9 -> 3791271.7 | N34: =B34*(1-Projects!Q2)+C34*(1-Projects!Q3)+D34*(1-Projects!Q4)+E34*(1-Projects!Q5)+F34*(1-Projects!Q6)+G34*(1-Projects!Q7)+H34*(1-Projects!Q8)+I34*(1-Projects!Q9) -> 0 | O34: =IF(AND(J34<=Inputs!B2,L34>=Inputs!B3,M34>=Inputs!B18,N34=0),1,0) -> 0 | P34: =IF(O34=1,L34,-1) -> -1 | Q34: =IF(AND(O34=1,L34=MAX(P$2:P$257)),M34,-1E+99) -> -1e+99
A35: 33 | B35: 0 | C35: 0 | D35: 1 | E35: 0 | F35: 0 | G35: 0 | H35: 0 | I35: 1 | J35: =B35*Projects!N2+C35*Projects!N3+D35*Projects!N4+E35*Projects!N5+F35*Projects!N6+G35*Projects!N7+H35*Projects!N8+I35*Projects!N9 -> 9400000 | K35: =B35*Projects!C2+C35*Projects!C3+D35*Projects!C4+E35*Projects!C5+F35*Projects!C6+G35*Projects!C7+H35*Projects!C8+I35*Projects!C9 -> 210 | L35: =B35*Projects!D2+C35*Projects!D3+D35*Projects!D4+E35*Projects!D5+F35*Projects!D6+G35*Projects!D7+H35*Projects!D8+I35*Projects!D9 -> 87 | M35: =B35*Projects!O2+C35*Projects!O3+D35*Projects!O4+E35*Projects!O5+F35*Projects!O6+G35*Projects!O7+H35*Projects!O8+I35*Projects!O9 -> 8247899.2 | N35: =B35*(1-Projects!Q2)+C35*(1-Projects!Q3)+D35*(1-Projects!Q4)+E35*(1-Projects!Q5)+F35*(1-Projects!Q6)+G35*(1-Projects!Q7)+H35*(1-Projects!Q8)+I35*(1-Projects!Q9) -> 0 | O35: =IF(AND(J35<=Inputs!B2,L35>=Inputs!B3,M35>=Inputs!B18,N35=0),1,0) -> 1 | P35: =IF(O35=1,L35,-1) -> 87 | Q35: =IF(AND(O35=1,L35=MAX(P$2:P$257)),M35,-1E+99) -> -1e+99
A36: 34 | B36: 0 | C36: 0 | D36: 1 | E36: 0 | F36: 0 | G36: 0 | H36: 1 | I36: 0 | J36: =B36*Projects!N2+C36*Projects!N3+D36*Projects!N4+E36*Projects!N5+F36*Projects!N6+G36*Projects!N7+H36*Projects!N8+I36*Projects!N9 -> 9000000 | K36: =B36*Projects!C2+C36*Projects!C3+D36*Projects!C4+E36*Projects!C5+F36*Projects!C6+G36*Projects!C7+H36*Projects!C8+I36*Projects!C9 -> 230 | L36: =B36*Projects!D2+C36*Projects!D3+D36*Projects!D4+E36*Projects!D5+F36*Projects!D6+G36*Projects!D7+H36*Projects!D8+I36*Projects!D9 -> 126 | M36: =B36*Projects!O2+C36*Projects!O3+D36*Projects!O4+E36*Projects!O5+F36*Projects!O6+G36*Projects!O7+H36*Projects!O8+I36*Projects!O9 -> 6826645.7 | N36: =B36*(1-Projects!Q2)+C36*(1-Projects!Q3)+D36*(1-Projects!Q4)+E36*(1-Projects!Q5)+F36*(1-Projects!Q6)+G36*(1-Projects!Q7)+H36*(1-Projects!Q8)+I36*(1-Projects!Q9) -> 0 | O36: =IF(AND(J36<=Inputs!B2,L36>=Inputs!B3,M36>=Inputs!B18,N36=0),1,0) -> 1 | P36: =IF(O36=1,L36,-1) -> 126 | Q36: =IF(AND(O36=1,L36=MAX(P$2:P$257)),M36,-1E+99) -> -1e+99
A37: 35 | B37: 0 | C37: 0 | D37: 1 | E37: 0 | F37: 0 | G37: 0 | H37: 1 | I37: 1 | J37: =B37*Projects!N2+C37*Projects!N3+D37*Projects!N4+E37*Projects!N5+F37*Projects!N6+G37*Projects!N7+H37*Projects!N8+I37*Projects!N9 -> 13500000 | K37: =B37*Projects!C2+C37*Projects!C3+D37*Projects!C4+E37*Projects!C5+F37*Projects!C6+G37*Projects!C7+H37*Projects!C8+I37*Projects!C9 -> 320 | L37: =B37*Projects!D2+C37*Projects!D3+D37*Projects!D4+E37*Projects!D5+F37*Projects!D6+G37*Projects!D7+H37*Projects!D8+I37*Projects!D9 -> 153 | M37: =B37*Projects!O2+C37*Projects!O3+D37*Projects!O4+E37*Projects!O5+F37*Projects!O6+G37*Projects!O7+H37*Projects!O8+I37*Projects!O9 -> 11283273 | N37: =B37*(1-Projects!Q2)+C37*(1-Projects!Q3)+D37*(1-Projects!Q4)+E37*(1-Projects!Q5)+F37*(1-Projects!Q6)+G37*(1-Projects!Q7)+H37*(1-Projects!Q8)+I37*(1-Projects!Q9) -> 0 | O37: =IF(AND(J37<=Inputs!B2,L37>=Inputs!B3,M37>=Inputs!B18,N37=0),1,0) -> 1 | P37: =IF(O37=1,L37,-1) -> 153 | Q37: =IF(AND(O37=1,L37=MAX(P$2:P$257)),M37,-1E+99) -> -1e+99
A38: 36 | B38: 0 | C38: 0 | D38: 1 | E38: 0 | F38: 0 | G38: 1 | H38: 0 | I38: 0 | J38: =B38*Projects!N2+C38*Projects!N3+D38*Projects!N4+E38*Projects!N5+F38*Projects!N6+G38*Projects!N7+H38*Projects!N8+I38*Projects!N9 -> 8100000 | K38: =B38*Projects!C2+C38*Projects!C3+D38*Projects!C4+E38*Projects!C5+F38*Projects!C6+G38*Projects!C7+H38*Projects!C8+I38*Projects!C9 -> 200 | L38: =B38*Projects!D2+C38*Projects!D3+D38*Projects!D4+E38*Projects!D5+F38*Projects!D6+G38*Projects!D7+H38*Projects!D8+I38*Projects!D9 -> 100 | M38: =B38*Projects!O2+C38*Projects!O3+D38*Projects!O4+E38*Projects!O5+F38*Projects!O6+G38*Projects!O7+H38*Projects!O8+I38*Projects!O9 -> 6301450.4 | N38: =B38*(1-Projects!Q2)+C38*(1-Projects!Q3)+D38*(1-Projects!Q4)+E38*(1-Projects!Q5)+F38*(1-Projects!Q6)+G38*(1-Projects!Q7)+H38*(1-Projects!Q8)+I38*(1-Projects!Q9) -> 0 | O38: =IF(AND(J38<=Inputs!B2,L38>=Inputs!B3,M38>=Inputs!B18,N38=0),1,0) -> 1 | P38: =IF(O38=1,L38,-1) -> 100 | Q38: =IF(AND(O38=1,L38=MAX(P$2:P$257)),M38,-1E+99) -> -1e+99
A39: 37 | B39: 0 | C39: 0 | D39: 1 | E39: 0 | F39: 0 | G39: 1 | H39: 0 | I39: 1 | J39: =B39*Projects!N2+C39*Projects!N3+D39*Projects!N4+E39*Projects!N5+F39*Projects!N6+G39*Projects!N7+H39*Projects!N8+I39*Projects!N9 -> 12600000 | K39: =B39*Projects!C2+C39*Projects!C3+D39*Projects!C4+E39*Projects!C5+F39*Projects!C6+G39*Projects!C7+H39*Projects!C8+I39*Projects!C9 -> 290 | L39: =B39*Projects!D2+C39*Projects!D3+D39*Projects!D4+E39*Projects!D5+F39*Projects!D6+G39*Projects!D7+H39*Projects!D8+I39*Projects!D9 -> 127 | M39: =B39*Projects!O2+C39*Projects!O3+D39*Projects!O4+E39*Projects!O5+F39*Projects!O6+G39*Projects!O7+H39*Projects!O8+I39*Projects!O9 -> 10758078 | N39: =B39*(1-Projects!Q2)+C39*(1-Projects!Q3)+D39*(1-Projects!Q4)+E39*(1-Projects!Q5)+F39*(1-Projects!Q6)+G39*(1-Projects!Q7)+H39*(1-Projects!Q8)+I39*(1-Projects!Q9) -> 0 | O39: =IF(AND(J39<=Inputs!B2,L39>=Inputs!B3,M39>=Inputs!B18,N39=0),1,0) -> 1 | P39: =IF(O39=1,L39,-1) -> 127 | Q39: =IF(AND(O39=1,L39=MAX(P$2:P$257)),M39,-1E+99) -> -1e+99
A40: 38 | B40: 0 | C40: 0 | D40: 1 | E40: 0 | F40: 0 | G40: 1 | H40: 1 | I40: 0 | J40: =B40*Projects!N2+C40*Projects!N3+D40*Projects!N4+E40*Projects!N5+F40*Projects!N6+G40*Projects!N7+H40*Projects!N8+I40*Projects!N9 -> 12200000 | K40: =B40*Projects!C2+C40*Projects!C3+D40*Projects!C4+E40*Projects!C5+F40*Projects!C6+G40*Projects!C7+H40*Projects!C8+I40*Projects!C9 -> 310 | L40: =B40*Projects!D2+C40*Projects!D3+D40*Projects!D4+E40*Projects!D5+F40*Projects!D6+G40*Projects!D7+H40*Projects!D8+I40*Projects!D9 -> 166 | M40: =B40*Projects!O2+C40*Projects!O3+D40*Projects!O4+E40*Projects!O5+F40*Projects!O6+G40*Projects!O7+H40*Projects!O8+I40*Projects!O9 -> 9336824.3 | N40: =B40*(1-Projects!Q2)+C40*(1-Projects!Q3)+D40*(1-Projects!Q4)+E40*(1-Projects!Q5)+F40*(1-Projects!Q6)+G40*(1-Projects!Q7)+H40*(1-Projects!Q8)+I40*(1-Projects!Q9) -> 0 | O40: =IF(AND(J40<=Inputs!B2,L40>=Inputs!B3,M40>=Inputs!B18,N40=0),1,0) -> 1 | P40: =IF(O40=1,L40,-1) -> 166 | Q40: =IF(AND(O40=1,L40=MAX(P$2:P$257)),M40,-1E+99) -> -1e+99
A41: 39 | B41: 0 | C41: 0 | D41: 1 | E41: 0 | F41: 0 | G41: 1 | H41: 1 | I41: 1 | J41: =B41*Projects!N2+C41*Projects!N3+D41*Projects!N4+E41*Projects!N5+F41*Projects!N6+G41*Projects!N7+H41*Projects!N8+I41*Projects!N9 -> 16700000 | K41: =B41*Projects!C2+C41*Projects!C3+D41*Projects!C4+E41*Projects!C5+F41*Projects!C6+G41*Projects!C7+H41*Projects!C8+I41*Projects!C9 -> 400 | L41: =B41*Projects!D2+C41*Projects!D3+D41*Projects!D4+E41*Projects!D5+F41*Projects!D6+G41*Projects!D7+H41*Projects!D8+I41*Projects!D9 -> 193 | M41: =B41*Projects!O2+C41*Projects!O3+D41*Projects!O4+E41*Projects!O5+F41*Projects!O6+G41*Projects!O7+H41*Projects!O8+I41*Projects!O9 -> 13793452 | N41: =B41*(1-Projects!Q2)+C41*(1-Projects!Q3)+D41*(1-Projects!Q4)+E41*(1-Projects!Q5)+F41*(1-Projects!Q6)+G41*(1-Projects!Q7)+H41*(1-Projects!Q8)+I41*(1-Projects!Q9) -> 0 | O41: =IF(AND(J41<=Inputs!B2,L41>=Inputs!B3,M41>=Inputs!B18,N41=0),1,0) -> 0 | P41: =IF(O41=1,L41,-1) -> -1 | Q41: =IF(AND(O41=1,L41=MAX(P$2:P$257)),M41,-1E+99) -> -1e+99
A42: 40 | B42: 0 | C42: 0 | D42: 1 | E42: 0 | F42: 1 | G42: 0 | H42: 0 | I42: 0 | J42: =B42*Projects!N2+C42*Projects!N3+D42*Projects!N4+E42*Projects!N5+F42*Projects!N6+G42*Projects!N7+H42*Projects!N8+I42*Projects!N9 -> 8700000 | K42: =B42*Projects!C2+C42*Projects!C3+D42*Projects!C4+E42*Projects!C5+F42*Projects!C6+G42*Projects!C7+H42*Projects!C8+I42*Projects!C9 -> 210 | L42: =B42*Projects!D2+C42*Projects!D3+D42*Projects!D4+E42*Projects!D5+F42*Projects!D6+G42*Projects!D7+H42*Projects!D8+I42*Projects!D9 -> 105 | M42: =B42*Projects!O2+C42*Projects!O3+D42*Projects!O4+E42*Projects!O5+F42*Projects!O6+G42*Projects!O7+H42*Projects!O8+I42*Projects!O9 -> 6793234.1 | N42: =B42*(1-Projects!Q2)+C42*(1-Projects!Q3)+D42*(1-Projects!Q4)+E42*(1-Projects!Q5)+F42*(1-Projects!Q6)+G42*(1-Projects!Q7)+H42*(1-Projects!Q8)+I42*(1-Projects!Q9) -> 0 | O42: =IF(AND(J42<=Inputs!B2,L42>=Inputs!B3,M42>=Inputs!B18,N42=0),1,0) -> 1 | P42: =IF(O42=1,L42,-1) -> 105 | Q42: =IF(AND(O42=1,L42=MAX(P$2:P$257)),M42,-1E+99) -> -1e+99
A43: 41 | B43: 0 | C43: 0 | D43: 1 | E43: 0 | F43: 1 | G43: 0 | H43: 0 | I43: 1 | J43: =B43*Projects!N2+C43*Projects!N3+D43*Projects!N4+E43*Projects!N5+F43*Projects!N6+G43*Projects!N7+H43*Projects!N8+I43*Projects!N9 -> 13200000 | K43: =B43*Projects!C2+C43*Projects!C3+D43*Projects!C4+E43*Projects!C5+F43*Projects!C6+G43*Projects!C7+H43*Projects!C8+I43*Projects!C9 -> 300 | L43: =B43*Projects!D2+C43*Projects!D3+D43*Projects!D4+E43*Projects!D5+F43*Projects!D6+G43*Projects!D7+H43*Projects!D8+I43*Projects!D9 -> 132 | M43: =B43*Projects!O2+C43*Projects!O3+D43*Projects!O4+E43*Projects!O5+F43*Projects!O6+G43*Projects!O7+H43*Projects!O8+I43*Projects!O9 -> 11249862 | N43: =B43*(1-Projects!Q2)+C43*(1-Projects!Q3)+D43*(1-Projects!Q4)+E43*(1-Projects!Q5)+F43*(1-Projects!Q6)+G43*(1-Projects!Q7)+H43*(1-Projects!Q8)+I43*(1-Projects!Q9) -> 0 | O43: =IF(AND(J43<=Inputs!B2,L43>=Inputs!B3,M43>=Inputs!B18,N43=0),1,0) -> 1 | P43: =IF(O43=1,L43,-1) -> 132 | Q43: =IF(AND(O43=1,L43=MAX(P$2:P$257)),M43,-1E+99) -> -1e+99
A44: 42 | B44: 0 | C44: 0 | D44: 1 | E44: 0 | F44: 1 | G44: 0 | H44: 1 | I44: 0 | J44: =B44*Projects!N2+C44*Projects!N3+D44*Projects!N4+E44*Projects!N5+F44*Projects!N6+G44*Projects!N7+H44*Projects!N8+I44*Projects!N9 -> 12800000 | K44: =B44*Projects!C2+C44*Projects!C3+D44*Projects!C4+E44*Projects!C5+F44*Projects!C6+G44*Projects!C7+H44*Projects!C8+I44*Projects!C9 -> 320 | L44: =B44*Projects!D2+C44*Projects!D3+D44*Projects!D4+E44*Projects!D5+F44*Projects!D6+G44*Projects!D7+H44*Projects!D8+I44*Projects!D9 -> 171 | M44: =B44*Projects!O2+C44*Projects!O3+D44*Projects!O4+E44*Projects!O5+F44*Projects!O6+G44*Projects!O7+H44*Projects!O8+I44*Projects!O9 -> 9828608.1 | N44: =B44*(1-Projects!Q2)+C44*(1-Projects!Q3)+D44*(1-Projects!Q4)+E44*(1-Projects!Q5)+F44*(1-Projects!Q6)+G44*(1-Projects!Q7)+H44*(1-Projects!Q8)+I44*(1-Projects!Q9) -> 0 | O44: =IF(AND(J44<=Inputs!B2,L44>=Inputs!B3,M44>=Inputs!B18,N44=0),1,0) -> 1 | P44: =IF(O44=1,L44,-1) -> 171 | Q44: =IF(AND(O44=1,L44=MAX(P$2:P$257)),M44,-1E+99) -> -1e+99
A45: 43 | B45: 0 | C45: 0 | D45: 1 | E45: 0 | F45: 1 | G45: 0 | H45: 1 | I45: 1 | J45: =B45*Projects!N2+C45*Projects!N3+D45*Projects!N4+E45*Projects!N5+F45*Projects!N6+G45*Projects!N7+H45*Projects!N8+I45*Projects!N9 -> 17300000 | K45: =B45*Projects!C2+C45*Projects!C3+D45*Projects!C4+E45*Projects!C5+F45*Projects!C6+G45*Projects!C7+H45*Projects!C8+I45*Projects!C9 -> 410 | L45: =B45*Projects!D2+C45*Projects!D3+D45*Projects!D4+E45*Projects!D5+F45*Projects!D6+G45*Projects!D7+H45*Projects!D8+I45*Projects!D9 -> 198 | M45: =B45*Projects!O2+C45*Projects!O3+D45*Projects!O4+E45*Projects!O5+F45*Projects!O6+G45*Projects!O7+H45*Projects!O8+I45*Projects!O9 -> 14285236 | N45: =B45*(1-Projects!Q2)+C45*(1-Projects!Q3)+D45*(1-Projects!Q4)+E45*(1-Projects!Q5)+F45*(1-Projects!Q6)+G45*(1-Projects!Q7)+H45*(1-Projects!Q8)+I45*(1-Projects!Q9) -> 0 | O45: =IF(AND(J45<=Inputs!B2,L45>=Inputs!B3,M45>=Inputs!B18,N45=0),1,0) -> 0 | P45: =IF(O45=1,L45,-1) -> -1 | Q45: =IF(AND(O45=1,L45=MAX(P$2:P$257)),M45,-1E+99) -> -1e+99
A46: 44 | B46: 0 | C46: 0 | D46: 1 | E46: 0 | F46: 1 | G46: 1 | H46: 0 | I46: 0 | J46: =B46*Projects!N2+C46*Projects!N3+D46*Projects!N4+E46*Projects!N5+F46*Projects!N6+G46*Projects!N7+H46*Projects!N8+I46*Projects!N9 -> 11900000 | K46: =B46*Projects!C2+C46*Projects!C3+D46*Projects!C4+E46*Projects!C5+F46*Projects!C6+G46*Projects!C7+H46*Projects!C8+I46*Projects!C9 -> 290 | L46: =B46*Projects!D2+C46*Projects!D3+D46*Projects!D4+E46*Projects!D5+F46*Projects!D6+G46*Projects!D7+H46*Projects!D8+I46*Projects!D9 -> 145 | M46: =B46*Projects!O2+C46*Projects!O3+D46*Projects!O4+E46*Projects!O5+F46*Projects!O6+G46*Projects!O7+H46*Projects!O8+I46*Projects!O9 -> 9303412.7 | N46: =B46*(1-Projects!Q2)+C46*(1-Projects!Q3)+D46*(1-Projects!Q4)+E46*(1-Projects!Q5)+F46*(1-Projects!Q6)+G46*(1-Projects!Q7)+H46*(1-Projects!Q8)+I46*(1-Projects!Q9) -> 0 | O46: =IF(AND(J46<=Inputs!B2,L46>=Inputs!B3,M46>=Inputs!B18,N46=0),1,0) -> 1 | P46: =IF(O46=1,L46,-1) -> 145 | Q46: =IF(AND(O46=1,L46=MAX(P$2:P$257)),M46,-1E+99) -> -1e+99
A47: 45 | B47: 0 | C47: 0 | D47: 1 | E47: 0 | F47: 1 | G47: 1 | H47: 0 | I47: 1 | J47: =B47*Projects!N2+C47*Projects!N3+D47*Projects!N4+E47*Projects!N5+F47*Projects!N6+G47*Projects!N7+H47*Projects!N8+I47*Projects!N9 -> 16400000 | K47: =B47*Projects!C2+C47*Projects!C3+D47*Projects!C4+E47*Projects!C5+F47*Projects!C6+G47*Projects!C7+H47*Projects!C8+I47*Projects!C9 -> 380 | L47: =B47*Projects!D2+C47*Projects!D3+D47*Projects!D4+E47*Projects!D5+F47*Projects!D6+G47*Projects!D7+H47*Projects!D8+I47*Projects!D9 -> 172 | M47: =B47*Projects!O2+C47*Projects!O3+D47*Projects!O4+E47*Projects!O5+F47*Projects!O6+G47*Projects!O7+H47*Projects!O8+I47*Projects!O9 -> 13760040 | N47: =B47*(1-Projects!Q2)+C47*(1-Projects!Q3)+D47*(1-Projects!Q4)+E47*(1-Projects!Q5)+F47*(1-Projects!Q6)+G47*(1-Projects!Q7)+H47*(1-Projects!Q8)+I47*(1-Projects!Q9) -> 0 | O47: =IF(AND(J47<=Inputs!B2,L47>=Inputs!B3,M47>=Inputs!B18,N47=0),1,0) -> 0 | P47: =IF(O47=1,L47,-1) -> -1 | Q47: =IF(AND(O47=1,L47=MAX(P$2:P$257)),M47,-1E+99) -> -1e+99
A48: 46 | B48: 0 | C48: 0 | D48: 1 | E48: 0 | F48: 1 | G48: 1 | H48: 1 | I48: 0 | J48: =B48*Projects!N2+C48*Projects!N3+D48*Projects!N4+E48*Projects!N5+F48*Projects!N6+G48*Projects!N7+H48*Projects!N8+I48*Projects!N9 -> 16000000 | K48: =B48*Projects!C2+C48*Projects!C3+D48*Projects!C4+E48*Projects!C5+F48*Projects!C6+G48*Projects!C7+H48*Projects!C8+I48*Projects!C9 -> 400 | L48: =B48*Projects!D2+C48*Projects!D3+D48*Projects!D4+E48*Projects!D5+F48*Projects!D6+G48*Projects!D7+H48*Projects!D8+I48*Projects!D9 -> 211 | M48: =B48*Projects!O2+C48*Projects!O3+D48*Projects!O4+E48*Projects!O5+F48*Projects!O6+G48*Projects!O7+H48*Projects!O8+I48*Projects!O9 -> 12338787 | N48: =B48*(1-Projects!Q2)+C48*(1-Projects!Q3)+D48*(1-Projects!Q4)+E48*(1-Projects!Q5)+F48*(1-Projects!Q6)+G48*(1-Projects!Q7)+H48*(1-Projects!Q8)+I48*(1-Projects!Q9) -> 0 | O48: =IF(AND(J48<=Inputs!B2,L48>=Inputs!B3,M48>=Inputs!B18,N48=0),1,0) -> 0 | P48: =IF(O48=1,L48,-1) -> -1 | Q48: =IF(AND(O48=1,L48=MAX(P$2:P$257)),M48,-1E+99) -> -1e+99
A49: 47 | B49: 0 | C49: 0 | D49: 1 | E49: 0 | F49: 1 | G49: 1 | H49: 1 | I49: 1 | J49: =B49*Projects!N2+C49*Projects!N3+D49*Projects!N4+E49*Projects!N5+F49*Projects!N6+G49*Projects!N7+H49*Projects!N8+I49*Projects!N9 -> 20500000 | K49: =B49*Projects!C2+C49*Projects!C3+D49*Projects!C4+E49*Projects!C5+F49*Projects!C6+G49*Projects!C7+H49*Projects!C8+I49*Projects!C9 -> 490 | L49: =B49*Projects!D2+C49*Projects!D3+D49*Projects!D4+E49*Projects!D5+F49*Projects!D6+G49*Projects!D7+H49*Projects!D8+I49*Projects!D9 -> 238 | M49: =B49*Projects!O2+C49*Projects!O3+D49*Projects!O4+E49*Projects!O5+F49*Projects!O6+G49*Projects!O7+H49*Projects!O8+I49*Projects!O9 -> 16795414 | N49: =B49*(1-Projects!Q2)+C49*(1-Projects!Q3)+D49*(1-Projects!Q4)+E49*(1-Projects!Q5)+F49*(1-Projects!Q6)+G49*(1-Projects!Q7)+H49*(1-Projects!Q8)+I49*(1-Projects!Q9) -> 0 | O49: =IF(AND(J49<=Inputs!B2,L49>=Inputs!B3,M49>=Inputs!B18,N49=0),1,0) -> 0 | P49: =IF(O49=1,L49,-1) -> -1 | Q49: =IF(AND(O49=1,L49=MAX(P$2:P$257)),M49,-1E+99) -> -1e+99
A50: 48 | B50: 0 | C50: 0 | D50: 1 | E50: 1 | F50: 0 | G50: 0 | H50: 0 | I50: 0 | J50: =B50*Projects!N2+C50*Projects!N3+D50*Projects!N4+E50*Projects!N5+F50*Projects!N6+G50*Projects!N7+H50*Projects!N8+I50*Projects!N9 -> 8300000 | K50: =B50*Projects!C2+C50*Projects!C3+D50*Projects!C4+E50*Projects!C5+F50*Projects!C6+G50*Projects!C7+H50*Projects!C8+I50*Projects!C9 -> 190 | L50: =B50*Projects!D2+C50*Projects!D3+D50*Projects!D4+E50*Projects!D5+F50*Projects!D6+G50*Projects!D7+H50*Projects!D8+I50*Projects!D9 -> 81 | M50: =B50*Projects!O2+C50*Projects!O3+D50*Projects!O4+E50*Projects!O5+F50*Projects!O6+G50*Projects!O7+H50*Projects!O8+I50*Projects!O9 -> 7107630 | N50: =B50*(1-Projects!Q2)+C50*(1-Projects!Q3)+D50*(1-Projects!Q4)+E50*(1-Projects!Q5)+F50*(1-Projects!Q6)+G50*(1-Projects!Q7)+H50*(1-Projects!Q8)+I50*(1-Projects!Q9) -> 0 | O50: =IF(AND(J50<=Inputs!B2,L50>=Inputs!B3,M50>=Inputs!B18,N50=0),1,0) -> 1 | P50: =IF(O50=1,L50,-1) -> 81 | Q50: =IF(AND(O50=1,L50=MAX(P$2:P$257)),M50,-1E+99) -> -1e+99
A51: 49 | B51: 0 | C51: 0 | D51: 1 | E51: 1 | F51: 0 | G51: 0 | H51: 0 | I51: 1 | J51: =B51*Projects!N2+C51*Projects!N3+D51*Projects!N4+E51*Projects!N5+F51*Projects!N6+G51*Projects!N7+H51*Projects!N8+I51*Projects!N9 -> 12800000 | K51: =B51*Projects!C2+C51*Projects!C3+D51*Projects!C4+E51*Projects!C5+F51*Projects!C6+G51*Projects!C7+H51*Projects!C8+I51*Projects!C9 -> 280 | L51: =B51*Projects!D2+C51*Projects!D3+D51*Projects!D4+E51*Projects!D5+F51*Projects!D6+G51*Projects!D7+H51*Projects!D8+I51*Projects!D9 -> 108 | M51: =B51*Projects!O2+C51*Projects!O3+D51*Projects!O4+E51*Projects!O5+F51*Projects!O6+G51*Projects!O7+H51*Projects!O8+I51*Projects!O9 -> 11564257 | N51: =B51*(1-Projects!Q2)+C51*(1-Projects!Q3)+D51*(1-Projects!Q4)+E51*(1-Projects!Q5)+F51*(1-Projects!Q6)+G51*(1-Projects!Q7)+H51*(1-Projects!Q8)+I51*(1-Projects!Q9) -> 0 | O51: =IF(AND(J51<=Inputs!B2,L51>=Inputs!B3,M51>=Inputs!B18,N51=0),1,0) -> 1 | P51: =IF(O51=1,L51,-1) -> 108 | Q51: =IF(AND(O51=1,L51=MAX(P$2:P$257)),M51,-1E+99) -> -1e+99
A52: 50 | B52: 0 | C52: 0 | D52: 1 | E52: 1 | F52: 0 | G52: 0 | H52: 1 | I52: 0 | J52: =B52*Projects!N2+C52*Projects!N3+D52*Projects!N4+E52*Projects!N5+F52*Projects!N6+G52*Projects!N7+H52*Projects!N8+I52*Projects!N9 -> 12400000 | K52: =B52*Projects!C2+C52*Projects!C3+D52*Projects!C4+E52*Projects!C5+F52*Projects!C6+G52*Projects!C7+H52*Projects!C8+I52*Projects!C9 -> 300 | L52: =B52*Projects!D2+C52*Projects!D3+D52*Projects!D4+E52*Projects!D5+F52*Projects!D6+G52*Projects!D7+H52*Projects!D8+I52*Projects!D9 -> 147 | M52: =B52*Projects!O2+C52*Projects!O3+D52*Projects!O4+E52*Projects!O5+F52*Projects!O6+G52*Projects!O7+H52*Projects!O8+I52*Projects!O9 -> 10143004 | N52: =B52*(1-Projects!Q2)+C52*(1-Projects!Q3)+D52*(1-Projects!Q4)+E52*(1-Projects!Q5)+F52*(1-Projects!Q6)+G52*(1-Projects!Q7)+H52*(1-Projects!Q8)+I52*(1-Projects!Q9) -> 0 | O52: =IF(AND(J52<=Inputs!B2,L52>=Inputs!B3,M52>=Inputs!B18,N52=0),1,0) -> 1 | P52: =IF(O52=1,L52,-1) -> 147 | Q52: =IF(AND(O52=1,L52=MAX(P$2:P$257)),M52,-1E+99) -> -1e+99
A53: 51 | B53: 0 | C53: 0 | D53: 1 | E53: 1 | F53: 0 | G53: 0 | H53: 1 | I53: 1 | J53: =B53*Projects!N2+C53*Projects!N3+D53*Projects!N4+E53*Projects!N5+F53*Projects!N6+G53*Projects!N7+H53*Projects!N8+I53*Projects!N9 -> 16900000 | K53: =B53*Projects!C2+C53*Projects!C3+D53*Projects!C4+E53*Projects!C5+F53*Projects!C6+G53*Projects!C7+H53*Projects!C8+I53*Projects!C9 -> 390 | L53: =B53*Projects!D2+C53*Projects!D3+D53*Projects!D4+E53*Projects!D5+F53*Projects!D6+G53*Projects!D7+H53*Projects!D8+I53*Projects!D9 -> 174 | M53: =B53*Projects!O2+C53*Projects!O3+D53*Projects!O4+E53*Projects!O5+F53*Projects!O6+G53*Projects!O7+H53*Projects!O8+I53*Projects!O9 -> 14599631 | N53: =B53*(1-Projects!Q2)+C53*(1-Projects!Q3)+D53*(1-Projects!Q4)+E53*(1-Projects!Q5)+F53*(1-Projects!Q6)+G53*(1-Projects!Q7)+H53*(1-Projects!Q8)+I53*(1-Projects!Q9) -> 0 | O53: =IF(AND(J53<=Inputs!B2,L53>=Inputs!B3,M53>=Inputs!B18,N53=0),1,0) -> 0 | P53: =IF(O53=1,L53,-1) -> -1 | Q53: =IF(AND(O53=1,L53=MAX(P$2:P$257)),M53,-1E+99) -> -1e+99
A54: 52 | B54: 0 | C54: 0 | D54: 1 | E54: 1 | F54: 0 | G54: 1 | H54: 0 | I54: 0 | J54: =B54*Projects!N2+C54*Projects!N3+D54*Projects!N4+E54*Projects!N5+F54*Projects!N6+G54*Projects!N7+H54*Projects!N8+I54*Projects!N9 -> 11500000 | K54: =B54*Projects!C2+C54*Projects!C3+D54*Projects!C4+E54*Projects!C5+F54*Projects!C6+G54*Projects!C7+H54*Projects!C8+I54*Projects!C9 -> 270 | L54: =B54*Projects!D2+C54*Projects!D3+D54*Projects!D4+E54*Projects!D5+F54*Projects!D6+G54*Projects!D7+H54*Projects!D8+I54*Projects!D9 -> 121 | M54: =B54*Projects!O2+C54*Projects!O3+D54*Projects!O4+E54*Projects!O5+F54*Projects!O6+G54*Projects!O7+H54*Projects!O8+I54*Projects!O9 -> 9617808.6 | N54: =B54*(1-Projects!Q2)+C54*(1-Projects!Q3)+D54*(1-Projects!Q4)+E54*(1-Projects!Q5)+F54*(1-Projects!Q6)+G54*(1-Projects!Q7)+H54*(1-Projects!Q8)+I54*(1-Projects!Q9) -> 0 | O54: =IF(AND(J54<=Inputs!B2,L54>=Inputs!B3,M54>=Inputs!B18,N54=0),1,0) -> 1 | P54: =IF(O54=1,L54,-1) -> 121 | Q54: =IF(AND(O54=1,L54=MAX(P$2:P$257)),M54,-1E+99) -> -1e+99
A55: 53 | B55: 0 | C55: 0 | D55: 1 | E55: 1 | F55: 0 | G55: 1 | H55: 0 | I55: 1 | J55: =B55*Projects!N2+C55*Projects!N3+D55*Projects!N4+E55*Projects!N5+F55*Projects!N6+G55*Projects!N7+H55*Projects!N8+I55*Projects!N9 -> 16000000 | K55: =B55*Projects!C2+C55*Projects!C3+D55*Projects!C4+E55*Projects!C5+F55*Projects!C6+G55*Projects!C7+H55*Projects!C8+I55*Projects!C9 -> 360 | L55: =B55*Projects!D2+C55*Projects!D3+D55*Projects!D4+E55*Projects!D5+F55*Projects!D6+G55*Projects!D7+H55*Projects!D8+I55*Projects!D9 -> 148 | M55: =B55*Projects!O2+C55*Projects!O3+D55*Projects!O4+E55*Projects!O5+F55*Projects!O6+G55*Projects!O7+H55*Projects!O8+I55*Projects!O9 -> 14074436 | N55: =B55*(1-Projects!Q2)+C55*(1-Projects!Q3)+D55*(1-Projects!Q4)+E55*(1-Projects!Q5)+F55*(1-Projects!Q6)+G55*(1-Projects!Q7)+H55*(1-Projects!Q8)+I55*(1-Projects!Q9) -> 0 | O55: =IF(AND(J55<=Inputs!B2,L55>=Inputs!B3,M55>=Inputs!B18,N55=0),1,0) -> 0 | P55: =IF(O55=1,L55,-1) -> -1 | Q55: =IF(AND(O55=1,L55=MAX(P$2:P$257)),M55,-1E+99) -> -1e+99
A56: 54 | B56: 0 | C56: 0 | D56: 1 | E56: 1 | F56: 0 | G56: 1 | H56: 1 | I56: 0 | J56: =B56*Projects!N2+C56*Projects!N3+D56*Projects!N4+E56*Projects!N5+F56*Projects!N6+G56*Projects!N7+H56*Projects!N8+I56*Projects!N9 -> 15600000 | K56: =B56*Projects!C2+C56*Projects!C3+D56*Projects!C4+E56*Projects!C5+F56*Projects!C6+G56*Projects!C7+H56*Projects!C8+I56*Projects!C9 -> 380 | L56: =B56*Projects!D2+C56*Projects!D3+D56*Projects!D4+E56*Projects!D5+F56*Projects!D6+G56*Projects!D7+H56*Projects!D8+I56*Projects!D9 -> 187 | M56: =B56*Projects!O2+C56*Projects!O3+D56*Projects!O4+E56*Projects!O5+F56*Projects!O6+G56*Projects!O7+H56*Projects!O8+I56*Projects!O9 -> 12653183 | N56: =B56*(1-Projects!Q2)+C56*(1-Projects!Q3)+D56*(1-Projects!Q4)+E56*(1-Projects!Q5)+F56*(1-Projects!Q6)+G56*(1-Projects!Q7)+H56*(1-Projects!Q8)+I56*(1-Projects!Q9) -> 0 | O56: =IF(AND(J56<=Inputs!B2,L56>=Inputs!B3,M56>=Inputs!B18,N56=0),1,0) -> 0 | P56: =IF(O56=1,L56,-1) -> -1 | Q56: =IF(AND(O56=1,L56=MAX(P$2:P$257)),M56,-1E+99) -> -1e+99
A57: 55 | B57: 0 | C57: 0 | D57: 1 | E57: 1 | F57: 0 | G57: 1 | H57: 1 | I57: 1 | J57: =B57*Projects!N2+C57*Projects!N3+D57*Projects!N4+E57*Projects!N5+F57*Projects!N6+G57*Projects!N7+H57*Projects!N8+I57*Projects!N9 -> 20100000 | K57: =B57*Projects!C2+C57*Projects!C3+D57*Projects!C4+E57*Projects!C5+F57*Projects!C6+G57*Projects!C7+H57*Projects!C8+I57*Projects!C9 -> 470 | L57: =B57*Projects!D2+C57*Projects!D3+D57*Projects!D4+E57*Projects!D5+F57*Projects!D6+G57*Projects!D7+H57*Projects!D8+I57*Projects!D9 -> 214 | M57: =B57*Projects!O2+C57*Projects!O3+D57*Projects!O4+E57*Projects!O5+F57*Projects!O6+G57*Projects!O7+H57*Projects!O8+I57*Projects!O9 -> 17109810 | N57: =B57*(1-Projects!Q2)+C57*(1-Projects!Q3)+D57*(1-Projects!Q4)+E57*(1-Projects!Q5)+F57*(1-Projects!Q6)+G57*(1-Projects!Q7)+H57*(1-Projects!Q8)+I57*(1-Projects!Q9) -> 0 | O57: =IF(AND(J57<=Inputs!B2,L57>=Inputs!B3,M57>=Inputs!B18,N57=0),1,0) -> 0 | P57: =IF(O57=1,L57,-1) -> -1 | Q57: =IF(AND(O57=1,L57=MAX(P$2:P$257)),M57,-1E+99) -> -1e+99
A58: 56 | B58: 0 | C58: 0 | D58: 1 | E58: 1 | F58: 1 | G58: 0 | H58: 0 | I58: 0 | J58: =B58*Projects!N2+C58*Projects!N3+D58*Projects!N4+E58*Projects!N5+F58*Projects!N6+G58*Projects!N7+H58*Projects!N8+I58*Projects!N9 -> 12100000 | K58: =B58*Projects!C2+C58*Projects!C3+D58*Projects!C4+E58*Projects!C5+F58*Projects!C6+G58*Projects!C7+H58*Projects!C8+I58*Projects!C9 -> 280 | L58: =B58*Projects!D2+C58*Projects!D3+D58*Projects!D4+E58*Projects!D5+F58*Projects!D6+G58*Projects!D7+H58*Projects!D8+I58*Projects!D9 -> 126 | M58: =B58*Projects!O2+C58*Projects!O3+D58*Projects!O4+E58*Projects!O5+F58*Projects!O6+G58*Projects!O7+H58*Projects!O8+I58*Projects!O9 -> 10109592 | N58: =B58*(1-Projects!Q2)+C58*(1-Projects!Q3)+D58*(1-Projects!Q4)+E58*(1-Projects!Q5)+F58*(1-Projects!Q6)+G58*(1-Projects!Q7)+H58*(1-Projects!Q8)+I58*(1-Projects!Q9) -> 0 | O58: =IF(AND(J58<=Inputs!B2,L58>=Inputs!B3,M58>=Inputs!B18,N58=0),1,0) -> 1 | P58: =IF(O58=1,L58,-1) -> 126 | Q58: =IF(AND(O58=1,L58=MAX(P$2:P$257)),M58,-1E+99) -> -1e+99
A59: 57 | B59: 0 | C59: 0 | D59: 1 | E59: 1 | F59: 1 | G59: 0 | H59: 0 | I59: 1 | J59: =B59*Projects!N2+C59*Projects!N3+D59*Projects!N4+E59*Projects!N5+F59*Projects!N6+G59*Projects!N7+H59*Projects!N8+I59*Projects!N9 -> 16600000 | K59: =B59*Projects!C2+C59*Projects!C3+D59*Projects!C4+E59*Projects!C5+F59*Projects!C6+G59*Projects!C7+H59*Projects!C8+I59*Projects!C9 -> 370 | L59: =B59*Projects!D2+C59*Projects!D3+D59*Projects!D4+E59*Projects!D5+F59*Projects!D6+G59*Projects!D7+H59*Projects!D8+I59*Projects!D9 -> 153 | M59: =B59*Projects!O2+C59*Projects!O3+D59*Projects!O4+E59*Projects!O5+F59*Projects!O6+G59*Projects!O7+H59*Projects!O8+I59*Projects!O9 -> 14566220 | N59: =B59*(1-Projects!Q2)+C59*(1-Projects!Q3)+D59*(1-Projects!Q4)+E59*(1-Projects!Q5)+F59*(1-Projects!Q6)+G59*(1-Projects!Q7)+H59*(1-Projects!Q8)+I59*(1-Projects!Q9) -> 0 | O59: =IF(AND(J59<=Inputs!B2,L59>=Inputs!B3,M59>=Inputs!B18,N59=0),1,0) -> 0 | P59: =IF(O59=1,L59,-1) -> -1 | Q59: =IF(AND(O59=1,L59=MAX(P$2:P$257)),M59,-1E+99) -> -1e+99
A60: 58 | B60: 0 | C60: 0 | D60: 1 | E60: 1 | F60: 1 | G60: 0 | H60: 1 | I60: 0 | J60: =B60*Projects!N2+C60*Projects!N3+D60*Projects!N4+E60*Projects!N5+F60*Projects!N6+G60*Projects!N7+H60*Projects!N8+I60*Projects!N9 -> 16200000 | K60: =B60*Projects!C2+C60*Projects!C3+D60*Projects!C4+E60*Projects!C5+F60*Projects!C6+G60*Projects!C7+H60*Projects!C8+I60*Projects!C9 -> 390 | L60: =B60*Projects!D2+C60*Projects!D3+D60*Projects!D4+E60*Projects!D5+F60*Projects!D6+G60*Projects!D7+H60*Projects!D8+I60*Projects!D9 -> 192 | M60: =B60*Projects!O2+C60*Projects!O3+D60*Projects!O4+E60*Projects!O5+F60*Projects!O6+G60*Projects!O7+H60*Projects!O8+I60*Projects!O9 -> 13144966 | N60: =B60*(1-Projects!Q2)+C60*(1-Projects!Q3)+D60*(1-Projects!Q4)+E60*(1-Projects!Q5)+F60*(1-Projects!Q6)+G60*(1-Projects!Q7)+H60*(1-Projects!Q8)+I60*(1-Projects!Q9) -> 0 | O60: =IF(AND(J60<=Inputs!B2,L60>=Inputs!B3,M60>=Inputs!B18,N60=0),1,0) -> 0 | P60: =IF(O60=1,L60,-1) -> -1 | Q60: =IF(AND(O60=1,L60=MAX(P$2:P$257)),M60,-1E+99) -> -1e+99
A61: 59 | B61: 0 | C61: 0 | D61: 1 | E61: 1 | F61: 1 | G61: 0 | H61: 1 | I61: 1 | J61: =B61*Projects!N2+C61*Projects!N3+D61*Projects!N4+E61*Projects!N5+F61*Projects!N6+G61*Projects!N7+H61*Projects!N8+I61*Projects!N9 -> 20700000 | K61: =B61*Projects!C2+C61*Projects!C3+D61*Projects!C4+E61*Projects!C5+F61*Projects!C6+G61*Projects!C7+H61*Projects!C8+I61*Projects!C9 -> 480 | L61: =B61*Projects!D2+C61*Projects!D3+D61*Projects!D4+E61*Projects!D5+F61*Projects!D6+G61*Projects!D7+H61*Projects!D8+I61*Projects!D9 -> 219 | M61: =B61*Projects!O2+C61*Projects!O3+D61*Projects!O4+E61*Projects!O5+F61*Projects!O6+G61*Projects!O7+H61*Projects!O8+I61*Projects!O9 -> 17601594 | N61: =B61*(1-Projects!Q2)+C61*(1-Projects!Q3)+D61*(1-Projects!Q4)+E61*(1-Projects!Q5)+F61*(1-Projects!Q6)+G61*(1-Projects!Q7)+H61*(1-Projects!Q8)+I61*(1-Projects!Q9) -> 0 | O61: =IF(AND(J61<=Inputs!B2,L61>=Inputs!B3,M61>=Inputs!B18,N61=0),1,0) -> 0 | P61: =IF(O61=1,L61,-1) -> -1 | Q61: =IF(AND(O61=1,L61=MAX(P$2:P$257)),M61,-1E+99) -> -1e+99
A62: 60 | B62: 0 | C62: 0 | D62: 1 | E62: 1 | F62: 1 | G62: 1 | H62: 0 | I62: 0 | J62: =B62*Projects!N2+C62*Projects!N3+D62*Projects!N4+E62*Projects!N5+F62*Projects!N6+G62*Projects!N7+H62*Projects!N8+I62*Projects!N9 -> 15300000 | K62: =B62*Projects!C2+C62*Projects!C3+D62*Projects!C4+E62*Projects!C5+F62*Projects!C6+G62*Projects!C7+H62*Projects!C8+I62*Projects!C9 -> 360 | L62: =B62*Projects!D2+C62*Projects!D3+D62*Projects!D4+E62*Projects!D5+F62*Projects!D6+G62*Projects!D7+H62*Projects!D8+I62*Projects!D9 -> 166 | M62: =B62*Projects!O2+C62*Projects!O3+D62*Projects!O4+E62*Projects!O5+F62*Projects!O6+G62*Projects!O7+H62*Projects!O8+I62*Projects!O9 -> 12619771 | N62: =B62*(1-Projects!Q2)+C62*(1-Projects!Q3)+D62*(1-Projects!Q4)+E62*(1-Projects!Q5)+F62*(1-Projects!Q6)+G62*(1-Projects!Q7)+H62*(1-Projects!Q8)+I62*(1-Projects!Q9) -> 0 | O62: =IF(AND(J62<=Inputs!B2,L62>=Inputs!B3,M62>=Inputs!B18,N62=0),1,0) -> 0 | P62: =IF(O62=1,L62,-1) -> -1 | Q62: =IF(AND(O62=1,L62=MAX(P$2:P$257)),M62,-1E+99) -> -1e+99
A63: 61 | B63: 0 | C63: 0 | D63: 1 | E63: 1 | F63: 1 | G63: 1 | H63: 0 | I63: 1 | J63: =B63*Projects!N2+C63*Projects!N3+D63*Projects!N4+E63*Projects!N5+F63*Projects!N6+G63*Projects!N7+H63*Projects!N8+I63*Projects!N9 -> 19800000 | K63: =B63*Projects!C2+C63*Projects!C3+D63*Projects!C4+E63*Projects!C5+F63*Projects!C6+G63*Projects!C7+H63*Projects!C8+I63*Projects!C9 -> 450 | L63: =B63*Projects!D2+C63*Projects!D3+D63*Projects!D4+E63*Projects!D5+F63*Projects!D6+G63*Projects!D7+H63*Projects!D8+I63*Projects!D9 -> 193 | M63: =B63*Projects!O2+C63*Projects!O3+D63*Projects!O4+E63*Projects!O5+F63*Projects!O6+G63*Projects!O7+H63*Projects!O8+I63*Projects!O9 -> 17076398 | N63: =B63*(1-Projects!Q2)+C63*(1-Projects!Q3)+D63*(1-Projects!Q4)+E63*(1-Projects!Q5)+F63*(1-Projects!Q6)+G63*(1-Projects!Q7)+H63*(1-Projects!Q8)+I63*(1-Projects!Q9) -> 0 | O63: =IF(AND(J63<=Inputs!B2,L63>=Inputs!B3,M63>=Inputs!B18,N63=0),1,0) -> 0 | P63: =IF(O63=1,L63,-1) -> -1 | Q63: =IF(AND(O63=1,L63=MAX(P$2:P$257)),M63,-1E+99) -> -1e+99
A64: 62 | B64: 0 | C64: 0 | D64: 1 | E64: 1 | F64: 1 | G64: 1 | H64: 1 | I64: 0 | J64: =B64*Projects!N2+C64*Projects!N3+D64*Projects!N4+E64*Projects!N5+F64*Projects!N6+G64*Projects!N7+H64*Projects!N8+I64*Projects!N9 -> 19400000 | K64: =B64*Projects!C2+C64*Projects!C3+D64*Projects!C4+E64*Projects!C5+F64*Projects!C6+G64*Projects!C7+H64*Projects!C8+I64*Projects!C9 -> 470 | L64: =B64*Projects!D2+C64*Projects!D3+D64*Projects!D4+E64*Projects!D5+F64*Projects!D6+G64*Projects!D7+H64*Projects!D8+I64*Projects!D9 -> 232 | M64: =B64*Projects!O2+C64*Projects!O3+D64*Projects!O4+E64*Projects!O5+F64*Projects!O6+G64*Projects!O7+H64*Projects!O8+I64*Projects!O9 -> 15655145 | N64: =B64*(1-Projects!Q2)+C64*(1-Projects!Q3)+D64*(1-Projects!Q4)+E64*(1-Projects!Q5)+F64*(1-Projects!Q6)+G64*(1-Projects!Q7)+H64*(1-Projects!Q8)+I64*(1-Projects!Q9) -> 0 | O64: =IF(AND(J64<=Inputs!B2,L64>=Inputs!B3,M64>=Inputs!B18,N64=0),1,0) -> 0 | P64: =IF(O64=1,L64,-1) -> -1 | Q64: =IF(AND(O64=1,L64=MAX(P$2:P$257)),M64,-1E+99) -> -1e+99
A65: 63 | B65: 0 | C65: 0 | D65: 1 | E65: 1 | F65: 1 | G65: 1 | H65: 1 | I65: 1 | J65: =B65*Projects!N2+C65*Projects!N3+D65*Projects!N4+E65*Projects!N5+F65*Projects!N6+G65*Projects!N7+H65*Projects!N8+I65*Projects!N9 -> 23900000 | K65: =B65*Projects!C2+C65*Projects!C3+D65*Projects!C4+E65*Projects!C5+F65*Projects!C6+G65*Projects!C7+H65*Projects!C8+I65*Projects!C9 -> 560 | L65: =B65*Projects!D2+C65*Projects!D3+D65*Projects!D4+E65*Projects!D5+F65*Projects!D6+G65*Projects!D7+H65*Projects!D8+I65*Projects!D9 -> 259 | M65: =B65*Projects!O2+C65*Projects!O3+D65*Projects!O4+E65*Projects!O5+F65*Projects!O6+G65*Projects!O7+H65*Projects!O8+I65*Projects!O9 -> 20111772 | N65: =B65*(1-Projects!Q2)+C65*(1-Projects!Q3)+D65*(1-Projects!Q4)+E65*(1-Projects!Q5)+F65*(1-Projects!Q6)+G65*(1-Projects!Q7)+H65*(1-Projects!Q8)+I65*(1-Projects!Q9) -> 0 | O65: =IF(AND(J65<=Inputs!B2,L65>=Inputs!B3,M65>=Inputs!B18,N65=0),1,0) -> 0 | P65: =IF(O65=1,L65,-1) -> -1 | Q65: =IF(AND(O65=1,L65=MAX(P$2:P$257)),M65,-1E+99) -> -1e+99
A66: 64 | B66: 0 | C66: 1 | D66: 0 | E66: 0 | F66: 0 | G66: 0 | H66: 0 | I66: 0 | J66: =B66*Projects!N2+C66*Projects!N3+D66*Projects!N4+E66*Projects!N5+F66*Projects!N6+G66*Projects!N7+H66*Projects!N8+I66*Projects!N9 -> 4300000 | K66: =B66*Projects!C2+C66*Projects!C3+D66*Projects!C4+E66*Projects!C5+F66*Projects!C6+G66*Projects!C7+H66*Projects!C8+I66*Projects!C9 -> 80 | L66: =B66*Projects!D2+C66*Projects!D3+D66*Projects!D4+E66*Projects!D5+F66*Projects!D6+G66*Projects!D7+H66*Projects!D8+I66*Projects!D9 -> 24 | M66: =B66*Projects!O2+C66*Projects!O3+D66*Projects!O4+E66*Projects!O5+F66*Projects!O6+G66*Projects!O7+H66*Projects!O8+I66*Projects!O9 -> 3779050.2 | N66: =B66*(1-Projects!Q2)+C66*(1-Projects!Q3)+D66*(1-Projects!Q4)+E66*(1-Projects!Q5)+F66*(1-Projects!Q6)+G66*(1-Projects!Q7)+H66*(1-Projects!Q8)+I66*(1-Projects!Q9) -> 0 | O66: =IF(AND(J66<=Inputs!B2,L66>=Inputs!B3,M66>=Inputs!B18,N66=0),1,0) -> 0 | P66: =IF(O66=1,L66,-1) -> -1 | Q66: =IF(AND(O66=1,L66=MAX(P$2:P$257)),M66,-1E+99) -> -1e+99
A67: 65 | B67: 0 | C67: 1 | D67: 0 | E67: 0 | F67: 0 | G67: 0 | H67: 0 | I67: 1 | J67: =B67*Projects!N2+C67*Projects!N3+D67*Projects!N4+E67*Projects!N5+F67*Projects!N6+G67*Projects!N7+H67*Projects!N8+I67*Projects!N9 -> 8800000 | K67: =B67*Projects!C2+C67*Projects!C3+D67*Projects!C4+E67*Projects!C5+F67*Projects!C6+G67*Projects!C7+H67*Projects!C8+I67*Projects!C9 -> 170 | L67: =B67*Projects!D2+C67*Projects!D3+D67*Projects!D4+E67*Projects!D5+F67*Projects!D6+G67*Projects!D7+H67*Projects!D8+I67*Projects!D9 -> 51 | M67: =B67*Projects!O2+C67*Projects!O3+D67*Projects!O4+E67*Projects!O5+F67*Projects!O6+G67*Projects!O7+H67*Projects!O8+I67*Projects!O9 -> 8235677.6 | N67: =B67*(1-Projects!Q2)+C67*(1-Projects!Q3)+D67*(1-Projects!Q4)+E67*(1-Projects!Q5)+F67*(1-Projects!Q6)+G67*(1-Projects!Q7)+H67*(1-Projects!Q8)+I67*(1-Projects!Q9) -> 0 | O67: =IF(AND(J67<=Inputs!B2,L67>=Inputs!B3,M67>=Inputs!B18,N67=0),1,0) -> 0 | P67: =IF(O67=1,L67,-1) -> -1 | Q67: =IF(AND(O67=1,L67=MAX(P$2:P$257)),M67,-1E+99) -> -1e+99
A68: 66 | B68: 0 | C68: 1 | D68: 0 | E68: 0 | F68: 0 | G68: 0 | H68: 1 | I68: 0 | J68: =B68*Projects!N2+C68*Projects!N3+D68*Projects!N4+E68*Projects!N5+F68*Projects!N6+G68*Projects!N7+H68*Projects!N8+I68*Projects!N9 -> 8400000 | K68: =B68*Projects!C2+C68*Projects!C3+D68*Projects!C4+E68*Projects!C5+F68*Projects!C6+G68*Projects!C7+H68*Projects!C8+I68*Projects!C9 -> 190 | L68: =B68*Projects!D2+C68*Projects!D3+D68*Projects!D4+E68*Projects!D5+F68*Projects!D6+G68*Projects!D7+H68*Projects!D8+I68*Projects!D9 -> 90 | M68: =B68*Projects!O2+C68*Projects!O3+D68*Projects!O4+E68*Projects!O5+F68*Projects!O6+G68*Projects!O7+H68*Projects!O8+I68*Projects!O9 -> 6814424.1 | N68: =B68*(1-Projects!Q2)+C68*(1-Projects!Q3)+D68*(1-Projects!Q4)+E68*(1-Projects!Q5)+F68*(1-Projects!Q6)+G68*(1-Projects!Q7)+H68*(1-Projects!Q8)+I68*(1-Projects!Q9) -> 0 | O68: =IF(AND(J68<=Inputs!B2,L68>=Inputs!B3,M68>=Inputs!B18,N68=0),1,0) -> 1 | P68: =IF(O68=1,L68,-1) -> 90 | Q68: =IF(AND(O68=1,L68=MAX(P$2:P$257)),M68,-1E+99) -> -1e+99
A69: 67 | B69: 0 | C69: 1 | D69: 0 | E69: 0 | F69: 0 | G69: 0 | H69: 1 | I69: 1 | J69: =B69*Projects!N2+C69*Projects!N3+D69*Projects!N4+E69*Projects!N5+F69*Projects!N6+G69*Projects!N7+H69*Projects!N8+I69*Projects!N9 -> 12900000 | K69: =B69*Projects!C2+C69*Projects!C3+D69*Projects!C4+E69*Projects!C5+F69*Projects!C6+G69*Projects!C7+H69*Projects!C8+I69*Projects!C9 -> 280 | L69: =B69*Projects!D2+C69*Projects!D3+D69*Projects!D4+E69*Projects!D5+F69*Projects!D6+G69*Projects!D7+H69*Projects!D8+I69*Projects!D9 -> 117 | M69: =B69*Projects!O2+C69*Projects!O3+D69*Projects!O4+E69*Projects!O5+F69*Projects!O6+G69*Projects!O7+H69*Projects!O8+I69*Projects!O9 -> 11271052 | N69: =B69*(1-Projects!Q2)+C69*(1-Projects!Q3)+D69*(1-Projects!Q4)+E69*(1-Projects!Q5)+F69*(1-Projects!Q6)+G69*(1-Projects!Q7)+H69*(1-Projects!Q8)+I69*(1-Projects!Q9) -> 0 | O69: =IF(AND(J69<=Inputs!B2,L69>=Inputs!B3,M69>=Inputs!B18,N69=0),1,0) -> 1 | P69: =IF(O69=1,L69,-1) -> 117 | Q69: =IF(AND(O69=1,L69=MAX(P$2:P$257)),M69,-1E+99) -> -1e+99
A70: 68 | B70: 0 | C70: 1 | D70: 0 | E70: 0 | F70: 0 | G70: 1 | H70: 0 | I70: 0 | J70: =B70*Projects!N2+C70*Projects!N3+D70*Projects!N4+E70*Projects!N5+F70*Projects!N6+G70*Projects!N7+H70*Projects!N8+I70*Projects!N9 -> 7500000 | K70: =B70*Projects!C2+C70*Projects!C3+D70*Projects!C4+E70*Projects!C5+F70*Projects!C6+G70*Projects!C7+H70*Projects!C8+I70*Projects!C9 -> 160 | L70: =B70*Projects!D2+C70*Projects!D3+D70*Projects!D4+E70*Projects!D5+F70*Projects!D6+G70*Projects!D7+H70*Projects!D8+I70*Projects!D9 -> 64 | M70: =B70*Projects!O2+C70*Projects!O3+D70*Projects!O4+E70*Projects!O5+F70*Projects!O6+G70*Projects!O7+H70*Projects!O8+I70*Projects!O9 -> 6289228.8 | N70: =B70*(1-Projects!Q2)+C70*(1-Projects!Q3)+D70*(1-Projects!Q4)+E70*(1-Projects!Q5)+F70*(1-Projects!Q6)+G70*(1-Projects!Q7)+H70*(1-Projects!Q8)+I70*(1-Projects!Q9) -> 0 | O70: =IF(AND(J70<=Inputs!B2,L70>=Inputs!B3,M70>=Inputs!B18,N70=0),1,0) -> 0 | P70: =IF(O70=1,L70,-1) -> -1 | Q70: =IF(AND(O70=1,L70=MAX(P$2:P$257)),M70,-1E+99) -> -1e+99
A71: 69 | B71: 0 | C71: 1 | D71: 0 | E71: 0 | F71: 0 | G71: 1 | H71: 0 | I71: 1 | J71: =B71*Projects!N2+C71*Projects!N3+D71*Projects!N4+E71*Projects!N5+F71*Projects!N6+G71*Projects!N7+H71*Projects!N8+I71*Projects!N9 -> 12000000 | K71: =B71*Projects!C2+C71*Projects!C3+D71*Projects!C4+E71*Projects!C5+F71*Projects!C6+G71*Projects!C7+H71*Projects!C8+I71*Projects!C9 -> 250 | L71: =B71*Projects!D2+C71*Projects!D3+D71*Projects!D4+E71*Projects!D5+F71*Projects!D6+G71*Projects!D7+H71*Projects!D8+I71*Projects!D9 -> 91 | M71: =B71*Projects!O2+C71*Projects!O3+D71*Projects!O4+E71*Projects!O5+F71*Projects!O6+G71*Projects!O7+H71*Projects!O8+I71*Projects!O9 -> 10745856 | N71: =B71*(1-Projects!Q2)+C71*(1-Projects!Q3)+D71*(1-Projects!Q4)+E71*(1-Projects!Q5)+F71*(1-Projects!Q6)+G71*(1-Projects!Q7)+H71*(1-Projects!Q8)+I71*(1-Projects!Q9) -> 0 | O71: =IF(AND(J71<=Inputs!B2,L71>=Inputs!B3,M71>=Inputs!B18,N71=0),1,0) -> 1 | P71: =IF(O71=1,L71,-1) -> 91 | Q71: =IF(AND(O71=1,L71=MAX(P$2:P$257)),M71,-1E+99) -> -1e+99
A72: 70 | B72: 0 | C72: 1 | D72: 0 | E72: 0 | F72: 0 | G72: 1 | H72: 1 | I72: 0 | J72: =B72*Projects!N2+C72*Projects!N3+D72*Projects!N4+E72*Projects!N5+F72*Projects!N6+G72*Projects!N7+H72*Projects!N8+I72*Projects!N9 -> 11600000 | K72: =B72*Projects!C2+C72*Projects!C3+D72*Projects!C4+E72*Projects!C5+F72*Projects!C6+G72*Projects!C7+H72*Projects!C8+I72*Projects!C9 -> 270 | L72: =B72*Projects!D2+C72*Projects!D3+D72*Projects!D4+E72*Projects!D5+F72*Projects!D6+G72*Projects!D7+H72*Projects!D8+I72*Projects!D9 -> 130 | M72: =B72*Projects!O2+C72*Projects!O3+D72*Projects!O4+E72*Projects!O5+F72*Projects!O6+G72*Projects!O7+H72*Projects!O8+I72*Projects!O9 -> 9324602.7 | N72: =B72*(1-Projects!Q2)+C72*(1-Projects!Q3)+D72*(1-Projects!Q4)+E72*(1-Projects!Q5)+F72*(1-Projects!Q6)+G72*(1-Projects!Q7)+H72*(1-Projects!Q8)+I72*(1-Projects!Q9) -> 0 | O72: =IF(AND(J72<=Inputs!B2,L72>=Inputs!B3,M72>=Inputs!B18,N72=0),1,0) -> 1 | P72: =IF(O72=1,L72,-1) -> 130 | Q72: =IF(AND(O72=1,L72=MAX(P$2:P$257)),M72,-1E+99) -> -1e+99
A73: 71 | B73: 0 | C73: 1 | D73: 0 | E73: 0 | F73: 0 | G73: 1 | H73: 1 | I73: 1 | J73: =B73*Projects!N2+C73*Projects!N3+D73*Projects!N4+E73*Projects!N5+F73*Projects!N6+G73*Projects!N7+H73*Projects!N8+I73*Projects!N9 -> 16100000 | K73: =B73*Projects!C2+C73*Projects!C3+D73*Projects!C4+E73*Projects!C5+F73*Projects!C6+G73*Projects!C7+H73*Projects!C8+I73*Projects!C9 -> 360 | L73: =B73*Projects!D2+C73*Projects!D3+D73*Projects!D4+E73*Projects!D5+F73*Projects!D6+G73*Projects!D7+H73*Projects!D8+I73*Projects!D9 -> 157 | M73: =B73*Projects!O2+C73*Projects!O3+D73*Projects!O4+E73*Projects!O5+F73*Projects!O6+G73*Projects!O7+H73*Projects!O8+I73*Projects!O9 -> 13781230 | N73: =B73*(1-Projects!Q2)+C73*(1-Projects!Q3)+D73*(1-Projects!Q4)+E73*(1-Projects!Q5)+F73*(1-Projects!Q6)+G73*(1-Projects!Q7)+H73*(1-Projects!Q8)+I73*(1-Projects!Q9) -> 0 | O73: =IF(AND(J73<=Inputs!B2,L73>=Inputs!B3,M73>=Inputs!B18,N73=0),1,0) -> 0 | P73: =IF(O73=1,L73,-1) -> -1 | Q73: =IF(AND(O73=1,L73=MAX(P$2:P$257)),M73,-1E+99) -> -1e+99
A74: 72 | B74: 0 | C74: 1 | D74: 0 | E74: 0 | F74: 1 | G74: 0 | H74: 0 | I74: 0 | J74: =B74*Projects!N2+C74*Projects!N3+D74*Projects!N4+E74*Projects!N5+F74*Projects!N6+G74*Projects!N7+H74*Projects!N8+I74*Projects!N9 -> 8100000 | K74: =B74*Projects!C2+C74*Projects!C3+D74*Projects!C4+E74*Projects!C5+F74*Projects!C6+G74*Projects!C7+H74*Projects!C8+I74*Projects!C9 -> 170 | L74: =B74*Projects!D2+C74*Projects!D3+D74*Projects!D4+E74*Projects!D5+F74*Projects!D6+G74*Projects!D7+H74*Projects!D8+I74*Projects!D9 -> 69 | M74: =B74*Projects!O2+C74*Projects!O3+D74*Projects!O4+E74*Projects!O5+F74*Projects!O6+G74*Projects!O7+H74*Projects!O8+I74*Projects!O9 -> 6781012.5 | N74: =B74*(1-Projects!Q2)+C74*(1-Projects!Q3)+D74*(1-Projects!Q4)+E74*(1-Projects!Q5)+F74*(1-Projects!Q6)+G74*(1-Projects!Q7)+H74*(1-Projects!Q8)+I74*(1-Projects!Q9) -> 0 | O74: =IF(AND(J74<=Inputs!B2,L74>=Inputs!B3,M74>=Inputs!B18,N74=0),1,0) -> 0 | P74: =IF(O74=1,L74,-1) -> -1 | Q74: =IF(AND(O74=1,L74=MAX(P$2:P$257)),M74,-1E+99) -> -1e+99
A75: 73 | B75: 0 | C75: 1 | D75: 0 | E75: 0 | F75: 1 | G75: 0 | H75: 0 | I75: 1 | J75: =B75*Projects!N2+C75*Projects!N3+D75*Projects!N4+E75*Projects!N5+F75*Projects!N6+G75*Projects!N7+H75*Projects!N8+I75*Projects!N9 -> 12600000 | K75: =B75*Projects!C2+C75*Projects!C3+D75*Projects!C4+E75*Projects!C5+F75*Projects!C6+G75*Projects!C7+H75*Projects!C8+I75*Projects!C9 -> 260 | L75: =B75*Projects!D2+C75*Projects!D3+D75*Projects!D4+E75*Projects!D5+F75*Projects!D6+G75*Projects!D7+H75*Projects!D8+I75*Projects!D9 -> 96 | M75: =B75*Projects!O2+C75*Projects!O3+D75*Projects!O4+E75*Projects!O5+F75*Projects!O6+G75*Projects!O7+H75*Projects!O8+I75*Projects!O9 -> 11237640 | N75: =B75*(1-Projects!Q2)+C75*(1-Projects!Q3)+D75*(1-Projects!Q4)+E75*(1-Projects!Q5)+F75*(1-Projects!Q6)+G75*(1-Projects!Q7)+H75*(1-Projects!Q8)+I75*(1-Projects!Q9) -> 0 | O75: =IF(AND(J75<=Inputs!B2,L75>=Inputs!B3,M75>=Inputs!B18,N75=0),1,0) -> 1 | P75: =IF(O75=1,L75,-1) -> 96 | Q75: =IF(AND(O75=1,L75=MAX(P$2:P$257)),M75,-1E+99) -> -1e+99
A76: 74 | B76: 0 | C76: 1 | D76: 0 | E76: 0 | F76: 1 | G76: 0 | H76: 1 | I76: 0 | J76: =B76*Projects!N2+C76*Projects!N3+D76*Projects!N4+E76*Projects!N5+F76*Projects!N6+G76*Projects!N7+H76*Projects!N8+I76*Projects!N9 -> 12200000 | K76: =B76*Projects!C2+C76*Projects!C3+D76*Projects!C4+E76*Projects!C5+F76*Projects!C6+G76*Projects!C7+H76*Projects!C8+I76*Projects!C9 -> 280 | L76: =B76*Projects!D2+C76*Projects!D3+D76*Projects!D4+E76*Projects!D5+F76*Projects!D6+G76*Projects!D7+H76*Projects!D8+I76*Projects!D9 -> 135 | M76: =B76*Projects!O2+C76*Projects!O3+D76*Projects!O4+E76*Projects!O5+F76*Projects!O6+G76*Projects!O7+H76*Projects!O8+I76*Projects!O9 -> 9816386.5 | N76: =B76*(1-Projects!Q2)+C76*(1-Projects!Q3)+D76*(1-Projects!Q4)+E76*(1-Projects!Q5)+F76*(1-Projects!Q6)+G76*(1-Projects!Q7)+H76*(1-Projects!Q8)+I76*(1-Projects!Q9) -> 0 | O76: =IF(AND(J76<=Inputs!B2,L76>=Inputs!B3,M76>=Inputs!B18,N76=0),1,0) -> 1 | P76: =IF(O76=1,L76,-1) -> 135 | Q76: =IF(AND(O76=1,L76=MAX(P$2:P$257)),M76,-1E+99) -> -1e+99
A77: 75 | B77: 0 | C77: 1 | D77: 0 | E77: 0 | F77: 1 | G77: 0 | H77: 1 | I77: 1 | J77: =B77*Projects!N2+C77*Projects!N3+D77*Projects!N4+E77*Projects!N5+F77*Projects!N6+G77*Projects!N7+H77*Projects!N8+I77*Projects!N9 -> 16700000 | K77: =B77*Projects!C2+C77*Projects!C3+D77*Projects!C4+E77*Projects!C5+F77*Projects!C6+G77*Projects!C7+H77*Projects!C8+I77*Projects!C9 -> 370 | L77: =B77*Projects!D2+C77*Projects!D3+D77*Projects!D4+E77*Projects!D5+F77*Projects!D6+G77*Projects!D7+H77*Projects!D8+I77*Projects!D9 -> 162 | M77: =B77*Projects!O2+C77*Projects!O3+D77*Projects!O4+E77*Projects!O5+F77*Projects!O6+G77*Projects!O7+H77*Projects!O8+I77*Projects!O9 -> 14273014 | N77: =B77*(1-Projects!Q2)+C77*(1-Projects!Q3)+D77*(1-Projects!Q4)+E77*(1-Projects!Q5)+F77*(1-Projects!Q6)+G77*(1-Projects!Q7)+H77*(1-Projects!Q8)+I77*(1-Projects!Q9) -> 0 | O77: =IF(AND(J77<=Inputs!B2,L77>=Inputs!B3,M77>=Inputs!B18,N77=0),1,0) -> 0 | P77: =IF(O77=1,L77,-1) -> -1 | Q77: =IF(AND(O77=1,L77=MAX(P$2:P$257)),M77,-1E+99) -> -1e+99
A78: 76 | B78: 0 | C78: 1 | D78: 0 | E78: 0 | F78: 1 | G78: 1 | H78: 0 | I78: 0 | J78: =B78*Projects!N2+C78*Projects!N3+D78*Projects!N4+E78*Projects!N5+F78*Projects!N6+G78*Projects!N7+H78*Projects!N8+I78*Projects!N9 -> 11300000 | K78: =B78*Projects!C2+C78*Projects!C3+D78*Projects!C4+E78*Projects!C5+F78*Projects!C6+G78*Projects!C7+H78*Projects!C8+I78*Projects!C9 -> 250 | L78: =B78*Projects!D2+C78*Projects!D3+D78*Projects!D4+E78*Projects!D5+F78*Projects!D6+G78*Projects!D7+H78*Projects!D8+I78*Projects!D9 -> 109 | M78: =B78*Projects!O2+C78*Projects!O3+D78*Projects!O4+E78*Projects!O5+F78*Projects!O6+G78*Projects!O7+H78*Projects!O8+I78*Projects!O9 -> 9291191.1 | N78: =B78*(1-Projects!Q2)+C78*(1-Projects!Q3)+D78*(1-Projects!Q4)+E78*(1-Projects!Q5)+F78*(1-Projects!Q6)+G78*(1-Projects!Q7)+H78*(1-Projects!Q8)+I78*(1-Projects!Q9) -> 0 | O78: =IF(AND(J78<=Inputs!B2,L78>=Inputs!B3,M78>=Inputs!B18,N78=0),1,0) -> 1 | P78: =IF(O78=1,L78,-1) -> 109 | Q78: =IF(AND(O78=1,L78=MAX(P$2:P$257)),M78,-1E+99) -> -1e+99
A79: 77 | B79: 0 | C79: 1 | D79: 0 | E79: 0 | F79: 1 | G79: 1 | H79: 0 | I79: 1 | J79: =B79*Projects!N2+C79*Projects!N3+D79*Projects!N4+E79*Projects!N5+F79*Projects!N6+G79*Projects!N7+H79*Projects!N8+I79*Projects!N9 -> 15800000 | K79: =B79*Projects!C2+C79*Projects!C3+D79*Projects!C4+E79*Projects!C5+F79*Projects!C6+G79*Projects!C7+H79*Projects!C8+I79*Projects!C9 -> 340 | L79: =B79*Projects!D2+C79*Projects!D3+D79*Projects!D4+E79*Projects!D5+F79*Projects!D6+G79*Projects!D7+H79*Projects!D8+I79*Projects!D9 -> 136 | M79: =B79*Projects!O2+C79*Projects!O3+D79*Projects!O4+E79*Projects!O5+F79*Projects!O6+G79*Projects!O7+H79*Projects!O8+I79*Projects!O9 -> 13747819 | N79: =B79*(1-Projects!Q2)+C79*(1-Projects!Q3)+D79*(1-Projects!Q4)+E79*(1-Projects!Q5)+F79*(1-Projects!Q6)+G79*(1-Projects!Q7)+H79*(1-Projects!Q8)+I79*(1-Projects!Q9) -> 0 | O79: =IF(AND(J79<=Inputs!B2,L79>=Inputs!B3,M79>=Inputs!B18,N79=0),1,0) -> 0 | P79: =IF(O79=1,L79,-1) -> -1 | Q79: =IF(AND(O79=1,L79=MAX(P$2:P$257)),M79,-1E+99) -> -1e+99
A80: 78 | B80: 0 | C80: 1 | D80: 0 | E80: 0 | F80: 1 | G80: 1 | H80: 1 | I80: 0 | J80: =B80*Projects!N2+C80*Projects!N3+D80*Projects!N4+E80*Projects!N5+F80*Projects!N6+G80*Projects!N7+H80*Projects!N8+I80*Projects!N9 -> 15400000 | K80: =B80*Projects!C2+C80*Projects!C3+D80*Projects!C4+E80*Projects!C5+F80*Projects!C6+G80*Projects!C7+H80*Projects!C8+I80*Projects!C9 -> 360 | L80: =B80*Projects!D2+C80*Projects!D3+D80*Projects!D4+E80*Projects!D5+F80*Projects!D6+G80*Projects!D7+H80*Projects!D8+I80*Projects!D9 -> 175 | M80: =B80*Projects!O2+C80*Projects!O3+D80*Projects!O4+E80*Projects!O5+F80*Projects!O6+G80*Projects!O7+H80*Projects!O8+I80*Projects!O9 -> 12326565 | N80: =B80*(1-Projects!Q2)+C80*(1-Projects!Q3)+D80*(1-Projects!Q4)+E80*(1-Projects!Q5)+F80*(1-Projects!Q6)+G80*(1-Projects!Q7)+H80*(1-Projects!Q8)+I80*(1-Projects!Q9) -> 0 | O80: =IF(AND(J80<=Inputs!B2,L80>=Inputs!B3,M80>=Inputs!B18,N80=0),1,0) -> 0 | P80: =IF(O80=1,L80,-1) -> -1 | Q80: =IF(AND(O80=1,L80=MAX(P$2:P$257)),M80,-1E+99) -> -1e+99
A81: 79 | B81: 0 | C81: 1 | D81: 0 | E81: 0 | F81: 1 | G81: 1 | H81: 1 | I81: 1 | J81: =B81*Projects!N2+C81*Projects!N3+D81*Projects!N4+E81*Projects!N5+F81*Projects!N6+G81*Projects!N7+H81*Projects!N8+I81*Projects!N9 -> 19900000 | K81: =B81*Projects!C2+C81*Projects!C3+D81*Projects!C4+E81*Projects!C5+F81*Projects!C6+G81*Projects!C7+H81*Projects!C8+I81*Projects!C9 -> 450 | L81: =B81*Projects!D2+C81*Projects!D3+D81*Projects!D4+E81*Projects!D5+F81*Projects!D6+G81*Projects!D7+H81*Projects!D8+I81*Projects!D9 -> 202 | M81: =B81*Projects!O2+C81*Projects!O3+D81*Projects!O4+E81*Projects!O5+F81*Projects!O6+G81*Projects!O7+H81*Projects!O8+I81*Projects!O9 -> 16783193 | N81: =B81*(1-Projects!Q2)+C81*(1-Projects!Q3)+D81*(1-Projects!Q4)+E81*(1-Projects!Q5)+F81*(1-Projects!Q6)+G81*(1-Projects!Q7)+H81*(1-Projects!Q8)+I81*(1-Projects!Q9) -> 0 | O81: =IF(AND(J81<=Inputs!B2,L81>=Inputs!B3,M81>=Inputs!B18,N81=0),1,0) -> 0 | P81: =IF(O81=1,L81,-1) -> -1 | Q81: =IF(AND(O81=1,L81=MAX(P$2:P$257)),M81,-1E+99) -> -1e+99
A82: 80 | B82: 0 | C82: 1 | D82: 0 | E82: 1 | F82: 0 | G82: 0 | H82: 0 | I82: 0 | J82: =B82*Projects!N2+C82*Projects!N3+D82*Projects!N4+E82*Projects!N5+F82*Projects!N6+G82*Projects!N7+H82*Projects!N8+I82*Projects!N9 -> 7700000 | K82: =B82*Projects!C2+C82*Projects!C3+D82*Projects!C4+E82*Projects!C5+F82*Projects!C6+G82*Projects!C7+H82*Projects!C8+I82*Projects!C9 -> 150 | L82: =B82*Projects!D2+C82*Projects!D3+D82*Projects!D4+E82*Projects!D5+F82*Projects!D6+G82*Projects!D7+H82*Projects!D8+I82*Projects!D9 -> 45 | M82: =B82*Projects!O2+C82*Projects!O3+D82*Projects!O4+E82*Projects!O5+F82*Projects!O6+G82*Projects!O7+H82*Projects!O8+I82*Projects!O9 -> 7095408.4 | N82: =B82*(1-Projects!Q2)+C82*(1-Projects!Q3)+D82*(1-Projects!Q4)+E82*(1-Projects!Q5)+F82*(1-Projects!Q6)+G82*(1-Projects!Q7)+H82*(1-Projects!Q8)+I82*(1-Projects!Q9) -> 0 | O82: =IF(AND(J82<=Inputs!B2,L82>=Inputs!B3,M82>=Inputs!B18,N82=0),1,0) -> 0 | P82: =IF(O82=1,L82,-1) -> -1 | Q82: =IF(AND(O82=1,L82=MAX(P$2:P$257)),M82,-1E+99) -> -1e+99
A83: 81 | B83: 0 | C83: 1 | D83: 0 | E83: 1 | F83: 0 | G83: 0 | H83: 0 | I83: 1 | J83: =B83*Projects!N2+C83*Projects!N3+D83*Projects!N4+E83*Projects!N5+F83*Projects!N6+G83*Projects!N7+H83*Projects!N8+I83*Projects!N9 -> 12200000 | K83: =B83*Projects!C2+C83*Projects!C3+D83*Projects!C4+E83*Projects!C5+F83*Projects!C6+G83*Projects!C7+H83*Projects!C8+I83*Projects!C9 -> 240 | L83: =B83*Projects!D2+C83*Projects!D3+D83*Projects!D4+E83*Projects!D5+F83*Projects!D6+G83*Projects!D7+H83*Projects!D8+I83*Projects!D9 -> 72 | M83: =B83*Projects!O2+C83*Projects!O3+D83*Projects!O4+E83*Projects!O5+F83*Projects!O6+G83*Projects!O7+H83*Projects!O8+I83*Projects!O9 -> 11552036 | N83: =B83*(1-Projects!Q2)+C83*(1-Projects!Q3)+D83*(1-Projects!Q4)+E83*(1-Projects!Q5)+F83*(1-Projects!Q6)+G83*(1-Projects!Q7)+H83*(1-Projects!Q8)+I83*(1-Projects!Q9) -> 0 | O83: =IF(AND(J83<=Inputs!B2,L83>=Inputs!B3,M83>=Inputs!B18,N83=0),1,0) -> 0 | P83: =IF(O83=1,L83,-1) -> -1 | Q83: =IF(AND(O83=1,L83=MAX(P$2:P$257)),M83,-1E+99) -> -1e+99
A84: 82 | B84: 0 | C84: 1 | D84: 0 | E84: 1 | F84: 0 | G84: 0 | H84: 1 | I84: 0 | J84: =B84*Projects!N2+C84*Projects!N3+D84*Projects!N4+E84*Projects!N5+F84*Projects!N6+G84*Projects!N7+H84*Projects!N8+I84*Projects!N9 -> 11800000 | K84: =B84*Projects!C2+C84*Projects!C3+D84*Projects!C4+E84*Projects!C5+F84*Projects!C6+G84*Projects!C7+H84*Projects!C8+I84*Projects!C9 -> 260 | L84: =B84*Projects!D2+C84*Projects!D3+D84*Projects!D4+E84*Projects!D5+F84*Projects!D6+G84*Projects!D7+H84*Projects!D8+I84*Projects!D9 -> 111 | M84: =B84*Projects!O2+C84*Projects!O3+D84*Projects!O4+E84*Projects!O5+F84*Projects!O6+G84*Projects!O7+H84*Projects!O8+I84*Projects!O9 -> 10130782 | N84: =B84*(1-Projects!Q2)+C84*(1-Projects!Q3)+D84*(1-Projects!Q4)+E84*(1-Projects!Q5)+F84*(1-Projects!Q6)+G84*(1-Projects!Q7)+H84*(1-Projects!Q8)+I84*(1-Projects!Q9) -> 0 | O84: =IF(AND(J84<=Inputs!B2,L84>=Inputs!B3,M84>=Inputs!B18,N84=0),1,0) -> 1 | P84: =IF(O84=1,L84,-1) -> 111 | Q84: =IF(AND(O84=1,L84=MAX(P$2:P$257)),M84,-1E+99) -> -1e+99
A85: 83 | B85: 0 | C85: 1 | D85: 0 | E85: 1 | F85: 0 | G85: 0 | H85: 1 | I85: 1 | J85: =B85*Projects!N2+C85*Projects!N3+D85*Projects!N4+E85*Projects!N5+F85*Projects!N6+G85*Projects!N7+H85*Projects!N8+I85*Projects!N9 -> 16300000 | K85: =B85*Projects!C2+C85*Projects!C3+D85*Projects!C4+E85*Projects!C5+F85*Projects!C6+G85*Projects!C7+H85*Projects!C8+I85*Projects!C9 -> 350 | L85: =B85*Projects!D2+C85*Projects!D3+D85*Projects!D4+E85*Projects!D5+F85*Projects!D6+G85*Projects!D7+H85*Projects!D8+I85*Projects!D9 -> 138 | M85: =B85*Projects!O2+C85*Projects!O3+D85*Projects!O4+E85*Projects!O5+F85*Projects!O6+G85*Projects!O7+H85*Projects!O8+I85*Projects!O9 -> 14587410 | N85: =B85*(1-Projects!Q2)+C85*(1-Projects!Q3)+D85*(1-Projects!Q4)+E85*(1-Projects!Q5)+F85*(1-Projects!Q6)+G85*(1-Projects!Q7)+H85*(1-Projects!Q8)+I85*(1-Projects!Q9) -> 0 | O85: =IF(AND(J85<=Inputs!B2,L85>=Inputs!B3,M85>=Inputs!B18,N85=0),1,0) -> 0 | P85: =IF(O85=1,L85,-1) -> -1 | Q85: =IF(AND(O85=1,L85=MAX(P$2:P$257)),M85,-1E+99) -> -1e+99
A86: 84 | B86: 0 | C86: 1 | D86: 0 | E86: 1 | F86: 0 | G86: 1 | H86: 0 | I86: 0 | J86: =B86*Projects!N2+C86*Projects!N3+D86*Projects!N4+E86*Projects!N5+F86*Projects!N6+G86*Projects!N7+H86*Projects!N8+I86*Projects!N9 -> 10900000 | K86: =B86*Projects!C2+C86*Projects!C3+D86*Projects!C4+E86*Projects!C5+F86*Projects!C6+G86*Projects!C7+H86*Projects!C8+I86*Projects!C9 -> 230 | L86: =B86*Projects!D2+C86*Projects!D3+D86*Projects!D4+E86*Projects!D5+F86*Projects!D6+G86*Projects!D7+H86*Projects!D8+I86*Projects!D9 -> 85 | M86: =B86*Projects!O2+C86*Projects!O3+D86*Projects!O4+E86*Projects!O5+F86*Projects!O6+G86*Projects!O7+H86*Projects!O8+I86*Projects!O9 -> 9605587 | N86: =B86*(1-Projects!Q2)+C86*(1-Projects!Q3)+D86*(1-Projects!Q4)+E86*(1-Projects!Q5)+F86*(1-Projects!Q6)+G86*(1-Projects!Q7)+H86*(1-Projects!Q8)+I86*(1-Projects!Q9) -> 0 | O86: =IF(AND(J86<=Inputs!B2,L86>=Inputs!B3,M86>=Inputs!B18,N86=0),1,0) -> 1 | P86: =IF(O86=1,L86,-1) -> 85 | Q86: =IF(AND(O86=1,L86=MAX(P$2:P$257)),M86,-1E+99) -> -1e+99
A87: 85 | B87: 0 | C87: 1 | D87: 0 | E87: 1 | F87: 0 | G87: 1 | H87: 0 | I87: 1 | J87: =B87*Projects!N2+C87*Projects!N3+D87*Projects!N4+E87*Projects!N5+F87*Projects!N6+G87*Projects!N7+H87*Projects!N8+I87*Projects!N9 -> 15400000 | K87: =B87*Projects!C2+C87*Projects!C3+D87*Projects!C4+E87*Projects!C5+F87*Projects!C6+G87*Projects!C7+H87*Projects!C8+I87*Projects!C9 -> 320 | L87: =B87*Projects!D2+C87*Projects!D3+D87*Projects!D4+E87*Projects!D5+F87*Projects!D6+G87*Projects!D7+H87*Projects!D8+I87*Projects!D9 -> 112 | M87: =B87*Projects!O2+C87*Projects!O3+D87*Projects!O4+E87*Projects!O5+F87*Projects!O6+G87*Projects!O7+H87*Projects!O8+I87*Projects!O9 -> 14062214 | N87: =B87*(1-Projects!Q2)+C87*(1-Projects!Q3)+D87*(1-Projects!Q4)+E87*(1-Projects!Q5)+F87*(1-Projects!Q6)+G87*(1-Projects!Q7)+H87*(1-Projects!Q8)+I87*(1-Projects!Q9) -> 0 | O87: =IF(AND(J87<=Inputs!B2,L87>=Inputs!B3,M87>=Inputs!B18,N87=0),1,0) -> 0 | P87: =IF(O87=1,L87,-1) -> -1 | Q87: =IF(AND(O87=1,L87=MAX(P$2:P$257)),M87,-1E+99) -> -1e+99
A88: 86 | B88: 0 | C88: 1 | D88: 0 | E88: 1 | F88: 0 | G88: 1 | H88: 1 | I88: 0 | J88: =B88*Projects!N2+C88*Projects!N3+D88*Projects!N4+E88*Projects!N5+F88*Projects!N6+G88*Projects!N7+H88*Projects!N8+I88*Projects!N9 -> 15000000 | K88: =B88*Projects!C2+C88*Projects!C3+D88*Projects!C4+E88*Projects!C5+F88*Projects!C6+G88*Projects!C7+H88*Projects!C8+I88*Projects!C9 -> 340 | L88: =B88*Projects!D2+C88*Projects!D3+D88*Projects!D4+E88*Projects!D5+F88*Projects!D6+G88*Projects!D7+H88*Projects!D8+I88*Projects!D9 -> 151 | M88: =B88*Projects!O2+C88*Projects!O3+D88*Projects!O4+E88*Projects!O5+F88*Projects!O6+G88*Projects!O7+H88*Projects!O8+I88*Projects!O9 -> 12640961 | N88: =B88*(1-Projects!Q2)+C88*(1-Projects!Q3)+D88*(1-Projects!Q4)+E88*(1-Projects!Q5)+F88*(1-Projects!Q6)+G88*(1-Projects!Q7)+H88*(1-Projects!Q8)+I88*(1-Projects!Q9) -> 0 | O88: =IF(AND(J88<=Inputs!B2,L88>=Inputs!B3,M88>=Inputs!B18,N88=0),1,0) -> 1 | P88: =IF(O88=1,L88,-1) -> 151 | Q88: =IF(AND(O88=1,L88=MAX(P$2:P$257)),M88,-1E+99) -> -1e+99
A89: 87 | B89: 0 | C89: 1 | D89: 0 | E89: 1 | F89: 0 | G89: 1 | H89: 1 | I89: 1 | J89: =B89*Projects!N2+C89*Projects!N3+D89*Projects!N4+E89*Projects!N5+F89*Projects!N6+G89*Projects!N7+H89*Projects!N8+I89*Projects!N9 -> 19500000 | K89: =B89*Projects!C2+C89*Projects!C3+D89*Projects!C4+E89*Projects!C5+F89*Projects!C6+G89*Projects!C7+H89*Projects!C8+I89*Projects!C9 -> 430 | L89: =B89*Projects!D2+C89*Projects!D3+D89*Projects!D4+E89*Projects!D5+F89*Projects!D6+G89*Projects!D7+H89*Projects!D8+I89*Projects!D9 -> 178 | M89: =B89*Projects!O2+C89*Projects!O3+D89*Projects!O4+E89*Projects!O5+F89*Projects!O6+G89*Projects!O7+H89*Projects!O8+I89*Projects!O9 -> 17097588 | N89: =B89*(1-Projects!Q2)+C89*(1-Projects!Q3)+D89*(1-Projects!Q4)+E89*(1-Projects!Q5)+F89*(1-Projects!Q6)+G89*(1-Projects!Q7)+H89*(1-Projects!Q8)+I89*(1-Projects!Q9) -> 0 | O89: =IF(AND(J89<=Inputs!B2,L89>=Inputs!B3,M89>=Inputs!B18,N89=0),1,0) -> 0 | P89: =IF(O89=1,L89,-1) -> -1 | Q89: =IF(AND(O89=1,L89=MAX(P$2:P$257)),M89,-1E+99) -> -1e+99
A90: 88 | B90: 0 | C90: 1 | D90: 0 | E90: 1 | F90: 1 | G90: 0 | H90: 0 | I90: 0 | J90: =B90*Projects!N2+C90*Projects!N3+D90*Projects!N4+E90*Projects!N5+F90*Projects!N6+G90*Projects!N7+H90*Projects!N8+I90*Projects!N9 -> 11500000 | K90: =B90*Projects!C2+C90*Projects!C3+D90*Projects!C4+E90*Projects!C5+F90*Projects!C6+G90*Projects!C7+H90*Projects!C8+I90*Projects!C9 -> 240 | L90: =B90*Projects!D2+C90*Projects!D3+D90*Projects!D4+E90*Projects!D5+F90*Projects!D6+G90*Projects!D7+H90*Projects!D8+I90*Projects!D9 -> 90 | M90: =B90*Projects!O2+C90*Projects!O3+D90*Projects!O4+E90*Projects!O5+F90*Projects!O6+G90*Projects!O7+H90*Projects!O8+I90*Projects!O9 -> 10097371 | N90: =B90*(1-Projects!Q2)+C90*(1-Projects!Q3)+D90*(1-Projects!Q4)+E90*(1-Projects!Q5)+F90*(1-Projects!Q6)+G90*(1-Projects!Q7)+H90*(1-Projects!Q8)+I90*(1-Projects!Q9) -> 0 | O90: =IF(AND(J90<=Inputs!B2,L90>=Inputs!B3,M90>=Inputs!B18,N90=0),1,0) -> 1 | P90: =IF(O90=1,L90,-1) -> 90 | Q90: =IF(AND(O90=1,L90=MAX(P$2:P$257)),M90,-1E+99) -> -1e+99
A91: 89 | B91: 0 | C91: 1 | D91: 0 | E91: 1 | F91: 1 | G91: 0 | H91: 0 | I91: 1 | J91: =B91*Projects!N2+C91*Projects!N3+D91*Projects!N4+E91*Projects!N5+F91*Projects!N6+G91*Projects!N7+H91*Projects!N8+I91*Projects!N9 -> 16000000 | K91: =B91*Projects!C2+C91*Projects!C3+D91*Projects!C4+E91*Projects!C5+F91*Projects!C6+G91*Projects!C7+H91*Projects!C8+I91*Projects!C9 -> 330 | L91: =B91*Projects!D2+C91*Projects!D3+D91*Projects!D4+E91*Projects!D5+F91*Projects!D6+G91*Projects!D7+H91*Projects!D8+I91*Projects!D9 -> 117 | M91: =B91*Projects!O2+C91*Projects!O3+D91*Projects!O4+E91*Projects!O5+F91*Projects!O6+G91*Projects!O7+H91*Projects!O8+I91*Projects!O9 -> 14553998 | N91: =B91*(1-Projects!Q2)+C91*(1-Projects!Q3)+D91*(1-Projects!Q4)+E91*(1-Projects!Q5)+F91*(1-Projects!Q6)+G91*(1-Projects!Q7)+H91*(1-Projects!Q8)+I91*(1-Projects!Q9) -> 0 | O91: =IF(AND(J91<=Inputs!B2,L91>=Inputs!B3,M91>=Inputs!B18,N91=0),1,0) -> 0 | P91: =IF(O91=1,L91,-1) -> -1 | Q91: =IF(AND(O91=1,L91=MAX(P$2:P$257)),M91,-1E+99) -> -1e+99
A92: 90 | B92: 0 | C92: 1 | D92: 0 | E92: 1 | F92: 1 | G92: 0 | H92: 1 | I92: 0 | J92: =B92*Projects!N2+C92*Projects!N3+D92*Projects!N4+E92*Projects!N5+F92*Projects!N6+G92*Projects!N7+H92*Projects!N8+I92*Projects!N9 -> 15600000 | K92: =B92*Projects!C2+C92*Projects!C3+D92*Projects!C4+E92*Projects!C5+F92*Projects!C6+G92*Projects!C7+H92*Projects!C8+I92*Projects!C9 -> 350 | L92: =B92*Projects!D2+C92*Projects!D3+D92*Projects!D4+E92*Projects!D5+F92*Projects!D6+G92*Projects!D7+H92*Projects!D8+I92*Projects!D9 -> 156 | M92: =B92*Projects!O2+C92*Projects!O3+D92*Projects!O4+E92*Projects!O5+F92*Projects!O6+G92*Projects!O7+H92*Projects!O8+I92*Projects!O9 -> 13132745 | N92: =B92*(1-Projects!Q2)+C92*(1-Projects!Q3)+D92*(1-Projects!Q4)+E92*(1-Projects!Q5)+F92*(1-Projects!Q6)+G92*(1-Projects!Q7)+H92*(1-Projects!Q8)+I92*(1-Projects!Q9) -> 0 | O92: =IF(AND(J92<=Inputs!B2,L92>=Inputs!B3,M92>=Inputs!B18,N92=0),1,0) -> 0 | P92: =IF(O92=1,L92,-1) -> -1 | Q92: =IF(AND(O92=1,L92=MAX(P$2:P$257)),M92,-1E+99) -> -1e+99
A93: 91 | B93: 0 | C93: 1 | D93: 0 | E93: 1 | F93: 1 | G93: 0 | H93: 1 | I93: 1 | J93: =B93*Projects!N2+C93*Projects!N3+D93*Projects!N4+E93*Projects!N5+F93*Projects!N6+G93*Projects!N7+H93*Projects!N8+I93*Projects!N9 -> 20100000 | K93: =B93*Projects!C2+C93*Projects!C3+D93*Projects!C4+E93*Projects!C5+F93*Projects!C6+G93*Projects!C7+H93*Projects!C8+I93*Projects!C9 -> 440 | L93: =B93*Projects!D2+C93*Projects!D3+D93*Projects!D4+E93*Projects!D5+F93*Projects!D6+G93*Projects!D7+H93*Projects!D8+I93*Projects!D9 -> 183 | M93: =B93*Projects!O2+C93*Projects!O3+D93*Projects!O4+E93*Projects!O5+F93*Projects!O6+G93*Projects!O7+H93*Projects!O8+I93*Projects!O9 -> 17589372 | N93: =B93*(1-Projects!Q2)+C93*(1-Projects!Q3)+D93*(1-Projects!Q4)+E93*(1-Projects!Q5)+F93*(1-Projects!Q6)+G93*(1-Projects!Q7)+H93*(1-Projects!Q8)+I93*(1-Projects!Q9) -> 0 | O93: =IF(AND(J93<=Inputs!B2,L93>=Inputs!B3,M93>=Inputs!B18,N93=0),1,0) -> 0 | P93: =IF(O93=1,L93,-1) -> -1 | Q93: =IF(AND(O93=1,L93=MAX(P$2:P$257)),M93,-1E+99) -> -1e+99
A94: 92 | B94: 0 | C94: 1 | D94: 0 | E94: 1 | F94: 1 | G94: 1 | H94: 0 | I94: 0 | J94: =B94*Projects!N2+C94*Projects!N3+D94*Projects!N4+E94*Projects!N5+F94*Projects!N6+G94*Projects!N7+H94*Projects!N8+I94*Projects!N9 -> 14700000 | K94: =B94*Projects!C2+C94*Projects!C3+D94*Projects!C4+E94*Projects!C5+F94*Projects!C6+G94*Projects!C7+H94*Projects!C8+I94*Projects!C9 -> 320 | L94: =B94*Projects!D2+C94*Projects!D3+D94*Projects!D4+E94*Projects!D5+F94*Projects!D6+G94*Projects!D7+H94*Projects!D8+I94*Projects!D9 -> 130 | M94: =B94*Projects!O2+C94*Projects!O3+D94*Projects!O4+E94*Projects!O5+F94*Projects!O6+G94*Projects!O7+H94*Projects!O8+I94*Projects!O9 -> 12607549 | N94: =B94*(1-Projects!Q2)+C94*(1-Projects!Q3)+D94*(1-Projects!Q4)+E94*(1-Projects!Q5)+F94*(1-Projects!Q6)+G94*(1-Projects!Q7)+H94*(1-Projects!Q8)+I94*(1-Projects!Q9) -> 0 | O94: =IF(AND(J94<=Inputs!B2,L94>=Inputs!B3,M94>=Inputs!B18,N94=0),1,0) -> 1 | P94: =IF(O94=1,L94,-1) -> 130 | Q94: =IF(AND(O94=1,L94=MAX(P$2:P$257)),M94,-1E+99) -> -1e+99
A95: 93 | B95: 0 | C95: 1 | D95: 0 | E95: 1 | F95: 1 | G95: 1 | H95: 0 | I95: 1 | J95: =B95*Projects!N2+C95*Projects!N3+D95*Projects!N4+E95*Projects!N5+F95*Projects!N6+G95*Projects!N7+H95*Projects!N8+I95*Projects!N9 -> 19200000 | K95: =B95*Projects!C2+C95*Projects!C3+D95*Projects!C4+E95*Projects!C5+F95*Projects!C6+G95*Projects!C7+H95*Projects!C8+I95*Projects!C9 -> 410 | L95: =B95*Projects!D2+C95*Projects!D3+D95*Projects!D4+E95*Projects!D5+F95*Projects!D6+G95*Projects!D7+H95*Projects!D8+I95*Projects!D9 -> 157 | M95: =B95*Projects!O2+C95*Projects!O3+D95*Projects!O4+E95*Projects!O5+F95*Projects!O6+G95*Projects!O7+H95*Projects!O8+I95*Projects!O9 -> 17064177 | N95: =B95*(1-Projects!Q2)+C95*(1-Projects!Q3)+D95*(1-Projects!Q4)+E95*(1-Projects!Q5)+F95*(1-Projects!Q6)+G95*(1-Projects!Q7)+H95*(1-Projects!Q8)+I95*(1-Projects!Q9) -> 0 | O95: =IF(AND(J95<=Inputs!B2,L95>=Inputs!B3,M95>=Inputs!B18,N95=0),1,0) -> 0 | P95: =IF(O95=1,L95,-1) -> -1 | Q95: =IF(AND(O95=1,L95=MAX(P$2:P$257)),M95,-1E+99) -> -1e+99
A96: 94 | B96: 0 | C96: 1 | D96: 0 | E96: 1 | F96: 1 | G96: 1 | H96: 1 | I96: 0 | J96: =B96*Projects!N2+C96*Projects!N3+D96*Projects!N4+E96*Projects!N5+F96*Projects!N6+G96*Projects!N7+H96*Projects!N8+I96*Projects!N9 -> 18800000 | K96: =B96*Projects!C2+C96*Projects!C3+D96*Projects!C4+E96*Projects!C5+F96*Projects!C6+G96*Projects!C7+H96*Projects!C8+I96*Projects!C9 -> 430 | L96: =B96*Projects!D2+C96*Projects!D3+D96*Projects!D4+E96*Projects!D5+F96*Projects!D6+G96*Projects!D7+H96*Projects!D8+I96*Projects!D9 -> 196 | M96: =B96*Projects!O2+C96*Projects!O3+D96*Projects!O4+E96*Projects!O5+F96*Projects!O6+G96*Projects!O7+H96*Projects!O8+I96*Projects!O9 -> 15642923 | N96: =B96*(1-Projects!Q2)+C96*(1-Projects!Q3)+D96*(1-Projects!Q4)+E96*(1-Projects!Q5)+F96*(1-Projects!Q6)+G96*(1-Projects!Q7)+H96*(1-Projects!Q8)+I96*(1-Projects!Q9) -> 0 | O96: =IF(AND(J96<=Inputs!B2,L96>=Inputs!B3,M96>=Inputs!B18,N96=0),1,0) -> 0 | P96: =IF(O96=1,L96,-1) -> -1 | Q96: =IF(AND(O96=1,L96=MAX(P$2:P$257)),M96,-1E+99) -> -1e+99
A97: 95 | B97: 0 | C97: 1 | D97: 0 | E97: 1 | F97: 1 | G97: 1 | H97: 1 | I97: 1 | J97: =B97*Projects!N2+C97*Projects!N3+D97*Projects!N4+E97*Projects!N5+F97*Projects!N6+G97*Projects!N7+H97*Projects!N8+I97*Projects!N9 -> 23300000 | K97: =B97*Projects!C2+C97*Projects!C3+D97*Projects!C4+E97*Projects!C5+F97*Projects!C6+G97*Projects!C7+H97*Projects!C8+I97*Projects!C9 -> 520 | L97: =B97*Projects!D2+C97*Projects!D3+D97*Projects!D4+E97*Projects!D5+F97*Projects!D6+G97*Projects!D7+H97*Projects!D8+I97*Projects!D9 -> 223 | M97: =B97*Projects!O2+C97*Projects!O3+D97*Projects!O4+E97*Projects!O5+F97*Projects!O6+G97*Projects!O7+H97*Projects!O8+I97*Projects!O9 -> 20099551 | N97: =B97*(1-Projects!Q2)+C97*(1-Projects!Q3)+D97*(1-Projects!Q4)+E97*(1-Projects!Q5)+F97*(1-Projects!Q6)+G97*(1-Projects!Q7)+H97*(1-Projects!Q8)+I97*(1-Projects!Q9) -> 0 | O97: =IF(AND(J97<=Inputs!B2,L97>=Inputs!B3,M97>=Inputs!B18,N97=0),1,0) -> 0 | P97: =IF(O97=1,L97,-1) -> -1 | Q97: =IF(AND(O97=1,L97=MAX(P$2:P$257)),M97,-1E+99) -> -1e+99
A98: 96 | B98: 0 | C98: 1 | D98: 1 | E98: 0 | F98: 0 | G98: 0 | H98: 0 | I98: 0 | J98: =B98*Projects!N2+C98*Projects!N3+D98*Projects!N4+E98*Projects!N5+F98*Projects!N6+G98*Projects!N7+H98*Projects!N8+I98*Projects!N9 -> 9200000 | K98: =B98*Projects!C2+C98*Projects!C3+D98*Projects!C4+E98*Projects!C5+F98*Projects!C6+G98*Projects!C7+H98*Projects!C8+I98*Projects!C9 -> 200 | L98: =B98*Projects!D2+C98*Projects!D3+D98*Projects!D4+E98*Projects!D5+F98*Projects!D6+G98*Projects!D7+H98*Projects!D8+I98*Projects!D9 -> 84 | M98: =B98*Projects!O2+C98*Projects!O3+D98*Projects!O4+E98*Projects!O5+F98*Projects!O6+G98*Projects!O7+H98*Projects!O8+I98*Projects!O9 -> 7570321.9 | N98: =B98*(1-Projects!Q2)+C98*(1-Projects!Q3)+D98*(1-Projects!Q4)+E98*(1-Projects!Q5)+F98*(1-Projects!Q6)+G98*(1-Projects!Q7)+H98*(1-Projects!Q8)+I98*(1-Projects!Q9) -> 0 | O98: =IF(AND(J98<=Inputs!B2,L98>=Inputs!B3,M98>=Inputs!B18,N98=0),1,0) -> 1 | P98: =IF(O98=1,L98,-1) -> 84 | Q98: =IF(AND(O98=1,L98=MAX(P$2:P$257)),M98,-1E+99) -> -1e+99
A99: 97 | B99: 0 | C99: 1 | D99: 1 | E99: 0 | F99: 0 | G99: 0 | H99: 0 | I99: 1 | J99: =B99*Projects!N2+C99*Projects!N3+D99*Projects!N4+E99*Projects!N5+F99*Projects!N6+G99*Projects!N7+H99*Projects!N8+I99*Projects!N9 -> 13700000 | K99: =B99*Projects!C2+C99*Projects!C3+D99*Projects!C4+E99*Projects!C5+F99*Projects!C6+G99*Projects!C7+H99*Projects!C8+I99*Projects!C9 -> 290 | L99: =B99*Projects!D2+C99*Projects!D3+D99*Projects!D4+E99*Projects!D5+F99*Projects!D6+G99*Projects!D7+H99*Projects!D8+I99*Projects!D9 -> 111 | M99: =B99*Projects!O2+C99*Projects!O3+D99*Projects!O4+E99*Projects!O5+F99*Projects!O6+G99*Projects!O7+H99*Projects!O8+I99*Projects!O9 -> 12026949 | N99: =B99*(1-Projects!Q2)+C99*(1-Projects!Q3)+D99*(1-Projects!Q4)+E99*(1-Projects!Q5)+F99*(1-Projects!Q6)+G99*(1-Projects!Q7)+H99*(1-Projects!Q8)+I99*(1-Projects!Q9) -> 0 | O99: =IF(AND(J99<=Inputs!B2,L99>=Inputs!B3,M99>=Inputs!B18,N99=0),1,0) -> 1 | P99: =IF(O99=1,L99,-1) -> 111 | Q99: =IF(AND(O99=1,L99=MAX(P$2:P$257)),M99,-1E+99) -> -1e+99
A100: 98 | B100: 0 | C100: 1 | D100: 1 | E100: 0 | F100: 0 | G100: 0 | H100: 1 | I100: 0 | J100: =B100*Projects!N2+C100*Projects!N3+D100*Projects!N4+E100*Projects!N5+F100*Projects!N6+G100*Projects!N7+H100*Projects!N8+I100*Projects!N9 -> 13300000 | K100: =B100*Projects!C2+C100*Projects!C3+D100*Projects!C4+E100*Projects!C5+F100*Projects!C6+G100*Projects!C7+H100*Projects!C8+I100*Projects!C9 -> 310 | L100: =B100*Projects!D2+C100*Projects!D3+D100*Projects!D4+E100*Projects!D5+F100*Projects!D6+G100*Projects!D7+H100*Projects!D8+I100*Projects!D9 -> 150 | M100: =B100*Projects!O2+C100*Projects!O3+D100*Projects!O4+E100*Projects!O5+F100*Projects!O6+G100*Projects!O7+H100*Projects!O8+I100*Projects!O9 -> 10605696 | N100: =B100*(1-Projects!Q2)+C100*(1-Projects!Q3)+D100*(1-Projects!Q4)+E100*(1-Projects!Q5)+F100*(1-Projects!Q6)+G100*(1-Projects!Q7)+H100*(1-Projects!Q8)+I100*(1-Projects!Q9) -> 0 | O100: =IF(AND(J100<=Inputs!B2,L100>=Inputs!B3,M100>=Inputs!B18,N100=0),1,0) -> 1 | P100: =IF(O100=1,L100,-1) -> 150 | Q100: =IF(AND(O100=1,L100=MAX(P$2:P$257)),M100,-1E+99) -> -1e+99
...

Sheet Scenarios
A1: Scenario | B1: Occupancy | C1: Capex multiplier | D1: Rent multiplier | E1: Discount rate | F1: Exit cap rate | G1: Selected investment | H1: Year 1 NOI | I1: NPV | J1: Affordable beds | K1: Planning budget check
A2: Base | B2: =Inputs!B4 -> 0.95 | C2: 1 | D2: 1 | E2: =Inputs!B9 -> 0.06 | F2: =Inputs!B10 -> 0.055 | G2: ='Executive Report'!B9*C2 -> 14500000 | H2: =(Projects!R2*(Projects!D2*Projects!E2+(Projects!C2-Projects!D2)*Projects!F2)*Inputs!B5+Projects!R3*(Projects!D3*Projects!E3+(Projects!C3-Projects!D3)*Projects!F3)*Inputs!B5+Projects!R4*(Projects!D4*Projects!E4+(Projects!C4-Projects!D4)*Projects!F4)*Inputs!B5+Projects!R5*(Projects!D5*Projects!E5+(Projects!C5-Projects!D5)*Projects!F5)*Inputs!B5+Projects!R6*(Projects!D6*Projects!E6+(Projects!C6-Projects!D6)*Projects!F6)*Inputs!B5+Projects!R7*(Projects!D7*Projects!E7+(Projects!C7-Projects!D7)*Projects!F7)*Inputs!B5+Projects!R8*(Projects!D8*Projects!E8+(Projects!C8-Projects!D8)*Projects!F8)*Inputs!B5+Projects!R9*(Projects!D9*Projects!E9+(Projects!C9-Projects!D9)*Projects!F9)*Inputs!B5)*B2*D2*(1-Inputs!B6)-'Executive Report'!B10*Inputs!B7 -> 1216467.7 | I2: =-G2+H2*(1+Inputs!B8)^0/(1+E2)^1+H2*(1+Inputs!B8)^1/(1+E2)^2+H2*(1+Inputs!B8)^2/(1+E2)^3+H2*(1+Inputs!B8)^3/(1+E2)^4+H2*(1+Inputs!B8)^4/(1+E2)^5+H2*(1+Inputs!B8)^5/(1+E2)^6+H2*(1+Inputs!B8)^6/(1+E2)^7+H2*(1+Inputs!B8)^7/(1+E2)^8+H2*(1+Inputs!B8)^8/(1+E2)^9+H2*(1+Inputs!B8)^9/(1+E2)^10+H2*(1+Inputs!B8)^10/(1+E2)^11+H2*(1+Inputs!B8)^11/(1+E2)^12+H2*(1+Inputs!B8)^12/(1+E2)^13+H2*(1+Inputs!B8)^13/(1+E2)^14+H2*(1+Inputs!B8)^14/(1+E2)^15+H2*(1+Inputs!B8)^15/(1+E2)^16+H2*(1+Inputs!B8)^16/(1+E2)^17+H2*(1+Inputs!B8)^17/(1+E2)^18+H2*(1+Inputs!B8)^18/(1+E2)^19+H2*(1+Inputs!B8)^19/(1+E2)^20+H2*(1+Inputs!B8)^20/F2*(1-Inputs!B11)/(1+E2)^20 -> 11863873 | J2: ='Executive Report'!B11 -> 172 | K2: =IF(G2<=Inputs!B2,"PASS","OVER BUDGET") -> PASS
A3: Downside | B3: 0.85 | C3: 1.15 | D3: 0.95 | E3: 0.075 | F3: 0.065 | G3: ='Executive Report'!B9*C3 -> 16675000 | H3: =(Projects!R2*(Projects!D2*Projects!E2+(Projects!C2-Projects!D2)*Projects!F2)*Inputs!B5+Projects!R3*(Projects!D3*Projects!E3+(Projects!C3-Projects!D3)*Projects!F3)*Inputs!B5+Projects!R4*(Projects!D4*Projects!E4+(Projects!C4-Projects!D4)*Projects!F4)*Inputs!B5+Projects!R5*(Projects!D5*Projects!E5+(Projects!C5-Projects!D5)*Projects!F5)*Inputs!B5+Projects!R6*(Projects!D6*Projects!E6+(Projects!C6-Projects!D6)*Projects!F6)*Inputs!B5+Projects!R7*(Projects!D7*Projects!E7+(Projects!C7-Projects!D7)*Projects!F7)*Inputs!B5+Projects!R8*(Projects!D8*Projects!E8+(Projects!C8-Projects!D8)*Projects!F8)*Inputs!B5+Projects!R9*(Projects!D9*Projects!E9+(Projects!C9-Projects!D9)*Projects!F9)*Inputs!B5)*B3*D3*(1-Inputs!B6)-'Executive Report'!B10*Inputs!B7 -> 949997.54 | I3: =-G3+H3*(1+Inputs!B8)^0/(1+E3)^1+H3*(1+Inputs!B8)^1/(1+E3)^2+H3*(1+Inputs!B8)^2/(1+E3)^3+H3*(1+Inputs!B8)^3/(1+E3)^4+H3*(1+Inputs!B8)^4/(1+E3)^5+H3*(1+Inputs!B8)^5/(1+E3)^6+H3*(1+Inputs!B8)^6/(1+E3)^7+H3*(1+Inputs!B8)^7/(1+E3)^8+H3*(1+Inputs!B8)^8/(1+E3)^9+H3*(1+Inputs!B8)^9/(1+E3)^10+H3*(1+Inputs!B8)^10/(1+E3)^11+H3*(1+Inputs!B8)^11/(1+E3)^12+H3*(1+Inputs!B8)^12/(1+E3)^13+H3*(1+Inputs!B8)^13/(1+E3)^14+H3*(1+Inputs!B8)^14/(1+E3)^15+H3*(1+Inputs!B8)^15/(1+E3)^16+H3*(1+Inputs!B8)^16/(1+E3)^17+H3*(1+Inputs!B8)^17/(1+E3)^18+H3*(1+Inputs!B8)^18/(1+E3)^19+H3*(1+Inputs!B8)^19/(1+E3)^20+H3*(1+Inputs!B8)^20/F3*(1-Inputs!B11)/(1+E3)^20 -> -434136.47 | J3: ='Executive Report'!B11 -> 172 | K3: =IF(G3<=Inputs!B2,"PASS","OVER BUDGET") -> OVER BUDGET
A4: Upside | B4: 0.98 | C4: 0.95 | D4: 1.05 | E4: 0.05 | F4: 0.05 | G4: ='Executive Report'!B9*C4 -> 13775000 | H4: =(Projects!R2*(Projects!D2*Projects!E2+(Projects!C2-Projects!D2)*Projects!F2)*Inputs!B5+Projects!R3*(Projects!D3*Projects!E3+(Projects!C3-Projects!D3)*Projects!F3)*Inputs!B5+Projects!R4*(Projects!D4*Projects!E4+(Projects!C4-Projects!D4)*Projects!F4)*Inputs!B5+Projects!R5*(Projects!D5*Projects!E5+(Projects!C5-Projects!D5)*Projects!F5)*Inputs!B5+Projects!R6*(Projects!D6*Projects!E6+(Projects!C6-Projects!D6)*Projects!F6)*Inputs!B5+Projects!R7*(Projects!D7*Projects!E7+(Projects!C7-Projects!D7)*Projects!F7)*Inputs!B5+Projects!R8*(Projects!D8*Projects!E8+(Projects!C8-Projects!D8)*Projects!F8)*Inputs!B5+Projects!R9*(Projects!D9*Projects!E9+(Projects!C9-Projects!D9)*Projects!F9)*Inputs!B5)*B4*D4*(1-Inputs!B6)-'Executive Report'!B10*Inputs!B7 -> 1364195 | I4: =-G4+H4*(1+Inputs!B8)^0/(1+E4)^1+H4*(1+Inputs!B8)^1/(1+E4)^2+H4*(1+Inputs!B8)^2/(1+E4)^3+H4*(1+Inputs!B8)^3/(1+E4)^4+H4*(1+Inputs!B8)^4/(1+E4)^5+H4*(1+Inputs!B8)^5/(1+E4)^6+H4*(1+Inputs!B8)^6/(1+E4)^7+H4*(1+Inputs!B8)^7/(1+E4)^8+H4*(1+Inputs!B8)^8/(1+E4)^9+H4*(1+Inputs!B8)^9/(1+E4)^10+H4*(1+Inputs!B8)^10/(1+E4)^11+H4*(1+Inputs!B8)^11/(1+E4)^12+H4*(1+Inputs!B8)^12/(1+E4)^13+H4*(1+Inputs!B8)^13/(1+E4)^14+H4*(1+Inputs!B8)^14/(1+E4)^15+H4*(1+Inputs!B8)^15/(1+E4)^16+H4*(1+Inputs!B8)^16/(1+E4)^17+H4*(1+Inputs!B8)^17/(1+E4)^18+H4*(1+Inputs!B8)^18/(1+E4)^19+H4*(1+Inputs!B8)^19/(1+E4)^20+H4*(1+Inputs!B8)^20/F4*(1-Inputs!B11)/(1+E4)^20 -> 21205887 | J4: ='Executive Report'!B11 -> 172 | K4: =IF(G4<=Inputs!B2,"PASS","OVER BUDGET") -> PASS
A5: Interpretation | B5: Fixed recommended base portfolio under changed financial assumptions; no scenario reoptimization.

Sheet Iterations
A1: Iteration | B1: Increment delivered | C1: Evaluation / feedback | D1: Reinvestment in next sprint | E1: Status
A2: 1 | B2: Baseline saved immediately | C2: Three candidate projects, live NOI and basic municipality registry | D2: Prioritize evidence and policy differences | E2: Saved v1.0
A3: 2 | B3: Sourced baseline saved | C3: Primary policy evidence: Brussels 20%, Ixelles 15%; no blanket quota found for 19 communes | D3: Add conditional compliance, DCF and exact portfolio enumeration | E3: Saved v1.1
A4: 3 | B4: 8-project financial / portfolio model | C4: 256 combinations compared; financial and affordability constraints separated from legal approval | D4: Stress-test selected portfolio; validate formula caches and workbook integrity | E4: Saved v2.0
A5: 4 | B5: Next course sprint | C5: Pending municipal confirmation, real costs and demand studies | D5: Update assumptions; compare changed recommendation; add financing/construction timing | E5: Future work, not claimed complete

Sheet Sources
A1: Source | B1: URL | C1: Evidence / limitations | D1: Accessed
A2: City Brussels 2021 recommendations | B2: https://www.bruxelles.be/sites/default/files/bxl/Recommandations_logements_etudiants_VBX_17juin2021.pdf | C2: 20% social student units from 30 units; policy applicability must be confirmed | D2: 2026-10-14
A3: Ixelles municipal magazine March–April 2025 | B3: https://www.ixelles.be/site/downloads/publications/infoxl-2014-/infoxl20250304.pdf | C3: 15% moderate-rent units for large kot developments; size trigger not specified in article | D3: 2026-10-14
A4: Perspective monitoring January 2026 | B4: https://perspective.brussels/fr/actualites/un-etudiant-sur-trois-trouve-un-kot-dans-un-logement-qui-lui-est-destine | C4: 11,305 dedicated units in 2025; around 37,000 housed students in 2022–2023; different reference years | D4: 2026-10-14
A5: Kotkompas pricing 2025–2026 | B5: https://www.diggitstudentlife.eu/sites/default/files/2025-11/Kotkompas%20Pricing%20Update%202025Q4%20-%20E_0.pdf | C5: Brussels average base rent EUR570 + EUR125 costs = EUR695 total; indicative industry sample | D5: 2026-10-14
A6: Assumption register | B6: Course model | C6: All project beds, rents, capex and financial inputs are illustrative; only cited policy shares and benchmark are sourced | D6: 2026-10-14
A7: Assumption register | B7: Course model | C7: All project beds, rents, capex and financial inputs are illustrative; only cited policy shares and benchmark are sourced | D7: 2026-10-14

Sheet Checks
A1: Check | B1: Result | C1: Interpretation
A2: Budget | B2: =IF('Executive Report'!B9<=Inputs!B2,"PASS","FAIL") -> PASS | C2: Recommended cost <= budget
A3: Target | B3: =IF('Executive Report'!B11>=Inputs!B3,"PASS","FAIL") -> PASS | C3: Affordable beds >= target
A4: Search coverage | B4: =IF(COUNTA(Portfolios!A2:A257)=256,"PASS","FAIL") -> PASS | C4: All 2^8 portfolios
A5: Planning validity | B5: =IF(SUMPRODUCT(Projects!R2:R9,Projects!Q2:Q9)=SUM(Projects!R2:R9),"PASS","FAIL") -> PASS | C5: Every recommended project satisfies planning checks
A6: Legal approval | B6: UNVERIFIED | C6: All municipalities need current project-specific confirmation; no approval inferred
A7: Formula cache | B7: PASS | C7: Cached values independently computed at build; Excel recalculates on open
