Workbook

Sheet Start
A1: STUDENT HOUSING | IXELLES / ELSENE | B1: 20-year investment appraisal
A2: Prepared for | B2: Jennifer, Sara, Madiha and team
A3: Purpose | B3: Illustrative feasibility model; replace blue assumptions with property-specific evidence.
A4: Use | B4: Inputs → scenarios → Dashboard. All cash flows in nominal EUR; annual end-year convention.
A5: Horizon | B5: Year 0 acquisition plus years 1–20 including development; sale at end of year 20.
A6: Affordability | B6: Rent is capped by an editable policy ceiling; utilities shown separately. Ceiling is a project assumption, not a statutory rent limit.
A7: Status | B7: Pre-tax, unlevered property returns. Debt KPIs are indicative; equity cash flows include debt repayment on sale.
A8: Timing | B8: Acquisition in year 0; construction equally spread over development years; rent begins the following year.
A9: Limitations | B9: No corporate/personal income tax, VAT recovery, depreciation, subsidies, refinancing or monthly draw schedules. Land/build cost include irrecoverable VAT.
A10: Decision | B10: Do not commit until planning, housing, fire, energy, tenancy and affordability checks are cleared.
A11: Sources | B11: Regulations and evidence are documented on Due diligence and Sources; unknown checks remain open.
A12: Illustrative conclusion | B12: All three scenarios have negative NPV at their assumed discount rates. Intermediate and Optimal payback require the year-20 sale; operating-only payback exceeds 20 years. These results do not describe an identified property.
... A18: Scenario labels | B18: Bad, Intermediate and Optimal are stress cases, not probabilities or best-possible achievable outcomes. Rooms and affordable headline rent stay constant across scenarios.

Sheet Inputs
A1: ASSUMPTION | B1: Bad | C1: Intermediate | D1: Optimal | E1: Unit | F1: Basis / interpretation
A2: Rooms | B2: 30 | C2: 30 | D2: 30 | E2: beds | F2: Illustrative; verify permitted capacity
A3: Acquisition price | B3: 1800000 | C3: 1800000 | D3: 1800000 | E3: EUR | F3: Illustrative property cost
A4: Acquisition costs | B4: 0.15 | C4: 0.15 | D4: 0.15 | E4: ratio | F4: Allowance incl. duties/notary/advice; not a tax determination
A5: Base construction budget | B5: 1500000 | C5: 1500000 | D5: 1500000 | E5: EUR | F5: Gross including irrecoverable VAT; quote required
A6: Construction overrun | B6: 0.25 | C6: 0.1 | D6: 0 | E6: ratio | F6: Stress assumption
A7: Professional fees / works | B7: 0.15 | C7: 0.12 | D7: 0.1 | E7: ratio | F7: Architect, engineering and permits allowance
A8: Development years | B8: 3 | C8: 2 | D8: 1 | E8: years | F8: Full non-operating years after acquisition
A9: Requested monthly room rent | B9: 550 | C9: 550 | D9: 550 | E9: EUR/month | F9: Illustrative target rent excluding utilities
A10: Affordable monthly rent ceiling | B10: 550 | C10: 550 | D10: 550 | E10: EUR/month | F10: Owner policy; validate against student budgets
A11: Rent annual growth | B11: 0.01 | C11: 0.02 | D11: 0.025 | E11: ratio | F11: Only if legally allowed; lease/PEB restrictions must be checked
A12: Ceiling annual growth | B12: 0.01 | C12: 0.02 | D12: 0.02 | E12: ratio | F12: Affordability policy assumption
A13: Occupancy | B13: 0.85 | C13: 0.94 | D13: 0.98 | E13: ratio | F13: Economic occupancy; 12 billed months assumption
... A27: Maximum housing budget share | B27: 0.6 | C27: 0.6 | D27: 0.6 | E27: ratio | F27: Owner policy; rent plus utilities / student resources

Sheet Dashboard
A1: INVESTMENT KPI | B1: Bad | C1: Intermediate | D1: Optimal | E1: Interpretation
A2: Project NPV | B2: =SUM('Bad'!I2:I22) -> -3274165.9 | C2: =SUM('Intermediate'!I2:I22) -> -2166675.5 | D2: =SUM('Optimal'!I2:I22) -> -1170564.6 | E2: Discounted unlevered cash flows, including exit
A3: Project IRR | B3: =IFERROR(IRR('Bad'!H2:H22),"No IRR") -> -0.044660672 | C3: =IFERROR(IRR('Intermediate'!H2:H22),"No IRR") -> 0.012656467 | D3: =IFERROR(IRR('Optimal'!H2:H22),"No IRR") -> 0.036540789 | E3: Annual unlevered return
A4: Payback, years | B4: =IF(COUNTIF('Bad'!J3:J22,">=0")=0,"Beyond 20",MATCH(TRUE,INDEX('Bad'!J3:J22>=0,0),0)) -> Beyond 20 | C4: =IF(COUNTIF('Intermediate'!J3:J22,">=0")=0,"Beyond 20",MATCH(TRUE,INDEX('Intermediate'!J3:J22>=0,0),0)) -> 20 | D4: =IF(COUNTIF('Optimal'!J3:J22,">=0")=0,"Beyond 20",MATCH(TRUE,INDEX('Optimal'!J3:J22>=0,0),0)) -> 20 | E4: First full year recovered; includes sale
A5: Discounted payback, years | B5: =IF(COUNTIF('Bad'!K3:K22,">=0")=0,"Beyond 20",MATCH(TRUE,INDEX('Bad'!K3:K22>=0,0),0)) -> Beyond 20 | C5: =IF(COUNTIF('Intermediate'!K3:K22,">=0")=0,"Beyond 20",MATCH(TRUE,INDEX('Intermediate'!K3:K22>=0,0),0)) -> Beyond 20 | D5: =IF(COUNTIF('Optimal'!K3:K22,">=0")=0,"Beyond 20",MATCH(TRUE,INDEX('Optimal'!K3:K22>=0,0),0)) -> Beyond 20 | E5: At scenario discount rate; includes sale
A6: Total development cost | B6: =SUM('Bad'!B2:B22) -> 4226250 | C6: =SUM('Intermediate'!C2:C22) -> 3918000 | D6: =SUM('Optimal'!D2:D22) -> 3720000 | E6: Acquisition plus works, overrun and fees
A7: Cost per bed | B7: =B6/Inputs!B2 -> 140875 | C7: =C6/Inputs!C2 -> 130600 | D7: =D6/Inputs!D2 -> 124000 | E7: Total development cost / rooms
A8: First operating NOI | B8: =INDEX('Bad'!E2:E22,Inputs!B8+2) -> 85600.8 | C8: =INDEX('Intermediate'!E2:E22,Inputs!C8+2) -> 112162.41 | D8: =INDEX('Optimal'!E2:E22,Inputs!D8+2) -> 128109.33 | E8: Before capital reserve and financing
A9: Initial yield on cost | B9: =B8/B6 -> 0.020254552 | C9: =C8/C6 -> 0.028627465 | D9: =D8/D6 -> 0.034437992 | E9: First operating NOI / cost
A10: Minimum operating DSCR | B10: =MIN(INDEX('Bad'!P2:P22,Inputs!B8+2):'Bad'!P22) -> 0.22569113 | C10: =MIN(INDEX('Intermediate'!P2:P22,Inputs!C8+2):'Intermediate'!P22) -> 0.58651557 | D10: =MIN(INDEX('Optimal'!P2:P22,Inputs!D8+2):'Optimal'!P22) -> 0.77124325 | E10: NOI less capital reserve / debt service
A11: Equity IRR | B11: =IFERROR(IRR('Bad'!O2:O22),"No IRR") -> -0.24977336 | C11: =IFERROR(IRR('Intermediate'!O2:O22),"No IRR") -> -0.0065137831 | D11: =IFERROR(IRR('Optimal'!O2:O22),"No IRR") -> 0.034787278 | E11: Includes loan draw, service and exit repayment; no bridge costs
A12: Exit value net of selling costs | B12: ='Bad'!G22 -> 1102975.2 | C12: ='Intermediate'!G22 -> 2746646.6 | D12: ='Optimal'!G22 -> 3850494.3 | E12: Capitalized year-21 NOI
A13: Exit share of PV inflows | B13: ='Bad'!G22/(1+Inputs!B21)^20/SUMPRODUCT(('Bad'!E2:E22-'Bad'!F2:F22+'Bad'!G2:G22)/(1+Inputs!B21)^'Bad'!A2:A22) -> 0.34164233 | C13: ='Intermediate'!G22/(1+Inputs!C21)^20/SUMPRODUCT(('Intermediate'!E2:E22-'Intermediate'!F2:F22+'Intermediate'!G2:G22)/(1+Inputs!C21)^'Intermediate'!A2:A22) -> 0.41384132 | D13: ='Optimal'!G22/(1+Inputs!D21)^20/SUMPRODUCT(('Optimal'!E2:E22-'Optimal'!F2:F22+'Optimal'!G2:G22)/(1+Inputs!D21)^'Optimal'!A2:A22) -> 0.44625512 | E13: High share signals dependence on exit value
A14: Student housing budget share | B14: =(MIN(Inputs!B9,Inputs!B10)+Inputs!B26)/Inputs!B25 -> 0.59090909 | C14: =(MIN(Inputs!C9,Inputs!C10)+Inputs!C26)/Inputs!C25 -> 0.58181818 | D14: =(MIN(Inputs!D9,Inputs!D10)+Inputs!D26)/Inputs!D25 -> 0.57272727 | E14: First operating-year rent plus utilities / assumed budget
A15: Affordability policy | B15: =IF(B14<=Inputs!B27,"Pass","Fail") -> Pass | C15: =IF(C14<=Inputs!C27,"Pass","Fail") -> Pass | D15: =IF(D14<=Inputs!D27,"Pass","Fail") -> Pass | E15: Budget share ceiling; not proof of legal rent compliance
A16: Operating break-even occupancy | B16: =(Inputs!B15+Inputs!B2*Inputs!B18)/(Inputs!B2*12*MIN(Inputs!B9,Inputs!B10)*(1-Inputs!B14)*(1-Inputs!B16)) -> 0.41002812 | C16: =(Inputs!C15+Inputs!C2*Inputs!C18)/(Inputs!C2*12*MIN(Inputs!C9,Inputs!C10)*(1-Inputs!C14)*(1-Inputs!C16)) -> 0.33976855 | D16: =(Inputs!D15+Inputs!D2*Inputs!D18)/(Inputs!D2*12*MIN(Inputs!D9,Inputs!D10)*(1-Inputs!D14)*(1-Inputs!D16)) -> 0.28663818 | E16: First operating year; includes capital reserve, excludes debt
A17: Development / operating years | B17: =Inputs!B8&" / "&(20-Inputs!B8) -> 3 / 17 | C17: =Inputs!C8&" / "&(20-Inputs!C8) -> 2 / 18 | D17: =Inputs!D8&" / "&(20-Inputs!D8) -> 1 / 19 | E17: 20-year total excludes year 0
A18: Investment screen | B18: =IF(AND(B2>0,ISNUMBER(B3),B3>Inputs!B21,B10>=1.2,B15="Pass"),"Financial screen passes","Review / reject") -> Review / reject | C18: =IF(AND(C2>0,ISNUMBER(C3),C3>Inputs!C21,C10>=1.2,C15="Pass"),"Financial screen passes","Review / reject") -> Review / reject | D18: =IF(AND(D2>0,ISNUMBER(D3),D3>Inputs!D21,D10>=1.2,D15="Pass"),"Financial screen passes","Review / reject") -> Review / reject | E18: Illustrative thresholds; ALL regulatory checks still required
A19: Operating-only payback | B19: =IF(COUNTIF('Bad'!Q3:Q22,">=0")=0,"Beyond 20",MATCH(TRUE,INDEX('Bad'!Q3:Q22>=0,0),0)) -> Beyond 20 | C19: =IF(COUNTIF('Intermediate'!Q3:Q22,">=0")=0,"Beyond 20",MATCH(TRUE,INDEX('Intermediate'!Q3:Q22>=0,0),0)) -> Beyond 20 | D19: =IF(COUNTIF('Optimal'!Q3:Q22,">=0")=0,"Beyond 20",MATCH(TRUE,INDEX('Optimal'!Q3:Q22>=0,0),0)) -> Beyond 20 | E19: Calculated below with sale excluded; full-year convention
A20: Regulatory decision gate | B20: OPEN | C20: OPEN | D20: OPEN | E20: No acquisition commitment before all required evidence is cleared

Sheet Bad
A1: YEAR | B1: Build spend | C1: Collected rent | D1: Owner costs | E1: NOI | F1: Capital reserve | G1: Exit proceeds | H1: Project cash flow | I1: Discounted CF | J1: Cumulative CF | K1: Cumulative discounted | L1: Debt draw | M1: Debt service | N1: Closing debt | O1: Equity cash flow | P1: DSCR | Q1: Cumulative excluding sale | R1: Discounted cash flow check
A2: 0 | B2: =IF(A2=0,Inputs!$B$3*(1+Inputs!$B$4),IF(A2<=Inputs!$B$8,Inputs!$B$5*(1+Inputs!$B$6)*(1+Inputs!$B$7)/Inputs!$B$8,0)) -> 2070000 | C2: =IF(A2>Inputs!$B$8,Inputs!$B$2*12*MIN(Inputs!$B$9*(1+Inputs!$B$11)^(A2-Inputs!$B$8-1),Inputs!$B$10*(1+Inputs!$B$12)^(A2-Inputs!$B$8-1))*Inputs!$B$13*(1-Inputs!$B$14),0) -> 0 | D2: =IF(C2>0,Inputs!$B$15*(1+Inputs!$B$17)^(A2-Inputs!$B$8-1)+C2*Inputs!$B$16,0) -> 0 | E2: =C2-D2 -> 0 | F2: =IF(C2>0,Inputs!$B$2*Inputs!$B$18*(1+Inputs!$B$17)^(A2-Inputs!$B$8-1),0) -> 0 | G2: =IF(A2=20,MAX(0,(Inputs!$B$2*12*MIN(Inputs!$B$9*(1+Inputs!$B$11)^(20-Inputs!$B$8),Inputs!$B$10*(1+Inputs!$B$12)^(20-Inputs!$B$8))*Inputs!$B$13*(1-Inputs!$B$14))*(1-Inputs!$B$16)-Inputs!$B$15*(1+Inputs!$B$17)^(20-Inputs!$B$8))/Inputs!$B$19*(1-Inputs!$B$20),0) -> 0 | H2: =E2-F2-B2+G2 -> -2070000 | I2: =H2/(1+Inputs!$B$21)^A2 -> -2070000 | J2: =SUM(H$2:H2) -> -2070000 | K2: =SUM(I$2:I2) -> -2070000 | L2: =IF(A2=Inputs!$B$8,SUM(B$2:B$22)*Inputs!$B$22,0) -> 0 | M2: =IF(AND(A2>Inputs!$B$8,A2<=Inputs!$B$8+Inputs!$B$24),-PMT(Inputs!$B$23,Inputs!$B$24,SUM(B$2:B$22)*Inputs!$B$22),0) -> 0 | N2: =L2 -> 0 | O2: =H2+L2-M2-IF(A2=20,N2,0) -> -2070000 | P2: =IF(M2>0,(E2-F2)/M2,0) -> 0 | Q2: =J2-SUM(G$2:G2) -> -2070000 | R2: =H2-(E2-F2-B2+G2) -> 0
A3: 1 | B3: =IF(A3=0,Inputs!$B$3*(1+Inputs!$B$4),IF(A3<=Inputs!$B$8,Inputs!$B$5*(1+Inputs!$B$6)*(1+Inputs!$B$7)/Inputs!$B$8,0)) -> 718750 | C3: =IF(A3>Inputs!$B$8,Inputs!$B$2*12*MIN(Inputs!$B$9*(1+Inputs!$B$11)^(A3-Inputs!$B$8-1),Inputs!$B$10*(1+Inputs!$B$12)^(A3-Inputs!$B$8-1))*Inputs!$B$13*(1-Inputs!$B$14),0) -> 0 | D3: =IF(C3>0,Inputs!$B$15*(1+Inputs!$B$17)^(A3-Inputs!$B$8-1)+C3*Inputs!$B$16,0) -> 0 | E3: =C3-D3 -> 0 | F3: =IF(C3>0,Inputs!$B$2*Inputs!$B$18*(1+Inputs!$B$17)^(A3-Inputs!$B$8-1),0) -> 0 | G3: =IF(A3=20,MAX(0,(Inputs!$B$2*12*MIN(Inputs!$B$9*(1+Inputs!$B$11)^(20-Inputs!$B$8),Inputs!$B$10*(1+Inputs!$B$12)^(20-Inputs!$B$8))*Inputs!$B$13*(1-Inputs!$B$14))*(1-Inputs!$B$16)-Inputs!$B$15*(1+Inputs!$B$17)^(20-Inputs!$B$8))/Inputs!$B$19*(1-Inputs!$B$20),0) -> 0 | H3: =E3-F3-B3+G3 -> -718750 | I3: =H3/(1+Inputs!$B$21)^A3 -> -662442.4 | J3: =SUM(H$2:H3) -> -2788750 | K3: =SUM(I$2:I3) -> -2732442.4 | L3: =IF(A3=Inputs!$B$8,SUM(B$2:B$22)*Inputs!$B$22,0) -> 0 | M3: =IF(AND(A3>Inputs!$B$8,A3<=Inputs!$B$8+Inputs!$B$24),-PMT(Inputs!$B$23,Inputs!$B$24,SUM(B$2:B$22)*Inputs!$B$22),0) -> 0 | N3: =MAX(0,N2*(1+IF(M3>0,Inputs!$B$23,0))+L3-M3) -> 0 | O3: =H3+L3-M3-IF(A3=20,N3,0) -> -718750 | P3: =IF(M3>0,(E3-F3)/M3,0) -> 0 | Q3: =J3-SUM(G$2:G3) -> -2788750 | R3: =H3-(E3-F3-B3+G3) -> 0
A4: 2 | B4: =IF(A4=0,Inputs!$B$3*(1+Inputs!$B$4),IF(A4<=Inputs!$B$8,Inputs!$B$5*(1+Inputs!$B$6)*(1+Inputs!$B$7)/Inputs!$B$8,0)) -> 718750 | C4: =IF(A4>Inputs!$B$8,Inputs!$B$2*12*MIN(Inputs!$B$9*(1+Inputs!$B$11)^(A4-Inputs!$B$8-1),Inputs!$B$10*(1+Inputs!$B$12)^(A4-Inputs!$B$8-1))*Inputs!$B$13*(1-Inputs!$B$14),0) -> 0 | D4: =IF(C4>0,Inputs!$B$15*(1+Inputs!$B$17)^(A4-Inputs!$B$8-1)+C4*Inputs!$B$16,0) -> 0 | E4: =C4-D4 -> 0 | F4: =IF(C4>0,Inputs!$B$2*Inputs!$B$18*(1+Inputs!$B$17)^(A4-Inputs!$B$8-1),0) -> 0 | G4: =IF(A4=20,MAX(0,(Inputs!$B$2*12*MIN(Inputs!$B$9*(1+Inputs!$B$11)^(20-Inputs!$B$8),Inputs!$B$10*(1+Inputs!$B$12)^(20-Inputs!$B$8))*Inputs!$B$13*(1-Inputs!$B$14))*(1-Inputs!$B$16)-Inputs!$B$15*(1+Inputs!$B$17)^(20-Inputs!$B$8))/Inputs!$B$19*(1-Inputs!$B$20),0) -> 0 | H4: =E4-F4-B4+G4 -> -718750 | I4: =H4/(1+Inputs!$B$21)^A4 -> -610545.99 | J4: =SUM(H$2:H4) -> -3507500 | K4: =SUM(I$2:I4) -> -3342988.4 | L4: =IF(A4=Inputs!$B$8,SUM(B$2:B$22)*Inputs!$B$22,0) -> 0 | M4: =IF(AND(A4>Inputs!$B$8,A4<=Inputs!$B$8+Inputs!$B$24),-PMT(Inputs!$B$23,Inputs!$B$24,SUM(B$2:B$22)*Inputs!$B$22),0) -> 0 | N4: =MAX(0,N3*(1+IF(M4>0,Inputs!$B$23,0))+L4-M4) -> 0 | O4: =H4+L4-M4-IF(A4=20,N4,0) -> -718750 | P4: =IF(M4>0,(E4-F4)/M4,0) -> 0 | Q4: =J4-SUM(G$2:G4) -> -3507500 | R4: =H4-(E4-F4-B4+G4) -> 0
A5: 3 | B5: =IF(A5=0,Inputs!$B$3*(1+Inputs!$B$4),IF(A5<=Inputs!$B$8,Inputs!$B$5*(1+Inputs!$B$6)*(1+Inputs!$B$7)/Inputs!$B$8,0)) -> 718750 | C5: =IF(A5>Inputs!$B$8,Inputs!$B$2*12*MIN(Inputs!$B$9*(1+Inputs!$B$11)^(A5-Inputs!$B$8-1),Inputs!$B$10*(1+Inputs!$B$12)^(A5-Inputs!$B$8-1))*Inputs!$B$13*(1-Inputs!$B$14),0) -> 0 | D5: =IF(C5>0,Inputs!$B$15*(1+Inputs!$B$17)^(A5-Inputs!$B$8-1)+C5*Inputs!$B$16,0) -> 0 | E5: =C5-D5 -> 0 | F5: =IF(C5>0,Inputs!$B$2*Inputs!$B$18*(1+Inputs!$B$17)^(A5-Inputs!$B$8-1),0) -> 0 | G5: =IF(A5=20,MAX(0,(Inputs!$B$2*12*MIN(Inputs!$B$9*(1+Inputs!$B$11)^(20-Inputs!$B$8),Inputs!$B$10*(1+Inputs!$B$12)^(20-Inputs!$B$8))*Inputs!$B$13*(1-Inputs!$B$14))*(1-Inputs!$B$16)-Inputs!$B$15*(1+Inputs!$B$17)^(20-Inputs!$B$8))/Inputs!$B$19*(1-Inputs!$B$20),0) -> 0 | H5: =E5-F5-B5+G5 -> -718750 | I5: =H5/(1+Inputs!$B$21)^A5 -> -562715.2 | J5: =SUM(H$2:H5) -> -4226250 | K5: =SUM(I$2:I5) -> -3905703.6 | L5: =IF(A5=Inputs!$B$8,SUM(B$2:B$22)*Inputs!$B$22,0) -> 2324437.5 | M5: =IF(AND(A5>Inputs!$B$8,A5<=Inputs!$B$8+Inputs!$B$24),-PMT(Inputs!$B$23,Inputs!$B$24,SUM(B$2:B$22)*Inputs!$B$22),0) -> 0 | N5: =MAX(0,N4*(1+IF(M5>0,Inputs!$B$23,0))+L5-M5) -> 2324437.5 | O5: =H5+L5-M5-IF(A5=20,N5,0) -> 1605687.5 | P5: =IF(M5>0,(E5-F5)/M5,0) -> 0 | Q5: =J5-SUM(G$2:G5) -> -4226250 | R5: =H5-(E5-F5-B5+G5) -> 0
A6: 4 | B6: =IF(A6=0,Inputs!$B$3*(1+Inputs!$B$4),IF(A6<=Inputs!$B$8,Inputs!$B$5*(1+Inputs!$B$6)*(1+Inputs!$B$7)/Inputs!$B$8,0)) -> 0 | C6: =IF(A6>Inputs!$B$8,Inputs!$B$2*12*MIN(Inputs!$B$9*(1+Inputs!$B$11)^(A6-Inputs!$B$8-1),Inputs!$B$10*(1+Inputs!$B$12)^(A6-Inputs!$B$8-1))*Inputs!$B$13*(1-Inputs!$B$14),0) -> 163251 | D6: =IF(C6>0,Inputs!$B$15*(1+Inputs!$B$17)^(A6-Inputs!$B$8-1)+C6*Inputs!$B$16,0) -> 77650.2 | E6: =C6-D6 -> 85600.8 | F6: =IF(C6>0,Inputs!$B$2*Inputs!$B$18*(1+Inputs!$B$17)^(A6-Inputs!$B$8-1),0) -> 18000 | G6: =IF(A6=20,MAX(0,(Inputs!$B$2*12*MIN(Inputs!$B$9*(1+Inputs!$B$11)^(20-Inputs!$B$8),Inputs!$B$10*(1+Inputs!$B$12)^(20-Inputs!$B$8))*Inputs!$B$13*(1-Inputs!$B$14))*(1-Inputs!$B$16)-Inputs!$B$15*(1+Inputs!$B$17)^(20-Inputs!$B$8))/Inputs!$B$19*(1-Inputs!$B$20),0) -> 0 | H6: =E6-F6-B6+G6 -> 67600.8 | I6: =H6/(1+Inputs!$B$21)^A6 -> 48778.999 | J6: =SUM(H$2:H6) -> -4158649.2 | K6: =SUM(I$2:I6) -> -3856924.6 | L6: =IF(A6=Inputs!$B$8,SUM(B$2:B$22)*Inputs!$B$22,0) -> 0 | M6: =IF(AND(A6>Inputs!$B$8,A6<=Inputs!$B$8+Inputs!$B$24),-PMT(Inputs!$B$23,Inputs!$B$24,SUM(B$2:B$22)*Inputs!$B$22),0) -> 194507.37 | N6: =MAX(0,N5*(1+IF(M6>0,Inputs!$B$23,0))+L6-M6) -> 2257774.2 | O6: =H6+L6-M6-IF(A6=20,N6,0) -> -126906.57 | P6: =IF(M6>0,(E6-F6)/M6,0) -> 0.34754878 | Q6: =J6-SUM(G$2:G6) -> -4158649.2 | R6: =H6-(E6-F6-B6+G6) -> 0
A7: 5 | B7: =IF(A7=0,Inputs!$B$3*(1+Inputs!$B$4),IF(A7<=Inputs!$B$8,Inputs!$B$5*(1+Inputs!$B$6)*(1+Inputs!$B$7)/Inputs!$B$8,0)) -> 0 | C7: =IF(A7>Inputs!$B$8,Inputs!$B$2*12*MIN(Inputs!$B$9*(1+Inputs!$B$11)^(A7-Inputs!$B$8-1),Inputs!$B$10*(1+Inputs!$B$12)^(A7-Inputs!$B$8-1))*Inputs!$B$13*(1-Inputs!$B$14),0) -> 164883.51 | D7: =IF(C7>0,Inputs!$B$15*(1+Inputs!$B$17)^(A7-Inputs!$B$8-1)+C7*Inputs!$B$16,0) -> 79551.702 | E7: =C7-D7 -> 85331.808 | F7: =IF(C7>0,Inputs!$B$2*Inputs!$B$18*(1+Inputs!$B$17)^(A7-Inputs!$B$8-1),0) -> 18630 | G7: =IF(A7=20,MAX(0,(Inputs!$B$2*12*MIN(Inputs!$B$9*(1+Inputs!$B$11)^(20-Inputs!$B$8),Inputs!$B$10*(1+Inputs!$B$12)^(20-Inputs!$B$8))*Inputs!$B$13*(1-Inputs!$B$14))*(1-Inputs!$B$16)-Inputs!$B$15*(1+Inputs!$B$17)^(20-Inputs!$B$8))/Inputs!$B$19*(1-Inputs!$B$20),0) -> 0 | H7: =E7-F7-B7+G7 -> 66701.808 | I7: =H7/(1+Inputs!$B$21)^A7 -> 44359.732 | J7: =SUM(H$2:H7) -> -4091947.4 | K7: =SUM(I$2:I7) -> -3812564.8 | L7: =IF(A7=Inputs!$B$8,SUM(B$2:B$22)*Inputs!$B$22,0) -> 0 | M7: =IF(AND(A7>Inputs!$B$8,A7<=Inputs!$B$8+Inputs!$B$24),-PMT(Inputs!$B$23,Inputs!$B$24,SUM(B$2:B$22)*Inputs!$B$22),0) -> 194507.37 | N7: =MAX(0,N6*(1+IF(M7>0,Inputs!$B$23,0))+L7-M7) -> 2187444.4 | O7: =H7+L7-M7-IF(A7=20,N7,0) -> -127805.56 | P7: =IF(M7>0,(E7-F7)/M7,0) -> 0.34292689 | Q7: =J7-SUM(G$2:G7) -> -4091947.4 | R7: =H7-(E7-F7-B7+G7) -> 0
A8: 6 | B8: =IF(A8=0,Inputs!$B$3*(1+Inputs!$B$4),IF(A8<=Inputs!$B$8,Inputs!$B$5*(1+Inputs!$B$6)*(1+Inputs!$B$7)/Inputs!$B$8,0)) -> 0 | C8: =IF(A8>Inputs!$B$8,Inputs!$B$2*12*MIN(Inputs!$B$9*(1+Inputs!$B$11)^(A8-Inputs!$B$8-1),Inputs!$B$10*(1+Inputs!$B$12)^(A8-Inputs!$B$8-1))*Inputs!$B$13*(1-Inputs!$B$14),0) -> 166532.35 | D8: =IF(C8>0,Inputs!$B$15*(1+Inputs!$B$17)^(A8-Inputs!$B$8-1)+C8*Inputs!$B$16,0) -> 81511.594 | E8: =C8-D8 -> 85020.751 | F8: =IF(C8>0,Inputs!$B$2*Inputs!$B$18*(1+Inputs!$B$17)^(A8-Inputs!$B$8-1),0) -> 19282.05 | G8: =IF(A8=20,MAX(0,(Inputs!$B$2*12*MIN(Inputs!$B$9*(1+Inputs!$B$11)^(20-Inputs!$B$8),Inputs!$B$10*(1+Inputs!$B$12)^(20-Inputs!$B$8))*Inputs!$B$13*(1-Inputs!$B$14))*(1-Inputs!$B$16)-Inputs!$B$15*(1+Inputs!$B$17)^(20-Inputs!$B$8))/Inputs!$B$19*(1-Inputs!$B$20),0) -> 0 | H8: =E8-F8-B8+G8 -> 65738.701 | I8: =H8/(1+Inputs!$B$21)^A8 -> 40294.214 | J8: =SUM(H$2:H8) -> -4026208.7 | K8: =SUM(I$2:I8) -> -3772270.6 | L8: =IF(A8=Inputs!$B$8,SUM(B$2:B$22)*Inputs!$B$22,0) -> 0 | M8: =IF(AND(A8>Inputs!$B$8,A8<=Inputs!$B$8+Inputs!$B$24),-PMT(Inputs!$B$23,Inputs!$B$24,SUM(B$2:B$22)*Inputs!$B$22),0) -> 194507.37 | N8: =MAX(0,N7*(1+IF(M8>0,Inputs!$B$23,0))+L8-M8) -> 2113246.5 | O8: =H8+L8-M8-IF(A8=20,N8,0) -> -128768.67 | P8: =IF(M8>0,(E8-F8)/M8,0) -> 0.33797537 | Q8: =J8-SUM(G$2:G8) -> -4026208.7 | R8: =H8-(E8-F8-B8+G8) -> 0
A9: 7 | B9: =IF(A9=0,Inputs!$B$3*(1+Inputs!$B$4),IF(A9<=Inputs!$B$8,Inputs!$B$5*(1+Inputs!$B$6)*(1+Inputs!$B$7)/Inputs!$B$8,0)) -> 0 | C9: =IF(A9>Inputs!$B$8,Inputs!$B$2*12*MIN(Inputs!$B$9*(1+Inputs!$B$11)^(A9-Inputs!$B$8-1),Inputs!$B$10*(1+Inputs!$B$12)^(A9-Inputs!$B$8-1))*Inputs!$B$13*(1-Inputs!$B$14),0) -> 168197.67 | D9: =IF(C9>0,Inputs!$B$15*(1+Inputs!$B$17)^(A9-Inputs!$B$8-1)+C9*Inputs!$B$16,0) -> 83531.838 | E9: =C9-D9 -> 84665.83 | F9: =IF(C9>0,Inputs!$B$2*Inputs!$B$18*(1+Inputs!$B$17)^(A9-Inputs!$B$8-1),0) -> 19956.922 | G9: =IF(A9=20,MAX(0,(Inputs!$B$2*12*MIN(Inputs!$B$9*(1+Inputs!$B$11)^(20-Inputs!$B$8),Inputs!$B$10*(1+Inputs!$B$12)^(20-Inputs!$B$8))*Inputs!$B$13*(1-Inputs!$B$14))*(1-Inputs!$B$16)-Inputs!$B$15*(1+Inputs!$B$17)^(20-Inputs!$B$8))/Inputs!$B$19*(1-Inputs!$B$20),0) -> 0 | H9: =E9-F9-B9+G9 -> 64708.909 | I9: =H9/(1+Inputs!$B$21)^A9 -> 36555.768 | J9: =SUM(H$2:H9) -> -3961499.8 | K9: =SUM(I$2:I9) -> -3735714.9 | L9: =IF(A9=Inputs!$B$8,SUM(B$2:B$22)*Inputs!$B$22,0) -> 0 | M9: =IF(AND(A9>Inputs!$B$8,A9<=Inputs!$B$8+Inputs!$B$24),-PMT(Inputs!$B$23,Inputs!$B$24,SUM(B$2:B$22)*Inputs!$B$22),0) -> 194507.37 | N9: =MAX(0,N8*(1+IF(M9>0,Inputs!$B$23,0))+L9-M9) -> 2034967.6 | O9: =H9+L9-M9-IF(A9=20,N9,0) -> -129798.46 | P9: =IF(M9>0,(E9-F9)/M9,0) -> 0.33268101 | Q9: =J9-SUM(G$2:G9) -> -3961499.8 | R9: =H9-(E9-F9-B9+G9) -> 0
A10: 8 | B10: =IF(A10=0,Inputs!$B$3*(1+Inputs!$B$4),IF(A10<=Inputs!$B$8,Inputs!$B$5*(1+Inputs!$B$6)*(1+Inputs!$B$7)/Inputs!$B$8,0)) -> 0 | C10: =IF(A10>Inputs!$B$8,Inputs!$B$2*12*MIN(Inputs!$B$9*(1+Inputs!$B$11)^(A10-Inputs!$B$8-1),Inputs!$B$10*(1+Inputs!$B$12)^(A10-Inputs!$B$8-1))*Inputs!$B$13*(1-Inputs!$B$14),0) -> 169879.65 | D10: =IF(C10>0,Inputs!$B$15*(1+Inputs!$B$17)^(A10-Inputs!$B$8-1)+C10*Inputs!$B$16,0) -> 85614.464 | E10: =C10-D10 -> 84265.181 | F10: =IF(C10>0,Inputs!$B$2*Inputs!$B$18*(1+Inputs!$B$17)^(A10-Inputs!$B$8-1),0) -> 20655.414 | G10: =IF(A10=20,MAX(0,(Inputs!$B$2*12*MIN(Inputs!$B$9*(1+Inputs!$B$11)^(20-Inputs!$B$8),Inputs!$B$10*(1+Inputs!$B$12)^(20-Inputs!$B$8))*Inputs!$B$13*(1-Inputs!$B$14))*(1-Inputs!$B$16)-Inputs!$B$15*(1+Inputs!$B$17)^(20-Inputs!$B$8))/Inputs!$B$19*(1-Inputs!$B$20),0) -> 0 | H10: =E10-F10-B10+G10 -> 63609.767 | I10: =H10/(1+Inputs!$B$21)^A10 -> 33119.662 | J10: =SUM(H$2:H10) -> -3897890 | K10: =SUM(I$2:I10) -> -3702595.2 | L10: =IF(A10=Inputs!$B$8,SUM(B$2:B$22)*Inputs!$B$22,0) -> 0 | M10: =IF(AND(A10>Inputs!$B$8,A10<=Inputs!$B$8+Inputs!$B$24),-PMT(Inputs!$B$23,Inputs!$B$24,SUM(B$2:B$22)*Inputs!$B$22),0) -> 194507.37 | N10: =MAX(0,N9*(1+IF(M10>0,Inputs!$B$23,0))+L10-M10) -> 1952383.5 | O10: =H10+L10-M10-IF(A10=20,N10,0) -> -130897.61 | P10: =IF(M10>0,(E10-F10)/M10,0) -> 0.32703011 | Q10: =J10-SUM(G$2:G10) -> -3897890 | R10: =H10-(E10-F10-B10+G10) -> 0
A11: 9 | B11: =IF(A11=0,Inputs!$B$3*(1+Inputs!$B$4),IF(A11<=Inputs!$B$8,Inputs!$B$5*(1+Inputs!$B$6)*(1+Inputs!$B$7)/Inputs!$B$8,0)) -> 0 | C11: =IF(A11>Inputs!$B$8,Inputs!$B$2*12*MIN(Inputs!$B$9*(1+Inputs!$B$11)^(A11-Inputs!$B$8-1),Inputs!$B$10*(1+Inputs!$B$12)^(A11-Inputs!$B$8-1))*Inputs!$B$13*(1-Inputs!$B$14),0) -> 171578.44 | D11: =IF(C11>0,Inputs!$B$15*(1+Inputs!$B$17)^(A11-Inputs!$B$8-1)+C11*Inputs!$B$16,0) -> 87761.572 | E11: =C11-D11 -> 83816.87 | F11: =IF(C11>0,Inputs!$B$2*Inputs!$B$18*(1+Inputs!$B$17)^(A11-Inputs!$B$8-1),0) -> 21378.354 | G11: =IF(A11=20,MAX(0,(Inputs!$B$2*12*MIN(Inputs!$B$9*(1+Inputs!$B$11)^(20-Inputs!$B$8),Inputs!$B$10*(1+Inputs!$B$12)^(20-Inputs!$B$8))*Inputs!$B$13*(1-Inputs!$B$14))*(1-Inputs!$B$16)-Inputs!$B$15*(1+Inputs!$B$17)^(20-Inputs!$B$8))/Inputs!$B$19*(1-Inputs!$B$20),0) -> 0 | H11: =E11-F11-B11+G11 -> 62438.516 | I11: =H11/(1+Inputs!$B$21)^A11 -> 29962.975 | J11: =SUM(H$2:H11) -> -3835451.5 | K11: =SUM(I$2:I11) -> -3672632.2 | L11: =IF(A11=Inputs!$B$8,SUM(B$2:B$22)*Inputs!$B$22,0) -> 0 | M11: =IF(AND(A11>Inputs!$B$8,A11<=Inputs!$B$8+Inputs!$B$24),-PMT(Inputs!$B$23,Inputs!$B$24,SUM(B$2:B$22)*Inputs!$B$22),0) -> 194507.37 | N11: =MAX(0,N10*(1+IF(M11>0,Inputs!$B$23,0))+L11-M11) -> 1865257.2 | O11: =H11+L11-M11-IF(A11=20,N11,0) -> -132068.86 | P11: =IF(M11>0,(E11-F11)/M11,0) -> 0.32100848 | Q11: =J11-SUM(G$2:G11) -> -3835451.5 | R11: =H11-(E11-F11-B11+G11) -> 0
A12: 10 | B12: =IF(A12=0,Inputs!$B$3*(1+Inputs!$B$4),IF(A12<=Inputs!$B$8,Inputs!$B$5*(1+Inputs!$B$6)*(1+Inputs!$B$7)/Inputs!$B$8,0)) -> 0 | C12: =IF(A12>Inputs!$B$8,Inputs!$B$2*12*MIN(Inputs!$B$9*(1+Inputs!$B$11)^(A12-Inputs!$B$8-1),Inputs!$B$10*(1+Inputs!$B$12)^(A12-Inputs!$B$8-1))*Inputs!$B$13*(1-Inputs!$B$14),0) -> 173294.23 | D12: =IF(C12>0,Inputs!$B$15*(1+Inputs!$B$17)^(A12-Inputs!$B$8-1)+C12*Inputs!$B$16,0) -> 89975.335 | E12: =C12-D12 -> 83318.891 | F12: =IF(C12>0,Inputs!$B$2*Inputs!$B$18*(1+Inputs!$B$17)^(A12-Inputs!$B$8-1),0) -> 22126.596 | G12: =IF(A12=20,MAX(0,(Inputs!$B$2*12*MIN(Inputs!$B$9*(1+Inputs!$B$11)^(20-Inputs!$B$8),Inputs!$B$10*(1+Inputs!$B$12)^(20-Inputs!$B$8))*Inputs!$B$13*(1-Inputs!$B$14))*(1-Inputs!$B$16)-Inputs!$B$15*(1+Inputs!$B$17)^(20-Inputs!$B$8))/Inputs!$B$19*(1-Inputs!$B$20),0) -> 0 | H12: =E12-F12-B12+G12 -> 61192.295 | I12: =H12/(1+Inputs!$B$21)^A12 -> 27064.46 | J12: =SUM(H$2:H12) -> -3774259.2 | K12: =SUM(I$2:I12) -> -3645567.8 | L12: =IF(A12=Inputs!$B$8,SUM(B$2:B$22)*Inputs!$B$22,0) -> 0 | M12: =IF(AND(A12>Inputs!$B$8,A12<=Inputs!$B$8+Inputs!$B$24),-PMT(Inputs!$B$23,Inputs!$B$24,SUM(B$2:B$22)*Inputs!$B$22),0) -> 194507.37 | N12: =MAX(0,N11*(1+IF(M12>0,Inputs!$B$23,0))+L12-M12) -> 1773339 | O12: =H12+L12-M12-IF(A12=20,N12,0) -> -133315.08 | P12: =IF(M12>0,(E12-F12)/M12,0) -> 0.31460142 | Q12: =J12-SUM(G$2:G12) -> -3774259.2 | R12: =H12-(E12-F12-B12+G12) -> 0
A13: 11 | B13: =IF(A13=0,Inputs!$B$3*(1+Inputs!$B$4),IF(A13<=Inputs!$B$8,Inputs!$B$5*(1+Inputs!$B$6)*(1+Inputs!$B$7)/Inputs!$B$8,0)) -> 0 | C13: =IF(A13>Inputs!$B$8,Inputs!$B$2*12*MIN(Inputs!$B$9*(1+Inputs!$B$11)^(A13-Inputs!$B$8-1),Inputs!$B$10*(1+Inputs!$B$12)^(A13-Inputs!$B$8-1))*Inputs!$B$13*(1-Inputs!$B$14),0) -> 175027.17 | D13: =IF(C13>0,Inputs!$B$15*(1+Inputs!$B$17)^(A13-Inputs!$B$8-1)+C13*Inputs!$B$16,0) -> 92258 | E13: =C13-D13 -> 82769.168 | F13: =IF(C13>0,Inputs!$B$2*Inputs!$B$18*(1+Inputs!$B$17)^(A13-Inputs!$B$8-1),0) -> 22901.027 | G13: =IF(A13=20,MAX(0,(Inputs!$B$2*12*MIN(Inputs!$B$9*(1+Inputs!$B$11)^(20-Inputs!$B$8),Inputs!$B$10*(1+Inputs!$B$12)^(20-Inputs!$B$8))*Inputs!$B$13*(1-Inputs!$B$14))*(1-Inputs!$B$16)-Inputs!$B$15*(1+Inputs!$B$17)^(20-Inputs!$B$8))/Inputs!$B$19*(1-Inputs!$B$20),0) -> 0 | H13: =E13-F13-B13+G13 -> 59868.141 | I13: =H13/(1+Inputs!$B$21)^A13 -> 24404.429 | J13: =SUM(H$2:H13) -> -3714391.1 | K13: =SUM(I$2:I13) -> -3621163.3 | L13: =IF(A13=Inputs!$B$8,SUM(B$2:B$22)*Inputs!$B$22,0) -> 0 | M13: =IF(AND(A13>Inputs!$B$8,A13<=Inputs!$B$8+Inputs!$B$24),-PMT(Inputs!$B$23,Inputs!$B$24,SUM(B$2:B$22)*Inputs!$B$22),0) -> 194507.37 | N13: =MAX(0,N12*(1+IF(M13>0,Inputs!$B$23,0))+L13-M13) -> 1676365.3 | O13: =H13+L13-M13-IF(A13=20,N13,0) -> -134639.23 | P13: =IF(M13>0,(E13-F13)/M13,0) -> 0.30779369 | Q13: =J13-SUM(G$2:G13) -> -3714391.1 | R13: =H13-(E13-F13-B13+G13) -> 0
A14: 12 | B14: =IF(A14=0,Inputs!$B$3*(1+Inputs!$B$4),IF(A14<=Inputs!$B$8,Inputs!$B$5*(1+Inputs!$B$6)*(1+Inputs!$B$7)/Inputs!$B$8,0)) -> 0 | C14: =IF(A14>Inputs!$B$8,Inputs!$B$2*12*MIN(Inputs!$B$9*(1+Inputs!$B$11)^(A14-Inputs!$B$8-1),Inputs!$B$10*(1+Inputs!$B$12)^(A14-Inputs!$B$8-1))*Inputs!$B$13*(1-Inputs!$B$14),0) -> 176777.44 | D14: =IF(C14>0,Inputs!$B$15*(1+Inputs!$B$17)^(A14-Inputs!$B$8-1)+C14*Inputs!$B$16,0) -> 94611.895 | E14: =C14-D14 -> 82165.545 | F14: =IF(C14>0,Inputs!$B$2*Inputs!$B$18*(1+Inputs!$B$17)^(A14-Inputs!$B$8-1),0) -> 23702.563 | G14: =IF(A14=20,MAX(0,(Inputs!$B$2*12*MIN(Inputs!$B$9*(1+Inputs!$B$11)^(20-Inputs!$B$8),Inputs!$B$10*(1+Inputs!$B$12)^(20-Inputs!$B$8))*Inputs!$B$13*(1-Inputs!$B$14))*(1-Inputs!$B$16)-Inputs!$B$15*(1+Inputs!$B$17)^(20-Inputs!$B$8))/Inputs!$B$19*(1-Inputs!$B$20),0) -> 0 | H14: =E14-F14-B14+G14 -> 58462.983 | I14: =H14/(1+Inputs!$B$21)^A14 -> 21964.641 | J14: =SUM(H$2:H14) -> -3655928.1 | K14: =SUM(I$2:I14) -> -3599198.7 | L14: =IF(A14=Inputs!$B$8,SUM(B$2:B$22)*Inputs!$B$22,0) -> 0 | M14: =IF(AND(A14>Inputs!$B$8,A14<=Inputs!$B$8+Inputs!$B$24),-PMT(Inputs!$B$23,Inputs!$B$24,SUM(B$2:B$22)*Inputs!$B$22),0) -> 194507.37 | N14: =MAX(0,N13*(1+IF(M14>0,Inputs!$B$23,0))+L14-M14) -> 1574058 | O14: =H14+L14-M14-IF(A14=20,N14,0) -> -136044.39 | P14: =IF(M14>0,(E14-F14)/M14,0) -> 0.30056949 | Q14: =J14-SUM(G$2:G14) -> -3655928.1 | R14: =H14-(E14-F14-B14+G14) -> 0
... A22: 20 | B22: =IF(A22=0,Inputs!$B$3*(1+Inputs!$B$4),IF(A22<=Inputs!$B$8,Inputs!$B$5*(1+Inputs!$B$6)*(1+Inputs!$B$7)/Inputs!$B$8,0)) -> 0 | C22: =IF(A22>Inputs!$B$8,Inputs!$B$2*12*MIN(Inputs!$B$9*(1+Inputs!$B$11)^(A22-Inputs!$B$8-1),Inputs!$B$10*(1+Inputs!$B$12)^(A22-Inputs!$B$8-1))*Inputs!$B$13*(1-Inputs!$B$14),0) -> 191424.64 | D22: =IF(C22>0,Inputs!$B$15*(1+Inputs!$B$17)^(A22-Inputs!$B$8-1)+C22*Inputs!$B$16,0) -> 116314.3 | E22: =C22-D22 -> 75110.337 | F22: =IF(C22>0,Inputs!$B$2*Inputs!$B$18*(1+Inputs!$B$17)^(A22-Inputs!$B$8-1),0) -> 31211.749 | G22: =IF(A22=20,MAX(0,(Inputs!$B$2*12*MIN(Inputs!$B$9*(1+Inputs!$B$11)^(20-Inputs!$B$8),Inputs!$B$10*(1+Inputs!$B$12)^(20-Inputs!$B$8))*Inputs!$B$13*(1-Inputs!$B$14))*(1-Inputs!$B$16)-Inputs!$B$15*(1+Inputs!$B$17)^(20-Inputs!$B$8))/Inputs!$B$19*(1-Inputs!$B$20),0) -> 1102975.2 | H22: =E22-F22-B22+G22 -> 1146873.7 | I22: =H22/(1+Inputs!$B$21)^A22 -> 224347.3 | J22: =SUM(H$2:H22) -> -2146660.2 | K22: =SUM(I$2:I22) -> -3274165.9 | L22: =IF(A22=Inputs!$B$8,SUM(B$2:B$22)*Inputs!$B$22,0) -> 0 | M22: =IF(AND(A22>Inputs!$B$8,A22<=Inputs!$B$8+Inputs!$B$24),-PMT(Inputs!$B$23,Inputs!$B$24,SUM(B$2:B$22)*Inputs!$B$22),0) -> 194507.37 | N22: =MAX(0,N21*(1+IF(M22>0,Inputs!$B$23,0))+L22-M22) -> 524767.93 | O22: =H22+L22-M22-IF(A22=20,N22,0) -> 427598.44 | P22: =IF(M22>0,(E22-F22)/M22,0) -> 0.22569113 | Q22: =J22-SUM(G$2:G22) -> -3249635.4 | R22: =H22-(E22-F22-B22+G22) -> 0
A25: Payback uses first nonnegative cumulative end-year; includes sale at year 20 if needed.
A26: Debt drawn at completion; bridging interest and loan fees excluded. Equity IRR is indicative.

Sheet Intermediate
A1: YEAR | B1: Build spend | C1: Collected rent | D1: Owner costs | E1: NOI | F1: Capital reserve | G1: Exit proceeds | H1: Project cash flow | I1: Discounted CF | J1: Cumulative CF | K1: Cumulative discounted | L1: Debt draw | M1: Debt service | N1: Closing debt | O1: Equity cash flow | P1: DSCR | Q1: Cumulative excluding sale | R1: Discounted cash flow check
A2: 0 | B2: =IF(A2=0,Inputs!$C$3*(1+Inputs!$C$4),IF(A2<=Inputs!$C$8,Inputs!$C$5*(1+Inputs!$C$6)*(1+Inputs!$C$7)/Inputs!$C$8,0)) -> 2070000 | C2: =IF(A2>Inputs!$C$8,Inputs!$C$2*12*MIN(Inputs!$C$9*(1+Inputs!$C$11)^(A2-Inputs!$C$8-1),Inputs!$C$10*(1+Inputs!$C$12)^(A2-Inputs!$C$8-1))*Inputs!$C$13*(1-Inputs!$C$14),0) -> 0 | D2: =IF(C2>0,Inputs!$C$15*(1+Inputs!$C$17)^(A2-Inputs!$C$8-1)+C2*Inputs!$C$16,0) -> 0 | E2: =C2-D2 -> 0 | F2: =IF(C2>0,Inputs!$C$2*Inputs!$C$18*(1+Inputs!$C$17)^(A2-Inputs!$C$8-1),0) -> 0 | G2: =IF(A2=20,MAX(0,(Inputs!$C$2*12*MIN(Inputs!$C$9*(1+Inputs!$C$11)^(20-Inputs!$C$8),Inputs!$C$10*(1+Inputs!$C$12)^(20-Inputs!$C$8))*Inputs!$C$13*(1-Inputs!$C$14))*(1-Inputs!$C$16)-Inputs!$C$15*(1+Inputs!$C$17)^(20-Inputs!$C$8))/Inputs!$C$19*(1-Inputs!$C$20),0) -> 0 | H2: =E2-F2-B2+G2 -> -2070000 | I2: =H2/(1+Inputs!$C$21)^A2 -> -2070000 | J2: =SUM(H$2:H2) -> -2070000 | K2: =SUM(I$2:I2) -> -2070000 | L2: =IF(A2=Inputs!$C$8,SUM(B$2:B$22)*Inputs!$C$22,0) -> 0 | M2: =IF(AND(A2>Inputs!$C$8,A2<=Inputs!$C$8+Inputs!$C$24),-PMT(Inputs!$C$23,Inputs!$C$24,SUM(B$2:B$22)*Inputs!$C$22),0) -> 0 | N2: =L2 -> 0 | O2: =H2+L2-M2-IF(A2=20,N2,0) -> -2070000 | P2: =IF(M2>0,(E2-F2)/M2,0) -> 0 | Q2: =J2-SUM(G$2:G2) -> -2070000 | R2: =H2-(E2-F2-B2+G2) -> 0
A3: 1 | B3: =IF(A3=0,Inputs!$C$3*(1+Inputs!$C$4),IF(A3<=Inputs!$C$8,Inputs!$C$5*(1+Inputs!$C$6)*(1+Inputs!$C$7)/Inputs!$C$8,0)) -> 924000 | C3: =IF(A3>Inputs!$C$8,Inputs!$C$2*12*MIN(Inputs!$C$9*(1+Inputs!$C$11)^(A3-Inputs!$C$8-1),Inputs!$C$10*(1+Inputs!$C$12)^(A3-Inputs!$C$8-1))*Inputs!$C$13*(1-Inputs!$C$14),0) -> 0 | D3: =IF(C3>0,Inputs!$C$15*(1+Inputs!$C$17)^(A3-Inputs!$C$8-1)+C3*Inputs!$C$16,0) -> 0 | E3: =C3-D3 -> 0 | F3: =IF(C3>0,Inputs!$C$2*Inputs!$C$18*(1+Inputs!$C$17)^(A3-Inputs!$C$8-1),0) -> 0 | G3: =IF(A3=20,MAX(0,(Inputs!$C$2*12*MIN(Inputs!$C$9*(1+Inputs!$C$11)^(20-Inputs!$C$8),Inputs!$C$10*(1+Inputs!$C$12)^(20-Inputs!$C$8))*Inputs!$C$13*(1-Inputs!$C$14))*(1-Inputs!$C$16)-Inputs!$C$15*(1+Inputs!$C$17)^(20-Inputs!$C$8))/Inputs!$C$19*(1-Inputs!$C$20),0) -> 0 | H3: =E3-F3-B3+G3 -> -924000 | I3: =H3/(1+Inputs!$C$21)^A3 -> -859534.88 | J3: =SUM(H$2:H3) -> -2994000 | K3: =SUM(I$2:I3) -> -2929534.9 | L3: =IF(A3=Inputs!$C$8,SUM(B$2:B$22)*Inputs!$C$22,0) -> 0 | M3: =IF(AND(A3>Inputs!$C$8,A3<=Inputs!$C$8+Inputs!$C$24),-PMT(Inputs!$C$23,Inputs!$C$24,SUM(B$2:B$22)*Inputs!$C$22),0) -> 0 | N3: =MAX(0,N2*(1+IF(M3>0,Inputs!$C$23,0))+L3-M3) -> 0 | O3: =H3+L3-M3-IF(A3=20,N3,0) -> -924000 | P3: =IF(M3>0,(E3-F3)/M3,0) -> 0 | Q3: =J3-SUM(G$2:G3) -> -2994000 | R3: =H3-(E3-F3-B3+G3) -> 0
A4: 2 | B4: =IF(A4=0,Inputs!$C$3*(1+Inputs!$C$4),IF(A4<=Inputs!$C$8,Inputs!$C$5*(1+Inputs!$C$6)*(1+Inputs!$C$7)/Inputs!$C$8,0)) -> 924000 | C4: =IF(A4>Inputs!$C$8,Inputs!$C$2*12*MIN(Inputs!$C$9*(1+Inputs!$C$11)^(A4-Inputs!$C$8-1),Inputs!$C$10*(1+Inputs!$C$12)^(A4-Inputs!$C$8-1))*Inputs!$C$13*(1-Inputs!$C$14),0) -> 0 | D4: =IF(C4>0,Inputs!$C$15*(1+Inputs!$C$17)^(A4-Inputs!$C$8-1)+C4*Inputs!$C$16,0) -> 0 | E4: =C4-D4 -> 0 | F4: =IF(C4>0,Inputs!$C$2*Inputs!$C$18*(1+Inputs!$C$17)^(A4-Inputs!$C$8-1),0) -> 0 | G4: =IF(A4=20,MAX(0,(Inputs!$C$2*12*MIN(Inputs!$C$9*(1+Inputs!$C$11)^(20-Inputs!$C$8),Inputs!$C$10*(1+Inputs!$C$12)^(20-Inputs!$C$8))*Inputs!$C$13*(1-Inputs!$C$14))*(1-Inputs!$C$16)-Inputs!$C$15*(1+Inputs!$C$17)^(20-Inputs!$C$8))/Inputs!$C$19*(1-Inputs!$C$20),0) -> 0 | H4: =E4-F4-B4+G4 -> -924000 | I4: =H4/(1+Inputs!$C$21)^A4 -> -799567.33 | J4: =SUM(H$2:H4) -> -3918000 | K4: =SUM(I$2:I4) -> -3729102.2 | L4: =IF(A4=Inputs!$C$8,SUM(B$2:B$22)*Inputs!$C$22,0) -> 2154900 | M4: =IF(AND(A4>Inputs!$C$8,A4<=Inputs!$C$8+Inputs!$C$24),-PMT(Inputs!$C$23,Inputs!$C$24,SUM(B$2:B$22)*Inputs!$C$22),0) -> 0 | N4: =MAX(0,N3*(1+IF(M4>0,Inputs!$C$23,0))+L4-M4) -> 2154900 | O4: =H4+L4-M4-IF(A4=20,N4,0) -> 1230900 | P4: =IF(M4>0,(E4-F4)/M4,0) -> 0 | Q4: =J4-SUM(G$2:G4) -> -3918000 | R4: =H4-(E4-F4-B4+G4) -> 0
A5: 3 | B5: =IF(A5=0,Inputs!$C$3*(1+Inputs!$C$4),IF(A5<=Inputs!$C$8,Inputs!$C$5*(1+Inputs!$C$6)*(1+Inputs!$C$7)/Inputs!$C$8,0)) -> 0 | C5: =IF(A5>Inputs!$C$8,Inputs!$C$2*12*MIN(Inputs!$C$9*(1+Inputs!$C$11)^(A5-Inputs!$C$8-1),Inputs!$C$10*(1+Inputs!$C$12)^(A5-Inputs!$C$8-1))*Inputs!$C$13*(1-Inputs!$C$14),0) -> 183328.2 | D5: =IF(C5>0,Inputs!$C$15*(1+Inputs!$C$17)^(A5-Inputs!$C$8-1)+C5*Inputs!$C$16,0) -> 71165.794 | E5: =C5-D5 -> 112162.41 | F5: =IF(C5>0,Inputs!$C$2*Inputs!$C$18*(1+Inputs!$C$17)^(A5-Inputs!$C$8-1),0) -> 15000 | G5: =IF(A5=20,MAX(0,(Inputs!$C$2*12*MIN(Inputs!$C$9*(1+Inputs!$C$11)^(20-Inputs!$C$8),Inputs!$C$10*(1+Inputs!$C$12)^(20-Inputs!$C$8))*Inputs!$C$13*(1-Inputs!$C$14))*(1-Inputs!$C$16)-Inputs!$C$15*(1+Inputs!$C$17)^(20-Inputs!$C$8))/Inputs!$C$19*(1-Inputs!$C$20),0) -> 0 | H5: =E5-F5-B5+G5 -> 97162.406 | I5: =H5/(1+Inputs!$C$21)^A5 -> 78211.906 | J5: =SUM(H$2:H5) -> -3820837.6 | K5: =SUM(I$2:I5) -> -3650890.3 | L5: =IF(A5=Inputs!$C$8,SUM(B$2:B$22)*Inputs!$C$22,0) -> 0 | M5: =IF(AND(A5>Inputs!$C$8,A5<=Inputs!$C$8+Inputs!$C$24),-PMT(Inputs!$C$23,Inputs!$C$24,SUM(B$2:B$22)*Inputs!$C$22),0) -> 165660.4 | N5: =MAX(0,N4*(1+IF(M5>0,Inputs!$C$23,0))+L5-M5) -> 2086210.1 | O5: =H5+L5-M5-IF(A5=20,N5,0) -> -68497.997 | P5: =IF(M5>0,(E5-F5)/M5,0) -> 0.58651557 | Q5: =J5-SUM(G$2:G5) -> -3820837.6 | R5: =H5-(E5-F5-B5+G5) -> 0
A6: 4 | B6: =IF(A6=0,Inputs!$C$3*(1+Inputs!$C$4),IF(A6<=Inputs!$C$8,Inputs!$C$5*(1+Inputs!$C$6)*(1+Inputs!$C$7)/Inputs!$C$8,0)) -> 0 | C6: =IF(A6>Inputs!$C$8,Inputs!$C$2*12*MIN(Inputs!$C$9*(1+Inputs!$C$11)^(A6-Inputs!$C$8-1),Inputs!$C$10*(1+Inputs!$C$12)^(A6-Inputs!$C$8-1))*Inputs!$C$13*(1-Inputs!$C$14),0) -> 186994.76 | D6: =IF(C6>0,Inputs!$C$15*(1+Inputs!$C$17)^(A6-Inputs!$C$8-1)+C6*Inputs!$C$16,0) -> 72789.11 | E6: =C6-D6 -> 114205.65 | F6: =IF(C6>0,Inputs!$C$2*Inputs!$C$18*(1+Inputs!$C$17)^(A6-Inputs!$C$8-1),0) -> 15375 | G6: =IF(A6=20,MAX(0,(Inputs!$C$2*12*MIN(Inputs!$C$9*(1+Inputs!$C$11)^(20-Inputs!$C$8),Inputs!$C$10*(1+Inputs!$C$12)^(20-Inputs!$C$8))*Inputs!$C$13*(1-Inputs!$C$14))*(1-Inputs!$C$16)-Inputs!$C$15*(1+Inputs!$C$17)^(20-Inputs!$C$8))/Inputs!$C$19*(1-Inputs!$C$20),0) -> 0 | H6: =E6-F6-B6+G6 -> 98830.654 | I6: =H6/(1+Inputs!$C$21)^A6 -> 74004.446 | J6: =SUM(H$2:H6) -> -3722006.9 | K6: =SUM(I$2:I6) -> -3576885.9 | L6: =IF(A6=Inputs!$C$8,SUM(B$2:B$22)*Inputs!$C$22,0) -> 0 | M6: =IF(AND(A6>Inputs!$C$8,A6<=Inputs!$C$8+Inputs!$C$24),-PMT(Inputs!$C$23,Inputs!$C$24,SUM(B$2:B$22)*Inputs!$C$22),0) -> 165660.4 | N6: =MAX(0,N5*(1+IF(M6>0,Inputs!$C$23,0))+L6-M6) -> 2014429.1 | O6: =H6+L6-M6-IF(A6=20,N6,0) -> -66829.749 | P6: =IF(M6>0,(E6-F6)/M6,0) -> 0.59658586 | Q6: =J6-SUM(G$2:G6) -> -3722006.9 | R6: =H6-(E6-F6-B6+G6) -> 0
A7: 5 | B7: =IF(A7=0,Inputs!$C$3*(1+Inputs!$C$4),IF(A7<=Inputs!$C$8,Inputs!$C$5*(1+Inputs!$C$6)*(1+Inputs!$C$7)/Inputs!$C$8,0)) -> 0 | C7: =IF(A7>Inputs!$C$8,Inputs!$C$2*12*MIN(Inputs!$C$9*(1+Inputs!$C$11)^(A7-Inputs!$C$8-1),Inputs!$C$10*(1+Inputs!$C$12)^(A7-Inputs!$C$8-1))*Inputs!$C$13*(1-Inputs!$C$14),0) -> 190734.66 | D7: =IF(C7>0,Inputs!$C$15*(1+Inputs!$C$17)^(A7-Inputs!$C$8-1)+C7*Inputs!$C$16,0) -> 74449.892 | E7: =C7-D7 -> 116284.77 | F7: =IF(C7>0,Inputs!$C$2*Inputs!$C$18*(1+Inputs!$C$17)^(A7-Inputs!$C$8-1),0) -> 15759.375 | G7: =IF(A7=20,MAX(0,(Inputs!$C$2*12*MIN(Inputs!$C$9*(1+Inputs!$C$11)^(20-Inputs!$C$8),Inputs!$C$10*(1+Inputs!$C$12)^(20-Inputs!$C$8))*Inputs!$C$13*(1-Inputs!$C$14))*(1-Inputs!$C$16)-Inputs!$C$15*(1+Inputs!$C$17)^(20-Inputs!$C$8))/Inputs!$C$19*(1-Inputs!$C$20),0) -> 0 | H7: =E7-F7-B7+G7 -> 100525.39 | I7: =H7/(1+Inputs!$C$21)^A7 -> 70021.83 | J7: =SUM(H$2:H7) -> -3621481.5 | K7: =SUM(I$2:I7) -> -3506864 | L7: =IF(A7=Inputs!$C$8,SUM(B$2:B$22)*Inputs!$C$22,0) -> 0 | M7: =IF(AND(A7>Inputs!$C$8,A7<=Inputs!$C$8+Inputs!$C$24),-PMT(Inputs!$C$23,Inputs!$C$24,SUM(B$2:B$22)*Inputs!$C$22),0) -> 165660.4 | N7: =MAX(0,N6*(1+IF(M7>0,Inputs!$C$23,0))+L7-M7) -> 1939418.1 | O7: =H7+L7-M7-IF(A7=20,N7,0) -> -65135.011 | P7: =IF(M7>0,(E7-F7)/M7,0) -> 0.60681605 | Q7: =J7-SUM(G$2:G7) -> -3621481.5 | R7: =H7-(E7-F7-B7+G7) -> 0
A8: 6 | B8: =IF(A8=0,Inputs!$C$3*(1+Inputs!$C$4),IF(A8<=Inputs!$C$8,Inputs!$C$5*(1+Inputs!$C$6)*(1+Inputs!$C$7)/Inputs!$C$8,0)) -> 0 | C8: =IF(A8>Inputs!$C$8,Inputs!$C$2*12*MIN(Inputs!$C$9*(1+Inputs!$C$11)^(A8-Inputs!$C$8-1),Inputs!$C$10*(1+Inputs!$C$12)^(A8-Inputs!$C$8-1))*Inputs!$C$13*(1-Inputs!$C$14),0) -> 194549.35 | D8: =IF(C8>0,Inputs!$C$15*(1+Inputs!$C$17)^(A8-Inputs!$C$8-1)+C8*Inputs!$C$16,0) -> 76149.015 | E8: =C8-D8 -> 118400.34 | F8: =IF(C8>0,Inputs!$C$2*Inputs!$C$18*(1+Inputs!$C$17)^(A8-Inputs!$C$8-1),0) -> 16153.359 | G8: =IF(A8=20,MAX(0,(Inputs!$C$2*12*MIN(Inputs!$C$9*(1+Inputs!$C$11)^(20-Inputs!$C$8),Inputs!$C$10*(1+Inputs!$C$12)^(20-Inputs!$C$8))*Inputs!$C$13*(1-Inputs!$C$14))*(1-Inputs!$C$16)-Inputs!$C$15*(1+Inputs!$C$17)^(20-Inputs!$C$8))/Inputs!$C$19*(1-Inputs!$C$20),0) -> 0 | H8: =E8-F8-B8+G8 -> 102246.98 | I8: =H8/(1+Inputs!$C$21)^A8 -> 66252.107 | J8: =SUM(H$2:H8) -> -3519234.6 | K8: =SUM(I$2:I8) -> -3440611.9 | L8: =IF(A8=Inputs!$C$8,SUM(B$2:B$22)*Inputs!$C$22,0) -> 0 | M8: =IF(AND(A8>Inputs!$C$8,A8<=Inputs!$C$8+Inputs!$C$24),-PMT(Inputs!$C$23,Inputs!$C$24,SUM(B$2:B$22)*Inputs!$C$22),0) -> 165660.4 | N8: =MAX(0,N7*(1+IF(M8>0,Inputs!$C$23,0))+L8-M8) -> 1861031.5 | O8: =H8+L8-M8-IF(A8=20,N8,0) -> -63413.425 | P8: =IF(M8>0,(E8-F8)/M8,0) -> 0.61720831 | Q8: =J8-SUM(G$2:G8) -> -3519234.6 | R8: =H8-(E8-F8-B8+G8) -> 0
A9: 7 | B9: =IF(A9=0,Inputs!$C$3*(1+Inputs!$C$4),IF(A9<=Inputs!$C$8,Inputs!$C$5*(1+Inputs!$C$6)*(1+Inputs!$C$7)/Inputs!$C$8,0)) -> 0 | C9: =IF(A9>Inputs!$C$8,Inputs!$C$2*12*MIN(Inputs!$C$9*(1+Inputs!$C$11)^(A9-Inputs!$C$8-1),Inputs!$C$10*(1+Inputs!$C$12)^(A9-Inputs!$C$8-1))*Inputs!$C$13*(1-Inputs!$C$14),0) -> 198440.34 | D9: =IF(C9>0,Inputs!$C$15*(1+Inputs!$C$17)^(A9-Inputs!$C$8-1)+C9*Inputs!$C$16,0) -> 77887.373 | E9: =C9-D9 -> 120552.97 | F9: =IF(C9>0,Inputs!$C$2*Inputs!$C$18*(1+Inputs!$C$17)^(A9-Inputs!$C$8-1),0) -> 16557.193 | G9: =IF(A9=20,MAX(0,(Inputs!$C$2*12*MIN(Inputs!$C$9*(1+Inputs!$C$11)^(20-Inputs!$C$8),Inputs!$C$10*(1+Inputs!$C$12)^(20-Inputs!$C$8))*Inputs!$C$13*(1-Inputs!$C$14))*(1-Inputs!$C$16)-Inputs!$C$15*(1+Inputs!$C$17)^(20-Inputs!$C$8))/Inputs!$C$19*(1-Inputs!$C$20),0) -> 0 | H9: =E9-F9-B9+G9 -> 103995.77 | I9: =H9/(1+Inputs!$C$21)^A9 -> 62683.962 | J9: =SUM(H$2:H9) -> -3415238.8 | K9: =SUM(I$2:I9) -> -3377928 | L9: =IF(A9=Inputs!$C$8,SUM(B$2:B$22)*Inputs!$C$22,0) -> 0 | M9: =IF(AND(A9>Inputs!$C$8,A9<=Inputs!$C$8+Inputs!$C$24),-PMT(Inputs!$C$23,Inputs!$C$24,SUM(B$2:B$22)*Inputs!$C$22),0) -> 165660.4 | N9: =MAX(0,N8*(1+IF(M9>0,Inputs!$C$23,0))+L9-M9) -> 1779117.5 | O9: =H9+L9-M9-IF(A9=20,N9,0) -> -61664.631 | P9: =IF(M9>0,(E9-F9)/M9,0) -> 0.62776482 | Q9: =J9-SUM(G$2:G9) -> -3415238.8 | R9: =H9-(E9-F9-B9+G9) -> 0
A10: 8 | B10: =IF(A10=0,Inputs!$C$3*(1+Inputs!$C$4),IF(A10<=Inputs!$C$8,Inputs!$C$5*(1+Inputs!$C$6)*(1+Inputs!$C$7)/Inputs!$C$8,0)) -> 0 | C10: =IF(A10>Inputs!$C$8,Inputs!$C$2*12*MIN(Inputs!$C$9*(1+Inputs!$C$11)^(A10-Inputs!$C$8-1),Inputs!$C$10*(1+Inputs!$C$12)^(A10-Inputs!$C$8-1))*Inputs!$C$13*(1-Inputs!$C$14),0) -> 202409.15 | D10: =IF(C10>0,Inputs!$C$15*(1+Inputs!$C$17)^(A10-Inputs!$C$8-1)+C10*Inputs!$C$16,0) -> 79665.883 | E10: =C10-D10 -> 122743.26 | F10: =IF(C10>0,Inputs!$C$2*Inputs!$C$18*(1+Inputs!$C$17)^(A10-Inputs!$C$8-1),0) -> 16971.123 | G10: =IF(A10=20,MAX(0,(Inputs!$C$2*12*MIN(Inputs!$C$9*(1+Inputs!$C$11)^(20-Inputs!$C$8),Inputs!$C$10*(1+Inputs!$C$12)^(20-Inputs!$C$8))*Inputs!$C$13*(1-Inputs!$C$14))*(1-Inputs!$C$16)-Inputs!$C$15*(1+Inputs!$C$17)^(20-Inputs!$C$8))/Inputs!$C$19*(1-Inputs!$C$20),0) -> 0 | H10: =E10-F10-B10+G10 -> 105772.14 | I10: =H10/(1+Inputs!$C$21)^A10 -> 59306.675 | J10: =SUM(H$2:H10) -> -3309466.7 | K10: =SUM(I$2:I10) -> -3318621.3 | L10: =IF(A10=Inputs!$C$8,SUM(B$2:B$22)*Inputs!$C$22,0) -> 0 | M10: =IF(AND(A10>Inputs!$C$8,A10<=Inputs!$C$8+Inputs!$C$24),-PMT(Inputs!$C$23,Inputs!$C$24,SUM(B$2:B$22)*Inputs!$C$22),0) -> 165660.4 | N10: =MAX(0,N9*(1+IF(M10>0,Inputs!$C$23,0))+L10-M10) -> 1693517.4 | O10: =H10+L10-M10-IF(A10=20,N10,0) -> -59888.264 | P10: =IF(M10>0,(E10-F10)/M10,0) -> 0.63848776 | Q10: =J10-SUM(G$2:G10) -> -3309466.7 | R10: =H10-(E10-F10-B10+G10) -> 0
A11: 9 | B11: =IF(A11=0,Inputs!$C$3*(1+Inputs!$C$4),IF(A11<=Inputs!$C$8,Inputs!$C$5*(1+Inputs!$C$6)*(1+Inputs!$C$7)/Inputs!$C$8,0)) -> 0 | C11: =IF(A11>Inputs!$C$8,Inputs!$C$2*12*MIN(Inputs!$C$9*(1+Inputs!$C$11)^(A11-Inputs!$C$8-1),Inputs!$C$10*(1+Inputs!$C$12)^(A11-Inputs!$C$8-1))*Inputs!$C$13*(1-Inputs!$C$14),0) -> 206457.33 | D11: =IF(C11>0,Inputs!$C$15*(1+Inputs!$C$17)^(A11-Inputs!$C$8-1)+C11*Inputs!$C$16,0) -> 81485.483 | E11: =C11-D11 -> 124971.85 | F11: =IF(C11>0,Inputs!$C$2*Inputs!$C$18*(1+Inputs!$C$17)^(A11-Inputs!$C$8-1),0) -> 17395.401 | G11: =IF(A11=20,MAX(0,(Inputs!$C$2*12*MIN(Inputs!$C$9*(1+Inputs!$C$11)^(20-Inputs!$C$8),Inputs!$C$10*(1+Inputs!$C$12)^(20-Inputs!$C$8))*Inputs!$C$13*(1-Inputs!$C$14))*(1-Inputs!$C$16)-Inputs!$C$15*(1+Inputs!$C$17)^(20-Inputs!$C$8))/Inputs!$C$19*(1-Inputs!$C$20),0) -> 0 | H11: =E11-F11-B11+G11 -> 107576.45 | I11: =H11/(1+Inputs!$C$21)^A11 -> 56110.096 | J11: =SUM(H$2:H11) -> -3201890.2 | K11: =SUM(I$2:I11) -> -3262511.2 | L11: =IF(A11=Inputs!$C$8,SUM(B$2:B$22)*Inputs!$C$22,0) -> 0 | M11: =IF(AND(A11>Inputs!$C$8,A11<=Inputs!$C$8+Inputs!$C$24),-PMT(Inputs!$C$23,Inputs!$C$24,SUM(B$2:B$22)*Inputs!$C$22),0) -> 165660.4 | N11: =MAX(0,N10*(1+IF(M11>0,Inputs!$C$23,0))+L11-M11) -> 1604065.2 | O11: =H11+L11-M11-IF(A11=20,N11,0) -> -58083.958 | P11: =IF(M11>0,(E11-F11)/M11,0) -> 0.64937935 | Q11: =J11-SUM(G$2:G11) -> -3201890.2 | R11: =H11-(E11-F11-B11+G11) -> 0
A12: 10 | B12: =IF(A12=0,Inputs!$C$3*(1+Inputs!$C$4),IF(A12<=Inputs!$C$8,Inputs!$C$5*(1+Inputs!$C$6)*(1+Inputs!$C$7)/Inputs!$C$8,0)) -> 0 | C12: =IF(A12>Inputs!$C$8,Inputs!$C$2*12*MIN(Inputs!$C$9*(1+Inputs!$C$11)^(A12-Inputs!$C$8-1),Inputs!$C$10*(1+Inputs!$C$12)^(A12-Inputs!$C$8-1))*Inputs!$C$13*(1-Inputs!$C$14),0) -> 210586.48 | D12: =IF(C12>0,Inputs!$C$15*(1+Inputs!$C$17)^(A12-Inputs!$C$8-1)+C12*Inputs!$C$16,0) -> 83347.131 | E12: =C12-D12 -> 127239.34 | F12: =IF(C12>0,Inputs!$C$2*Inputs!$C$18*(1+Inputs!$C$17)^(A12-Inputs!$C$8-1),0) -> 17830.286 | G12: =IF(A12=20,MAX(0,(Inputs!$C$2*12*MIN(Inputs!$C$9*(1+Inputs!$C$11)^(20-Inputs!$C$8),Inputs!$C$10*(1+Inputs!$C$12)^(20-Inputs!$C$8))*Inputs!$C$13*(1-Inputs!$C$14))*(1-Inputs!$C$16)-Inputs!$C$15*(1+Inputs!$C$17)^(20-Inputs!$C$8))/Inputs!$C$19*(1-Inputs!$C$20),0) -> 0 | H12: =E12-F12-B12+G12 -> 109409.06 | I12: =H12/(1+Inputs!$C$21)^A12 -> 53084.611 | J12: =SUM(H$2:H12) -> -3092481.2 | K12: =SUM(I$2:I12) -> -3209426.6 | L12: =IF(A12=Inputs!$C$8,SUM(B$2:B$22)*Inputs!$C$22,0) -> 0 | M12: =IF(AND(A12>Inputs!$C$8,A12<=Inputs!$C$8+Inputs!$C$24),-PMT(Inputs!$C$23,Inputs!$C$24,SUM(B$2:B$22)*Inputs!$C$22),0) -> 165660.4 | N12: =MAX(0,N11*(1+IF(M12>0,Inputs!$C$23,0))+L12-M12) -> 1510587.8 | O12: =H12+L12-M12-IF(A12=20,N12,0) -> -56251.345 | P12: =IF(M12>0,(E12-F12)/M12,0) -> 0.66044182 | Q12: =J12-SUM(G$2:G12) -> -3092481.2 | R12: =H12-(E12-F12-B12+G12) -> 0
A13: 11 | B13: =IF(A13=0,Inputs!$C$3*(1+Inputs!$C$4),IF(A13<=Inputs!$C$8,Inputs!$C$5*(1+Inputs!$C$6)*(1+Inputs!$C$7)/Inputs!$C$8,0)) -> 0 | C13: =IF(A13>Inputs!$C$8,Inputs!$C$2*12*MIN(Inputs!$C$9*(1+Inputs!$C$11)^(A13-Inputs!$C$8-1),Inputs!$C$10*(1+Inputs!$C$12)^(A13-Inputs!$C$8-1))*Inputs!$C$13*(1-Inputs!$C$14),0) -> 214798.21 | D13: =IF(C13>0,Inputs!$C$15*(1+Inputs!$C$17)^(A13-Inputs!$C$8-1)+C13*Inputs!$C$16,0) -> 85251.811 | E13: =C13-D13 -> 129546.39 | F13: =IF(C13>0,Inputs!$C$2*Inputs!$C$18*(1+Inputs!$C$17)^(A13-Inputs!$C$8-1),0) -> 18276.043 | G13: =IF(A13=20,MAX(0,(Inputs!$C$2*12*MIN(Inputs!$C$9*(1+Inputs!$C$11)^(20-Inputs!$C$8),Inputs!$C$10*(1+Inputs!$C$12)^(20-Inputs!$C$8))*Inputs!$C$13*(1-Inputs!$C$14))*(1-Inputs!$C$16)-Inputs!$C$15*(1+Inputs!$C$17)^(20-Inputs!$C$8))/Inputs!$C$19*(1-Inputs!$C$20),0) -> 0 | H13: =E13-F13-B13+G13 -> 111270.35 | I13: =H13/(1+Inputs!$C$21)^A13 -> 50221.115 | J13: =SUM(H$2:H13) -> -2981210.8 | K13: =SUM(I$2:I13) -> -3159205.5 | L13: =IF(A13=Inputs!$C$8,SUM(B$2:B$22)*Inputs!$C$22,0) -> 0 | M13: =IF(AND(A13>Inputs!$C$8,A13<=Inputs!$C$8+Inputs!$C$24),-PMT(Inputs!$C$23,Inputs!$C$24,SUM(B$2:B$22)*Inputs!$C$22),0) -> 165660.4 | N13: =MAX(0,N12*(1+IF(M13>0,Inputs!$C$23,0))+L13-M13) -> 1412903.8 | O13: =H13+L13-M13-IF(A13=20,N13,0) -> -54390.052 | P13: =IF(M13>0,(E13-F13)/M13,0) -> 0.67167741 | Q13: =J13-SUM(G$2:G13) -> -2981210.8 | R13: =H13-(E13-F13-B13+G13) -> 0
A14: 12 | B14: =IF(A14=0,Inputs!$C$3*(1+Inputs!$C$4),IF(A14<=Inputs!$C$8,Inputs!$C$5*(1+Inputs!$C$6)*(1+Inputs!$C$7)/Inputs!$C$8,0)) -> 0 | C14: =IF(A14>Inputs!$C$8,Inputs!$C$2*12*MIN(Inputs!$C$9*(1+Inputs!$C$11)^(A14-Inputs!$C$8-1),Inputs!$C$10*(1+Inputs!$C$12)^(A14-Inputs!$C$8-1))*Inputs!$C$13*(1-Inputs!$C$14),0) -> 219094.17 | D14: =IF(C14>0,Inputs!$C$15*(1+Inputs!$C$17)^(A14-Inputs!$C$8-1)+C14*Inputs!$C$16,0) -> 87200.528 | E14: =C14-D14 -> 131893.64 | F14: =IF(C14>0,Inputs!$C$2*Inputs!$C$18*(1+Inputs!$C$17)^(A14-Inputs!$C$8-1),0) -> 18732.945 | G14: =IF(A14=20,MAX(0,(Inputs!$C$2*12*MIN(Inputs!$C$9*(1+Inputs!$C$11)^(20-Inputs!$C$8),Inputs!$C$10*(1+Inputs!$C$12)^(20-Inputs!$C$8))*Inputs!$C$13*(1-Inputs!$C$14))*(1-Inputs!$C$16)-Inputs!$C$15*(1+Inputs!$C$17)^(20-Inputs!$C$8))/Inputs!$C$19*(1-Inputs!$C$20),0) -> 0 | H14: =E14-F14-B14+G14 -> 113160.7 | I14: =H14/(1+Inputs!$C$21)^A14 -> 47510.986 | J14: =SUM(H$2:H14) -> -2868050.1 | K14: =SUM(I$2:I14) -> -3111694.5 | L14: =IF(A14=Inputs!$C$8,SUM(B$2:B$22)*Inputs!$C$22,0) -> 0 | M14: =IF(AND(A14>Inputs!$C$8,A14<=Inputs!$C$8+Inputs!$C$24),-PMT(Inputs!$C$23,Inputs!$C$24,SUM(B$2:B$22)*Inputs!$C$22),0) -> 165660.4 | N14: =MAX(0,N13*(1+IF(M14>0,Inputs!$C$23,0))+L14-M14) -> 1310824.1 | O14: =H14+L14-M14-IF(A14=20,N14,0) -> -52499.706 | P14: =IF(M14>0,(E14-F14)/M14,0) -> 0.68308838 | Q14: =J14-SUM(G$2:G14) -> -2868050.1 | R14: =H14-(E14-F14-B14+G14) -> 0
... A22: 20 | B22: =IF(A22=0,Inputs!$C$3*(1+Inputs!$C$4),IF(A22<=Inputs!$C$8,Inputs!$C$5*(1+Inputs!$C$6)*(1+Inputs!$C$7)/Inputs!$C$8,0)) -> 0 | C22: =IF(A22>Inputs!$C$8,Inputs!$C$2*12*MIN(Inputs!$C$9*(1+Inputs!$C$11)^(A22-Inputs!$C$8-1),Inputs!$C$10*(1+Inputs!$C$12)^(A22-Inputs!$C$8-1))*Inputs!$C$13*(1-Inputs!$C$14),0) -> 256703.74 | D22: =IF(C22>0,Inputs!$C$15*(1+Inputs!$C$17)^(A22-Inputs!$C$8-1)+C22*Inputs!$C$16,0) -> 104504.37 | E22: =C22-D22 -> 152199.37 | F22: =IF(C22>0,Inputs!$C$2*Inputs!$C$18*(1+Inputs!$C$17)^(A22-Inputs!$C$8-1),0) -> 22824.274 | G22: =IF(A22=20,MAX(0,(Inputs!$C$2*12*MIN(Inputs!$C$9*(1+Inputs!$C$11)^(20-Inputs!$C$8),Inputs!$C$10*(1+Inputs!$C$12)^(20-Inputs!$C$8))*Inputs!$C$13*(1-Inputs!$C$14))*(1-Inputs!$C$16)-Inputs!$C$15*(1+Inputs!$C$17)^(20-Inputs!$C$8))/Inputs!$C$19*(1-Inputs!$C$20),0) -> 2746646.6 | H22: =E22-F22-B22+G22 -> 2876021.7 | I22: =H22/(1+Inputs!$C$21)^A22 -> 677053.31 | J22: =SUM(H$2:H22) -> 855546.35 | K22: =SUM(I$2:I22) -> -2166675.5 | L22: =IF(A22=Inputs!$C$8,SUM(B$2:B$22)*Inputs!$C$22,0) -> 0 | M22: =IF(AND(A22>Inputs!$C$8,A22<=Inputs!$C$8+Inputs!$C$24),-PMT(Inputs!$C$23,Inputs!$C$24,SUM(B$2:B$22)*Inputs!$C$22),0) -> 165660.4 | N22: =MAX(0,N21*(1+IF(M22>0,Inputs!$C$23,0))+L22-M22) -> 310226.89 | O22: =H22+L22-M22-IF(A22=20,N22,0) -> 2400134.4 | P22: =IF(M22>0,(E22-F22)/M22,0) -> 0.78096574 | Q22: =J22-SUM(G$2:G22) -> -1891100.2 | R22: =H22-(E22-F22-B22+G22) -> 0
A25: Payback uses first nonnegative cumulative end-year; includes sale at year 20 if needed.
A26: Debt drawn at completion; bridging interest and loan fees excluded. Equity IRR is indicative.

Sheet Optimal
A1: YEAR | B1: Build spend | C1: Collected rent | D1: Owner costs | E1: NOI | F1: Capital reserve | G1: Exit proceeds | H1: Project cash flow | I1: Discounted CF | J1: Cumulative CF | K1: Cumulative discounted | L1: Debt draw | M1: Debt service | N1: Closing debt | O1: Equity cash flow | P1: DSCR | Q1: Cumulative excluding sale | R1: Discounted cash flow check
A2: 0 | B2: =IF(A2=0,Inputs!$D$3*(1+Inputs!$D$4),IF(A2<=Inputs!$D$8,Inputs!$D$5*(1+Inputs!$D$6)*(1+Inputs!$D$7)/Inputs!$D$8,0)) -> 2070000 | C2: =IF(A2>Inputs!$D$8,Inputs!$D$2*12*MIN(Inputs!$D$9*(1+Inputs!$D$11)^(A2-Inputs!$D$8-1),Inputs!$D$10*(1+Inputs!$D$12)^(A2-Inputs!$D$8-1))*Inputs!$D$13*(1-Inputs!$D$14),0) -> 0 | D2: =IF(C2>0,Inputs!$D$15*(1+Inputs!$D$17)^(A2-Inputs!$D$8-1)+C2*Inputs!$D$16,0) -> 0 | E2: =C2-D2 -> 0 | F2: =IF(C2>0,Inputs!$D$2*Inputs!$D$18*(1+Inputs!$D$17)^(A2-Inputs!$D$8-1),0) -> 0 | G2: =IF(A2=20,MAX(0,(Inputs!$D$2*12*MIN(Inputs!$D$9*(1+Inputs!$D$11)^(20-Inputs!$D$8),Inputs!$D$10*(1+Inputs!$D$12)^(20-Inputs!$D$8))*Inputs!$D$13*(1-Inputs!$D$14))*(1-Inputs!$D$16)-Inputs!$D$15*(1+Inputs!$D$17)^(20-Inputs!$D$8))/Inputs!$D$19*(1-Inputs!$D$20),0) -> 0 | H2: =E2-F2-B2+G2 -> -2070000 | I2: =H2/(1+Inputs!$D$21)^A2 -> -2070000 | J2: =SUM(H$2:H2) -> -2070000 | K2: =SUM(I$2:I2) -> -2070000 | L2: =IF(A2=Inputs!$D$8,SUM(B$2:B$22)*Inputs!$D$22,0) -> 0 | M2: =IF(AND(A2>Inputs!$D$8,A2<=Inputs!$D$8+Inputs!$D$24),-PMT(Inputs!$D$23,Inputs!$D$24,SUM(B$2:B$22)*Inputs!$D$22),0) -> 0 | N2: =L2 -> 0 | O2: =H2+L2-M2-IF(A2=20,N2,0) -> -2070000 | P2: =IF(M2>0,(E2-F2)/M2,0) -> 0 | Q2: =J2-SUM(G$2:G2) -> -2070000 | R2: =H2-(E2-F2-B2+G2) -> 0
A3: 1 | B3: =IF(A3=0,Inputs!$D$3*(1+Inputs!$D$4),IF(A3<=Inputs!$D$8,Inputs!$D$5*(1+Inputs!$D$6)*(1+Inputs!$D$7)/Inputs!$D$8,0)) -> 1650000 | C3: =IF(A3>Inputs!$D$8,Inputs!$D$2*12*MIN(Inputs!$D$9*(1+Inputs!$D$11)^(A3-Inputs!$D$8-1),Inputs!$D$10*(1+Inputs!$D$12)^(A3-Inputs!$D$8-1))*Inputs!$D$13*(1-Inputs!$D$14),0) -> 0 | D3: =IF(C3>0,Inputs!$D$15*(1+Inputs!$D$17)^(A3-Inputs!$D$8-1)+C3*Inputs!$D$16,0) -> 0 | E3: =C3-D3 -> 0 | F3: =IF(C3>0,Inputs!$D$2*Inputs!$D$18*(1+Inputs!$D$17)^(A3-Inputs!$D$8-1),0) -> 0 | G3: =IF(A3=20,MAX(0,(Inputs!$D$2*12*MIN(Inputs!$D$9*(1+Inputs!$D$11)^(20-Inputs!$D$8),Inputs!$D$10*(1+Inputs!$D$12)^(20-Inputs!$D$8))*Inputs!$D$13*(1-Inputs!$D$14))*(1-Inputs!$D$16)-Inputs!$D$15*(1+Inputs!$D$17)^(20-Inputs!$D$8))/Inputs!$D$19*(1-Inputs!$D$20),0) -> 0 | H3: =E3-F3-B3+G3 -> -1650000 | I3: =H3/(1+Inputs!$D$21)^A3 -> -1549295.8 | J3: =SUM(H$2:H3) -> -3720000 | K3: =SUM(I$2:I3) -> -3619295.8 | L3: =IF(A3=Inputs!$D$8,SUM(B$2:B$22)*Inputs!$D$22,0) -> 2046000 | M3: =IF(AND(A3>Inputs!$D$8,A3<=Inputs!$D$8+Inputs!$D$24),-PMT(Inputs!$D$23,Inputs!$D$24,SUM(B$2:B$22)*Inputs!$D$22),0) -> 0 | N3: =MAX(0,N2*(1+IF(M3>0,Inputs!$D$23,0))+L3-M3) -> 2046000 | O3: =H3+L3-M3-IF(A3=20,N3,0) -> 396000 | P3: =IF(M3>0,(E3-F3)/M3,0) -> 0 | Q3: =J3-SUM(G$2:G3) -> -3720000 | R3: =H3-(E3-F3-B3+G3) -> 0
A4: 2 | B4: =IF(A4=0,Inputs!$D$3*(1+Inputs!$D$4),IF(A4<=Inputs!$D$8,Inputs!$D$5*(1+Inputs!$D$6)*(1+Inputs!$D$7)/Inputs!$D$8,0)) -> 0 | C4: =IF(A4>Inputs!$D$8,Inputs!$D$2*12*MIN(Inputs!$D$9*(1+Inputs!$D$11)^(A4-Inputs!$D$8-1),Inputs!$D$10*(1+Inputs!$D$12)^(A4-Inputs!$D$8-1))*Inputs!$D$13*(1-Inputs!$D$14),0) -> 193069.8 | D4: =IF(C4>0,Inputs!$D$15*(1+Inputs!$D$17)^(A4-Inputs!$D$8-1)+C4*Inputs!$D$16,0) -> 64960.47 | E4: =C4-D4 -> 128109.33 | F4: =IF(C4>0,Inputs!$D$2*Inputs!$D$18*(1+Inputs!$D$17)^(A4-Inputs!$D$8-1),0) -> 12000 | G4: =IF(A4=20,MAX(0,(Inputs!$D$2*12*MIN(Inputs!$D$9*(1+Inputs!$D$11)^(20-Inputs!$D$8),Inputs!$D$10*(1+Inputs!$D$12)^(20-Inputs!$D$8))*Inputs!$D$13*(1-Inputs!$D$14))*(1-Inputs!$D$16)-Inputs!$D$15*(1+Inputs!$D$17)^(20-Inputs!$D$8))/Inputs!$D$19*(1-Inputs!$D$20),0) -> 0 | H4: =E4-F4-B4+G4 -> 116109.33 | I4: =H4/(1+Inputs!$D$21)^A4 -> 102368.87 | J4: =SUM(H$2:H4) -> -3603890.7 | K4: =SUM(I$2:I4) -> -3516926.9 | L4: =IF(A4=Inputs!$D$8,SUM(B$2:B$22)*Inputs!$D$22,0) -> 0 | M4: =IF(AND(A4>Inputs!$D$8,A4<=Inputs!$D$8+Inputs!$D$24),-PMT(Inputs!$D$23,Inputs!$D$24,SUM(B$2:B$22)*Inputs!$D$22),0) -> 150548.26 | N4: =MAX(0,N3*(1+IF(M4>0,Inputs!$D$23,0))+L4-M4) -> 1977291.7 | O4: =H4+L4-M4-IF(A4=20,N4,0) -> -34438.931 | P4: =IF(M4>0,(E4-F4)/M4,0) -> 0.77124325 | Q4: =J4-SUM(G$2:G4) -> -3603890.7 | R4: =H4-(E4-F4-B4+G4) -> 0
A5: 3 | B5: =IF(A5=0,Inputs!$D$3*(1+Inputs!$D$4),IF(A5<=Inputs!$D$8,Inputs!$D$5*(1+Inputs!$D$6)*(1+Inputs!$D$7)/Inputs!$D$8,0)) -> 0 | C5: =IF(A5>Inputs!$D$8,Inputs!$D$2*12*MIN(Inputs!$D$9*(1+Inputs!$D$11)^(A5-Inputs!$D$8-1),Inputs!$D$10*(1+Inputs!$D$12)^(A5-Inputs!$D$8-1))*Inputs!$D$13*(1-Inputs!$D$14),0) -> 196931.2 | D5: =IF(C5>0,Inputs!$D$15*(1+Inputs!$D$17)^(A5-Inputs!$D$8-1)+C5*Inputs!$D$16,0) -> 66259.679 | E5: =C5-D5 -> 130671.52 | F5: =IF(C5>0,Inputs!$D$2*Inputs!$D$18*(1+Inputs!$D$17)^(A5-Inputs!$D$8-1),0) -> 12240 | G5: =IF(A5=20,MAX(0,(Inputs!$D$2*12*MIN(Inputs!$D$9*(1+Inputs!$D$11)^(20-Inputs!$D$8),Inputs!$D$10*(1+Inputs!$D$12)^(20-Inputs!$D$8))*Inputs!$D$13*(1-Inputs!$D$14))*(1-Inputs!$D$16)-Inputs!$D$15*(1+Inputs!$D$17)^(20-Inputs!$D$8))/Inputs!$D$19*(1-Inputs!$D$20),0) -> 0 | H5: =E5-F5-B5+G5 -> 118431.52 | I5: =H5/(1+Inputs!$D$21)^A5 -> 98043.423 | J5: =SUM(H$2:H5) -> -3485459.2 | K5: =SUM(I$2:I5) -> -3418883.5 | L5: =IF(A5=Inputs!$D$8,SUM(B$2:B$22)*Inputs!$D$22,0) -> 0 | M5: =IF(AND(A5>Inputs!$D$8,A5<=Inputs!$D$8+Inputs!$D$24),-PMT(Inputs!$D$23,Inputs!$D$24,SUM(B$2:B$22)*Inputs!$D$22),0) -> 150548.26 | N5: =MAX(0,N4*(1+IF(M5>0,Inputs!$D$23,0))+L5-M5) -> 1905835.1 | O5: =H5+L5-M5-IF(A5=20,N5,0) -> -32116.745 | P5: =IF(M5>0,(E5-F5)/M5,0) -> 0.78666811 | Q5: =J5-SUM(G$2:G5) -> -3485459.2 | R5: =H5-(E5-F5-B5+G5) -> 0
A6: 4 | B6: =IF(A6=0,Inputs!$D$3*(1+Inputs!$D$4),IF(A6<=Inputs!$D$8,Inputs!$D$5*(1+Inputs!$D$6)*(1+Inputs!$D$7)/Inputs!$D$8,0)) -> 0 | C6: =IF(A6>Inputs!$D$8,Inputs!$D$2*12*MIN(Inputs!$D$9*(1+Inputs!$D$11)^(A6-Inputs!$D$8-1),Inputs!$D$10*(1+Inputs!$D$12)^(A6-Inputs!$D$8-1))*Inputs!$D$13*(1-Inputs!$D$14),0) -> 200869.82 | D6: =IF(C6>0,Inputs!$D$15*(1+Inputs!$D$17)^(A6-Inputs!$D$8-1)+C6*Inputs!$D$16,0) -> 67584.873 | E6: =C6-D6 -> 133284.95 | F6: =IF(C6>0,Inputs!$D$2*Inputs!$D$18*(1+Inputs!$D$17)^(A6-Inputs!$D$8-1),0) -> 12484.8 | G6: =IF(A6=20,MAX(0,(Inputs!$D$2*12*MIN(Inputs!$D$9*(1+Inputs!$D$11)^(20-Inputs!$D$8),Inputs!$D$10*(1+Inputs!$D$12)^(20-Inputs!$D$8))*Inputs!$D$13*(1-Inputs!$D$14))*(1-Inputs!$D$16)-Inputs!$D$15*(1+Inputs!$D$17)^(20-Inputs!$D$8))/Inputs!$D$19*(1-Inputs!$D$20),0) -> 0 | H6: =E6-F6-B6+G6 -> 120800.15 | I6: =H6/(1+Inputs!$D$21)^A6 -> 93900.744 | J6: =SUM(H$2:H6) -> -3364659 | K6: =SUM(I$2:I6) -> -3324982.7 | L6: =IF(A6=Inputs!$D$8,SUM(B$2:B$22)*Inputs!$D$22,0) -> 0 | M6: =IF(AND(A6>Inputs!$D$8,A6<=Inputs!$D$8+Inputs!$D$24),-PMT(Inputs!$D$23,Inputs!$D$24,SUM(B$2:B$22)*Inputs!$D$22),0) -> 150548.26 | N6: =MAX(0,N5*(1+IF(M6>0,Inputs!$D$23,0))+L6-M6) -> 1831520.3 | O6: =H6+L6-M6-IF(A6=20,N6,0) -> -29748.114 | P6: =IF(M6>0,(E6-F6)/M6,0) -> 0.80240148 | Q6: =J6-SUM(G$2:G6) -> -3364659 | R6: =H6-(E6-F6-B6+G6) -> 0
A7: 5 | B7: =IF(A7=0,Inputs!$D$3*(1+Inputs!$D$4),IF(A7<=Inputs!$D$8,Inputs!$D$5*(1+Inputs!$D$6)*(1+Inputs!$D$7)/Inputs!$D$8,0)) -> 0 | C7: =IF(A7>Inputs!$D$8,Inputs!$D$2*12*MIN(Inputs!$D$9*(1+Inputs!$D$11)^(A7-Inputs!$D$8-1),Inputs!$D$10*(1+Inputs!$D$12)^(A7-Inputs!$D$8-1))*Inputs!$D$13*(1-Inputs!$D$14),0) -> 204887.22 | D7: =IF(C7>0,Inputs!$D$15*(1+Inputs!$D$17)^(A7-Inputs!$D$8-1)+C7*Inputs!$D$16,0) -> 68936.57 | E7: =C7-D7 -> 135950.65 | F7: =IF(C7>0,Inputs!$D$2*Inputs!$D$18*(1+Inputs!$D$17)^(A7-Inputs!$D$8-1),0) -> 12734.496 | G7: =IF(A7=20,MAX(0,(Inputs!$D$2*12*MIN(Inputs!$D$9*(1+Inputs!$D$11)^(20-Inputs!$D$8),Inputs!$D$10*(1+Inputs!$D$12)^(20-Inputs!$D$8))*Inputs!$D$13*(1-Inputs!$D$14))*(1-Inputs!$D$16)-Inputs!$D$15*(1+Inputs!$D$17)^(20-Inputs!$D$8))/Inputs!$D$19*(1-Inputs!$D$20),0) -> 0 | H7: =E7-F7-B7+G7 -> 123216.15 | I7: =H7/(1+Inputs!$D$21)^A7 -> 89933.107 | J7: =SUM(H$2:H7) -> -3241442.9 | K7: =SUM(I$2:I7) -> -3235049.6 | L7: =IF(A7=Inputs!$D$8,SUM(B$2:B$22)*Inputs!$D$22,0) -> 0 | M7: =IF(AND(A7>Inputs!$D$8,A7<=Inputs!$D$8+Inputs!$D$24),-PMT(Inputs!$D$23,Inputs!$D$24,SUM(B$2:B$22)*Inputs!$D$22),0) -> 150548.26 | N7: =MAX(0,N6*(1+IF(M7>0,Inputs!$D$23,0))+L7-M7) -> 1754232.8 | O7: =H7+L7-M7-IF(A7=20,N7,0) -> -27332.111 | P7: =IF(M7>0,(E7-F7)/M7,0) -> 0.81844951 | Q7: =J7-SUM(G$2:G7) -> -3241442.9 | R7: =H7-(E7-F7-B7+G7) -> 0
A8: 6 | B8: =IF(A8=0,Inputs!$D$3*(1+Inputs!$D$4),IF(A8<=Inputs!$D$8,Inputs!$D$5*(1+Inputs!$D$6)*(1+Inputs!$D$7)/Inputs!$D$8,0)) -> 0 | C8: =IF(A8>Inputs!$D$8,Inputs!$D$2*12*MIN(Inputs!$D$9*(1+Inputs!$D$11)^(A8-Inputs!$D$8-1),Inputs!$D$10*(1+Inputs!$D$12)^(A8-Inputs!$D$8-1))*Inputs!$D$13*(1-Inputs!$D$14),0) -> 208984.96 | D8: =IF(C8>0,Inputs!$D$15*(1+Inputs!$D$17)^(A8-Inputs!$D$8-1)+C8*Inputs!$D$16,0) -> 70315.302 | E8: =C8-D8 -> 138669.66 | F8: =IF(C8>0,Inputs!$D$2*Inputs!$D$18*(1+Inputs!$D$17)^(A8-Inputs!$D$8-1),0) -> 12989.186 | G8: =IF(A8=20,MAX(0,(Inputs!$D$2*12*MIN(Inputs!$D$9*(1+Inputs!$D$11)^(20-Inputs!$D$8),Inputs!$D$10*(1+Inputs!$D$12)^(20-Inputs!$D$8))*Inputs!$D$13*(1-Inputs!$D$14))*(1-Inputs!$D$16)-Inputs!$D$15*(1+Inputs!$D$17)^(20-Inputs!$D$8))/Inputs!$D$19*(1-Inputs!$D$20),0) -> 0 | H8: =E8-F8-B8+G8 -> 125680.47 | I8: =H8/(1+Inputs!$D$21)^A8 -> 86133.116 | J8: =SUM(H$2:H8) -> -3115762.4 | K8: =SUM(I$2:I8) -> -3148916.5 | L8: =IF(A8=Inputs!$D$8,SUM(B$2:B$22)*Inputs!$D$22,0) -> 0 | M8: =IF(AND(A8>Inputs!$D$8,A8<=Inputs!$D$8+Inputs!$D$24),-PMT(Inputs!$D$23,Inputs!$D$24,SUM(B$2:B$22)*Inputs!$D$22),0) -> 150548.26 | N8: =MAX(0,N7*(1+IF(M8>0,Inputs!$D$23,0))+L8-M8) -> 1673853.9 | O8: =H8+L8-M8-IF(A8=20,N8,0) -> -24867.788 | P8: =IF(M8>0,(E8-F8)/M8,0) -> 0.8348185 | Q8: =J8-SUM(G$2:G8) -> -3115762.4 | R8: =H8-(E8-F8-B8+G8) -> 0
A9: 7 | B9: =IF(A9=0,Inputs!$D$3*(1+Inputs!$D$4),IF(A9<=Inputs!$D$8,Inputs!$D$5*(1+Inputs!$D$6)*(1+Inputs!$D$7)/Inputs!$D$8,0)) -> 0 | C9: =IF(A9>Inputs!$D$8,Inputs!$D$2*12*MIN(Inputs!$D$9*(1+Inputs!$D$11)^(A9-Inputs!$D$8-1),Inputs!$D$10*(1+Inputs!$D$12)^(A9-Inputs!$D$8-1))*Inputs!$D$13*(1-Inputs!$D$14),0) -> 213164.66 | D9: =IF(C9>0,Inputs!$D$15*(1+Inputs!$D$17)^(A9-Inputs!$D$8-1)+C9*Inputs!$D$16,0) -> 71721.608 | E9: =C9-D9 -> 141443.05 | F9: =IF(C9>0,Inputs!$D$2*Inputs!$D$18*(1+Inputs!$D$17)^(A9-Inputs!$D$8-1),0) -> 13248.97 | G9: =IF(A9=20,MAX(0,(Inputs!$D$2*12*MIN(Inputs!$D$9*(1+Inputs!$D$11)^(20-Inputs!$D$8),Inputs!$D$10*(1+Inputs!$D$12)^(20-Inputs!$D$8))*Inputs!$D$13*(1-Inputs!$D$14))*(1-Inputs!$D$16)-Inputs!$D$15*(1+Inputs!$D$17)^(20-Inputs!$D$8))/Inputs!$D$19*(1-Inputs!$D$20),0) -> 0 | H9: =E9-F9-B9+G9 -> 128194.08 | I9: =H9/(1+Inputs!$D$21)^A9 -> 82493.689 | J9: =SUM(H$2:H9) -> -2987568.3 | K9: =SUM(I$2:I9) -> -3066422.8 | L9: =IF(A9=Inputs!$D$8,SUM(B$2:B$22)*Inputs!$D$22,0) -> 0 | M9: =IF(AND(A9>Inputs!$D$8,A9<=Inputs!$D$8+Inputs!$D$24),-PMT(Inputs!$D$23,Inputs!$D$24,SUM(B$2:B$22)*Inputs!$D$22),0) -> 150548.26 | N9: =MAX(0,N8*(1+IF(M9>0,Inputs!$D$23,0))+L9-M9) -> 1590259.8 | O9: =H9+L9-M9-IF(A9=20,N9,0) -> -22354.179 | P9: =IF(M9>0,(E9-F9)/M9,0) -> 0.85151487 | Q9: =J9-SUM(G$2:G9) -> -2987568.3 | R9: =H9-(E9-F9-B9+G9) -> 0
A10: 8 | B10: =IF(A10=0,Inputs!$D$3*(1+Inputs!$D$4),IF(A10<=Inputs!$D$8,Inputs!$D$5*(1+Inputs!$D$6)*(1+Inputs!$D$7)/Inputs!$D$8,0)) -> 0 | C10: =IF(A10>Inputs!$D$8,Inputs!$D$2*12*MIN(Inputs!$D$9*(1+Inputs!$D$11)^(A10-Inputs!$D$8-1),Inputs!$D$10*(1+Inputs!$D$12)^(A10-Inputs!$D$8-1))*Inputs!$D$13*(1-Inputs!$D$14),0) -> 217427.95 | D10: =IF(C10>0,Inputs!$D$15*(1+Inputs!$D$17)^(A10-Inputs!$D$8-1)+C10*Inputs!$D$16,0) -> 73156.04 | E10: =C10-D10 -> 144271.91 | F10: =IF(C10>0,Inputs!$D$2*Inputs!$D$18*(1+Inputs!$D$17)^(A10-Inputs!$D$8-1),0) -> 13513.949 | G10: =IF(A10=20,MAX(0,(Inputs!$D$2*12*MIN(Inputs!$D$9*(1+Inputs!$D$11)^(20-Inputs!$D$8),Inputs!$D$10*(1+Inputs!$D$12)^(20-Inputs!$D$8))*Inputs!$D$13*(1-Inputs!$D$14))*(1-Inputs!$D$16)-Inputs!$D$15*(1+Inputs!$D$17)^(20-Inputs!$D$8))/Inputs!$D$19*(1-Inputs!$D$20),0) -> 0 | H10: =E10-F10-B10+G10 -> 130757.96 | I10: =H10/(1+Inputs!$D$21)^A10 -> 79008.04 | J10: =SUM(H$2:H10) -> -2856810.3 | K10: =SUM(I$2:I10) -> -2987414.8 | L10: =IF(A10=Inputs!$D$8,SUM(B$2:B$22)*Inputs!$D$22,0) -> 0 | M10: =IF(AND(A10>Inputs!$D$8,A10<=Inputs!$D$8+Inputs!$D$24),-PMT(Inputs!$D$23,Inputs!$D$24,SUM(B$2:B$22)*Inputs!$D$22),0) -> 150548.26 | N10: =MAX(0,N9*(1+IF(M10>0,Inputs!$D$23,0))+L10-M10) -> 1503321.9 | O10: =H10+L10-M10-IF(A10=20,N10,0) -> -19790.297 | P10: =IF(M10>0,(E10-F10)/M10,0) -> 0.86854516 | Q10: =J10-SUM(G$2:G10) -> -2856810.3 | R10: =H10-(E10-F10-B10+G10) -> 0
A11: 9 | B11: =IF(A11=0,Inputs!$D$3*(1+Inputs!$D$4),IF(A11<=Inputs!$D$8,Inputs!$D$5*(1+Inputs!$D$6)*(1+Inputs!$D$7)/Inputs!$D$8,0)) -> 0 | C11: =IF(A11>Inputs!$D$8,Inputs!$D$2*12*MIN(Inputs!$D$9*(1+Inputs!$D$11)^(A11-Inputs!$D$8-1),Inputs!$D$10*(1+Inputs!$D$12)^(A11-Inputs!$D$8-1))*Inputs!$D$13*(1-Inputs!$D$14),0) -> 221776.51 | D11: =IF(C11>0,Inputs!$D$15*(1+Inputs!$D$17)^(A11-Inputs!$D$8-1)+C11*Inputs!$D$16,0) -> 74619.161 | E11: =C11-D11 -> 147157.35 | F11: =IF(C11>0,Inputs!$D$2*Inputs!$D$18*(1+Inputs!$D$17)^(A11-Inputs!$D$8-1),0) -> 13784.228 | G11: =IF(A11=20,MAX(0,(Inputs!$D$2*12*MIN(Inputs!$D$9*(1+Inputs!$D$11)^(20-Inputs!$D$8),Inputs!$D$10*(1+Inputs!$D$12)^(20-Inputs!$D$8))*Inputs!$D$13*(1-Inputs!$D$14))*(1-Inputs!$D$16)-Inputs!$D$15*(1+Inputs!$D$17)^(20-Inputs!$D$8))/Inputs!$D$19*(1-Inputs!$D$20),0) -> 0 | H11: =E11-F11-B11+G11 -> 133373.12 | I11: =H11/(1+Inputs!$D$21)^A11 -> 75669.672 | J11: =SUM(H$2:H11) -> -2723437.2 | K11: =SUM(I$2:I11) -> -2911745.1 | L11: =IF(A11=Inputs!$D$8,SUM(B$2:B$22)*Inputs!$D$22,0) -> 0 | M11: =IF(AND(A11>Inputs!$D$8,A11<=Inputs!$D$8+Inputs!$D$24),-PMT(Inputs!$D$23,Inputs!$D$24,SUM(B$2:B$22)*Inputs!$D$22),0) -> 150548.26 | N11: =MAX(0,N10*(1+IF(M11>0,Inputs!$D$23,0))+L11-M11) -> 1412906.5 | O11: =H11+L11-M11-IF(A11=20,N11,0) -> -17175.138 | P11: =IF(M11>0,(E11-F11)/M11,0) -> 0.88591607 | Q11: =J11-SUM(G$2:G11) -> -2723437.2 | R11: =H11-(E11-F11-B11+G11) -> 0
A12: 10 | B12: =IF(A12=0,Inputs!$D$3*(1+Inputs!$D$4),IF(A12<=Inputs!$D$8,Inputs!$D$5*(1+Inputs!$D$6)*(1+Inputs!$D$7)/Inputs!$D$8,0)) -> 0 | C12: =IF(A12>Inputs!$D$8,Inputs!$D$2*12*MIN(Inputs!$D$9*(1+Inputs!$D$11)^(A12-Inputs!$D$8-1),Inputs!$D$10*(1+Inputs!$D$12)^(A12-Inputs!$D$8-1))*Inputs!$D$13*(1-Inputs!$D$14),0) -> 226212.04 | D12: =IF(C12>0,Inputs!$D$15*(1+Inputs!$D$17)^(A12-Inputs!$D$8-1)+C12*Inputs!$D$16,0) -> 76111.544 | E12: =C12-D12 -> 150100.5 | F12: =IF(C12>0,Inputs!$D$2*Inputs!$D$18*(1+Inputs!$D$17)^(A12-Inputs!$D$8-1),0) -> 14059.913 | G12: =IF(A12=20,MAX(0,(Inputs!$D$2*12*MIN(Inputs!$D$9*(1+Inputs!$D$11)^(20-Inputs!$D$8),Inputs!$D$10*(1+Inputs!$D$12)^(20-Inputs!$D$8))*Inputs!$D$13*(1-Inputs!$D$14))*(1-Inputs!$D$16)-Inputs!$D$15*(1+Inputs!$D$17)^(20-Inputs!$D$8))/Inputs!$D$19*(1-Inputs!$D$20),0) -> 0 | H12: =E12-F12-B12+G12 -> 136040.59 | I12: =H12/(1+Inputs!$D$21)^A12 -> 72472.362 | J12: =SUM(H$2:H12) -> -2587396.6 | K12: =SUM(I$2:I12) -> -2839272.8 | L12: =IF(A12=Inputs!$D$8,SUM(B$2:B$22)*Inputs!$D$22,0) -> 0 | M12: =IF(AND(A12>Inputs!$D$8,A12<=Inputs!$D$8+Inputs!$D$24),-PMT(Inputs!$D$23,Inputs!$D$24,SUM(B$2:B$22)*Inputs!$D$22),0) -> 150548.26 | N12: =MAX(0,N11*(1+IF(M12>0,Inputs!$D$23,0))+L12-M12) -> 1318874.5 | O12: =H12+L12-M12-IF(A12=20,N12,0) -> -14507.675 | P12: =IF(M12>0,(E12-F12)/M12,0) -> 0.90363439 | Q12: =J12-SUM(G$2:G12) -> -2587396.6 | R12: =H12-(E12-F12-B12+G12) -> 0
A13: 11 | B13: =IF(A13=0,Inputs!$D$3*(1+Inputs!$D$4),IF(A13<=Inputs!$D$8,Inputs!$D$5*(1+Inputs!$D$6)*(1+Inputs!$D$7)/Inputs!$D$8,0)) -> 0 | C13: =IF(A13>Inputs!$D$8,Inputs!$D$2*12*MIN(Inputs!$D$9*(1+Inputs!$D$11)^(A13-Inputs!$D$8-1),Inputs!$D$10*(1+Inputs!$D$12)^(A13-Inputs!$D$8-1))*Inputs!$D$13*(1-Inputs!$D$14),0) -> 230736.28 | D13: =IF(C13>0,Inputs!$D$15*(1+Inputs!$D$17)^(A13-Inputs!$D$8-1)+C13*Inputs!$D$16,0) -> 77633.775 | E13: =C13-D13 -> 153102.51 | F13: =IF(C13>0,Inputs!$D$2*Inputs!$D$18*(1+Inputs!$D$17)^(A13-Inputs!$D$8-1),0) -> 14341.111 | G13: =IF(A13=20,MAX(0,(Inputs!$D$2*12*MIN(Inputs!$D$9*(1+Inputs!$D$11)^(20-Inputs!$D$8),Inputs!$D$10*(1+Inputs!$D$12)^(20-Inputs!$D$8))*Inputs!$D$13*(1-Inputs!$D$14))*(1-Inputs!$D$16)-Inputs!$D$15*(1+Inputs!$D$17)^(20-Inputs!$D$8))/Inputs!$D$19*(1-Inputs!$D$20),0) -> 0 | H13: =E13-F13-B13+G13 -> 138761.4 | I13: =H13/(1+Inputs!$D$21)^A13 -> 69410.149 | J13: =SUM(H$2:H13) -> -2448635.2 | K13: =SUM(I$2:I13) -> -2769862.6 | L13: =IF(A13=Inputs!$D$8,SUM(B$2:B$22)*Inputs!$D$22,0) -> 0 | M13: =IF(AND(A13>Inputs!$D$8,A13<=Inputs!$D$8+Inputs!$D$24),-PMT(Inputs!$D$23,Inputs!$D$24,SUM(B$2:B$22)*Inputs!$D$22),0) -> 150548.26 | N13: =MAX(0,N12*(1+IF(M13>0,Inputs!$D$23,0))+L13-M13) -> 1221081.3 | O13: =H13+L13-M13-IF(A13=20,N13,0) -> -11786.864 | P13: =IF(M13>0,(E13-F13)/M13,0) -> 0.92170707 | Q13: =J13-SUM(G$2:G13) -> -2448635.2 | R13: =H13-(E13-F13-B13+G13) -> 0
A14: 12 | B14: =IF(A14=0,Inputs!$D$3*(1+Inputs!$D$4),IF(A14<=Inputs!$D$8,Inputs!$D$5*(1+Inputs!$D$6)*(1+Inputs!$D$7)/Inputs!$D$8,0)) -> 0 | C14: =IF(A14>Inputs!$D$8,Inputs!$D$2*12*MIN(Inputs!$D$9*(1+Inputs!$D$11)^(A14-Inputs!$D$8-1),Inputs!$D$10*(1+Inputs!$D$12)^(A14-Inputs!$D$8-1))*Inputs!$D$13*(1-Inputs!$D$14),0) -> 235351.01 | D14: =IF(C14>0,Inputs!$D$15*(1+Inputs!$D$17)^(A14-Inputs!$D$8-1)+C14*Inputs!$D$16,0) -> 79186.45 | E14: =C14-D14 -> 156164.56 | F14: =IF(C14>0,Inputs!$D$2*Inputs!$D$18*(1+Inputs!$D$17)^(A14-Inputs!$D$8-1),0) -> 14627.933 | G14: =IF(A14=20,MAX(0,(Inputs!$D$2*12*MIN(Inputs!$D$9*(1+Inputs!$D$11)^(20-Inputs!$D$8),Inputs!$D$10*(1+Inputs!$D$12)^(20-Inputs!$D$8))*Inputs!$D$13*(1-Inputs!$D$14))*(1-Inputs!$D$16)-Inputs!$D$15*(1+Inputs!$D$17)^(20-Inputs!$D$8))/Inputs!$D$19*(1-Inputs!$D$20),0) -> 0 | H14: =E14-F14-B14+G14 -> 141536.63 | I14: =H14/(1+Inputs!$D$21)^A14 -> 66477.326 | J14: =SUM(H$2:H14) -> -2307098.6 | K14: =SUM(I$2:I14) -> -2703385.3 | L14: =IF(A14=Inputs!$D$8,SUM(B$2:B$22)*Inputs!$D$22,0) -> 0 | M14: =IF(AND(A14>Inputs!$D$8,A14<=Inputs!$D$8+Inputs!$D$24),-PMT(Inputs!$D$23,Inputs!$D$24,SUM(B$2:B$22)*Inputs!$D$22),0) -> 150548.26 | N14: =MAX(0,N13*(1+IF(M14>0,Inputs!$D$23,0))+L14-M14) -> 1119376.2 | O14: =H14+L14-M14-IF(A14=20,N14,0) -> -9011.6358 | P14: =IF(M14>0,(E14-F14)/M14,0) -> 0.94014122 | Q14: =J14-SUM(G$2:G14) -> -2307098.6 | R14: =H14-(E14-F14-B14+G14) -> 0
... A22: 20 | B22: =IF(A22=0,Inputs!$D$3*(1+Inputs!$D$4),IF(A22<=Inputs!$D$8,Inputs!$D$5*(1+Inputs!$D$6)*(1+Inputs!$D$7)/Inputs!$D$8,0)) -> 0 | C22: =IF(A22>Inputs!$D$8,Inputs!$D$2*12*MIN(Inputs!$D$9*(1+Inputs!$D$11)^(A22-Inputs!$D$8-1),Inputs!$D$10*(1+Inputs!$D$12)^(A22-Inputs!$D$8-1))*Inputs!$D$13*(1-Inputs!$D$14),0) -> 275751.22 | D22: =IF(C22>0,Inputs!$D$15*(1+Inputs!$D$17)^(A22-Inputs!$D$8-1)+C22*Inputs!$D$16,0) -> 92779.548 | E22: =C22-D22 -> 182971.67 | F22: =IF(C22>0,Inputs!$D$2*Inputs!$D$18*(1+Inputs!$D$17)^(A22-Inputs!$D$8-1),0) -> 17138.955 | G22: =IF(A22=20,MAX(0,(Inputs!$D$2*12*MIN(Inputs!$D$9*(1+Inputs!$D$11)^(20-Inputs!$D$8),Inputs!$D$10*(1+Inputs!$D$12)^(20-Inputs!$D$8))*Inputs!$D$13*(1-Inputs!$D$14))*(1-Inputs!$D$16)-Inputs!$D$15*(1+Inputs!$D$17)^(20-Inputs!$D$8))/Inputs!$D$19*(1-Inputs!$D$20),0) -> 3850494.3 | H22: =E22-F22-B22+G22 -> 4016327.1 | I22: =H22/(1+Inputs!$D$21)^A22 -> 1139821.7 | J22: =SUM(H$2:H22) -> 2782496.3 | K22: =SUM(I$2:I22) -> -1170564.6 | L22: =IF(A22=Inputs!$D$8,SUM(B$2:B$22)*Inputs!$D$22,0) -> 0 | M22: =IF(AND(A22>Inputs!$D$8,A22<=Inputs!$D$8+Inputs!$D$24),-PMT(Inputs!$D$23,Inputs!$D$24,SUM(B$2:B$22)*Inputs!$D$22),0) -> 150548.26 | N22: =MAX(0,N21*(1+IF(M22>0,Inputs!$D$23,0))+L22-M22) -> 144757.94 | O22: =H22+L22-M22-IF(A22=20,N22,0) -> 3721020.9 | P22: =IF(M22>0,(E22-F22)/M22,0) -> 1.1015253 | Q22: =J22-SUM(G$2:G22) -> -1067998 | R22: =H22-(E22-F22-B22+G22) -> 0
A25: Payback uses first nonnegative cumulative end-year; includes sale at year 20 if needed.
A26: Debt drawn at completion; bridging interest and loan fees excluded. Equity IRR is indicative.

Sheet Due diligence
A1: Area | B1: Requirement / question | C1: Evidence needed | D1: Status | E1: Impact
A2: Planning / permitted use | B2: Obtain title, planning history, approved plans, subdivision/change-of-use and heritage constraints. | C2: Architect + Ixelles written planning position; S3 | D2: OPEN — not verified | E2: Capacity, delay, redesign and refusal risk
A3: Housing quality | B3: Verify 2026 standards: net area, height, daylight, ventilation, sanitation, heating and electrical/gas safety. | C3: Architect room schedule and technical reports; S1/S2 | D3: OPEN — not verified | E3: Room count and capex
A4: Fire strategy | B4: Confirm evacuation, compartmentation, access, detection and any SIAMU review/certification applicable to this building. | C4: Fire engineer + competent authority; S2 | D4: OPEN — not verified | E4: Design and opening date
A5: PEB and environment | B5: Confirm building classification, certificates, works procedure, renovation duties and environmental permit applicability. | C5: PEB adviser + permit assessment; S6 | D5: OPEN — not verified | E5: Initial and future capex, utilities
A6: Accessibility / amenity | B6: Verify applicable accessibility, bicycle, waste, noise and shared-facility requirements. | C6: Architect and municipality; S3 | D6: OPEN — not verified | E6: Usable area / costs
A7: Student leases | B7: Review student eligibility, duration, termination, inventory, deposits, charges, registration and indexation conditions. | C7: Brussels housing lawyer; S4 | D7: OPEN — not verified | E7: Turnover, revenue timing, enforceability
A8: Rent legality | B8: Obtain reference-rent assessment; assess excessive-rent rules and applicable indexation restrictions. | C8: Legal opinion and reference calculation; S5/S7 | D8: OPEN — not verified | E8: Rent cap may need reduction
A9: Local affordability obligation | B9: Check whether municipal affordable-kot policy or permit agreement applies and on what terms. | C9: Written Ixelles confirmation; S8 | D9: OPEN — not verified | E9: Unit mix / affordable rent obligations
A10: Affordability evidence | B10: Validate rent + utilities against target student resources; confirm no hidden charges and summer contract assumptions. | C10: Student survey, university partners and charge budget | D10: OPEN — not verified | E10: Demand, ethical affordability
A11: Tax / VAT / ownership | B11: Confirm duties, municipal/property taxes, VAT and recovery, transaction structure, corporate or personal income tax. | C11: Notary and tax adviser; acquisition allowance is unverified | D11: OPEN — not verified | E11: After-tax return not yet modelled
A12: Funding | B12: Obtain term sheet and bridge interest/fees; test covenant DSCR and cost overruns. | C12: Lender and quantity surveyor | D12: OPEN — not verified | E12: Liquidity and equity requirement
A13: Demand and comparables | B13: Collect dated comparable asking/achieved rents, vacancy, enrollment, pipeline and travel times. | C13: University/Brik/Mykot data + local inspections | D13: OPEN — not verified | E13: Scenario calibration

Sheet Sources
A1: Topic | B1: URL | C1: Verified date | D1: Finding / limitation
A2: S1 Housing quality 2026 | B2: https://be.brussels/fr/logement/nouvelles-normes-minimales-de-qualite-partir-de-2026 | C2: 2026-10-14 | D2: New minimum standards apply from 1 Jan 2026; official summary gives 12 m² student minimum. Architect must assess actual layout, shared areas and all technical rules.
A3: S2 Safety and fire | B3: https://be.brussels/fr/logement/location/conformite-logement/normes-et-securite | C3: 2026-10-14 | D3: Housing must meet safety, health and equipment standards; smoke detection requirements updated from 2025. Building-specific fire strategy remains to be agreed.
A4: S3 Ixelles planning | B4: https://www.ixelles.be/site/880-Guichet-electronique-Urbanisme | C4: 2026-10-14 | D4: Municipal portal provides planning permit and urban-planning information requests; address-specific permitted use/capacity not verified.
A5: S4 Lease process | B5: https://be.brussels/fr/logement/location/les-differentes-etapes-de-la-location | C5: 2026-10-14 | D5: Regional portal explains disclosure, lease types and reference rents; check current student lease terms and registration procedure before letting.
A6: S5 Excessive rents | B6: https://be.brussels/fr/logement/creation-de-la-commission-paritaire-locative | C6: 2026-10-14 | D6: Landlords must not offer abusive rents from 1 May 2025; CPL offers free nonbinding opinions. A policy affordability ceiling alone does not establish compliance.
A7: S6 PEB works | B7: https://environnement.brussels/pro/reglementation-et-inspection/obligations-et-autorisations/objectifs-peb-pour-chaque-bien-et-exigences-peb-en-cas-de-travaux | C7: 2026-10-14 | D7: PEB requirements depend on use and nature of works; establish classification with PEB adviser and include required measures in budget.
A8: S7 Reference rents | B8: https://loyers.brussels/a-propos-des-loyers-de-reference | C8: 2026-10-14 | D8: Reference rent methodology indexed January 2026. Obtain address/layout-specific assessment and legal interpretation.
A9: S8 Ixelles market context | B9: https://www.ixelles.be/site/downloads/publications/infoxl-2014-/infoxl20250708.pdf | C9: 2026-10-14 | D9: Municipal July/August 2025 dossier describes strong student demand and insufficient supply. It mentions a 15% affordable-kot initiative for large projects; verify adoption, scope and site applicability. This is not an underwriting rent survey.
A10: S9 Housing label | B10: https://be.brussels/en/about-region/structure-and-organisations/overview-administrations-and-institutions-region/brussels-housing/structure-brussels-housing/regional-housing-inspectorate-dirl | C10: 2026-10-14 | D10: DIRL enforces housing standards and awards student quality label. Optional conformity certificate is distinct from mandatory compliance and post-ban attestation.

Sheet Prompt
A1: REUSABLE PROJECT PROMPT | B1: Instructions
A2: Copy and reuse | B2: Act as a real estate investment analyst specializing in affordable student housing in Ixelles/Elsene, Brussels. Build a transparent, editable 20-year nominal EUR model with Bad, Intermediate and Optimal scenarios. Ask for property address, title, permitted use, rooms and areas, acquisition terms, gross works quotes, student rent/budget evidence, operating costs, financing, legal entity and tax treatment. Clearly label any missing data and illustrative assumptions. Verify current rules using official Brussels and Ixelles sources; cite dated links, distinguish mandatory obligations from voluntary labels, and never assume a permit or compliance. Cover change of use, planning, housing quality, fire safety, energy/PEB, accessibility, leases, rent reference/excessive rent controls, indexation, charges, deposits, registration and taxation. Apply an explicit affordable rent ceiling and test rent plus utilities against student resources. Include construction delays, cost overruns, vacancy, bad debt, maintenance, capex and exit yield risk. Calculate annual project and equity cash flows, NPV, IRR, simple and discounted payback, yield on cost, cost per bed, DSCR, operating break-even occupancy, affordability share and dependence on terminal value. Define timing, discount rates, tax/VAT assumptions, financing and terminal value; show operating-only versus sale-assisted payback. Add rent/works-cost/exit-yield sensitivities, qualitative risks, evidence gaps and go/no-go conditions. Explain market complexity including student demand, seasonality, substitutes, neighbourhood fit, transport, university proximity and supply pipeline. Do not improve returns by violating affordability or regulatory requirements. Deliver a usable workbook with traceable formulas, sources and limitations; state whether results justify proceeding to property-specific due diligence.

Sheet Market and risks
A1: Driver | B1: Quantitative model link | C1: Qualitative assessment / evidence to collect | D1: Mitigation / gate
A2: University proximity | B2: Occupancy / rent | C2: Measure walking/cycling/transit times to ULB and VUB; exact site not provided. | D2: Verify catchment before purchase
A3: Demand segmentation | B3: Rent ceiling / budget share | C3: Local, international, grant-supported students have different budgets and contract needs. | D3: Survey intended tenants; avoid dependence on premium rents
A4: Seasonality / turnover | B4: Annual occupancy | C4: 12-month billing assumed. Summer vacancies and short contracts reduce effective occupancy. | D4: Underwrite achieved annual collections; stress summer gap
A5: Competitive supply | B5: Occupancy / exit yield | C5: University residences, private kots, shared flats and pipeline projects compete by price and quality. | D5: Dated comparable and pipeline study
A6: Planning uncertainty | B6: Development years / overrun | C6: Permits, objections, heritage and room-layout limits can delay opening or reduce beds. | D6: Conditional acquisition and detailed feasibility
A7: Neighbourhood acceptance | B7: Delay / owner costs | C7: Noise, waste, cycling, visitor management and community relations affect operation. | D7: Management plan and municipal consultation
A8: Energy and ageing assets | B8: Inflation / reserve | C8: Envelope, heating and compliance renewal may cost more than annual allowance. | D8: 20-year technical capex plan and contingency
A9: Affordability vs viability | B9: Ceiling / NPV / DSCR | C9: Returns may fail at affordable prices. Do not solve a poor investment by assuming unaffordable rent. | D9: Negotiate purchase/build cost; consider evidenced grants or lower required return
A10: Exit liquidity | B10: Exit yield / exit PV share | C10: Single-use assets and regulation can narrow buyer pool; terminal value is uncertain. | D10: Conservative exit yield; inspect no-sale returns

Sheet Sensitivity
A1: INTERMEDIATE NPV | works cost vs exit yield | B1: Works -20% | C1: Works base | D1: Works +20%
A2: Exit yield -1pp | B2: =Dashboard!C2-(-0.2)*SUMPRODUCT(Intermediate!B3:B22/(1+Inputs!C21)^Intermediate!A3:A22)+(Intermediate!G22*(Inputs!C19/(Inputs!C19+(-0.01))-1))/(1+Inputs!C21)^20 -> -1691166.9 | C2: =Dashboard!C2-(0)*SUMPRODUCT(Intermediate!B3:B22/(1+Inputs!C21)^Intermediate!A3:A22)+(Intermediate!G22*(Inputs!C19/(Inputs!C19+(-0.01))-1))/(1+Inputs!C21)^20 -> -2022987.4 | D2: =Dashboard!C2-(0.2)*SUMPRODUCT(Intermediate!B3:B22/(1+Inputs!C21)^Intermediate!A3:A22)+(Intermediate!G22*(Inputs!C19/(Inputs!C19+(-0.01))-1))/(1+Inputs!C21)^20 -> -2354807.8
A3: Exit yield base | B3: =Dashboard!C2-(-0.2)*SUMPRODUCT(Intermediate!B3:B22/(1+Inputs!C21)^Intermediate!A3:A22)+(Intermediate!G22*(Inputs!C19/(Inputs!C19+(0))-1))/(1+Inputs!C21)^20 -> -1834855.1 | C3: =Dashboard!C2-(0)*SUMPRODUCT(Intermediate!B3:B22/(1+Inputs!C21)^Intermediate!A3:A22)+(Intermediate!G22*(Inputs!C19/(Inputs!C19+(0))-1))/(1+Inputs!C21)^20 -> -2166675.5 | D3: =Dashboard!C2-(0.2)*SUMPRODUCT(Intermediate!B3:B22/(1+Inputs!C21)^Intermediate!A3:A22)+(Intermediate!G22*(Inputs!C19/(Inputs!C19+(0))-1))/(1+Inputs!C21)^20 -> -2498496
A4: Exit yield +1pp | B4: =Dashboard!C2-(-0.2)*SUMPRODUCT(Intermediate!B3:B22/(1+Inputs!C21)^Intermediate!A3:A22)+(Intermediate!G22*(Inputs!C19/(Inputs!C19+(0.01))-1))/(1+Inputs!C21)^20 -> -1934331.5 | C4: =Dashboard!C2-(0)*SUMPRODUCT(Intermediate!B3:B22/(1+Inputs!C21)^Intermediate!A3:A22)+(Intermediate!G22*(Inputs!C19/(Inputs!C19+(0.01))-1))/(1+Inputs!C21)^20 -> -2266152 | D4: =Dashboard!C2-(0.2)*SUMPRODUCT(Intermediate!B3:B22/(1+Inputs!C21)^Intermediate!A3:A22)+(Intermediate!G22*(Inputs!C19/(Inputs!C19+(0.01))-1))/(1+Inputs!C21)^20 -> -2597972.4
A7: Holds rent and affordability ceiling fixed. Works multiplier includes proportional professional fees; acquisition unchanged.
A8: Delay and occupancy stress are represented jointly by the three main scenarios. Sensitivity is not a forecast probability.
