Workbook

Sheet Read me
A1: VUB student housing | investment feasibility
A3: Research version | 14 October 2026 | educational feasibility, pre-tax cash flows
A4: Location: assumed site within walking/cycling distance of VUB Etterbeek campus; no land secured.
A5: No classroom workbook supplied in the working folder; model built from first principles.
A6: Shared studio means two students per studio. Rents exclude separately billed actual utilities.
A7: Blue cells = editable inputs; black cells = formulas. EUR nominal, annual periods.
A8: Recommendation: test 120 beds in 100 units (60 normal, 20 two-person studios, 20 single studios). Demand case is plausible; financial acceptance depends on dashboard.
A9: 120 beds limits exposure to the 465-room Usquare pipeline. No verified VUB waiting-list count or secured plot: capacity remains a testable proposal.
A10: Model timeline: year 0 = 2027, year 1 = 2028 construction, year 2 = 2029 opening; 20 operating years; sale at end of year 21.
A11: Cash flows are year-end; debt draws are half in each construction year. Construction interest uses midyear draws; first debt repayment at opening.
A12: Nonrecoverable VAT 21%, land transaction allowance 15%, construction price, land price and financing are assumptions requiring professional quotations.
A13: Utilities are reimbursed at actual cost, outside revenue and expenses. Operating ratio includes management, insurance, owner property tax, maintenance and administration.
... A18: Shared studio is let as one unit to two occupants; divide the unit rent by two for per-person affordability. Validate compatibility with actual tenant arrangements.

Sheet Inputs
A1: Assumption | B1: Value | C1: Basis / unit
A2: Normal rooms | B2: 60 | C2: units
A3: Shared studios | B3: 20 | C3: units; 2 beds each
A4: Single studios | B4: 20 | C4: units
A5: Normal monthly rent | B5: 480 | C5: EUR per room; provisional
A6: Shared monthly rent | B6: 390 | C6: EUR per person; provisional
A7: Single studio monthly rent | B7: 650 | C7: EUR per unit; provisional
A8: Letting months | B8: 12 | C8: months/year
A9: Occupancy | B9: 0.95 | C9: stabilised
A10: Rent growth | B10: 0.02 | C10: annual
A11: Operating expense ratio | B11: 0.28 | C11: share of effective rent
A12: Reserve per bed | B12: 150 | C12: EUR/year
A13: Hard cost per gross sqm | B13: 2200 | C13: EUR; assumption
... A23: Selling cost | B23: 0.02 | C23: share exit value
A24: Construction years | B24: 2 years fixed | C24: fixed 2-year baseline
A25: Normal room net area | B25: 18 | C25: sqm
A26: Shared studio net area | B26: 32 | C26: sqm per unit
A27: Single studio net area | B27: 25 | C27: sqm
A28: Grossing factor | B28: 1.4 | C28: gross / net
A29: Opening occupancy | B29: 0.85 | C29: first operating year
A30: Operating years | B30: 20 years fixed | C30: fixed baseline
A31: Equity discount rate | B31: 0.1 | C31: annual
A32: Land acquisition allowance | B32: 0.15 | C32: assumption; land price includes no transaction fees
A33: Furniture per bed | B33: 1800 | C33: EUR; initial furnishing
A34: Initial working capital | B34: 50000 | C34: EUR; conservatively unrecovered at exit
A35: Reference rent policy factor | B35: 1 | C35: stay at/below reference when supplied; max 1.2 screening threshold
A36: Candidate beds | B36: 120 | C36: planning target; mix on rows 2:4 drives actual capacity

Sheet Room mix
A1: Type | B1: Units | C1: Beds per unit | D1: Beds | E1: Net sqm/unit | F1: Gross sqm | G1: Rent/person/month | H1: Annual gross rent
A2: Normal dorm | B2: =Inputs!B2 -> 60 | C2: 1 | D2: =B2*C2 -> 60 | E2: =Inputs!B25 -> 18 | F2: =B2*E2*Inputs!B28 -> 1512 | G2: ='Rent rules'!F2 -> 480 | H2: =D2*G2*Inputs!B8 -> 345600
A3: Shared studio | B3: =Inputs!B3 -> 20 | C3: 2 | D3: =B3*C3 -> 40 | E3: =Inputs!B26 -> 32 | F3: =B3*E3*Inputs!B28 -> 896 | G3: ='Rent rules'!F3 -> 390 | H3: =D3*G3*Inputs!B8 -> 187200
A4: Single studio | B4: =Inputs!B4 -> 20 | C4: 1 | D4: =B4*C4 -> 20 | E4: =Inputs!B27 -> 25 | F4: =B4*E4*Inputs!B28 -> 700 | G4: ='Rent rules'!F4 -> 650 | H4: =D4*G4*Inputs!B8 -> 156000
A5: Total | B5: =SUM(B2:B4) -> 100 | D5: =SUM(D2:D4) -> 120 | F5: =SUM(F2:F4) -> 3108 | H5: =SUM(H2:H4) -> 688800

Sheet Development
A1: Development budget | B1: EUR
A2: Land | B2: =Inputs!B14 -> 1800000
A3: Hard costs | B3: ='Room mix'!F5*Inputs!B13 -> 6837600
A4: Soft costs | B4: =B3*Inputs!B15 -> 1025640
A5: Contingency | B5: =SUM(B3:B4)*Inputs!B16 -> 786324
A6: Nonrecoverable VAT | B6: =SUM(B3:B5)*Inputs!B17 -> 1816408.4
A7: Total funding need | B7: =B15+B14 -> 13118821
A8: Debt | B8: =B15*Inputs!B18 -> 7041084.8
A9: Equity | B9: =B7-B8 -> 6077736.4
A10: Annual debt service | B10: =-PMT(Inputs!B19,Inputs!B20,B8) -> 474843.92
A11: Land transaction allowance | B11: =B2*Inputs!B32 -> 270000
A12: Furniture | B12: ='Room mix'!D5*Inputs!B33 -> 216000
A13: Working capital | B13: =Inputs!B34 -> 50000
A14: Construction interest (equity-funded) | B14: =B8*Inputs!B19 -> 316848.82
A15: Unlevered project cost | B15: =SUM(B2:B6,B11:B13) -> 12801972
A16: Cost per bed | B16: =B7/'Room mix'!D5 -> 109323.51

Sheet Cash flow
A1: Year | B1: Gross rent | C1: Occupancy | D1: Effective rent | E1: Operating cost | F1: Reserve | G1: NOI | H1: Development spend | I1: Debt draw | J1: Debt service | K1: Exit proceeds | L1: Debt outstanding | M1: Unlevered CF | N1: Equity CF | O1: Interest paid | P1: Principal repaid | Q1: Calendar year | R1: DSCR
A2: 0 | B2: 0 | C2: 0 | D2: 0 | E2: 0 | F2: 0 | G2: 0 | H2: =Development!B15*0.5 -> 6400986.2 | I2: =Development!B8*0.5 -> 3520542.4 | J2: 0 | K2: 0 | L2: =SUM(I$2:I2) -> 3520542.4 | M2: =G2-H2+K2 -> -6400986.2 | N2: =M2+I2-J2-Development!B14*0.5 -> -3038868.2 | O2: 0 | P2: 0 | Q2: =A2+2027 -> 2027 | R2: 0
A3: 1 | B3: 0 | C3: 0 | D3: 0 | E3: 0 | F3: 0 | G3: 0 | H3: =Development!B15*0.5 -> 6400986.2 | I3: =Development!B8*0.5 -> 3520542.4 | J3: 0 | K3: 0 | L3: =SUM(I$2:I3) -> 7041084.8 | M3: =G3-H3+K3 -> -6400986.2 | N3: =M3+I3-J3-Development!B14*0.5 -> -3038868.2 | O3: 0 | P3: 0 | Q3: =A3+2027 -> 2028 | R3: 0
A4: 2 | B4: ='Room mix'!H5*(1+Inputs!B10)^(1-1) -> 688800 | C4: =Inputs!B29 -> 0.85 | D4: =B4*C4 -> 585480 | E4: =D4*Inputs!B11 -> 163934.4 | F4: ='Room mix'!D5*Inputs!B12*(1+Inputs!B10)^(1-1) -> 18000 | G4: =D4-E4-F4 -> 403545.6 | H4: 0 | I4: 0 | J4: =IF(A4-1<=Inputs!B20,Development!B10,0) -> 474843.92 | K4: 0 | L4: =MAX(0,L3*(1+Inputs!B19)-J4) -> 6883089.7 | M4: =G4-H4+K4 -> 403545.6 | N4: =M4+I4-J4 -> -71298.318 | O4: =L3*Inputs!B19 -> 316848.82 | P4: =J4-O4 -> 157995.1 | Q4: =A4+2027 -> 2029 | R4: =IF(J4>0,G4/J4,0) -> 0.84984894
A5: 3 | B5: ='Room mix'!H5*(1+Inputs!B10)^(2-1) -> 702576 | C5: =Inputs!B9 -> 0.95 | D5: =B5*C5 -> 667447.2 | E5: =D5*Inputs!B11 -> 186885.22 | F5: ='Room mix'!D5*Inputs!B12*(1+Inputs!B10)^(2-1) -> 18360 | G5: =D5-E5-F5 -> 462201.98 | H5: 0 | I5: 0 | J5: =IF(A5-1<=Inputs!B20,Development!B10,0) -> 474843.92 | K5: 0 | L5: =MAX(0,L4*(1+Inputs!B19)-J5) -> 6717984.9 | M5: =G5-H5+K5 -> 462201.98 | N5: =M5+I5-J5 -> -12641.934 | O5: =L4*Inputs!B19 -> 309739.04 | P5: =J5-O5 -> 165104.88 | Q5: =A5+2027 -> 2030 | R5: =IF(J5>0,G5/J5,0) -> 0.97337665
A6: 4 | B6: ='Room mix'!H5*(1+Inputs!B10)^(3-1) -> 716627.52 | C6: =Inputs!B9 -> 0.95 | D6: =B6*C6 -> 680796.14 | E6: =D6*Inputs!B11 -> 190622.92 | F6: ='Room mix'!D5*Inputs!B12*(1+Inputs!B10)^(3-1) -> 18727.2 | G6: =D6-E6-F6 -> 471446.02 | H6: 0 | I6: 0 | J6: =IF(A6-1<=Inputs!B20,Development!B10,0) -> 474843.92 | K6: 0 | L6: =MAX(0,L5*(1+Inputs!B19)-J6) -> 6545450.3 | M6: =G6-H6+K6 -> 471446.02 | N6: =M6+I6-J6 -> -3397.8944 | O6: =L5*Inputs!B19 -> 302309.32 | P6: =J6-O6 -> 172534.6 | Q6: =A6+2027 -> 2031 | R6: =IF(J6>0,G6/J6,0) -> 0.99284419
A7: 5 | B7: ='Room mix'!H5*(1+Inputs!B10)^(4-1) -> 730960.07 | C7: =Inputs!B9 -> 0.95 | D7: =B7*C7 -> 694412.07 | E7: =D7*Inputs!B11 -> 194435.38 | F7: ='Room mix'!D5*Inputs!B12*(1+Inputs!B10)^(4-1) -> 19101.744 | G7: =D7-E7-F7 -> 480874.94 | H7: 0 | I7: 0 | J7: =IF(A7-1<=Inputs!B20,Development!B10,0) -> 474843.92 | K7: 0 | L7: =MAX(0,L6*(1+Inputs!B19)-J7) -> 6365151.6 | M7: =G7-H7+K7 -> 480874.94 | N7: =M7+I7-J7 -> 6031.0261 | O7: =L6*Inputs!B19 -> 294545.26 | P7: =J7-O7 -> 180298.66 | Q7: =A7+2027 -> 2032 | R7: =IF(J7>0,G7/J7,0) -> 1.0127011
A8: 6 | B8: ='Room mix'!H5*(1+Inputs!B10)^(5-1) -> 745579.27 | C8: =Inputs!B9 -> 0.95 | D8: =B8*C8 -> 708300.31 | E8: =D8*Inputs!B11 -> 198324.09 | F8: ='Room mix'!D5*Inputs!B12*(1+Inputs!B10)^(5-1) -> 19483.779 | G8: =D8-E8-F8 -> 490492.44 | H8: 0 | I8: 0 | J8: =IF(A8-1<=Inputs!B20,Development!B10,0) -> 474843.92 | K8: 0 | L8: =MAX(0,L7*(1+Inputs!B19)-J8) -> 6176739.5 | M8: =G8-H8+K8 -> 490492.44 | N8: =M8+I8-J8 -> 15648.525 | O8: =L7*Inputs!B19 -> 286431.82 | P8: =J8-O8 -> 188412.1 | Q8: =A8+2027 -> 2033 | R8: =IF(J8>0,G8/J8,0) -> 1.0329551
A9: 7 | B9: ='Room mix'!H5*(1+Inputs!B10)^(6-1) -> 760490.86 | C9: =Inputs!B9 -> 0.95 | D9: =B9*C9 -> 722466.31 | E9: =D9*Inputs!B11 -> 202290.57 | F9: ='Room mix'!D5*Inputs!B12*(1+Inputs!B10)^(6-1) -> 19873.454 | G9: =D9-E9-F9 -> 500302.29 | H9: 0 | I9: 0 | J9: =IF(A9-1<=Inputs!B20,Development!B10,0) -> 474843.92 | K9: 0 | L9: =MAX(0,L8*(1+Inputs!B19)-J9) -> 5979848.9 | M9: =G9-H9+K9 -> 500302.29 | N9: =M9+I9-J9 -> 25458.374 | O9: =L8*Inputs!B19 -> 277953.28 | P9: =J9-O9 -> 196890.64 | Q9: =A9+2027 -> 2034 | R9: =IF(J9>0,G9/J9,0) -> 1.0536142
A10: 8 | B10: ='Room mix'!H5*(1+Inputs!B10)^(7-1) -> 775700.67 | C10: =Inputs!B9 -> 0.95 | D10: =B10*C10 -> 736915.64 | E10: =D10*Inputs!B11 -> 206336.38 | F10: ='Room mix'!D5*Inputs!B12*(1+Inputs!B10)^(7-1) -> 20270.924 | G10: =D10-E10-F10 -> 510308.34 | H10: 0 | I10: 0 | J10: =IF(A10-1<=Inputs!B20,Development!B10,0) -> 474843.92 | K10: 0 | L10: =MAX(0,L9*(1+Inputs!B19)-J10) -> 5774098.2 | M10: =G10-H10+K10 -> 510308.34 | N10: =M10+I10-J10 -> 35464.42 | O10: =L9*Inputs!B19 -> 269093.2 | P10: =J10-O10 -> 205750.72 | Q10: =A10+2027 -> 2035 | R10: =IF(J10>0,G10/J10,0) -> 1.0746865
A11: 9 | B11: ='Room mix'!H5*(1+Inputs!B10)^(8-1) -> 791214.69 | C11: =Inputs!B9 -> 0.95 | D11: =B11*C11 -> 751653.95 | E11: =D11*Inputs!B11 -> 210463.11 | F11: ='Room mix'!D5*Inputs!B12*(1+Inputs!B10)^(8-1) -> 20676.342 | G11: =D11-E11-F11 -> 520514.5 | H11: 0 | I11: 0 | J11: =IF(A11-1<=Inputs!B20,Development!B10,0) -> 474843.92 | K11: 0 | L11: =MAX(0,L10*(1+Inputs!B19)-J11) -> 5559088.7 | M11: =G11-H11+K11 -> 520514.5 | N11: =M11+I11-J11 -> 45670.586 | O11: =L10*Inputs!B19 -> 259834.42 | P11: =J11-O11 -> 215009.5 | Q11: =A11+2027 -> 2036 | R11: =IF(J11>0,G11/J11,0) -> 1.0961802
A12: 10 | B12: ='Room mix'!H5*(1+Inputs!B10)^(9-1) -> 807038.98 | C12: =Inputs!B9 -> 0.95 | D12: =B12*C12 -> 766687.03 | E12: =D12*Inputs!B11 -> 214672.37 | F12: ='Room mix'!D5*Inputs!B12*(1+Inputs!B10)^(9-1) -> 21089.869 | G12: =D12-E12-F12 -> 530924.79 | H12: 0 | I12: 0 | J12: =IF(A12-1<=Inputs!B20,Development!B10,0) -> 474843.92 | K12: 0 | L12: =MAX(0,L11*(1+Inputs!B19)-J12) -> 5334403.7 | M12: =G12-H12+K12 -> 530924.79 | N12: =M12+I12-J12 -> 56080.876 | O12: =L11*Inputs!B19 -> 250158.99 | P12: =J12-O12 -> 224684.93 | Q12: =A12+2027 -> 2037 | R12: =IF(J12>0,G12/J12,0) -> 1.1181038
A13: 11 | B13: ='Room mix'!H5*(1+Inputs!B10)^(10-1) -> 823179.76 | C13: =Inputs!B9 -> 0.95 | D13: =B13*C13 -> 782020.77 | E13: =D13*Inputs!B11 -> 218965.82 | F13: ='Room mix'!D5*Inputs!B12*(1+Inputs!B10)^(10-1) -> 21511.666 | G13: =D13-E13-F13 -> 541543.29 | H13: 0 | I13: 0 | J13: =IF(A13-1<=Inputs!B20,Development!B10,0) -> 474843.92 | K13: 0 | L13: =MAX(0,L12*(1+Inputs!B19)-J13) -> 5099608 | M13: =G13-H13+K13 -> 541543.29 | N13: =M13+I13-J13 -> 66699.372 | O13: =L12*Inputs!B19 -> 240048.17 | P13: =J13-O13 -> 234795.75 | Q13: =A13+2027 -> 2038 | R13: =IF(J13>0,G13/J13,0) -> 1.1404659
A14: 12 | B14: ='Room mix'!H5*(1+Inputs!B10)^(11-1) -> 839643.36 | C14: =Inputs!B9 -> 0.95 | D14: =B14*C14 -> 797661.19 | E14: =D14*Inputs!B11 -> 223345.13 | F14: ='Room mix'!D5*Inputs!B12*(1+Inputs!B10)^(11-1) -> 21941.9 | G14: =D14-E14-F14 -> 552374.16 | H14: 0 | I14: 0 | J14: =IF(A14-1<=Inputs!B20,Development!B10,0) -> 474843.92 | K14: 0 | L14: =MAX(0,L13*(1+Inputs!B19)-J14) -> 4854246.4 | M14: =G14-H14+K14 -> 552374.16 | N14: =M14+I14-J14 -> 77530.238 | O14: =L13*Inputs!B19 -> 229482.36 | P14: =J14-O14 -> 245361.56 | Q14: =A14+2027 -> 2039 | R14: =IF(J14>0,G14/J14,0) -> 1.1632752
A15: 13 | B15: ='Room mix'!H5*(1+Inputs!B10)^(12-1) -> 856436.22 | C15: =Inputs!B9 -> 0.95 | D15: =B15*C15 -> 813614.41 | E15: =D15*Inputs!B11 -> 227812.04 | F15: ='Room mix'!D5*Inputs!B12*(1+Inputs!B10)^(12-1) -> 22380.738 | G15: =D15-E15-F15 -> 563421.64 | H15: 0 | I15: 0 | J15: =IF(A15-1<=Inputs!B20,Development!B10,0) -> 474843.92 | K15: 0 | L15: =MAX(0,L14*(1+Inputs!B19)-J15) -> 4597843.6 | M15: =G15-H15+K15 -> 563421.64 | N15: =M15+I15-J15 -> 88577.721 | O15: =L14*Inputs!B19 -> 218441.09 | P15: =J15-O15 -> 256402.83 | Q15: =A15+2027 -> 2040 | R15: =IF(J15>0,G15/J15,0) -> 1.1865407
A16: 14 | B16: ='Room mix'!H5*(1+Inputs!B10)^(13-1) -> 873564.95 | C16: =Inputs!B9 -> 0.95 | D16: =B16*C16 -> 829886.7 | E16: =D16*Inputs!B11 -> 232368.28 | F16: ='Room mix'!D5*Inputs!B12*(1+Inputs!B10)^(13-1) -> 22828.352 | G16: =D16-E16-F16 -> 574690.07 | H16: 0 | I16: 0 | J16: =IF(A16-1<=Inputs!B20,Development!B10,0) -> 474843.92 | K16: 0 | L16: =MAX(0,L15*(1+Inputs!B19)-J16) -> 4329902.6 | M16: =G16-H16+K16 -> 574690.07 | N16: =M16+I16-J16 -> 99846.154 | O16: =L15*Inputs!B19 -> 206902.96 | P16: =J16-O16 -> 267940.96 | Q16: =A16+2027 -> 2041 | R16: =IF(J16>0,G16/J16,0) -> 1.2102715
A17: 15 | B17: ='Room mix'!H5*(1+Inputs!B10)^(14-1) -> 891036.25 | C17: =Inputs!B9 -> 0.95 | D17: =B17*C17 -> 846484.43 | E17: =D17*Inputs!B11 -> 237015.64 | F17: ='Room mix'!D5*Inputs!B12*(1+Inputs!B10)^(14-1) -> 23284.919 | G17: =D17-E17-F17 -> 586183.87 | H17: 0 | I17: 0 | J17: =IF(A17-1<=Inputs!B20,Development!B10,0) -> 474843.92 | K17: 0 | L17: =MAX(0,L16*(1+Inputs!B19)-J17) -> 4049904.3 | M17: =G17-H17+K17 -> 586183.87 | N17: =M17+I17-J17 -> 111339.96 | O17: =L16*Inputs!B19 -> 194845.62 | P17: =J17-O17 -> 279998.3 | Q17: =A17+2027 -> 2042 | R17: =IF(J17>0,G17/J17,0) -> 1.234477
A18: 16 | B18: ='Room mix'!H5*(1+Inputs!B10)^(15-1) -> 908856.97 | C18: =Inputs!B9 -> 0.95 | D18: =B18*C18 -> 863414.12 | E18: =D18*Inputs!B11 -> 241755.95 | F18: ='Room mix'!D5*Inputs!B12*(1+Inputs!B10)^(15-1) -> 23750.618 | G18: =D18-E18-F18 -> 597907.55 | H18: 0 | I18: 0 | J18: =IF(A18-1<=Inputs!B20,Development!B10,0) -> 474843.92 | K18: 0 | L18: =MAX(0,L17*(1+Inputs!B19)-J18) -> 3757306.1 | M18: =G18-H18+K18 -> 597907.55 | N18: =M18+I18-J18 -> 123063.63 | O18: =L17*Inputs!B19 -> 182245.69 | P18: =J18-O18 -> 292598.22 | Q18: =A18+2027 -> 2043 | R18: =IF(J18>0,G18/J18,0) -> 1.2591665
A19: 17 | B19: ='Room mix'!H5*(1+Inputs!B10)^(16-1) -> 927034.11 | C19: =Inputs!B9 -> 0.95 | D19: =B19*C19 -> 880682.41 | E19: =D19*Inputs!B11 -> 246591.07 | F19: ='Room mix'!D5*Inputs!B12*(1+Inputs!B10)^(16-1) -> 24225.63 | G19: =D19-E19-F19 -> 609865.7 | H19: 0 | I19: 0 | J19: =IF(A19-1<=Inputs!B20,Development!B10,0) -> 474843.92 | K19: 0 | L19: =MAX(0,L18*(1+Inputs!B19)-J19) -> 3451541 | M19: =G19-H19+K19 -> 609865.7 | N19: =M19+I19-J19 -> 135021.78 | O19: =L18*Inputs!B19 -> 169078.77 | P19: =J19-O19 -> 305765.14 | Q19: =A19+2027 -> 2044 | R19: =IF(J19>0,G19/J19,0) -> 1.2843498
A20: 18 | B20: ='Room mix'!H5*(1+Inputs!B10)^(17-1) -> 945574.79 | C20: =Inputs!B9 -> 0.95 | D20: =B20*C20 -> 898296.05 | E20: =D20*Inputs!B11 -> 251522.9 | F20: ='Room mix'!D5*Inputs!B12*(1+Inputs!B10)^(17-1) -> 24710.143 | G20: =D20-E20-F20 -> 622063.02 | H20: 0 | I20: 0 | J20: =IF(A20-1<=Inputs!B20,Development!B10,0) -> 474843.92 | K20: 0 | L20: =MAX(0,L19*(1+Inputs!B19)-J20) -> 3132016.4 | M20: =G20-H20+K20 -> 622063.02 | N20: =M20+I20-J20 -> 147219.1 | O20: =L19*Inputs!B19 -> 155319.34 | P20: =J20-O20 -> 319524.57 | Q20: =A20+2027 -> 2045 | R20: =IF(J20>0,G20/J20,0) -> 1.3100368
A21: 19 | B21: ='Room mix'!H5*(1+Inputs!B10)^(18-1) -> 964486.29 | C21: =Inputs!B9 -> 0.95 | D21: =B21*C21 -> 916261.98 | E21: =D21*Inputs!B11 -> 256553.35 | F21: ='Room mix'!D5*Inputs!B12*(1+Inputs!B10)^(18-1) -> 25204.346 | G21: =D21-E21-F21 -> 634504.28 | H21: 0 | I21: 0 | J21: =IF(A21-1<=Inputs!B20,Development!B10,0) -> 474843.92 | K21: 0 | L21: =MAX(0,L20*(1+Inputs!B19)-J21) -> 2798113.2 | M21: =G21-H21+K21 -> 634504.28 | N21: =M21+I21-J21 -> 159660.36 | O21: =L20*Inputs!B19 -> 140940.74 | P21: =J21-O21 -> 333903.18 | Q21: =A21+2027 -> 2046 | R21: =IF(J21>0,G21/J21,0) -> 1.3362376
A22: 20 | B22: ='Room mix'!H5*(1+Inputs!B10)^(19-1) -> 983776.02 | C22: =Inputs!B9 -> 0.95 | D22: =B22*C22 -> 934587.21 | E22: =D22*Inputs!B11 -> 261684.42 | F22: ='Room mix'!D5*Inputs!B12*(1+Inputs!B10)^(19-1) -> 25708.432 | G22: =D22-E22-F22 -> 647194.36 | H22: 0 | I22: 0 | J22: =IF(A22-1<=Inputs!B20,Development!B10,0) -> 474843.92 | K22: 0 | L22: =MAX(0,L21*(1+Inputs!B19)-J22) -> 2449184.4 | M22: =G22-H22+K22 -> 647194.36 | N22: =M22+I22-J22 -> 172350.44 | O22: =L21*Inputs!B19 -> 125915.09 | P22: =J22-O22 -> 348928.82 | Q22: =A22+2027 -> 2047 | R22: =IF(J22>0,G22/J22,0) -> 1.3629623
A23: 21 | B23: ='Room mix'!H5*(1+Inputs!B10)^(20-1) -> 1003451.5 | C23: =Inputs!B9 -> 0.95 | D23: =B23*C23 -> 953278.96 | E23: =D23*Inputs!B11 -> 266918.11 | F23: ='Room mix'!D5*Inputs!B12*(1+Inputs!B10)^(20-1) -> 26222.601 | G23: =D23-E23-F23 -> 660138.25 | H23: 0 | I23: 0 | J23: =IF(A23-1<=Inputs!B20,Development!B10,0) -> 474843.92 | K23: =G23*(1+Inputs!B10)/Inputs!B22*(1-Inputs!B23) -> 11997713 | L23: =MAX(0,L22*(1+Inputs!B19)-J23) -> 2084553.8 | M23: =G23-H23+K23 -> 12657851 | N23: =M23+I23-J23-L23 -> 10098453 | O23: =L22*Inputs!B19 -> 110213.3 | P23: =J23-O23 -> 364630.62 | Q23: =A23+2027 -> 2048 | R23: =IF(J23>0,G23/J23,0) -> 1.3902216
A25: Development costs exclude financing interest; equity cash flow includes it. NOI is after a replacement reserve.
A26: First operating NOI is G4. G5 is the second operating year (stabilised occupancy). Exit uses next-year NOI.

Sheet Dashboard
A1: Decision dashboard | B1: Value
A3: Total beds | B3: ='Room mix'!D5 -> 120
A4: Total units | B4: ='Room mix'!B5 -> 100
A5: Total gross area | B5: ='Room mix'!F5 -> 3108
A6: Total development cost | B6: =Development!B7 -> 13118821
A7: Stabilised NOI | B7: ='Cash flow'!G5 -> 462201.98
A8: Yield on cost | B8: =B7/B6 -> 0.035231975
A9: Unlevered NPV | B9: =NPV(Inputs!B21,'Cash flow'!M3:M23)+'Cash flow'!M2 -> -5223424.7
A10: Unlevered IRR | B10: =IFERROR(IRR('Cash flow'!M2:M23),0) -> 0.038157396
A11: Equity NPV | B11: =NPV(Inputs!B31,'Cash flow'!N3:N23)+'Cash flow'!N2 -> -4166047.7
A12: Equity IRR | B12: =IFERROR(IRR('Cash flow'!N2:N23),0) -> 0.031977438
A13: Stabilised DSCR | B13: =B7/Development!B10 -> 0.97337665
A14: Preliminary decision | B14: =IF(B9>0,"Financially viable under assumptions","Redesign / lower land and construction cost") -> Redesign / lower land and construction cost
A16: Rent reference status | B16: =IF(COUNTIF('Rent rules'!C2:C4,">0")=3,"Reference inputs supplied; final legal review required","NOT VERIFIED - enter official references") -> NOT VERIFIED - enter official references
A17: Demand screen | B17: ='Demand & competition'!B12 -> Within planning envelope
A18: Opening calendar year | B18: 2029
A19: Funding per bed | B19: =Development!B16 -> 109323.51
A20: Break-even occupancy (NOI covers debt) | B20: =(Development!B10+'Cash flow'!F5)/('Cash flow'!B5*(1-Inputs!B11)) -> 0.97499123
A21: Operating rent multiplier for NPV=0 | B21: See sensitivity and scenarios; increases remain subject to reference-rent rules.
A23: Investment gate | B23: =IF(AND(B9>0,B13>=1.2,COUNTIF('Rent rules'!C2:C4,">0")=3),"Proceed to detailed due diligence","HOLD: financial and/or rent-reference gate unmet") -> HOLD: financial and/or rent-reference gate unmet

Sheet Sources
A1: ID / topic | B1: Primary URL | C1: Evidence / model treatment | D1: Publication / access
A2: S1 Demand | B2: https://perspective.brussels/fr/actualites/un-etudiant-sur-trois-trouve-un-kot-dans-un-logement-qui-lui-est-destine | C2: 137,000+ students; 37,000+ housing users; 11,305 dedicated units. Cross-year regional proxy only. | D2: 6 Jan 2026 / 14 Oct 2026
A3: S2 Usquare permit | B3: https://msi.brussels/nieuws/usquare-de-msi-dient-vergunningsaanvraag-voor-465-studentenwoningen | C3: 465 student rooms in permit application; replaces older 460-room concept. | D3: 25 Aug 2026 / 14 Oct 2026
A4: S3 Usquare schedule | B4: https://usquare.brussels/en/schedule | C4: Provisional September 2029 commissioning; 30-36 month works. Not a completion guarantee. | D4: Access 14 Oct 2026
A5: S4 Bru Upkot | B5: https://www.upkot.be/en/locations/brussels/bru-upkot | C5: 216 rooms; 2026-27 prices: entry 589+119; 1p studio 769+134; 2p studio 859+164 EUR/month. | D5: 2026-27 / 14 Oct 2026
A6: S5 VUB stock | B6: https://www.vub.be/en/studying-vub/practical-info-for-students/student-housing | C6: 1,540 rooms across campus network, not Etterbeek alone. | D6: Access 14 Oct 2026
A7: S6 VUB rents | B7: https://www.vub.be/en/studying-vub/practical-info-for-students/student-housing/practical-housing-information | C7: 2026-27: room 449.30, single studio 561.60, two-person flat 674 EUR/month including listed services; demand exceeds supply. | D7: Updated 18 Sep 2026 / 14 Oct 2026
A8: S7 Rent regulation | B8: https://be.brussels/fr/logement/location/bail-dhabitation/loyers-de-reference | C8: Reference must be in lease; >20% above reference presumed excessive with potential justification; quality issues can affect lower rents; obligation from 1 May 2025. | D8: Access 14 Oct 2026
A9: S8 Calculator | B9: https://loyers.brussels/ | C9: Exact site and property details required. No official reference amount assumed in this model. | D9: Not calculated: missing site
A10: A1 Cost / finance | B10: Analyst assumptions, not market quotes | C10: Hard costs 2200 EUR/gross sqm, land 1.8m, 21% nonrecoverable VAT, financing 4.5%, land fees 15%; obtain quotations. | D10: 14 Oct 2026

Sheet Demand & competition
A1: Evidence / planning assumption | B1: Value | C1: Interpretation / source ID
A2: Brussels students, 2022-23 | B2: 137000 | C2: Lower-bound rounded figure; S1
A3: Students using accommodation, 2022-23 | B3: 37000 | C3: At least; regional demand indicator, not new vacant demand; S1
A4: Dedicated student units, 2025 | B4: 11305 | C4: Units are not necessarily beds; cross-period comparison; S1
A5: Indicative non-dedicated demand | B5: =B3-B4 -> 25695 | C5: Proxy only; many already housed in ordinary rentals
A6: Usquare proposed rooms | B6: 465 | C6: Permit submitted 25 Aug 2026; S2
A7: Pipeline overlap factor | B7: 1 | C7: Conservative assumption: all compete with project
A8: Residual proxy | B8: =MAX(0,B5-B6*B7) -> 25230 | C8: Not a verified local waiting list
A9: Local addressable capture assumption | B9: 0.006 | C9: 0.6% of proxy; replace with local survey
A10: Indicative addressable beds | B10: =B8*B9 -> 151.38 | C10: Screening estimate only
A11: Proposed beds | B11: ='Room mix'!D5 -> 120 | C11: 100 units / 120 beds baseline
A12: Beds versus addressable estimate | B12: =IF(B11<=B10,"Within planning envelope","Capacity exceeds assumed envelope") -> Within planning envelope | C12: Demand gate; validate pre-letting
A13: Expected stabilised occupied beds | B13: =B11*Inputs!B9 -> 114 | C13: 95% assumption, not observed market occupancy
A14: Usquare opening target | B14: 2029 | C14: S3 provisional schedule; older 2026 announcement superseded
A17: Competitor / status | B17: Beds or units | C17: Rent/month | D17: Charges | E17: Source / implication
A18: Usquare / proposed | B18: 465 | C18: Not published | D18: Unknown | E18: S2/S3: affordable pipeline, 2029 target; monitor permit and delivery
A19: Bru Upkot / operating | B19: 216 | C19: 589 | D19: 119 | E19: S4: entry room; 0.75km to VUB; existing stock, do not subtract again
A20: Bru Upkot / 1p studio | C20: 769 | D20: 134 | E20: S4: 2026-27 asking rent
A21: Bru Upkot / 2p studio | C21: 859 | D21: 164 | E21: S4: unit asking rent; per person half if 2 tenants
A22: VUB / operating network | B22: 1540 | C22: 449.3 | D22: Included | E22: S5/S6: across Etterbeek + Jette; not all local
A23: VUB / restricted single studio | B23: 12 | C23: 561.6 | D23: Included | E23: S6: reserved for medical need; not general private market
A24: VUB / two-person flats | B24: 35 | C24: 674 | D24: Included | E24: S6: unit price; limited institutional allocation
A26: Positioning | B26: Base rent below private Bru Upkot examples; VUB institutional all-inclusive prices are lower and not directly comparable.
A27: Sizing rationale | B27: 60 normal beds + 40 shared-studio beds + 20 single-studio beds; 83% of beds in lower-price products.
A28: Site concept | B28: Approximately 3,108 gross sqm; at 4 floors, ~777 sqm footprint, before site circulation and external space. Assumption, no planning assurance.

Sheet Rent rules
A1: Room type | B1: Desired rent/unit/month | C1: Official reference/unit/month | D1: Planning affordability cap/unit | E1: Applied unit rent | F1: Applied per person | G1: Verification
A2: Normal dorm | B2: =Inputs!B5*1 -> 480 | C2: 0 | D2: 480 | E2: =MIN(B2,D2,IF(C2>0,C2*Inputs!B35,D2)) -> 480 | F2: =E2/1 -> 480 | G2: =IF(C2>0,"Reference supplied - review quality and lease","NOT VERIFIED") -> NOT VERIFIED
A3: Shared studio | B3: =Inputs!B6*2 -> 780 | C3: 0 | D3: 780 | E3: =MIN(B3,D3,IF(C3>0,C3*Inputs!B35,D3)) -> 780 | F3: =E3/2 -> 390 | G3: =IF(C3>0,"Reference supplied - review quality and lease","NOT VERIFIED") -> NOT VERIFIED
A4: Single studio | B4: =Inputs!B7*1 -> 650 | C4: 0 | D4: 650 | E4: =MIN(B4,D4,IF(C4>0,C4*Inputs!B35,D4)) -> 650 | F4: =E4/1 -> 650 | G4: =IF(C4>0,"Reference supplied - review quality and lease","NOT VERIFIED") -> NOT VERIFIED
A6: Rule | B6: Reference rent depends on address, area, condition and amenities. No universal Brussels student-room tariff.
A7: 20% screen | B7: Above reference +20% is presumed excessive, subject to specific justifications. Lower rents may also be excessive due to quality defects.
A8: Model policy | B8: At/below supplied reference by default. Enter official calculator output per rented unit; a zero means missing, not zero allowable rent.
A9: Lease review | B9: Reference must appear in lease; verify student lease, indexation and separate utility settlement before offering units.
A10: Official calculator | B10: https://loyers.brussels/
A11: Source | B11: https://be.brussels/fr/logement/location/bail-dhabitation/loyers-de-reference

Sheet Scenarios
A1: Scenario | B1: Cost multiplier | C1: Stabilised occupancy | D1: Rent multiplier | E1: Exit cap | F1: Project NPV | G1: Project IRR | H1: Stabilised DSCR | I1: CF year 0 | J1: CF year 1 | K1: CF year 2 | L1: CF year 3 | M1: CF year 4 | N1: CF year 5 | O1: CF year 6 | P1: CF year 7 | Q1: CF year 8 | R1: CF year 9 | S1: CF year 10 | T1: CF year 11 | U1: CF year 12 | V1: CF year 13 | W1: CF year 14 | X1: CF year 15 | Y1: CF year 16 | Z1: CF year 17 | AA1: CF year 18 | AB1: CF year 19 | AC1: CF year 20 | AD1: CF year 21
A2: Downside | B2: 1.1 | C2: 0.85 | D2: 0.95 | E2: 0.06 | F2: =NPV(Inputs!B21,J2:AD2)+I2 -> -7732093.6 | G2: =IFERROR(IRR(I2:AD2),0) -> 0.017547748 | H2: =('Cash flow'!B5*D2*C2*(1-Inputs!B11)-'Cash flow'!F5)/(-PMT(Inputs!B19,Inputs!B20,Development!B8*B2)) -> 0.74688214 | I2: =-Development!B15*B2/2 -> -7041084.8 | J2: =-Development!B15*B2/2 -> -7041084.8 | K2: =('Cash flow'!B4*D2*(Inputs!B29*C2/Inputs!B9)*(1-Inputs!B11)-'Cash flow'!F4) -> 340313.76 | L2: =('Cash flow'!B5*D2*(C2)*(1-Inputs!B11)-'Cash flow'!F5) -> 390117.69 | M2: =('Cash flow'!B6*D2*(C2)*(1-Inputs!B11)-'Cash flow'!F6) -> 397920.04 | N2: =('Cash flow'!B7*D2*(C2)*(1-Inputs!B11)-'Cash flow'!F7) -> 405878.44 | O2: =('Cash flow'!B8*D2*(C2)*(1-Inputs!B11)-'Cash flow'!F8) -> 413996.01 | P2: =('Cash flow'!B9*D2*(C2)*(1-Inputs!B11)-'Cash flow'!F9) -> 422275.93 | Q2: =('Cash flow'!B10*D2*(C2)*(1-Inputs!B11)-'Cash flow'!F10) -> 430721.45 | R2: =('Cash flow'!B11*D2*(C2)*(1-Inputs!B11)-'Cash flow'!F11) -> 439335.88 | S2: =('Cash flow'!B12*D2*(C2)*(1-Inputs!B11)-'Cash flow'!F12) -> 448122.6 | T2: =('Cash flow'!B13*D2*(C2)*(1-Inputs!B11)-'Cash flow'!F13) -> 457085.05 | U2: =('Cash flow'!B14*D2*(C2)*(1-Inputs!B11)-'Cash flow'!F14) -> 466226.75 | V2: =('Cash flow'!B15*D2*(C2)*(1-Inputs!B11)-'Cash flow'!F15) -> 475551.28 | W2: =('Cash flow'!B16*D2*(C2)*(1-Inputs!B11)-'Cash flow'!F16) -> 485062.31 | X2: =('Cash flow'!B17*D2*(C2)*(1-Inputs!B11)-'Cash flow'!F17) -> 494763.55 | Y2: =('Cash flow'!B18*D2*(C2)*(1-Inputs!B11)-'Cash flow'!F18) -> 504658.83 | Z2: =('Cash flow'!B19*D2*(C2)*(1-Inputs!B11)-'Cash flow'!F19) -> 514752 | AA2: =('Cash flow'!B20*D2*(C2)*(1-Inputs!B11)-'Cash flow'!F20) -> 525047.04 | AB2: =('Cash flow'!B21*D2*(C2)*(1-Inputs!B11)-'Cash flow'!F21) -> 535547.98 | AC2: =('Cash flow'!B22*D2*(C2)*(1-Inputs!B11)-'Cash flow'!F22) -> 546258.94 | AD2: =('Cash flow'!B23*D2*(C2)*(1-Inputs!B11)-'Cash flow'!F23)+('Cash flow'!B23*D2*(C2)*(1-Inputs!B11)-'Cash flow'!F23)*(1+Inputs!B10)/E2*(1-Inputs!B23) -> 9839871.6
A3: Base | B3: 1 | C3: 0.95 | D3: 1 | E3: 0.055 | F3: =NPV(Inputs!B21,J3:AD3)+I3 -> -5223424.7 | G3: =IFERROR(IRR(I3:AD3),0) -> 0.038157396 | H3: =('Cash flow'!B5*D3*C3*(1-Inputs!B11)-'Cash flow'!F5)/(-PMT(Inputs!B19,Inputs!B20,Development!B8*B3)) -> 0.97337665 | I3: =-Development!B15*B3/2 -> -6400986.2 | J3: =-Development!B15*B3/2 -> -6400986.2 | K3: =('Cash flow'!B4*D3*(Inputs!B29*C3/Inputs!B9)*(1-Inputs!B11)-'Cash flow'!F4) -> 403545.6 | L3: =('Cash flow'!B5*D3*(C3)*(1-Inputs!B11)-'Cash flow'!F5) -> 462201.98 | M3: =('Cash flow'!B6*D3*(C3)*(1-Inputs!B11)-'Cash flow'!F6) -> 471446.02 | N3: =('Cash flow'!B7*D3*(C3)*(1-Inputs!B11)-'Cash flow'!F7) -> 480874.94 | O3: =('Cash flow'!B8*D3*(C3)*(1-Inputs!B11)-'Cash flow'!F8) -> 490492.44 | P3: =('Cash flow'!B9*D3*(C3)*(1-Inputs!B11)-'Cash flow'!F9) -> 500302.29 | Q3: =('Cash flow'!B10*D3*(C3)*(1-Inputs!B11)-'Cash flow'!F10) -> 510308.34 | R3: =('Cash flow'!B11*D3*(C3)*(1-Inputs!B11)-'Cash flow'!F11) -> 520514.5 | S3: =('Cash flow'!B12*D3*(C3)*(1-Inputs!B11)-'Cash flow'!F12) -> 530924.79 | T3: =('Cash flow'!B13*D3*(C3)*(1-Inputs!B11)-'Cash flow'!F13) -> 541543.29 | U3: =('Cash flow'!B14*D3*(C3)*(1-Inputs!B11)-'Cash flow'!F14) -> 552374.16 | V3: =('Cash flow'!B15*D3*(C3)*(1-Inputs!B11)-'Cash flow'!F15) -> 563421.64 | W3: =('Cash flow'!B16*D3*(C3)*(1-Inputs!B11)-'Cash flow'!F16) -> 574690.07 | X3: =('Cash flow'!B17*D3*(C3)*(1-Inputs!B11)-'Cash flow'!F17) -> 586183.87 | Y3: =('Cash flow'!B18*D3*(C3)*(1-Inputs!B11)-'Cash flow'!F18) -> 597907.55 | Z3: =('Cash flow'!B19*D3*(C3)*(1-Inputs!B11)-'Cash flow'!F19) -> 609865.7 | AA3: =('Cash flow'!B20*D3*(C3)*(1-Inputs!B11)-'Cash flow'!F20) -> 622063.02 | AB3: =('Cash flow'!B21*D3*(C3)*(1-Inputs!B11)-'Cash flow'!F21) -> 634504.28 | AC3: =('Cash flow'!B22*D3*(C3)*(1-Inputs!B11)-'Cash flow'!F22) -> 647194.36 | AD3: =('Cash flow'!B23*D3*(C3)*(1-Inputs!B11)-'Cash flow'!F23)+('Cash flow'!B23*D3*(C3)*(1-Inputs!B11)-'Cash flow'!F23)*(1+Inputs!B10)/E3*(1-Inputs!B23) -> 12657851
A4: Upside | B4: 0.9 | C4: 0.98 | D4: 1.05 | E4: 0.05 | F4: =NPV(Inputs!B21,J4:AD4)+I4 -> -3117298.3 | G4: =IFERROR(IRR(I4:AD4),0) -> 0.054548249 | H4: =('Cash flow'!B5*D4*C4*(1-Inputs!B11)-'Cash flow'!F5)/(-PMT(Inputs!B19,Inputs!B20,Development!B8*B4)) -> 1.1750399 | I4: =-Development!B15*B4/2 -> -5760887.6 | J4: =-Development!B15*B4/2 -> -5760887.6 | K4: =('Cash flow'!B4*D4*(Inputs!B29*C4/Inputs!B9)*(1-Inputs!B11)-'Cash flow'!F4) -> 438600.44 | L4: =('Cash flow'!B5*D4*(C4)*(1-Inputs!B11)-'Cash flow'!F5) -> 502164.51 | M4: =('Cash flow'!B6*D4*(C4)*(1-Inputs!B11)-'Cash flow'!F6) -> 512207.8 | N4: =('Cash flow'!B7*D4*(C4)*(1-Inputs!B11)-'Cash flow'!F7) -> 522451.95 | O4: =('Cash flow'!B8*D4*(C4)*(1-Inputs!B11)-'Cash flow'!F8) -> 532900.99 | P4: =('Cash flow'!B9*D4*(C4)*(1-Inputs!B11)-'Cash flow'!F9) -> 543559.01 | Q4: =('Cash flow'!B10*D4*(C4)*(1-Inputs!B11)-'Cash flow'!F10) -> 554430.19 | R4: =('Cash flow'!B11*D4*(C4)*(1-Inputs!B11)-'Cash flow'!F11) -> 565518.8 | S4: =('Cash flow'!B12*D4*(C4)*(1-Inputs!B11)-'Cash flow'!F12) -> 576829.17 | T4: =('Cash flow'!B13*D4*(C4)*(1-Inputs!B11)-'Cash flow'!F13) -> 588365.76 | U4: =('Cash flow'!B14*D4*(C4)*(1-Inputs!B11)-'Cash flow'!F14) -> 600133.07 | V4: =('Cash flow'!B15*D4*(C4)*(1-Inputs!B11)-'Cash flow'!F15) -> 612135.73 | W4: =('Cash flow'!B16*D4*(C4)*(1-Inputs!B11)-'Cash flow'!F16) -> 624378.45 | X4: =('Cash flow'!B17*D4*(C4)*(1-Inputs!B11)-'Cash flow'!F17) -> 636866.02 | Y4: =('Cash flow'!B18*D4*(C4)*(1-Inputs!B11)-'Cash flow'!F18) -> 649603.34 | Z4: =('Cash flow'!B19*D4*(C4)*(1-Inputs!B11)-'Cash flow'!F19) -> 662595.4 | AA4: =('Cash flow'!B20*D4*(C4)*(1-Inputs!B11)-'Cash flow'!F20) -> 675847.31 | AB4: =('Cash flow'!B21*D4*(C4)*(1-Inputs!B11)-'Cash flow'!F21) -> 689364.26 | AC4: =('Cash flow'!B22*D4*(C4)*(1-Inputs!B11)-'Cash flow'!F22) -> 703151.54 | AD4: =('Cash flow'!B23*D4*(C4)*(1-Inputs!B11)-'Cash flow'!F23)+('Cash flow'!B23*D4*(C4)*(1-Inputs!B11)-'Cash flow'!F23)*(1+Inputs!B10)/E4*(1-Inputs!B23) -> 15055768
A7: Scenario occupancy replaces stabilised input; opening occupancy scales proportionally. Debt scales with capex for DSCR. Rent upside is a stress case, not legal permission.

Sheet Sensitivity
A1: Unlevered NPV: cost vs occupancy | B1: 0.85 | C1: 0.95 | D1: 0.98
A2: 0.9 | B2: =-Development!B15*$A2/2+-Development!B15*$A2/2/(1+Inputs!B21)+('Cash flow'!B4*Inputs!B29*B$1/Inputs!B9*(1-Inputs!B11)-'Cash flow'!F4)/(1+Inputs!B21)^2+('Cash flow'!B5*B$1*(1-Inputs!B11)-'Cash flow'!F5)/(1+Inputs!B21)^3+('Cash flow'!B6*B$1*(1-Inputs!B11)-'Cash flow'!F6)/(1+Inputs!B21)^4+('Cash flow'!B7*B$1*(1-Inputs!B11)-'Cash flow'!F7)/(1+Inputs!B21)^5+('Cash flow'!B8*B$1*(1-Inputs!B11)-'Cash flow'!F8)/(1+Inputs!B21)^6+('Cash flow'!B9*B$1*(1-Inputs!B11)-'Cash flow'!F9)/(1+Inputs!B21)^7+('Cash flow'!B10*B$1*(1-Inputs!B11)-'Cash flow'!F10)/(1+Inputs!B21)^8+('Cash flow'!B11*B$1*(1-Inputs!B11)-'Cash flow'!F11)/(1+Inputs!B21)^9+('Cash flow'!B12*B$1*(1-Inputs!B11)-'Cash flow'!F12)/(1+Inputs!B21)^10+('Cash flow'!B13*B$1*(1-Inputs!B11)-'Cash flow'!F13)/(1+Inputs!B21)^11+('Cash flow'!B14*B$1*(1-Inputs!B11)-'Cash flow'!F14)/(1+Inputs!B21)^12+('Cash flow'!B15*B$1*(1-Inputs!B11)-'Cash flow'!F15)/(1+Inputs!B21)^13+('Cash flow'!B16*B$1*(1-Inputs!B11)-'Cash flow'!F16)/(1+Inputs!B21)^14+('Cash flow'!B17*B$1*(1-Inputs!B11)-'Cash flow'!F17)/(1+Inputs!B21)^15+('Cash flow'!B18*B$1*(1-Inputs!B11)-'Cash flow'!F18)/(1+Inputs!B21)^16+('Cash flow'!B19*B$1*(1-Inputs!B11)-'Cash flow'!F19)/(1+Inputs!B21)^17+('Cash flow'!B20*B$1*(1-Inputs!B11)-'Cash flow'!F20)/(1+Inputs!B21)^18+('Cash flow'!B21*B$1*(1-Inputs!B11)-'Cash flow'!F21)/(1+Inputs!B21)^19+('Cash flow'!B22*B$1*(1-Inputs!B11)-'Cash flow'!F22)/(1+Inputs!B21)^20+(('Cash flow'!B23*B$1*(1-Inputs!B11)-'Cash flow'!F23)+('Cash flow'!B23*B$1*(1-Inputs!B11)-'Cash flow'!F23)*(1+Inputs!B10)/Inputs!B22*(1-Inputs!B23))/(1+Inputs!B21)^21 -> -4768357.7 | C2: =-Development!B15*$A2/2+-Development!B15*$A2/2/(1+Inputs!B21)+('Cash flow'!B4*Inputs!B29*C$1/Inputs!B9*(1-Inputs!B11)-'Cash flow'!F4)/(1+Inputs!B21)^2+('Cash flow'!B5*C$1*(1-Inputs!B11)-'Cash flow'!F5)/(1+Inputs!B21)^3+('Cash flow'!B6*C$1*(1-Inputs!B11)-'Cash flow'!F6)/(1+Inputs!B21)^4+('Cash flow'!B7*C$1*(1-Inputs!B11)-'Cash flow'!F7)/(1+Inputs!B21)^5+('Cash flow'!B8*C$1*(1-Inputs!B11)-'Cash flow'!F8)/(1+Inputs!B21)^6+('Cash flow'!B9*C$1*(1-Inputs!B11)-'Cash flow'!F9)/(1+Inputs!B21)^7+('Cash flow'!B10*C$1*(1-Inputs!B11)-'Cash flow'!F10)/(1+Inputs!B21)^8+('Cash flow'!B11*C$1*(1-Inputs!B11)-'Cash flow'!F11)/(1+Inputs!B21)^9+('Cash flow'!B12*C$1*(1-Inputs!B11)-'Cash flow'!F12)/(1+Inputs!B21)^10+('Cash flow'!B13*C$1*(1-Inputs!B11)-'Cash flow'!F13)/(1+Inputs!B21)^11+('Cash flow'!B14*C$1*(1-Inputs!B11)-'Cash flow'!F14)/(1+Inputs!B21)^12+('Cash flow'!B15*C$1*(1-Inputs!B11)-'Cash flow'!F15)/(1+Inputs!B21)^13+('Cash flow'!B16*C$1*(1-Inputs!B11)-'Cash flow'!F16)/(1+Inputs!B21)^14+('Cash flow'!B17*C$1*(1-Inputs!B11)-'Cash flow'!F17)/(1+Inputs!B21)^15+('Cash flow'!B18*C$1*(1-Inputs!B11)-'Cash flow'!F18)/(1+Inputs!B21)^16+('Cash flow'!B19*C$1*(1-Inputs!B11)-'Cash flow'!F19)/(1+Inputs!B21)^17+('Cash flow'!B20*C$1*(1-Inputs!B11)-'Cash flow'!F20)/(1+Inputs!B21)^18+('Cash flow'!B21*C$1*(1-Inputs!B11)-'Cash flow'!F21)/(1+Inputs!B21)^19+('Cash flow'!B22*C$1*(1-Inputs!B11)-'Cash flow'!F22)/(1+Inputs!B21)^20+(('Cash flow'!B23*C$1*(1-Inputs!B11)-'Cash flow'!F23)+('Cash flow'!B23*C$1*(1-Inputs!B11)-'Cash flow'!F23)*(1+Inputs!B10)/Inputs!B22*(1-Inputs!B23))/(1+Inputs!B21)^21 -> -3990642.2 | D2: =-Development!B15*$A2/2+-Development!B15*$A2/2/(1+Inputs!B21)+('Cash flow'!B4*Inputs!B29*D$1/Inputs!B9*(1-Inputs!B11)-'Cash flow'!F4)/(1+Inputs!B21)^2+('Cash flow'!B5*D$1*(1-Inputs!B11)-'Cash flow'!F5)/(1+Inputs!B21)^3+('Cash flow'!B6*D$1*(1-Inputs!B11)-'Cash flow'!F6)/(1+Inputs!B21)^4+('Cash flow'!B7*D$1*(1-Inputs!B11)-'Cash flow'!F7)/(1+Inputs!B21)^5+('Cash flow'!B8*D$1*(1-Inputs!B11)-'Cash flow'!F8)/(1+Inputs!B21)^6+('Cash flow'!B9*D$1*(1-Inputs!B11)-'Cash flow'!F9)/(1+Inputs!B21)^7+('Cash flow'!B10*D$1*(1-Inputs!B11)-'Cash flow'!F10)/(1+Inputs!B21)^8+('Cash flow'!B11*D$1*(1-Inputs!B11)-'Cash flow'!F11)/(1+Inputs!B21)^9+('Cash flow'!B12*D$1*(1-Inputs!B11)-'Cash flow'!F12)/(1+Inputs!B21)^10+('Cash flow'!B13*D$1*(1-Inputs!B11)-'Cash flow'!F13)/(1+Inputs!B21)^11+('Cash flow'!B14*D$1*(1-Inputs!B11)-'Cash flow'!F14)/(1+Inputs!B21)^12+('Cash flow'!B15*D$1*(1-Inputs!B11)-'Cash flow'!F15)/(1+Inputs!B21)^13+('Cash flow'!B16*D$1*(1-Inputs!B11)-'Cash flow'!F16)/(1+Inputs!B21)^14+('Cash flow'!B17*D$1*(1-Inputs!B11)-'Cash flow'!F17)/(1+Inputs!B21)^15+('Cash flow'!B18*D$1*(1-Inputs!B11)-'Cash flow'!F18)/(1+Inputs!B21)^16+('Cash flow'!B19*D$1*(1-Inputs!B11)-'Cash flow'!F19)/(1+Inputs!B21)^17+('Cash flow'!B20*D$1*(1-Inputs!B11)-'Cash flow'!F20)/(1+Inputs!B21)^18+('Cash flow'!B21*D$1*(1-Inputs!B11)-'Cash flow'!F21)/(1+Inputs!B21)^19+('Cash flow'!B22*D$1*(1-Inputs!B11)-'Cash flow'!F22)/(1+Inputs!B21)^20+(('Cash flow'!B23*D$1*(1-Inputs!B11)-'Cash flow'!F23)+('Cash flow'!B23*D$1*(1-Inputs!B11)-'Cash flow'!F23)*(1+Inputs!B10)/Inputs!B22*(1-Inputs!B23))/(1+Inputs!B21)^21 -> -3757327.6
A3: 1 | B3: =-Development!B15*$A3/2+-Development!B15*$A3/2/(1+Inputs!B21)+('Cash flow'!B4*Inputs!B29*B$1/Inputs!B9*(1-Inputs!B11)-'Cash flow'!F4)/(1+Inputs!B21)^2+('Cash flow'!B5*B$1*(1-Inputs!B11)-'Cash flow'!F5)/(1+Inputs!B21)^3+('Cash flow'!B6*B$1*(1-Inputs!B11)-'Cash flow'!F6)/(1+Inputs!B21)^4+('Cash flow'!B7*B$1*(1-Inputs!B11)-'Cash flow'!F7)/(1+Inputs!B21)^5+('Cash flow'!B8*B$1*(1-Inputs!B11)-'Cash flow'!F8)/(1+Inputs!B21)^6+('Cash flow'!B9*B$1*(1-Inputs!B11)-'Cash flow'!F9)/(1+Inputs!B21)^7+('Cash flow'!B10*B$1*(1-Inputs!B11)-'Cash flow'!F10)/(1+Inputs!B21)^8+('Cash flow'!B11*B$1*(1-Inputs!B11)-'Cash flow'!F11)/(1+Inputs!B21)^9+('Cash flow'!B12*B$1*(1-Inputs!B11)-'Cash flow'!F12)/(1+Inputs!B21)^10+('Cash flow'!B13*B$1*(1-Inputs!B11)-'Cash flow'!F13)/(1+Inputs!B21)^11+('Cash flow'!B14*B$1*(1-Inputs!B11)-'Cash flow'!F14)/(1+Inputs!B21)^12+('Cash flow'!B15*B$1*(1-Inputs!B11)-'Cash flow'!F15)/(1+Inputs!B21)^13+('Cash flow'!B16*B$1*(1-Inputs!B11)-'Cash flow'!F16)/(1+Inputs!B21)^14+('Cash flow'!B17*B$1*(1-Inputs!B11)-'Cash flow'!F17)/(1+Inputs!B21)^15+('Cash flow'!B18*B$1*(1-Inputs!B11)-'Cash flow'!F18)/(1+Inputs!B21)^16+('Cash flow'!B19*B$1*(1-Inputs!B11)-'Cash flow'!F19)/(1+Inputs!B21)^17+('Cash flow'!B20*B$1*(1-Inputs!B11)-'Cash flow'!F20)/(1+Inputs!B21)^18+('Cash flow'!B21*B$1*(1-Inputs!B11)-'Cash flow'!F21)/(1+Inputs!B21)^19+('Cash flow'!B22*B$1*(1-Inputs!B11)-'Cash flow'!F22)/(1+Inputs!B21)^20+(('Cash flow'!B23*B$1*(1-Inputs!B11)-'Cash flow'!F23)+('Cash flow'!B23*B$1*(1-Inputs!B11)-'Cash flow'!F23)*(1+Inputs!B10)/Inputs!B22*(1-Inputs!B23))/(1+Inputs!B21)^21 -> -6001140.2 | C3: =-Development!B15*$A3/2+-Development!B15*$A3/2/(1+Inputs!B21)+('Cash flow'!B4*Inputs!B29*C$1/Inputs!B9*(1-Inputs!B11)-'Cash flow'!F4)/(1+Inputs!B21)^2+('Cash flow'!B5*C$1*(1-Inputs!B11)-'Cash flow'!F5)/(1+Inputs!B21)^3+('Cash flow'!B6*C$1*(1-Inputs!B11)-'Cash flow'!F6)/(1+Inputs!B21)^4+('Cash flow'!B7*C$1*(1-Inputs!B11)-'Cash flow'!F7)/(1+Inputs!B21)^5+('Cash flow'!B8*C$1*(1-Inputs!B11)-'Cash flow'!F8)/(1+Inputs!B21)^6+('Cash flow'!B9*C$1*(1-Inputs!B11)-'Cash flow'!F9)/(1+Inputs!B21)^7+('Cash flow'!B10*C$1*(1-Inputs!B11)-'Cash flow'!F10)/(1+Inputs!B21)^8+('Cash flow'!B11*C$1*(1-Inputs!B11)-'Cash flow'!F11)/(1+Inputs!B21)^9+('Cash flow'!B12*C$1*(1-Inputs!B11)-'Cash flow'!F12)/(1+Inputs!B21)^10+('Cash flow'!B13*C$1*(1-Inputs!B11)-'Cash flow'!F13)/(1+Inputs!B21)^11+('Cash flow'!B14*C$1*(1-Inputs!B11)-'Cash flow'!F14)/(1+Inputs!B21)^12+('Cash flow'!B15*C$1*(1-Inputs!B11)-'Cash flow'!F15)/(1+Inputs!B21)^13+('Cash flow'!B16*C$1*(1-Inputs!B11)-'Cash flow'!F16)/(1+Inputs!B21)^14+('Cash flow'!B17*C$1*(1-Inputs!B11)-'Cash flow'!F17)/(1+Inputs!B21)^15+('Cash flow'!B18*C$1*(1-Inputs!B11)-'Cash flow'!F18)/(1+Inputs!B21)^16+('Cash flow'!B19*C$1*(1-Inputs!B11)-'Cash flow'!F19)/(1+Inputs!B21)^17+('Cash flow'!B20*C$1*(1-Inputs!B11)-'Cash flow'!F20)/(1+Inputs!B21)^18+('Cash flow'!B21*C$1*(1-Inputs!B11)-'Cash flow'!F21)/(1+Inputs!B21)^19+('Cash flow'!B22*C$1*(1-Inputs!B11)-'Cash flow'!F22)/(1+Inputs!B21)^20+(('Cash flow'!B23*C$1*(1-Inputs!B11)-'Cash flow'!F23)+('Cash flow'!B23*C$1*(1-Inputs!B11)-'Cash flow'!F23)*(1+Inputs!B10)/Inputs!B22*(1-Inputs!B23))/(1+Inputs!B21)^21 -> -5223424.7 | D3: =-Development!B15*$A3/2+-Development!B15*$A3/2/(1+Inputs!B21)+('Cash flow'!B4*Inputs!B29*D$1/Inputs!B9*(1-Inputs!B11)-'Cash flow'!F4)/(1+Inputs!B21)^2+('Cash flow'!B5*D$1*(1-Inputs!B11)-'Cash flow'!F5)/(1+Inputs!B21)^3+('Cash flow'!B6*D$1*(1-Inputs!B11)-'Cash flow'!F6)/(1+Inputs!B21)^4+('Cash flow'!B7*D$1*(1-Inputs!B11)-'Cash flow'!F7)/(1+Inputs!B21)^5+('Cash flow'!B8*D$1*(1-Inputs!B11)-'Cash flow'!F8)/(1+Inputs!B21)^6+('Cash flow'!B9*D$1*(1-Inputs!B11)-'Cash flow'!F9)/(1+Inputs!B21)^7+('Cash flow'!B10*D$1*(1-Inputs!B11)-'Cash flow'!F10)/(1+Inputs!B21)^8+('Cash flow'!B11*D$1*(1-Inputs!B11)-'Cash flow'!F11)/(1+Inputs!B21)^9+('Cash flow'!B12*D$1*(1-Inputs!B11)-'Cash flow'!F12)/(1+Inputs!B21)^10+('Cash flow'!B13*D$1*(1-Inputs!B11)-'Cash flow'!F13)/(1+Inputs!B21)^11+('Cash flow'!B14*D$1*(1-Inputs!B11)-'Cash flow'!F14)/(1+Inputs!B21)^12+('Cash flow'!B15*D$1*(1-Inputs!B11)-'Cash flow'!F15)/(1+Inputs!B21)^13+('Cash flow'!B16*D$1*(1-Inputs!B11)-'Cash flow'!F16)/(1+Inputs!B21)^14+('Cash flow'!B17*D$1*(1-Inputs!B11)-'Cash flow'!F17)/(1+Inputs!B21)^15+('Cash flow'!B18*D$1*(1-Inputs!B11)-'Cash flow'!F18)/(1+Inputs!B21)^16+('Cash flow'!B19*D$1*(1-Inputs!B11)-'Cash flow'!F19)/(1+Inputs!B21)^17+('Cash flow'!B20*D$1*(1-Inputs!B11)-'Cash flow'!F20)/(1+Inputs!B21)^18+('Cash flow'!B21*D$1*(1-Inputs!B11)-'Cash flow'!F21)/(1+Inputs!B21)^19+('Cash flow'!B22*D$1*(1-Inputs!B11)-'Cash flow'!F22)/(1+Inputs!B21)^20+(('Cash flow'!B23*D$1*(1-Inputs!B11)-'Cash flow'!F23)+('Cash flow'!B23*D$1*(1-Inputs!B11)-'Cash flow'!F23)*(1+Inputs!B10)/Inputs!B22*(1-Inputs!B23))/(1+Inputs!B21)^21 -> -4990110.1
A4: 1.1 | B4: =-Development!B15*$A4/2+-Development!B15*$A4/2/(1+Inputs!B21)+('Cash flow'!B4*Inputs!B29*B$1/Inputs!B9*(1-Inputs!B11)-'Cash flow'!F4)/(1+Inputs!B21)^2+('Cash flow'!B5*B$1*(1-Inputs!B11)-'Cash flow'!F5)/(1+Inputs!B21)^3+('Cash flow'!B6*B$1*(1-Inputs!B11)-'Cash flow'!F6)/(1+Inputs!B21)^4+('Cash flow'!B7*B$1*(1-Inputs!B11)-'Cash flow'!F7)/(1+Inputs!B21)^5+('Cash flow'!B8*B$1*(1-Inputs!B11)-'Cash flow'!F8)/(1+Inputs!B21)^6+('Cash flow'!B9*B$1*(1-Inputs!B11)-'Cash flow'!F9)/(1+Inputs!B21)^7+('Cash flow'!B10*B$1*(1-Inputs!B11)-'Cash flow'!F10)/(1+Inputs!B21)^8+('Cash flow'!B11*B$1*(1-Inputs!B11)-'Cash flow'!F11)/(1+Inputs!B21)^9+('Cash flow'!B12*B$1*(1-Inputs!B11)-'Cash flow'!F12)/(1+Inputs!B21)^10+('Cash flow'!B13*B$1*(1-Inputs!B11)-'Cash flow'!F13)/(1+Inputs!B21)^11+('Cash flow'!B14*B$1*(1-Inputs!B11)-'Cash flow'!F14)/(1+Inputs!B21)^12+('Cash flow'!B15*B$1*(1-Inputs!B11)-'Cash flow'!F15)/(1+Inputs!B21)^13+('Cash flow'!B16*B$1*(1-Inputs!B11)-'Cash flow'!F16)/(1+Inputs!B21)^14+('Cash flow'!B17*B$1*(1-Inputs!B11)-'Cash flow'!F17)/(1+Inputs!B21)^15+('Cash flow'!B18*B$1*(1-Inputs!B11)-'Cash flow'!F18)/(1+Inputs!B21)^16+('Cash flow'!B19*B$1*(1-Inputs!B11)-'Cash flow'!F19)/(1+Inputs!B21)^17+('Cash flow'!B20*B$1*(1-Inputs!B11)-'Cash flow'!F20)/(1+Inputs!B21)^18+('Cash flow'!B21*B$1*(1-Inputs!B11)-'Cash flow'!F21)/(1+Inputs!B21)^19+('Cash flow'!B22*B$1*(1-Inputs!B11)-'Cash flow'!F22)/(1+Inputs!B21)^20+(('Cash flow'!B23*B$1*(1-Inputs!B11)-'Cash flow'!F23)+('Cash flow'!B23*B$1*(1-Inputs!B11)-'Cash flow'!F23)*(1+Inputs!B10)/Inputs!B22*(1-Inputs!B23))/(1+Inputs!B21)^21 -> -7233922.7 | C4: =-Development!B15*$A4/2+-Development!B15*$A4/2/(1+Inputs!B21)+('Cash flow'!B4*Inputs!B29*C$1/Inputs!B9*(1-Inputs!B11)-'Cash flow'!F4)/(1+Inputs!B21)^2+('Cash flow'!B5*C$1*(1-Inputs!B11)-'Cash flow'!F5)/(1+Inputs!B21)^3+('Cash flow'!B6*C$1*(1-Inputs!B11)-'Cash flow'!F6)/(1+Inputs!B21)^4+('Cash flow'!B7*C$1*(1-Inputs!B11)-'Cash flow'!F7)/(1+Inputs!B21)^5+('Cash flow'!B8*C$1*(1-Inputs!B11)-'Cash flow'!F8)/(1+Inputs!B21)^6+('Cash flow'!B9*C$1*(1-Inputs!B11)-'Cash flow'!F9)/(1+Inputs!B21)^7+('Cash flow'!B10*C$1*(1-Inputs!B11)-'Cash flow'!F10)/(1+Inputs!B21)^8+('Cash flow'!B11*C$1*(1-Inputs!B11)-'Cash flow'!F11)/(1+Inputs!B21)^9+('Cash flow'!B12*C$1*(1-Inputs!B11)-'Cash flow'!F12)/(1+Inputs!B21)^10+('Cash flow'!B13*C$1*(1-Inputs!B11)-'Cash flow'!F13)/(1+Inputs!B21)^11+('Cash flow'!B14*C$1*(1-Inputs!B11)-'Cash flow'!F14)/(1+Inputs!B21)^12+('Cash flow'!B15*C$1*(1-Inputs!B11)-'Cash flow'!F15)/(1+Inputs!B21)^13+('Cash flow'!B16*C$1*(1-Inputs!B11)-'Cash flow'!F16)/(1+Inputs!B21)^14+('Cash flow'!B17*C$1*(1-Inputs!B11)-'Cash flow'!F17)/(1+Inputs!B21)^15+('Cash flow'!B18*C$1*(1-Inputs!B11)-'Cash flow'!F18)/(1+Inputs!B21)^16+('Cash flow'!B19*C$1*(1-Inputs!B11)-'Cash flow'!F19)/(1+Inputs!B21)^17+('Cash flow'!B20*C$1*(1-Inputs!B11)-'Cash flow'!F20)/(1+Inputs!B21)^18+('Cash flow'!B21*C$1*(1-Inputs!B11)-'Cash flow'!F21)/(1+Inputs!B21)^19+('Cash flow'!B22*C$1*(1-Inputs!B11)-'Cash flow'!F22)/(1+Inputs!B21)^20+(('Cash flow'!B23*C$1*(1-Inputs!B11)-'Cash flow'!F23)+('Cash flow'!B23*C$1*(1-Inputs!B11)-'Cash flow'!F23)*(1+Inputs!B10)/Inputs!B22*(1-Inputs!B23))/(1+Inputs!B21)^21 -> -6456207.3 | D4: =-Development!B15*$A4/2+-Development!B15*$A4/2/(1+Inputs!B21)+('Cash flow'!B4*Inputs!B29*D$1/Inputs!B9*(1-Inputs!B11)-'Cash flow'!F4)/(1+Inputs!B21)^2+('Cash flow'!B5*D$1*(1-Inputs!B11)-'Cash flow'!F5)/(1+Inputs!B21)^3+('Cash flow'!B6*D$1*(1-Inputs!B11)-'Cash flow'!F6)/(1+Inputs!B21)^4+('Cash flow'!B7*D$1*(1-Inputs!B11)-'Cash flow'!F7)/(1+Inputs!B21)^5+('Cash flow'!B8*D$1*(1-Inputs!B11)-'Cash flow'!F8)/(1+Inputs!B21)^6+('Cash flow'!B9*D$1*(1-Inputs!B11)-'Cash flow'!F9)/(1+Inputs!B21)^7+('Cash flow'!B10*D$1*(1-Inputs!B11)-'Cash flow'!F10)/(1+Inputs!B21)^8+('Cash flow'!B11*D$1*(1-Inputs!B11)-'Cash flow'!F11)/(1+Inputs!B21)^9+('Cash flow'!B12*D$1*(1-Inputs!B11)-'Cash flow'!F12)/(1+Inputs!B21)^10+('Cash flow'!B13*D$1*(1-Inputs!B11)-'Cash flow'!F13)/(1+Inputs!B21)^11+('Cash flow'!B14*D$1*(1-Inputs!B11)-'Cash flow'!F14)/(1+Inputs!B21)^12+('Cash flow'!B15*D$1*(1-Inputs!B11)-'Cash flow'!F15)/(1+Inputs!B21)^13+('Cash flow'!B16*D$1*(1-Inputs!B11)-'Cash flow'!F16)/(1+Inputs!B21)^14+('Cash flow'!B17*D$1*(1-Inputs!B11)-'Cash flow'!F17)/(1+Inputs!B21)^15+('Cash flow'!B18*D$1*(1-Inputs!B11)-'Cash flow'!F18)/(1+Inputs!B21)^16+('Cash flow'!B19*D$1*(1-Inputs!B11)-'Cash flow'!F19)/(1+Inputs!B21)^17+('Cash flow'!B20*D$1*(1-Inputs!B11)-'Cash flow'!F20)/(1+Inputs!B21)^18+('Cash flow'!B21*D$1*(1-Inputs!B11)-'Cash flow'!F21)/(1+Inputs!B21)^19+('Cash flow'!B22*D$1*(1-Inputs!B11)-'Cash flow'!F22)/(1+Inputs!B21)^20+(('Cash flow'!B23*D$1*(1-Inputs!B11)-'Cash flow'!F23)+('Cash flow'!B23*D$1*(1-Inputs!B11)-'Cash flow'!F23)*(1+Inputs!B10)/Inputs!B22*(1-Inputs!B23))/(1+Inputs!B21)^21 -> -6222892.6
A6: Rows = development cost multiplier. Columns = stabilised occupancy. Opening occupancy scales with stabilised occupancy. Rents unchanged.

Sheet Checks
A1: Control | B1: Value | C1: Expected
A2: Beds reconcile | B2: ='Room mix'!D5-(Inputs!B2+Inputs!B3*2+Inputs!B4) -> 0 | C2: 0
A3: Sources = funding | B3: =Development!B7-Development!B8-Development!B9 -> 0 | C3: 0
A4: Debt fully drawn | B4: =SUM('Cash flow'!I2:I23)-Development!B8 -> 0 | C4: 0
A5: Unlevered spend matches budget | B5: =SUM('Cash flow'!H2:H23)-Development!B15 -> 0 | C5: 0
A6: Equity invested | B6: =-SUM('Cash flow'!N2:N3)-Development!B9 -> 0 | C6: 0
A7: Base scenario NPV reconciles | B7: =Scenarios!F3-Dashboard!B9 -> 1.8626451e-09 | C7: 0
A8: Rent references supplied | B8: =COUNTIF('Rent rules'!C2:C4,">0") -> 0 | C8: 3
A9: Occupancy bounds | B9: =IF(AND(Inputs!B9>0,Inputs!B9<=1,Inputs!B29>0,Inputs!B29<=1),0,1) -> 0 | C9: 0
A10: Candidate capacity reconciliation | B10: ='Room mix'!D5-Inputs!B36 -> 0 | C10: 0
A11: Capacity option cost reconciliation | B11: ='Capacity options'!I3-Development!B7 -> 1.8626451e-09 | C11: 0

Sheet Capacity options
A1: Design | B1: Normal rooms | C1: Shared studios | D1: Single studios | E1: Beds | F1: Gross sqm | G1: Gross annual rent | H1: Project cost ex interest | I1: Funding incl interest | J1: Stabilised NOI | K1: Yield on cost | L1: DSCR | M1: Demand screen
A2: Compact | B2: 40 | C2: 12 | D2: 16 | E2: =B2+2*C2+D2 -> 80 | F2: =(B2*Inputs!B25+C2*Inputs!B26+D2*Inputs!B27)*Inputs!B28 -> 2105.6 | G2: =(B2*'Rent rules'!F2+C2*2*'Rent rules'!F3+D2*'Rent rules'!F4)*Inputs!B8 -> 467520 | H2: =Inputs!B14*(1+Inputs!B32)+F2*Inputs!B13*(1+Inputs!B15)*(1+Inputs!B16)*(1+Inputs!B17)+E2*Inputs!B33+Inputs!B34 -> 9354460.6 | I2: =H2*(1+Inputs!B18*Inputs!B19) -> 9585983.5 | J2: =(G2*Inputs!B9*(1-Inputs!B11)-E2*Inputs!B12)*(1+Inputs!B10) -> 313939.35 | K2: =J2/I2 -> 0.032749832 | L2: =J2/(-PMT(Inputs!B19,Inputs!B20,H2*Inputs!B18)) -> 0.90480089 | M2: =IF(E2<='Demand & competition'!B10,"Within assumed demand","Above assumed demand") -> Within assumed demand
A3: Proposed | B3: 60 | C3: 20 | D3: 20 | E3: =B3+2*C3+D3 -> 120 | F3: =(B3*Inputs!B25+C3*Inputs!B26+D3*Inputs!B27)*Inputs!B28 -> 3108 | G3: =(B3*'Rent rules'!F2+C3*2*'Rent rules'!F3+D3*'Rent rules'!F4)*Inputs!B8 -> 688800 | H3: =Inputs!B14*(1+Inputs!B32)+F3*Inputs!B13*(1+Inputs!B15)*(1+Inputs!B16)*(1+Inputs!B17)+E3*Inputs!B33+Inputs!B34 -> 12801972 | I3: =H3*(1+Inputs!B18*Inputs!B19) -> 13118821 | J3: =(G3*Inputs!B9*(1-Inputs!B11)-E3*Inputs!B12)*(1+Inputs!B10) -> 462201.98 | K3: =J3/I3 -> 0.035231975 | L3: =J3/(-PMT(Inputs!B19,Inputs!B20,H3*Inputs!B18)) -> 0.97337665 | M3: =IF(E3<='Demand & competition'!B10,"Within assumed demand","Above assumed demand") -> Within assumed demand
A4: Larger | B4: 80 | C4: 28 | D4: 24 | E4: =B4+2*C4+D4 -> 160 | F4: =(B4*Inputs!B25+C4*Inputs!B26+D4*Inputs!B27)*Inputs!B28 -> 4110.4 | G4: =(B4*'Rent rules'!F2+C4*2*'Rent rules'!F3+D4*'Rent rules'!F4)*Inputs!B8 -> 910080 | H4: =Inputs!B14*(1+Inputs!B32)+F4*Inputs!B13*(1+Inputs!B15)*(1+Inputs!B16)*(1+Inputs!B17)+E4*Inputs!B33+Inputs!B34 -> 16249484 | I4: =H4*(1+Inputs!B18*Inputs!B19) -> 16651659 | J4: =(G4*Inputs!B9*(1-Inputs!B11)-E4*Inputs!B12)*(1+Inputs!B10) -> 610464.61 | K4: =J4/I4 -> 0.036660889 | L4: =J4/(-PMT(Inputs!B19,Inputs!B20,H4*Inputs!B18)) -> 1.0128542 | M4: =IF(E4<='Demand & competition'!B10,"Within assumed demand","Above assumed demand") -> Above assumed demand
A7: Selection rationale | B7: 120 beds is the largest tested design within the assumed local demand envelope (~151 beds). The 80-bed design limits lease-up exposure; 160 beds exceeds the envelope.
A8: Financial conclusion | B8: Demand alone does not justify construction. All sizes require yield and debt-coverage review; base 120-bed case fails the investment gate.
